Workbook

Sheet README
A1: Hoja | B1: Descripción
A2: EFACT_CNE | B2: Información de facturación definitiva proveniente de los archivos EFACT publicados por la CNE en los Decretos de Precio de Nudo
A3: FACT_EMITIDA | B3: Información de facturación real desde PDFs y sistema SIGGE (gestión facturación electrónica)
A4: SIGGE_E | B4: Información de facturación real de Energía desde PDFs y sistema SIGGE (gestión facturación electrónica)
A5: SIGGE_P | B5: Información de facturación real de Potencia desde PDFs y sistema SIGGE (gestión facturación electrónica)
A6: FACT_EST_EFACT | B6: Estimación de facturación emitida en base a información de los EFACT Decretos Precios de Nudo
A7: FACT_EST_CEN | B7: Estimación de la facturación emitida en base a los balances mensuales publicados por el Coordinador

Sheet MAPA_DATA
A1: Num | B1: Anho | C1: Mes | D1: Fecha | E1: FACT_EMITIDA | F1: FACT_EST_EFACT | G1: FACT_EST_CEN | H1: EFACT_CNE | I1: EFACT_EST_CEN | J1: OrigenData1 | K1: OrigenData2
A2: 1 | B2: 2020 | C2: 10 | D2: 44105 | E2: 1 | F2: 0 | G2: 0 | H2: 1 | I2: 0 | J2: FACT_EMITIDA | K2: EFACT_CNE
A3: 2 | B3: 2020 | C3: 11 | D3: 44136 | E3: 1 | F3: 0 | G3: 0 | H3: 1 | I3: 0 | J3: FACT_EMITIDA | K3: EFACT_CNE
A4: 3 | B4: 2020 | C4: 12 | D4: 44166 | E4: 1 | F4: 0 | G4: 0 | H4: 1 | I4: 0 | J4: FACT_EMITIDA | K4: EFACT_CNE
A5: 4 | B5: 2021 | C5: 1 | D5: 44197 | E5: 1 | F5: 0 | G5: 0 | H5: 1 | I5: 0 | J5: FACT_EMITIDA | K5: EFACT_CNE
A6: 5 | B6: 2021 | C6: 2 | D6: 44228 | E6: 1 | F6: 0 | G6: 0 | H6: 1 | I6: 0 | J6: FACT_EMITIDA | K6: EFACT_CNE
A7: 6 | B7: 2021 | C7: 3 | D7: 44256 | E7: 1 | F7: 0 | G7: 0 | H7: 1 | I7: 0 | J7: FACT_EMITIDA | K7: EFACT_CNE

Sheet ReliquidacionEFACT
A2: Generador | B2: [GX]
A3: Distribuidor | B3: [EEDD]
A4: Licitacion | B4: 2013/03-2° Llamado
A5: Bloque | B5: [BLOQUE]
C7: LO QUE SE FACTURÓ | L7: LO QUE SE DEBIÓ HABER FACTURADO | U7: RELQUIDACIÓN Y CÁLCULO INTERESES
A8: ID | B8: MES | C8: ORIGEN DATA | D8: Energía (kWh) | E8: Monto Energía ($) | F8: $/kWh | G8: Potencia (kW) | H8: Monto Potencia ($) | I8: $/kW-mes | J8: Monto Total ($) | L8: ORIGEN DATA | M8: Energía (kWh) | N8: Monto Energía ($) | O8: $/kWh | P8: Potencia (kW) | Q8: Monto Potencia ($) | R8: $/kW-mes | S8: Monto Total ($) | U8: Mes | V8: Reliquidación mensual ($) | W8: Decreto PNP Reliquidación | X8: Fecha publicación Diario Oficial | Y8: Interés Anual | Z8: Fecha Facturación | AA8: Fecha Reliquidación | AB8: N° de días de intereses | AC8: Interés total según n° de días | AD8: Intereses ($) | AE8: Reliquidación Total ($)
A9: 9 | B9: 44105 | C9: FACT_EMITIDA | D9: =CONCATENATE("SUMIF(",IF(C9="FACT_EMITIDA","SIGGE_E",C9),"!B:B,ReliquidacionEFACT!B",A9,",",IF(C9="FACT_EMITIDA","SIGGE_E",C9),"!S:S)") -> SUMIF(SIGGE_E!B:B,ReliquidacionEFACT!B9,SIGGE_E!S:S) | E9: =CONCATENATE("SUMIF(",IF(C9="FACT_EMITIDA","SIGGE_E",C9),"!B:B,ReliquidacionEFACT!B",A9,",",IF(C9="FACT_EMITIDA","SIGGE_E",C9),"!T:T)") -> SUMIF(SIGGE_E!B:B,ReliquidacionEFACT!B9,SIGGE_E!T:T) | F9: =CONCATENATE("IFERROR((E",A9,"/D",A9,"),0)") -> IFERROR((E9/D9),0) | G9: =CONCATENATE("SUMIF(",IF(C9="FACT_EMITIDA","SIGGE_P",C9),"!B:B,ReliquidacionEFACT!B",A9,",",IF(C9="FACT_EMITIDA","SIGGE_P",C9),"!U:U)") -> SUMIF(SIGGE_P!B:B,ReliquidacionEFACT!B9,SIGGE_P!U:U) | H9: =CONCATENATE("SUMIF(",IF(C9="FACT_EMITIDA","SIGGE_P",C9),"!B:B,ReliquidacionEFACT!B",A9,",",IF(C9="FACT_EMITIDA","SIGGE_P",C9),"!V:V)") -> SUMIF(SIGGE_P!B:B,ReliquidacionEFACT!B9,SIGGE_P!V:V) | I9: =CONCATENATE("IFERROR((H",A9,"/G",A9,"),0)") -> IFERROR((H9/G9),0) | J9: =CONCATENATE("(E",A9,"+H",A9,")") -> (E9+H9) | L9: =(MAPA_DATA!K2) -> EFACT_CNE | M9: =CONCATENATE("SUMIF(",L9,"!B:B,ReliquidacionEFACT!B",A9,",",L9,"!S:S)") -> SUMIF(EFACT_CNE!B:B,ReliquidacionEFACT!B9,EFACT_CNE!S:S) | N9: =CONCATENATE("SUMIF(",L9,"!B:B,ReliquidacionEFACT!B",A9,",",L9,"!T:T)") -> SUMIF(EFACT_CNE!B:B,ReliquidacionEFACT!B9,EFACT_CNE!T:T) | O9: =CONCATENATE("IFERROR((N",A9,"/M",A9,"),0)") -> IFERROR((N9/M9),0) | P9: =CONCATENATE("SUMIF(",L9,"!B:B,ReliquidacionEFACT!B",A9,",",L9,"!U:U)") -> SUMIF(EFACT_CNE!B:B,ReliquidacionEFACT!B9,EFACT_CNE!U:U) | Q9: =CONCATENATE("SUMIF(",L9,"!B:B,ReliquidacionEFACT!B",A9,",",L9,"!V:V)") -> SUMIF(EFACT_CNE!B:B,ReliquidacionEFACT!B9,EFACT_CNE!V:V) | R9: =CONCATENATE("IFERROR((Q",A9,"/P",A9,"),0)") -> IFERROR((Q9/P9),0) | S9: =CONCATENATE("(N",A9,"+Q",A9,")") -> (N9+Q9) | U9: 44105 | V9: =CONCATENATE("(S",A9,"-J",A9,")") -> (S9-J9) | W9: PNP_8T | X9: 44600 | Y9: 0.0328 | Z9: 44129 | AA9: 44651 | AB9: =CONCATENATE("(AA",A9,"-Z",A9,")") -> (AA9-Z9) | AC9: =CONCATENATE("(1+Y",A9,")^(AB",A9,"/360)-1") -> (1+Y9)^(AB9/360)-1 | AD9: =CONCATENATE("(AC",A9,"*V",A9,")") -> (AC9*V9) | AE9: =CONCATENATE("(V",A9,"+AD",A9,")") -> (V9+AD9)
A10: =A9+1 -> 10 | B10: 44136 | C10: FACT_EMITIDA | D10: =CONCATENATE("SUMIF(",IF(C10="FACT_EMITIDA","SIGGE_E",C10),"!B:B,ReliquidacionEFACT!B",A10,",",IF(C10="FACT_EMITIDA","SIGGE_E",C10),"!S:S)") -> SUMIF(SIGGE_E!B:B,ReliquidacionEFACT!B10,SIGGE_E!S:S) | E10: =CONCATENATE("SUMIF(",IF(C10="FACT_EMITIDA","SIGGE_E",C10),"!B:B,ReliquidacionEFACT!B",A10,",",IF(C10="FACT_EMITIDA","SIGGE_E",C10),"!T:T)") -> SUMIF(SIGGE_E!B:B,ReliquidacionEFACT!B10,SIGGE_E!T:T) | F10: =CONCATENATE("IFERROR((E",A10,"/D",A10,"),0)") -> IFERROR((E10/D10),0) | G10: =CONCATENATE("SUMIF(",IF(C10="FACT_EMITIDA","SIGGE_P",C10),"!B:B,ReliquidacionEFACT!B",A10,",",IF(C10="FACT_EMITIDA","SIGGE_P",C10),"!U:U)") -> SUMIF(SIGGE_P!B:B,ReliquidacionEFACT!B10,SIGGE_P!U:U) | H10: =CONCATENATE("SUMIF(",IF(C10="FACT_EMITIDA","SIGGE_P",C10),"!B:B,ReliquidacionEFACT!B",A10,",",IF(C10="FACT_EMITIDA","SIGGE_P",C10),"!V:V)") -> SUMIF(SIGGE_P!B:B,ReliquidacionEFACT!B10,SIGGE_P!V:V) | I10: =CONCATENATE("IFERROR((H",A10,"/G",A10,"),0)") -> IFERROR((H10/G10),0) | J10: =CONCATENATE("(E",A10,"+H",A10,")") -> (E10+H10) | L10: =(MAPA_DATA!K3) -> EFACT_CNE | M10: =CONCATENATE("SUMIF(",L10,"!B:B,ReliquidacionEFACT!B",A10,",",L10,"!S:S)") -> SUMIF(EFACT_CNE!B:B,ReliquidacionEFACT!B10,EFACT_CNE!S:S) | N10: =CONCATENATE("SUMIF(",L10,"!B:B,ReliquidacionEFACT!B",A10,",",L10,"!T:T)") -> SUMIF(EFACT_CNE!B:B,ReliquidacionEFACT!B10,EFACT_CNE!T:T) | O10: =CONCATENATE("IFERROR((N",A10,"/M",A10,"),0)") -> IFERROR((N10/M10),0) | P10: =CONCATENATE("SUMIF(",L10,"!B:B,ReliquidacionEFACT!B",A10,",",L10,"!U:U)") -> SUMIF(EFACT_CNE!B:B,ReliquidacionEFACT!B10,EFACT_CNE!U:U) | Q10: =CONCATENATE("SUMIF(",L10,"!B:B,ReliquidacionEFACT!B",A10,",",L10,"!V:V)") -> SUMIF(EFACT_CNE!B:B,ReliquidacionEFACT!B10,EFACT_CNE!V:V) | R10: =CONCATENATE("IFERROR((Q",A10,"/P",A10,"),0)") -> IFERROR((Q10/P10),0) | S10: =CONCATENATE("(N",A10,"+Q",A10,")") -> (N10+Q10) | U10: 44136 | V10: =CONCATENATE("(S",A10,"-J",A10,")") -> (S10-J10) | W10: PNP_8T | X10: 44600 | Y10: 0.0328 | Z10: 44160 | AA10: =AA9 -> 44651 | AB10: =CONCATENATE("(AA",A10,"-Z",A10,")") -> (AA10-Z10) | AC10: =CONCATENATE("(1+Y",A10,")^(AB",A10,"/360)-1") -> (1+Y10)^(AB10/360)-1 | AD10: =CONCATENATE("(AC",A10,"*V",A10,")") -> (AC10*V10) | AE10: =CONCATENATE("(V",A10,"+AD",A10,")") -> (V10+AD10)
A11: =A10+1 -> 11 | B11: 44166 | C11: FACT_EMITIDA | D11: =CONCATENATE("SUMIF(",IF(C11="FACT_EMITIDA","SIGGE_E",C11),"!B:B,ReliquidacionEFACT!B",A11,",",IF(C11="FACT_EMITIDA","SIGGE_E",C11),"!S:S)") -> SUMIF(SIGGE_E!B:B,ReliquidacionEFACT!B11,SIGGE_E!S:S) | E11: =CONCATENATE("SUMIF(",IF(C11="FACT_EMITIDA","SIGGE_E",C11),"!B:B,ReliquidacionEFACT!B",A11,",",IF(C11="FACT_EMITIDA","SIGGE_E",C11),"!T:T)") -> SUMIF(SIGGE_E!B:B,ReliquidacionEFACT!B11,SIGGE_E!T:T) | F11: =CONCATENATE("IFERROR((E",A11,"/D",A11,"),0)") -> IFERROR((E11/D11),0) | G11: =CONCATENATE("SUMIF(",IF(C11="FACT_EMITIDA","SIGGE_P",C11),"!B:B,ReliquidacionEFACT!B",A11,",",IF(C11="FACT_EMITIDA","SIGGE_P",C11),"!U:U)") -> SUMIF(SIGGE_P!B:B,ReliquidacionEFACT!B11,SIGGE_P!U:U) | H11: =CONCATENATE("SUMIF(",IF(C11="FACT_EMITIDA","SIGGE_P",C11),"!B:B,ReliquidacionEFACT!B",A11,",",IF(C11="FACT_EMITIDA","SIGGE_P",C11),"!V:V)") -> SUMIF(SIGGE_P!B:B,ReliquidacionEFACT!B11,SIGGE_P!V:V) | I11: =CONCATENATE("IFERROR((H",A11,"/G",A11,"),0)") -> IFERROR((H11/G11),0) | J11: =CONCATENATE("(E",A11,"+H",A11,")") -> (E11+H11) | L11: =(MAPA_DATA!K4) -> EFACT_CNE | M11: =CONCATENATE("SUMIF(",L11,"!B:B,ReliquidacionEFACT!B",A11,",",L11,"!S:S)") -> SUMIF(EFACT_CNE!B:B,ReliquidacionEFACT!B11,EFACT_CNE!S:S) | N11: =CONCATENATE("SUMIF(",L11,"!B:B,ReliquidacionEFACT!B",A11,",",L11,"!T:T)") -> SUMIF(EFACT_CNE!B:B,ReliquidacionEFACT!B11,EFACT_CNE!T:T) | O11: =CONCATENATE("IFERROR((N",A11,"/M",A11,"),0)") -> IFERROR((N11/M11),0) | P11: =CONCATENATE("SUMIF(",L11,"!B:B,ReliquidacionEFACT!B",A11,",",L11,"!U:U)") -> SUMIF(EFACT_CNE!B:B,ReliquidacionEFACT!B11,EFACT_CNE!U:U) | Q11: =CONCATENATE("SUMIF(",L11,"!B:B,ReliquidacionEFACT!B",A11,",",L11,"!V:V)") -> SUMIF(EFACT_CNE!B:B,ReliquidacionEFACT!B11,EFACT_CNE!V:V) | R11: =CONCATENATE("IFERROR((Q",A11,"/P",A11,"),0)") -> IFERROR((Q11/P11),0) | S11: =CONCATENATE("(N",A11,"+Q",A11,")") -> (N11+Q11) | U11: 44166 | V11: =CONCATENATE("(S",A11,"-J",A11,")") -> (S11-J11) | W11: PNP_8T | X11: 44600 | Y11: 0.0328 | Z11: 44190 | AA11: =AA10 -> 44651 | AB11: =CONCATENATE("(AA",A11,"-Z",A11,")") -> (AA11-Z11) | AC11: =CONCATENATE("(1+Y",A11,")^(AB",A11,"/360)-1") -> (1+Y11)^(AB11/360)-1 | AD11: =CONCATENATE("(AC",A11,"*V",A11,")") -> (AC11*V11) | AE11: =CONCATENATE("(V",A11,"+AD",A11,")") -> (V11+AD11)
A12: =A11+1 -> 12 | B12: 44197 | C12: FACT_EMITIDA | D12: =CONCATENATE("SUMIF(",IF(C12="FACT_EMITIDA","SIGGE_E",C12),"!B:B,ReliquidacionEFACT!B",A12,",",IF(C12="FACT_EMITIDA","SIGGE_E",C12),"!S:S)") -> SUMIF(SIGGE_E!B:B,ReliquidacionEFACT!B12,SIGGE_E!S:S) | E12: =CONCATENATE("SUMIF(",IF(C12="FACT_EMITIDA","SIGGE_E",C12),"!B:B,ReliquidacionEFACT!B",A12,",",IF(C12="FACT_EMITIDA","SIGGE_E",C12),"!T:T)") -> SUMIF(SIGGE_E!B:B,ReliquidacionEFACT!B12,SIGGE_E!T:T) | F12: =CONCATENATE("IFERROR((E",A12,"/D",A12,"),0)") -> IFERROR((E12/D12),0) | G12: =CONCATENATE("SUMIF(",IF(C12="FACT_EMITIDA","SIGGE_P",C12),"!B:B,ReliquidacionEFACT!B",A12,",",IF(C12="FACT_EMITIDA","SIGGE_P",C12),"!U:U)") -> SUMIF(SIGGE_P!B:B,ReliquidacionEFACT!B12,SIGGE_P!U:U) | H12: =CONCATENATE("SUMIF(",IF(C12="FACT_EMITIDA","SIGGE_P",C12),"!B:B,ReliquidacionEFACT!B",A12,",",IF(C12="FACT_EMITIDA","SIGGE_P",C12),"!V:V)") -> SUMIF(SIGGE_P!B:B,ReliquidacionEFACT!B12,SIGGE_P!V:V) | I12: =CONCATENATE("IFERROR((H",A12,"/G",A12,"),0)") -> IFERROR((H12/G12),0) | J12: =CONCATENATE("(E",A12,"+H",A12,")") -> (E12+H12) | L12: =(MAPA_DATA!K5) -> EFACT_CNE | M12: =CONCATENATE("SUMIF(",L12,"!B:B,ReliquidacionEFACT!B",A12,",",L12,"!S:S)") -> SUMIF(EFACT_CNE!B:B,ReliquidacionEFACT!B12,EFACT_CNE!S:S) | N12: =CONCATENATE("SUMIF(",L12,"!B:B,ReliquidacionEFACT!B",A12,",",L12,"!T:T)") -> SUMIF(EFACT_CNE!B:B,ReliquidacionEFACT!B12,EFACT_CNE!T:T) | O12: =CONCATENATE("IFERROR((N",A12,"/M",A12,"),0)") -> IFERROR((N12/M12),0) | P12: =CONCATENATE("SUMIF(",L12,"!B:B,ReliquidacionEFACT!B",A12,",",L12,"!U:U)") -> SUMIF(EFACT_CNE!B:B,ReliquidacionEFACT!B12,EFACT_CNE!U:U) | Q12: =CONCATENATE("SUMIF(",L12,"!B:B,ReliquidacionEFACT!B",A12,",",L12,"!V:V)") -> SUMIF(EFACT_CNE!B:B,ReliquidacionEFACT!B12,EFACT_CNE!V:V) | R12: =CONCATENATE("IFERROR((Q",A12,"/P",A12,"),0)") -> IFERROR((Q12/P12),0) | S12: =CONCATENATE("(N",A12,"+Q",A12,")") -> (N12+Q12) | U12: 44197 | V12: =CONCATENATE("(S",A12,"-J",A12,")") -> (S12-J12) | W12: PNP_8T | X12: 44600 | Y12: 0.0328 | Z12: 44221 | AA12: =AA11 -> 44651 | AB12: =CONCATENATE("(AA",A12,"-Z",A12,")") -> (AA12-Z12) | AC12: =CONCATENATE("(1+Y",A12,")^(AB",A12,"/360)-1") -> (1+Y12)^(AB12/360)-1 | AD12: =CONCATENATE("(AC",A12,"*V",A12,")") -> (AC12*V12) | AE12: =CONCATENATE("(V",A12,"+AD",A12,")") -> (V12+AD12)
A13: =A12+1 -> 13 | B13: 44228 | C13: FACT_EMITIDA | D13: =CONCATENATE("SUMIF(",IF(C13="FACT_EMITIDA","SIGGE_E",C13),"!B:B,ReliquidacionEFACT!B",A13,",",IF(C13="FACT_EMITIDA","SIGGE_E",C13),"!S:S)") -> SUMIF(SIGGE_E!B:B,ReliquidacionEFACT!B13,SIGGE_E!S:S) | E13: =CONCATENATE("SUMIF(",IF(C13="FACT_EMITIDA","SIGGE_E",C13),"!B:B,ReliquidacionEFACT!B",A13,",",IF(C13="FACT_EMITIDA","SIGGE_E",C13),"!T:T)") -> SUMIF(SIGGE_E!B:B,ReliquidacionEFACT!B13,SIGGE_E!T:T) | F13: =CONCATENATE("IFERROR((E",A13,"/D",A13,"),0)") -> IFERROR((E13/D13),0) | G13: =CONCATENATE("SUMIF(",IF(C13="FACT_EMITIDA","SIGGE_P",C13),"!B:B,ReliquidacionEFACT!B",A13,",",IF(C13="FACT_EMITIDA","SIGGE_P",C13),"!U:U)") -> SUMIF(SIGGE_P!B:B,ReliquidacionEFACT!B13,SIGGE_P!U:U) | H13: =CONCATENATE("SUMIF(",IF(C13="FACT_EMITIDA","SIGGE_P",C13),"!B:B,ReliquidacionEFACT!B",A13,",",IF(C13="FACT_EMITIDA","SIGGE_P",C13),"!V:V)") -> SUMIF(SIGGE_P!B:B,ReliquidacionEFACT!B13,SIGGE_P!V:V) | I13: =CONCATENATE("IFERROR((H",A13,"/G",A13,"),0)") -> IFERROR((H13/G13),0) | J13: =CONCATENATE("(E",A13,"+H",A13,")") -> (E13+H13) | L13: =(MAPA_DATA!K6) -> EFACT_CNE | M13: =CONCATENATE("SUMIF(",L13,"!B:B,ReliquidacionEFACT!B",A13,",",L13,"!S:S)") -> SUMIF(EFACT_CNE!B:B,ReliquidacionEFACT!B13,EFACT_CNE!S:S) | N13: =CONCATENATE("SUMIF(",L13,"!B:B,ReliquidacionEFACT!B",A13,",",L13,"!T:T)") -> SUMIF(EFACT_CNE!B:B,ReliquidacionEFACT!B13,EFACT_CNE!T:T) | O13: =CONCATENATE("IFERROR((N",A13,"/M",A13,"),0)") -> IFERROR((N13/M13),0) | P13: =CONCATENATE("SUMIF(",L13,"!B:B,ReliquidacionEFACT!B",A13,",",L13,"!U:U)") -> SUMIF(EFACT_CNE!B:B,ReliquidacionEFACT!B13,EFACT_CNE!U:U) | Q13: =CONCATENATE("SUMIF(",L13,"!B:B,ReliquidacionEFACT!B",A13,",",L13,"!V:V)") -> SUMIF(EFACT_CNE!B:B,ReliquidacionEFACT!B13,EFACT_CNE!V:V) | R13: =CONCATENATE("IFERROR((Q",A13,"/P",A13,"),0)") -> IFERROR((Q13/P13),0) | S13: =CONCATENATE("(N",A13,"+Q",A13,")") -> (N13+Q13) | U13: 44228 | V13: =CONCATENATE("(S",A13,"-J",A13,")") -> (S13-J13) | W13: PNP_8T | X13: 44600 | Y13: 0.0328 | Z13: 44252 | AA13: =AA12 -> 44651 | AB13: =CONCATENATE("(AA",A13,"-Z",A13,")") -> (AA13-Z13) | AC13: =CONCATENATE("(1+Y",A13,")^(AB",A13,"/360)-1") -> (1+Y13)^(AB13/360)-1 | AD13: =CONCATENATE("(AC",A13,"*V",A13,")") -> (AC13*V13) | AE13: =CONCATENATE("(V",A13,"+AD",A13,")") -> (V13+AD13)
A14: =A13+1 -> 14 | B14: 44256 | C14: FACT_EMITIDA | D14: =CONCATENATE("SUMIF(",IF(C14="FACT_EMITIDA","SIGGE_E",C14),"!B:B,ReliquidacionEFACT!B",A14,",",IF(C14="FACT_EMITIDA","SIGGE_E",C14),"!S:S)") -> SUMIF(SIGGE_E!B:B,ReliquidacionEFACT!B14,SIGGE_E!S:S) | E14: =CONCATENATE("SUMIF(",IF(C14="FACT_EMITIDA","SIGGE_E",C14),"!B:B,ReliquidacionEFACT!B",A14,",",IF(C14="FACT_EMITIDA","SIGGE_E",C14),"!T:T)") -> SUMIF(SIGGE_E!B:B,ReliquidacionEFACT!B14,SIGGE_E!T:T) | F14: =CONCATENATE("IFERROR((E",A14,"/D",A14,"),0)") -> IFERROR((E14/D14),0) | G14: =CONCATENATE("SUMIF(",IF(C14="FACT_EMITIDA","SIGGE_P",C14),"!B:B,ReliquidacionEFACT!B",A14,",",IF(C14="FACT_EMITIDA","SIGGE_P",C14),"!U:U)") -> SUMIF(SIGGE_P!B:B,ReliquidacionEFACT!B14,SIGGE_P!U:U) | H14: =CONCATENATE("SUMIF(",IF(C14="FACT_EMITIDA","SIGGE_P",C14),"!B:B,ReliquidacionEFACT!B",A14,",",IF(C14="FACT_EMITIDA","SIGGE_P",C14),"!V:V)") -> SUMIF(SIGGE_P!B:B,ReliquidacionEFACT!B14,SIGGE_P!V:V) | I14: =CONCATENATE("IFERROR((H",A14,"/G",A14,"),0)") -> IFERROR((H14/G14),0) | J14: =CONCATENATE("(E",A14,"+H",A14,")") -> (E14+H14) | L14: =(MAPA_DATA!K7) -> EFACT_CNE | M14: =CONCATENATE("SUMIF(",L14,"!B:B,ReliquidacionEFACT!B",A14,",",L14,"!S:S)") -> SUMIF(EFACT_CNE!B:B,ReliquidacionEFACT!B14,EFACT_CNE!S:S) | N14: =CONCATENATE("SUMIF(",L14,"!B:B,ReliquidacionEFACT!B",A14,",",L14,"!T:T)") -> SUMIF(EFACT_CNE!B:B,ReliquidacionEFACT!B14,EFACT_CNE!T:T) | O14: =CONCATENATE("IFERROR((N",A14,"/M",A14,"),0)") -> IFERROR((N14/M14),0) | P14: =CONCATENATE("SUMIF(",L14,"!B:B,ReliquidacionEFACT!B",A14,",",L14,"!U:U)") -> SUMIF(EFACT_CNE!B:B,ReliquidacionEFACT!B14,EFACT_CNE!U:U) | Q14: =CONCATENATE("SUMIF(",L14,"!B:B,ReliquidacionEFACT!B",A14,",",L14,"!V:V)") -> SUMIF(EFACT_CNE!B:B,ReliquidacionEFACT!B14,EFACT_CNE!V:V) | R14: =CONCATENATE("IFERROR((Q",A14,"/P",A14,"),0)") -> IFERROR((Q14/P14),0) | S14: =CONCATENATE("(N",A14,"+Q",A14,")") -> (N14+Q14) | U14: 44256 | V14: =CONCATENATE("(S",A14,"-J",A14,")") -> (S14-J14) | W14: PNP_8T | X14: 44600 | Y14: 0.0328 | Z14: 44280 | AA14: =AA13 -> 44651 | AB14: =CONCATENATE("(AA",A14,"-Z",A14,")") -> (AA14-Z14) | AC14: =CONCATENATE("(1+Y",A14,")^(AB",A14,"/360)-1") -> (1+Y14)^(AB14/360)-1 | AD14: =CONCATENATE("(AC",A14,"*V",A14,")") -> (AC14*V14) | AE14: =CONCATENATE("(V",A14,"+AD",A14,")") -> (V14+AD14)
AD15: Reliquidación | AE15: =CONCATENATE("SUM(AE9:AE14)") -> SUM(AE9:AE14)
AC17: Montos a favor | AD17: LAP emite factura
AC18: Montos en contra | AD18: LAP emite nota de crédito

Sheet ReliquidacionCEN
A2: Generador | B2: [GX]
A3: Distribuidor | B3: [EEDD]
A4: Licitacion | B4: 2013/03-2° Llamado
A5: Bloque | B5: [BLOQUE]
C7: LO QUE SE FACTURÓ (VIGENTE) | L7: LO QUE SE DEBIÓ HABER FACTURADO (RELIQUIDADO) | U7: RELQUIDACIÓN Y CÁLCULO INTERESES
A8: ID | B8: MES | C8: ORIGEN DATA | D8: Energía (kWh) | E8: Monto Energía ($) | F8: $/kWh | G8: Potencia (kW) | H8: Monto Potencia ($) | I8: $/kW-mes | J8: Monto Total ($) | L8: ORIGEN DATA | M8: Energía (kWh) | N8: Monto Energía ($) | O8: $/kWh | P8: Potencia (kW) | Q8: Monto Potencia ($) | R8: $/kW-mes | S8: Monto Total ($) | U8: Mes | V8: Reliquidación mensual ($) | W8: Decreto PNP Reliquidación | X8: Fecha publicación Diario Oficial | Y8: Interés Anual | Z8: Fecha Facturación | AA8: Fecha Reliquidación | AB8: N° de días de intereses | AC8: Interés total según n° de días | AD8: Intereses ($) | AE8: Reliquidación Total ($)
A9: 9 | B9: 44105 | C9: FACT_EMITIDA | D9: =CONCATENATE("SUMIF(",IF(C9="FACT_EMITIDA","SIGGE_E",C9),"!B:B,ReliquidacionCEN!B",A9,",",IF(C9="FACT_EMITIDA","SIGGE_E",C9),"!S:S)") -> SUMIF(SIGGE_E!B:B,ReliquidacionCEN!B9,SIGGE_E!S:S) | E9: =CONCATENATE("SUMIF(",IF(C9="FACT_EMITIDA","SIGGE_E",C9),"!B:B,ReliquidacionCEN!B",A9,",",IF(C9="FACT_EMITIDA","SIGGE_E",C9),"!T:T)") -> SUMIF(SIGGE_E!B:B,ReliquidacionCEN!B9,SIGGE_E!T:T) | F9: =CONCATENATE("IFERROR((E",A9,"/D",A9,"),0)") -> IFERROR((E9/D9),0) | G9: =CONCATENATE("SUMIF(",IF(C9="FACT_EMITIDA","SIGGE_P",C9),"!B:B,ReliquidacionCEN!B",A9,",",IF(C9="FACT_EMITIDA","SIGGE_P",C9),"!U:U)") -> SUMIF(SIGGE_P!B:B,ReliquidacionCEN!B9,SIGGE_P!U:U) | H9: =CONCATENATE("SUMIF(",IF(C9="FACT_EMITIDA","SIGGE_P",C9),"!B:B,ReliquidacionCEN!B",A9,",",IF(C9="FACT_EMITIDA","SIGGE_P",C9),"!V:V)") -> SUMIF(SIGGE_P!B:B,ReliquidacionCEN!B9,SIGGE_P!V:V) | I9: =CONCATENATE("IFERROR((H",A9,"/G",A9,"),0)") -> IFERROR((H9/G9),0) | J9: =CONCATENATE("(E",A9,"+H",A9,")") -> (E9+H9) | L9: FACT_EST_CEN | M9: =CONCATENATE("SUMIF(",IF(L9="FACT_EST_CEN","CEN_Energia",L9),"!B:B,ReliquidacionCEN!B",A9,",",IF(L9="FACT_EST_CEN","CEN_Energia",L9),"!Z:Z)") -> SUMIF(CEN_Energia!B:B,ReliquidacionCEN!B9,CEN_Energia!Z:Z) | N9: =CONCATENATE("SUMIF(",IF(L9="FACT_EST_CEN","CEN_Energia",L9),"!B:B,ReliquidacionCEN!B",A9,",",IF(L9="FACT_EST_CEN","CEN_Energia",L9),"!BK:BK)") -> SUMIF(CEN_Energia!B:B,ReliquidacionCEN!B9,CEN_Energia!BK:BK) | O9: =CONCATENATE("IFERROR((N",A9,"/M",A9,"),0)") -> IFERROR((N9/M9),0) | P9: =CONCATENATE("SUMIF(",IF(L9="FACT_EST_CEN","CEN_Potencia",L9),"!B:B,ReliquidacionCEN!B",A9,",",IF(L9="FACT_EST_CEN","CEN_Potencia",L9),"!R:R)") -> SUMIF(CEN_Potencia!B:B,ReliquidacionCEN!B9,CEN_Potencia!R:R) | Q9: =CONCATENATE("SUMIF(",IF(L9="FACT_EST_CEN","CEN_Potencia",L9),"!B:B,ReliquidacionCEN!B",A9,",",IF(L9="FACT_EST_CEN","CEN_Potencia",L9),"!BC:BC)") -> SUMIF(CEN_Potencia!B:B,ReliquidacionCEN!B9,CEN_Potencia!BC:BC) | R9: =CONCATENATE("IFERROR((Q",A9,"/P",A9,"),0)") -> IFERROR((Q9/P9),0) | S9: =CONCATENATE("(N",A9,"+Q",A9,")") -> (N9+Q9) | U9: 44105 | V9: =CONCATENATE("(S",A9,"-J",A9,")") -> (S9-J9) | W9: PNP_8T | X9: 44600 | Y9: 0.0328 | Z9: 44129 | AA9: 44651 | AB9: =CONCATENATE("(AA",A9,"-Z",A9,")") -> (AA9-Z9) | AC9: =CONCATENATE("(1+Y",A9,")^(AB",A9,"/360)-1") -> (1+Y9)^(AB9/360)-1 | AD9: =CONCATENATE("(AC",A9,"*V",A9,")") -> (AC9*V9) | AE9: =CONCATENATE("(V",A9,"+AD",A9,")") -> (V9+AD9)
A10: =A9+1 -> 10 | B10: 44136 | C10: FACT_EMITIDA | D10: =CONCATENATE("SUMIF(",IF(C10="FACT_EMITIDA","SIGGE_E",C10),"!B:B,ReliquidacionCEN!B",A10,",",IF(C10="FACT_EMITIDA","SIGGE_E",C10),"!S:S)") -> SUMIF(SIGGE_E!B:B,ReliquidacionCEN!B10,SIGGE_E!S:S) | E10: =CONCATENATE("SUMIF(",IF(C10="FACT_EMITIDA","SIGGE_E",C10),"!B:B,ReliquidacionCEN!B",A10,",",IF(C10="FACT_EMITIDA","SIGGE_E",C10),"!T:T)") -> SUMIF(SIGGE_E!B:B,ReliquidacionCEN!B10,SIGGE_E!T:T) | F10: =CONCATENATE("IFERROR((E",A10,"/D",A10,"),0)") -> IFERROR((E10/D10),0) | G10: =CONCATENATE("SUMIF(",IF(C10="FACT_EMITIDA","SIGGE_P",C10),"!B:B,ReliquidacionCEN!B",A10,",",IF(C10="FACT_EMITIDA","SIGGE_P",C10),"!U:U)") -> SUMIF(SIGGE_P!B:B,ReliquidacionCEN!B10,SIGGE_P!U:U) | H10: =CONCATENATE("SUMIF(",IF(C10="FACT_EMITIDA","SIGGE_P",C10),"!B:B,ReliquidacionCEN!B",A10,",",IF(C10="FACT_EMITIDA","SIGGE_P",C10),"!V:V)") -> SUMIF(SIGGE_P!B:B,ReliquidacionCEN!B10,SIGGE_P!V:V) | I10: =CONCATENATE("IFERROR((H",A10,"/G",A10,"),0)") -> IFERROR((H10/G10),0) | J10: =CONCATENATE("(E",A10,"+H",A10,")") -> (E10+H10) | L10: FACT_EST_CEN | M10: =CONCATENATE("SUMIF(",IF(L10="FACT_EST_CEN","CEN_Energia",L10),"!B:B,ReliquidacionCEN!B",A10,",",IF(L10="FACT_EST_CEN","CEN_Energia",L10),"!Z:Z)") -> SUMIF(CEN_Energia!B:B,ReliquidacionCEN!B10,CEN_Energia!Z:Z) | N10: =CONCATENATE("SUMIF(",IF(L10="FACT_EST_CEN","CEN_Energia",L10),"!B:B,ReliquidacionCEN!B",A10,",",IF(L10="FACT_EST_CEN","CEN_Energia",L10),"!BK:BK)") -> SUMIF(CEN_Energia!B:B,ReliquidacionCEN!B10,CEN_Energia!BK:BK) | O10: =CONCATENATE("IFERROR((N",A10,"/M",A10,"),0)") -> IFERROR((N10/M10),0) | P10: =CONCATENATE("SUMIF(",IF(L10="FACT_EST_CEN","CEN_Potencia",L10),"!B:B,ReliquidacionCEN!B",A10,",",IF(L10="FACT_EST_CEN","CEN_Potencia",L10),"!R:R)") -> SUMIF(CEN_Potencia!B:B,ReliquidacionCEN!B10,CEN_Potencia!R:R) | Q10: =CONCATENATE("SUMIF(",IF(L10="FACT_EST_CEN","CEN_Potencia",L10),"!B:B,ReliquidacionCEN!B",A10,",",IF(L10="FACT_EST_CEN","CEN_Potencia",L10),"!BC:BC)") -> SUMIF(CEN_Potencia!B:B,ReliquidacionCEN!B10,CEN_Potencia!BC:BC) | R10: =CONCATENATE("IFERROR((Q",A10,"/P",A10,"),0)") -> IFERROR((Q10/P10),0) | S10: =CONCATENATE("(N",A10,"+Q",A10,")") -> (N10+Q10) | U10: 44136 | V10: =CONCATENATE("(S",A10,"-J",A10,")") -> (S10-J10) | W10: PNP_8T | X10: 44600 | Y10: 0.0328 | Z10: 44160 | AA10: =AA9 -> 44651 | AB10: =CONCATENATE("(AA",A10,"-Z",A10,")") -> (AA10-Z10) | AC10: =CONCATENATE("(1+Y",A10,")^(AB",A10,"/360)-1") -> (1+Y10)^(AB10/360)-1 | AD10: =CONCATENATE("(AC",A10,"*V",A10,")") -> (AC10*V10) | AE10: =CONCATENATE("(V",A10,"+AD",A10,")") -> (V10+AD10)
A11: =A10+1 -> 11 | B11: 44166 | C11: FACT_EMITIDA | D11: =CONCATENATE("SUMIF(",IF(C11="FACT_EMITIDA","SIGGE_E",C11),"!B:B,ReliquidacionCEN!B",A11,",",IF(C11="FACT_EMITIDA","SIGGE_E",C11),"!S:S)") -> SUMIF(SIGGE_E!B:B,ReliquidacionCEN!B11,SIGGE_E!S:S) | E11: =CONCATENATE("SUMIF(",IF(C11="FACT_EMITIDA","SIGGE_E",C11),"!B:B,ReliquidacionCEN!B",A11,",",IF(C11="FACT_EMITIDA","SIGGE_E",C11),"!T:T)") -> SUMIF(SIGGE_E!B:B,ReliquidacionCEN!B11,SIGGE_E!T:T) | F11: =CONCATENATE("IFERROR((E",A11,"/D",A11,"),0)") -> IFERROR((E11/D11),0) | G11: =CONCATENATE("SUMIF(",IF(C11="FACT_EMITIDA","SIGGE_P",C11),"!B:B,ReliquidacionCEN!B",A11,",",IF(C11="FACT_EMITIDA","SIGGE_P",C11),"!U:U)") -> SUMIF(SIGGE_P!B:B,ReliquidacionCEN!B11,SIGGE_P!U:U) | H11: =CONCATENATE("SUMIF(",IF(C11="FACT_EMITIDA","SIGGE_P",C11),"!B:B,ReliquidacionCEN!B",A11,",",IF(C11="FACT_EMITIDA","SIGGE_P",C11),"!V:V)") -> SUMIF(SIGGE_P!B:B,ReliquidacionCEN!B11,SIGGE_P!V:V) | I11: =CONCATENATE("IFERROR((H",A11,"/G",A11,"),0)") -> IFERROR((H11/G11),0) | J11: =CONCATENATE("(E",A11,"+H",A11,")") -> (E11+H11) | L11: FACT_EST_CEN | M11: =CONCATENATE("SUMIF(",IF(L11="FACT_EST_CEN","CEN_Energia",L11),"!B:B,ReliquidacionCEN!B",A11,",",IF(L11="FACT_EST_CEN","CEN_Energia",L11),"!Z:Z)") -> SUMIF(CEN_Energia!B:B,ReliquidacionCEN!B11,CEN_Energia!Z:Z) | N11: =CONCATENATE("SUMIF(",IF(L11="FACT_EST_CEN","CEN_Energia",L11),"!B:B,ReliquidacionCEN!B",A11,",",IF(L11="FACT_EST_CEN","CEN_Energia",L11),"!BK:BK)") -> SUMIF(CEN_Energia!B:B,ReliquidacionCEN!B11,CEN_Energia!BK:BK) | O11: =CONCATENATE("IFERROR((N",A11,"/M",A11,"),0)") -> IFERROR((N11/M11),0) | P11: =CONCATENATE("SUMIF(",IF(L11="FACT_EST_CEN","CEN_Potencia",L11),"!B:B,ReliquidacionCEN!B",A11,",",IF(L11="FACT_EST_CEN","CEN_Potencia",L11),"!R:R)") -> SUMIF(CEN_Potencia!B:B,ReliquidacionCEN!B11,CEN_Potencia!R:R) | Q11: =CONCATENATE("SUMIF(",IF(L11="FACT_EST_CEN","CEN_Potencia",L11),"!B:B,ReliquidacionCEN!B",A11,",",IF(L11="FACT_EST_CEN","CEN_Potencia",L11),"!BC:BC)") -> SUMIF(CEN_Potencia!B:B,ReliquidacionCEN!B11,CEN_Potencia!BC:BC) | R11: =CONCATENATE("IFERROR((Q",A11,"/P",A11,"),0)") -> IFERROR((Q11/P11),0) | S11: =CONCATENATE("(N",A11,"+Q",A11,")") -> (N11+Q11) | U11: 44166 | V11: =CONCATENATE("(S",A11,"-J",A11,")") -> (S11-J11) | W11: PNP_8T | X11: 44600 | Y11: 0.0328 | Z11: 44190 | AA11: =AA10 -> 44651 | AB11: =CONCATENATE("(AA",A11,"-Z",A11,")") -> (AA11-Z11) | AC11: =CONCATENATE("(1+Y",A11,")^(AB",A11,"/360)-1") -> (1+Y11)^(AB11/360)-1 | AD11: =CONCATENATE("(AC",A11,"*V",A11,")") -> (AC11*V11) | AE11: =CONCATENATE("(V",A11,"+AD",A11,")") -> (V11+AD11)
A12: =A11+1 -> 12 | B12: 44197 | C12: FACT_EMITIDA | D12: =CONCATENATE("SUMIF(",IF(C12="FACT_EMITIDA","SIGGE_E",C12),"!B:B,ReliquidacionCEN!B",A12,",",IF(C12="FACT_EMITIDA","SIGGE_E",C12),"!S:S)") -> SUMIF(SIGGE_E!B:B,ReliquidacionCEN!B12,SIGGE_E!S:S) | E12: =CONCATENATE("SUMIF(",IF(C12="FACT_EMITIDA","SIGGE_E",C12),"!B:B,ReliquidacionCEN!B",A12,",",IF(C12="FACT_EMITIDA","SIGGE_E",C12),"!T:T)") -> SUMIF(SIGGE_E!B:B,ReliquidacionCEN!B12,SIGGE_E!T:T) | F12: =CONCATENATE("IFERROR((E",A12,"/D",A12,"),0)") -> IFERROR((E12/D12),0) | G12: =CONCATENATE("SUMIF(",IF(C12="FACT_EMITIDA","SIGGE_P",C12),"!B:B,ReliquidacionCEN!B",A12,",",IF(C12="FACT_EMITIDA","SIGGE_P",C12),"!U:U)") -> SUMIF(SIGGE_P!B:B,ReliquidacionCEN!B12,SIGGE_P!U:U) | H12: =CONCATENATE("SUMIF(",IF(C12="FACT_EMITIDA","SIGGE_P",C12),"!B:B,ReliquidacionCEN!B",A12,",",IF(C12="FACT_EMITIDA","SIGGE_P",C12),"!V:V)") -> SUMIF(SIGGE_P!B:B,ReliquidacionCEN!B12,SIGGE_P!V:V) | I12: =CONCATENATE("IFERROR((H",A12,"/G",A12,"),0)") -> IFERROR((H12/G12),0) | J12: =CONCATENATE("(E",A12,"+H",A12,")") -> (E12+H12) | L12: FACT_EST_CEN | M12: =CONCATENATE("SUMIF(",IF(L12="FACT_EST_CEN","CEN_Energia",L12),"!B:B,ReliquidacionCEN!B",A12,",",IF(L12="FACT_EST_CEN","CEN_Energia",L12),"!Z:Z)") -> SUMIF(CEN_Energia!B:B,ReliquidacionCEN!B12,CEN_Energia!Z:Z) | N12: =CONCATENATE("SUMIF(",IF(L12="FACT_EST_CEN","CEN_Energia",L12),"!B:B,ReliquidacionCEN!B",A12,",",IF(L12="FACT_EST_CEN","CEN_Energia",L12),"!BK:BK)") -> SUMIF(CEN_Energia!B:B,ReliquidacionCEN!B12,CEN_Energia!BK:BK) | O12: =CONCATENATE("IFERROR((N",A12,"/M",A12,"),0)") -> IFERROR((N12/M12),0) | P12: =CONCATENATE("SUMIF(",IF(L12="FACT_EST_CEN","CEN_Potencia",L12),"!B:B,ReliquidacionCEN!B",A12,",",IF(L12="FACT_EST_CEN","CEN_Potencia",L12),"!R:R)") -> SUMIF(CEN_Potencia!B:B,ReliquidacionCEN!B12,CEN_Potencia!R:R) | Q12: =CONCATENATE("SUMIF(",IF(L12="FACT_EST_CEN","CEN_Potencia",L12),"!B:B,ReliquidacionCEN!B",A12,",",IF(L12="FACT_EST_CEN","CEN_Potencia",L12),"!BC:BC)") -> SUMIF(CEN_Potencia!B:B,ReliquidacionCEN!B12,CEN_Potencia!BC:BC) | R12: =CONCATENATE("IFERROR((Q",A12,"/P",A12,"),0)") -> IFERROR((Q12/P12),0) | S12: =CONCATENATE("(N",A12,"+Q",A12,")") -> (N12+Q12) | U12: 44197 | V12: =CONCATENATE("(S",A12,"-J",A12,")") -> (S12-J12) | W12: PNP_8T | X12: 44600 | Y12: 0.0328 | Z12: 44221 | AA12: =AA11 -> 44651 | AB12: =CONCATENATE("(AA",A12,"-Z",A12,")") -> (AA12-Z12) | AC12: =CONCATENATE("(1+Y",A12,")^(AB",A12,"/360)-1") -> (1+Y12)^(AB12/360)-1 | AD12: =CONCATENATE("(AC",A12,"*V",A12,")") -> (AC12*V12) | AE12: =CONCATENATE("(V",A12,"+AD",A12,")") -> (V12+AD12)
A13: =A12+1 -> 13 | B13: 44228 | C13: FACT_EMITIDA | D13: =CONCATENATE("SUMIF(",IF(C13="FACT_EMITIDA","SIGGE_E",C13),"!B:B,ReliquidacionCEN!B",A13,",",IF(C13="FACT_EMITIDA","SIGGE_E",C13),"!S:S)") -> SUMIF(SIGGE_E!B:B,ReliquidacionCEN!B13,SIGGE_E!S:S) | E13: =CONCATENATE("SUMIF(",IF(C13="FACT_EMITIDA","SIGGE_E",C13),"!B:B,ReliquidacionCEN!B",A13,",",IF(C13="FACT_EMITIDA","SIGGE_E",C13),"!T:T)") -> SUMIF(SIGGE_E!B:B,ReliquidacionCEN!B13,SIGGE_E!T:T) | F13: =CONCATENATE("IFERROR((E",A13,"/D",A13,"),0)") -> IFERROR((E13/D13),0) | G13: =CONCATENATE("SUMIF(",IF(C13="FACT_EMITIDA","SIGGE_P",C13),"!B:B,ReliquidacionCEN!B",A13,",",IF(C13="FACT_EMITIDA","SIGGE_P",C13),"!U:U)") -> SUMIF(SIGGE_P!B:B,ReliquidacionCEN!B13,SIGGE_P!U:U) | H13: =CONCATENATE("SUMIF(",IF(C13="FACT_EMITIDA","SIGGE_P",C13),"!B:B,ReliquidacionCEN!B",A13,",",IF(C13="FACT_EMITIDA","SIGGE_P",C13),"!V:V)") -> SUMIF(SIGGE_P!B:B,ReliquidacionCEN!B13,SIGGE_P!V:V) | I13: =CONCATENATE("IFERROR((H",A13,"/G",A13,"),0)") -> IFERROR((H13/G13),0) | J13: =CONCATENATE("(E",A13,"+H",A13,")") -> (E13+H13) | L13: FACT_EST_CEN | M13: =CONCATENATE("SUMIF(",IF(L13="FACT_EST_CEN","CEN_Energia",L13),"!B:B,ReliquidacionCEN!B",A13,",",IF(L13="FACT_EST_CEN","CEN_Energia",L13),"!Z:Z)") -> SUMIF(CEN_Energia!B:B,ReliquidacionCEN!B13,CEN_Energia!Z:Z) | N13: =CONCATENATE("SUMIF(",IF(L13="FACT_EST_CEN","CEN_Energia",L13),"!B:B,ReliquidacionCEN!B",A13,",",IF(L13="FACT_EST_CEN","CEN_Energia",L13),"!BK:BK)") -> SUMIF(CEN_Energia!B:B,ReliquidacionCEN!B13,CEN_Energia!BK:BK) | O13: =CONCATENATE("IFERROR((N",A13,"/M",A13,"),0)") -> IFERROR((N13/M13),0) | P13: =CONCATENATE("SUMIF(",IF(L13="FACT_EST_CEN","CEN_Potencia",L13),"!B:B,ReliquidacionCEN!B",A13,",",IF(L13="FACT_EST_CEN","CEN_Potencia",L13),"!R:R)") -> SUMIF(CEN_Potencia!B:B,ReliquidacionCEN!B13,CEN_Potencia!R:R) | Q13: =CONCATENATE("SUMIF(",IF(L13="FACT_EST_CEN","CEN_Potencia",L13),"!B:B,ReliquidacionCEN!B",A13,",",IF(L13="FACT_EST_CEN","CEN_Potencia",L13),"!BC:BC)") -> SUMIF(CEN_Potencia!B:B,ReliquidacionCEN!B13,CEN_Potencia!BC:BC) | R13: =CONCATENATE("IFERROR((Q",A13,"/P",A13,"),0)") -> IFERROR((Q13/P13),0) | S13: =CONCATENATE("(N",A13,"+Q",A13,")") -> (N13+Q13) | U13: 44228 | V13: =CONCATENATE("(S",A13,"-J",A13,")") -> (S13-J13) | W13: PNP_8T | X13: 44600 | Y13: 0.0328 | Z13: 44252 | AA13: =AA12 -> 44651 | AB13: =CONCATENATE("(AA",A13,"-Z",A13,")") -> (AA13-Z13) | AC13: =CONCATENATE("(1+Y",A13,")^(AB",A13,"/360)-1") -> (1+Y13)^(AB13/360)-1 | AD13: =CONCATENATE("(AC",A13,"*V",A13,")") -> (AC13*V13) | AE13: =CONCATENATE("(V",A13,"+AD",A13,")") -> (V13+AD13)
A14: =A13+1 -> 14 | B14: 44256 | C14: FACT_EMITIDA | D14: =CONCATENATE("SUMIF(",IF(C14="FACT_EMITIDA","SIGGE_E",C14),"!B:B,ReliquidacionCEN!B",A14,",",IF(C14="FACT_EMITIDA","SIGGE_E",C14),"!S:S)") -> SUMIF(SIGGE_E!B:B,ReliquidacionCEN!B14,SIGGE_E!S:S) | E14: =CONCATENATE("SUMIF(",IF(C14="FACT_EMITIDA","SIGGE_E",C14),"!B:B,ReliquidacionCEN!B",A14,",",IF(C14="FACT_EMITIDA","SIGGE_E",C14),"!T:T)") -> SUMIF(SIGGE_E!B:B,ReliquidacionCEN!B14,SIGGE_E!T:T) | F14: =CONCATENATE("IFERROR((E",A14,"/D",A14,"),0)") -> IFERROR((E14/D14),0) | G14: =CONCATENATE("SUMIF(",IF(C14="FACT_EMITIDA","SIGGE_P",C14),"!B:B,ReliquidacionCEN!B",A14,",",IF(C14="FACT_EMITIDA","SIGGE_P",C14),"!U:U)") -> SUMIF(SIGGE_P!B:B,ReliquidacionCEN!B14,SIGGE_P!U:U) | H14: =CONCATENATE("SUMIF(",IF(C14="FACT_EMITIDA","SIGGE_P",C14),"!B:B,ReliquidacionCEN!B",A14,",",IF(C14="FACT_EMITIDA","SIGGE_P",C14),"!V:V)") -> SUMIF(SIGGE_P!B:B,ReliquidacionCEN!B14,SIGGE_P!V:V) | I14: =CONCATENATE("IFERROR((H",A14,"/G",A14,"),0)") -> IFERROR((H14/G14),0) | J14: =CONCATENATE("(E",A14,"+H",A14,")") -> (E14+H14) | L14: FACT_EST_CEN | M14: =CONCATENATE("SUMIF(",IF(L14="FACT_EST_CEN","CEN_Energia",L14),"!B:B,ReliquidacionCEN!B",A14,",",IF(L14="FACT_EST_CEN","CEN_Energia",L14),"!Z:Z)") -> SUMIF(CEN_Energia!B:B,ReliquidacionCEN!B14,CEN_Energia!Z:Z) | N14: =CONCATENATE("SUMIF(",IF(L14="FACT_EST_CEN","CEN_Energia",L14),"!B:B,ReliquidacionCEN!B",A14,",",IF(L14="FACT_EST_CEN","CEN_Energia",L14),"!BK:BK)") -> SUMIF(CEN_Energia!B:B,ReliquidacionCEN!B14,CEN_Energia!BK:BK) | O14: =CONCATENATE("IFERROR((N",A14,"/M",A14,"),0)") -> IFERROR((N14/M14),0) | P14: =CONCATENATE("SUMIF(",IF(L14="FACT_EST_CEN","CEN_Potencia",L14),"!B:B,ReliquidacionCEN!B",A14,",",IF(L14="FACT_EST_CEN","CEN_Potencia",L14),"!R:R)") -> SUMIF(CEN_Potencia!B:B,ReliquidacionCEN!B14,CEN_Potencia!R:R) | Q14: =CONCATENATE("SUMIF(",IF(L14="FACT_EST_CEN","CEN_Potencia",L14),"!B:B,ReliquidacionCEN!B",A14,",",IF(L14="FACT_EST_CEN","CEN_Potencia",L14),"!BC:BC)") -> SUMIF(CEN_Potencia!B:B,ReliquidacionCEN!B14,CEN_Potencia!BC:BC) | R14: =CONCATENATE("IFERROR((Q",A14,"/P",A14,"),0)") -> IFERROR((Q14/P14),0) | S14: =CONCATENATE("(N",A14,"+Q",A14,")") -> (N14+Q14) | U14: 44256 | V14: =CONCATENATE("(S",A14,"-J",A14,")") -> (S14-J14) | W14: PNP_8T | X14: 44600 | Y14: 0.0328 | Z14: 44280 | AA14: =AA13 -> 44651 | AB14: =CONCATENATE("(AA",A14,"-Z",A14,")") -> (AA14-Z14) | AC14: =CONCATENATE("(1+Y",A14,")^(AB",A14,"/360)-1") -> (1+Y14)^(AB14/360)-1 | AD14: =CONCATENATE("(AC",A14,"*V",A14,")") -> (AC14*V14) | AE14: =CONCATENATE("(V",A14,"+AD",A14,")") -> (V14+AD14)
AD15: Reliquidación | AE15: =CONCATENATE("SUM(AE9:AE14)") -> SUM(AE9:AE14)
AC17: Montos a favor | AD17: LAP emite factura
AC18: Montos en contra | AD18: LAP emite nota de crédito

Sheet ResumenRetiros
A2: Generador | B2: [GX]
A3: Distribuidor | B3: [EEDD]
A4: Licitacion | B4: 2013/03-2° Llamado
A5: Bloque | B5: [BLOQUE]
A8: ID | B8: MES | C8: ORIGEN DATA | D8: Energía SIGGE (kWh) | E8: Energía EFACT AT (kWh) | F8: Energía EFACT BT (kWh) | G8: Energía Coordinador AT (kWh) | H8: Energía Coordinador BT (kWh)
A9: 9 | B9: 44105 | C9: FACT_EMITIDA | D9: =CONCATENATE("SUMIF(","SIGGE_E!B:B,ResumenRetiros!B",A9,",","SIGGE_E","!S:S)") -> SUMIF(SIGGE_E!B:B,ResumenRetiros!B9,SIGGE_E!S:S) | E9: =CONCATENATE("SUMIF(","EFACT_CNE","!B:B,ResumenRetiros!B",A9,",","EFACT_CNE","!S:S)") -> SUMIF(EFACT_CNE!B:B,ResumenRetiros!B9,EFACT_CNE!S:S) | F9: =CONCATENATE("SUMIF(","EfactCNE_BT","!B:B,ResumenRetiros!B",A9,",","EfactCNE_BT","!M:M)") -> SUMIF(EfactCNE_BT!B:B,ResumenRetiros!B9,EfactCNE_BT!M:M) | G9: =CONCATENATE("SUMIF(CEN_Energia!B:B,ResumenRetiros!B",A9,",CEN_Energia!Z:Z)") -> SUMIF(CEN_Energia!B:B,ResumenRetiros!B9,CEN_Energia!Z:Z) | H9: =CONCATENATE("SUMIF(CEN_EnergiaBT!B:B,ResumenRetiros!B",A9,",CEN_EnergiaBT!K:K)") -> SUMIF(CEN_EnergiaBT!B:B,ResumenRetiros!B9,CEN_EnergiaBT!K:K)
A10: =A9+1 -> 10 | B10: 44136 | C10: FACT_EMITIDA | D10: =CONCATENATE("SUMIF(","SIGGE_E!B:B,ResumenRetiros!B",A10,",","SIGGE_E","!S:S)") -> SUMIF(SIGGE_E!B:B,ResumenRetiros!B10,SIGGE_E!S:S) | E10: =CONCATENATE("SUMIF(","EFACT_CNE","!B:B,ResumenRetiros!B",A10,",","EFACT_CNE","!S:S)") -> SUMIF(EFACT_CNE!B:B,ResumenRetiros!B10,EFACT_CNE!S:S) | F10: =CONCATENATE("SUMIF(","EfactCNE_BT","!B:B,ResumenRetiros!B",A10,",","EfactCNE_BT","!M:M)") -> SUMIF(EfactCNE_BT!B:B,ResumenRetiros!B10,EfactCNE_BT!M:M) | G10: =CONCATENATE("SUMIF(CEN_Energia!B:B,ResumenRetiros!B",A10,",CEN_Energia!Z:Z)") -> SUMIF(CEN_Energia!B:B,ResumenRetiros!B10,CEN_Energia!Z:Z) | H10: =CONCATENATE("SUMIF(CEN_EnergiaBT!B:B,ResumenRetiros!B",A10,",CEN_EnergiaBT!K:K)") -> SUMIF(CEN_EnergiaBT!B:B,ResumenRetiros!B10,CEN_EnergiaBT!K:K)
A11: =A10+1 -> 11 | B11: 44166 | C11: FACT_EMITIDA | D11: =CONCATENATE("SUMIF(","SIGGE_E!B:B,ResumenRetiros!B",A11,",","SIGGE_E","!S:S)") -> SUMIF(SIGGE_E!B:B,ResumenRetiros!B11,SIGGE_E!S:S) | E11: =CONCATENATE("SUMIF(","EFACT_CNE","!B:B,ResumenRetiros!B",A11,",","EFACT_CNE","!S:S)") -> SUMIF(EFACT_CNE!B:B,ResumenRetiros!B11,EFACT_CNE!S:S) | F11: =CONCATENATE("SUMIF(","EfactCNE_BT","!B:B,ResumenRetiros!B",A11,",","EfactCNE_BT","!M:M)") -> SUMIF(EfactCNE_BT!B:B,ResumenRetiros!B11,EfactCNE_BT!M:M) | G11: =CONCATENATE("SUMIF(CEN_Energia!B:B,ResumenRetiros!B",A11,",CEN_Energia!Z:Z)") -> SUMIF(CEN_Energia!B:B,ResumenRetiros!B11,CEN_Energia!Z:Z) | H11: =CONCATENATE("SUMIF(CEN_EnergiaBT!B:B,ResumenRetiros!B",A11,",CEN_EnergiaBT!K:K)") -> SUMIF(CEN_EnergiaBT!B:B,ResumenRetiros!B11,CEN_EnergiaBT!K:K)
A12: =A11+1 -> 12 | B12: 44197 | C12: FACT_EMITIDA | D12: =CONCATENATE("SUMIF(","SIGGE_E!B:B,ResumenRetiros!B",A12,",","SIGGE_E","!S:S)") -> SUMIF(SIGGE_E!B:B,ResumenRetiros!B12,SIGGE_E!S:S) | E12: =CONCATENATE("SUMIF(","EFACT_CNE","!B:B,ResumenRetiros!B",A12,",","EFACT_CNE","!S:S)") -> SUMIF(EFACT_CNE!B:B,ResumenRetiros!B12,EFACT_CNE!S:S) | F12: =CONCATENATE("SUMIF(","EfactCNE_BT","!B:B,ResumenRetiros!B",A12,",","EfactCNE_BT","!M:M)") -> SUMIF(EfactCNE_BT!B:B,ResumenRetiros!B12,EfactCNE_BT!M:M) | G12: =CONCATENATE("SUMIF(CEN_Energia!B:B,ResumenRetiros!B",A12,",CEN_Energia!Z:Z)") -> SUMIF(CEN_Energia!B:B,ResumenRetiros!B12,CEN_Energia!Z:Z) | H12: =CONCATENATE("SUMIF(CEN_EnergiaBT!B:B,ResumenRetiros!B",A12,",CEN_EnergiaBT!K:K)") -> SUMIF(CEN_EnergiaBT!B:B,ResumenRetiros!B12,CEN_EnergiaBT!K:K)
A13: =A12+1 -> 13 | B13: 44228 | C13: FACT_EMITIDA | D13: =CONCATENATE("SUMIF(","SIGGE_E!B:B,ResumenRetiros!B",A13,",","SIGGE_E","!S:S)") -> SUMIF(SIGGE_E!B:B,ResumenRetiros!B13,SIGGE_E!S:S) | E13: =CONCATENATE("SUMIF(","EFACT_CNE","!B:B,ResumenRetiros!B",A13,",","EFACT_CNE","!S:S)") -> SUMIF(EFACT_CNE!B:B,ResumenRetiros!B13,EFACT_CNE!S:S) | F13: =CONCATENATE("SUMIF(","EfactCNE_BT","!B:B,ResumenRetiros!B",A13,",","EfactCNE_BT","!M:M)") -> SUMIF(EfactCNE_BT!B:B,ResumenRetiros!B13,EfactCNE_BT!M:M) | G13: =CONCATENATE("SUMIF(CEN_Energia!B:B,ResumenRetiros!B",A13,",CEN_Energia!Z:Z)") -> SUMIF(CEN_Energia!B:B,ResumenRetiros!B13,CEN_Energia!Z:Z) | H13: =CONCATENATE("SUMIF(CEN_EnergiaBT!B:B,ResumenRetiros!B",A13,",CEN_EnergiaBT!K:K)") -> SUMIF(CEN_EnergiaBT!B:B,ResumenRetiros!B13,CEN_EnergiaBT!K:K)
A14: =A13+1 -> 14 | B14: 44256 | C14: FACT_EMITIDA | D14: =CONCATENATE("SUMIF(","SIGGE_E!B:B,ResumenRetiros!B",A14,",","SIGGE_E","!S:S)") -> SUMIF(SIGGE_E!B:B,ResumenRetiros!B14,SIGGE_E!S:S) | E14: =CONCATENATE("SUMIF(","EFACT_CNE","!B:B,ResumenRetiros!B",A14,",","EFACT_CNE","!S:S)") -> SUMIF(EFACT_CNE!B:B,ResumenRetiros!B14,EFACT_CNE!S:S) | F14: =CONCATENATE("SUMIF(","EfactCNE_BT","!B:B,ResumenRetiros!B",A14,",","EfactCNE_BT","!M:M)") -> SUMIF(EfactCNE_BT!B:B,ResumenRetiros!B14,EfactCNE_BT!M:M) | G14: =CONCATENATE("SUMIF(CEN_Energia!B:B,ResumenRetiros!B",A14,",CEN_Energia!Z:Z)") -> SUMIF(CEN_Energia!B:B,ResumenRetiros!B14,CEN_Energia!Z:Z) | H14: =CONCATENATE("SUMIF(CEN_EnergiaBT!B:B,ResumenRetiros!B",A14,",CEN_EnergiaBT!K:K)") -> SUMIF(CEN_EnergiaBT!B:B,ResumenRetiros!B14,CEN_EnergiaBT!K:K)
D15: =CONCATENATE("SUM(D9:D14)") -> SUM(D9:D14) | E15: =CONCATENATE("SUM(E9:E14)") -> SUM(E9:E14) | F15: =CONCATENATE("SUM(F9:F14)") -> SUM(F9:F14) | G15: =CONCATENATE("SUM(G9:G14)") -> SUM(G9:G14) | H15: =CONCATENATE("SUM(H9:H14)") -> SUM(H9:H14)

Sheet FACT_EMITIDA
A1: Periodo | B1: MesDevengado | C1: Nombre | D1: Concepto | E1: Agrupacion | F1: Glosa | G1: FechaCarga | H1: TipoDocumento | I1: Folio | J1: Vendedor | K1: Comprador | L1: Bloque | M1: Empresa | N1: ClaveEEDD | O1: Licitacion | P1: NomAgrupacion | Q1: Num | R1: Barra | S1: Energia | T1: PrecioEnergia | U1: Potencia | V1: PrecioPotencia | W1: Monto
A2: 43344 | B2: 43344 | C2: Licitación Caren y Cec (SIC 2013/03-2) BS1A | D2: Energia Licitaciones | E2: Energía | F2: Lic. SIC 2013/03-2 bloques BS1A: Energía sep 2018 | G2: 43392 | H2: 33 | I2: 6305 | J2: s | K2: s | L2: BS1A | M2: Caren | N2: Cec | O2: 41335 | P2: CEC | Q2: 1 | R2: TotalBarras | S2: 3000 | T2: 58.085 | U2: NULL | V2: NULL | W2: 174255
A3: 43374 | B3: 43374 | C3: Licitación Caren y Cec (SIC 2013/03-2) BS1A | D3: Energia Licitaciones | E3: Energía | F3: Lic. SIC 2013/03-2 bloques BS1A: Energía oct 2018 | G3: 43431 | H3: 33 | I3: 6796 | J3: s | K3: s | L3: BS1A | M3: Caren | N3: Cec | O3: 41335 | P3: CEC | Q3: 1 | R3: TotalBarras | S3: 3000 | T3: 59.678 | U3: NULL | V3: NULL | W3: 179035
A4: 43405 | B4: 43405 | C4: Licitación Caren y Cec (SIC 2013/03-2) BS1A | D4: Energia Licitaciones | E4: Energía | F4: Lic. SIC 2013/03-2 bloques BS1A: Energía nov 2018 | G4: 43448 | H4: 33 | I4: 6939 | J4: s | K4: s | L4: BS1A | M4: Caren | N4: Cec | O4: 41335 | P4: CEC | Q4: 1 | R4: TotalBarras | S4: 4000 | T4: 59.635 | U4: NULL | V4: NULL | W4: 238540
A5: 43435 | B5: 43435 | C5: Licitación Caren y Cec (SIC 2013/03-2) BS1A | D5: Energia Licitaciones | E5: Energía | F5: Lic. SIC 2013/03-2 bloques BS1A: Energía dic 2018 | G5: 43486 | H5: 33 | I5: 7194 | J5: s | K5: s | L5: BS1A | M5: Caren | N5: Cec | O5: 41335 | P5: CEC | Q5: 1 | R5: TotalBarras | S5: 5000 | T5: 67.951 | U5: NULL | V5: NULL | W5: 339757
A6: 43466 | B6: 43466 | C6: Licitación Caren y Cec (SIC 2013/03-2) BS1A | D6: Reliq. Energia Licitaciones | E6: Energía | F6: Lic. SIC 2013/03-2 bloques BS1A: Reliq. Energía ene 2019 | G6: 43539 | H6: 33 | I6: NULL | J6: s | K6: s | L6: BS1A | M6: Caren | N6: Cec | O6: 41335 | P6: CEC | Q6: 1 | R6: A.JAHUEL 220 | S6: 1.46188 | T6: 66.9 | U6: NULL | V6: NULL | W6: 98
A7: 43466 | B7: 43466 | C7: Licitación Caren y Cec (SIC 2013/03-2) BS1A | D7: Energia Licitaciones | E7: Energía | F7: Lic. SIC 2013/03-2 bloques BS1A: Energía ene 2019 | G7: 43504 | H7: 33 | I7: 7513 | J7: s | K7: s | L7: BS1A | M7: Caren | N7: Cec | O7: 41335 | P7: CEC | Q7: 1 | R7: A.JAHUEL 220 | S7: 1371.306 | T7: 66.9 | U7: NULL | V7: NULL | W7: 91740
A8: 43466 | B8: 43466 | C8: Licitación Caren y Cec (SIC 2013/03-2) BS1A | D8: Reliq. Energia Licitaciones | E8: Energía | F8: Lic. SIC 2013/03-2 bloques BS1A: Reliq. Energía ene 2019 | G8: 43539 | H8: 33 | I8: NULL | J8: s | K8: s | L8: BS1A | M8: Caren | N8: Cec | O8: 41335 | P8: CEC | Q8: 2 | R8: A.MELIP 220 | S8: 0.009388 | T8: 69.014 | U8: NULL | V8: NULL | W8: 1
A9: 43466 | B9: 43466 | C9: Licitación Caren y Cec (SIC 2013/03-2) BS1A | D9: Energia Licitaciones | E9: Energía | F9: Lic. SIC 2013/03-2 bloques BS1A: Energía ene 2019 | G9: 43504 | H9: 33 | I9: 7513 | J9: s | K9: s | L9: BS1A | M9: Caren | N9: Cec | O9: 41335 | P9: CEC | Q9: 2 | R9: A.MELIP 220 | S9: 8.806166 | T9: 69.014 | U9: NULL | V9: NULL | W9: 608
A10: 43466 | B10: 43466 | C10: Licitación Caren y Cec (SIC 2013/03-2) BS1A | D10: Reliq. Energia Licitaciones | E10: Energía | F10: Lic. SIC 2013/03-2 bloques BS1A: Reliq. Energía ene 2019 | G10: 43539 | H10: 33 | I10: NULL | J10: s | K10: s | L10: BS1A | M10: Caren | N10: Cec | O10: 41335 | P10: CEC | Q10: 3 | R10: CHARRUA 220 | S10: 0.453721 | T10: 63.27 | U10: NULL | V10: NULL | W10: 29
A11: 43466 | B11: 43466 | C11: Licitación Caren y Cec (SIC 2013/03-2) BS1A | D11: Energia Licitaciones | E11: Energía | F11: Lic. SIC 2013/03-2 bloques BS1A: Energía ene 2019 | G11: 43504 | H11: 33 | I11: 7513 | J11: s | K11: s | L11: BS1A | M11: Caren | N11: Cec | O11: 41335 | P11: CEC | Q11: 3 | R11: CHARRUA 220 | S11: 425.60961 | T11: 63.27 | U11: NULL | V11: NULL | W11: 26928
A12: 43466 | B12: 43466 | C12: Licitación Caren y Cec (SIC 2013/03-2) BS1A | D12: Reliq. Energia Licitaciones | E12: Energía | F12: Lic. SIC 2013/03-2 bloques BS1A: Reliq. Energía ene 2019 | G12: 43539 | H12: 33 | I12: NULL | J12: s | K12: s | L12: BS1A | M12: Caren | N12: Cec | O12: 41335 | P12: CEC | Q12: 4 | R12: ITAHUE 220 | S12: 2.212452 | T12: 65.349 | U12: NULL | V12: NULL | W12: 145
A13: 43466 | B13: 43466 | C13: Licitación Caren y Cec (SIC 2013/03-2) BS1A | D13: Energia Licitaciones | E13: Energía | F13: Lic. SIC 2013/03-2 bloques BS1A: Energía ene 2019 | G13: 43504 | H13: 33 | I13: 7513 | J13: s | K13: s | L13: BS1A | M13: Caren | N13: Cec | O13: 41335 | P13: CEC | Q13: 4 | R13: ITAHUE 220 | S13: 2075.374 | T13: 65.349 | U13: NULL | V13: NULL | W13: 135624
A14: 43466 | B14: 43466 | C14: Licitación Caren y Cec (SIC 2013/03-2) BS1A | D14: Reliq. Energia Licitaciones | E14: Energía | F14: Lic. SIC 2013/03-2 bloques BS1A: Reliq. Energía ene 2019 | G14: 43539 | H14: 33 | I14: NULL | J14: s | K14: s | L14: BS1A | M14: Caren | N14: Cec | O14: 41335 | P14: CEC | Q14: 5 | R14: RAPEL 220 | S14: 0.008637 | T14: 69.368 | U14: NULL | V14: NULL | W14: 1
A15: 43466 | B15: 43466 | C15: Licitación Caren y Cec (SIC 2013/03-2) BS1A | D15: Energia Licitaciones | E15: Energía | F15: Lic. SIC 2013/03-2 bloques BS1A: Energía ene 2019 | G15: 43504 | H15: 33 | I15: 7513 | J15: s | K15: s | L15: BS1A | M15: Caren | N15: Cec | O15: 41335 | P15: CEC | Q15: 5 | R15: RAPEL 220 | S15: 8.102057 | T15: 69.368 | U15: NULL | V15: NULL | W15: 562
A16: 43497 | B16: 43497 | C16: Licitación Caren y Cec (SIC 2013/03-2) BS1A | D16: Reliq. Energia Licitaciones | E16: Energía | F16: Lic. SIC 2013/03-2 bloques BS1A: Reliq. Energía feb 2019 | G16: 43564 | H16: 61 | I16: NULL | J16: s | K16: s | L16: BS1A | M16: Caren | N16: Cec | O16: 41335 | P16: CEC | Q16: 1 | R16: A.JAHUEL 220 | S16: 0.23349 | T16: 66.9 | U16: NULL | V16: NULL | W16: 16
A17: 43497 | B17: 43497 | C17: Licitación Caren y Cec (SIC 2013/03-2) BS1A | D17: Energia Licitaciones | E17: Energía | F17: Lic. SIC 2013/03-2 bloques BS1A: Energía feb 2019 | G17: 43532 | H17: 33 | I17: 7798 | J17: s | K17: s | L17: BS1A | M17: Caren | N17: Cec | O17: 41335 | P17: CEC | Q17: 1 | R17: A.JAHUEL 220 | S17: 1368.5299 | T17: 66.9 | U17: NULL | V17: NULL | W17: 91555
A18: 43497 | B18: 43497 | C18: Licitación Caren y Cec (SIC 2013/03-2) BS1A | D18: Energia Licitaciones | E18: Energía | F18: Lic. SIC 2013/03-2 bloques BS1A: Energía feb 2019 | G18: 43532 | H18: 33 | I18: 7798 | J18: s | K18: s | L18: BS1A | M18: Caren | N18: Cec | O18: 41335 | P18: CEC | Q18: 2 | R18: A.MELIP 220 | S18: 8.816632 | T18: 69.014 | U18: NULL | V18: NULL | W18: 608
A19: 43497 | B19: 43497 | C19: Licitación Caren y Cec (SIC 2013/03-2) BS1A | D19: Reliq. Energia Licitaciones | E19: Energía | F19: Lic. SIC 2013/03-2 bloques BS1A: Reliq. Energía feb 2019 | G19: 43564 | H19: 61 | I19: NULL | J19: s | K19: s | L19: BS1A | M19: Caren | N19: Cec | O19: 41335 | P19: CEC | Q19: 3 | R19: CHARRUA 220 | S19: 0.072089 | T19: 63.27 | U19: NULL | V19: NULL | W19: 5
A20: 43497 | B20: 43497 | C20: Licitación Caren y Cec (SIC 2013/03-2) BS1A | D20: Energia Licitaciones | E20: Energía | F20: Lic. SIC 2013/03-2 bloques BS1A: Energía feb 2019 | G20: 43532 | H20: 33 | I20: 7798 | J20: s | K20: s | L20: BS1A | M20: Caren | N20: Cec | O20: 41335 | P20: CEC | Q20: 3 | R20: CHARRUA 220 | S20: 422.52678 | T20: 63.27 | U20: NULL | V20: NULL | W20: 26733
A21: 43497 | B21: 43497 | C21: Licitación Caren y Cec (SIC 2013/03-2) BS1A | D21: Reliq. Energia Licitaciones | E21: Energía | F21: Lic. SIC 2013/03-2 bloques BS1A: Reliq. Energía feb 2019 | G21: 43564 | H21: 61 | I21: NULL | J21: s | K21: s | L21: BS1A | M21: Caren | N21: Cec | O21: 41335 | P21: CEC | Q21: 4 | R21: ITAHUE 220 | S21: 0.353269 | T21: 65.349 | U21: NULL | V21: NULL | W21: 23
A22: 43497 | B22: 43497 | C22: Licitación Caren y Cec (SIC 2013/03-2) BS1A | D22: Energia Licitaciones | E22: Energía | F22: Lic. SIC 2013/03-2 bloques BS1A: Energía feb 2019 | G22: 43532 | H22: 33 | I22: 7798 | J22: s | K22: s | L22: BS1A | M22: Caren | N22: Cec | O22: 41335 | P22: CEC | Q22: 4 | R22: ITAHUE 220 | S22: 2070.5801 | T22: 65.349 | U22: NULL | V22: NULL | W22: 135310
A23: 43497 | B23: 43497 | C23: Licitación Caren y Cec (SIC 2013/03-2) BS1A | D23: Energia Licitaciones | E23: Energía | F23: Lic. SIC 2013/03-2 bloques BS1A: Energía feb 2019 | G23: 43532 | H23: 33 | I23: 7798 | J23: s | K23: s | L23: BS1A | M23: Caren | N23: Cec | O23: 41335 | P23: CEC | Q23: 5 | R23: RAPEL 220 | S23: 8.102328 | T23: 69.368 | U23: NULL | V23: NULL | W23: 562
A24: 43525 | B24: 43525 | C24: Licitación Caren y Cec (SIC 2013/03-2) BS1A | D24: Reliq. Energia Licitaciones | E24: Energía | F24: Lic. SIC 2013/03-2 bloques BS1A: Reliq. Energía mar 2019 | G24: 43598 | H24: 33 | I24: NULL | J24: s | K24: s | L24: BS1A | M24: Caren | N24: Cec | O24: 41335 | P24: CEC | Q24: 1 | R24: A.JAHUEL 220 | S24: 0.580609 | T24: 66.9 | U24: NULL | V24: NULL | W24: 39
A25: 43525 | B25: 43525 | C25: Licitación Caren y Cec (SIC 2013/03-2) BS1A | D25: Energia Licitaciones | E25: Energía | F25: Lic. SIC 2013/03-2 bloques BS1A: Energía mar 2019 | G25: 43563 | H25: 33 | I25: 8389 | J25: s | K25: s | L25: BS1A | M25: Caren | N25: Cec | O25: 41335 | P25: CEC | Q25: 1 | R25: A.JAHUEL 220 | S25: 1311.6233 | T25: 66.9 | U25: NULL | V25: NULL | W25: 87748
A26: 43525 | B26: 43525 | C26: Licitación Caren y Cec (SIC 2013/03-2) BS1A | D26: Energia Licitaciones | E26: Energía | F26: Lic. SIC 2013/03-2 bloques BS1A: Energía mar 2019 | G26: 43563 | H26: 33 | I26: 8389 | J26: s | K26: s | L26: BS1A | M26: Caren | N26: Cec | O26: 41335 | P26: CEC | Q26: 2 | R26: A.MELIP 220 | S26: 8.173697 | T26: 69.014 | U26: NULL | V26: NULL | W26: 564
A27: 43525 | B27: 43525 | C27: Licitación Caren y Cec (SIC 2013/03-2) BS1A | D27: Reliq. Energia Licitaciones | E27: Energía | F27: Lic. SIC 2013/03-2 bloques BS1A: Reliq. Energía mar 2019 | G27: 43598 | H27: 33 | I27: NULL | J27: s | K27: s | L27: BS1A | M27: Caren | N27: Cec | O27: 41335 | P27: CEC | Q27: 3 | R27: CHARRUA 220 | S27: 0.178218 | T27: 63.27 | U27: NULL | V27: NULL | W27: 11
A28: 43525 | B28: 43525 | C28: Licitación Caren y Cec (SIC 2013/03-2) BS1A | D28: Energia Licitaciones | E28: Energía | F28: Lic. SIC 2013/03-2 bloques BS1A: Energía mar 2019 | G28: 43563 | H28: 33 | I28: 8389 | J28: s | K28: s | L28: BS1A | M28: Caren | N28: Cec | O28: 41335 | P28: CEC | Q28: 3 | R28: CHARRUA 220 | S28: 402.60399 | T28: 63.27 | U28: NULL | V28: NULL | W28: 25473
A29: 43525 | B29: 43525 | C29: Licitación Caren y Cec (SIC 2013/03-2) BS1A | D29: Reliq. Energia Licitaciones | E29: Energía | F29: Lic. SIC 2013/03-2 bloques BS1A: Reliq. Energía mar 2019 | G29: 43598 | H29: 33 | I29: NULL | J29: s | K29: s | L29: BS1A | M29: Caren | N29: Cec | O29: 41335 | P29: CEC | Q29: 4 | R29: ITAHUE 220 | S29: 0.87116 | T29: 65.349 | U29: NULL | V29: NULL | W29: 57
A30: 43525 | B30: 43525 | C30: Licitación Caren y Cec (SIC 2013/03-2) BS1A | D30: Energia Licitaciones | E30: Energía | F30: Lic. SIC 2013/03-2 bloques BS1A: Energía mar 2019 | G30: 43563 | H30: 33 | I30: 8389 | J30: s | K30: s | L30: BS1A | M30: Caren | N30: Cec | O30: 41335 | P30: CEC | Q30: 4 | R30: ITAHUE 220 | S30: 1967.9945 | T30: 65.349 | U30: NULL | V30: NULL | W30: 128606
A31: 43525 | B31: 43525 | C31: Licitación Caren y Cec (SIC 2013/03-2) BS1A | D31: Energia Licitaciones | E31: Energía | F31: Lic. SIC 2013/03-2 bloques BS1A: Energía mar 2019 | G31: 43563 | H31: 33 | I31: 8389 | J31: s | K31: s | L31: BS1A | M31: Caren | N31: Cec | O31: 41335 | P31: CEC | Q31: 5 | R31: RAPEL 220 | S31: 7.514895 | T31: 69.368 | U31: NULL | V31: NULL | W31: 521
A32: 43556 | B32: 43556 | C32: Licitación Caren y Cec (SIC 2013/03-2) BS1A | D32: Potencia Licitaciones | E32: Potencia | F32: Lic. SIC 2013/03-2 bloques BS1A: Potencia abr 2019 | G32: 43598 | H32: 33 | I32: 8451 | J32: s | K32: s | L32: BS1A | M32: Caren | N32: Cec | O32: 41335 | P32: CEC | Q32: 1 | R32: A.JAHUEL 220 | S32: NULL | T32: NULL | U32: 0 | V32: 0 | W32: 0
A33: 43556 | B33: 43556 | C33: Licitación Caren y Cec (SIC 2013/03-2) BS1A | D33: Reliq. Energia Licitaciones | E33: Energía | F33: Lic. SIC 2013/03-2 bloques BS1A: Reliq. Energía abr 2019 | G33: 43913.498 | H33: 61 | I33: NULL | J33: s | K33: s | L33: BS1A | M33: Caren | N33: Cec | O33: 41335 | P33: CEC | Q33: 1 | R33: A.JAHUEL 220 | S33: 1 | T33: -1091 | U33: NULL | V33: NULL | W33: -1091
A34: 43556 | B34: 43556 | C34: Licitación Caren y Cec (SIC 2013/03-2) BS1A | D34: Energia Licitaciones | E34: Energía | F34: Lic. SIC 2013/03-2 bloques BS1A: Energía abr 2019 | G34: 43598 | H34: 33 | I34: 8451 | J34: s | K34: s | L34: BS1A | M34: Caren | N34: Cec | O34: 41335 | P34: CEC | Q34: 1 | R34: A.JAHUEL 220 | S34: 897.9651 | T34: 66.9 | U34: NULL | V34: NULL | W34: 60074
A35: 43556 | B35: 43556 | C35: Licitación Caren y Cec (SIC 2013/03-2) BS1A | D35: Potencia Licitaciones | E35: Potencia | F35: Lic. SIC 2013/03-2 bloques BS1A: Potencia abr 2019 | G35: 43598 | H35: 33 | I35: 8451 | J35: s | K35: s | L35: BS1A | M35: Caren | N35: Cec | O35: 41335 | P35: CEC | Q35: 2 | R35: A.MELIP 220 | S35: NULL | T35: NULL | U35: 0 | V35: 0 | W35: 0
A36: 43556 | B36: 43556 | C36: Licitación Caren y Cec (SIC 2013/03-2) BS1A | D36: Reliq. Energia Licitaciones | E36: Energía | F36: Lic. SIC 2013/03-2 bloques BS1A: Reliq. Energía abr 2019 | G36: 43913.498 | H36: 61 | I36: NULL | J36: s | K36: s | L36: BS1A | M36: Caren | N36: Cec | O36: 41335 | P36: CEC | Q36: 2 | R36: A.MELIP 220 | S36: 1 | T36: -8 | U36: NULL | V36: NULL | W36: -8
A37: 43556 | B37: 43556 | C37: Licitación Caren y Cec (SIC 2013/03-2) BS1A | D37: Energia Licitaciones | E37: Energía | F37: Lic. SIC 2013/03-2 bloques BS1A: Energía abr 2019 | G37: 43598 | H37: 33 | I37: 8451 | J37: s | K37: s | L37: BS1A | M37: Caren | N37: Cec | O37: 41335 | P37: CEC | Q37: 2 | R37: A.MELIP 220 | S37: 5.912451 | T37: 69.014 | U37: NULL | V37: NULL | W37: 408
A38: 43556 | B38: 43556 | C38: Licitación Caren y Cec (SIC 2013/03-2) BS1A | D38: Potencia Licitaciones | E38: Potencia | F38: Lic. SIC 2013/03-2 bloques BS1A: Potencia abr 2019 | G38: 43598 | H38: 33 | I38: 8451 | J38: s | K38: s | L38: BS1A | M38: Caren | N38: Cec | O38: 41335 | P38: CEC | Q38: 3 | R38: CHARRUA 220 | S38: NULL | T38: NULL | U38: 0 | V38: 0 | W38: 0
A39: 43556 | B39: 43556 | C39: Licitación Caren y Cec (SIC 2013/03-2) BS1A | D39: Reliq. Energia Licitaciones | E39: Energía | F39: Lic. SIC 2013/03-2 bloques BS1A: Reliq. Energía abr 2019 | G39: 43913.498 | H39: 61 | I39: NULL | J39: s | K39: s | L39: BS1A | M39: Caren | N39: Cec | O39: 41335 | P39: CEC | Q39: 3 | R39: CHARRUA 220 | S39: 1 | T39: -327 | U39: NULL | V39: NULL | W39: -327
A40: 43556 | B40: 43556 | C40: Licitación Caren y Cec (SIC 2013/03-2) BS1A | D40: Energia Licitaciones | E40: Energía | F40: Lic. SIC 2013/03-2 bloques BS1A: Energía abr 2019 | G40: 43598 | H40: 33 | I40: 8451 | J40: s | K40: s | L40: BS1A | M40: Caren | N40: Cec | O40: 41335 | P40: CEC | Q40: 3 | R40: CHARRUA 220 | S40: 278.37089 | T40: 63.27 | U40: NULL | V40: NULL | W40: 17613
A41: 43556 | B41: 43556 | C41: Licitación Caren y Cec (SIC 2013/03-2) BS1A | D41: Potencia Licitaciones | E41: Potencia | F41: Lic. SIC 2013/03-2 bloques BS1A: Potencia abr 2019 | G41: 43598 | H41: 33 | I41: 8451 | J41: s | K41: s | L41: BS1A | M41: Caren | N41: Cec | O41: 41335 | P41: CEC | Q41: 4 | R41: ITAHUE 220 | S41: NULL | T41: NULL | U41: 0 | V41: 0 | W41: 0
A42: 43556 | B42: 43556 | C42: Licitación Caren y Cec (SIC 2013/03-2) BS1A | D42: Reliq. Energia Licitaciones | E42: Energía | F42: Lic. SIC 2013/03-2 bloques BS1A: Reliq. Energía abr 2019 | G42: 43913.498 | H42: 61 | I42: NULL | J42: s | K42: s | L42: BS1A | M42: Caren | N42: Cec | O42: 41335 | P42: CEC | Q42: 4 | R42: ITAHUE 220 | S42: 1 | T42: -1638 | U42: NULL | V42: NULL | W42: -1638
A43: 43556 | B43: 43556 | C43: Licitación Caren y Cec (SIC 2013/03-2) BS1A | D43: Energia Licitaciones | E43: Energía | F43: Lic. SIC 2013/03-2 bloques BS1A: Energía abr 2019 | G43: 43598 | H43: 33 | I43: 8451 | J43: s | K43: s | L43: BS1A | M43: Caren | N43: Cec | O43: 41335 | P43: CEC | Q43: 4 | R43: ITAHUE 220 | S43: 1366.2586 | T43: 65.349 | U43: NULL | V43: NULL | W43: 89284
A44: 43556 | B44: 43556 | C44: Licitación Caren y Cec (SIC 2013/03-2) BS1A | D44: Potencia Licitaciones | E44: Potencia | F44: Lic. SIC 2013/03-2 bloques BS1A: Potencia abr 2019 | G44: 43598 | H44: 33 | I44: 8451 | J44: s | K44: s | L44: BS1A | M44: Caren | N44: Cec | O44: 41335 | P44: CEC | Q44: 5 | R44: RAPEL 220 | S44: NULL | T44: NULL | U44: 0 | V44: 0 | W44: 0
A45: 43556 | B45: 43556 | C45: Licitación Caren y Cec (SIC 2013/03-2) BS1A | D45: Reliq. Energia Licitaciones | E45: Energía | F45: Lic. SIC 2013/03-2 bloques BS1A: Reliq. Energía abr 2019 | G45: 43913.498 | H45: 61 | I45: NULL | J45: s | K45: s | L45: BS1A | M45: Caren | N45: Cec | O45: 41335 | P45: CEC | Q45: 5 | R45: RAPEL 220 | S45: 1 | T45: -7 | U45: NULL | V45: NULL | W45: -7
A46: 43556 | B46: 43556 | C46: Licitación Caren y Cec (SIC 2013/03-2) BS1A | D46: Energia Licitaciones | E46: Energía | F46: Lic. SIC 2013/03-2 bloques BS1A: Energía abr 2019 | G46: 43598 | H46: 33 | I46: 8451 | J46: s | K46: s | L46: BS1A | M46: Caren | N46: Cec | O46: 41335 | P46: CEC | Q46: 5 | R46: RAPEL 220 | S46: 5.432024 | T46: 69.368 | U46: NULL | V46: NULL | W46: 377
A47: 43586 | B47: 43586 | C47: Licitación Caren y Cec (SIC 2013/03-2) BS1A | D47: Potencia Licitaciones | E47: Potencia | F47: Lic. SIC 2013/03-2 bloques BS1A: Potencia may 2019 | G47: 43627 | H47: 33 | I47: 8768 | J47: s | K47: s | L47: BS1A | M47: Caren | N47: Cec | O47: 41335 | P47: CEC | Q47: 1 | R47: A.JAHUEL 220 | S47: NULL | T47: NULL | U47: 0 | V47: 0 | W47: 0
A48: 43586 | B48: 43586 | C48: Licitación Caren y Cec (SIC 2013/03-2) BS1A | D48: Reliq. Energia Licitaciones | E48: Energía | F48: Lic. SIC 2013/03-2 bloques BS1A: Reliq. Energía may 2019 | G48: 43915.631 | H48: 61 | I48: NULL | J48: s | K48: s | L48: BS1A | M48: Caren | N48: Cec | O48: 41335 | P48: CEC | Q48: 1 | R48: A.JAHUEL 220 | S48: 1 | T48: -337 | U48: NULL | V48: NULL | W48: -337
A49: 43586 | B49: 43586 | C49: Licitación Caren y Cec (SIC 2013/03-2) BS1A | D49: Energia Licitaciones | E49: Energía | F49: Lic. SIC 2013/03-2 bloques BS1A: Energía may 2019 | G49: 43627 | H49: 33 | I49: 8768 | J49: s | K49: s | L49: BS1A | M49: Caren | N49: Cec | O49: 41335 | P49: CEC | Q49: 1 | R49: A.JAHUEL 220 | S49: 885.88967 | T49: 74.401 | U49: NULL | V49: NULL | W49: 65911
A50: 43586 | B50: 43586 | C50: Licitación Caren y Cec (SIC 2013/03-2) BS1A | D50: Potencia Licitaciones | E50: Potencia | F50: Lic. SIC 2013/03-2 bloques BS1A: Potencia may 2019 | G50: 43627 | H50: 33 | I50: 8768 | J50: s | K50: s | L50: BS1A | M50: Caren | N50: Cec | O50: 41335 | P50: CEC | Q50: 2 | R50: A.MELIP 220 | S50: NULL | T50: NULL | U50: 0 | V50: 0 | W50: 0
A51: 43586 | B51: 43586 | C51: Licitación Caren y Cec (SIC 2013/03-2) BS1A | D51: Reliq. Energia Licitaciones | E51: Energía | F51: Lic. SIC 2013/03-2 bloques BS1A: Reliq. Energía may 2019 | G51: 43915.631 | H51: 61 | I51: NULL | J51: s | K51: s | L51: BS1A | M51: Caren | N51: Cec | O51: 41335 | P51: CEC | Q51: 2 | R51: A.MELIP 220 | S51: 1 | T51: -2 | U51: NULL | V51: NULL | W51: -2
A52: 43586 | B52: 43586 | C52: Licitación Caren y Cec (SIC 2013/03-2) BS1A | D52: Energia Licitaciones | E52: Energía | F52: Lic. SIC 2013/03-2 bloques BS1A: Energía may 2019 | G52: 43627 | H52: 33 | I52: 8768 | J52: s | K52: s | L52: BS1A | M52: Caren | N52: Cec | O52: 41335 | P52: CEC | Q52: 2 | R52: A.MELIP 220 | S52: 5.728447 | T52: 75.737 | U52: NULL | V52: NULL | W52: 434
A53: 43586 | B53: 43586 | C53: Licitación Caren y Cec (SIC 2013/03-2) BS1A | D53: Potencia Licitaciones | E53: Potencia | F53: Lic. SIC 2013/03-2 bloques BS1A: Potencia may 2019 | G53: 43627 | H53: 33 | I53: 8768 | J53: s | K53: s | L53: BS1A | M53: Caren | N53: Cec | O53: 41335 | P53: CEC | Q53: 3 | R53: CHARRUA 220 | S53: NULL | T53: NULL | U53: 0 | V53: 0 | W53: 0
A54: 43586 | B54: 43586 | C54: Licitación Caren y Cec (SIC 2013/03-2) BS1A | D54: Reliq. Energia Licitaciones | E54: Energía | F54: Lic. SIC 2013/03-2 bloques BS1A: Reliq. Energía may 2019 | G54: 43915.631 | H54: 61 | I54: NULL | J54: s | K54: s | L54: BS1A | M54: Caren | N54: Cec | O54: 41335 | P54: CEC | Q54: 3 | R54: CHARRUA 220 | S54: 1 | T54: -99 | U54: NULL | V54: NULL | W54: -99
A55: 43586 | B55: 43586 | C55: Licitación Caren y Cec (SIC 2013/03-2) BS1A | D55: Energia Licitaciones | E55: Energía | F55: Lic. SIC 2013/03-2 bloques BS1A: Energía may 2019 | G55: 43627 | H55: 33 | I55: 8768 | J55: s | K55: s | L55: BS1A | M55: Caren | N55: Cec | O55: 41335 | P55: CEC | Q55: 3 | R55: CHARRUA 220 | S55: 273.81804 | T55: 70.437 | U55: NULL | V55: NULL | W55: 19287
A56: 43586 | B56: 43586 | C56: Licitación Caren y Cec (SIC 2013/03-2) BS1A | D56: Potencia Licitaciones | E56: Potencia | F56: Lic. SIC 2013/03-2 bloques BS1A: Potencia may 2019 | G56: 43627 | H56: 33 | I56: 8768 | J56: s | K56: s | L56: BS1A | M56: Caren | N56: Cec | O56: 41335 | P56: CEC | Q56: 4 | R56: ITAHUE 220 | S56: NULL | T56: NULL | U56: 0 | V56: 0 | W56: 0
A57: 43586 | B57: 43586 | C57: Licitación Caren y Cec (SIC 2013/03-2) BS1A | D57: Reliq. Energia Licitaciones | E57: Energía | F57: Lic. SIC 2013/03-2 bloques BS1A: Reliq. Energía may 2019 | G57: 43915.631 | H57: 61 | I57: NULL | J57: s | K57: s | L57: BS1A | M57: Caren | N57: Cec | O57: 41335 | P57: CEC | Q57: 4 | R57: ITAHUE 220 | S57: 1 | T57: -494 | U57: NULL | V57: NULL | W57: -494
A58: 43586 | B58: 43586 | C58: Licitación Caren y Cec (SIC 2013/03-2) BS1A | D58: Energia Licitaciones | E58: Energía | F58: Lic. SIC 2013/03-2 bloques BS1A: Energía may 2019 | G58: 43627 | H58: 33 | I58: 8768 | J58: s | K58: s | L58: BS1A | M58: Caren | N58: Cec | O58: 41335 | P58: CEC | Q58: 4 | R58: ITAHUE 220 | S58: 1341.7257 | T58: 71.984 | U58: NULL | V58: NULL | W58: 96583
A59: 43586 | B59: 43586 | C59: Licitación Caren y Cec (SIC 2013/03-2) BS1A | D59: Potencia Licitaciones | E59: Potencia | F59: Lic. SIC 2013/03-2 bloques BS1A: Potencia may 2019 | G59: 43627 | H59: 33 | I59: 8768 | J59: s | K59: s | L59: BS1A | M59: Caren | N59: Cec | O59: 41335 | P59: CEC | Q59: 5 | R59: RAPEL 220 | S59: NULL | T59: NULL | U59: 0 | V59: 0 | W59: 0
A60: 43586 | B60: 43586 | C60: Licitación Caren y Cec (SIC 2013/03-2) BS1A | D60: Reliq. Energia Licitaciones | E60: Energía | F60: Lic. SIC 2013/03-2 bloques BS1A: Reliq. Energía may 2019 | G60: 43915.631 | H60: 61 | I60: NULL | J60: s | K60: s | L60: BS1A | M60: Caren | N60: Cec | O60: 41335 | P60: CEC | Q60: 5 | R60: RAPEL 220 | S60: 1 | T60: -2 | U60: NULL | V60: NULL | W60: -2
A61: 43586 | B61: 43586 | C61: Licitación Caren y Cec (SIC 2013/03-2) BS1A | D61: Energia Licitaciones | E61: Energía | F61: Lic. SIC 2013/03-2 bloques BS1A: Energía may 2019 | G61: 43627 | H61: 33 | I61: 8768 | J61: s | K61: s | L61: BS1A | M61: Caren | N61: Cec | O61: 41335 | P61: CEC | Q61: 5 | R61: RAPEL 220 | S61: 5.26453 | T61: 75.617 | U61: NULL | V61: NULL | W61: 398
A62: 43617 | B62: 43617 | C62: Licitación Caren y Cec (SIC 2013/03-2) BS1A | D62: Potencia Licitaciones | E62: Potencia | F62: Lic. SIC 2013/03-2 bloques BS1A: Potencia jun 2019 | G62: 43655 | H62: 33 | I62: 9022 | J62: s | K62: s | L62: BS1A | M62: Caren | N62: Cec | O62: 41335 | P62: CEC | Q62: 1 | R62: A.JAHUEL 220 | S62: NULL | T62: NULL | U62: 0 | V62: 0 | W62: 0
A63: 43617 | B63: 43617 | C63: Licitación Caren y Cec (SIC 2013/03-2) BS1A | D63: Reliq. Energia Licitaciones | E63: Energía | F63: Lic. SIC 2013/03-2 bloques BS1A: Reliq. Energía jun 2019 | G63: 43693 | H63: 33 | I63: NULL | J63: s | K63: s | L63: BS1A | M63: Caren | N63: Cec | O63: 41335 | P63: CEC | Q63: 1 | R63: A.JAHUEL 220 | S63: 1.775945 | T63: 74.401 | U63: NULL | V63: NULL | W63: 132
A64: 43617 | B64: 43617 | C64: Licitación Caren y Cec (SIC 2013/03-2) BS1A | D64: Energia Licitaciones | E64: Energía | F64: Lic. SIC 2013/03-2 bloques BS1A: Energía jun 2019 | G64: 43655 | H64: 33 | I64: 9022 | J64: s | K64: s | L64: BS1A | M64: Caren | N64: Cec | O64: 41335 | P64: CEC | Q64: 1 | R64: A.JAHUEL 220 | S64: 790.40863 | T64: 74.401 | U64: NULL | V64: NULL | W64: 58807
A65: 43617 | B65: 43617 | C65: Licitación Caren y Cec (SIC 2013/03-2) BS1A | D65: Potencia Licitaciones | E65: Potencia | F65: Lic. SIC 2013/03-2 bloques BS1A: Potencia jun 2019 | G65: 43655 | H65: 33 | I65: 9022 | J65: s | K65: s | L65: BS1A | M65: Caren | N65: Cec | O65: 41335 | P65: CEC | Q65: 2 | R65: A.MELIP 220 | S65: NULL | T65: NULL | U65: 0 | V65: 0 | W65: 0
A66: 43617 | B66: 43617 | C66: Licitación Caren y Cec (SIC 2013/03-2) BS1A | D66: Reliq. Energia Licitaciones | E66: Energía | F66: Lic. SIC 2013/03-2 bloques BS1A: Reliq. Energía jun 2019 | G66: 43693 | H66: 33 | I66: NULL | J66: s | K66: s | L66: BS1A | M66: Caren | N66: Cec | O66: 41335 | P66: CEC | Q66: 2 | R66: A.MELIP 220 | S66: 0.011666 | T66: 75.737 | U66: NULL | V66: NULL | W66: 1
A67: 43617 | B67: 43617 | C67: Licitación Caren y Cec (SIC 2013/03-2) BS1A | D67: Energia Licitaciones | E67: Energía | F67: Lic. SIC 2013/03-2 bloques BS1A: Energía jun 2019 | G67: 43655 | H67: 33 | I67: 9022 | J67: s | K67: s | L67: BS1A | M67: Caren | N67: Cec | O67: 41335 | P67: CEC | Q67: 2 | R67: A.MELIP 220 | S67: 5.19207 | T67: 75.737 | U67: NULL | V67: NULL | W67: 393
A68: 43617 | B68: 43617 | C68: Licitación Caren y Cec (SIC 2013/03-2) BS1A | D68: Potencia Licitaciones | E68: Potencia | F68: Lic. SIC 2013/03-2 bloques BS1A: Potencia jun 2019 | G68: 43655 | H68: 33 | I68: 9022 | J68: s | K68: s | L68: BS1A | M68: Caren | N68: Cec | O68: 41335 | P68: CEC | Q68: 3 | R68: CHARRUA 220 | S68: NULL | T68: NULL | U68: 0 | V68: 0 | W68: 0
A69: 43617 | B69: 43617 | C69: Licitación Caren y Cec (SIC 2013/03-2) BS1A | D69: Reliq. Energia Licitaciones | E69: Energía | F69: Lic. SIC 2013/03-2 bloques BS1A: Reliq. Energía jun 2019 | G69: 43693 | H69: 33 | I69: NULL | J69: s | K69: s | L69: BS1A | M69: Caren | N69: Cec | O69: 41335 | P69: CEC | Q69: 3 | R69: CHARRUA 220 | S69: 0.551932 | T69: 70.437 | U69: NULL | V69: NULL | W69: 39
A70: 43617 | B70: 43617 | C70: Licitación Caren y Cec (SIC 2013/03-2) BS1A | D70: Energia Licitaciones | E70: Energía | F70: Lic. SIC 2013/03-2 bloques BS1A: Energía jun 2019 | G70: 43655 | H70: 33 | I70: 9022 | J70: s | K70: s | L70: BS1A | M70: Caren | N70: Cec | O70: 41335 | P70: CEC | Q70: 3 | R70: CHARRUA 220 | S70: 245.64498 | T70: 70.437 | U70: NULL | V70: NULL | W70: 17302
A71: 43617 | B71: 43617 | C71: Licitación Caren y Cec (SIC 2013/03-2) BS1A | D71: Potencia Licitaciones | E71: Potencia | F71: Lic. SIC 2013/03-2 bloques BS1A: Potencia jun 2019 | G71: 43655 | H71: 33 | I71: 9022 | J71: s | K71: s | L71: BS1A | M71: Caren | N71: Cec | O71: 41335 | P71: CEC | Q71: 4 | R71: ITAHUE 220 | S71: NULL | T71: NULL | U71: 0 | V71: 0 | W71: 0
A72: 43617 | B72: 43617 | C72: Licitación Caren y Cec (SIC 2013/03-2) BS1A | D72: Reliq. Energia Licitaciones | E72: Energía | F72: Lic. SIC 2013/03-2 bloques BS1A: Reliq. Energía jun 2019 | G72: 43693 | H72: 33 | I72: NULL | J72: s | K72: s | L72: BS1A | M72: Caren | N72: Cec | O72: 41335 | P72: CEC | Q72: 4 | R72: ITAHUE 220 | S72: 2.701975 | T72: 71.984 | U72: NULL | V72: NULL | W72: 194
A73: 43617 | B73: 43617 | C73: Licitación Caren y Cec (SIC 2013/03-2) BS1A | D73: Energia Licitaciones | E73: Energía | F73: Lic. SIC 2013/03-2 bloques BS1A: Energía jun 2019 | G73: 43655 | H73: 33 | I73: 9022 | J73: s | K73: s | L73: BS1A | M73: Caren | N73: Cec | O73: 41335 | P73: CEC | Q73: 4 | R73: ITAHUE 220 | S73: 1202.5506 | T73: 71.984 | U73: NULL | V73: NULL | W73: 86564
A74: 43617 | B74: 43617 | C74: Licitación Caren y Cec (SIC 2013/03-2) BS1A | D74: Potencia Licitaciones | E74: Potencia | F74: Lic. SIC 2013/03-2 bloques BS1A: Potencia jun 2019 | G74: 43655 | H74: 33 | I74: 9022 | J74: s | K74: s | L74: BS1A | M74: Caren | N74: Cec | O74: 41335 | P74: CEC | Q74: 5 | R74: RAPEL 220 | S74: NULL | T74: NULL | U74: 0 | V74: 0 | W74: 0
A75: 43617 | B75: 43617 | C75: Licitación Caren y Cec (SIC 2013/03-2) BS1A | D75: Reliq. Energia Licitaciones | E75: Energía | F75: Lic. SIC 2013/03-2 bloques BS1A: Reliq. Energía jun 2019 | G75: 43693 | H75: 33 | I75: NULL | J75: s | K75: s | L75: BS1A | M75: Caren | N75: Cec | O75: 41335 | P75: CEC | Q75: 5 | R75: RAPEL 220 | S75: 0.010724 | T75: 75.617 | U75: NULL | V75: NULL | W75: 1
A76: 43617 | B76: 43617 | C76: Licitación Caren y Cec (SIC 2013/03-2) BS1A | D76: Energia Licitaciones | E76: Energía | F76: Lic. SIC 2013/03-2 bloques BS1A: Energía jun 2019 | G76: 43655 | H76: 33 | I76: 9022 | J76: s | K76: s | L76: BS1A | M76: Caren | N76: Cec | O76: 41335 | P76: CEC | Q76: 5 | R76: RAPEL 220 | S76: 4.772954 | T76: 75.617 | U76: NULL | V76: NULL | W76: 361
A77: 43647 | B77: 43647 | C77: Licitación Caren y Cec (SIC 2013/03-2) BS1A | D77: Potencia Licitaciones | E77: Potencia | F77: Lic. SIC 2013/03-2 bloques BS1A: Potencia jul 2019 | G77: 43686 | H77: 33 | I77: 9466 | J77: s | K77: s | L77: BS1A | M77: Caren | N77: Cec | O77: 41335 | P77: CEC | Q77: 1 | R77: A.JAHUEL 220 | S77: NULL | T77: NULL | U77: 0 | V77: 0 | W77: 0
A78: 43647 | B78: 43647 | C78: Licitación Caren y Cec (SIC 2013/03-2) BS1A | D78: Reliq. Energia Licitaciones | E78: Energía | F78: Lic. SIC 2013/03-2 bloques BS1A: Reliq. Energía jul 2019 | G78: 43914.908 | H78: 61 | I78: NULL | J78: s | K78: s | L78: BS1A | M78: Caren | N78: Cec | O78: 41335 | P78: CEC | Q78: 1 | R78: A.JAHUEL 220 | S78: 1 | T78: -19 | U78: NULL | V78: NULL | W78: -19
A79: 43647 | B79: 43647 | C79: Licitación Caren y Cec (SIC 2013/03-2) BS1A | D79: Energia Licitaciones | E79: Energía | F79: Lic. SIC 2013/03-2 bloques BS1A: Energía jul 2019 | G79: 43686 | H79: 33 | I79: 9466 | J79: s | K79: s | L79: BS1A | M79: Caren | N79: Cec | O79: 41335 | P79: CEC | Q79: 1 | R79: A.JAHUEL 220 | S79: 842.75503 | T79: 74.401 | U79: NULL | V79: NULL | W79: 62702
A80: 43647 | B80: 43647 | C80: Licitación Caren y Cec (SIC 2013/03-2) BS1A | D80: Potencia Licitaciones | E80: Potencia | F80: Lic. SIC 2013/03-2 bloques BS1A: Potencia jul 2019 | G80: 43686 | H80: 33 | I80: 9466 | J80: s | K80: s | L80: BS1A | M80: Caren | N80: Cec | O80: 41335 | P80: CEC | Q80: 2 | R80: A.MELIP 220 | S80: NULL | T80: NULL | U80: 0 | V80: 0 | W80: 0
A81: 43647 | B81: 43647 | C81: Licitación Caren y Cec (SIC 2013/03-2) BS1A | D81: Energia Licitaciones | E81: Energía | F81: Lic. SIC 2013/03-2 bloques BS1A: Energía jul 2019 | G81: 43686 | H81: 33 | I81: 9466 | J81: s | K81: s | L81: BS1A | M81: Caren | N81: Cec | O81: 41335 | P81: CEC | Q81: 2 | R81: A.MELIP 220 | S81: 3.672508 | T81: 75.737 | U81: NULL | V81: NULL | W81: 278
A82: 43647 | B82: 43647 | C82: Licitación Caren y Cec (SIC 2013/03-2) BS1A | D82: Potencia Licitaciones | E82: Potencia | F82: Lic. SIC 2013/03-2 bloques BS1A: Potencia jul 2019 | G82: 43686 | H82: 33 | I82: 9466 | J82: s | K82: s | L82: BS1A | M82: Caren | N82: Cec | O82: 41335 | P82: CEC | Q82: 3 | R82: CHARRUA 220 | S82: NULL | T82: NULL | U82: 0 | V82: 0 | W82: 0
A83: 43647 | B83: 43647 | C83: Licitación Caren y Cec (SIC 2013/03-2) BS1A | D83: Reliq. Energia Licitaciones | E83: Energía | F83: Lic. SIC 2013/03-2 bloques BS1A: Reliq. Energía jul 2019 | G83: 43914.908 | H83: 61 | I83: NULL | J83: s | K83: s | L83: BS1A | M83: Caren | N83: Cec | O83: 41335 | P83: CEC | Q83: 3 | R83: CHARRUA 220 | S83: 1 | T83: -3 | U83: NULL | V83: NULL | W83: -3
A84: 43647 | B84: 43647 | C84: Licitación Caren y Cec (SIC 2013/03-2) BS1A | D84: Energia Licitaciones | E84: Energía | F84: Lic. SIC 2013/03-2 bloques BS1A: Energía jul 2019 | G84: 43686 | H84: 33 | I84: 9466 | J84: s | K84: s | L84: BS1A | M84: Caren | N84: Cec | O84: 41335 | P84: CEC | Q84: 3 | R84: CHARRUA 220 | S84: 171.56035 | T84: 70.437 | U84: NULL | V84: NULL | W84: 12084
A85: 43647 | B85: 43647 | C85: Licitación Caren y Cec (SIC 2013/03-2) BS1A | D85: Potencia Licitaciones | E85: Potencia | F85: Lic. SIC 2013/03-2 bloques BS1A: Potencia jul 2019 | G85: 43686 | H85: 33 | I85: 9466 | J85: s | K85: s | L85: BS1A | M85: Caren | N85: Cec | O85: 41335 | P85: CEC | Q85: 4 | R85: ITAHUE 220 | S85: NULL | T85: NULL | U85: 0 | V85: 0 | W85: 0
A86: 43647 | B86: 43647 | C86: Licitación Caren y Cec (SIC 2013/03-2) BS1A | D86: Reliq. Energia Licitaciones | E86: Energía | F86: Lic. SIC 2013/03-2 bloques BS1A: Reliq. Energía jul 2019 | G86: 43914.908 | H86: 61 | I86: NULL | J86: s | K86: s | L86: BS1A | M86: Caren | N86: Cec | O86: 41335 | P86: CEC | Q86: 4 | R86: ITAHUE 220 | S86: 1 | T86: -25 | U86: NULL | V86: NULL | W86: -25
A87: 43647 | B87: 43647 | C87: Licitación Caren y Cec (SIC 2013/03-2) BS1A | D87: Energia Licitaciones | E87: Energía | F87: Lic. SIC 2013/03-2 bloques BS1A: Energía jul 2019 | G87: 43686 | H87: 33 | I87: 9466 | J87: s | K87: s | L87: BS1A | M87: Caren | N87: Cec | O87: 41335 | P87: CEC | Q87: 4 | R87: ITAHUE 220 | S87: 1210.3737 | T87: 71.984 | U87: NULL | V87: NULL | W87: 87128
A88: 43647 | B88: 43647 | C88: Licitación Caren y Cec (SIC 2013/03-2) BS1A | D88: Potencia Licitaciones | E88: Potencia | F88: Lic. SIC 2013/03-2 bloques BS1A: Potencia jul 2019 | G88: 43686 | H88: 33 | I88: 9466 | J88: s | K88: s | L88: BS1A | M88: Caren | N88: Cec | O88: 41335 | P88: CEC | Q88: 5 | R88: RAPEL 220 | S88: NULL | T88: NULL | U88: 0 | V88: 0 | W88: 0
A89: 43647 | B89: 43647 | C89: Licitación Caren y Cec (SIC 2013/03-2) BS1A | D89: Energia Licitaciones | E89: Energía | F89: Lic. SIC 2013/03-2 bloques BS1A: Energía jul 2019 | G89: 43686 | H89: 33 | I89: 9466 | J89: s | K89: s | L89: BS1A | M89: Caren | N89: Cec | O89: 41335 | P89: CEC | Q89: 5 | R89: RAPEL 220 | S89: 3.777267 | T89: 75.617 | U89: NULL | V89: NULL | W89: 286
A90: 43678 | B90: 43678 | C90: Licitación Caren y Cec (SIC 2013/03-2) BS1A | D90: Reliq. Energia Licitaciones | E90: Energía | F90: Lic. SIC 2013/03-2 bloques BS1A: Reliq. Energía ago 2019 | G90: 43915.394 | H90: 61 | I90: NULL | J90: s | K90: s | L90: BS1A | M90: Caren | N90: Cec | O90: 41335 | P90: CEC | Q90: 1 | R90: A.JAHUEL 220 | S90: 1 | T90: -415 | U90: NULL | V90: NULL | W90: -415
A91: 43678 | B91: 43678 | C91: Licitación Caren y Cec (SIC 2013/03-2) BS1A | D91: Energia Licitaciones | E91: Energía | F91: Lic. SIC 2013/03-2 bloques BS1A: Energía ago 2019 | G91: 43719 | H91: 33 | I91: 9996 | J91: s | K91: s | L91: BS1A | M91: Caren | N91: Cec | O91: 41335 | P91: CEC | Q91: 1 | R91: A.JAHUEL 220 | S91: 797.16754 | T91: 74.401 | U91: NULL | V91: NULL | W91: 59310
A92: 43678 | B92: 43739 | C92: Licitación Caren y Cec (SIC 2013/03-2) BS1A | D92: Potencia Licitaciones | E92: Potencia | F92: Lic. SIC 2013/03-2 bloques BS1A: Potencia oct 2019 | G92: 43719 | H92: 33 | I92: 9996 | J92: s | K92: s | L92: BS1A | M92: Caren | N92: Cec | O92: 41335 | P92: CEC | Q92: 1 | R92: A.JAHUEL 220 | S92: NULL | T92: NULL | U92: 0 | V92: 0 | W92: 0
A93: 43678 | B93: 43678 | C93: Licitación Caren y Cec (SIC 2013/03-2) BS1A | D93: Reliq. Energia Licitaciones | E93: Energía | F93: Lic. SIC 2013/03-2 bloques BS1A: Reliq. Energía ago 2019 | G93: 43915.394 | H93: 61 | I93: NULL | J93: s | K93: s | L93: BS1A | M93: Caren | N93: Cec | O93: 41335 | P93: CEC | Q93: 2 | R93: A.MELIP 220 | S93: 1 | T93: -2 | U93: NULL | V93: NULL | W93: -2
A94: 43678 | B94: 43678 | C94: Licitación Caren y Cec (SIC 2013/03-2) BS1A | D94: Energia Licitaciones | E94: Energía | F94: Lic. SIC 2013/03-2 bloques BS1A: Energía ago 2019 | G94: 43719 | H94: 33 | I94: 9996 | J94: s | K94: s | L94: BS1A | M94: Caren | N94: Cec | O94: 41335 | P94: CEC | Q94: 2 | R94: A.MELIP 220 | S94: 3.351295 | T94: 75.737 | U94: NULL | V94: NULL | W94: 254
A95: 43678 | B95: 43739 | C95: Licitación Caren y Cec (SIC 2013/03-2) BS1A | D95: Potencia Licitaciones | E95: Potencia | F95: Lic. SIC 2013/03-2 bloques BS1A: Potencia oct 2019 | G95: 43719 | H95: 33 | I95: 9996 | J95: s | K95: s | L95: BS1A | M95: Caren | N95: Cec | O95: 41335 | P95: CEC | Q95: 2 | R95: A.MELIP 220 | S95: NULL | T95: NULL | U95: 0 | V95: 0 | W95: 0
A96: 43678 | B96: 43678 | C96: Licitación Caren y Cec (SIC 2013/03-2) BS1A | D96: Reliq. Energia Licitaciones | E96: Energía | F96: Lic. SIC 2013/03-2 bloques BS1A: Reliq. Energía ago 2019 | G96: 43915.394 | H96: 61 | I96: NULL | J96: s | K96: s | L96: BS1A | M96: Caren | N96: Cec | O96: 41335 | P96: CEC | Q96: 3 | R96: CHARRUA 220 | S96: 1 | T96: -80 | U96: NULL | V96: NULL | W96: -80
A97: 43678 | B97: 43678 | C97: Licitación Caren y Cec (SIC 2013/03-2) BS1A | D97: Energia Licitaciones | E97: Energía | F97: Lic. SIC 2013/03-2 bloques BS1A: Energía ago 2019 | G97: 43719 | H97: 33 | I97: 9996 | J97: s | K97: s | L97: BS1A | M97: Caren | N97: Cec | O97: 41335 | P97: CEC | Q97: 3 | R97: CHARRUA 220 | S97: 162.1168 | T97: 70.437 | U97: NULL | V97: NULL | W97: 11419
A98: 43678 | B98: 43739 | C98: Licitación Caren y Cec (SIC 2013/03-2) BS1A | D98: Potencia Licitaciones | E98: Potencia | F98: Lic. SIC 2013/03-2 bloques BS1A: Potencia oct 2019 | G98: 43719 | H98: 33 | I98: 9996 | J98: s | K98: s | L98: BS1A | M98: Caren | N98: Cec | O98: 41335 | P98: CEC | Q98: 3 | R98: CHARRUA 220 | S98: NULL | T98: NULL | U98: 0 | V98: 0 | W98: 0
A99: 43678 | B99: 43678 | C99: Licitación Caren y Cec (SIC 2013/03-2) BS1A | D99: Reliq. Energia Licitaciones | E99: Energía | F99: Lic. SIC 2013/03-2 bloques BS1A: Reliq. Energía ago 2019 | G99: 43915.394 | H99: 61 | I99: NULL | J99: s | K99: s | L99: BS1A | M99: Caren | N99: Cec | O99: 41335 | P99: CEC | Q99: 4 | R99: ITAHUE 220 | S99: 1 | T99: -572 | U99: NULL | V99: NULL | W99: -572
A100: 43678 | B100: 43678 | C100: Licitación Caren y Cec (SIC 2013/03-2) BS1A | D100: Energia Licitaciones | E100: Energía | F100: Lic. SIC 2013/03-2 bloques BS1A: Energía ago 2019 | G100: 43719 | H100: 33 | I100: 9996 | J100: s | K100: s | L100: BS1A | M100: Caren | N100: Cec | O100: 41335 | P100: CEC | Q100: 4 | R100: ITAHUE 220 | S100: 1136.7024 | T100: 71.984 | U100: NULL | V100: NULL | W100: 81824
...

Sheet SIGGE_E
A1: Periodo | B1: MesDevengado | C1: Nombre | D1: Concepto | E1: Agrupacion | F1: Glosa | G1: FechaCarga | H1: TipoDocumento | I1: Folio | J1: Vendedor | K1: Comprador | L1: Bloque | M1: Empresa | N1: ClaveEEDD | O1: Licitacion | P1: NomAgrupacion | Q1: Num | R1: Barra | S1: Energia | T1: PrecioEnergia | U1: Potencia | V1: PrecioPotencia | W1: Monto
A2: 43344 | B2: 43344 | C2: Licitación Caren y Cec (SIC 2013/03-2) BS1A | D2: Energia Licitaciones | E2: Energía | F2: Lic. SIC 2013/03-2 bloques BS1A: Energía sep 2018 | G2: 43392 | H2: 33 | I2: 6305 | J2: s | K2: s | L2: BS1A | M2: Caren | N2: Cec | O2: 41335 | P2: CEC | Q2: 1 | R2: TotalBarras | S2: 3000 | T2: 58.085 | U2: NULL | V2: NULL | W2: 174255
A3: 43374 | B3: 43374 | C3: Licitación Caren y Cec (SIC 2013/03-2) BS1A | D3: Energia Licitaciones | E3: Energía | F3: Lic. SIC 2013/03-2 bloques BS1A: Energía oct 2018 | G3: 43431 | H3: 33 | I3: 6796 | J3: s | K3: s | L3: BS1A | M3: Caren | N3: Cec | O3: 41335 | P3: CEC | Q3: 1 | R3: TotalBarras | S3: 3000 | T3: 59.678 | U3: NULL | V3: NULL | W3: 179035
A4: 43405 | B4: 43405 | C4: Licitación Caren y Cec (SIC 2013/03-2) BS1A | D4: Energia Licitaciones | E4: Energía | F4: Lic. SIC 2013/03-2 bloques BS1A: Energía nov 2018 | G4: 43448 | H4: 33 | I4: 6939 | J4: s | K4: s | L4: BS1A | M4: Caren | N4: Cec | O4: 41335 | P4: CEC | Q4: 1 | R4: TotalBarras | S4: 4000 | T4: 59.635 | U4: NULL | V4: NULL | W4: 238540
A5: 43435 | B5: 43435 | C5: Licitación Caren y Cec (SIC 2013/03-2) BS1A | D5: Energia Licitaciones | E5: Energía | F5: Lic. SIC 2013/03-2 bloques BS1A: Energía dic 2018 | G5: 43486 | H5: 33 | I5: 7194 | J5: s | K5: s | L5: BS1A | M5: Caren | N5: Cec | O5: 41335 | P5: CEC | Q5: 1 | R5: TotalBarras | S5: 5000 | T5: 67.951 | U5: NULL | V5: NULL | W5: 339757
A6: 43466 | B6: 43466 | C6: Licitación Caren y Cec (SIC 2013/03-2) BS1A | D6: Reliq. Energia Licitaciones | E6: Energía | F6: Lic. SIC 2013/03-2 bloques BS1A: Reliq. Energía ene 2019 | G6: 43539 | H6: 33 | I6: NULL | J6: s | K6: s | L6: BS1A | M6: Caren | N6: Cec | O6: 41335 | P6: CEC | Q6: 1 | R6: A.JAHUEL 220 | S6: 1.46188 | T6: 66.9 | U6: NULL | V6: NULL | W6: 98
A7: 43466 | B7: 43466 | C7: Licitación Caren y Cec (SIC 2013/03-2) BS1A | D7: Energia Licitaciones | E7: Energía | F7: Lic. SIC 2013/03-2 bloques BS1A: Energía ene 2019 | G7: 43504 | H7: 33 | I7: 7513 | J7: s | K7: s | L7: BS1A | M7: Caren | N7: Cec | O7: 41335 | P7: CEC | Q7: 1 | R7: A.JAHUEL 220 | S7: 1371.306 | T7: 66.9 | U7: NULL | V7: NULL | W7: 91740
A8: 43466 | B8: 43466 | C8: Licitación Caren y Cec (SIC 2013/03-2) BS1A | D8: Reliq. Energia Licitaciones | E8: Energía | F8: Lic. SIC 2013/03-2 bloques BS1A: Reliq. Energía ene 2019 | G8: 43539 | H8: 33 | I8: NULL | J8: s | K8: s | L8: BS1A | M8: Caren | N8: Cec | O8: 41335 | P8: CEC | Q8: 2 | R8: A.MELIP 220 | S8: 0.009388 | T8: 69.014 | U8: NULL | V8: NULL | W8: 1
A9: 43466 | B9: 43466 | C9: Licitación Caren y Cec (SIC 2013/03-2) BS1A | D9: Energia Licitaciones | E9: Energía | F9: Lic. SIC 2013/03-2 bloques BS1A: Energía ene 2019 | G9: 43504 | H9: 33 | I9: 7513 | J9: s | K9: s | L9: BS1A | M9: Caren | N9: Cec | O9: 41335 | P9: CEC | Q9: 2 | R9: A.MELIP 220 | S9: 8.806166 | T9: 69.014 | U9: NULL | V9: NULL | W9: 608
A10: 43466 | B10: 43466 | C10: Licitación Caren y Cec (SIC 2013/03-2) BS1A | D10: Reliq. Energia Licitaciones | E10: Energía | F10: Lic. SIC 2013/03-2 bloques BS1A: Reliq. Energía ene 2019 | G10: 43539 | H10: 33 | I10: NULL | J10: s | K10: s | L10: BS1A | M10: Caren | N10: Cec | O10: 41335 | P10: CEC | Q10: 3 | R10: CHARRUA 220 | S10: 0.453721 | T10: 63.27 | U10: NULL | V10: NULL | W10: 29
A11: 43466 | B11: 43466 | C11: Licitación Caren y Cec (SIC 2013/03-2) BS1A | D11: Energia Licitaciones | E11: Energía | F11: Lic. SIC 2013/03-2 bloques BS1A: Energía ene 2019 | G11: 43504 | H11: 33 | I11: 7513 | J11: s | K11: s | L11: BS1A | M11: Caren | N11: Cec | O11: 41335 | P11: CEC | Q11: 3 | R11: CHARRUA 220 | S11: 425.60961 | T11: 63.27 | U11: NULL | V11: NULL | W11: 26928
A12: 43466 | B12: 43466 | C12: Licitación Caren y Cec (SIC 2013/03-2) BS1A | D12: Reliq. Energia Licitaciones | E12: Energía | F12: Lic. SIC 2013/03-2 bloques BS1A: Reliq. Energía ene 2019 | G12: 43539 | H12: 33 | I12: NULL | J12: s | K12: s | L12: BS1A | M12: Caren | N12: Cec | O12: 41335 | P12: CEC | Q12: 4 | R12: ITAHUE 220 | S12: 2.212452 | T12: 65.349 | U12: NULL | V12: NULL | W12: 145
A13: 43466 | B13: 43466 | C13: Licitación Caren y Cec (SIC 2013/03-2) BS1A | D13: Energia Licitaciones | E13: Energía | F13: Lic. SIC 2013/03-2 bloques BS1A: Energía ene 2019 | G13: 43504 | H13: 33 | I13: 7513 | J13: s | K13: s | L13: BS1A | M13: Caren | N13: Cec | O13: 41335 | P13: CEC | Q13: 4 | R13: ITAHUE 220 | S13: 2075.374 | T13: 65.349 | U13: NULL | V13: NULL | W13: 135624
A14: 43466 | B14: 43466 | C14: Licitación Caren y Cec (SIC 2013/03-2) BS1A | D14: Reliq. Energia Licitaciones | E14: Energía | F14: Lic. SIC 2013/03-2 bloques BS1A: Reliq. Energía ene 2019 | G14: 43539 | H14: 33 | I14: NULL | J14: s | K14: s | L14: BS1A | M14: Caren | N14: Cec | O14: 41335 | P14: CEC | Q14: 5 | R14: RAPEL 220 | S14: 0.008637 | T14: 69.368 | U14: NULL | V14: NULL | W14: 1
A15: 43466 | B15: 43466 | C15: Licitación Caren y Cec (SIC 2013/03-2) BS1A | D15: Energia Licitaciones | E15: Energía | F15: Lic. SIC 2013/03-2 bloques BS1A: Energía ene 2019 | G15: 43504 | H15: 33 | I15: 7513 | J15: s | K15: s | L15: BS1A | M15: Caren | N15: Cec | O15: 41335 | P15: CEC | Q15: 5 | R15: RAPEL 220 | S15: 8.102057 | T15: 69.368 | U15: NULL | V15: NULL | W15: 562
A16: 43497 | B16: 43497 | C16: Licitación Caren y Cec (SIC 2013/03-2) BS1A | D16: Reliq. Energia Licitaciones | E16: Energía | F16: Lic. SIC 2013/03-2 bloques BS1A: Reliq. Energía feb 2019 | G16: 43564 | H16: 61 | I16: NULL | J16: s | K16: s | L16: BS1A | M16: Caren | N16: Cec | O16: 41335 | P16: CEC | Q16: 1 | R16: A.JAHUEL 220 | S16: 0.23349 | T16: 66.9 | U16: NULL | V16: NULL | W16: 16
A17: 43497 | B17: 43497 | C17: Licitación Caren y Cec (SIC 2013/03-2) BS1A | D17: Energia Licitaciones | E17: Energía | F17: Lic. SIC 2013/03-2 bloques BS1A: Energía feb 2019 | G17: 43532 | H17: 33 | I17: 7798 | J17: s | K17: s | L17: BS1A | M17: Caren | N17: Cec | O17: 41335 | P17: CEC | Q17: 1 | R17: A.JAHUEL 220 | S17: 1368.5299 | T17: 66.9 | U17: NULL | V17: NULL | W17: 91555
A18: 43497 | B18: 43497 | C18: Licitación Caren y Cec (SIC 2013/03-2) BS1A | D18: Energia Licitaciones | E18: Energía | F18: Lic. SIC 2013/03-2 bloques BS1A: Energía feb 2019 | G18: 43532 | H18: 33 | I18: 7798 | J18: s | K18: s | L18: BS1A | M18: Caren | N18: Cec | O18: 41335 | P18: CEC | Q18: 2 | R18: A.MELIP 220 | S18: 8.816632 | T18: 69.014 | U18: NULL | V18: NULL | W18: 608
A19: 43497 | B19: 43497 | C19: Licitación Caren y Cec (SIC 2013/03-2) BS1A | D19: Reliq. Energia Licitaciones | E19: Energía | F19: Lic. SIC 2013/03-2 bloques BS1A: Reliq. Energía feb 2019 | G19: 43564 | H19: 61 | I19: NULL | J19: s | K19: s | L19: BS1A | M19: Caren | N19: Cec | O19: 41335 | P19: CEC | Q19: 3 | R19: CHARRUA 220 | S19: 0.072089 | T19: 63.27 | U19: NULL | V19: NULL | W19: 5
A20: 43497 | B20: 43497 | C20: Licitación Caren y Cec (SIC 2013/03-2) BS1A | D20: Energia Licitaciones | E20: Energía | F20: Lic. SIC 2013/03-2 bloques BS1A: Energía feb 2019 | G20: 43532 | H20: 33 | I20: 7798 | J20: s | K20: s | L20: BS1A | M20: Caren | N20: Cec | O20: 41335 | P20: CEC | Q20: 3 | R20: CHARRUA 220 | S20: 422.52678 | T20: 63.27 | U20: NULL | V20: NULL | W20: 26733
A21: 43497 | B21: 43497 | C21: Licitación Caren y Cec (SIC 2013/03-2) BS1A | D21: Reliq. Energia Licitaciones | E21: Energía | F21: Lic. SIC 2013/03-2 bloques BS1A: Reliq. Energía feb 2019 | G21: 43564 | H21: 61 | I21: NULL | J21: s | K21: s | L21: BS1A | M21: Caren | N21: Cec | O21: 41335 | P21: CEC | Q21: 4 | R21: ITAHUE 220 | S21: 0.353269 | T21: 65.349 | U21: NULL | V21: NULL | W21: 23
A22: 43497 | B22: 43497 | C22: Licitación Caren y Cec (SIC 2013/03-2) BS1A | D22: Energia Licitaciones | E22: Energía | F22: Lic. SIC 2013/03-2 bloques BS1A: Energía feb 2019 | G22: 43532 | H22: 33 | I22: 7798 | J22: s | K22: s | L22: BS1A | M22: Caren | N22: Cec | O22: 41335 | P22: CEC | Q22: 4 | R22: ITAHUE 220 | S22: 2070.5801 | T22: 65.349 | U22: NULL | V22: NULL | W22: 135310
A23: 43497 | B23: 43497 | C23: Licitación Caren y Cec (SIC 2013/03-2) BS1A | D23: Energia Licitaciones | E23: Energía | F23: Lic. SIC 2013/03-2 bloques BS1A: Energía feb 2019 | G23: 43532 | H23: 33 | I23: 7798 | J23: s | K23: s | L23: BS1A | M23: Caren | N23: Cec | O23: 41335 | P23: CEC | Q23: 5 | R23: RAPEL 220 | S23: 8.102328 | T23: 69.368 | U23: NULL | V23: NULL | W23: 562
A24: 43525 | B24: 43525 | C24: Licitación Caren y Cec (SIC 2013/03-2) BS1A | D24: Reliq. Energia Licitaciones | E24: Energía | F24: Lic. SIC 2013/03-2 bloques BS1A: Reliq. Energía mar 2019 | G24: 43598 | H24: 33 | I24: NULL | J24: s | K24: s | L24: BS1A | M24: Caren | N24: Cec | O24: 41335 | P24: CEC | Q24: 1 | R24: A.JAHUEL 220 | S24: 0.580609 | T24: 66.9 | U24: NULL | V24: NULL | W24: 39
A25: 43525 | B25: 43525 | C25: Licitación Caren y Cec (SIC 2013/03-2) BS1A | D25: Energia Licitaciones | E25: Energía | F25: Lic. SIC 2013/03-2 bloques BS1A: Energía mar 2019 | G25: 43563 | H25: 33 | I25: 8389 | J25: s | K25: s | L25: BS1A | M25: Caren | N25: Cec | O25: 41335 | P25: CEC | Q25: 1 | R25: A.JAHUEL 220 | S25: 1311.6233 | T25: 66.9 | U25: NULL | V25: NULL | W25: 87748
A26: 43525 | B26: 43525 | C26: Licitación Caren y Cec (SIC 2013/03-2) BS1A | D26: Energia Licitaciones | E26: Energía | F26: Lic. SIC 2013/03-2 bloques BS1A: Energía mar 2019 | G26: 43563 | H26: 33 | I26: 8389 | J26: s | K26: s | L26: BS1A | M26: Caren | N26: Cec | O26: 41335 | P26: CEC | Q26: 2 | R26: A.MELIP 220 | S26: 8.173697 | T26: 69.014 | U26: NULL | V26: NULL | W26: 564
A27: 43525 | B27: 43525 | C27: Licitación Caren y Cec (SIC 2013/03-2) BS1A | D27: Reliq. Energia Licitaciones | E27: Energía | F27: Lic. SIC 2013/03-2 bloques BS1A: Reliq. Energía mar 2019 | G27: 43598 | H27: 33 | I27: NULL | J27: s | K27: s | L27: BS1A | M27: Caren | N27: Cec | O27: 41335 | P27: CEC | Q27: 3 | R27: CHARRUA 220 | S27: 0.178218 | T27: 63.27 | U27: NULL | V27: NULL | W27: 11
A28: 43525 | B28: 43525 | C28: Licitación Caren y Cec (SIC 2013/03-2) BS1A | D28: Energia Licitaciones | E28: Energía | F28: Lic. SIC 2013/03-2 bloques BS1A: Energía mar 2019 | G28: 43563 | H28: 33 | I28: 8389 | J28: s | K28: s | L28: BS1A | M28: Caren | N28: Cec | O28: 41335 | P28: CEC | Q28: 3 | R28: CHARRUA 220 | S28: 402.60399 | T28: 63.27 | U28: NULL | V28: NULL | W28: 25473
A29: 43525 | B29: 43525 | C29: Licitación Caren y Cec (SIC 2013/03-2) BS1A | D29: Reliq. Energia Licitaciones | E29: Energía | F29: Lic. SIC 2013/03-2 bloques BS1A: Reliq. Energía mar 2019 | G29: 43598 | H29: 33 | I29: NULL | J29: s | K29: s | L29: BS1A | M29: Caren | N29: Cec | O29: 41335 | P29: CEC | Q29: 4 | R29: ITAHUE 220 | S29: 0.87116 | T29: 65.349 | U29: NULL | V29: NULL | W29: 57
A30: 43525 | B30: 43525 | C30: Licitación Caren y Cec (SIC 2013/03-2) BS1A | D30: Energia Licitaciones | E30: Energía | F30: Lic. SIC 2013/03-2 bloques BS1A: Energía mar 2019 | G30: 43563 | H30: 33 | I30: 8389 | J30: s | K30: s | L30: BS1A | M30: Caren | N30: Cec | O30: 41335 | P30: CEC | Q30: 4 | R30: ITAHUE 220 | S30: 1967.9945 | T30: 65.349 | U30: NULL | V30: NULL | W30: 128606
A31: 43525 | B31: 43525 | C31: Licitación Caren y Cec (SIC 2013/03-2) BS1A | D31: Energia Licitaciones | E31: Energía | F31: Lic. SIC 2013/03-2 bloques BS1A: Energía mar 2019 | G31: 43563 | H31: 33 | I31: 8389 | J31: s | K31: s | L31: BS1A | M31: Caren | N31: Cec | O31: 41335 | P31: CEC | Q31: 5 | R31: RAPEL 220 | S31: 7.514895 | T31: 69.368 | U31: NULL | V31: NULL | W31: 521
A32: 43556 | B32: 43556 | C32: Licitación Caren y Cec (SIC 2013/03-2) BS1A | D32: Reliq. Energia Licitaciones | E32: Energía | F32: Lic. SIC 2013/03-2 bloques BS1A: Reliq. Energía abr 2019 | G32: 43913.498 | H32: 61 | I32: NULL | J32: s | K32: s | L32: BS1A | M32: Caren | N32: Cec | O32: 41335 | P32: CEC | Q32: 1 | R32: A.JAHUEL 220 | S32: 1 | T32: -1091 | U32: NULL | V32: NULL | W32: -1091
A33: 43556 | B33: 43556 | C33: Licitación Caren y Cec (SIC 2013/03-2) BS1A | D33: Energia Licitaciones | E33: Energía | F33: Lic. SIC 2013/03-2 bloques BS1A: Energía abr 2019 | G33: 43598 | H33: 33 | I33: 8451 | J33: s | K33: s | L33: BS1A | M33: Caren | N33: Cec | O33: 41335 | P33: CEC | Q33: 1 | R33: A.JAHUEL 220 | S33: 897.9651 | T33: 66.9 | U33: NULL | V33: NULL | W33: 60074
A34: 43556 | B34: 43556 | C34: Licitación Caren y Cec (SIC 2013/03-2) BS1A | D34: Reliq. Energia Licitaciones | E34: Energía | F34: Lic. SIC 2013/03-2 bloques BS1A: Reliq. Energía abr 2019 | G34: 43913.498 | H34: 61 | I34: NULL | J34: s | K34: s | L34: BS1A | M34: Caren | N34: Cec | O34: 41335 | P34: CEC | Q34: 2 | R34: A.MELIP 220 | S34: 1 | T34: -8 | U34: NULL | V34: NULL | W34: -8
A35: 43556 | B35: 43556 | C35: Licitación Caren y Cec (SIC 2013/03-2) BS1A | D35: Energia Licitaciones | E35: Energía | F35: Lic. SIC 2013/03-2 bloques BS1A: Energía abr 2019 | G35: 43598 | H35: 33 | I35: 8451 | J35: s | K35: s | L35: BS1A | M35: Caren | N35: Cec | O35: 41335 | P35: CEC | Q35: 2 | R35: A.MELIP 220 | S35: 5.912451 | T35: 69.014 | U35: NULL | V35: NULL | W35: 408
A36: 43556 | B36: 43556 | C36: Licitación Caren y Cec (SIC 2013/03-2) BS1A | D36: Reliq. Energia Licitaciones | E36: Energía | F36: Lic. SIC 2013/03-2 bloques BS1A: Reliq. Energía abr 2019 | G36: 43913.498 | H36: 61 | I36: NULL | J36: s | K36: s | L36: BS1A | M36: Caren | N36: Cec | O36: 41335 | P36: CEC | Q36: 3 | R36: CHARRUA 220 | S36: 1 | T36: -327 | U36: NULL | V36: NULL | W36: -327
A37: 43556 | B37: 43556 | C37: Licitación Caren y Cec (SIC 2013/03-2) BS1A | D37: Energia Licitaciones | E37: Energía | F37: Lic. SIC 2013/03-2 bloques BS1A: Energía abr 2019 | G37: 43598 | H37: 33 | I37: 8451 | J37: s | K37: s | L37: BS1A | M37: Caren | N37: Cec | O37: 41335 | P37: CEC | Q37: 3 | R37: CHARRUA 220 | S37: 278.37089 | T37: 63.27 | U37: NULL | V37: NULL | W37: 17613
A38: 43556 | B38: 43556 | C38: Licitación Caren y Cec (SIC 2013/03-2) BS1A | D38: Reliq. Energia Licitaciones | E38: Energía | F38: Lic. SIC 2013/03-2 bloques BS1A: Reliq. Energía abr 2019 | G38: 43913.498 | H38: 61 | I38: NULL | J38: s | K38: s | L38: BS1A | M38: Caren | N38: Cec | O38: 41335 | P38: CEC | Q38: 4 | R38: ITAHUE 220 | S38: 1 | T38: -1638 | U38: NULL | V38: NULL | W38: -1638
A39: 43556 | B39: 43556 | C39: Licitación Caren y Cec (SIC 2013/03-2) BS1A | D39: Energia Licitaciones | E39: Energía | F39: Lic. SIC 2013/03-2 bloques BS1A: Energía abr 2019 | G39: 43598 | H39: 33 | I39: 8451 | J39: s | K39: s | L39: BS1A | M39: Caren | N39: Cec | O39: 41335 | P39: CEC | Q39: 4 | R39: ITAHUE 220 | S39: 1366.2586 | T39: 65.349 | U39: NULL | V39: NULL | W39: 89284
A40: 43556 | B40: 43556 | C40: Licitación Caren y Cec (SIC 2013/03-2) BS1A | D40: Reliq. Energia Licitaciones | E40: Energía | F40: Lic. SIC 2013/03-2 bloques BS1A: Reliq. Energía abr 2019 | G40: 43913.498 | H40: 61 | I40: NULL | J40: s | K40: s | L40: BS1A | M40: Caren | N40: Cec | O40: 41335 | P40: CEC | Q40: 5 | R40: RAPEL 220 | S40: 1 | T40: -7 | U40: NULL | V40: NULL | W40: -7
A41: 43556 | B41: 43556 | C41: Licitación Caren y Cec (SIC 2013/03-2) BS1A | D41: Energia Licitaciones | E41: Energía | F41: Lic. SIC 2013/03-2 bloques BS1A: Energía abr 2019 | G41: 43598 | H41: 33 | I41: 8451 | J41: s | K41: s | L41: BS1A | M41: Caren | N41: Cec | O41: 41335 | P41: CEC | Q41: 5 | R41: RAPEL 220 | S41: 5.432024 | T41: 69.368 | U41: NULL | V41: NULL | W41: 377
A42: 43586 | B42: 43586 | C42: Licitación Caren y Cec (SIC 2013/03-2) BS1A | D42: Reliq. Energia Licitaciones | E42: Energía | F42: Lic. SIC 2013/03-2 bloques BS1A: Reliq. Energía may 2019 | G42: 43915.631 | H42: 61 | I42: NULL | J42: s | K42: s | L42: BS1A | M42: Caren | N42: Cec | O42: 41335 | P42: CEC | Q42: 1 | R42: A.JAHUEL 220 | S42: 1 | T42: -337 | U42: NULL | V42: NULL | W42: -337
A43: 43586 | B43: 43586 | C43: Licitación Caren y Cec (SIC 2013/03-2) BS1A | D43: Energia Licitaciones | E43: Energía | F43: Lic. SIC 2013/03-2 bloques BS1A: Energía may 2019 | G43: 43627 | H43: 33 | I43: 8768 | J43: s | K43: s | L43: BS1A | M43: Caren | N43: Cec | O43: 41335 | P43: CEC | Q43: 1 | R43: A.JAHUEL 220 | S43: 885.88967 | T43: 74.401 | U43: NULL | V43: NULL | W43: 65911
A44: 43586 | B44: 43586 | C44: Licitación Caren y Cec (SIC 2013/03-2) BS1A | D44: Reliq. Energia Licitaciones | E44: Energía | F44: Lic. SIC 2013/03-2 bloques BS1A: Reliq. Energía may 2019 | G44: 43915.631 | H44: 61 | I44: NULL | J44: s | K44: s | L44: BS1A | M44: Caren | N44: Cec | O44: 41335 | P44: CEC | Q44: 2 | R44: A.MELIP 220 | S44: 1 | T44: -2 | U44: NULL | V44: NULL | W44: -2
A45: 43586 | B45: 43586 | C45: Licitación Caren y Cec (SIC 2013/03-2) BS1A | D45: Energia Licitaciones | E45: Energía | F45: Lic. SIC 2013/03-2 bloques BS1A: Energía may 2019 | G45: 43627 | H45: 33 | I45: 8768 | J45: s | K45: s | L45: BS1A | M45: Caren | N45: Cec | O45: 41335 | P45: CEC | Q45: 2 | R45: A.MELIP 220 | S45: 5.728447 | T45: 75.737 | U45: NULL | V45: NULL | W45: 434
A46: 43586 | B46: 43586 | C46: Licitación Caren y Cec (SIC 2013/03-2) BS1A | D46: Reliq. Energia Licitaciones | E46: Energía | F46: Lic. SIC 2013/03-2 bloques BS1A: Reliq. Energía may 2019 | G46: 43915.631 | H46: 61 | I46: NULL | J46: s | K46: s | L46: BS1A | M46: Caren | N46: Cec | O46: 41335 | P46: CEC | Q46: 3 | R46: CHARRUA 220 | S46: 1 | T46: -99 | U46: NULL | V46: NULL | W46: -99
A47: 43586 | B47: 43586 | C47: Licitación Caren y Cec (SIC 2013/03-2) BS1A | D47: Energia Licitaciones | E47: Energía | F47: Lic. SIC 2013/03-2 bloques BS1A: Energía may 2019 | G47: 43627 | H47: 33 | I47: 8768 | J47: s | K47: s | L47: BS1A | M47: Caren | N47: Cec | O47: 41335 | P47: CEC | Q47: 3 | R47: CHARRUA 220 | S47: 273.81804 | T47: 70.437 | U47: NULL | V47: NULL | W47: 19287
A48: 43586 | B48: 43586 | C48: Licitación Caren y Cec (SIC 2013/03-2) BS1A | D48: Reliq. Energia Licitaciones | E48: Energía | F48: Lic. SIC 2013/03-2 bloques BS1A: Reliq. Energía may 2019 | G48: 43915.631 | H48: 61 | I48: NULL | J48: s | K48: s | L48: BS1A | M48: Caren | N48: Cec | O48: 41335 | P48: CEC | Q48: 4 | R48: ITAHUE 220 | S48: 1 | T48: -494 | U48: NULL | V48: NULL | W48: -494
A49: 43586 | B49: 43586 | C49: Licitación Caren y Cec (SIC 2013/03-2) BS1A | D49: Energia Licitaciones | E49: Energía | F49: Lic. SIC 2013/03-2 bloques BS1A: Energía may 2019 | G49: 43627 | H49: 33 | I49: 8768 | J49: s | K49: s | L49: BS1A | M49: Caren | N49: Cec | O49: 41335 | P49: CEC | Q49: 4 | R49: ITAHUE 220 | S49: 1341.7257 | T49: 71.984 | U49: NULL | V49: NULL | W49: 96583
A50: 43586 | B50: 43586 | C50: Licitación Caren y Cec (SIC 2013/03-2) BS1A | D50: Reliq. Energia Licitaciones | E50: Energía | F50: Lic. SIC 2013/03-2 bloques BS1A: Reliq. Energía may 2019 | G50: 43915.631 | H50: 61 | I50: NULL | J50: s | K50: s | L50: BS1A | M50: Caren | N50: Cec | O50: 41335 | P50: CEC | Q50: 5 | R50: RAPEL 220 | S50: 1 | T50: -2 | U50: NULL | V50: NULL | W50: -2
A51: 43586 | B51: 43586 | C51: Licitación Caren y Cec (SIC 2013/03-2) BS1A | D51: Energia Licitaciones | E51: Energía | F51: Lic. SIC 2013/03-2 bloques BS1A: Energía may 2019 | G51: 43627 | H51: 33 | I51: 8768 | J51: s | K51: s | L51: BS1A | M51: Caren | N51: Cec | O51: 41335 | P51: CEC | Q51: 5 | R51: RAPEL 220 | S51: 5.26453 | T51: 75.617 | U51: NULL | V51: NULL | W51: 398
A52: 43617 | B52: 43617 | C52: Licitación Caren y Cec (SIC 2013/03-2) BS1A | D52: Reliq. Energia Licitaciones | E52: Energía | F52: Lic. SIC 2013/03-2 bloques BS1A: Reliq. Energía jun 2019 | G52: 43693 | H52: 33 | I52: NULL | J52: s | K52: s | L52: BS1A | M52: Caren | N52: Cec | O52: 41335 | P52: CEC | Q52: 1 | R52: A.JAHUEL 220 | S52: 1.775945 | T52: 74.401 | U52: NULL | V52: NULL | W52: 132
A53: 43617 | B53: 43617 | C53: Licitación Caren y Cec (SIC 2013/03-2) BS1A | D53: Energia Licitaciones | E53: Energía | F53: Lic. SIC 2013/03-2 bloques BS1A: Energía jun 2019 | G53: 43655 | H53: 33 | I53: 9022 | J53: s | K53: s | L53: BS1A | M53: Caren | N53: Cec | O53: 41335 | P53: CEC | Q53: 1 | R53: A.JAHUEL 220 | S53: 790.40863 | T53: 74.401 | U53: NULL | V53: NULL | W53: 58807
A54: 43617 | B54: 43617 | C54: Licitación Caren y Cec (SIC 2013/03-2) BS1A | D54: Reliq. Energia Licitaciones | E54: Energía | F54: Lic. SIC 2013/03-2 bloques BS1A: Reliq. Energía jun 2019 | G54: 43693 | H54: 33 | I54: NULL | J54: s | K54: s | L54: BS1A | M54: Caren | N54: Cec | O54: 41335 | P54: CEC | Q54: 2 | R54: A.MELIP 220 | S54: 0.011666 | T54: 75.737 | U54: NULL | V54: NULL | W54: 1
A55: 43617 | B55: 43617 | C55: Licitación Caren y Cec (SIC 2013/03-2) BS1A | D55: Energia Licitaciones | E55: Energía | F55: Lic. SIC 2013/03-2 bloques BS1A: Energía jun 2019 | G55: 43655 | H55: 33 | I55: 9022 | J55: s | K55: s | L55: BS1A | M55: Caren | N55: Cec | O55: 41335 | P55: CEC | Q55: 2 | R55: A.MELIP 220 | S55: 5.19207 | T55: 75.737 | U55: NULL | V55: NULL | W55: 393
A56: 43617 | B56: 43617 | C56: Licitación Caren y Cec (SIC 2013/03-2) BS1A | D56: Reliq. Energia Licitaciones | E56: Energía | F56: Lic. SIC 2013/03-2 bloques BS1A: Reliq. Energía jun 2019 | G56: 43693 | H56: 33 | I56: NULL | J56: s | K56: s | L56: BS1A | M56: Caren | N56: Cec | O56: 41335 | P56: CEC | Q56: 3 | R56: CHARRUA 220 | S56: 0.551932 | T56: 70.437 | U56: NULL | V56: NULL | W56: 39
A57: 43617 | B57: 43617 | C57: Licitación Caren y Cec (SIC 2013/03-2) BS1A | D57: Energia Licitaciones | E57: Energía | F57: Lic. SIC 2013/03-2 bloques BS1A: Energía jun 2019 | G57: 43655 | H57: 33 | I57: 9022 | J57: s | K57: s | L57: BS1A | M57: Caren | N57: Cec | O57: 41335 | P57: CEC | Q57: 3 | R57: CHARRUA 220 | S57: 245.64498 | T57: 70.437 | U57: NULL | V57: NULL | W57: 17302
A58: 43617 | B58: 43617 | C58: Licitación Caren y Cec (SIC 2013/03-2) BS1A | D58: Reliq. Energia Licitaciones | E58: Energía | F58: Lic. SIC 2013/03-2 bloques BS1A: Reliq. Energía jun 2019 | G58: 43693 | H58: 33 | I58: NULL | J58: s | K58: s | L58: BS1A | M58: Caren | N58: Cec | O58: 41335 | P58: CEC | Q58: 4 | R58: ITAHUE 220 | S58: 2.701975 | T58: 71.984 | U58: NULL | V58: NULL | W58: 194
A59: 43617 | B59: 43617 | C59: Licitación Caren y Cec (SIC 2013/03-2) BS1A | D59: Energia Licitaciones | E59: Energía | F59: Lic. SIC 2013/03-2 bloques BS1A: Energía jun 2019 | G59: 43655 | H59: 33 | I59: 9022 | J59: s | K59: s | L59: BS1A | M59: Caren | N59: Cec | O59: 41335 | P59: CEC | Q59: 4 | R59: ITAHUE 220 | S59: 1202.5506 | T59: 71.984 | U59: NULL | V59: NULL | W59: 86564
A60: 43617 | B60: 43617 | C60: Licitación Caren y Cec (SIC 2013/03-2) BS1A | D60: Reliq. Energia Licitaciones | E60: Energía | F60: Lic. SIC 2013/03-2 bloques BS1A: Reliq. Energía jun 2019 | G60: 43693 | H60: 33 | I60: NULL | J60: s | K60: s | L60: BS1A | M60: Caren | N60: Cec | O60: 41335 | P60: CEC | Q60: 5 | R60: RAPEL 220 | S60: 0.010724 | T60: 75.617 | U60: NULL | V60: NULL | W60: 1
A61: 43617 | B61: 43617 | C61: Licitación Caren y Cec (SIC 2013/03-2) BS1A | D61: Energia Licitaciones | E61: Energía | F61: Lic. SIC 2013/03-2 bloques BS1A: Energía jun 2019 | G61: 43655 | H61: 33 | I61: 9022 | J61: s | K61: s | L61: BS1A | M61: Caren | N61: Cec | O61: 41335 | P61: CEC | Q61: 5 | R61: RAPEL 220 | S61: 4.772954 | T61: 75.617 | U61: NULL | V61: NULL | W61: 361
A62: 43647 | B62: 43647 | C62: Licitación Caren y Cec (SIC 2013/03-2) BS1A | D62: Reliq. Energia Licitaciones | E62: Energía | F62: Lic. SIC 2013/03-2 bloques BS1A: Reliq. Energía jul 2019 | G62: 43914.908 | H62: 61 | I62: NULL | J62: s | K62: s | L62: BS1A | M62: Caren | N62: Cec | O62: 41335 | P62: CEC | Q62: 1 | R62: A.JAHUEL 220 | S62: 1 | T62: -19 | U62: NULL | V62: NULL | W62: -19
A63: 43647 | B63: 43647 | C63: Licitación Caren y Cec (SIC 2013/03-2) BS1A | D63: Energia Licitaciones | E63: Energía | F63: Lic. SIC 2013/03-2 bloques BS1A: Energía jul 2019 | G63: 43686 | H63: 33 | I63: 9466 | J63: s | K63: s | L63: BS1A | M63: Caren | N63: Cec | O63: 41335 | P63: CEC | Q63: 1 | R63: A.JAHUEL 220 | S63: 842.75503 | T63: 74.401 | U63: NULL | V63: NULL | W63: 62702
A64: 43647 | B64: 43647 | C64: Licitación Caren y Cec (SIC 2013/03-2) BS1A | D64: Energia Licitaciones | E64: Energía | F64: Lic. SIC 2013/03-2 bloques BS1A: Energía jul 2019 | G64: 43686 | H64: 33 | I64: 9466 | J64: s | K64: s | L64: BS1A | M64: Caren | N64: Cec | O64: 41335 | P64: CEC | Q64: 2 | R64: A.MELIP 220 | S64: 3.672508 | T64: 75.737 | U64: NULL | V64: NULL | W64: 278
A65: 43647 | B65: 43647 | C65: Licitación Caren y Cec (SIC 2013/03-2) BS1A | D65: Reliq. Energia Licitaciones | E65: Energía | F65: Lic. SIC 2013/03-2 bloques BS1A: Reliq. Energía jul 2019 | G65: 43914.908 | H65: 61 | I65: NULL | J65: s | K65: s | L65: BS1A | M65: Caren | N65: Cec | O65: 41335 | P65: CEC | Q65: 3 | R65: CHARRUA 220 | S65: 1 | T65: -3 | U65: NULL | V65: NULL | W65: -3
A66: 43647 | B66: 43647 | C66: Licitación Caren y Cec (SIC 2013/03-2) BS1A | D66: Energia Licitaciones | E66: Energía | F66: Lic. SIC 2013/03-2 bloques BS1A: Energía jul 2019 | G66: 43686 | H66: 33 | I66: 9466 | J66: s | K66: s | L66: BS1A | M66: Caren | N66: Cec | O66: 41335 | P66: CEC | Q66: 3 | R66: CHARRUA 220 | S66: 171.56035 | T66: 70.437 | U66: NULL | V66: NULL | W66: 12084
A67: 43647 | B67: 43647 | C67: Licitación Caren y Cec (SIC 2013/03-2) BS1A | D67: Reliq. Energia Licitaciones | E67: Energía | F67: Lic. SIC 2013/03-2 bloques BS1A: Reliq. Energía jul 2019 | G67: 43914.908 | H67: 61 | I67: NULL | J67: s | K67: s | L67: BS1A | M67: Caren | N67: Cec | O67: 41335 | P67: CEC | Q67: 4 | R67: ITAHUE 220 | S67: 1 | T67: -25 | U67: NULL | V67: NULL | W67: -25
A68: 43647 | B68: 43647 | C68: Licitación Caren y Cec (SIC 2013/03-2) BS1A | D68: Energia Licitaciones | E68: Energía | F68: Lic. SIC 2013/03-2 bloques BS1A: Energía jul 2019 | G68: 43686 | H68: 33 | I68: 9466 | J68: s | K68: s | L68: BS1A | M68: Caren | N68: Cec | O68: 41335 | P68: CEC | Q68: 4 | R68: ITAHUE 220 | S68: 1210.3737 | T68: 71.984 | U68: NULL | V68: NULL | W68: 87128
A69: 43647 | B69: 43647 | C69: Licitación Caren y Cec (SIC 2013/03-2) BS1A | D69: Energia Licitaciones | E69: Energía | F69: Lic. SIC 2013/03-2 bloques BS1A: Energía jul 2019 | G69: 43686 | H69: 33 | I69: 9466 | J69: s | K69: s | L69: BS1A | M69: Caren | N69: Cec | O69: 41335 | P69: CEC | Q69: 5 | R69: RAPEL 220 | S69: 3.777267 | T69: 75.617 | U69: NULL | V69: NULL | W69: 286
A70: 43678 | B70: 43678 | C70: Licitación Caren y Cec (SIC 2013/03-2) BS1A | D70: Reliq. Energia Licitaciones | E70: Energía | F70: Lic. SIC 2013/03-2 bloques BS1A: Reliq. Energía ago 2019 | G70: 43915.394 | H70: 61 | I70: NULL | J70: s | K70: s | L70: BS1A | M70: Caren | N70: Cec | O70: 41335 | P70: CEC | Q70: 1 | R70: A.JAHUEL 220 | S70: 1 | T70: -415 | U70: NULL | V70: NULL | W70: -415
A71: 43678 | B71: 43678 | C71: Licitación Caren y Cec (SIC 2013/03-2) BS1A | D71: Energia Licitaciones | E71: Energía | F71: Lic. SIC 2013/03-2 bloques BS1A: Energía ago 2019 | G71: 43719 | H71: 33 | I71: 9996 | J71: s | K71: s | L71: BS1A | M71: Caren | N71: Cec | O71: 41335 | P71: CEC | Q71: 1 | R71: A.JAHUEL 220 | S71: 797.16754 | T71: 74.401 | U71: NULL | V71: NULL | W71: 59310
A72: 43678 | B72: 43678 | C72: Licitación Caren y Cec (SIC 2013/03-2) BS1A | D72: Reliq. Energia Licitaciones | E72: Energía | F72: Lic. SIC 2013/03-2 bloques BS1A: Reliq. Energía ago 2019 | G72: 43915.394 | H72: 61 | I72: NULL | J72: s | K72: s | L72: BS1A | M72: Caren | N72: Cec | O72: 41335 | P72: CEC | Q72: 2 | R72: A.MELIP 220 | S72: 1 | T72: -2 | U72: NULL | V72: NULL | W72: -2
A73: 43678 | B73: 43678 | C73: Licitación Caren y Cec (SIC 2013/03-2) BS1A | D73: Energia Licitaciones | E73: Energía | F73: Lic. SIC 2013/03-2 bloques BS1A: Energía ago 2019 | G73: 43719 | H73: 33 | I73: 9996 | J73: s | K73: s | L73: BS1A | M73: Caren | N73: Cec | O73: 41335 | P73: CEC | Q73: 2 | R73: A.MELIP 220 | S73: 3.351295 | T73: 75.737 | U73: NULL | V73: NULL | W73: 254
A74: 43678 | B74: 43678 | C74: Licitación Caren y Cec (SIC 2013/03-2) BS1A | D74: Reliq. Energia Licitaciones | E74: Energía | F74: Lic. SIC 2013/03-2 bloques BS1A: Reliq. Energía ago 2019 | G74: 43915.394 | H74: 61 | I74: NULL | J74: s | K74: s | L74: BS1A | M74: Caren | N74: Cec | O74: 41335 | P74: CEC | Q74: 3 | R74: CHARRUA 220 | S74: 1 | T74: -80 | U74: NULL | V74: NULL | W74: -80
A75: 43678 | B75: 43678 | C75: Licitación Caren y Cec (SIC 2013/03-2) BS1A | D75: Energia Licitaciones | E75: Energía | F75: Lic. SIC 2013/03-2 bloques BS1A: Energía ago 2019 | G75: 43719 | H75: 33 | I75: 9996 | J75: s | K75: s | L75: BS1A | M75: Caren | N75: Cec | O75: 41335 | P75: CEC | Q75: 3 | R75: CHARRUA 220 | S75: 162.1168 | T75: 70.437 | U75: NULL | V75: NULL | W75: 11419
A76: 43678 | B76: 43678 | C76: Licitación Caren y Cec (SIC 2013/03-2) BS1A | D76: Reliq. Energia Licitaciones | E76: Energía | F76: Lic. SIC 2013/03-2 bloques BS1A: Reliq. Energía ago 2019 | G76: 43915.394 | H76: 61 | I76: NULL | J76: s | K76: s | L76: BS1A | M76: Caren | N76: Cec | O76: 41335 | P76: CEC | Q76: 4 | R76: ITAHUE 220 | S76: 1 | T76: -572 | U76: NULL | V76: NULL | W76: -572
A77: 43678 | B77: 43678 | C77: Licitación Caren y Cec (SIC 2013/03-2) BS1A | D77: Energia Licitaciones | E77: Energía | F77: Lic. SIC 2013/03-2 bloques BS1A: Energía ago 2019 | G77: 43719 | H77: 33 | I77: 9996 | J77: s | K77: s | L77: BS1A | M77: Caren | N77: Cec | O77: 41335 | P77: CEC | Q77: 4 | R77: ITAHUE 220 | S77: 1136.7024 | T77: 71.984 | U77: NULL | V77: NULL | W77: 81824
A78: 43678 | B78: 43678 | C78: Licitación Caren y Cec (SIC 2013/03-2) BS1A | D78: Reliq. Energia Licitaciones | E78: Energía | F78: Lic. SIC 2013/03-2 bloques BS1A: Reliq. Energía ago 2019 | G78: 43915.394 | H78: 61 | I78: NULL | J78: s | K78: s | L78: BS1A | M78: Caren | N78: Cec | O78: 41335 | P78: CEC | Q78: 5 | R78: RAPEL 220 | S78: 1 | T78: -2 | U78: NULL | V78: NULL | W78: -2
A79: 43678 | B79: 43678 | C79: Licitación Caren y Cec (SIC 2013/03-2) BS1A | D79: Energia Licitaciones | E79: Energía | F79: Lic. SIC 2013/03-2 bloques BS1A: Energía ago 2019 | G79: 43719 | H79: 33 | I79: 9996 | J79: s | K79: s | L79: BS1A | M79: Caren | N79: Cec | O79: 41335 | P79: CEC | Q79: 5 | R79: RAPEL 220 | S79: 3.471597 | T79: 75.617 | U79: NULL | V79: NULL | W79: 263
A80: 43709 | B80: 43709 | C80: Licitación Caren y Cec (SIC 2013/03-2) BS1A | D80: Energia Licitaciones | E80: Energía | F80: Lic. SIC 2013/03-2 bloques BS1A: Energía sep 2019 | G80: 43748 | H80: 33 | I80: 10390 | J80: s | K80: s | L80: BS1A | M80: Caren | N80: Cec | O80: 41335 | P80: CEC | Q80: 1 | R80: A.JAHUEL 220 | S80: 755.96652 | T80: 77.384 | U80: NULL | V80: NULL | W80: 58500
A81: 43709 | B81: 43709 | C81: Licitación Caren y Cec (SIC 2013/03-2) BS1A | D81: Energia Licitaciones | E81: Energía | F81: Lic. SIC 2013/03-2 bloques BS1A: Energía sep 2019 | G81: 43748 | H81: 33 | I81: 10390 | J81: s | K81: s | L81: BS1A | M81: Caren | N81: Cec | O81: 41335 | P81: CEC | Q81: 2 | R81: A.MELIP 220 | S81: 3.24005 | T81: 79.429 | U81: NULL | V81: NULL | W81: 257
A82: 43709 | B82: 43709 | C82: Licitación Caren y Cec (SIC 2013/03-2) BS1A | D82: Energia Licitaciones | E82: Energía | F82: Lic. SIC 2013/03-2 bloques BS1A: Energía sep 2019 | G82: 43748 | H82: 33 | I82: 10390 | J82: s | K82: s | L82: BS1A | M82: Caren | N82: Cec | O82: 41335 | P82: CEC | Q82: 3 | R82: CHARRUA 220 | S82: 154.71328 | T82: 72.4 | U82: NULL | V82: NULL | W82: 11201
A83: 43709 | B83: 43709 | C83: Licitación Caren y Cec (SIC 2013/03-2) BS1A | D83: Energia Licitaciones | E83: Energía | F83: Lic. SIC 2013/03-2 bloques BS1A: Energía sep 2019 | G83: 43748 | H83: 33 | I83: 10390 | J83: s | K83: s | L83: BS1A | M83: Caren | N83: Cec | O83: 41335 | P83: CEC | Q83: 4 | R83: ITAHUE 220 | S83: 1084.1758 | T83: 74.936 | U83: NULL | V83: NULL | W83: 81244
A84: 43709 | B84: 43709 | C84: Licitación Caren y Cec (SIC 2013/03-2) BS1A | D84: Energia Licitaciones | E84: Energía | F84: Lic. SIC 2013/03-2 bloques BS1A: Energía sep 2019 | G84: 43748 | H84: 33 | I84: 10390 | J84: s | K84: s | L84: BS1A | M84: Caren | N84: Cec | O84: 41335 | P84: CEC | Q84: 5 | R84: RAPEL 220 | S84: 3.358734 | T84: 75.665 | U84: NULL | V84: NULL | W84: 254
A85: 43739 | B85: 43709 | C85: Licitación Caren y Cec (SIC 2013/03-2) BS1A | D85: Reliq. por PNP Energia Licitaciones | E85: Energía | F85: Lic. SIC 2013/03-2 bloques BS1A: Energía 2019-9 facturada | G85: 43944.473 | H85: 61 | I85: NULL | J85: s | K85: s | L85: BS1A | M85: Caren | N85: Cec | O85: 41335 | P85: CEC | Q85: 1 | R85: A.JAHUEL 220 | S85: -755.96652 | T85: 77.384 | U85: NULL | V85: NULL | W85: -58500
A86: 43739 | B86: 43709 | C86: Licitación Caren y Cec (SIC 2013/03-2) BS1A | D86: Reliq. por PNP Energia Licitaciones | E86: Energía | F86: Lic. SIC 2013/03-2 bloques BS1A: Energía 2019-9 PEC 7T-2019 | G86: 43944.473 | H86: 61 | I86: NULL | J86: s | K86: s | L86: BS1A | M86: Caren | N86: Cec | O86: 41335 | P86: CEC | Q86: 1 | R86: A.JAHUEL 220 | S86: 764.87857 | T86: 74.401 | U86: NULL | V86: NULL | W86: 56908
A87: 43739 | B87: 43739 | C87: Licitación Caren y Cec (SIC 2013/03-2) BS1A | D87: Reliq. Energia Licitaciones | E87: Energía | F87: Reliq. Lic. SIC 2013/03-2 bloques BS1A: Energía oct 2019 | G87: 43812 | H87: 61 | I87: NULL | J87: s | K87: s | L87: BS1A | M87: Caren | N87: Cec | O87: 41335 | P87: CEC | Q87: 1 | R87: A.JAHUEL 220 | S87: 1 | T87: -194 | U87: NULL | V87: NULL | W87: -194
A88: 43739 | B88: 43739 | C88: Licitación Caren y Cec (SIC 2013/03-2) BS1A | D88: Energia Licitaciones | E88: Energía | F88: Lic. SIC 2013/03-2 bloques BS1A: Energía oct 2019 | G88: 43781 | H88: 33 | I88: 10809 | J88: s | K88: s | L88: BS1A | M88: Caren | N88: Cec | O88: 41335 | P88: CEC | Q88: 1 | R88: A.JAHUEL 220 | S88: 910.42412 | T88: 74.401 | U88: NULL | V88: NULL | W88: 67736
A89: 43739 | B89: 43709 | C89: Licitación Caren y Cec (SIC 2013/03-2) BS1A | D89: Reliq. por PNP Energia Licitaciones | E89: Energía | F89: Lic. SIC 2013/03-2 bloques BS1A: Energía 2019-9 facturada | G89: 43944.473 | H89: 61 | I89: NULL | J89: s | K89: s | L89: BS1A | M89: Caren | N89: Cec | O89: 41335 | P89: CEC | Q89: 2 | R89: A.MELIP 220 | S89: -3.24005 | T89: 79.429 | U89: NULL | V89: NULL | W89: -257
A90: 43739 | B90: 43709 | C90: Licitación Caren y Cec (SIC 2013/03-2) BS1A | D90: Reliq. por PNP Energia Licitaciones | E90: Energía | F90: Lic. SIC 2013/03-2 bloques BS1A: Energía 2019-9 PEC 7T-2019 | G90: 43944.473 | H90: 61 | I90: NULL | J90: s | K90: s | L90: BS1A | M90: Caren | N90: Cec | O90: 41335 | P90: CEC | Q90: 2 | R90: A.MELIP 220 | S90: 3.278247 | T90: 75.737 | U90: NULL | V90: NULL | W90: 248
A91: 43739 | B91: 43739 | C91: Licitación Caren y Cec (SIC 2013/03-2) BS1A | D91: Reliq. Energia Licitaciones | E91: Energía | F91: Reliq. Lic. SIC 2013/03-2 bloques BS1A: Energía oct 2019 | G91: 43812 | H91: 61 | I91: NULL | J91: s | K91: s | L91: BS1A | M91: Caren | N91: Cec | O91: 41335 | P91: CEC | Q91: 2 | R91: A.MELIP 220 | S91: 1 | T91: -1 | U91: NULL | V91: NULL | W91: -1
A92: 43739 | B92: 43739 | C92: Licitación Caren y Cec (SIC 2013/03-2) BS1A | D92: Energia Licitaciones | E92: Energía | F92: Lic. SIC 2013/03-2 bloques BS1A: Energía oct 2019 | G92: 43781 | H92: 33 | I92: 10809 | J92: s | K92: s | L92: BS1A | M92: Caren | N92: Cec | O92: 41335 | P92: CEC | Q92: 2 | R92: A.MELIP 220 | S92: 3.92416 | T92: 75.737 | U92: NULL | V92: NULL | W92: 297
A93: 43739 | B93: 43709 | C93: Licitación Caren y Cec (SIC 2013/03-2) BS1A | D93: Reliq. por PNP Energia Licitaciones | E93: Energía | F93: Lic. SIC 2013/03-2 bloques BS1A: Energía 2019-9 facturada | G93: 43944.473 | H93: 61 | I93: NULL | J93: s | K93: s | L93: BS1A | M93: Caren | N93: Cec | O93: 41335 | P93: CEC | Q93: 3 | R93: CHARRUA 220 | S93: -154.71328 | T93: 72.4 | U93: NULL | V93: NULL | W93: -11201
A94: 43739 | B94: 43709 | C94: Licitación Caren y Cec (SIC 2013/03-2) BS1A | D94: Reliq. por PNP Energia Licitaciones | E94: Energía | F94: Lic. SIC 2013/03-2 bloques BS1A: Energía 2019-9 PEC 7T-2019 | G94: 43944.473 | H94: 61 | I94: NULL | J94: s | K94: s | L94: BS1A | M94: Caren | N94: Cec | O94: 41335 | P94: CEC | Q94: 3 | R94: CHARRUA 220 | S94: 156.53718 | T94: 70.437 | U94: NULL | V94: NULL | W94: 11026
A95: 43739 | B95: 43739 | C95: Licitación Caren y Cec (SIC 2013/03-2) BS1A | D95: Reliq. Energia Licitaciones | E95: Energía | F95: Reliq. Lic. SIC 2013/03-2 bloques BS1A: Energía oct 2019 | G95: 43812 | H95: 61 | I95: NULL | J95: s | K95: s | L95: BS1A | M95: Caren | N95: Cec | O95: 41335 | P95: CEC | Q95: 3 | R95: CHARRUA 220 | S95: 1 | T95: -38 | U95: NULL | V95: NULL | W95: -38
A96: 43739 | B96: 43739 | C96: Licitación Caren y Cec (SIC 2013/03-2) BS1A | D96: Energia Licitaciones | E96: Energía | F96: Lic. SIC 2013/03-2 bloques BS1A: Energía oct 2019 | G96: 43781 | H96: 33 | I96: 10809 | J96: s | K96: s | L96: BS1A | M96: Caren | N96: Cec | O96: 41335 | P96: CEC | Q96: 3 | R96: CHARRUA 220 | S96: 188.28671 | T96: 70.437 | U96: NULL | V96: NULL | W96: 13262
A97: 43739 | B97: 43709 | C97: Licitación Caren y Cec (SIC 2013/03-2) BS1A | D97: Reliq. por PNP Energia Licitaciones | E97: Energía | F97: Lic. SIC 2013/03-2 bloques BS1A: Energía 2019-9 facturada | G97: 43944.473 | H97: 61 | I97: NULL | J97: s | K97: s | L97: BS1A | M97: Caren | N97: Cec | O97: 41335 | P97: CEC | Q97: 4 | R97: ITAHUE 220 | S97: -1084.1758 | T97: 74.936 | U97: NULL | V97: NULL | W97: -81244
A98: 43739 | B98: 43709 | C98: Licitación Caren y Cec (SIC 2013/03-2) BS1A | D98: Reliq. por PNP Energia Licitaciones | E98: Energía | F98: Lic. SIC 2013/03-2 bloques BS1A: Energía 2019-9 PEC 7T-2019 | G98: 43944.473 | H98: 61 | I98: NULL | J98: s | K98: s | L98: BS1A | M98: Caren | N98: Cec | O98: 41335 | P98: CEC | Q98: 4 | R98: ITAHUE 220 | S98: 1096.9571 | T98: 71.984 | U98: NULL | V98: NULL | W98: 78963
A99: 43739 | B99: 43739 | C99: Licitación Caren y Cec (SIC 2013/03-2) BS1A | D99: Reliq. Energia Licitaciones | E99: Energía | F99: Reliq. Lic. SIC 2013/03-2 bloques BS1A: Energía oct 2019 | G99: 43812 | H99: 61 | I99: NULL | J99: s | K99: s | L99: BS1A | M99: Caren | N99: Cec | O99: 41335 | P99: CEC | Q99: 4 | R99: ITAHUE 220 | S99: 1 | T99: -270 | U99: NULL | V99: NULL | W99: -270
A100: 43739 | B100: 43739 | C100: Licitación Caren y Cec (SIC 2013/03-2) BS1A | D100: Energia Licitaciones | E100: Energía | F100: Lic. SIC 2013/03-2 bloques BS1A: Energía oct 2019 | G100: 43781 | H100: 33 | I100: 10809 | J100: s | K100: s | L100: BS1A | M100: Caren | N100: Cec | O100: 41335 | P100: CEC | Q100: 4 | R100: ITAHUE 220 | S100: 1311.6713 | T100: 71.984 | U100: NULL | V100: NULL | W100: 94419
...

Sheet SIGGE_P
A1: Periodo | B1: MesDevengado | C1: Nombre | D1: Concepto | E1: Agrupacion | F1: Glosa | G1: FechaCarga | H1: TipoDocumento | I1: Folio | J1: Vendedor | K1: Comprador | L1: Bloque | M1: Empresa | N1: ClaveEEDD | O1: Licitacion | P1: NomAgrupacion | Q1: Num | R1: Barra | S1: Energia | T1: PrecioEnergia | U1: Potencia | V1: PrecioPotencia | W1: Monto
A2: 43556 | B2: 43556 | C2: Licitación Caren y Cec (SIC 2013/03-2) BS1A | D2: Potencia Licitaciones | E2: Potencia | F2: Lic. SIC 2013/03-2 bloques BS1A: Potencia abr 2019 | G2: 43598 | H2: 33 | I2: 8451 | J2: s | K2: s | L2: BS1A | M2: Caren | N2: Cec | O2: 41335 | P2: CEC | Q2: 1 | R2: A.JAHUEL 220 | S2: NULL | T2: NULL | U2: 0 | V2: 0 | W2: 0
A3: 43556 | B3: 43556 | C3: Licitación Caren y Cec (SIC 2013/03-2) BS1A | D3: Potencia Licitaciones | E3: Potencia | F3: Lic. SIC 2013/03-2 bloques BS1A: Potencia abr 2019 | G3: 43598 | H3: 33 | I3: 8451 | J3: s | K3: s | L3: BS1A | M3: Caren | N3: Cec | O3: 41335 | P3: CEC | Q3: 2 | R3: A.MELIP 220 | S3: NULL | T3: NULL | U3: 0 | V3: 0 | W3: 0
A4: 43556 | B4: 43556 | C4: Licitación Caren y Cec (SIC 2013/03-2) BS1A | D4: Potencia Licitaciones | E4: Potencia | F4: Lic. SIC 2013/03-2 bloques BS1A: Potencia abr 2019 | G4: 43598 | H4: 33 | I4: 8451 | J4: s | K4: s | L4: BS1A | M4: Caren | N4: Cec | O4: 41335 | P4: CEC | Q4: 3 | R4: CHARRUA 220 | S4: NULL | T4: NULL | U4: 0 | V4: 0 | W4: 0
A5: 43556 | B5: 43556 | C5: Licitación Caren y Cec (SIC 2013/03-2) BS1A | D5: Potencia Licitaciones | E5: Potencia | F5: Lic. SIC 2013/03-2 bloques BS1A: Potencia abr 2019 | G5: 43598 | H5: 33 | I5: 8451 | J5: s | K5: s | L5: BS1A | M5: Caren | N5: Cec | O5: 41335 | P5: CEC | Q5: 4 | R5: ITAHUE 220 | S5: NULL | T5: NULL | U5: 0 | V5: 0 | W5: 0
A6: 43556 | B6: 43556 | C6: Licitación Caren y Cec (SIC 2013/03-2) BS1A | D6: Potencia Licitaciones | E6: Potencia | F6: Lic. SIC 2013/03-2 bloques BS1A: Potencia abr 2019 | G6: 43598 | H6: 33 | I6: 8451 | J6: s | K6: s | L6: BS1A | M6: Caren | N6: Cec | O6: 41335 | P6: CEC | Q6: 5 | R6: RAPEL 220 | S6: NULL | T6: NULL | U6: 0 | V6: 0 | W6: 0
A7: 43586 | B7: 43586 | C7: Licitación Caren y Cec (SIC 2013/03-2) BS1A | D7: Potencia Licitaciones | E7: Potencia | F7: Lic. SIC 2013/03-2 bloques BS1A: Potencia may 2019 | G7: 43627 | H7: 33 | I7: 8768 | J7: s | K7: s | L7: BS1A | M7: Caren | N7: Cec | O7: 41335 | P7: CEC | Q7: 1 | R7: A.JAHUEL 220 | S7: NULL | T7: NULL | U7: 0 | V7: 0 | W7: 0
A8: 43586 | B8: 43586 | C8: Licitación Caren y Cec (SIC 2013/03-2) BS1A | D8: Potencia Licitaciones | E8: Potencia | F8: Lic. SIC 2013/03-2 bloques BS1A: Potencia may 2019 | G8: 43627 | H8: 33 | I8: 8768 | J8: s | K8: s | L8: BS1A | M8: Caren | N8: Cec | O8: 41335 | P8: CEC | Q8: 2 | R8: A.MELIP 220 | S8: NULL | T8: NULL | U8: 0 | V8: 0 | W8: 0
A9: 43586 | B9: 43586 | C9: Licitación Caren y Cec (SIC 2013/03-2) BS1A | D9: Potencia Licitaciones | E9: Potencia | F9: Lic. SIC 2013/03-2 bloques BS1A: Potencia may 2019 | G9: 43627 | H9: 33 | I9: 8768 | J9: s | K9: s | L9: BS1A | M9: Caren | N9: Cec | O9: 41335 | P9: CEC | Q9: 3 | R9: CHARRUA 220 | S9: NULL | T9: NULL | U9: 0 | V9: 0 | W9: 0
A10: 43586 | B10: 43586 | C10: Licitación Caren y Cec (SIC 2013/03-2) BS1A | D10: Potencia Licitaciones | E10: Potencia | F10: Lic. SIC 2013/03-2 bloques BS1A: Potencia may 2019 | G10: 43627 | H10: 33 | I10: 8768 | J10: s | K10: s | L10: BS1A | M10: Caren | N10: Cec | O10: 41335 | P10: CEC | Q10: 4 | R10: ITAHUE 220 | S10: NULL | T10: NULL | U10: 0 | V10: 0 | W10: 0
A11: 43586 | B11: 43586 | C11: Licitación Caren y Cec (SIC 2013/03-2) BS1A | D11: Potencia Licitaciones | E11: Potencia | F11: Lic. SIC 2013/03-2 bloques BS1A: Potencia may 2019 | G11: 43627 | H11: 33 | I11: 8768 | J11: s | K11: s | L11: BS1A | M11: Caren | N11: Cec | O11: 41335 | P11: CEC | Q11: 5 | R11: RAPEL 220 | S11: NULL | T11: NULL | U11: 0 | V11: 0 | W11: 0
A12: 43617 | B12: 43617 | C12: Licitación Caren y Cec (SIC 2013/03-2) BS1A | D12: Potencia Licitaciones | E12: Potencia | F12: Lic. SIC 2013/03-2 bloques BS1A: Potencia jun 2019 | G12: 43655 | H12: 33 | I12: 9022 | J12: s | K12: s | L12: BS1A | M12: Caren | N12: Cec | O12: 41335 | P12: CEC | Q12: 1 | R12: A.JAHUEL 220 | S12: NULL | T12: NULL | U12: 0 | V12: 0 | W12: 0
A13: 43617 | B13: 43617 | C13: Licitación Caren y Cec (SIC 2013/03-2) BS1A | D13: Potencia Licitaciones | E13: Potencia | F13: Lic. SIC 2013/03-2 bloques BS1A: Potencia jun 2019 | G13: 43655 | H13: 33 | I13: 9022 | J13: s | K13: s | L13: BS1A | M13: Caren | N13: Cec | O13: 41335 | P13: CEC | Q13: 2 | R13: A.MELIP 220 | S13: NULL | T13: NULL | U13: 0 | V13: 0 | W13: 0
... A31: 43709 | B31: 43739 | C31: Licitación Caren y Cec (SIC 2013/03-2) BS1A | D31: Potencia Licitaciones | E31: Potencia | F31: Lic. SIC 2013/03-2 bloques BS1A: Potencia oct 2019 | G31: 43748 | H31: 33 | I31: 10390 | J31: s | K31: s | L31: BS1A | M31: Caren | N31: Cec | O31: 41335 | P31: CEC | Q31: 5 | R31: RAPEL 220 | S31: NULL | T31: NULL | U31: 0 | V31: 0 | W31: 0
A32: 43739 | B32: 43709 | C32: Licitación Caren y Cec (SIC 2013/03-2) BS1A | D32: Reliq. por PNP Potencia Licitaciones | E32: Potencia | F32: Lic. SIC 2013/03-2 bloques BS1A: Potencia 2019-9 PEC 7T-2019 | G32: 43944.473 | H32: 61 | I32: NULL | J32: s | K32: s | L32: BS1A | M32: Caren | N32: Cec | O32: 41335 | P32: CEC | Q32: 1 | R32: A.JAHUEL 220 | S32: NULL | T32: NULL | U32: 0 | V32: 5969.53 | W32: 0
A33: 43739 | B33: 43709 | C33: Licitación Caren y Cec (SIC 2013/03-2) BS1A | D33: Reliq. por PNP Potencia Licitaciones | E33: Potencia | F33: Lic. SIC 2013/03-2 bloques BS1A: Potencia 2019-9 facturada | G33: 43944.473 | H33: 61 | I33: NULL | J33: s | K33: s | L33: BS1A | M33: Caren | N33: Cec | O33: 41335 | P33: CEC | Q33: 1 | R33: A.JAHUEL 220 | S33: NULL | T33: NULL | U33: 0 | V33: 6360.2 | W33: 0
A34: 43739 | B34: 43739 | C34: Licitación Caren y Cec (SIC 2013/03-2) BS1A | D34: Potencia Licitaciones | E34: Potencia | F34: Lic. SIC 2013/03-2 bloques BS1A: Potencia oct 2019 | G34: 43781 | H34: 33 | I34: 10809 | J34: s | K34: s | L34: BS1A | M34: Caren | N34: Cec | O34: 41335 | P34: CEC | Q34: 1 | R34: A.JAHUEL 220 | S34: NULL | T34: NULL | U34: 0 | V34: 5969.53 | W34: 0
A35: 43739 | B35: 43709 | C35: Licitación Caren y Cec (SIC 2013/03-2) BS1A | D35: Reliq. por PNP Potencia Licitaciones | E35: Potencia | F35: Lic. SIC 2013/03-2 bloques BS1A: Potencia 2019-9 PEC 7T-2019 | G35: 43944.473 | H35: 61 | I35: NULL | J35: s | K35: s | L35: BS1A | M35: Caren | N35: Cec | O35: 41335 | P35: CEC | Q35: 2 | R35: A.MELIP 220 | S35: NULL | T35: NULL | U35: 0 | V35: 6128.55 | W35: 0
A36: 43739 | B36: 43709 | C36: Licitación Caren y Cec (SIC 2013/03-2) BS1A | D36: Reliq. por PNP Potencia Licitaciones | E36: Potencia | F36: Lic. SIC 2013/03-2 bloques BS1A: Potencia 2019-9 facturada | G36: 43944.473 | H36: 61 | I36: NULL | J36: s | K36: s | L36: BS1A | M36: Caren | N36: Cec | O36: 41335 | P36: CEC | Q36: 2 | R36: A.MELIP 220 | S36: NULL | T36: NULL | U36: 0 | V36: 6409.16 | W36: 0
A37: 43739 | B37: 43739 | C37: Licitación Caren y Cec (SIC 2013/03-2) BS1A | D37: Potencia Licitaciones | E37: Potencia | F37: Lic. SIC 2013/03-2 bloques BS1A: Potencia oct 2019 | G37: 43781 | H37: 33 | I37: 10809 | J37: s | K37: s | L37: BS1A | M37: Caren | N37: Cec | O37: 41335 | P37: CEC | Q37: 2 | R37: A.MELIP 220 | S37: NULL | T37: NULL | U37: 0 | V37: 6128.55 | W37: 0
A38: 43739 | B38: 43709 | C38: Licitación Caren y Cec (SIC 2013/03-2) BS1A | D38: Reliq. por PNP Potencia Licitaciones | E38: Potencia | F38: Lic. SIC 2013/03-2 bloques BS1A: Potencia 2019-9 PEC 7T-2019 | G38: 43944.473 | H38: 61 | I38: NULL | J38: s | K38: s | L38: BS1A | M38: Caren | N38: Cec | O38: 41335 | P38: CEC | Q38: 3 | R38: CHARRUA 220 | S38: NULL | T38: NULL | U38: 0 | V38: 5735.8 | W38: 0
A39: 43739 | B39: 43709 | C39: Licitación Caren y Cec (SIC 2013/03-2) BS1A | D39: Reliq. por PNP Potencia Licitaciones | E39: Potencia | F39: Lic. SIC 2013/03-2 bloques BS1A: Potencia 2019-9 facturada | G39: 43944.473 | H39: 61 | I39: NULL | J39: s | K39: s | L39: BS1A | M39: Caren | N39: Cec | O39: 41335 | P39: CEC | Q39: 3 | R39: CHARRUA 220 | S39: NULL | T39: NULL | U39: 0 | V39: 6046.73 | W39: 0
A40: 43739 | B40: 43739 | C40: Licitación Caren y Cec (SIC 2013/03-2) BS1A | D40: Potencia Licitaciones | E40: Potencia | F40: Lic. SIC 2013/03-2 bloques BS1A: Potencia oct 2019 | G40: 43781 | H40: 33 | I40: 10809 | J40: s | K40: s | L40: BS1A | M40: Caren | N40: Cec | O40: 41335 | P40: CEC | Q40: 3 | R40: CHARRUA 220 | S40: NULL | T40: NULL | U40: 0 | V40: 5735.8 | W40: 0
A41: 43739 | B41: 43709 | C41: Licitación Caren y Cec (SIC 2013/03-2) BS1A | D41: Reliq. por PNP Potencia Licitaciones | E41: Potencia | F41: Lic. SIC 2013/03-2 bloques BS1A: Potencia 2019-9 PEC 7T-2019 | G41: 43944.473 | H41: 61 | I41: NULL | J41: s | K41: s | L41: BS1A | M41: Caren | N41: Cec | O41: 41335 | P41: CEC | Q41: 4 | R41: ITAHUE 220 | S41: NULL | T41: NULL | U41: 0 | V41: 5821.34 | W41: 0
A42: 43739 | B42: 43709 | C42: Licitación Caren y Cec (SIC 2013/03-2) BS1A | D42: Reliq. por PNP Potencia Licitaciones | E42: Potencia | F42: Lic. SIC 2013/03-2 bloques BS1A: Potencia 2019-9 facturada | G42: 43944.473 | H42: 61 | I42: NULL | J42: s | K42: s | L42: BS1A | M42: Caren | N42: Cec | O42: 41335 | P42: CEC | Q42: 4 | R42: ITAHUE 220 | S42: NULL | T42: NULL | U42: 0 | V42: 6160.55 | W42: 0
A43: 43739 | B43: 43739 | C43: Licitación Caren y Cec (SIC 2013/03-2) BS1A | D43: Potencia Licitaciones | E43: Potencia | F43: Lic. SIC 2013/03-2 bloques BS1A: Potencia oct 2019 | G43: 43781 | H43: 33 | I43: 10809 | J43: s | K43: s | L43: BS1A | M43: Caren | N43: Cec | O43: 41335 | P43: CEC | Q43: 4 | R43: ITAHUE 220 | S43: NULL | T43: NULL | U43: 0 | V43: 5821.34 | W43: 0
A44: 43739 | B44: 43709 | C44: Licitación Caren y Cec (SIC 2013/03-2) BS1A | D44: Reliq. por PNP Potencia Licitaciones | E44: Potencia | F44: Lic. SIC 2013/03-2 bloques BS1A: Potencia 2019-9 facturada | G44: 43944.473 | H44: 61 | I44: NULL | J44: s | K44: s | L44: BS1A | M44: Caren | N44: Cec | O44: 41335 | P44: CEC | Q44: 5 | R44: RAPEL 220 | S44: NULL | T44: NULL | U44: 0 | V44: 5634.08 | W44: 0
A45: 43739 | B45: 43709 | C45: Licitación Caren y Cec (SIC 2013/03-2) BS1A | D45: Reliq. por PNP Potencia Licitaciones | E45: Potencia | F45: Lic. SIC 2013/03-2 bloques BS1A: Potencia 2019-9 PEC 7T-2019 | G45: 43944.473 | H45: 61 | I45: NULL | J45: s | K45: s | L45: BS1A | M45: Caren | N45: Cec | O45: 41335 | P45: CEC | Q45: 5 | R45: RAPEL 220 | S45: NULL | T45: NULL | U45: 0 | V45: 6082.17 | W45: 0
A46: 43739 | B46: 43739 | C46: Licitación Caren y Cec (SIC 2013/03-2) BS1A | D46: Potencia Licitaciones | E46: Potencia | F46: Lic. SIC 2013/03-2 bloques BS1A: Potencia oct 2019 | G46: 43781 | H46: 33 | I46: 10809 | J46: s | K46: s | L46: BS1A | M46: Caren | N46: Cec | O46: 41335 | P46: CEC | Q46: 5 | R46: RAPEL 220 | S46: NULL | T46: NULL | U46: 0 | V46: 6082.17 | W46: 0
A47: 43770 | B47: 43770 | C47: Licitación Caren y Cec (SIC 2013/03-2) BS1A | D47: Potencia Licitaciones | E47: Potencia | F47: Lic. SIC 2013/03-2 bloques BS1A: Potencia nov 2019 | G47: 43805 | H47: 33 | I47: 11167 | J47: s | K47: s | L47: BS1A | M47: Caren | N47: Cec | O47: 41335 | P47: CEC | Q47: 1 | R47: A.JAHUEL 220 | S47: NULL | T47: NULL | U47: 0 | V47: 5969.53 | W47: 0
A48: 43770 | B48: 43770 | C48: Licitación Caren y Cec (SIC 2013/03-2) BS1A | D48: Potencia Licitaciones | E48: Potencia | F48: Lic. SIC 2013/03-2 bloques BS1A: Potencia nov 2019 | G48: 43805 | H48: 33 | I48: 11167 | J48: s | K48: s | L48: BS1A | M48: Caren | N48: Cec | O48: 41335 | P48: CEC | Q48: 2 | R48: A.MELIP 220 | S48: NULL | T48: NULL | U48: 0 | V48: 6128.55 | W48: 0
A49: 43770 | B49: 43770 | C49: Licitación Caren y Cec (SIC 2013/03-2) BS1A | D49: Potencia Licitaciones | E49: Potencia | F49: Lic. SIC 2013/03-2 bloques BS1A: Potencia nov 2019 | G49: 43805 | H49: 33 | I49: 11167 | J49: s | K49: s | L49: BS1A | M49: Caren | N49: Cec | O49: 41335 | P49: CEC | Q49: 3 | R49: CHARRUA 220 | S49: NULL | T49: NULL | U49: 0 | V49: 5735.8 | W49: 0
A50: 43770 | B50: 43770 | C50: Licitación Caren y Cec (SIC 2013/03-2) BS1A | D50: Potencia Licitaciones | E50: Potencia | F50: Lic. SIC 2013/03-2 bloques BS1A: Potencia nov 2019 | G50: 43805 | H50: 33 | I50: 11167 | J50: s | K50: s | L50: BS1A | M50: Caren | N50: Cec | O50: 41335 | P50: CEC | Q50: 4 | R50: ITAHUE 220 | S50: NULL | T50: NULL | U50: 0 | V50: 5821.34 | W50: 0
A51: 43770 | B51: 43770 | C51: Licitación Caren y Cec (SIC 2013/03-2) BS1A | D51: Potencia Licitaciones | E51: Potencia | F51: Lic. SIC 2013/03-2 bloques BS1A: Potencia nov 2019 | G51: 43805 | H51: 33 | I51: 11167 | J51: s | K51: s | L51: BS1A | M51: Caren | N51: Cec | O51: 41335 | P51: CEC | Q51: 5 | R51: RAPEL 220 | S51: NULL | T51: NULL | U51: 0 | V51: 6082.17 | W51: 0
A52: 43800 | B52: 43800 | C52: Licitación Caren y Cec (SIC 2013/03-2) BS1A | D52: Potencia Licitaciones | E52: Potencia | F52: Lic. SIC 2013/03-2 bloques BS1A: Potencia dic 2019 | G52: 43837 | H52: 33 | I52: 11902 | J52: s | K52: s | L52: BS1A | M52: Caren | N52: Cec | O52: 41335 | P52: CEC | Q52: 1 | R52: A.JAHUEL 220 | S52: NULL | T52: NULL | U52: 0 | V52: 5969.53 | W52: 0
A53: 43800 | B53: 43800 | C53: Licitación Caren y Cec (SIC 2013/03-2) BS1A | D53: Potencia Licitaciones | E53: Potencia | F53: Lic. SIC 2013/03-2 bloques BS1A: Potencia dic 2019 | G53: 43837 | H53: 33 | I53: 11902 | J53: s | K53: s | L53: BS1A | M53: Caren | N53: Cec | O53: 41335 | P53: CEC | Q53: 2 | R53: A.MELIP 220 | S53: NULL | T53: NULL | U53: 0 | V53: 6128.55 | W53: 0
A54: 43800 | B54: 43800 | C54: Licitación Caren y Cec (SIC 2013/03-2) BS1A | D54: Potencia Licitaciones | E54: Potencia | F54: Lic. SIC 2013/03-2 bloques BS1A: Potencia dic 2019 | G54: 43837 | H54: 33 | I54: 11902 | J54: s | K54: s | L54: BS1A | M54: Caren | N54: Cec | O54: 41335 | P54: CEC | Q54: 3 | R54: CHARRUA 220 | S54: NULL | T54: NULL | U54: 0 | V54: 5735.8 | W54: 0
A55: 43800 | B55: 43800 | C55: Licitación Caren y Cec (SIC 2013/03-2) BS1A | D55: Potencia Licitaciones | E55: Potencia | F55: Lic. SIC 2013/03-2 bloques BS1A: Potencia dic 2019 | G55: 43837 | H55: 33 | I55: 11902 | J55: s | K55: s | L55: BS1A | M55: Caren | N55: Cec | O55: 41335 | P55: CEC | Q55: 4 | R55: ITAHUE 220 | S55: NULL | T55: NULL | U55: 0 | V55: 5821.34 | W55: 0
A56: 43800 | B56: 43800 | C56: Licitación Caren y Cec (SIC 2013/03-2) BS1A | D56: Potencia Licitaciones | E56: Potencia | F56: Lic. SIC 2013/03-2 bloques BS1A: Potencia dic 2019 | G56: 43837 | H56: 33 | I56: 11902 | J56: s | K56: s | L56: BS1A | M56: Caren | N56: Cec | O56: 41335 | P56: CEC | Q56: 5 | R56: RAPEL 220 | S56: NULL | T56: NULL | U56: 0 | V56: 6082.17 | W56: 0
A57: 43831 | B57: 43831 | C57: Licitación Caren y Cec (SIC 2013/03-2) BS1A | D57: Potencia Licitaciones | E57: Potencia | F57: Lic. SIC 2013/03-2 bloques BS1A: Potencia ene 2020 | G57: 43910.519 | H57: 33 | I57: 13159 | J57: s | K57: s | L57: BS1A | M57: Caren | N57: Cec | O57: 41335 | P57: CEC | Q57: 1 | R57: A.JAHUEL 220 | S57: NULL | T57: NULL | U57: 0 | V57: 5969.53 | W57: 0
... A136: 44287 | B136: 44287 | C136: Licitación Caren y Cec (SIC 2013/03-2) BS1A | D136: Potencia Licitaciones | E136: Potencia | F136: Lic. SIC 2013/03-2 bloques BS1A: Potencia abr 2021 | G136: 44323.703 | H136: 33 | I136: 18700 | J136: s | K136: s | L136: BS1A | M136: Caren | N136: Cec | O136: 41335 | P136: CEC | Q136: 5 | R136: RAPEL 220 | S136: NULL | T136: NULL | U136: 0 | V136: 5963.281 | W136: 0

Sheet FACT_EST_EFACT
A1: IdContrato | B1: MesDevengado | C1: Anho | D1: Mes | E1: Codigo | F1: DX | G1: NomEmpresaDistribuidora | H1: GX | I1: NomSuministrador | J1: CodigoContrato | K1: PuntoRetiro | L1: Contrato | M1: Energia_kWh | N1: Potencia_kW | O1: Sistema | P1: DataCreated | Q1: IdBarra | R1: NomBarra | S1: Energia | T1: PrecioEnergia | U1: PrecioEnergiaAjustado | V1: TotalEnergia | W1: TotalEnergiaAjustado | X1: Potencia | Y1: PrecioPotencia | Z1: PrecioPotenciaAjustado | AA1: TotalPotencia | AB1: TotalPotenciaAjustado | AC1: EmpresaDistribuidora | AD1: Fecha
A2: 607827 | B2: 01-03-2016 | C2: 2016 | D2: 3 | E2: QUINTA | F2: CEC | G2: CEC | H2: Empresa Eléctrica Carén S.A. | I2: CAREN | J2: SIC 2013/03_2_BS1A_BB_CEC_Empresa Eléctrica Carén S.A. | K2: QUINTA 13,2 | L2: SIC 2013/03_2_BS1A_BB | M2: 1703.6854 | N2: 0 | O2: SIC4 | P2: 44330.495 | Q2: 5439222 | R2: Charrua 220 | S2: 45.689989 | X2: 0 | AC2: CEC | AD2: 42430
A3: 607809 | B3: 01-03-2016 | C3: 2016 | D3: 3 | E3: Curico | F3: CEC | G3: CEC | H3: Empresa Eléctrica Carén S.A. | I3: CAREN | J3: SIC 2013/03_2_BS1A_BB_CEC_Empresa Eléctrica Carén S.A. | K3: CURICÓ 13,2 | L3: SIC 2013/03_2_BS1A_BB | M3: 6396.7767 | N3: 0 | O3: SIC4 | P3: 44330.495 | Q3: 5439188 | R3: Charrua 220 | S3: 95.084381 | X3: 0 | AC3: CEC | AD3: 42430
A4: 607845 | B4: 01-03-2016 | C4: 2016 | D4: 3 | E4: TENO | F4: CEC | G4: CEC | H4: Empresa Eléctrica Carén S.A. | I4: CAREN | J4: SIC 2013/03_2_BS1A_BB_CEC_Empresa Eléctrica Carén S.A. | K4: TENO 13,2 | L4: SIC 2013/03_2_BS1A_BB | M4: 2312.6678 | N4: 0 | O4: SIC4 | P4: 44330.495 | Q4: 5439256 | R4: Charrua 220 | S4: 61.060298 | X4: 0 | AC4: CEC | AD4: 42430
A5: 607827 | B5: 01-03-2016 | C5: 2016 | D5: 3 | E5: QUINTA | F5: CEC | G5: CEC | H5: Empresa Eléctrica Carén S.A. | I5: CAREN | J5: SIC 2013/03_2_BS1A_BB_CEC_Empresa Eléctrica Carén S.A. | K5: QUINTA 13,2 | L5: SIC 2013/03_2_BS1A_BB | M5: 1703.6854 | N5: 0 | O5: SIC4 | P5: 44330.495 | Q5: 5439221 | R5: Itahue 220 | S5: 1725.2398 | X5: 0 | AC5: CEC | AD5: 42430
A6: 607845 | B6: 01-03-2016 | C6: 2016 | D6: 3 | E6: TENO | F6: CEC | G6: CEC | H6: Empresa Eléctrica Carén S.A. | I6: CAREN | J6: SIC 2013/03_2_BS1A_BB_CEC_Empresa Eléctrica Carén S.A. | K6: TENO 13,2 | L6: SIC 2013/03_2_BS1A_BB | M6: 2312.6678 | N6: 0 | O6: SIC4 | P6: 44330.495 | Q6: 5439255 | R6: Itahue 220 | S6: 2342.8885 | X6: 0 | AC6: CEC | AD6: 42430
A7: 607809 | B7: 01-03-2016 | C7: 2016 | D7: 3 | E7: Curico | F7: CEC | G7: CEC | H7: Empresa Eléctrica Carén S.A. | I7: CAREN | J7: SIC 2013/03_2_BS1A_BB_CEC_Empresa Eléctrica Carén S.A. | K7: CURICÓ 13,2 | L7: SIC 2013/03_2_BS1A_BB | M7: 6396.7767 | N7: 0 | O7: SIC4 | P7: 44330.495 | Q7: 5439187 | R7: Itahue 220 | S7: 6554.173 | X7: 0 | AC7: CEC | AD7: 42430
A8: 600911 | B8: 01-04-2016 | C8: 2016 | D8: 4 | E8: Curico | F8: CEC | G8: CEC | H8: Empresa Eléctrica Carén S.A. | I8: CAREN | J8: SIC 2013/03_2_BS1A_BB_CEC_Empresa Eléctrica Carén S.A. | K8: CURICÓ 13,2 | L8: SIC 2013/03_2_BS1A_BB | M8: 4919.3409 | N8: 0 | O8: SIC4 | P8: 44330.488 | Q8: 5423000 | R8: Charrua 220 | S8: 73.123154 | X8: 0 | AC8: CEC | AD8: 42461
A9: 600947 | B9: 01-04-2016 | C9: 2016 | D9: 4 | E9: TENO | F9: CEC | G9: CEC | H9: Empresa Eléctrica Carén S.A. | I9: CAREN | J9: SIC 2013/03_2_BS1A_BB_CEC_Empresa Eléctrica Carén S.A. | K9: TENO 13,2 | L9: SIC 2013/03_2_BS1A_BB | M9: 2065.7815 | N9: 0 | O9: SIC4 | P9: 44330.488 | Q9: 5423068 | R9: Charrua 220 | S9: 54.541875 | X9: 0 | AC9: CEC | AD9: 42461
A10: 600929 | B10: 01-04-2016 | C10: 2016 | D10: 4 | E10: QUINTA | F10: CEC | G10: CEC | H10: Empresa Eléctrica Carén S.A. | I10: CAREN | J10: SIC 2013/03_2_BS1A_BB_CEC_Empresa Eléctrica Carén S.A. | K10: QUINTA 13,2 | L10: SIC 2013/03_2_BS1A_BB | M10: 1317.6215 | N10: 0 | O10: SIC4 | P10: 44330.488 | Q10: 5423034 | R10: Charrua 220 | S10: 35.336403 | X10: 0 | AC10: CEC | AD10: 42461
A11: 600929 | B11: 01-04-2016 | C11: 2016 | D11: 4 | E11: QUINTA | F11: CEC | G11: CEC | H11: Empresa Eléctrica Carén S.A. | I11: CAREN | J11: SIC 2013/03_2_BS1A_BB_CEC_Empresa Eléctrica Carén S.A. | K11: QUINTA 13,2 | L11: SIC 2013/03_2_BS1A_BB | M11: 1317.6215 | N11: 0 | O11: SIC4 | P11: 44330.488 | Q11: 5423033 | R11: Itahue 220 | S11: 1334.2916 | X11: 0 | AC11: CEC | AD11: 42461
A12: 600911 | B12: 01-04-2016 | C12: 2016 | D12: 4 | E12: Curico | F12: CEC | G12: CEC | H12: Empresa Eléctrica Carén S.A. | I12: CAREN | J12: SIC 2013/03_2_BS1A_BB_CEC_Empresa Eléctrica Carén S.A. | K12: CURICÓ 13,2 | L12: SIC 2013/03_2_BS1A_BB | M12: 4919.3409 | N12: 0 | O12: SIC4 | P12: 44330.488 | Q12: 5422999 | R12: Itahue 220 | S12: 5040.3841 | X12: 0 | AC12: CEC | AD12: 42461
A13: 600947 | B13: 01-04-2016 | C13: 2016 | D13: 4 | E13: TENO | F13: CEC | G13: CEC | H13: Empresa Eléctrica Carén S.A. | I13: CAREN | J13: SIC 2013/03_2_BS1A_BB_CEC_Empresa Eléctrica Carén S.A. | K13: TENO 13,2 | L13: SIC 2013/03_2_BS1A_BB | M13: 2065.7815 | N13: 0 | O13: SIC4 | P13: 44330.488 | Q13: 5423067 | R13: Itahue 220 | S13: 2092.776 | X13: 0 | AC13: CEC | AD13: 42461
... A517: 420506 | B517: 01-06-2020 | C517: 2020 | D517: 6 | E517: Curico 13.2 | F517: CEC | G517: CEC | H517: Empresa Eléctrica Carén S.A. | I517: Empresa Eléctrica Carén S.A. | J517: SIC 2013/03_2_BS1A_BB_CEC_Empresa Eléctrica Carén S.A. | K517: Curico 13.2 | L517: SIC 2013/03_2_BS1A_BB | M517: 2681.58 | N517: 0 | O517: STX E | P517: 44277.586 | Q517: 3980788 | R517: RAPEL 220 | S517: 8.3052895 | X517: 0 | AC517: CEC | AD517: 43983

Sheet FactRealE
A1: Empresa | B1: MesDevengado | C1: IdAgrupacion | D1: NomAgrupacion | E1: Bloque | F1: NombreCliente | G1: FechaDeContabilizacion | H1: PrefijoFolio | I1: CuentaDeMayor | J1: CodigoDeArticulo | K1: NumDeFolio | L1: MontoCLP | M1: TotalUSD
A2: SAN_JUAN_LAP | B2: 01-01-2018 | C2: 1 | D2: CEC | E2: BS3 | F2: COOPERATIVA DE ABASTECIMIENTO DE ENERGIA ELECTRICA CURICO LTDA. | G2: 43152 | H2: 33 | I2: 4110600 | J2: VENTA PPA ENERGIA | K2: 2660 | L2: 2976186 | M2: 4996.7
A3: SAN_JUAN_LAP | B3: 01-01-2019 | C3: 1 | D3: CEC | E3: BS3 | F3: COOPERATIVA DE ABASTECIMIENTO DE ENERGIA ELECTRICA CURICO LTDA. | G3: 43518 | H3: 33 | I3: 4110600 | J3: VENTA PPA ENERGIA | K3: 5253 | L3: 5548783 | M3: 8480.1
A4: SAN_JUAN_LAP | B4: 01-01-2019 | C4: 1 | D4: CEC | E4: BS3 | F4: COOPERATIVA DE ABASTECIMIENTO DE ENERGIA ELECTRICA CURICO LTDA. | G4: 43789 | H4: 33 | I4: 4110600 | J4: VENTA PPA ENERGIA | K4: 8690 | L4: 5916 | M4: 7.56
A5: SAN_JUAN_LAP | B5: 01-01-2019 | C5: 1 | D5: CEC | E5: BS3 | F5: COOPERATIVA DE ABASTECIMIENTO DE ENERGIA ELECTRICA CURICO LTDA. | G5: 43789 | H5: 33 | I5: 4110600 | J5: VENTA PPA ENERGIA | K5: 8796 | L5: 5916 | M5: 7.56
A6: SAN_JUAN_LAP | B6: 01-02-2018 | C6: 1 | D6: CEC | E6: BS3 | F6: COOPERATIVA DE ABASTECIMIENTO DE ENERGIA ELECTRICA CURICO LTDA. | G6: 43188 | H6: 33 | I6: 4110600 | J6: VENTA PPA ENERGIA | K6: 2965 | L6: 2970366 | M6: 4907.59
A7: SAN_JUAN_LAP | B7: 01-02-2019 | C7: 1 | D7: CEC | E7: BS3 | F7: COOPERATIVA DE ABASTECIMIENTO DE ENERGIA ELECTRICA CURICO LTDA. | G7: 43543 | H7: 33 | I7: 4110600 | J7: VENTA PPA ENERGIA | K7: 5420 | L7: 5511858 | M7: 8261.05
A8: SAN_JUAN_LAP | B8: 01-02-2019 | C8: 1 | D8: CEC | E8: BS3 | F8: COOPERATIVA DE ABASTECIMIENTO DE ENERGIA ELECTRICA CURICO LTDA. | G8: 43581 | H8: 33 | I8: 4110600 | J8: VENTA PPA ENERGIA | K8: 6437 | L8: 940 | M8: 1.39
A9: SAN_JUAN_LAP | B9: 01-03-2018 | C9: 1 | D9: CEC | E9: BS3 | F9: COOPERATIVA DE ABASTECIMIENTO DE ENERGIA ELECTRICA CURICO LTDA. | G9: 43208 | H9: 33 | I9: 4110600 | J9: VENTA PPA ENERGIA | K9: 3190 | L9: 2906148 | M9: 4877.56
A10: SAN_JUAN_LAP | B10: 01-03-2019 | C10: 1 | D10: CEC | E10: BS3 | F10: COOPERATIVA DE ABASTECIMIENTO DE ENERGIA ELECTRICA CURICO LTDA. | G10: 43585 | H10: 33 | I10: 4110600 | J10: VENTA PPA ENERGIA | K10: 6455 | L10: 5412779 | M10: 7987.34
A11: SAN_JUAN_LAP | B11: 01-03-2019 | C11: 1 | D11: CEC | E11: BS3 | F11: COOPERATIVA DE ABASTECIMIENTO DE ENERGIA ELECTRICA CURICO LTDA. | G11: 43789 | I11: 4110600 | J11: VENTA PPA ENERGIA | L11: 2396 | M11: 3.06
A12: SAN_JUAN_LAP | B12: 01-03-2019 | C12: 1 | D12: CEC | E12: BS3 | F12: COOPERATIVA DE ABASTECIMIENTO DE ENERGIA ELECTRICA CURICO LTDA. | G12: 43789 | H12: 33 | I12: 4110600 | J12: VENTA PPA ENERGIA | K12: 8710 | L12: 2396 | M12: 3.06
A13: SAN_JUAN_LAP | B13: 01-04-2018 | C13: 1 | D13: CEC | E13: BS3 | F13: COOPERATIVA DE ABASTECIMIENTO DE ENERGIA ELECTRICA CURICO LTDA. | G13: 43245 | H13: 33 | I13: 4110600 | J13: VENTA PPA ENERGIA | K13: 3375 | L13: 2017272 | M13: 3231.2
A14: SAN_JUAN_LAP | B14: 01-04-2019 | C14: 1 | D14: CEC | E14: BS3 | F14: COOPERATIVA DE ABASTECIMIENTO DE ENERGIA ELECTRICA CURICO LTDA. | G14: 43601 | H14: 33 | I14: 4110600 | J14: VENTA PPA ENERGIA | K14: 6506 | L14: 3662698 | M14: 5288.18
A15: SAN_JUAN_LAP | B15: 01-04-2019 | C15: 1 | D15: CEC | E15: BS3 | F15: COOPERATIVA DE ABASTECIMIENTO DE ENERGIA ELECTRICA CURICO LTDA. | G15: 43789 | I15: 4110600 | J15: VENTA PPA ENERGIA | L15: 4987 | M15: 6.37
A16: SAN_JUAN_LAP | B16: 01-04-2019 | C16: 1 | D16: CEC | E16: BS3 | F16: COOPERATIVA DE ABASTECIMIENTO DE ENERGIA ELECTRICA CURICO LTDA. | G16: 43789 | H16: 33 | I16: 4110600 | J16: VENTA PPA ENERGIA | K16: 8735 | L16: 4987 | M16: 6.37
A17: SAN_JUAN_LAP | B17: 01-05-2018 | C17: 1 | D17: CEC | E17: BS3 | F17: COOPERATIVA DE ABASTECIMIENTO DE ENERGIA ELECTRICA CURICO LTDA. | G17: 43266 | H17: 33 | I17: 4110600 | J17: VENTA PPA ENERGIA | K17: 3630 | L17: 1971676 | M17: 3109.95
A18: SAN_JUAN_LAP | B18: 01-05-2019 | C18: 1 | D18: CEC | E18: BS3 | F18: COOPERATIVA DE ABASTECIMIENTO DE ENERGIA ELECTRICA CURICO LTDA. | G18: 43634 | H18: 33 | I18: 4110600 | J18: VENTA PPA ENERGIA | K18: 6776 | L18: 3863654 | M18: 5523.29
A19: SAN_JUAN_LAP | B19: 01-06-2018 | C19: 1 | D19: CEC | E19: BS3 | F19: COOPERATIVA DE ABASTECIMIENTO DE ENERGIA ELECTRICA CURICO LTDA. | G19: 43294 | H19: 33 | I19: 4110600 | J19: VENTA PPA ENERGIA | K19: 3770 | L19: 1881616 | M19: 2903.5
A20: SAN_JUAN_LAP | B20: 01-06-2019 | C20: 1 | D20: CEC | E20: BS3 | F20: COOPERATIVA DE ABASTECIMIENTO DE ENERGIA ELECTRICA CURICO LTDA. | G20: 43658 | H20: 33 | I20: 4110600 | J20: VENTA PPA ENERGIA | K20: 6977 | L20: 3578184 | M20: 5236.01
A21: SAN_JUAN_LAP | B21: 01-06-2019 | C21: 1 | D21: CEC | E21: BS3 | F21: COOPERATIVA DE ABASTECIMIENTO DE ENERGIA ELECTRICA CURICO LTDA. | G21: 43789 | I21: 4110600 | J21: VENTA PPA ENERGIA | L21: 8039 | M21: 10.28
A22: SAN_JUAN_LAP | B22: 01-06-2019 | C22: 1 | D22: CEC | E22: BS3 | F22: COOPERATIVA DE ABASTECIMIENTO DE ENERGIA ELECTRICA CURICO LTDA. | G22: 43789 | H22: 33 | I22: 4110600 | J22: VENTA PPA ENERGIA | K22: 8764 | L22: 8039 | M22: 10.28
A23: SAN_JUAN_LAP | B23: 01-07-2018 | C23: 1 | D23: CEC | E23: BS3 | F23: COOPERATIVA DE ABASTECIMIENTO DE ENERGIA ELECTRICA CURICO LTDA. | G23: 43329 | H23: 33 | I23: 4110600 | J23: VENTA PPA ENERGIA | K23: 4135 | L23: 1844533 | M23: 2769.03
A24: SAN_JUAN_LAP | B24: 01-07-2019 | C24: 1 | D24: CEC | E24: BS3 | F24: COOPERATIVA DE ABASTECIMIENTO DE ENERGIA ELECTRICA CURICO LTDA. | G24: 43691 | H24: 33 | I24: 4110600 | J24: VENTA PPA ENERGIA | K24: 7372 | L24: 3599792 | M24: 5081.79
A25: SAN_JUAN_LAP | B25: 01-08-2018 | C25: 1 | D25: CEC | E25: BS3 | F25: COOPERATIVA DE ABASTECIMIENTO DE ENERGIA ELECTRICA CURICO LTDA. | G25: 43356 | H25: 33 | I25: 4110600 | J25: VENTA PPA ENERGIA | K25: 4315 | L25: 1697400 | M25: 2456.23
A26: SAN_JUAN_LAP | B26: 01-08-2019 | C26: 1 | D26: CEC | E26: BS3 | F26: COOPERATIVA DE ABASTECIMIENTO DE ENERGIA ELECTRICA CURICO LTDA. | G26: 43720 | H26: 33 | I26: 4110600 | J26: VENTA PPA ENERGIA | K26: 7848 | L26: 3367044 | M26: 4713.17
A27: SAN_JUAN_LAP | B27: 01-09-2018 | C27: 1 | D27: CEC | E27: BS3 | F27: COOPERATIVA DE ABASTECIMIENTO DE ENERGIA ELECTRICA CURICO LTDA. | G27: 43392 | H27: 33 | I27: 4110600 | J27: VENTA PPA ENERGIA | K27: 4513 | L27: 1472717 | M27: 2182.84
A28: SAN_JUAN_LAP | B28: 01-09-2019 | C28: 1 | D28: CEC | E28: BS3 | F28: COOPERATIVA DE ABASTECIMIENTO DE ENERGIA ELECTRICA CURICO LTDA. | G28: 43754 | H28: 33 | I28: 4110600 | J28: VENTA PPA ENERGIA | K28: 8168 | L28: 3332938 | M28: 4658.32
A29: SAN_JUAN_LAP | B29: 01-10-2018 | C29: 1 | D29: CEC | E29: BS3 | F29: COOPERATIVA DE ABASTECIMIENTO DE ENERGIA ELECTRICA CURICO LTDA. | G29: 43431 | H29: 33 | I29: 4110600 | J29: VENTA PPA ENERGIA | K29: 4847 | L29: 1648963 | M29: 2439.69
A30: SAN_JUAN_LAP | B30: 01-10-2019 | C30: 1 | D30: CEC | E30: BS3 | F30: COOPERATIVA DE ABASTECIMIENTO DE ENERGIA ELECTRICA CURICO LTDA. | G30: 43783 | H30: 33 | I30: 4110600 | J30: VENTA PPA ENERGIA | K30: 8549 | L30: 4210239 | M30: 5299.16
A31: SAN_JUAN_LAP | B31: 01-11-2018 | C31: 1 | D31: CEC | E31: BS3 | F31: COOPERATIVA DE ABASTECIMIENTO DE ENERGIA ELECTRICA CURICO LTDA. | G31: 43448 | H31: 33 | I31: 4110600 | J31: VENTA PPA ENERGIA | K31: 4953 | L31: 2192015 | M31: 3218.01
A32: SAN_JUAN_LAP | B32: 01-11-2019 | C32: 1 | D32: CEC | E32: BS3 | F32: COOPERATIVA DE ABASTECIMIENTO DE ENERGIA ELECTRICA CURICO LTDA. | G32: 43816 | H32: 33 | I32: 4110600 | J32: VENTA PPA ENERGIA | K32: 9039 | L32: 5194344 | M32: 6809.31
A33: SAN_JUAN_LAP | B33: 01-12-2018 | C33: 1 | D33: CEC | E33: BS3 | F33: COOPERATIVA DE ABASTECIMIENTO DE ENERGIA ELECTRICA CURICO LTDA. | G33: 43486 | H33: 33 | I33: 4110600 | J33: VENTA PPA ENERGIA | K33: 5148 | L33: 2970075 | M33: 4432.29

Sheet FactRealP
A1: Empresa | B1: MesDevengado | C1: IdAgrupacion | D1: NomAgrupacion | E1: Bloque | F1: NombreCliente | G1: FechaDeContabilizacion | H1: PrefijoFolio | I1: CuentaDeMayor | J1: CodigoDeArticulo | K1: NumDeFolio | L1: MontoCLP | M1: TotalUSD
A2: SAN_JUAN_LAP | B2: 01-01-2018 | C2: 1 | D2: CEC | E2: BS3 | F2: COOPERATIVA DE ABASTECIMIENTO DE ENERGIA ELECTRICA CURICO LTDA. | G2: 43152 | H2: 33 | I2: 4110700 | J2: VENTA PPA POTENCIA | K2: 2660 | L2: 241227 | M2: 404.99
A3: SAN_JUAN_LAP | B3: 01-01-2019 | C3: 1 | D3: CEC | E3: BS3 | F3: COOPERATIVA DE ABASTECIMIENTO DE ENERGIA ELECTRICA CURICO LTDA. | G3: 43518 | H3: 33 | I3: 4110700 | J3: VENTA PPA POTENCIA | K3: 5253 | L3: 501158 | M3: 765.91
A4: SAN_JUAN_LAP | B4: 01-02-2018 | C4: 1 | D4: CEC | E4: BS3 | F4: COOPERATIVA DE ABASTECIMIENTO DE ENERGIA ELECTRICA CURICO LTDA. | G4: 43188 | H4: 33 | I4: 4110700 | J4: VENTA PPA POTENCIA | K4: 2965 | L4: 241845 | M4: 399.57
A5: SAN_JUAN_LAP | B5: 01-02-2019 | C5: 1 | D5: CEC | E5: BS3 | F5: COOPERATIVA DE ABASTECIMIENTO DE ENERGIA ELECTRICA CURICO LTDA. | G5: 43543 | H5: 33 | I5: 4110700 | J5: VENTA PPA POTENCIA | K5: 5420 | L5: 501163 | M5: 751.13
A6: SAN_JUAN_LAP | B6: 01-03-2018 | C6: 1 | D6: CEC | E6: BS3 | F6: COOPERATIVA DE ABASTECIMIENTO DE ENERGIA ELECTRICA CURICO LTDA. | G6: 43208 | H6: 33 | I6: 4110700 | J6: VENTA PPA POTENCIA | K6: 3190 | L6: 241901 | M6: 406
A7: SAN_JUAN_LAP | B7: 01-03-2019 | C7: 1 | D7: CEC | E7: BS3 | F7: COOPERATIVA DE ABASTECIMIENTO DE ENERGIA ELECTRICA CURICO LTDA. | G7: 43585 | H7: 33 | I7: 4110700 | J7: VENTA PPA POTENCIA | K7: 6455 | L7: 501181 | M7: 739.56
A8: SAN_JUAN_LAP | B8: 01-04-2018 | C8: 1 | D8: CEC | E8: BS3 | F8: COOPERATIVA DE ABASTECIMIENTO DE ENERGIA ELECTRICA CURICO LTDA. | G8: 43245 | H8: 33 | I8: 4110700 | J8: VENTA PPA POTENCIA | K8: 3375 | L8: 247218 | M8: 395.99
A9: SAN_JUAN_LAP | B9: 01-04-2019 | C9: 1 | D9: CEC | E9: BS3 | F9: COOPERATIVA DE ABASTECIMIENTO DE ENERGIA ELECTRICA CURICO LTDA. | G9: 43601 | H9: 33 | I9: 4110700 | J9: VENTA PPA POTENCIA | K9: 6506 | L9: 460407 | M9: 664.73
A10: SAN_JUAN_LAP | B10: 01-05-2018 | C10: 1 | D10: CEC | E10: BS3 | F10: COOPERATIVA DE ABASTECIMIENTO DE ENERGIA ELECTRICA CURICO LTDA. | G10: 43266 | H10: 33 | I10: 4110700 | J10: VENTA PPA POTENCIA | K10: 3630 | L10: 241841 | M10: 381.46
A11: SAN_JUAN_LAP | B11: 01-05-2019 | C11: 1 | D11: CEC | E11: BS3 | F11: COOPERATIVA DE ABASTECIMIENTO DE ENERGIA ELECTRICA CURICO LTDA. | G11: 43634 | H11: 33 | I11: 4110700 | J11: VENTA PPA POTENCIA | K11: 6776 | L11: 513609 | M11: 734.23
A12: SAN_JUAN_LAP | B12: 01-06-2018 | C12: 1 | D12: CEC | E12: BS3 | F12: COOPERATIVA DE ABASTECIMIENTO DE ENERGIA ELECTRICA CURICO LTDA. | G12: 43294 | H12: 33 | I12: 4110700 | J12: VENTA PPA POTENCIA | K12: 3770 | L12: 248282 | M12: 383.12
A13: SAN_JUAN_LAP | B13: 01-06-2019 | C13: 1 | D13: CEC | E13: BS3 | F13: COOPERATIVA DE ABASTECIMIENTO DE ENERGIA ELECTRICA CURICO LTDA. | G13: 43658 | H13: 33 | I13: 4110700 | J13: VENTA PPA POTENCIA | K13: 6977 | L13: 519014 | M13: 759.48
... A24: SAN_JUAN_LAP | B24: 01-12-2018 | C24: 1 | D24: CEC | E24: BS3 | F24: COOPERATIVA DE ABASTECIMIENTO DE ENERGIA ELECTRICA CURICO LTDA. | G24: 43486 | H24: 33 | I24: 4110700 | J24: VENTA PPA POTENCIA | K24: 5148 | L24: 239731 | M24: 357.75

Sheet CEN_Energia
A1: Num | B1: MesDevengado | C1: Anho | D1: Mes | E1: Empresa | F1: Propietario | G1: Turno | H1: Distribuidora | I1: Clave | J1: PuntoRetiro | K1: Medida_kWh | L1: PuntoRetiroBT | M1: BarraEnAT | N1: FactorRef_BT_AT | O1: ValorAT | P1: Bloque | Q1: Incremento | R1: kWhAnho | S1: PorcenEnergiaAnho | T1: kWh_AnhoMes | U1: PorcenBarraAnho | V1: EnergiaBloqueAnhoMesBarra_kWh | W1: Amplificacion24h | X1: Denominador | Y1: Prorrata | Z1: EnergiaBloqueTurnoAnhoMesBarra_kWh | AA1: V_DecretoPNPVigente | AB1: V_DecretoPNCPAsociado | AC1: V_DecretoPNCPLicitacion | AD1: V_Barra | AE1: V_PrecioOferta_EnergiaPolpaico220 | AF1: V_Indexacion | AG1: V_PrecioEnergiaIndexado_USDMWh | AH1: V_DolarPNPVigente | AI1: V_FactorAjusteEnergia | AJ1: V_PrecioEnergiaAjustado_CLP_kWh_Polpaico220 | AK1: V_FPEnergia | AL1: V_PrecioEnergiaAjustado_CLP_kWh | AM1: V_PrecioPotenciaUSD_kW_Mes | AN1: V_PrecioPotenciaIndexadoUSD_kW_Mes | AO1: V_FactorAjustePotencia | AP1: V_PrecioPotenciaAjustado_CLP_kW_Mes_Polpaico220 | AQ1: V_FPPotencia | AR1: V_PrecioPotenciaAjustado_CLP_kW_Mes | AS1: V_TotalEnergiaMesBarraGxDxBloque_CLP_kW_Mes | AT1: R_DecretoPNPReliquidacion | AU1: R_DecretoPNCPAsociado | AV1: R_DecretoPNCPLicitacion | AW1: R_Barra | AX1: R_PrecioOfertaEnergiaPolpaico220 | AY1: R_Indexacion | AZ1: R_PrecioEnergiaIndexado_USDMWh | BA1: R_DolarPNPReliquidacion | BB1: R_FactorAjusteEnergia | BC1: R_PrecioEnergiaAjustado_CLP_kWh_Polpaico220 | BD1: R_FPEnergia | BE1: R_PrecioEnergiaAjustado_CLP_kWh | BF1: R_PrecioPotenciaUSD_kW_Mes | BG1: R_FactorAjustePotencia | BH1: R_PrecioPotenciaAjustado_CLP_kW_Mes_Polpaico220 | BI1: R_FPPotencia | BJ1: R_PrecioPotenciaAjustado_CLP_kW_Mes | BK1: R_TotalEnergiaMesBarraGxDxBloque_CLP_kW_Mes
A2: 9 | B2: 01-01-2016 | C2: 2016 | D2: 1 | E2: CAREN | F2: SUM_CEC_C | G2: C | H2: CEC | I2: CCURCURIBLOQC | J2: CURICO | K2: -1412.8211 | L2: CURICO | M2: Charrua | N2: 0.014864421 | O2: 21.000768 | P2: BS1C | Q2: 2 | R2: 31.61594 | S2: 0.104 | T2: 3.2880578 | U2: 0.019 | V2: 62.473 | W2: 2 | X2: 0.0080034575 | Y2: 1 | Z2: 21.000768 | AA2: PNP_1T_05-02-2016 | AB2: PNCP_17T_30-10-2015 | AC2: PNCP_4T_30-04-2013 | AD2: CHARRUA 220 | AE2: 111.133 | AF2: 0.9965617 | AG2: 110.75089 | AH2: 628.50318 | AI2: 1 | AJ2: 69.607287 | AK2: 0.8924 | AL2: 62.118 | AM2: 8.9176 | AN2: 8.8869386 | AO2: 1 | AP2: 5585.4692 | AQ2: 0.9814345 | AR2: 5481.7722 | AS2: 115121.43 | AT2: PNP_1T_05-02-2016 | AU2: PNCP_17T_30-10-2015 | AV2: PNCP_4T_30-04-2013 | AW2: CHARRUA 220 | AX2: 111.133 | AY2: 0.9965617 | AZ2: 110.75089 | BA2: 691.73 | BB2: 1 | BC2: 76.609714 | BD2: 0.8924 | BE2: 68.367 | BF2: 8.9176 | BG2: 1 | BH2: 6147.362 | BI2: 0.9814345 | BJ2: 6033.2332 | BK2: 126702.53
A3: 9 | B3: 01-01-2016 | C3: 2016 | D3: 1 | E3: CAREN | F3: SUM_CEC_C | G3: C | H3: CEC | I3: CCURQUINBLOQC | J3: QUINTA | K3: -317.12643 | L3: QUINTA | M3: Charrua | N3: 0.026818326 | O3: 8.5047999 | P3: BS1C | Q3: 2 | R3: 31.61594 | S3: 0.104 | T3: 3.2880578 | U3: 0.019 | V3: 62.473 | W3: 2 | X3: 0.0080034575 | Y3: 1 | Z3: 8.5048 | AA3: PNP_1T_05-02-2016 | AB3: PNCP_17T_30-10-2015 | AC3: PNCP_4T_30-04-2013 | AD3: CHARRUA 220 | AE3: 111.133 | AF3: 0.9965617 | AG3: 110.75089 | AH3: 628.50318 | AI3: 1 | AJ3: 69.607287 | AK3: 0.8924 | AL3: 62.118 | AM3: 8.9176 | AN3: 8.8869386 | AO3: 1 | AP3: 5585.4692 | AQ3: 0.9814345 | AR3: 5481.7722 | AS3: 46621.376 | AT3: PNP_1T_05-02-2016 | AU3: PNCP_17T_30-10-2015 | AV3: PNCP_4T_30-04-2013 | AW3: CHARRUA 220 | AX3: 111.133 | AY3: 0.9965617 | AZ3: 110.75089 | BA3: 691.73 | BB3: 1 | BC3: 76.609714 | BD3: 0.8924 | BE3: 68.367 | BF3: 8.9176 | BG3: 1 | BH3: 6147.362 | BI3: 0.9814345 | BJ3: 6033.2332 | BK3: 51311.442
A4: 9 | B4: 01-01-2016 | C4: 2016 | D4: 1 | E4: CAREN | F4: SUM_CEC_C | G4: C | H4: CEC | I4: CCURTENOBLOQC | J4: TENO | K4: -586.29806 | L4: TENO | M4: Charrua | N4: 0.026402538 | O4: 15.479757 | P4: BS1C | Q4: 2 | R4: 31.61594 | S4: 0.104 | T4: 3.2880578 | U4: 0.019 | V4: 62.473 | W4: 2 | X4: 0.0080034575 | Y4: 1 | Z4: 15.479757 | AA4: PNP_1T_05-02-2016 | AB4: PNCP_17T_30-10-2015 | AC4: PNCP_4T_30-04-2013 | AD4: CHARRUA 220 | AE4: 111.133 | AF4: 0.9965617 | AG4: 110.75089 | AH4: 628.50318 | AI4: 1 | AJ4: 69.607287 | AK4: 0.8924 | AL4: 62.118 | AM4: 8.9176 | AN4: 8.8869386 | AO4: 1 | AP4: 5585.4692 | AQ4: 0.9814345 | AR4: 5481.7722 | AS4: 84856.502 | AT4: PNP_1T_05-02-2016 | AU4: PNCP_17T_30-10-2015 | AV4: PNCP_4T_30-04-2013 | AW4: CHARRUA 220 | AX4: 111.133 | AY4: 0.9965617 | AZ4: 110.75089 | BA4: 691.73 | BB4: 1 | BC4: 76.609714 | BD4: 0.8924 | BE4: 68.367 | BF4: 8.9176 | BG4: 1 | BH4: 6147.362 | BI4: 0.9814345 | BJ4: 6033.2332 | BK4: 93392.984
A5: 11 | B5: 01-01-2016 | C5: 2016 | D5: 1 | E5: CAREN | F5: SUM_CEC_C | G5: C | H5: CEC | I5: CCURCURIBLOQC | J5: CURICO | K5: -1412.8211 | L5: CURICO | M5: Itahue | N5: 1.0246056 | O5: 1447.5844 | P5: BS1C | Q5: 2 | R5: 31.61594 | S5: 0.104 | T5: 3.2880578 | U5: 0.981 | V5: 3225.585 | W5: 2 | X5: 0.00015501064 | Y5: 1 | Z5: 1447.5844 | AA5: PNP_1T_05-02-2016 | AB5: PNCP_17T_30-10-2015 | AC5: PNCP_4T_30-04-2013 | AD5: ITAHUE 220 | AE5: 111.133 | AF5: 0.9965617 | AG5: 110.75089 | AH5: 628.50318 | AI5: 1 | AJ5: 69.607287 | AK5: 1.008 | AL5: 70.164 | AM5: 8.9176 | AN5: 8.8869386 | AO5: 1 | AP5: 5585.4692 | AQ5: 1.0131255 | AR5: 5658.7813 | AS5: 8191563.4 | AT5: PNP_1T_05-02-2016 | AU5: PNCP_17T_30-10-2015 | AV5: PNCP_4T_30-04-2013 | AW5: ITAHUE 220 | AX5: 111.133 | AY5: 0.9965617 | AZ5: 110.75089 | BA5: 691.73 | BB5: 1 | BC5: 76.609714 | BD5: 1.008 | BE5: 77.223 | BF5: 8.9176 | BG5: 1 | BH5: 6147.362 | BI5: 1.0131255 | BJ5: 6228.0493 | BK5: 9015626.8
A6: 11 | B6: 01-01-2016 | C6: 2016 | D6: 1 | E6: CAREN | F6: SUM_CEC_C | G6: C | H6: CEC | I6: CCURQUINBLOQC | J6: QUINTA | K6: -317.12643 | L6: QUINTA | M6: Itahue | N6: 1.0126517 | O6: 321.13861 | P6: BS1C | Q6: 2 | R6: 31.61594 | S6: 0.104 | T6: 3.2880578 | U6: 0.981 | V6: 3225.585 | W6: 2 | X6: 0.00015501064 | Y6: 1 | Z6: 321.13861 | AA6: PNP_1T_05-02-2016 | AB6: PNCP_17T_30-10-2015 | AC6: PNCP_4T_30-04-2013 | AD6: ITAHUE 220 | AE6: 111.133 | AF6: 0.9965617 | AG6: 110.75089 | AH6: 628.50318 | AI6: 1 | AJ6: 69.607287 | AK6: 1.008 | AL6: 70.164 | AM6: 8.9176 | AN6: 8.8869386 | AO6: 1 | AP6: 5585.4692 | AQ6: 1.0131255 | AR6: 5658.7813 | AS6: 1817253.1 | AT6: PNP_1T_05-02-2016 | AU6: PNCP_17T_30-10-2015 | AV6: PNCP_4T_30-04-2013 | AW6: ITAHUE 220 | AX6: 111.133 | AY6: 0.9965617 | AZ6: 110.75089 | BA6: 691.73 | BB6: 1 | BC6: 76.609714 | BD6: 1.008 | BE6: 77.223 | BF6: 8.9176 | BG6: 1 | BH6: 6147.362 | BI6: 1.0131255 | BJ6: 6228.0493 | BK6: 2000067.1
A7: 11 | B7: 01-01-2016 | C7: 2016 | D7: 1 | E7: CAREN | F7: SUM_CEC_C | G7: C | H7: CEC | I7: CCURTENOBLOQC | J7: TENO | K7: -586.29806 | L7: TENO | M7: Itahue | N7: 1.0130675 | O7: 593.95949 | P7: BS1C | Q7: 2 | R7: 31.61594 | S7: 0.104 | T7: 3.2880578 | U7: 0.981 | V7: 3225.585 | W7: 2 | X7: 0.00015501064 | Y7: 1 | Z7: 593.95949 | AA7: PNP_1T_05-02-2016 | AB7: PNCP_17T_30-10-2015 | AC7: PNCP_4T_30-04-2013 | AD7: ITAHUE 220 | AE7: 111.133 | AF7: 0.9965617 | AG7: 110.75089 | AH7: 628.50318 | AI7: 1 | AJ7: 69.607287 | AK7: 1.008 | AL7: 70.164 | AM7: 8.9176 | AN7: 8.8869386 | AO7: 1 | AP7: 5585.4692 | AQ7: 1.0131255 | AR7: 5658.7813 | AS7: 3361086.8 | AT7: PNP_1T_05-02-2016 | AU7: PNCP_17T_30-10-2015 | AV7: PNCP_4T_30-04-2013 | AW7: ITAHUE 220 | AX7: 111.133 | AY7: 0.9965617 | AZ7: 110.75089 | BA7: 691.73 | BB7: 1 | BC7: 76.609714 | BD7: 1.008 | BE7: 77.223 | BF7: 8.9176 | BG7: 1 | BH7: 6147.362 | BI7: 1.0131255 | BJ7: 6228.0493 | BK7: 3699209
A8: 21 | B8: 01-02-2016 | C8: 2016 | D8: 2 | E8: CAREN | F8: SUM_CEC_C | G8: C | H8: CEC | I8: CCURCURIBLOQC | J8: CURICO | K8: -1839.3539 | L8: CURICO | M8: Charrua | N8: 0.014864421 | O8: 27.34093 | P8: BS1C | Q8: 2 | R8: 31.61594 | S8: 0.106 | T8: 3.3512896 | U8: 0.019 | V8: 63.675 | W8: 2 | X8: 0.0078523753 | Y8: 1 | Z8: 27.34093 | AA8: PNP_1T_05-02-2016 | AB8: PNCP_17T_30-10-2015 | AC8: PNCP_4T_30-04-2013 | AD8: CHARRUA 220 | AE8: 111.133 | AF8: 0.9965617 | AG8: 110.75089 | AH8: 691.73 | AI8: 1 | AJ8: 76.609714 | AK8: 0.8924 | AL8: 68.367 | AM8: 8.9176 | AN8: 8.8869386 | AO8: 1 | AP8: 6147.362 | AQ8: 0.9814345 | AR8: 6033.2332 | AS8: 164954.21 | AT8: PNP_1T_05-02-2016 | AU8: PNCP_17T_30-10-2015 | AV8: PNCP_4T_30-04-2013 | AW8: CHARRUA 220 | AX8: 111.133 | AY8: 0.9965617 | AZ8: 110.75089 | BA8: 691.73 | BB8: 1 | BC8: 76.609714 | BD8: 0.8924 | BE8: 68.367 | BF8: 8.9176 | BG8: 1 | BH8: 6147.362 | BI8: 0.9814345 | BJ8: 6033.2332 | BK8: 164954.21
A9: 21 | B9: 01-02-2016 | C9: 2016 | D9: 2 | E9: CAREN | F9: SUM_CEC_C | G9: C | H9: CEC | I9: CCURQUINBLOQC | J9: QUINTA | K9: -439.07082 | L9: QUINTA | M9: Charrua | N9: 0.026818326 | O9: 11.775144 | P9: BS1C | Q9: 2 | R9: 31.61594 | S9: 0.106 | T9: 3.3512896 | U9: 0.019 | V9: 63.675 | W9: 2 | X9: 0.0078523753 | Y9: 1 | Z9: 11.775144 | AA9: PNP_1T_05-02-2016 | AB9: PNCP_17T_30-10-2015 | AC9: PNCP_4T_30-04-2013 | AD9: CHARRUA 220 | AE9: 111.133 | AF9: 0.9965617 | AG9: 110.75089 | AH9: 691.73 | AI9: 1 | AJ9: 76.609714 | AK9: 0.8924 | AL9: 68.367 | AM9: 8.9176 | AN9: 8.8869386 | AO9: 1 | AP9: 6147.362 | AQ9: 0.9814345 | AR9: 6033.2332 | AS9: 71042.19 | AT9: PNP_1T_05-02-2016 | AU9: PNCP_17T_30-10-2015 | AV9: PNCP_4T_30-04-2013 | AW9: CHARRUA 220 | AX9: 111.133 | AY9: 0.9965617 | AZ9: 110.75089 | BA9: 691.73 | BB9: 1 | BC9: 76.609714 | BD9: 0.8924 | BE9: 68.367 | BF9: 8.9176 | BG9: 1 | BH9: 6147.362 | BI9: 0.9814345 | BJ9: 6033.2332 | BK9: 71042.19
A10: 21 | B10: 01-02-2016 | C10: 2016 | D10: 2 | E10: CAREN | F10: SUM_CEC_C | G10: C | H10: CEC | I10: CCURTENOBLOQC | J10: TENO | K10: -685.92496 | L10: TENO | M10: Charrua | N10: 0.026402538 | O10: 18.11016 | P10: BS1C | Q10: 2 | R10: 31.61594 | S10: 0.106 | T10: 3.3512896 | U10: 0.019 | V10: 63.675 | W10: 2 | X10: 0.0078523753 | Y10: 1 | Z10: 18.11016 | AA10: PNP_1T_05-02-2016 | AB10: PNCP_17T_30-10-2015 | AC10: PNCP_4T_30-04-2013 | AD10: CHARRUA 220 | AE10: 111.133 | AF10: 0.9965617 | AG10: 110.75089 | AH10: 691.73 | AI10: 1 | AJ10: 76.609714 | AK10: 0.8924 | AL10: 68.367 | AM10: 8.9176 | AN10: 8.8869386 | AO10: 1 | AP10: 6147.362 | AQ10: 0.9814345 | AR10: 6033.2332 | AS10: 109262.82 | AT10: PNP_1T_05-02-2016 | AU10: PNCP_17T_30-10-2015 | AV10: PNCP_4T_30-04-2013 | AW10: CHARRUA 220 | AX10: 111.133 | AY10: 0.9965617 | AZ10: 110.75089 | BA10: 691.73 | BB10: 1 | BC10: 76.609714 | BD10: 0.8924 | BE10: 68.367 | BF10: 8.9176 | BG10: 1 | BH10: 6147.362 | BI10: 0.9814345 | BJ10: 6033.2332 | BK10: 109262.82
A11: 23 | B11: 01-02-2016 | C11: 2016 | D11: 2 | E11: CAREN | F11: SUM_CEC_C | G11: C | H11: CEC | I11: CCURCURIBLOQC | J11: CURICO | K11: -1839.3539 | L11: CURICO | M11: Itahue | N11: 1.0246056 | O11: 1884.6122 | P11: BS1C | Q11: 2 | R11: 31.61594 | S11: 0.106 | T11: 3.3512896 | U11: 0.981 | V11: 3287.615 | W11: 2 | X11: 0.00015208593 | Y11: 1 | Z11: 1884.6122 | AA11: PNP_1T_05-02-2016 | AB11: PNCP_17T_30-10-2015 | AC11: PNCP_4T_30-04-2013 | AD11: ITAHUE 220 | AE11: 111.133 | AF11: 0.9965617 | AG11: 110.75089 | AH11: 691.73 | AI11: 1 | AJ11: 76.609714 | AK11: 1.008 | AL11: 77.223 | AM11: 8.9176 | AN11: 8.8869386 | AO11: 1 | AP11: 6147.362 | AQ11: 1.0131255 | AR11: 6228.0493 | AS11: 11737458 | AT11: PNP_1T_05-02-2016 | AU11: PNCP_17T_30-10-2015 | AV11: PNCP_4T_30-04-2013 | AW11: ITAHUE 220 | AX11: 111.133 | AY11: 0.9965617 | AZ11: 110.75089 | BA11: 691.73 | BB11: 1 | BC11: 76.609714 | BD11: 1.008 | BE11: 77.223 | BF11: 8.9176 | BG11: 1 | BH11: 6147.362 | BI11: 1.0131255 | BJ11: 6228.0493 | BK11: 11737458
A12: 23 | B12: 01-02-2016 | C12: 2016 | D12: 2 | E12: CAREN | F12: SUM_CEC_C | G12: C | H12: CEC | I12: CCURQUINBLOQC | J12: QUINTA | K12: -439.07082 | L12: QUINTA | M12: Itahue | N12: 1.0126517 | O12: 444.6258 | P12: BS1C | Q12: 2 | R12: 31.61594 | S12: 0.106 | T12: 3.3512896 | U12: 0.981 | V12: 3287.615 | W12: 2 | X12: 0.00015208593 | Y12: 1 | Z12: 444.6258 | AA12: PNP_1T_05-02-2016 | AB12: PNCP_17T_30-10-2015 | AC12: PNCP_4T_30-04-2013 | AD12: ITAHUE 220 | AE12: 111.133 | AF12: 0.9965617 | AG12: 110.75089 | AH12: 691.73 | AI12: 1 | AJ12: 76.609714 | AK12: 1.008 | AL12: 77.223 | AM12: 8.9176 | AN12: 8.8869386 | AO12: 1 | AP12: 6147.362 | AQ12: 1.0131255 | AR12: 6228.0493 | AS12: 2769151.4 | AT12: PNP_1T_05-02-2016 | AU12: PNCP_17T_30-10-2015 | AV12: PNCP_4T_30-04-2013 | AW12: ITAHUE 220 | AX12: 111.133 | AY12: 0.9965617 | AZ12: 110.75089 | BA12: 691.73 | BB12: 1 | BC12: 76.609714 | BD12: 1.008 | BE12: 77.223 | BF12: 8.9176 | BG12: 1 | BH12: 6147.362 | BI12: 1.0131255 | BJ12: 6228.0493 | BK12: 2769151.4
A13: 23 | B13: 01-02-2016 | C13: 2016 | D13: 2 | E13: CAREN | F13: SUM_CEC_C | G13: C | H13: CEC | I13: CCURTENOBLOQC | J13: TENO | K13: -685.92496 | L13: TENO | M13: Itahue | N13: 1.0130675 | O13: 694.88826 | P13: BS1C | Q13: 2 | R13: 31.61594 | S13: 0.106 | T13: 3.3512896 | U13: 0.981 | V13: 3287.615 | W13: 2 | X13: 0.00015208593 | Y13: 1 | Z13: 694.88826 | AA13: PNP_1T_05-02-2016 | AB13: PNCP_17T_30-10-2015 | AC13: PNCP_4T_30-04-2013 | AD13: ITAHUE 220 | AE13: 111.133 | AF13: 0.9965617 | AG13: 110.75089 | AH13: 691.73 | AI13: 1 | AJ13: 76.609714 | AK13: 1.008 | AL13: 77.223 | AM13: 8.9176 | AN13: 8.8869386 | AO13: 1 | AP13: 6147.362 | AQ13: 1.0131255 | AR13: 6228.0493 | AS13: 4327798.3 | AT13: PNP_1T_05-02-2016 | AU13: PNCP_17T_30-10-2015 | AV13: PNCP_4T_30-04-2013 | AW13: ITAHUE 220 | AX13: 111.133 | AY13: 0.9965617 | AZ13: 110.75089 | BA13: 691.73 | BB13: 1 | BC13: 76.609714 | BD13: 1.008 | BE13: 77.223 | BF13: 8.9176 | BG13: 1 | BH13: 6147.362 | BI13: 1.0131255 | BJ13: 6228.0493 | BK13: 4327798.3
... A343: 1107 | B343: 01-09-2020 | C343: 2020 | D343: 9 | E343: CAREN | F343: SUM_CEC_C | G343: C | H343: CEC | I343: CCURTENOBLOQC | J343: TENO | K343: -1910.2344 | L343: TENO | M343: ITAHUE | N343: 0.55635924 | O343: 1062.7766 | P343: BS1C | Q343: 2 | R343: 47.63659 | S343: 0.047 | T343: 2.2389197 | U343: 0.981 | V343: 2196.38 | W343: 2 | X343: 3.252104e-05 | Y343: 0.142857 | Z343: 151.82507 | AA343: PNP_20T_13-12-2018 | AB343: PNCP_12T_24-08-2018 | AC343: PNCP_4T_30-04-2013 | AD343: ITAHUE 220 | AE343: 111.133 | AF343: 1.0541007 | AG343: 117.14538 | AH343: 640.82 | AI343: 1 | AJ343: 75.069101 | AK343: 0.9589 | AL343: 71.984 | AM343: 8.9176 | AN343: 9.4000488 | AO343: 1 | AP343: 6023.7393 | AQ343: 0.99097621 | AR343: 5969.3823 | AS343: 906301.89 | AT343: PNP_16T_02-11-2020 | AU343: PNCP_2T_10-02-2020 | AV343: PNCP_4T_30-04-2013 | AW343: ITAHUE 220 | AX343: 111.133 | AY343: 1.0808212 | AZ343: 120.1149 | BA343: 779.31 | BB343: 0.879 | BC343: 82.280325 | BD343: 0.9327 | BE343: 76.743 | BF343: 8.9176 | BG343: 0.804 | BH343: 6039.043 | BI343: 1.0164069 | BJ343: 6138.1249 | BK343: 931921.24

Sheet CEN_Potencia
A1: Num | B1: MesDevengado | C1: Anho | D1: Mes | E1: Empresa | F1: Cliente | G1: Distribuidora | H1: BarraBT | I1: Turno | J1: PotenciaConsumo_kW | K1: BloqueCompleto | L1: BarraEnAT | M1: FactorRefPotencia_BT_AT | N1: Potencia_kW_AT | O1: MaxPPA | P1: Denominador | Q1: Prorrata | R1: PotenciaBloqueTurnoAnhoMesBarra_kW | S1: V_DecretoPNPVigente | T1: V_DecretoPNCPAsociado | U1: V_DecretoPNCPLicitacion | V1: V_Barra | W1: V_PrecioOferta_EnergiaPolpaico220 | X1: V_Indexacion | Y1: V_PrecioEnergiaIndexado_USDMWh | Z1: V_DolarPNPVigente | AA1: V_FactorAjusteEnergia | AB1: V_PrecioEnergiaAjustado_CLP_kWh_Polpaico220 | AC1: V_FPEnergia | AD1: V_PrecioEnergiaAjustado_CLP_kWh | AE1: V_PrecioPotenciaUSD_kW_Mes | AF1: V_PrecioPotenciaIndexadoUSD_kW_Mes | AG1: V_FactorAjustePotencia | AH1: V_PrecioPotenciaAjustado_CLP_kW_Mes_Polpaico220 | AI1: V_FPPotencia | AJ1: V_PrecioPotenciaAjustado_CLP_kW_Mes | AK1: V_TotalPotenciaMesBarraGxDxBloque_CLP_kW_Mes | AL1: R_DecretoPNPReliquidacion | AM1: R_DecretoPNCPAsociado | AN1: R_DecretoPNCPLicitacion | AO1: R_Barra | AP1: R_PrecioOfertaEnergiaPolpaico220 | AQ1: R_Indexacion | AR1: R_PrecioEnergiaIndexado_USDMWh | AS1: R_DolarPNPReliquidacion | AT1: R_FactorAjusteEnergia | AU1: R_PrecioEnergiaAjustado_CLP_kWh_Polpaico220 | AV1: R_FPEnergia | AW1: R_PrecioEnergiaAjustado_CLP_kWh | AX1: R_PrecioPotenciaUSD_kW_Mes | AY1: R_FactorAjustePotencia | AZ1: R_PrecioPotenciaAjustado_CLP_kW_Mes_Polpaico220 | BA1: R_FPPotencia | BB1: R_PrecioPotenciaAjustado_CLP_kW_Mes | BC1: R_TotalPotenciaMesBarraGxDxBloque_CLP_kW_Mes
A2: 2521 | B2: 01-04-2016 | C2: 2016 | D2: 4 | E2: Caren | F2: SUM_CEC | G2: CEC | H2: CURICO | I2: C | J2: -4.6399156 | K2: BS1C | L2: ALTO JAHUEL | M2: 0.15011158 | N2: 0.69650506 | O2: 31615.94 | P2: 1.5814807e-05 | Q2: 1 | R2: 0.69650506 | S2: PNP_1T_05-02-2016 | T2: PNCP_17T_30-10-2015 | U2: PNCP_4T_30-04-2013 | V2: ALTO JAHUEL 220 | W2: 111.133 | X2: 0.9965617 | Y2: 110.75089 | Z2: 691.73 | AA2: 1 | AB2: 76.609714 | AC2: 1.0244 | AD2: 78.479 | AE2: 8.9176 | AF2: 8.8869386 | AG2: 1 | AH2: 6147.362 | AI2: 1.0034719 | AJ2: 6168.7049 | AK2: 4296.5342 | AL2: PNP_1T_05-02-2016 | AM2: PNCP_17T_30-10-2015 | AN2: PNCP_4T_30-04-2013 | AO2: ALTO JAHUEL 220 | AP2: 111.133 | AQ2: 0.9965617 | AR2: 110.75089 | AS2: 691.73 | AT2: 1 | AU2: 76.609714 | AV2: 1.0244 | AW2: 78.479 | AX2: 8.9176 | AY2: 1 | AZ2: 6147.362 | BA2: 1.0034719 | BB2: 6168.7049 | BC2: 4296.5342
A3: 2522 | B3: 01-04-2016 | C3: 2016 | D3: 4 | E3: Caren | F3: SUM_CEC | G3: CEC | H3: CURICO | I3: C | J3: -4.6399156 | K3: BS1C | L3: CHARRUA | M3: 0.045811354 | N3: 0.21256082 | O3: 31615.94 | P3: 1.5814807e-05 | Q3: 1 | R3: 0.21256082 | S3: PNP_1T_05-02-2016 | T3: PNCP_17T_30-10-2015 | U3: PNCP_4T_30-04-2013 | V3: CHARRUA 220 | W3: 111.133 | X3: 0.9965617 | Y3: 110.75089 | Z3: 691.73 | AA3: 1 | AB3: 76.609714 | AC3: 0.8924 | AD3: 68.367 | AE3: 8.9176 | AF3: 8.8869386 | AG3: 1 | AH3: 6147.362 | AI3: 0.9814345 | AJ3: 6033.2332 | AK3: 1282.429 | AL3: PNP_1T_05-02-2016 | AM3: PNCP_17T_30-10-2015 | AN3: PNCP_4T_30-04-2013 | AO3: CHARRUA 220 | AP3: 111.133 | AQ3: 0.9965617 | AR3: 110.75089 | AS3: 691.73 | AT3: 1 | AU3: 76.609714 | AV3: 0.8924 | AW3: 68.367 | AX3: 8.9176 | AY3: 1 | AZ3: 6147.362 | BA3: 0.9814345 | BB3: 6033.2332 | BC3: 1282.429
A4: 2523 | B4: 01-04-2016 | C4: 2016 | D4: 4 | E4: Caren | F4: SUM_CEC | G4: CEC | H4: CURICO | I4: C | J4: -4.6399156 | K4: BS1C | L4: ITAHUE | M4: 0.43232641 | N4: 2.0059581 | O4: 31615.94 | P4: 1.5814807e-05 | Q4: 1 | R4: 2.0059581 | S4: PNP_1T_05-02-2016 | T4: PNCP_17T_30-10-2015 | U4: PNCP_4T_30-04-2013 | V4: ITAHUE 220 | W4: 111.133 | X4: 0.9965617 | Y4: 110.75089 | Z4: 691.73 | AA4: 1 | AB4: 76.609714 | AC4: 1.008 | AD4: 77.223 | AE4: 8.9176 | AF4: 8.8869386 | AG4: 1 | AH4: 6147.362 | AI4: 1.0131255 | AJ4: 6228.0493 | AK4: 12493.206 | AL4: PNP_1T_05-02-2016 | AM4: PNCP_17T_30-10-2015 | AN4: PNCP_4T_30-04-2013 | AO4: ITAHUE 220 | AP4: 111.133 | AQ4: 0.9965617 | AR4: 110.75089 | AS4: 691.73 | AT4: 1 | AU4: 76.609714 | AV4: 1.008 | AW4: 77.223 | AX4: 8.9176 | AY4: 1 | AZ4: 6147.362 | BA4: 1.0131255 | BB4: 6228.0493 | BC4: 12493.206
A5: 2524 | B5: 01-04-2016 | C5: 2016 | D5: 4 | E5: Caren | F5: SUM_CEC | G5: CEC | H5: CURICO | I5: C | J5: -4.6399156 | K5: BS1C | L5: MELIPILLA | M5: 0.0016825116 | N5: 0.0078067117 | O5: 31615.94 | P5: 1.5814807e-05 | Q5: 1 | R5: 0.0078067117 | S5: PNP_1T_05-02-2016 | T5: PNCP_17T_30-10-2015 | U5: PNCP_4T_30-04-2013 | V5: MELIPILLA 220 | W5: 111.133 | X5: 0.9965617 | Y5: 110.75089 | Z5: 691.73 | AA5: 1 | AB5: 76.609714 | AC5: 1.0369 | AD5: 79.437 | AE5: 8.9176 | AF5: 8.8869386 | AG5: 1 | AH5: 6147.362 | AI5: 0.98272159 | AJ5: 6041.1454 | AK5: 47.161481 | AL5: PNP_1T_05-02-2016 | AM5: PNCP_17T_30-10-2015 | AN5: PNCP_4T_30-04-2013 | AO5: MELIPILLA 220 | AP5: 111.133 | AQ5: 0.9965617 | AR5: 110.75089 | AS5: 691.73 | AT5: 1 | AU5: 76.609714 | AV5: 1.0369 | AW5: 79.437 | AX5: 8.9176 | AY5: 1 | AZ5: 6147.362 | BA5: 0.98272159 | BB5: 6041.1454 | BC5: 47.161481
A6: 2525 | B6: 01-04-2016 | C6: 2016 | D6: 4 | E6: Caren | F6: SUM_CEC | G6: CEC | H6: CURICO | I6: C | J6: -4.6399156 | K6: BS1C | L6: RAPEL | M6: 0.0015368216 | N6: 0.0071307226 | O6: 31615.94 | P6: 1.5814807e-05 | Q6: 1 | R6: 0.0071307226 | S6: PNP_1T_05-02-2016 | T6: PNCP_17T_30-10-2015 | U6: PNCP_4T_30-04-2013 | V6: RAPEL 220 | W6: 111.133 | X6: 0.9965617 | Y6: 110.75089 | Z6: 691.73 | AA6: 1 | AB6: 76.609714 | AC6: 1.0342 | AD6: 79.23 | AE6: 8.9176 | AF6: 8.8869386 | AG6: 1 | AH6: 6147.362 | AI6: 0.98050797 | AJ6: 6027.5375 | AK6: 42.980698 | AL6: PNP_1T_05-02-2016 | AM6: PNCP_17T_30-10-2015 | AN6: PNCP_4T_30-04-2013 | AO6: RAPEL 220 | AP6: 111.133 | AQ6: 0.9965617 | AR6: 110.75089 | AS6: 691.73 | AT6: 1 | AU6: 76.609714 | AV6: 1.0342 | AW6: 79.23 | AX6: 8.9176 | AY6: 1 | AZ6: 6147.362 | BA6: 0.98050797 | BB6: 6027.5375 | BC6: 42.980698
A7: 2526 | B7: 01-04-2016 | C7: 2016 | D7: 4 | E7: Caren | F7: SUM_CEC | G7: CEC | H7: QUINTA | I7: C | J7: -0.9543722 | K7: BS1C | L7: ALTO JAHUEL | M7: 0.26601384 | N7: 0.25387621 | O7: 31615.94 | P7: 1.5814807e-05 | Q7: 1 | R7: 0.25387621 | S7: PNP_1T_05-02-2016 | T7: PNCP_17T_30-10-2015 | U7: PNCP_4T_30-04-2013 | V7: ALTO JAHUEL 220 | W7: 111.133 | X7: 0.9965617 | Y7: 110.75089 | Z7: 691.73 | AA7: 1 | AB7: 76.609714 | AC7: 1.0244 | AD7: 78.479 | AE7: 8.9176 | AF7: 8.8869386 | AG7: 1 | AH7: 6147.362 | AI7: 1.0034719 | AJ7: 6168.7049 | AK7: 1566.0874 | AL7: PNP_1T_05-02-2016 | AM7: PNCP_17T_30-10-2015 | AN7: PNCP_4T_30-04-2013 | AO7: ALTO JAHUEL 220 | AP7: 111.133 | AQ7: 0.9965617 | AR7: 110.75089 | AS7: 691.73 | AT7: 1 | AU7: 76.609714 | AV7: 1.0244 | AW7: 78.479 | AX7: 8.9176 | AY7: 1 | AZ7: 6147.362 | BA7: 1.0034719 | BB7: 6168.7049 | BC7: 1566.0874
A8: 2527 | B8: 01-04-2016 | C8: 2016 | D8: 4 | E8: Caren | F8: SUM_CEC | G8: CEC | H8: QUINTA | I8: C | J8: -0.9543722 | K8: BS1C | L8: CHARRUA | M8: 0.03950956 | N8: 0.037706826 | O8: 31615.94 | P8: 1.5814807e-05 | Q8: 1 | R8: 0.037706826 | S8: PNP_1T_05-02-2016 | T8: PNCP_17T_30-10-2015 | U8: PNCP_4T_30-04-2013 | V8: CHARRUA 220 | W8: 111.133 | X8: 0.9965617 | Y8: 110.75089 | Z8: 691.73 | AA8: 1 | AB8: 76.609714 | AC8: 0.8924 | AD8: 68.367 | AE8: 8.9176 | AF8: 8.8869386 | AG8: 1 | AH8: 6147.362 | AI8: 0.9814345 | AJ8: 6033.2332 | AK8: 227.49407 | AL8: PNP_1T_05-02-2016 | AM8: PNCP_17T_30-10-2015 | AN8: PNCP_4T_30-04-2013 | AO8: CHARRUA 220 | AP8: 111.133 | AQ8: 0.9965617 | AR8: 110.75089 | AS8: 691.73 | AT8: 1 | AU8: 76.609714 | AV8: 0.8924 | AW8: 68.367 | AX8: 8.9176 | AY8: 1 | AZ8: 6147.362 | BA8: 0.9814345 | BB8: 6033.2332 | BC8: 227.49407
A9: 2528 | B9: 01-04-2016 | C9: 2016 | D9: 4 | E9: Caren | F9: SUM_CEC | G9: CEC | H9: QUINTA | I9: C | J9: -0.9543722 | K9: BS1C | L9: ITAHUE | M9: 0.39737543 | N9: 0.37924406 | O9: 31615.94 | P9: 1.5814807e-05 | Q9: 1 | R9: 0.37924406 | S9: PNP_1T_05-02-2016 | T9: PNCP_17T_30-10-2015 | U9: PNCP_4T_30-04-2013 | V9: ITAHUE 220 | W9: 111.133 | X9: 0.9965617 | Y9: 110.75089 | Z9: 691.73 | AA9: 1 | AB9: 76.609714 | AC9: 1.008 | AD9: 77.223 | AE9: 8.9176 | AF9: 8.8869386 | AG9: 1 | AH9: 6147.362 | AI9: 1.0131255 | AJ9: 6228.0493 | AK9: 2361.9507 | AL9: PNP_1T_05-02-2016 | AM9: PNCP_17T_30-10-2015 | AN9: PNCP_4T_30-04-2013 | AO9: ITAHUE 220 | AP9: 111.133 | AQ9: 0.9965617 | AR9: 110.75089 | AS9: 691.73 | AT9: 1 | AU9: 76.609714 | AV9: 1.008 | AW9: 77.223 | AX9: 8.9176 | AY9: 1 | AZ9: 6147.362 | BA9: 1.0131255 | BB9: 6228.0493 | BC9: 2361.9507
A10: 2529 | B10: 01-04-2016 | C10: 2016 | D10: 4 | E10: Caren | F10: SUM_CEC | G10: CEC | H10: QUINTA | I10: C | J10: -0.9543722 | K10: BS1C | L10: RAPEL | M10: 0.00084248021 | N10: 0.00080403969 | O10: 31615.94 | P10: 1.5814807e-05 | Q10: 1 | R10: 0.00080403969 | S10: PNP_1T_05-02-2016 | T10: PNCP_17T_30-10-2015 | U10: PNCP_4T_30-04-2013 | V10: RAPEL 220 | W10: 111.133 | X10: 0.9965617 | Y10: 110.75089 | Z10: 691.73 | AA10: 1 | AB10: 76.609714 | AC10: 1.0342 | AD10: 79.23 | AE10: 8.9176 | AF10: 8.8869386 | AG10: 1 | AH10: 6147.362 | AI10: 0.98050797 | AJ10: 6027.5375 | AK10: 4.8463794 | AL10: PNP_1T_05-02-2016 | AM10: PNCP_17T_30-10-2015 | AN10: PNCP_4T_30-04-2013 | AO10: RAPEL 220 | AP10: 111.133 | AQ10: 0.9965617 | AR10: 110.75089 | AS10: 691.73 | AT10: 1 | AU10: 76.609714 | AV10: 1.0342 | AW10: 79.23 | AX10: 8.9176 | AY10: 1 | AZ10: 6147.362 | BA10: 0.98050797 | BB10: 6027.5375 | BC10: 4.8463794
A11: 2530 | B11: 01-04-2016 | C11: 2016 | D11: 4 | E11: Caren | F11: SUM_CEC | G11: CEC | H11: TENO | I11: C | J11: -2.7798719 | K11: BS1C | L11: ALTO JAHUEL | M11: 0.1593171 | N11: 0.44288112 | O11: 31615.94 | P11: 1.5814807e-05 | Q11: 1 | R11: 0.44288112 | S11: PNP_1T_05-02-2016 | T11: PNCP_17T_30-10-2015 | U11: PNCP_4T_30-04-2013 | V11: ALTO JAHUEL 220 | W11: 111.133 | X11: 0.9965617 | Y11: 110.75089 | Z11: 691.73 | AA11: 1 | AB11: 76.609714 | AC11: 1.0244 | AD11: 78.479 | AE11: 8.9176 | AF11: 8.8869386 | AG11: 1 | AH11: 6147.362 | AI11: 1.0034719 | AJ11: 6168.7049 | AK11: 2732.0029 | AL11: PNP_1T_05-02-2016 | AM11: PNCP_17T_30-10-2015 | AN11: PNCP_4T_30-04-2013 | AO11: ALTO JAHUEL 220 | AP11: 111.133 | AQ11: 0.9965617 | AR11: 110.75089 | AS11: 691.73 | AT11: 1 | AU11: 76.609714 | AV11: 1.0244 | AW11: 78.479 | AX11: 8.9176 | AY11: 1 | AZ11: 6147.362 | BA11: 1.0034719 | BB11: 6168.7049 | BC11: 2732.0029
A12: 2531 | B12: 01-04-2016 | C12: 2016 | D12: 4 | E12: Caren | F12: SUM_CEC | G12: CEC | H12: TENO | I12: C | J12: -2.7798719 | K12: BS1C | L12: CHARRUA | M12: 0.041785184 | N12: 0.11615746 | O12: 31615.94 | P12: 1.5814807e-05 | Q12: 1 | R12: 0.11615746 | S12: PNP_1T_05-02-2016 | T12: PNCP_17T_30-10-2015 | U12: PNCP_4T_30-04-2013 | V12: CHARRUA 220 | W12: 111.133 | X12: 0.9965617 | Y12: 110.75089 | Z12: 691.73 | AA12: 1 | AB12: 76.609714 | AC12: 0.8924 | AD12: 68.367 | AE12: 8.9176 | AF12: 8.8869386 | AG12: 1 | AH12: 6147.362 | AI12: 0.9814345 | AJ12: 6033.2332 | AK12: 700.80503 | AL12: PNP_1T_05-02-2016 | AM12: PNCP_17T_30-10-2015 | AN12: PNCP_4T_30-04-2013 | AO12: CHARRUA 220 | AP12: 111.133 | AQ12: 0.9965617 | AR12: 110.75089 | AS12: 691.73 | AT12: 1 | AU12: 76.609714 | AV12: 0.8924 | AW12: 68.367 | AX12: 8.9176 | AY12: 1 | AZ12: 6147.362 | BA12: 0.9814345 | BB12: 6033.2332 | BC12: 700.80503
A13: 2532 | B13: 01-04-2016 | C13: 2016 | D13: 4 | E13: Caren | F13: SUM_CEC | G13: CEC | H13: TENO | I13: C | J13: -2.7798719 | K13: BS1C | L13: ITAHUE | M13: 0.43497567 | N13: 1.2091767 | O13: 31615.94 | P13: 1.5814807e-05 | Q13: 1 | R13: 1.2091767 | S13: PNP_1T_05-02-2016 | T13: PNCP_17T_30-10-2015 | U13: PNCP_4T_30-04-2013 | V13: ITAHUE 220 | W13: 111.133 | X13: 0.9965617 | Y13: 110.75089 | Z13: 691.73 | AA13: 1 | AB13: 76.609714 | AC13: 1.008 | AD13: 77.223 | AE13: 8.9176 | AF13: 8.8869386 | AG13: 1 | AH13: 6147.362 | AI13: 1.0131255 | AJ13: 6228.0493 | AK13: 7530.8118 | AL13: PNP_1T_05-02-2016 | AM13: PNCP_17T_30-10-2015 | AN13: PNCP_4T_30-04-2013 | AO13: ITAHUE 220 | AP13: 111.133 | AQ13: 0.9965617 | AR13: 110.75089 | AS13: 691.73 | AT13: 1 | AU13: 76.609714 | AV13: 1.008 | AW13: 77.223 | AX13: 8.9176 | AY13: 1 | AZ13: 6147.362 | BA13: 1.0131255 | BB13: 6228.0493 | BC13: 7530.8118
... A785: 274537 | B785: 01-12-2020 | C785: 2020 | D785: 12 | E785: CAREN | F785: SUM_CEC_C | G785: CEC | H785: TENO | I785: C | J785: -17.390263 | K785: BS1C | L785: RAPEL | M785: 0.0014858046 | N785: 0.025838532 | O785: 47588.953 | P785: 1.500949e-06 | Q785: 0.142857 | R785: 0.0036912152 | S785: PNP_6T_08-05-2020 | T785: PNCP_9T_12-08-2019 | U785: PNCP_4T_30-04-2013 | V785: RAPEL 220 | W785: 111.133 | X785: 1.072776 | Y785: 119.22082 | Z785: 694.38 | AA785: 0.875 | AB785: 72.436483 | AC785: 0.9925 | AD785: 71.893 | AE785: 8.9176 | AF785: 9.5665875 | AG785: 0.913 | AH785: 6064.9194 | AI785: 0.93847214 | AJ785: 5691.7579 | AK785: 21.009503 | AL785: PNP_16T_02-11-2020 | AM785: PNCP_2T_10-02-2020 | AN785: PNCP_4T_30-04-2013 | AO785: RAPEL 220 | AP785: 111.133 | AQ785: 1.0808212 | AR785: 120.1149 | AS785: 779.31 | AT785: 0.879 | AU785: 82.280325 | AV785: 0.9638 | AW785: 79.302 | AX785: 8.9176 | AY785: 0.804 | AZ785: 6039.043 | BA785: 0.93699547 | BB785: 5658.556 | BC785: 20.886948

Sheet EFACT_CNE
A1: IdContrato | B1: MesDevengado | C1: Anho | D1: Mes | E1: Codigo | F1: DX | G1: NomEmpresaDistribuidora | H1: GX | I1: NomSuministrador | J1: CodigoContrato | K1: PuntoRetiro | L1: Contrato | M1: Energia_kWh | N1: Potencia_kW | O1: Sistema | P1: DataCreated | Q1: IdBarra | R1: NomBarra | S1: Energia | T1: PrecioEnergia | U1: PrecioEnergiaAjustado | V1: TotalEnergia | W1: TotalEnergiaAjustado | X1: Potencia | Y1: PrecioPotencia | Z1: PrecioPotenciaAjustado | AA1: TotalPotencia | AB1: TotalPotenciaAjustado | AC1: EmpresaDistribuidora | AD1: Fecha
A2: 600911 | B2: 01-04-2016 | C2: 2016 | D2: 4 | E2: Curico | F2: CEC | G2: CEC | H2: Empresa Eléctrica Carén S.A. | I2: CAREN | J2: SIC 2013/03_2_BS1A_BB_CEC_Empresa Eléctrica Carén S.A. | K2: CURICÓ 13,2 | L2: SIC 2013/03_2_BS1A_BB | M2: 4919.3409 | N2: 0 | O2: SIC4 | P2: 44330.488 | Q2: 5423000 | R2: Charrua 220 | S2: 73.123154 | T2: 68.686022 | U2: 68.686022 | V2: 5022.5386 | W2: 5022.5386 | X2: 0 | Y2: 0 | Z2: 0 | AA2: 0 | AB2: 0 | AC2: CEC | AD2: 42461
A3: 600929 | B3: 01-04-2016 | C3: 2016 | D3: 4 | E3: QUINTA | F3: CEC | G3: CEC | H3: Empresa Eléctrica Carén S.A. | I3: CAREN | J3: SIC 2013/03_2_BS1A_BB_CEC_Empresa Eléctrica Carén S.A. | K3: QUINTA 13,2 | L3: SIC 2013/03_2_BS1A_BB | M3: 1317.6215 | N3: 0 | O3: SIC4 | P3: 44330.488 | Q3: 5423034 | R3: Charrua 220 | S3: 35.336403 | T3: 68.686022 | U3: 68.686022 | V3: 2427.117 | W3: 2427.117 | X3: 0 | Y3: 0 | Z3: 0 | AA3: 0 | AB3: 0 | AC3: CEC | AD3: 42461
A4: 607827 | B4: 01-03-2016 | C4: 2016 | D4: 3 | E4: QUINTA | F4: CEC | G4: CEC | H4: Empresa Eléctrica Carén S.A. | I4: CAREN | J4: SIC 2013/03_2_BS1A_BB_CEC_Empresa Eléctrica Carén S.A. | K4: QUINTA 13,2 | L4: SIC 2013/03_2_BS1A_BB | M4: 1703.6854 | N4: 0 | O4: SIC4 | P4: 44330.495 | Q4: 5439222 | R4: Charrua 220 | S4: 45.689989 | T4: 68.686022 | U4: 68.686022 | V4: 3138.2636 | W4: 3138.2636 | X4: 0 | Y4: 0 | Z4: 0 | AA4: 0 | AB4: 0 | AC4: CEC | AD4: 42430
A5: 600947 | B5: 01-04-2016 | C5: 2016 | D5: 4 | E5: TENO | F5: CEC | G5: CEC | H5: Empresa Eléctrica Carén S.A. | I5: CAREN | J5: SIC 2013/03_2_BS1A_BB_CEC_Empresa Eléctrica Carén S.A. | K5: TENO 13,2 | L5: SIC 2013/03_2_BS1A_BB | M5: 2065.7815 | N5: 0 | O5: SIC4 | P5: 44330.488 | Q5: 5423068 | R5: Charrua 220 | S5: 54.541875 | T5: 68.686022 | U5: 68.686022 | V5: 3746.2644 | W5: 3746.2644 | X5: 0 | Y5: 0 | Z5: 0 | AA5: 0 | AB5: 0 | AC5: CEC | AD5: 42461
A6: 607809 | B6: 01-03-2016 | C6: 2016 | D6: 3 | E6: Curico | F6: CEC | G6: CEC | H6: Empresa Eléctrica Carén S.A. | I6: CAREN | J6: SIC 2013/03_2_BS1A_BB_CEC_Empresa Eléctrica Carén S.A. | K6: CURICÓ 13,2 | L6: SIC 2013/03_2_BS1A_BB | M6: 6396.7767 | N6: 0 | O6: SIC4 | P6: 44330.495 | Q6: 5439188 | R6: Charrua 220 | S6: 95.084381 | T6: 68.686022 | U6: 68.686022 | V6: 6530.9679 | W6: 6530.9679 | X6: 0 | Y6: 0 | Z6: 0 | AA6: 0 | AB6: 0 | AC6: CEC | AD6: 42430
A7: 607845 | B7: 01-03-2016 | C7: 2016 | D7: 3 | E7: TENO | F7: CEC | G7: CEC | H7: Empresa Eléctrica Carén S.A. | I7: CAREN | J7: SIC 2013/03_2_BS1A_BB_CEC_Empresa Eléctrica Carén S.A. | K7: TENO 13,2 | L7: SIC 2013/03_2_BS1A_BB | M7: 2312.6678 | N7: 0 | O7: SIC4 | P7: 44330.495 | Q7: 5439256 | R7: Charrua 220 | S7: 61.060298 | T7: 68.686022 | U7: 68.686022 | V7: 4193.989 | W7: 4193.989 | X7: 0 | Y7: 0 | Z7: 0 | AA7: 0 | AB7: 0 | AC7: CEC | AD7: 42430
A8: 607809 | B8: 01-03-2016 | C8: 2016 | D8: 3 | E8: Curico | F8: CEC | G8: CEC | H8: Empresa Eléctrica Carén S.A. | I8: CAREN | J8: SIC 2013/03_2_BS1A_BB_CEC_Empresa Eléctrica Carén S.A. | K8: CURICÓ 13,2 | L8: SIC 2013/03_2_BS1A_BB | M8: 6396.7767 | N8: 0 | O8: SIC4 | P8: 44330.495 | Q8: 5439187 | R8: Itahue 220 | S8: 6554.173 | T8: 77.583745 | U8: 77.583745 | V8: 508497.29 | W8: 508497.29 | X8: 0 | Y8: 0 | Z8: 0 | AA8: 0 | AB8: 0 | AC8: CEC | AD8: 42430
A9: 607845 | B9: 01-03-2016 | C9: 2016 | D9: 3 | E9: TENO | F9: CEC | G9: CEC | H9: Empresa Eléctrica Carén S.A. | I9: CAREN | J9: SIC 2013/03_2_BS1A_BB_CEC_Empresa Eléctrica Carén S.A. | K9: TENO 13,2 | L9: SIC 2013/03_2_BS1A_BB | M9: 2312.6678 | N9: 0 | O9: SIC4 | P9: 44330.495 | Q9: 5439255 | R9: Itahue 220 | S9: 2342.8885 | T9: 77.583745 | U9: 77.583745 | V9: 181770.06 | W9: 181770.06 | X9: 0 | Y9: 0 | Z9: 0 | AA9: 0 | AB9: 0 | AC9: CEC | AD9: 42430
A10: 600929 | B10: 01-04-2016 | C10: 2016 | D10: 4 | E10: QUINTA | F10: CEC | G10: CEC | H10: Empresa Eléctrica Carén S.A. | I10: CAREN | J10: SIC 2013/03_2_BS1A_BB_CEC_Empresa Eléctrica Carén S.A. | K10: QUINTA 13,2 | L10: SIC 2013/03_2_BS1A_BB | M10: 1317.6215 | N10: 0 | O10: SIC4 | P10: 44330.488 | Q10: 5423033 | R10: Itahue 220 | S10: 1334.2916 | T10: 77.583745 | U10: 77.583745 | V10: 103519.34 | W10: 103519.34 | X10: 0 | Y10: 0 | Z10: 0 | AA10: 0 | AB10: 0 | AC10: CEC | AD10: 42461
A11: 600947 | B11: 01-04-2016 | C11: 2016 | D11: 4 | E11: TENO | F11: CEC | G11: CEC | H11: Empresa Eléctrica Carén S.A. | I11: CAREN | J11: SIC 2013/03_2_BS1A_BB_CEC_Empresa Eléctrica Carén S.A. | K11: TENO 13,2 | L11: SIC 2013/03_2_BS1A_BB | M11: 2065.7815 | N11: 0 | O11: SIC4 | P11: 44330.488 | Q11: 5423067 | R11: Itahue 220 | S11: 2092.776 | T11: 77.583745 | U11: 77.583745 | V11: 162365.4 | W11: 162365.4 | X11: 0 | Y11: 0 | Z11: 0 | AA11: 0 | AB11: 0 | AC11: CEC | AD11: 42461
A12: 607827 | B12: 01-03-2016 | C12: 2016 | D12: 3 | E12: QUINTA | F12: CEC | G12: CEC | H12: Empresa Eléctrica Carén S.A. | I12: CAREN | J12: SIC 2013/03_2_BS1A_BB_CEC_Empresa Eléctrica Carén S.A. | K12: QUINTA 13,2 | L12: SIC 2013/03_2_BS1A_BB | M12: 1703.6854 | N12: 0 | O12: SIC4 | P12: 44330.495 | Q12: 5439221 | R12: Itahue 220 | S12: 1725.2398 | T12: 77.583745 | U12: 77.583745 | V12: 133850.57 | W12: 133850.57 | X12: 0 | Y12: 0 | Z12: 0 | AA12: 0 | AB12: 0 | AC12: CEC | AD12: 42430
A13: 600911 | B13: 01-04-2016 | C13: 2016 | D13: 4 | E13: Curico | F13: CEC | G13: CEC | H13: Empresa Eléctrica Carén S.A. | I13: CAREN | J13: SIC 2013/03_2_BS1A_BB_CEC_Empresa Eléctrica Carén S.A. | K13: CURICÓ 13,2 | L13: SIC 2013/03_2_BS1A_BB | M13: 4919.3409 | N13: 0 | O13: SIC4 | P13: 44330.488 | Q13: 5422999 | R13: Itahue 220 | S13: 5040.3841 | T13: 77.583745 | U13: 77.583745 | V13: 391051.88 | W13: 391051.88 | X13: 0 | Y13: 0 | Z13: 0 | AA13: 0 | AB13: 0 | AC13: CEC | AD13: 42461
... A235: 301089 | B235: 01-11-2019 | C235: 2019 | D235: 11 | E235: Curico 13.2 | F235: CEC | G235: CEC | H235: Empresa Eléctrica Carén S.A. | I235: Empresa Eléctrica Carén S.A. | J235: SIC 2013/03_2_BS1A_BB_CEC_Empresa Eléctrica Carén S.A. | K235: Curico 13.2 | L235: SIC 2013/03_2_BS1A_BB | M235: 1777.6837 | N235: 0 | O235: STX E | P235: 44269.874 | Q235: 2848156 | R235: CHARRUA 220 | S235: 211.65708 | T235: 70.437338 | U235: 70.437338 | V235: 14908.561 | W235: 14908.561 | X235: 0 | Y235: 5735.8045 | Z235: 5735.8045 | AA235: 0 | AB235: 0 | AC235: CEC | AD235: 43770

Sheet EFACT_EST_CEN

Sheet SIN_DATA
A1: IdContrato | B1: MesDevengado | C1: Anho | D1: Mes | E1: Codigo | F1: DX | G1: NomEmpresaDistribuidora | H1: GX | I1: NomSuministrador | J1: CodigoContrato | K1: PuntoRetiro | L1: Contrato | M1: Energia_kWh | N1: Potencia_kW | O1: Sistema | P1: DataCreated | Q1: IdBarra | R1: NomBarra | S1: Energia | T1: PrecioEnergia | U1: PrecioEnergiaAjustado | V1: TotalEnergia | W1: TotalEnergiaAjustado | X1: Potencia | Y1: PrecioPotencia | Z1: PrecioPotenciaAjustado | AA1: TotalPotencia | AB1: TotalPotenciaAjustado | AC1: EmpresaDistribuidora | AD1: Fecha
B2: 42370
B3: 42401
B4: 42430
B5: 42461
B6: 42491
B7: 42522
B8: 42552
B9: 42583
B10: 42614
B11: 42644
B12: 42675
B13: 42705
... B235: 49461

Sheet INTERESES
A1: Decreto | B1: Fecha Publicación | C1: Interés vigente | D1: Desde | E1: Hasta | F1: Interés anual | G1: Link
A2: PNP_8T_11-07-2016 | B2: 42588 | C2: Certicado N°7/2016 | D2: 42566 | E2: 42594 | F2: 0.0546 | G2: https://www.bcn.cl/leychile/navegar?idNorma=1092549
A3: PNP_9T_25-07-2016 | B3: 42614 | C3: Certificado N°8/2016 | D3: 42595 | E3: 42627 | F3: 0.0542 | G3: https://www.bcn.cl/leychile/navegar?idNorma=1093605
A4: PNP_12T_20-12-2016 | B4: 43018 | C4: Certificado N°9/2017 | D4: 42993 | E4: 43021 | F4: 0.0416 | G4: https://www.diariooficial.interior.gob.cl/publicaciones/2017/09/15/41861/01/1272697.pdf
A5: PNP_3T_15-05-2017 | B5: 43018 | C5: Certificado N°9/2017 | D5: 42993 | E5: 43021 | F5: 0.0416 | G5: https://www.diariooficial.interior.gob.cl/publicaciones/2017/09/15/41861/01/1272697.pdf
A6: PNP_12T_28-11-2017 | B6: 43183 | C6: Certificado N°3/2018 | D6: 43174 | E6: 43203 | F6: 0.042 | G6: https://www.diariooficial.interior.gob.cl/publicaciones/2018/03/15/42008/01/1366088.pdf
A7: PNP_7T_18-05-2018 | B7: 43371 | C7: Certificado N°9/2018 | D7: 43358 | E7: 43385 | F7: 0.0438 | G7: https://www.diariooficial.interior.gob.cl/publicaciones/2018/09/15/42159/01/1465375.pdf
A8: PNP_20T_13-12-2018 | B8: 43591 | C8: Certificado N°4/2019 | D8: 43570 | E8: 43599 | F8: 0.0446 | G8: https://www.diariooficial.interior.gob.cl/publicaciones/2019/04/15/42331/01/1576341.pdf
A9: PNP_6T_08-05-2020 | B9: 44137 | C9: Certificado N° 10/2020 | D9: 44119 | E9: 44148 | F9: 0.0361 | G9: https://www.diariooficial.interior.gob.cl/publicaciones/2020/10/15/42780/01/1830437.pdf
A10: PNP_16T_02-11-2020 | B10: 44275 | C10: Certificado N° 3/2021 | D10: 44270 | E10: 44300 | F10: 0.0391 | G10: https://www.diariooficial.interior.gob.cl/publicaciones/2021/03/15/42905/01/1910115.pdf
A11: PNP_19T_30-12-2020 | B11: 44336 | C11: Certificado N° 05/2021 | D11: 44330 | F11: 0.0328 | G11: https://www.diariooficial.interior.gob.cl/publicaciones/2021/05/14/42954/01/1943780.pdf
A13: Interés ResEx 703 (06-nov.2018), Artículo 13
A14: Operaciones no reajustables en moneda nacional de menos de 90 días, superiores al equivalente de 5.000 unidades de fomento
