Workbook

Sheet Reliquidacion
A2: Generador | B2: [GX]
A3: Distribuidor | B3: [EEDD]
A4: Licitacion | B4: 2013/03-2° Llamado
A5: Bloque | B5: [BLOQUE]
U6: RELQUIDACIÓN Y CÁLCULO INTERESES
C7: LO QUE SE FACTURÓ | L7: LO QUE SE DEBIÓ HABER FACTURADO | U7: Reliquidación mensual | V7: Decreto PNP | W7: Fecha publicación | X7: Interes | Y7: Fecha | Z7: Fecha | AA7: N° de días | AB7: Interés total | AC7: Intereses | AD7: Reliquidación
A8: ID | B8: MES | C8: ORIGEN DATA | D8: Energía (kWh) | E8: $/kWh | F8: Monto Energía ($) | G8: Potencia (kW) | H8: $/kW-mes | I8: Monto Potencia ($) | J8: Monto Total ($) | L8: ORIGEN DATA | M8: Energía (kWh) | N8: $/kWh | O8: Monto Energía ($) | P8: Potencia (kW) | Q8: $/kW-mes | R8: Monto Potencia ($) | S8: Monto Total ($) | V8: Reliquidación | W8: Diario Oficial | X8: Anual | Y8: Facturación | Z8: Reliquidación | AA8: de intereses | AB8: según n° de días | AD8: Total
A9: 9 | B9: 42370 | C9: =IF(VLOOKUP(B9,'MAPA DATA'!C:F,2,0)=1,"FACT_EMITIDA",IF(VLOOKUP(B9,'MAPA DATA'!C:F,3,0)=1,"FACT_EST_EFACT",(IF(VLOOKUP(B9,'MAPA DATA'!C:F,4,0)=1,"FACT_EST_CEN","SIN DATA")))) -> SIN DATA | D9: =CONCATENATE("=SUMAR.SI(",IF(C9="FACT_EMITIDA","SIGGE_E",C9),"!B:B;Reliquidacion!B",A9,";",IF(C9="FACT_EMITIDA","SIGGE_E",C9),"!F:F)") -> =SUMAR.SI(SIN DATA!B:B;Reliquidacion!B9;SIN DATA!F:F) | E9: =CONCATENATE("=(F",A9,"/D",A9,")") -> =(F9/D9) | F9: =CONCATENATE("=SUMAR.SI(",IF(C9="FACT_EMITIDA","SIGGE_E",C9),"!B:B;Reliquidacion!B",A9,";",IF(C9="FACT_EMITIDA","SIGGE_E",C9),"!H:H)") -> =SUMAR.SI(SIN DATA!B:B;Reliquidacion!B9;SIN DATA!H:H) | G9: =CONCATENATE("=SUMAR.SI(",IF(C9="FACT_EMITIDA","SIGGE_P",C9),"!B:B;Reliquidacion!B",A9,";",IF(C9="FACT_EMITIDA","SIGGE_P",C9),"!F:F)") -> =SUMAR.SI(SIN DATA!B:B;Reliquidacion!B9;SIN DATA!F:F) | H9: =CONCATENATE("=(I",A9,"/G",A9,")") -> =(I9/G9) | I9: =CONCATENATE("=SUMAR.SI(",IF(C9="FACT_EMITIDA","SIGGE_P",C9),"!B:B;Reliquidacion!B",A9,";",IF(C9="FACT_EMITIDA","SIGGE_P",C9),"!H:H)") -> =SUMAR.SI(SIN DATA!B:B;Reliquidacion!B9;SIN DATA!H:H) | J9: =CONCATENATE("=(F",A9,"+I",A9,")") -> =(F9+I9) | L9: =IF(VLOOKUP(B9,'MAPA DATA'!C:H,5,0)=1,"EFACT_CNE",IF(VLOOKUP(B9,'MAPA DATA'!C:H,6,0)=1,"EFACT_EST_CNE","SIN DATA")) -> EFACT_CNE | M9: =CONCATENATE("=SUMAR.SI(",L9,"!B:B;Reliquidacion!B",A9,";",L9,"!S:S)") -> =SUMAR.SI(EFACT_CNE!B:B;Reliquidacion!B9;EFACT_CNE!S:S) | N9: =CONCATENATE("=(O",A9,"/M",A9,")") -> =(O9/M9) | O9: =CONCATENATE("=SUMAR.SI(",L9,"!B:B;Reliquidacion!B",A9,";",L9,"!W:W)") -> =SUMAR.SI(EFACT_CNE!B:B;Reliquidacion!B9;EFACT_CNE!W:W) | P9: =CONCATENATE("=SUMAR.SI(",L9,"!B:B;Reliquidacion!B",A9,";",L9,"!X:X)") -> =SUMAR.SI(EFACT_CNE!B:B;Reliquidacion!B9;EFACT_CNE!X:X) | Q9: =CONCATENATE("=(R",A9,"/P",A9,")") -> =(R9/P9) | R9: =CONCATENATE("=SUMAR.SI(",L9,"!B:B;Reliquidacion!B",A9,";",L9,"!AB:AB)") -> =SUMAR.SI(EFACT_CNE!B:B;Reliquidacion!B9;EFACT_CNE!AB:AB) | S9: =CONCATENATE("=(O",A9,"+R",A9,")") -> =(O9+R9) | U9: =CONCATENATE("=(S",A9,"-J",A9,")") -> =(S9-J9) | V9: PNP 7T/2018 | W9: =VLOOKUP(V9,#REF!,2,0) -> #REF! | X9: =VLOOKUP(V9,#REF!,6,0) -> #REF! | Y9: 43156 | Z9: 44377 | AA9: =Z9-Y9 -> 1221 | AB9: =+(1+X9)^(AA9/360)-1 -> #REF! | AC9: =AB9*U9 -> #REF! | AD9: =+U9+AC9 -> #VALUE!
A10: =A9+1 -> 10 | B10: 42401 | C10: =IF(VLOOKUP(B10,'MAPA DATA'!C:F,2,0)=1,"FACT_EMITIDA",IF(VLOOKUP(B10,'MAPA DATA'!C:F,3,0)=1,"FACT_EST_EFACT",(IF(VLOOKUP(B10,'MAPA DATA'!C:F,4,0)=1,"FACT_EST_CEN","SIN DATA")))) -> SIN DATA | D10: =CONCATENATE("=SUMAR.SI(",IF(C10="FACT_EMITIDA","SIGGE_E",C10),"!B:B;Reliquidacion!B",A10,";",IF(C10="FACT_EMITIDA","SIGGE_E",C10),"!F:F)") -> =SUMAR.SI(SIN DATA!B:B;Reliquidacion!B10;SIN DATA!F:F) | E10: =CONCATENATE("=(F",A10,"/D",A10,")") -> =(F10/D10) | F10: =CONCATENATE("=SUMAR.SI(",IF(C10="FACT_EMITIDA","SIGGE_E",C10),"!B:B;Reliquidacion!B",A10,";",IF(C10="FACT_EMITIDA","SIGGE_E",C10),"!H:H)") -> =SUMAR.SI(SIN DATA!B:B;Reliquidacion!B10;SIN DATA!H:H) | G10: =CONCATENATE("=SUMAR.SI(",IF(C10="FACT_EMITIDA","SIGGE_P",C10),"!B:B;Reliquidacion!B",A10,";",IF(C10="FACT_EMITIDA","SIGGE_P",C10),"!F:F)") -> =SUMAR.SI(SIN DATA!B:B;Reliquidacion!B10;SIN DATA!F:F) | H10: =CONCATENATE("=(I",A10,"/G",A10,")") -> =(I10/G10) | I10: =CONCATENATE("=SUMAR.SI(",IF(C10="FACT_EMITIDA","SIGGE_P",C10),"!B:B;Reliquidacion!B",A10,";",IF(C10="FACT_EMITIDA","SIGGE_P",C10),"!H:H)") -> =SUMAR.SI(SIN DATA!B:B;Reliquidacion!B10;SIN DATA!H:H) | J10: =CONCATENATE("=(F",A10,"+I",A10,")") -> =(F10+I10) | L10: =IF(VLOOKUP(B10,'MAPA DATA'!C:H,5,0)=1,"EFACT_CNE",IF(VLOOKUP(B10,'MAPA DATA'!C:H,6,0)=1,"EFACT_EST_CNE","SIN DATA")) -> EFACT_CNE | M10: =CONCATENATE("=SUMAR.SI(",L10,"!B:B;Reliquidacion!B",A10,";",L10,"!S:S)") -> =SUMAR.SI(EFACT_CNE!B:B;Reliquidacion!B10;EFACT_CNE!S:S) | N10: =CONCATENATE("=(O",A10,"/M",A10,")") -> =(O10/M10) | O10: =CONCATENATE("=SUMAR.SI(",L10,"!B:B;Reliquidacion!B",A10,";",L10,"!W:W)") -> =SUMAR.SI(EFACT_CNE!B:B;Reliquidacion!B10;EFACT_CNE!W:W) | P10: =CONCATENATE("=SUMAR.SI(",L10,"!B:B;Reliquidacion!B",A10,";",L10,"!X:X)") -> =SUMAR.SI(EFACT_CNE!B:B;Reliquidacion!B10;EFACT_CNE!X:X) | Q10: =CONCATENATE("=(R",A10,"/P",A10,")") -> =(R10/P10) | R10: =CONCATENATE("=SUMAR.SI(",L10,"!B:B;Reliquidacion!B",A10,";",L10,"!AB:AB)") -> =SUMAR.SI(EFACT_CNE!B:B;Reliquidacion!B10;EFACT_CNE!AB:AB) | S10: =CONCATENATE("=(O",A10,"+R",A10,")") -> =(O10+R10) | U10: =CONCATENATE("=(S",A10,"-J",A10,")") -> =(S10-J10) | V10: PNP 7T/2019 | W10: =VLOOKUP(V10,#REF!,2,0) -> #REF! | X10: =VLOOKUP(V10,#REF!,6,0) -> #REF! | Y10: 43156 | Z10: 44377 | AA10: =Z10-Y10 -> 1221 | AB10: =+(1+X10)^(AA10/360)-1 -> #REF! | AC10: =AB10*U10 -> #REF! | AD10: =+U10+AC10 -> #VALUE!
A11: =A10+1 -> 11 | B11: 42430 | C11: =IF(VLOOKUP(B11,'MAPA DATA'!C:F,2,0)=1,"FACT_EMITIDA",IF(VLOOKUP(B11,'MAPA DATA'!C:F,3,0)=1,"FACT_EST_EFACT",(IF(VLOOKUP(B11,'MAPA DATA'!C:F,4,0)=1,"FACT_EST_CEN","SIN DATA")))) -> FACT_EST_EFACT | D11: =CONCATENATE("=SUMAR.SI(",IF(C11="FACT_EMITIDA","SIGGE_E",C11),"!B:B;Reliquidacion!B",A11,";",IF(C11="FACT_EMITIDA","SIGGE_E",C11),"!F:F)") -> =SUMAR.SI(FACT_EST_EFACT!B:B;Reliquidacion!B11;FACT_EST_EFACT!F:F) | E11: =CONCATENATE("=(F",A11,"/D",A11,")") -> =(F11/D11) | F11: =CONCATENATE("=SUMAR.SI(",IF(C11="FACT_EMITIDA","SIGGE_E",C11),"!B:B;Reliquidacion!B",A11,";",IF(C11="FACT_EMITIDA","SIGGE_E",C11),"!H:H)") -> =SUMAR.SI(FACT_EST_EFACT!B:B;Reliquidacion!B11;FACT_EST_EFACT!H:H) | G11: =CONCATENATE("=SUMAR.SI(",IF(C11="FACT_EMITIDA","SIGGE_P",C11),"!B:B;Reliquidacion!B",A11,";",IF(C11="FACT_EMITIDA","SIGGE_P",C11),"!F:F)") -> =SUMAR.SI(FACT_EST_EFACT!B:B;Reliquidacion!B11;FACT_EST_EFACT!F:F) | H11: =CONCATENATE("=(I",A11,"/G",A11,")") -> =(I11/G11) | I11: =CONCATENATE("=SUMAR.SI(",IF(C11="FACT_EMITIDA","SIGGE_P",C11),"!B:B;Reliquidacion!B",A11,";",IF(C11="FACT_EMITIDA","SIGGE_P",C11),"!H:H)") -> =SUMAR.SI(FACT_EST_EFACT!B:B;Reliquidacion!B11;FACT_EST_EFACT!H:H) | J11: =CONCATENATE("=(F",A11,"+I",A11,")") -> =(F11+I11) | L11: =IF(VLOOKUP(B11,'MAPA DATA'!C:H,5,0)=1,"EFACT_CNE",IF(VLOOKUP(B11,'MAPA DATA'!C:H,6,0)=1,"EFACT_EST_CNE","SIN DATA")) -> EFACT_CNE | M11: =CONCATENATE("=SUMAR.SI(",L11,"!B:B;Reliquidacion!B",A11,";",L11,"!S:S)") -> =SUMAR.SI(EFACT_CNE!B:B;Reliquidacion!B11;EFACT_CNE!S:S) | N11: =CONCATENATE("=(O",A11,"/M",A11,")") -> =(O11/M11) | O11: =CONCATENATE("=SUMAR.SI(",L11,"!B:B;Reliquidacion!B",A11,";",L11,"!W:W)") -> =SUMAR.SI(EFACT_CNE!B:B;Reliquidacion!B11;EFACT_CNE!W:W) | P11: =CONCATENATE("=SUMAR.SI(",L11,"!B:B;Reliquidacion!B",A11,";",L11,"!X:X)") -> =SUMAR.SI(EFACT_CNE!B:B;Reliquidacion!B11;EFACT_CNE!X:X) | Q11: =CONCATENATE("=(R",A11,"/P",A11,")") -> =(R11/P11) | R11: =CONCATENATE("=SUMAR.SI(",L11,"!B:B;Reliquidacion!B",A11,";",L11,"!AB:AB)") -> =SUMAR.SI(EFACT_CNE!B:B;Reliquidacion!B11;EFACT_CNE!AB:AB) | S11: =CONCATENATE("=(O",A11,"+R",A11,")") -> =(O11+R11) | U11: =CONCATENATE("=(S",A11,"-J",A11,")") -> =(S11-J11) | V11: PNP 7T/2020 | W11: =VLOOKUP(V11,#REF!,2,0) -> #REF! | X11: =VLOOKUP(V11,#REF!,6,0) -> #REF! | Y11: 43156 | Z11: 44377 | AA11: =Z11-Y11 -> 1221 | AB11: =+(1+X11)^(AA11/360)-1 -> #REF! | AC11: =AB11*U11 -> #REF! | AD11: =+U11+AC11 -> #VALUE!
A12: =A11+1 -> 12 | B12: 42461 | C12: =IF(VLOOKUP(B12,'MAPA DATA'!C:F,2,0)=1,"FACT_EMITIDA",IF(VLOOKUP(B12,'MAPA DATA'!C:F,3,0)=1,"FACT_EST_EFACT",(IF(VLOOKUP(B12,'MAPA DATA'!C:F,4,0)=1,"FACT_EST_CEN","SIN DATA")))) -> FACT_EST_EFACT | D12: =CONCATENATE("=SUMAR.SI(",IF(C12="FACT_EMITIDA","SIGGE_E",C12),"!B:B;Reliquidacion!B",A12,";",IF(C12="FACT_EMITIDA","SIGGE_E",C12),"!F:F)") -> =SUMAR.SI(FACT_EST_EFACT!B:B;Reliquidacion!B12;FACT_EST_EFACT!F:F) | E12: =CONCATENATE("=(F",A12,"/D",A12,")") -> =(F12/D12) | F12: =CONCATENATE("=SUMAR.SI(",IF(C12="FACT_EMITIDA","SIGGE_E",C12),"!B:B;Reliquidacion!B",A12,";",IF(C12="FACT_EMITIDA","SIGGE_E",C12),"!H:H)") -> =SUMAR.SI(FACT_EST_EFACT!B:B;Reliquidacion!B12;FACT_EST_EFACT!H:H) | G12: =CONCATENATE("=SUMAR.SI(",IF(C12="FACT_EMITIDA","SIGGE_P",C12),"!B:B;Reliquidacion!B",A12,";",IF(C12="FACT_EMITIDA","SIGGE_P",C12),"!F:F)") -> =SUMAR.SI(FACT_EST_EFACT!B:B;Reliquidacion!B12;FACT_EST_EFACT!F:F) | H12: =CONCATENATE("=(I",A12,"/G",A12,")") -> =(I12/G12) | I12: =CONCATENATE("=SUMAR.SI(",IF(C12="FACT_EMITIDA","SIGGE_P",C12),"!B:B;Reliquidacion!B",A12,";",IF(C12="FACT_EMITIDA","SIGGE_P",C12),"!H:H)") -> =SUMAR.SI(FACT_EST_EFACT!B:B;Reliquidacion!B12;FACT_EST_EFACT!H:H) | J12: =CONCATENATE("=(F",A12,"+I",A12,")") -> =(F12+I12) | L12: =IF(VLOOKUP(B12,'MAPA DATA'!C:H,5,0)=1,"EFACT_CNE",IF(VLOOKUP(B12,'MAPA DATA'!C:H,6,0)=1,"EFACT_EST_CNE","SIN DATA")) -> EFACT_CNE | M12: =CONCATENATE("=SUMAR.SI(",L12,"!B:B;Reliquidacion!B",A12,";",L12,"!S:S)") -> =SUMAR.SI(EFACT_CNE!B:B;Reliquidacion!B12;EFACT_CNE!S:S) | N12: =CONCATENATE("=(O",A12,"/M",A12,")") -> =(O12/M12) | O12: =CONCATENATE("=SUMAR.SI(",L12,"!B:B;Reliquidacion!B",A12,";",L12,"!W:W)") -> =SUMAR.SI(EFACT_CNE!B:B;Reliquidacion!B12;EFACT_CNE!W:W) | P12: =CONCATENATE("=SUMAR.SI(",L12,"!B:B;Reliquidacion!B",A12,";",L12,"!X:X)") -> =SUMAR.SI(EFACT_CNE!B:B;Reliquidacion!B12;EFACT_CNE!X:X) | Q12: =CONCATENATE("=(R",A12,"/P",A12,")") -> =(R12/P12) | R12: =CONCATENATE("=SUMAR.SI(",L12,"!B:B;Reliquidacion!B",A12,";",L12,"!AB:AB)") -> =SUMAR.SI(EFACT_CNE!B:B;Reliquidacion!B12;EFACT_CNE!AB:AB) | S12: =CONCATENATE("=(O",A12,"+R",A12,")") -> =(O12+R12) | U12: =CONCATENATE("=(S",A12,"-J",A12,")") -> =(S12-J12) | V12: PNP 7T/2021 | W12: =VLOOKUP(V12,#REF!,2,0) -> #REF! | X12: =VLOOKUP(V12,#REF!,6,0) -> #REF! | Y12: 43156 | Z12: 44377 | AA12: =Z12-Y12 -> 1221 | AB12: =+(1+X12)^(AA12/360)-1 -> #REF! | AC12: =AB12*U12 -> #REF! | AD12: =+U12+AC12 -> #VALUE!
A13: =A12+1 -> 13 | B13: 42491 | C13: =IF(VLOOKUP(B13,'MAPA DATA'!C:F,2,0)=1,"FACT_EMITIDA",IF(VLOOKUP(B13,'MAPA DATA'!C:F,3,0)=1,"FACT_EST_EFACT",(IF(VLOOKUP(B13,'MAPA DATA'!C:F,4,0)=1,"FACT_EST_CEN","SIN DATA")))) -> FACT_EST_EFACT | D13: =CONCATENATE("=SUMAR.SI(",IF(C13="FACT_EMITIDA","SIGGE_E",C13),"!B:B;Reliquidacion!B",A13,";",IF(C13="FACT_EMITIDA","SIGGE_E",C13),"!F:F)") -> =SUMAR.SI(FACT_EST_EFACT!B:B;Reliquidacion!B13;FACT_EST_EFACT!F:F) | E13: =CONCATENATE("=(F",A13,"/D",A13,")") -> =(F13/D13) | F13: =CONCATENATE("=SUMAR.SI(",IF(C13="FACT_EMITIDA","SIGGE_E",C13),"!B:B;Reliquidacion!B",A13,";",IF(C13="FACT_EMITIDA","SIGGE_E",C13),"!H:H)") -> =SUMAR.SI(FACT_EST_EFACT!B:B;Reliquidacion!B13;FACT_EST_EFACT!H:H) | G13: =CONCATENATE("=SUMAR.SI(",IF(C13="FACT_EMITIDA","SIGGE_P",C13),"!B:B;Reliquidacion!B",A13,";",IF(C13="FACT_EMITIDA","SIGGE_P",C13),"!F:F)") -> =SUMAR.SI(FACT_EST_EFACT!B:B;Reliquidacion!B13;FACT_EST_EFACT!F:F) | H13: =CONCATENATE("=(I",A13,"/G",A13,")") -> =(I13/G13) | I13: =CONCATENATE("=SUMAR.SI(",IF(C13="FACT_EMITIDA","SIGGE_P",C13),"!B:B;Reliquidacion!B",A13,";",IF(C13="FACT_EMITIDA","SIGGE_P",C13),"!H:H)") -> =SUMAR.SI(FACT_EST_EFACT!B:B;Reliquidacion!B13;FACT_EST_EFACT!H:H) | J13: =CONCATENATE("=(F",A13,"+I",A13,")") -> =(F13+I13) | L13: =IF(VLOOKUP(B13,'MAPA DATA'!C:H,5,0)=1,"EFACT_CNE",IF(VLOOKUP(B13,'MAPA DATA'!C:H,6,0)=1,"EFACT_EST_CNE","SIN DATA")) -> EFACT_CNE | M13: =CONCATENATE("=SUMAR.SI(",L13,"!B:B;Reliquidacion!B",A13,";",L13,"!S:S)") -> =SUMAR.SI(EFACT_CNE!B:B;Reliquidacion!B13;EFACT_CNE!S:S) | N13: =CONCATENATE("=(O",A13,"/M",A13,")") -> =(O13/M13) | O13: =CONCATENATE("=SUMAR.SI(",L13,"!B:B;Reliquidacion!B",A13,";",L13,"!W:W)") -> =SUMAR.SI(EFACT_CNE!B:B;Reliquidacion!B13;EFACT_CNE!W:W) | P13: =CONCATENATE("=SUMAR.SI(",L13,"!B:B;Reliquidacion!B",A13,";",L13,"!X:X)") -> =SUMAR.SI(EFACT_CNE!B:B;Reliquidacion!B13;EFACT_CNE!X:X) | Q13: =CONCATENATE("=(R",A13,"/P",A13,")") -> =(R13/P13) | R13: =CONCATENATE("=SUMAR.SI(",L13,"!B:B;Reliquidacion!B",A13,";",L13,"!AB:AB)") -> =SUMAR.SI(EFACT_CNE!B:B;Reliquidacion!B13;EFACT_CNE!AB:AB) | S13: =CONCATENATE("=(O",A13,"+R",A13,")") -> =(O13+R13) | U13: =CONCATENATE("=(S",A13,"-J",A13,")") -> =(S13-J13) | V13: PNP 7T/2022 | W13: =VLOOKUP(V13,#REF!,2,0) -> #REF! | X13: =VLOOKUP(V13,#REF!,6,0) -> #REF! | Y13: 43156 | Z13: 44377 | AA13: =Z13-Y13 -> 1221 | AB13: =+(1+X13)^(AA13/360)-1 -> #REF! | AC13: =AB13*U13 -> #REF! | AD13: =+U13+AC13 -> #VALUE!
A14: =A13+1 -> 14 | B14: 42522 | C14: =IF(VLOOKUP(B14,'MAPA DATA'!C:F,2,0)=1,"FACT_EMITIDA",IF(VLOOKUP(B14,'MAPA DATA'!C:F,3,0)=1,"FACT_EST_EFACT",(IF(VLOOKUP(B14,'MAPA DATA'!C:F,4,0)=1,"FACT_EST_CEN","SIN DATA")))) -> FACT_EST_EFACT | D14: =CONCATENATE("=SUMAR.SI(",IF(C14="FACT_EMITIDA","SIGGE_E",C14),"!B:B;Reliquidacion!B",A14,";",IF(C14="FACT_EMITIDA","SIGGE_E",C14),"!F:F)") -> =SUMAR.SI(FACT_EST_EFACT!B:B;Reliquidacion!B14;FACT_EST_EFACT!F:F) | E14: =CONCATENATE("=(F",A14,"/D",A14,")") -> =(F14/D14) | F14: =CONCATENATE("=SUMAR.SI(",IF(C14="FACT_EMITIDA","SIGGE_E",C14),"!B:B;Reliquidacion!B",A14,";",IF(C14="FACT_EMITIDA","SIGGE_E",C14),"!H:H)") -> =SUMAR.SI(FACT_EST_EFACT!B:B;Reliquidacion!B14;FACT_EST_EFACT!H:H) | G14: =CONCATENATE("=SUMAR.SI(",IF(C14="FACT_EMITIDA","SIGGE_P",C14),"!B:B;Reliquidacion!B",A14,";",IF(C14="FACT_EMITIDA","SIGGE_P",C14),"!F:F)") -> =SUMAR.SI(FACT_EST_EFACT!B:B;Reliquidacion!B14;FACT_EST_EFACT!F:F) | H14: =CONCATENATE("=(I",A14,"/G",A14,")") -> =(I14/G14) | I14: =CONCATENATE("=SUMAR.SI(",IF(C14="FACT_EMITIDA","SIGGE_P",C14),"!B:B;Reliquidacion!B",A14,";",IF(C14="FACT_EMITIDA","SIGGE_P",C14),"!H:H)") -> =SUMAR.SI(FACT_EST_EFACT!B:B;Reliquidacion!B14;FACT_EST_EFACT!H:H) | J14: =CONCATENATE("=(F",A14,"+I",A14,")") -> =(F14+I14) | L14: =IF(VLOOKUP(B14,'MAPA DATA'!C:H,5,0)=1,"EFACT_CNE",IF(VLOOKUP(B14,'MAPA DATA'!C:H,6,0)=1,"EFACT_EST_CNE","SIN DATA")) -> EFACT_CNE | M14: =CONCATENATE("=SUMAR.SI(",L14,"!B:B;Reliquidacion!B",A14,";",L14,"!S:S)") -> =SUMAR.SI(EFACT_CNE!B:B;Reliquidacion!B14;EFACT_CNE!S:S) | N14: =CONCATENATE("=(O",A14,"/M",A14,")") -> =(O14/M14) | O14: =CONCATENATE("=SUMAR.SI(",L14,"!B:B;Reliquidacion!B",A14,";",L14,"!W:W)") -> =SUMAR.SI(EFACT_CNE!B:B;Reliquidacion!B14;EFACT_CNE!W:W) | P14: =CONCATENATE("=SUMAR.SI(",L14,"!B:B;Reliquidacion!B",A14,";",L14,"!X:X)") -> =SUMAR.SI(EFACT_CNE!B:B;Reliquidacion!B14;EFACT_CNE!X:X) | Q14: =CONCATENATE("=(R",A14,"/P",A14,")") -> =(R14/P14) | R14: =CONCATENATE("=SUMAR.SI(",L14,"!B:B;Reliquidacion!B",A14,";",L14,"!AB:AB)") -> =SUMAR.SI(EFACT_CNE!B:B;Reliquidacion!B14;EFACT_CNE!AB:AB) | S14: =CONCATENATE("=(O",A14,"+R",A14,")") -> =(O14+R14) | U14: =CONCATENATE("=(S",A14,"-J",A14,")") -> =(S14-J14) | V14: PNP 7T/2023 | W14: =VLOOKUP(V14,#REF!,2,0) -> #REF! | X14: =VLOOKUP(V14,#REF!,6,0) -> #REF! | Y14: 43156 | Z14: 44377 | AA14: =Z14-Y14 -> 1221 | AB14: =+(1+X14)^(AA14/360)-1 -> #REF! | AC14: =AB14*U14 -> #REF! | AD14: =+U14+AC14 -> #VALUE!
A15: =A14+1 -> 15 | B15: 42552 | C15: =IF(VLOOKUP(B15,'MAPA DATA'!C:F,2,0)=1,"FACT_EMITIDA",IF(VLOOKUP(B15,'MAPA DATA'!C:F,3,0)=1,"FACT_EST_EFACT",(IF(VLOOKUP(B15,'MAPA DATA'!C:F,4,0)=1,"FACT_EST_CEN","SIN DATA")))) -> FACT_EST_EFACT | D15: =CONCATENATE("=SUMAR.SI(",IF(C15="FACT_EMITIDA","SIGGE_E",C15),"!B:B;Reliquidacion!B",A15,";",IF(C15="FACT_EMITIDA","SIGGE_E",C15),"!F:F)") -> =SUMAR.SI(FACT_EST_EFACT!B:B;Reliquidacion!B15;FACT_EST_EFACT!F:F) | E15: =CONCATENATE("=(F",A15,"/D",A15,")") -> =(F15/D15) | F15: =CONCATENATE("=SUMAR.SI(",IF(C15="FACT_EMITIDA","SIGGE_E",C15),"!B:B;Reliquidacion!B",A15,";",IF(C15="FACT_EMITIDA","SIGGE_E",C15),"!H:H)") -> =SUMAR.SI(FACT_EST_EFACT!B:B;Reliquidacion!B15;FACT_EST_EFACT!H:H) | G15: =CONCATENATE("=SUMAR.SI(",IF(C15="FACT_EMITIDA","SIGGE_P",C15),"!B:B;Reliquidacion!B",A15,";",IF(C15="FACT_EMITIDA","SIGGE_P",C15),"!F:F)") -> =SUMAR.SI(FACT_EST_EFACT!B:B;Reliquidacion!B15;FACT_EST_EFACT!F:F) | H15: =CONCATENATE("=(I",A15,"/G",A15,")") -> =(I15/G15) | I15: =CONCATENATE("=SUMAR.SI(",IF(C15="FACT_EMITIDA","SIGGE_P",C15),"!B:B;Reliquidacion!B",A15,";",IF(C15="FACT_EMITIDA","SIGGE_P",C15),"!H:H)") -> =SUMAR.SI(FACT_EST_EFACT!B:B;Reliquidacion!B15;FACT_EST_EFACT!H:H) | J15: =CONCATENATE("=(F",A15,"+I",A15,")") -> =(F15+I15) | L15: =IF(VLOOKUP(B15,'MAPA DATA'!C:H,5,0)=1,"EFACT_CNE",IF(VLOOKUP(B15,'MAPA DATA'!C:H,6,0)=1,"EFACT_EST_CNE","SIN DATA")) -> EFACT_CNE | M15: =CONCATENATE("=SUMAR.SI(",L15,"!B:B;Reliquidacion!B",A15,";",L15,"!S:S)") -> =SUMAR.SI(EFACT_CNE!B:B;Reliquidacion!B15;EFACT_CNE!S:S) | N15: =CONCATENATE("=(O",A15,"/M",A15,")") -> =(O15/M15) | O15: =CONCATENATE("=SUMAR.SI(",L15,"!B:B;Reliquidacion!B",A15,";",L15,"!W:W)") -> =SUMAR.SI(EFACT_CNE!B:B;Reliquidacion!B15;EFACT_CNE!W:W) | P15: =CONCATENATE("=SUMAR.SI(",L15,"!B:B;Reliquidacion!B",A15,";",L15,"!X:X)") -> =SUMAR.SI(EFACT_CNE!B:B;Reliquidacion!B15;EFACT_CNE!X:X) | Q15: =CONCATENATE("=(R",A15,"/P",A15,")") -> =(R15/P15) | R15: =CONCATENATE("=SUMAR.SI(",L15,"!B:B;Reliquidacion!B",A15,";",L15,"!AB:AB)") -> =SUMAR.SI(EFACT_CNE!B:B;Reliquidacion!B15;EFACT_CNE!AB:AB) | S15: =CONCATENATE("=(O",A15,"+R",A15,")") -> =(O15+R15) | U15: =CONCATENATE("=(S",A15,"-J",A15,")") -> =(S15-J15) | V15: PNP 7T/2024 | W15: =VLOOKUP(V15,#REF!,2,0) -> #REF! | X15: =VLOOKUP(V15,#REF!,6,0) -> #REF! | Y15: 43156 | Z15: 44377 | AA15: =Z15-Y15 -> 1221 | AB15: =+(1+X15)^(AA15/360)-1 -> #REF! | AC15: =AB15*U15 -> #REF! | AD15: =+U15+AC15 -> #VALUE!
A16: =A15+1 -> 16 | B16: 42583 | C16: =IF(VLOOKUP(B16,'MAPA DATA'!C:F,2,0)=1,"FACT_EMITIDA",IF(VLOOKUP(B16,'MAPA DATA'!C:F,3,0)=1,"FACT_EST_EFACT",(IF(VLOOKUP(B16,'MAPA DATA'!C:F,4,0)=1,"FACT_EST_CEN","SIN DATA")))) -> SIN DATA | D16: =CONCATENATE("=SUMAR.SI(",IF(C16="FACT_EMITIDA","SIGGE_E",C16),"!B:B;Reliquidacion!B",A16,";",IF(C16="FACT_EMITIDA","SIGGE_E",C16),"!F:F)") -> =SUMAR.SI(SIN DATA!B:B;Reliquidacion!B16;SIN DATA!F:F) | E16: =CONCATENATE("=(F",A16,"/D",A16,")") -> =(F16/D16) | F16: =CONCATENATE("=SUMAR.SI(",IF(C16="FACT_EMITIDA","SIGGE_E",C16),"!B:B;Reliquidacion!B",A16,";",IF(C16="FACT_EMITIDA","SIGGE_E",C16),"!H:H)") -> =SUMAR.SI(SIN DATA!B:B;Reliquidacion!B16;SIN DATA!H:H) | G16: =CONCATENATE("=SUMAR.SI(",IF(C16="FACT_EMITIDA","SIGGE_P",C16),"!B:B;Reliquidacion!B",A16,";",IF(C16="FACT_EMITIDA","SIGGE_P",C16),"!F:F)") -> =SUMAR.SI(SIN DATA!B:B;Reliquidacion!B16;SIN DATA!F:F) | H16: =CONCATENATE("=(I",A16,"/G",A16,")") -> =(I16/G16) | I16: =CONCATENATE("=SUMAR.SI(",IF(C16="FACT_EMITIDA","SIGGE_P",C16),"!B:B;Reliquidacion!B",A16,";",IF(C16="FACT_EMITIDA","SIGGE_P",C16),"!H:H)") -> =SUMAR.SI(SIN DATA!B:B;Reliquidacion!B16;SIN DATA!H:H) | J16: =CONCATENATE("=(F",A16,"+I",A16,")") -> =(F16+I16) | L16: =IF(VLOOKUP(B16,'MAPA DATA'!C:H,5,0)=1,"EFACT_CNE",IF(VLOOKUP(B16,'MAPA DATA'!C:H,6,0)=1,"EFACT_EST_CNE","SIN DATA")) -> EFACT_CNE | M16: =CONCATENATE("=SUMAR.SI(",L16,"!B:B;Reliquidacion!B",A16,";",L16,"!S:S)") -> =SUMAR.SI(EFACT_CNE!B:B;Reliquidacion!B16;EFACT_CNE!S:S) | N16: =CONCATENATE("=(O",A16,"/M",A16,")") -> =(O16/M16) | O16: =CONCATENATE("=SUMAR.SI(",L16,"!B:B;Reliquidacion!B",A16,";",L16,"!W:W)") -> =SUMAR.SI(EFACT_CNE!B:B;Reliquidacion!B16;EFACT_CNE!W:W) | P16: =CONCATENATE("=SUMAR.SI(",L16,"!B:B;Reliquidacion!B",A16,";",L16,"!X:X)") -> =SUMAR.SI(EFACT_CNE!B:B;Reliquidacion!B16;EFACT_CNE!X:X) | Q16: =CONCATENATE("=(R",A16,"/P",A16,")") -> =(R16/P16) | R16: =CONCATENATE("=SUMAR.SI(",L16,"!B:B;Reliquidacion!B",A16,";",L16,"!AB:AB)") -> =SUMAR.SI(EFACT_CNE!B:B;Reliquidacion!B16;EFACT_CNE!AB:AB) | S16: =CONCATENATE("=(O",A16,"+R",A16,")") -> =(O16+R16) | U16: =CONCATENATE("=(S",A16,"-J",A16,")") -> =(S16-J16) | V16: PNP 7T/2025 | W16: =VLOOKUP(V16,#REF!,2,0) -> #REF! | X16: =VLOOKUP(V16,#REF!,6,0) -> #REF! | Y16: 43156 | Z16: 44377 | AA16: =Z16-Y16 -> 1221 | AB16: =+(1+X16)^(AA16/360)-1 -> #REF! | AC16: =AB16*U16 -> #REF! | AD16: =+U16+AC16 -> #VALUE!
A17: =A16+1 -> 17 | B17: 42614 | C17: =IF(VLOOKUP(B17,'MAPA DATA'!C:F,2,0)=1,"FACT_EMITIDA",IF(VLOOKUP(B17,'MAPA DATA'!C:F,3,0)=1,"FACT_EST_EFACT",(IF(VLOOKUP(B17,'MAPA DATA'!C:F,4,0)=1,"FACT_EST_CEN","SIN DATA")))) -> FACT_EST_EFACT | D17: =CONCATENATE("=SUMAR.SI(",IF(C17="FACT_EMITIDA","SIGGE_E",C17),"!B:B;Reliquidacion!B",A17,";",IF(C17="FACT_EMITIDA","SIGGE_E",C17),"!F:F)") -> =SUMAR.SI(FACT_EST_EFACT!B:B;Reliquidacion!B17;FACT_EST_EFACT!F:F) | E17: =CONCATENATE("=(F",A17,"/D",A17,")") -> =(F17/D17) | F17: =CONCATENATE("=SUMAR.SI(",IF(C17="FACT_EMITIDA","SIGGE_E",C17),"!B:B;Reliquidacion!B",A17,";",IF(C17="FACT_EMITIDA","SIGGE_E",C17),"!H:H)") -> =SUMAR.SI(FACT_EST_EFACT!B:B;Reliquidacion!B17;FACT_EST_EFACT!H:H) | G17: =CONCATENATE("=SUMAR.SI(",IF(C17="FACT_EMITIDA","SIGGE_P",C17),"!B:B;Reliquidacion!B",A17,";",IF(C17="FACT_EMITIDA","SIGGE_P",C17),"!F:F)") -> =SUMAR.SI(FACT_EST_EFACT!B:B;Reliquidacion!B17;FACT_EST_EFACT!F:F) | H17: =CONCATENATE("=(I",A17,"/G",A17,")") -> =(I17/G17) | I17: =CONCATENATE("=SUMAR.SI(",IF(C17="FACT_EMITIDA","SIGGE_P",C17),"!B:B;Reliquidacion!B",A17,";",IF(C17="FACT_EMITIDA","SIGGE_P",C17),"!H:H)") -> =SUMAR.SI(FACT_EST_EFACT!B:B;Reliquidacion!B17;FACT_EST_EFACT!H:H) | J17: =CONCATENATE("=(F",A17,"+I",A17,")") -> =(F17+I17) | L17: =IF(VLOOKUP(B17,'MAPA DATA'!C:H,5,0)=1,"EFACT_CNE",IF(VLOOKUP(B17,'MAPA DATA'!C:H,6,0)=1,"EFACT_EST_CNE","SIN DATA")) -> EFACT_CNE | M17: =CONCATENATE("=SUMAR.SI(",L17,"!B:B;Reliquidacion!B",A17,";",L17,"!S:S)") -> =SUMAR.SI(EFACT_CNE!B:B;Reliquidacion!B17;EFACT_CNE!S:S) | N17: =CONCATENATE("=(O",A17,"/M",A17,")") -> =(O17/M17) | O17: =CONCATENATE("=SUMAR.SI(",L17,"!B:B;Reliquidacion!B",A17,";",L17,"!W:W)") -> =SUMAR.SI(EFACT_CNE!B:B;Reliquidacion!B17;EFACT_CNE!W:W) | P17: =CONCATENATE("=SUMAR.SI(",L17,"!B:B;Reliquidacion!B",A17,";",L17,"!X:X)") -> =SUMAR.SI(EFACT_CNE!B:B;Reliquidacion!B17;EFACT_CNE!X:X) | Q17: =CONCATENATE("=(R",A17,"/P",A17,")") -> =(R17/P17) | R17: =CONCATENATE("=SUMAR.SI(",L17,"!B:B;Reliquidacion!B",A17,";",L17,"!AB:AB)") -> =SUMAR.SI(EFACT_CNE!B:B;Reliquidacion!B17;EFACT_CNE!AB:AB) | S17: =CONCATENATE("=(O",A17,"+R",A17,")") -> =(O17+R17) | U17: =CONCATENATE("=(S",A17,"-J",A17,")") -> =(S17-J17) | V17: PNP 7T/2026 | W17: =VLOOKUP(V17,#REF!,2,0) -> #REF! | X17: =VLOOKUP(V17,#REF!,6,0) -> #REF! | Y17: 43156 | Z17: 44377 | AA17: =Z17-Y17 -> 1221 | AB17: =+(1+X17)^(AA17/360)-1 -> #REF! | AC17: =AB17*U17 -> #REF! | AD17: =+U17+AC17 -> #VALUE!
A18: =A17+1 -> 18 | B18: 42644 | C18: =IF(VLOOKUP(B18,'MAPA DATA'!C:F,2,0)=1,"FACT_EMITIDA",IF(VLOOKUP(B18,'MAPA DATA'!C:F,3,0)=1,"FACT_EST_EFACT",(IF(VLOOKUP(B18,'MAPA DATA'!C:F,4,0)=1,"FACT_EST_CEN","SIN DATA")))) -> FACT_EST_EFACT | D18: =CONCATENATE("=SUMAR.SI(",IF(C18="FACT_EMITIDA","SIGGE_E",C18),"!B:B;Reliquidacion!B",A18,";",IF(C18="FACT_EMITIDA","SIGGE_E",C18),"!F:F)") -> =SUMAR.SI(FACT_EST_EFACT!B:B;Reliquidacion!B18;FACT_EST_EFACT!F:F) | E18: =CONCATENATE("=(F",A18,"/D",A18,")") -> =(F18/D18) | F18: =CONCATENATE("=SUMAR.SI(",IF(C18="FACT_EMITIDA","SIGGE_E",C18),"!B:B;Reliquidacion!B",A18,";",IF(C18="FACT_EMITIDA","SIGGE_E",C18),"!H:H)") -> =SUMAR.SI(FACT_EST_EFACT!B:B;Reliquidacion!B18;FACT_EST_EFACT!H:H) | G18: =CONCATENATE("=SUMAR.SI(",IF(C18="FACT_EMITIDA","SIGGE_P",C18),"!B:B;Reliquidacion!B",A18,";",IF(C18="FACT_EMITIDA","SIGGE_P",C18),"!F:F)") -> =SUMAR.SI(FACT_EST_EFACT!B:B;Reliquidacion!B18;FACT_EST_EFACT!F:F) | H18: =CONCATENATE("=(I",A18,"/G",A18,")") -> =(I18/G18) | I18: =CONCATENATE("=SUMAR.SI(",IF(C18="FACT_EMITIDA","SIGGE_P",C18),"!B:B;Reliquidacion!B",A18,";",IF(C18="FACT_EMITIDA","SIGGE_P",C18),"!H:H)") -> =SUMAR.SI(FACT_EST_EFACT!B:B;Reliquidacion!B18;FACT_EST_EFACT!H:H) | J18: =CONCATENATE("=(F",A18,"+I",A18,")") -> =(F18+I18) | L18: =IF(VLOOKUP(B18,'MAPA DATA'!C:H,5,0)=1,"EFACT_CNE",IF(VLOOKUP(B18,'MAPA DATA'!C:H,6,0)=1,"EFACT_EST_CNE","SIN DATA")) -> EFACT_CNE | M18: =CONCATENATE("=SUMAR.SI(",L18,"!B:B;Reliquidacion!B",A18,";",L18,"!S:S)") -> =SUMAR.SI(EFACT_CNE!B:B;Reliquidacion!B18;EFACT_CNE!S:S) | N18: =CONCATENATE("=(O",A18,"/M",A18,")") -> =(O18/M18) | O18: =CONCATENATE("=SUMAR.SI(",L18,"!B:B;Reliquidacion!B",A18,";",L18,"!W:W)") -> =SUMAR.SI(EFACT_CNE!B:B;Reliquidacion!B18;EFACT_CNE!W:W) | P18: =CONCATENATE("=SUMAR.SI(",L18,"!B:B;Reliquidacion!B",A18,";",L18,"!X:X)") -> =SUMAR.SI(EFACT_CNE!B:B;Reliquidacion!B18;EFACT_CNE!X:X) | Q18: =CONCATENATE("=(R",A18,"/P",A18,")") -> =(R18/P18) | R18: =CONCATENATE("=SUMAR.SI(",L18,"!B:B;Reliquidacion!B",A18,";",L18,"!AB:AB)") -> =SUMAR.SI(EFACT_CNE!B:B;Reliquidacion!B18;EFACT_CNE!AB:AB) | S18: =CONCATENATE("=(O",A18,"+R",A18,")") -> =(O18+R18) | U18: =CONCATENATE("=(S",A18,"-J",A18,")") -> =(S18-J18) | V18: PNP 7T/2027 | W18: =VLOOKUP(V18,#REF!,2,0) -> #REF! | X18: =VLOOKUP(V18,#REF!,6,0) -> #REF! | Y18: 43156 | Z18: 44377 | AA18: =Z18-Y18 -> 1221 | AB18: =+(1+X18)^(AA18/360)-1 -> #REF! | AC18: =AB18*U18 -> #REF! | AD18: =+U18+AC18 -> #VALUE!
A19: =A18+1 -> 19 | B19: 42675 | C19: =IF(VLOOKUP(B19,'MAPA DATA'!C:F,2,0)=1,"FACT_EMITIDA",IF(VLOOKUP(B19,'MAPA DATA'!C:F,3,0)=1,"FACT_EST_EFACT",(IF(VLOOKUP(B19,'MAPA DATA'!C:F,4,0)=1,"FACT_EST_CEN","SIN DATA")))) -> FACT_EST_EFACT | D19: =CONCATENATE("=SUMAR.SI(",IF(C19="FACT_EMITIDA","SIGGE_E",C19),"!B:B;Reliquidacion!B",A19,";",IF(C19="FACT_EMITIDA","SIGGE_E",C19),"!F:F)") -> =SUMAR.SI(FACT_EST_EFACT!B:B;Reliquidacion!B19;FACT_EST_EFACT!F:F) | E19: =CONCATENATE("=(F",A19,"/D",A19,")") -> =(F19/D19) | F19: =CONCATENATE("=SUMAR.SI(",IF(C19="FACT_EMITIDA","SIGGE_E",C19),"!B:B;Reliquidacion!B",A19,";",IF(C19="FACT_EMITIDA","SIGGE_E",C19),"!H:H)") -> =SUMAR.SI(FACT_EST_EFACT!B:B;Reliquidacion!B19;FACT_EST_EFACT!H:H) | G19: =CONCATENATE("=SUMAR.SI(",IF(C19="FACT_EMITIDA","SIGGE_P",C19),"!B:B;Reliquidacion!B",A19,";",IF(C19="FACT_EMITIDA","SIGGE_P",C19),"!F:F)") -> =SUMAR.SI(FACT_EST_EFACT!B:B;Reliquidacion!B19;FACT_EST_EFACT!F:F) | H19: =CONCATENATE("=(I",A19,"/G",A19,")") -> =(I19/G19) | I19: =CONCATENATE("=SUMAR.SI(",IF(C19="FACT_EMITIDA","SIGGE_P",C19),"!B:B;Reliquidacion!B",A19,";",IF(C19="FACT_EMITIDA","SIGGE_P",C19),"!H:H)") -> =SUMAR.SI(FACT_EST_EFACT!B:B;Reliquidacion!B19;FACT_EST_EFACT!H:H) | J19: =CONCATENATE("=(F",A19,"+I",A19,")") -> =(F19+I19) | L19: =IF(VLOOKUP(B19,'MAPA DATA'!C:H,5,0)=1,"EFACT_CNE",IF(VLOOKUP(B19,'MAPA DATA'!C:H,6,0)=1,"EFACT_EST_CNE","SIN DATA")) -> EFACT_CNE | M19: =CONCATENATE("=SUMAR.SI(",L19,"!B:B;Reliquidacion!B",A19,";",L19,"!S:S)") -> =SUMAR.SI(EFACT_CNE!B:B;Reliquidacion!B19;EFACT_CNE!S:S) | N19: =CONCATENATE("=(O",A19,"/M",A19,")") -> =(O19/M19) | O19: =CONCATENATE("=SUMAR.SI(",L19,"!B:B;Reliquidacion!B",A19,";",L19,"!W:W)") -> =SUMAR.SI(EFACT_CNE!B:B;Reliquidacion!B19;EFACT_CNE!W:W) | P19: =CONCATENATE("=SUMAR.SI(",L19,"!B:B;Reliquidacion!B",A19,";",L19,"!X:X)") -> =SUMAR.SI(EFACT_CNE!B:B;Reliquidacion!B19;EFACT_CNE!X:X) | Q19: =CONCATENATE("=(R",A19,"/P",A19,")") -> =(R19/P19) | R19: =CONCATENATE("=SUMAR.SI(",L19,"!B:B;Reliquidacion!B",A19,";",L19,"!AB:AB)") -> =SUMAR.SI(EFACT_CNE!B:B;Reliquidacion!B19;EFACT_CNE!AB:AB) | S19: =CONCATENATE("=(O",A19,"+R",A19,")") -> =(O19+R19) | U19: =CONCATENATE("=(S",A19,"-J",A19,")") -> =(S19-J19) | V19: PNP 7T/2028 | W19: =VLOOKUP(V19,#REF!,2,0) -> #REF! | X19: =VLOOKUP(V19,#REF!,6,0) -> #REF! | Y19: 43156 | Z19: 44377 | AA19: =Z19-Y19 -> 1221 | AB19: =+(1+X19)^(AA19/360)-1 -> #REF! | AC19: =AB19*U19 -> #REF! | AD19: =+U19+AC19 -> #VALUE!
A20: =A19+1 -> 20 | B20: 42705 | C20: =IF(VLOOKUP(B20,'MAPA DATA'!C:F,2,0)=1,"FACT_EMITIDA",IF(VLOOKUP(B20,'MAPA DATA'!C:F,3,0)=1,"FACT_EST_EFACT",(IF(VLOOKUP(B20,'MAPA DATA'!C:F,4,0)=1,"FACT_EST_CEN","SIN DATA")))) -> FACT_EST_EFACT | D20: =CONCATENATE("=SUMAR.SI(",IF(C20="FACT_EMITIDA","SIGGE_E",C20),"!B:B;Reliquidacion!B",A20,";",IF(C20="FACT_EMITIDA","SIGGE_E",C20),"!F:F)") -> =SUMAR.SI(FACT_EST_EFACT!B:B;Reliquidacion!B20;FACT_EST_EFACT!F:F) | E20: =CONCATENATE("=(F",A20,"/D",A20,")") -> =(F20/D20) | F20: =CONCATENATE("=SUMAR.SI(",IF(C20="FACT_EMITIDA","SIGGE_E",C20),"!B:B;Reliquidacion!B",A20,";",IF(C20="FACT_EMITIDA","SIGGE_E",C20),"!H:H)") -> =SUMAR.SI(FACT_EST_EFACT!B:B;Reliquidacion!B20;FACT_EST_EFACT!H:H) | G20: =CONCATENATE("=SUMAR.SI(",IF(C20="FACT_EMITIDA","SIGGE_P",C20),"!B:B;Reliquidacion!B",A20,";",IF(C20="FACT_EMITIDA","SIGGE_P",C20),"!F:F)") -> =SUMAR.SI(FACT_EST_EFACT!B:B;Reliquidacion!B20;FACT_EST_EFACT!F:F) | H20: =CONCATENATE("=(I",A20,"/G",A20,")") -> =(I20/G20) | I20: =CONCATENATE("=SUMAR.SI(",IF(C20="FACT_EMITIDA","SIGGE_P",C20),"!B:B;Reliquidacion!B",A20,";",IF(C20="FACT_EMITIDA","SIGGE_P",C20),"!H:H)") -> =SUMAR.SI(FACT_EST_EFACT!B:B;Reliquidacion!B20;FACT_EST_EFACT!H:H) | J20: =CONCATENATE("=(F",A20,"+I",A20,")") -> =(F20+I20) | L20: =IF(VLOOKUP(B20,'MAPA DATA'!C:H,5,0)=1,"EFACT_CNE",IF(VLOOKUP(B20,'MAPA DATA'!C:H,6,0)=1,"EFACT_EST_CNE","SIN DATA")) -> EFACT_CNE | M20: =CONCATENATE("=SUMAR.SI(",L20,"!B:B;Reliquidacion!B",A20,";",L20,"!S:S)") -> =SUMAR.SI(EFACT_CNE!B:B;Reliquidacion!B20;EFACT_CNE!S:S) | N20: =CONCATENATE("=(O",A20,"/M",A20,")") -> =(O20/M20) | O20: =CONCATENATE("=SUMAR.SI(",L20,"!B:B;Reliquidacion!B",A20,";",L20,"!W:W)") -> =SUMAR.SI(EFACT_CNE!B:B;Reliquidacion!B20;EFACT_CNE!W:W) | P20: =CONCATENATE("=SUMAR.SI(",L20,"!B:B;Reliquidacion!B",A20,";",L20,"!X:X)") -> =SUMAR.SI(EFACT_CNE!B:B;Reliquidacion!B20;EFACT_CNE!X:X) | Q20: =CONCATENATE("=(R",A20,"/P",A20,")") -> =(R20/P20) | R20: =CONCATENATE("=SUMAR.SI(",L20,"!B:B;Reliquidacion!B",A20,";",L20,"!AB:AB)") -> =SUMAR.SI(EFACT_CNE!B:B;Reliquidacion!B20;EFACT_CNE!AB:AB) | S20: =CONCATENATE("=(O",A20,"+R",A20,")") -> =(O20+R20) | U20: =CONCATENATE("=(S",A20,"-J",A20,")") -> =(S20-J20) | V20: PNP 7T/2029 | W20: =VLOOKUP(V20,#REF!,2,0) -> #REF! | X20: =VLOOKUP(V20,#REF!,6,0) -> #REF! | Y20: 43156 | Z20: 44377 | AA20: =Z20-Y20 -> 1221 | AB20: =+(1+X20)^(AA20/360)-1 -> #REF! | AC20: =AB20*U20 -> #REF! | AD20: =+U20+AC20 -> #VALUE!
A21: =A20+1 -> 21 | B21: 42736 | C21: =IF(VLOOKUP(B21,'MAPA DATA'!C:F,2,0)=1,"FACT_EMITIDA",IF(VLOOKUP(B21,'MAPA DATA'!C:F,3,0)=1,"FACT_EST_EFACT",(IF(VLOOKUP(B21,'MAPA DATA'!C:F,4,0)=1,"FACT_EST_CEN","SIN DATA")))) -> SIN DATA | D21: =CONCATENATE("=SUMAR.SI(",IF(C21="FACT_EMITIDA","SIGGE_E",C21),"!B:B;Reliquidacion!B",A21,";",IF(C21="FACT_EMITIDA","SIGGE_E",C21),"!F:F)") -> =SUMAR.SI(SIN DATA!B:B;Reliquidacion!B21;SIN DATA!F:F) | E21: =CONCATENATE("=(F",A21,"/D",A21,")") -> =(F21/D21) | F21: =CONCATENATE("=SUMAR.SI(",IF(C21="FACT_EMITIDA","SIGGE_E",C21),"!B:B;Reliquidacion!B",A21,";",IF(C21="FACT_EMITIDA","SIGGE_E",C21),"!H:H)") -> =SUMAR.SI(SIN DATA!B:B;Reliquidacion!B21;SIN DATA!H:H) | G21: =CONCATENATE("=SUMAR.SI(",IF(C21="FACT_EMITIDA","SIGGE_P",C21),"!B:B;Reliquidacion!B",A21,";",IF(C21="FACT_EMITIDA","SIGGE_P",C21),"!F:F)") -> =SUMAR.SI(SIN DATA!B:B;Reliquidacion!B21;SIN DATA!F:F) | H21: =CONCATENATE("=(I",A21,"/G",A21,")") -> =(I21/G21) | I21: =CONCATENATE("=SUMAR.SI(",IF(C21="FACT_EMITIDA","SIGGE_P",C21),"!B:B;Reliquidacion!B",A21,";",IF(C21="FACT_EMITIDA","SIGGE_P",C21),"!H:H)") -> =SUMAR.SI(SIN DATA!B:B;Reliquidacion!B21;SIN DATA!H:H) | J21: =CONCATENATE("=(F",A21,"+I",A21,")") -> =(F21+I21) | L21: =IF(VLOOKUP(B21,'MAPA DATA'!C:H,5,0)=1,"EFACT_CNE",IF(VLOOKUP(B21,'MAPA DATA'!C:H,6,0)=1,"EFACT_EST_CNE","SIN DATA")) -> EFACT_CNE | M21: =CONCATENATE("=SUMAR.SI(",L21,"!B:B;Reliquidacion!B",A21,";",L21,"!S:S)") -> =SUMAR.SI(EFACT_CNE!B:B;Reliquidacion!B21;EFACT_CNE!S:S) | N21: =CONCATENATE("=(O",A21,"/M",A21,")") -> =(O21/M21) | O21: =CONCATENATE("=SUMAR.SI(",L21,"!B:B;Reliquidacion!B",A21,";",L21,"!W:W)") -> =SUMAR.SI(EFACT_CNE!B:B;Reliquidacion!B21;EFACT_CNE!W:W) | P21: =CONCATENATE("=SUMAR.SI(",L21,"!B:B;Reliquidacion!B",A21,";",L21,"!X:X)") -> =SUMAR.SI(EFACT_CNE!B:B;Reliquidacion!B21;EFACT_CNE!X:X) | Q21: =CONCATENATE("=(R",A21,"/P",A21,")") -> =(R21/P21) | R21: =CONCATENATE("=SUMAR.SI(",L21,"!B:B;Reliquidacion!B",A21,";",L21,"!AB:AB)") -> =SUMAR.SI(EFACT_CNE!B:B;Reliquidacion!B21;EFACT_CNE!AB:AB) | S21: =CONCATENATE("=(O",A21,"+R",A21,")") -> =(O21+R21) | U21: =CONCATENATE("=(S",A21,"-J",A21,")") -> =(S21-J21) | V21: PNP 7T/2030 | W21: =VLOOKUP(V21,#REF!,2,0) -> #REF! | X21: =VLOOKUP(V21,#REF!,6,0) -> #REF! | Y21: 43156 | Z21: 44377 | AA21: =Z21-Y21 -> 1221 | AB21: =+(1+X21)^(AA21/360)-1 -> #REF! | AC21: =AB21*U21 -> #REF! | AD21: =+U21+AC21 -> #VALUE!
A22: =A21+1 -> 22 | B22: 42767 | C22: =IF(VLOOKUP(B22,'MAPA DATA'!C:F,2,0)=1,"FACT_EMITIDA",IF(VLOOKUP(B22,'MAPA DATA'!C:F,3,0)=1,"FACT_EST_EFACT",(IF(VLOOKUP(B22,'MAPA DATA'!C:F,4,0)=1,"FACT_EST_CEN","SIN DATA")))) -> FACT_EST_EFACT | D22: =CONCATENATE("=SUMAR.SI(",IF(C22="FACT_EMITIDA","SIGGE_E",C22),"!B:B;Reliquidacion!B",A22,";",IF(C22="FACT_EMITIDA","SIGGE_E",C22),"!F:F)") -> =SUMAR.SI(FACT_EST_EFACT!B:B;Reliquidacion!B22;FACT_EST_EFACT!F:F) | E22: =CONCATENATE("=(F",A22,"/D",A22,")") -> =(F22/D22) | F22: =CONCATENATE("=SUMAR.SI(",IF(C22="FACT_EMITIDA","SIGGE_E",C22),"!B:B;Reliquidacion!B",A22,";",IF(C22="FACT_EMITIDA","SIGGE_E",C22),"!H:H)") -> =SUMAR.SI(FACT_EST_EFACT!B:B;Reliquidacion!B22;FACT_EST_EFACT!H:H) | G22: =CONCATENATE("=SUMAR.SI(",IF(C22="FACT_EMITIDA","SIGGE_P",C22),"!B:B;Reliquidacion!B",A22,";",IF(C22="FACT_EMITIDA","SIGGE_P",C22),"!F:F)") -> =SUMAR.SI(FACT_EST_EFACT!B:B;Reliquidacion!B22;FACT_EST_EFACT!F:F) | H22: =CONCATENATE("=(I",A22,"/G",A22,")") -> =(I22/G22) | I22: =CONCATENATE("=SUMAR.SI(",IF(C22="FACT_EMITIDA","SIGGE_P",C22),"!B:B;Reliquidacion!B",A22,";",IF(C22="FACT_EMITIDA","SIGGE_P",C22),"!H:H)") -> =SUMAR.SI(FACT_EST_EFACT!B:B;Reliquidacion!B22;FACT_EST_EFACT!H:H) | J22: =CONCATENATE("=(F",A22,"+I",A22,")") -> =(F22+I22) | L22: =IF(VLOOKUP(B22,'MAPA DATA'!C:H,5,0)=1,"EFACT_CNE",IF(VLOOKUP(B22,'MAPA DATA'!C:H,6,0)=1,"EFACT_EST_CNE","SIN DATA")) -> EFACT_CNE | M22: =CONCATENATE("=SUMAR.SI(",L22,"!B:B;Reliquidacion!B",A22,";",L22,"!S:S)") -> =SUMAR.SI(EFACT_CNE!B:B;Reliquidacion!B22;EFACT_CNE!S:S) | N22: =CONCATENATE("=(O",A22,"/M",A22,")") -> =(O22/M22) | O22: =CONCATENATE("=SUMAR.SI(",L22,"!B:B;Reliquidacion!B",A22,";",L22,"!W:W)") -> =SUMAR.SI(EFACT_CNE!B:B;Reliquidacion!B22;EFACT_CNE!W:W) | P22: =CONCATENATE("=SUMAR.SI(",L22,"!B:B;Reliquidacion!B",A22,";",L22,"!X:X)") -> =SUMAR.SI(EFACT_CNE!B:B;Reliquidacion!B22;EFACT_CNE!X:X) | Q22: =CONCATENATE("=(R",A22,"/P",A22,")") -> =(R22/P22) | R22: =CONCATENATE("=SUMAR.SI(",L22,"!B:B;Reliquidacion!B",A22,";",L22,"!AB:AB)") -> =SUMAR.SI(EFACT_CNE!B:B;Reliquidacion!B22;EFACT_CNE!AB:AB) | S22: =CONCATENATE("=(O",A22,"+R",A22,")") -> =(O22+R22) | U22: =CONCATENATE("=(S",A22,"-J",A22,")") -> =(S22-J22) | V22: PNP 7T/2031 | W22: =VLOOKUP(V22,#REF!,2,0) -> #REF! | X22: =VLOOKUP(V22,#REF!,6,0) -> #REF! | Y22: 43156 | Z22: 44377 | AA22: =Z22-Y22 -> 1221 | AB22: =+(1+X22)^(AA22/360)-1 -> #REF! | AC22: =AB22*U22 -> #REF! | AD22: =+U22+AC22 -> #VALUE!
A23: =A22+1 -> 23 | B23: 42795 | C23: =IF(VLOOKUP(B23,'MAPA DATA'!C:F,2,0)=1,"FACT_EMITIDA",IF(VLOOKUP(B23,'MAPA DATA'!C:F,3,0)=1,"FACT_EST_EFACT",(IF(VLOOKUP(B23,'MAPA DATA'!C:F,4,0)=1,"FACT_EST_CEN","SIN DATA")))) -> FACT_EST_EFACT | D23: =CONCATENATE("=SUMAR.SI(",IF(C23="FACT_EMITIDA","SIGGE_E",C23),"!B:B;Reliquidacion!B",A23,";",IF(C23="FACT_EMITIDA","SIGGE_E",C23),"!F:F)") -> =SUMAR.SI(FACT_EST_EFACT!B:B;Reliquidacion!B23;FACT_EST_EFACT!F:F) | E23: =CONCATENATE("=(F",A23,"/D",A23,")") -> =(F23/D23) | F23: =CONCATENATE("=SUMAR.SI(",IF(C23="FACT_EMITIDA","SIGGE_E",C23),"!B:B;Reliquidacion!B",A23,";",IF(C23="FACT_EMITIDA","SIGGE_E",C23),"!H:H)") -> =SUMAR.SI(FACT_EST_EFACT!B:B;Reliquidacion!B23;FACT_EST_EFACT!H:H) | G23: =CONCATENATE("=SUMAR.SI(",IF(C23="FACT_EMITIDA","SIGGE_P",C23),"!B:B;Reliquidacion!B",A23,";",IF(C23="FACT_EMITIDA","SIGGE_P",C23),"!F:F)") -> =SUMAR.SI(FACT_EST_EFACT!B:B;Reliquidacion!B23;FACT_EST_EFACT!F:F) | H23: =CONCATENATE("=(I",A23,"/G",A23,")") -> =(I23/G23) | I23: =CONCATENATE("=SUMAR.SI(",IF(C23="FACT_EMITIDA","SIGGE_P",C23),"!B:B;Reliquidacion!B",A23,";",IF(C23="FACT_EMITIDA","SIGGE_P",C23),"!H:H)") -> =SUMAR.SI(FACT_EST_EFACT!B:B;Reliquidacion!B23;FACT_EST_EFACT!H:H) | J23: =CONCATENATE("=(F",A23,"+I",A23,")") -> =(F23+I23) | L23: =IF(VLOOKUP(B23,'MAPA DATA'!C:H,5,0)=1,"EFACT_CNE",IF(VLOOKUP(B23,'MAPA DATA'!C:H,6,0)=1,"EFACT_EST_CNE","SIN DATA")) -> EFACT_CNE | M23: =CONCATENATE("=SUMAR.SI(",L23,"!B:B;Reliquidacion!B",A23,";",L23,"!S:S)") -> =SUMAR.SI(EFACT_CNE!B:B;Reliquidacion!B23;EFACT_CNE!S:S) | N23: =CONCATENATE("=(O",A23,"/M",A23,")") -> =(O23/M23) | O23: =CONCATENATE("=SUMAR.SI(",L23,"!B:B;Reliquidacion!B",A23,";",L23,"!W:W)") -> =SUMAR.SI(EFACT_CNE!B:B;Reliquidacion!B23;EFACT_CNE!W:W) | P23: =CONCATENATE("=SUMAR.SI(",L23,"!B:B;Reliquidacion!B",A23,";",L23,"!X:X)") -> =SUMAR.SI(EFACT_CNE!B:B;Reliquidacion!B23;EFACT_CNE!X:X) | Q23: =CONCATENATE("=(R",A23,"/P",A23,")") -> =(R23/P23) | R23: =CONCATENATE("=SUMAR.SI(",L23,"!B:B;Reliquidacion!B",A23,";",L23,"!AB:AB)") -> =SUMAR.SI(EFACT_CNE!B:B;Reliquidacion!B23;EFACT_CNE!AB:AB) | S23: =CONCATENATE("=(O",A23,"+R",A23,")") -> =(O23+R23) | U23: =CONCATENATE("=(S",A23,"-J",A23,")") -> =(S23-J23)
A24: =A23+1 -> 24 | B24: 42826 | C24: =IF(VLOOKUP(B24,'MAPA DATA'!C:F,2,0)=1,"FACT_EMITIDA",IF(VLOOKUP(B24,'MAPA DATA'!C:F,3,0)=1,"FACT_EST_EFACT",(IF(VLOOKUP(B24,'MAPA DATA'!C:F,4,0)=1,"FACT_EST_CEN","SIN DATA")))) -> FACT_EST_EFACT | D24: =CONCATENATE("=SUMAR.SI(",IF(C24="FACT_EMITIDA","SIGGE_E",C24),"!B:B;Reliquidacion!B",A24,";",IF(C24="FACT_EMITIDA","SIGGE_E",C24),"!F:F)") -> =SUMAR.SI(FACT_EST_EFACT!B:B;Reliquidacion!B24;FACT_EST_EFACT!F:F) | E24: =CONCATENATE("=(F",A24,"/D",A24,")") -> =(F24/D24) | F24: =CONCATENATE("=SUMAR.SI(",IF(C24="FACT_EMITIDA","SIGGE_E",C24),"!B:B;Reliquidacion!B",A24,";",IF(C24="FACT_EMITIDA","SIGGE_E",C24),"!H:H)") -> =SUMAR.SI(FACT_EST_EFACT!B:B;Reliquidacion!B24;FACT_EST_EFACT!H:H) | G24: =CONCATENATE("=SUMAR.SI(",IF(C24="FACT_EMITIDA","SIGGE_P",C24),"!B:B;Reliquidacion!B",A24,";",IF(C24="FACT_EMITIDA","SIGGE_P",C24),"!F:F)") -> =SUMAR.SI(FACT_EST_EFACT!B:B;Reliquidacion!B24;FACT_EST_EFACT!F:F) | H24: =CONCATENATE("=(I",A24,"/G",A24,")") -> =(I24/G24) | I24: =CONCATENATE("=SUMAR.SI(",IF(C24="FACT_EMITIDA","SIGGE_P",C24),"!B:B;Reliquidacion!B",A24,";",IF(C24="FACT_EMITIDA","SIGGE_P",C24),"!H:H)") -> =SUMAR.SI(FACT_EST_EFACT!B:B;Reliquidacion!B24;FACT_EST_EFACT!H:H) | J24: =CONCATENATE("=(F",A24,"+I",A24,")") -> =(F24+I24) | L24: =IF(VLOOKUP(B24,'MAPA DATA'!C:H,5,0)=1,"EFACT_CNE",IF(VLOOKUP(B24,'MAPA DATA'!C:H,6,0)=1,"EFACT_EST_CNE","SIN DATA")) -> EFACT_CNE | M24: =CONCATENATE("=SUMAR.SI(",L24,"!B:B;Reliquidacion!B",A24,";",L24,"!S:S)") -> =SUMAR.SI(EFACT_CNE!B:B;Reliquidacion!B24;EFACT_CNE!S:S) | N24: =CONCATENATE("=(O",A24,"/M",A24,")") -> =(O24/M24) | O24: =CONCATENATE("=SUMAR.SI(",L24,"!B:B;Reliquidacion!B",A24,";",L24,"!W:W)") -> =SUMAR.SI(EFACT_CNE!B:B;Reliquidacion!B24;EFACT_CNE!W:W) | P24: =CONCATENATE("=SUMAR.SI(",L24,"!B:B;Reliquidacion!B",A24,";",L24,"!X:X)") -> =SUMAR.SI(EFACT_CNE!B:B;Reliquidacion!B24;EFACT_CNE!X:X) | Q24: =CONCATENATE("=(R",A24,"/P",A24,")") -> =(R24/P24) | R24: =CONCATENATE("=SUMAR.SI(",L24,"!B:B;Reliquidacion!B",A24,";",L24,"!AB:AB)") -> =SUMAR.SI(EFACT_CNE!B:B;Reliquidacion!B24;EFACT_CNE!AB:AB) | S24: =CONCATENATE("=(O",A24,"+R",A24,")") -> =(O24+R24) | U24: =CONCATENATE("=(S",A24,"-J",A24,")") -> =(S24-J24)
A25: =A24+1 -> 25 | B25: 42856 | C25: =IF(VLOOKUP(B25,'MAPA DATA'!C:F,2,0)=1,"FACT_EMITIDA",IF(VLOOKUP(B25,'MAPA DATA'!C:F,3,0)=1,"FACT_EST_EFACT",(IF(VLOOKUP(B25,'MAPA DATA'!C:F,4,0)=1,"FACT_EST_CEN","SIN DATA")))) -> FACT_EST_EFACT | D25: =CONCATENATE("=SUMAR.SI(",IF(C25="FACT_EMITIDA","SIGGE_E",C25),"!B:B;Reliquidacion!B",A25,";",IF(C25="FACT_EMITIDA","SIGGE_E",C25),"!F:F)") -> =SUMAR.SI(FACT_EST_EFACT!B:B;Reliquidacion!B25;FACT_EST_EFACT!F:F) | E25: =CONCATENATE("=(F",A25,"/D",A25,")") -> =(F25/D25) | F25: =CONCATENATE("=SUMAR.SI(",IF(C25="FACT_EMITIDA","SIGGE_E",C25),"!B:B;Reliquidacion!B",A25,";",IF(C25="FACT_EMITIDA","SIGGE_E",C25),"!H:H)") -> =SUMAR.SI(FACT_EST_EFACT!B:B;Reliquidacion!B25;FACT_EST_EFACT!H:H) | G25: =CONCATENATE("=SUMAR.SI(",IF(C25="FACT_EMITIDA","SIGGE_P",C25),"!B:B;Reliquidacion!B",A25,";",IF(C25="FACT_EMITIDA","SIGGE_P",C25),"!F:F)") -> =SUMAR.SI(FACT_EST_EFACT!B:B;Reliquidacion!B25;FACT_EST_EFACT!F:F) | H25: =CONCATENATE("=(I",A25,"/G",A25,")") -> =(I25/G25) | I25: =CONCATENATE("=SUMAR.SI(",IF(C25="FACT_EMITIDA","SIGGE_P",C25),"!B:B;Reliquidacion!B",A25,";",IF(C25="FACT_EMITIDA","SIGGE_P",C25),"!H:H)") -> =SUMAR.SI(FACT_EST_EFACT!B:B;Reliquidacion!B25;FACT_EST_EFACT!H:H) | J25: =CONCATENATE("=(F",A25,"+I",A25,")") -> =(F25+I25) | L25: =IF(VLOOKUP(B25,'MAPA DATA'!C:H,5,0)=1,"EFACT_CNE",IF(VLOOKUP(B25,'MAPA DATA'!C:H,6,0)=1,"EFACT_EST_CNE","SIN DATA")) -> EFACT_CNE | M25: =CONCATENATE("=SUMAR.SI(",L25,"!B:B;Reliquidacion!B",A25,";",L25,"!S:S)") -> =SUMAR.SI(EFACT_CNE!B:B;Reliquidacion!B25;EFACT_CNE!S:S) | N25: =CONCATENATE("=(O",A25,"/M",A25,")") -> =(O25/M25) | O25: =CONCATENATE("=SUMAR.SI(",L25,"!B:B;Reliquidacion!B",A25,";",L25,"!W:W)") -> =SUMAR.SI(EFACT_CNE!B:B;Reliquidacion!B25;EFACT_CNE!W:W) | P25: =CONCATENATE("=SUMAR.SI(",L25,"!B:B;Reliquidacion!B",A25,";",L25,"!X:X)") -> =SUMAR.SI(EFACT_CNE!B:B;Reliquidacion!B25;EFACT_CNE!X:X) | Q25: =CONCATENATE("=(R",A25,"/P",A25,")") -> =(R25/P25) | R25: =CONCATENATE("=SUMAR.SI(",L25,"!B:B;Reliquidacion!B",A25,";",L25,"!AB:AB)") -> =SUMAR.SI(EFACT_CNE!B:B;Reliquidacion!B25;EFACT_CNE!AB:AB) | S25: =CONCATENATE("=(O",A25,"+R",A25,")") -> =(O25+R25) | U25: =CONCATENATE("=(S",A25,"-J",A25,")") -> =(S25-J25)
A26: =A25+1 -> 26 | B26: 42887 | C26: =IF(VLOOKUP(B26,'MAPA DATA'!C:F,2,0)=1,"FACT_EMITIDA",IF(VLOOKUP(B26,'MAPA DATA'!C:F,3,0)=1,"FACT_EST_EFACT",(IF(VLOOKUP(B26,'MAPA DATA'!C:F,4,0)=1,"FACT_EST_CEN","SIN DATA")))) -> FACT_EST_EFACT | D26: =CONCATENATE("=SUMAR.SI(",IF(C26="FACT_EMITIDA","SIGGE_E",C26),"!B:B;Reliquidacion!B",A26,";",IF(C26="FACT_EMITIDA","SIGGE_E",C26),"!F:F)") -> =SUMAR.SI(FACT_EST_EFACT!B:B;Reliquidacion!B26;FACT_EST_EFACT!F:F) | E26: =CONCATENATE("=(F",A26,"/D",A26,")") -> =(F26/D26) | F26: =CONCATENATE("=SUMAR.SI(",IF(C26="FACT_EMITIDA","SIGGE_E",C26),"!B:B;Reliquidacion!B",A26,";",IF(C26="FACT_EMITIDA","SIGGE_E",C26),"!H:H)") -> =SUMAR.SI(FACT_EST_EFACT!B:B;Reliquidacion!B26;FACT_EST_EFACT!H:H) | G26: =CONCATENATE("=SUMAR.SI(",IF(C26="FACT_EMITIDA","SIGGE_P",C26),"!B:B;Reliquidacion!B",A26,";",IF(C26="FACT_EMITIDA","SIGGE_P",C26),"!F:F)") -> =SUMAR.SI(FACT_EST_EFACT!B:B;Reliquidacion!B26;FACT_EST_EFACT!F:F) | H26: =CONCATENATE("=(I",A26,"/G",A26,")") -> =(I26/G26) | I26: =CONCATENATE("=SUMAR.SI(",IF(C26="FACT_EMITIDA","SIGGE_P",C26),"!B:B;Reliquidacion!B",A26,";",IF(C26="FACT_EMITIDA","SIGGE_P",C26),"!H:H)") -> =SUMAR.SI(FACT_EST_EFACT!B:B;Reliquidacion!B26;FACT_EST_EFACT!H:H) | J26: =CONCATENATE("=(F",A26,"+I",A26,")") -> =(F26+I26) | L26: =IF(VLOOKUP(B26,'MAPA DATA'!C:H,5,0)=1,"EFACT_CNE",IF(VLOOKUP(B26,'MAPA DATA'!C:H,6,0)=1,"EFACT_EST_CNE","SIN DATA")) -> EFACT_CNE | M26: =CONCATENATE("=SUMAR.SI(",L26,"!B:B;Reliquidacion!B",A26,";",L26,"!S:S)") -> =SUMAR.SI(EFACT_CNE!B:B;Reliquidacion!B26;EFACT_CNE!S:S) | N26: =CONCATENATE("=(O",A26,"/M",A26,")") -> =(O26/M26) | O26: =CONCATENATE("=SUMAR.SI(",L26,"!B:B;Reliquidacion!B",A26,";",L26,"!W:W)") -> =SUMAR.SI(EFACT_CNE!B:B;Reliquidacion!B26;EFACT_CNE!W:W) | P26: =CONCATENATE("=SUMAR.SI(",L26,"!B:B;Reliquidacion!B",A26,";",L26,"!X:X)") -> =SUMAR.SI(EFACT_CNE!B:B;Reliquidacion!B26;EFACT_CNE!X:X) | Q26: =CONCATENATE("=(R",A26,"/P",A26,")") -> =(R26/P26) | R26: =CONCATENATE("=SUMAR.SI(",L26,"!B:B;Reliquidacion!B",A26,";",L26,"!AB:AB)") -> =SUMAR.SI(EFACT_CNE!B:B;Reliquidacion!B26;EFACT_CNE!AB:AB) | S26: =CONCATENATE("=(O",A26,"+R",A26,")") -> =(O26+R26) | U26: =CONCATENATE("=(S",A26,"-J",A26,")") -> =(S26-J26)
A27: =A26+1 -> 27 | B27: 42917 | C27: =IF(VLOOKUP(B27,'MAPA DATA'!C:F,2,0)=1,"FACT_EMITIDA",IF(VLOOKUP(B27,'MAPA DATA'!C:F,3,0)=1,"FACT_EST_EFACT",(IF(VLOOKUP(B27,'MAPA DATA'!C:F,4,0)=1,"FACT_EST_CEN","SIN DATA")))) -> FACT_EST_EFACT | D27: =CONCATENATE("=SUMAR.SI(",IF(C27="FACT_EMITIDA","SIGGE_E",C27),"!B:B;Reliquidacion!B",A27,";",IF(C27="FACT_EMITIDA","SIGGE_E",C27),"!F:F)") -> =SUMAR.SI(FACT_EST_EFACT!B:B;Reliquidacion!B27;FACT_EST_EFACT!F:F) | E27: =CONCATENATE("=(F",A27,"/D",A27,")") -> =(F27/D27) | F27: =CONCATENATE("=SUMAR.SI(",IF(C27="FACT_EMITIDA","SIGGE_E",C27),"!B:B;Reliquidacion!B",A27,";",IF(C27="FACT_EMITIDA","SIGGE_E",C27),"!H:H)") -> =SUMAR.SI(FACT_EST_EFACT!B:B;Reliquidacion!B27;FACT_EST_EFACT!H:H) | G27: =CONCATENATE("=SUMAR.SI(",IF(C27="FACT_EMITIDA","SIGGE_P",C27),"!B:B;Reliquidacion!B",A27,";",IF(C27="FACT_EMITIDA","SIGGE_P",C27),"!F:F)") -> =SUMAR.SI(FACT_EST_EFACT!B:B;Reliquidacion!B27;FACT_EST_EFACT!F:F) | H27: =CONCATENATE("=(I",A27,"/G",A27,")") -> =(I27/G27) | I27: =CONCATENATE("=SUMAR.SI(",IF(C27="FACT_EMITIDA","SIGGE_P",C27),"!B:B;Reliquidacion!B",A27,";",IF(C27="FACT_EMITIDA","SIGGE_P",C27),"!H:H)") -> =SUMAR.SI(FACT_EST_EFACT!B:B;Reliquidacion!B27;FACT_EST_EFACT!H:H) | J27: =CONCATENATE("=(F",A27,"+I",A27,")") -> =(F27+I27) | L27: =IF(VLOOKUP(B27,'MAPA DATA'!C:H,5,0)=1,"EFACT_CNE",IF(VLOOKUP(B27,'MAPA DATA'!C:H,6,0)=1,"EFACT_EST_CNE","SIN DATA")) -> EFACT_CNE | M27: =CONCATENATE("=SUMAR.SI(",L27,"!B:B;Reliquidacion!B",A27,";",L27,"!S:S)") -> =SUMAR.SI(EFACT_CNE!B:B;Reliquidacion!B27;EFACT_CNE!S:S) | N27: =CONCATENATE("=(O",A27,"/M",A27,")") -> =(O27/M27) | O27: =CONCATENATE("=SUMAR.SI(",L27,"!B:B;Reliquidacion!B",A27,";",L27,"!W:W)") -> =SUMAR.SI(EFACT_CNE!B:B;Reliquidacion!B27;EFACT_CNE!W:W) | P27: =CONCATENATE("=SUMAR.SI(",L27,"!B:B;Reliquidacion!B",A27,";",L27,"!X:X)") -> =SUMAR.SI(EFACT_CNE!B:B;Reliquidacion!B27;EFACT_CNE!X:X) | Q27: =CONCATENATE("=(R",A27,"/P",A27,")") -> =(R27/P27) | R27: =CONCATENATE("=SUMAR.SI(",L27,"!B:B;Reliquidacion!B",A27,";",L27,"!AB:AB)") -> =SUMAR.SI(EFACT_CNE!B:B;Reliquidacion!B27;EFACT_CNE!AB:AB) | S27: =CONCATENATE("=(O",A27,"+R",A27,")") -> =(O27+R27) | U27: =CONCATENATE("=(S",A27,"-J",A27,")") -> =(S27-J27)
A28: =A27+1 -> 28 | B28: 42948 | C28: =IF(VLOOKUP(B28,'MAPA DATA'!C:F,2,0)=1,"FACT_EMITIDA",IF(VLOOKUP(B28,'MAPA DATA'!C:F,3,0)=1,"FACT_EST_EFACT",(IF(VLOOKUP(B28,'MAPA DATA'!C:F,4,0)=1,"FACT_EST_CEN","SIN DATA")))) -> FACT_EST_EFACT | D28: =CONCATENATE("=SUMAR.SI(",IF(C28="FACT_EMITIDA","SIGGE_E",C28),"!B:B;Reliquidacion!B",A28,";",IF(C28="FACT_EMITIDA","SIGGE_E",C28),"!F:F)") -> =SUMAR.SI(FACT_EST_EFACT!B:B;Reliquidacion!B28;FACT_EST_EFACT!F:F) | E28: =CONCATENATE("=(F",A28,"/D",A28,")") -> =(F28/D28) | F28: =CONCATENATE("=SUMAR.SI(",IF(C28="FACT_EMITIDA","SIGGE_E",C28),"!B:B;Reliquidacion!B",A28,";",IF(C28="FACT_EMITIDA","SIGGE_E",C28),"!H:H)") -> =SUMAR.SI(FACT_EST_EFACT!B:B;Reliquidacion!B28;FACT_EST_EFACT!H:H) | G28: =CONCATENATE("=SUMAR.SI(",IF(C28="FACT_EMITIDA","SIGGE_P",C28),"!B:B;Reliquidacion!B",A28,";",IF(C28="FACT_EMITIDA","SIGGE_P",C28),"!F:F)") -> =SUMAR.SI(FACT_EST_EFACT!B:B;Reliquidacion!B28;FACT_EST_EFACT!F:F) | H28: =CONCATENATE("=(I",A28,"/G",A28,")") -> =(I28/G28) | I28: =CONCATENATE("=SUMAR.SI(",IF(C28="FACT_EMITIDA","SIGGE_P",C28),"!B:B;Reliquidacion!B",A28,";",IF(C28="FACT_EMITIDA","SIGGE_P",C28),"!H:H)") -> =SUMAR.SI(FACT_EST_EFACT!B:B;Reliquidacion!B28;FACT_EST_EFACT!H:H) | J28: =CONCATENATE("=(F",A28,"+I",A28,")") -> =(F28+I28) | L28: =IF(VLOOKUP(B28,'MAPA DATA'!C:H,5,0)=1,"EFACT_CNE",IF(VLOOKUP(B28,'MAPA DATA'!C:H,6,0)=1,"EFACT_EST_CNE","SIN DATA")) -> EFACT_CNE | M28: =CONCATENATE("=SUMAR.SI(",L28,"!B:B;Reliquidacion!B",A28,";",L28,"!S:S)") -> =SUMAR.SI(EFACT_CNE!B:B;Reliquidacion!B28;EFACT_CNE!S:S) | N28: =CONCATENATE("=(O",A28,"/M",A28,")") -> =(O28/M28) | O28: =CONCATENATE("=SUMAR.SI(",L28,"!B:B;Reliquidacion!B",A28,";",L28,"!W:W)") -> =SUMAR.SI(EFACT_CNE!B:B;Reliquidacion!B28;EFACT_CNE!W:W) | P28: =CONCATENATE("=SUMAR.SI(",L28,"!B:B;Reliquidacion!B",A28,";",L28,"!X:X)") -> =SUMAR.SI(EFACT_CNE!B:B;Reliquidacion!B28;EFACT_CNE!X:X) | Q28: =CONCATENATE("=(R",A28,"/P",A28,")") -> =(R28/P28) | R28: =CONCATENATE("=SUMAR.SI(",L28,"!B:B;Reliquidacion!B",A28,";",L28,"!AB:AB)") -> =SUMAR.SI(EFACT_CNE!B:B;Reliquidacion!B28;EFACT_CNE!AB:AB) | S28: =CONCATENATE("=(O",A28,"+R",A28,")") -> =(O28+R28) | U28: =CONCATENATE("=(S",A28,"-J",A28,")") -> =(S28-J28)
A29: =A28+1 -> 29 | B29: 42979 | C29: =IF(VLOOKUP(B29,'MAPA DATA'!C:F,2,0)=1,"FACT_EMITIDA",IF(VLOOKUP(B29,'MAPA DATA'!C:F,3,0)=1,"FACT_EST_EFACT",(IF(VLOOKUP(B29,'MAPA DATA'!C:F,4,0)=1,"FACT_EST_CEN","SIN DATA")))) -> FACT_EST_EFACT | D29: =CONCATENATE("=SUMAR.SI(",IF(C29="FACT_EMITIDA","SIGGE_E",C29),"!B:B;Reliquidacion!B",A29,";",IF(C29="FACT_EMITIDA","SIGGE_E",C29),"!F:F)") -> =SUMAR.SI(FACT_EST_EFACT!B:B;Reliquidacion!B29;FACT_EST_EFACT!F:F) | E29: =CONCATENATE("=(F",A29,"/D",A29,")") -> =(F29/D29) | F29: =CONCATENATE("=SUMAR.SI(",IF(C29="FACT_EMITIDA","SIGGE_E",C29),"!B:B;Reliquidacion!B",A29,";",IF(C29="FACT_EMITIDA","SIGGE_E",C29),"!H:H)") -> =SUMAR.SI(FACT_EST_EFACT!B:B;Reliquidacion!B29;FACT_EST_EFACT!H:H) | G29: =CONCATENATE("=SUMAR.SI(",IF(C29="FACT_EMITIDA","SIGGE_P",C29),"!B:B;Reliquidacion!B",A29,";",IF(C29="FACT_EMITIDA","SIGGE_P",C29),"!F:F)") -> =SUMAR.SI(FACT_EST_EFACT!B:B;Reliquidacion!B29;FACT_EST_EFACT!F:F) | H29: =CONCATENATE("=(I",A29,"/G",A29,")") -> =(I29/G29) | I29: =CONCATENATE("=SUMAR.SI(",IF(C29="FACT_EMITIDA","SIGGE_P",C29),"!B:B;Reliquidacion!B",A29,";",IF(C29="FACT_EMITIDA","SIGGE_P",C29),"!H:H)") -> =SUMAR.SI(FACT_EST_EFACT!B:B;Reliquidacion!B29;FACT_EST_EFACT!H:H) | J29: =CONCATENATE("=(F",A29,"+I",A29,")") -> =(F29+I29) | L29: =IF(VLOOKUP(B29,'MAPA DATA'!C:H,5,0)=1,"EFACT_CNE",IF(VLOOKUP(B29,'MAPA DATA'!C:H,6,0)=1,"EFACT_EST_CNE","SIN DATA")) -> EFACT_CNE | M29: =CONCATENATE("=SUMAR.SI(",L29,"!B:B;Reliquidacion!B",A29,";",L29,"!S:S)") -> =SUMAR.SI(EFACT_CNE!B:B;Reliquidacion!B29;EFACT_CNE!S:S) | N29: =CONCATENATE("=(O",A29,"/M",A29,")") -> =(O29/M29) | O29: =CONCATENATE("=SUMAR.SI(",L29,"!B:B;Reliquidacion!B",A29,";",L29,"!W:W)") -> =SUMAR.SI(EFACT_CNE!B:B;Reliquidacion!B29;EFACT_CNE!W:W) | P29: =CONCATENATE("=SUMAR.SI(",L29,"!B:B;Reliquidacion!B",A29,";",L29,"!X:X)") -> =SUMAR.SI(EFACT_CNE!B:B;Reliquidacion!B29;EFACT_CNE!X:X) | Q29: =CONCATENATE("=(R",A29,"/P",A29,")") -> =(R29/P29) | R29: =CONCATENATE("=SUMAR.SI(",L29,"!B:B;Reliquidacion!B",A29,";",L29,"!AB:AB)") -> =SUMAR.SI(EFACT_CNE!B:B;Reliquidacion!B29;EFACT_CNE!AB:AB) | S29: =CONCATENATE("=(O",A29,"+R",A29,")") -> =(O29+R29) | U29: =CONCATENATE("=(S",A29,"-J",A29,")") -> =(S29-J29)
A30: =A29+1 -> 30 | B30: 43009 | C30: =IF(VLOOKUP(B30,'MAPA DATA'!C:F,2,0)=1,"FACT_EMITIDA",IF(VLOOKUP(B30,'MAPA DATA'!C:F,3,0)=1,"FACT_EST_EFACT",(IF(VLOOKUP(B30,'MAPA DATA'!C:F,4,0)=1,"FACT_EST_CEN","SIN DATA")))) -> FACT_EST_EFACT | D30: =CONCATENATE("=SUMAR.SI(",IF(C30="FACT_EMITIDA","SIGGE_E",C30),"!B:B;Reliquidacion!B",A30,";",IF(C30="FACT_EMITIDA","SIGGE_E",C30),"!F:F)") -> =SUMAR.SI(FACT_EST_EFACT!B:B;Reliquidacion!B30;FACT_EST_EFACT!F:F) | E30: =CONCATENATE("=(F",A30,"/D",A30,")") -> =(F30/D30) | F30: =CONCATENATE("=SUMAR.SI(",IF(C30="FACT_EMITIDA","SIGGE_E",C30),"!B:B;Reliquidacion!B",A30,";",IF(C30="FACT_EMITIDA","SIGGE_E",C30),"!H:H)") -> =SUMAR.SI(FACT_EST_EFACT!B:B;Reliquidacion!B30;FACT_EST_EFACT!H:H) | G30: =CONCATENATE("=SUMAR.SI(",IF(C30="FACT_EMITIDA","SIGGE_P",C30),"!B:B;Reliquidacion!B",A30,";",IF(C30="FACT_EMITIDA","SIGGE_P",C30),"!F:F)") -> =SUMAR.SI(FACT_EST_EFACT!B:B;Reliquidacion!B30;FACT_EST_EFACT!F:F) | H30: =CONCATENATE("=(I",A30,"/G",A30,")") -> =(I30/G30) | I30: =CONCATENATE("=SUMAR.SI(",IF(C30="FACT_EMITIDA","SIGGE_P",C30),"!B:B;Reliquidacion!B",A30,";",IF(C30="FACT_EMITIDA","SIGGE_P",C30),"!H:H)") -> =SUMAR.SI(FACT_EST_EFACT!B:B;Reliquidacion!B30;FACT_EST_EFACT!H:H) | J30: =CONCATENATE("=(F",A30,"+I",A30,")") -> =(F30+I30) | L30: =IF(VLOOKUP(B30,'MAPA DATA'!C:H,5,0)=1,"EFACT_CNE",IF(VLOOKUP(B30,'MAPA DATA'!C:H,6,0)=1,"EFACT_EST_CNE","SIN DATA")) -> EFACT_CNE | M30: =CONCATENATE("=SUMAR.SI(",L30,"!B:B;Reliquidacion!B",A30,";",L30,"!S:S)") -> =SUMAR.SI(EFACT_CNE!B:B;Reliquidacion!B30;EFACT_CNE!S:S) | N30: =CONCATENATE("=(O",A30,"/M",A30,")") -> =(O30/M30) | O30: =CONCATENATE("=SUMAR.SI(",L30,"!B:B;Reliquidacion!B",A30,";",L30,"!W:W)") -> =SUMAR.SI(EFACT_CNE!B:B;Reliquidacion!B30;EFACT_CNE!W:W) | P30: =CONCATENATE("=SUMAR.SI(",L30,"!B:B;Reliquidacion!B",A30,";",L30,"!X:X)") -> =SUMAR.SI(EFACT_CNE!B:B;Reliquidacion!B30;EFACT_CNE!X:X) | Q30: =CONCATENATE("=(R",A30,"/P",A30,")") -> =(R30/P30) | R30: =CONCATENATE("=SUMAR.SI(",L30,"!B:B;Reliquidacion!B",A30,";",L30,"!AB:AB)") -> =SUMAR.SI(EFACT_CNE!B:B;Reliquidacion!B30;EFACT_CNE!AB:AB) | S30: =CONCATENATE("=(O",A30,"+R",A30,")") -> =(O30+R30) | U30: =CONCATENATE("=(S",A30,"-J",A30,")") -> =(S30-J30)
A31: =A30+1 -> 31 | B31: 43040 | C31: =IF(VLOOKUP(B31,'MAPA DATA'!C:F,2,0)=1,"FACT_EMITIDA",IF(VLOOKUP(B31,'MAPA DATA'!C:F,3,0)=1,"FACT_EST_EFACT",(IF(VLOOKUP(B31,'MAPA DATA'!C:F,4,0)=1,"FACT_EST_CEN","SIN DATA")))) -> FACT_EST_EFACT | D31: =CONCATENATE("=SUMAR.SI(",IF(C31="FACT_EMITIDA","SIGGE_E",C31),"!B:B;Reliquidacion!B",A31,";",IF(C31="FACT_EMITIDA","SIGGE_E",C31),"!F:F)") -> =SUMAR.SI(FACT_EST_EFACT!B:B;Reliquidacion!B31;FACT_EST_EFACT!F:F) | E31: =CONCATENATE("=(F",A31,"/D",A31,")") -> =(F31/D31) | F31: =CONCATENATE("=SUMAR.SI(",IF(C31="FACT_EMITIDA","SIGGE_E",C31),"!B:B;Reliquidacion!B",A31,";",IF(C31="FACT_EMITIDA","SIGGE_E",C31),"!H:H)") -> =SUMAR.SI(FACT_EST_EFACT!B:B;Reliquidacion!B31;FACT_EST_EFACT!H:H) | G31: =CONCATENATE("=SUMAR.SI(",IF(C31="FACT_EMITIDA","SIGGE_P",C31),"!B:B;Reliquidacion!B",A31,";",IF(C31="FACT_EMITIDA","SIGGE_P",C31),"!F:F)") -> =SUMAR.SI(FACT_EST_EFACT!B:B;Reliquidacion!B31;FACT_EST_EFACT!F:F) | H31: =CONCATENATE("=(I",A31,"/G",A31,")") -> =(I31/G31) | I31: =CONCATENATE("=SUMAR.SI(",IF(C31="FACT_EMITIDA","SIGGE_P",C31),"!B:B;Reliquidacion!B",A31,";",IF(C31="FACT_EMITIDA","SIGGE_P",C31),"!H:H)") -> =SUMAR.SI(FACT_EST_EFACT!B:B;Reliquidacion!B31;FACT_EST_EFACT!H:H) | J31: =CONCATENATE("=(F",A31,"+I",A31,")") -> =(F31+I31) | L31: =IF(VLOOKUP(B31,'MAPA DATA'!C:H,5,0)=1,"EFACT_CNE",IF(VLOOKUP(B31,'MAPA DATA'!C:H,6,0)=1,"EFACT_EST_CNE","SIN DATA")) -> EFACT_CNE | M31: =CONCATENATE("=SUMAR.SI(",L31,"!B:B;Reliquidacion!B",A31,";",L31,"!S:S)") -> =SUMAR.SI(EFACT_CNE!B:B;Reliquidacion!B31;EFACT_CNE!S:S) | N31: =CONCATENATE("=(O",A31,"/M",A31,")") -> =(O31/M31) | O31: =CONCATENATE("=SUMAR.SI(",L31,"!B:B;Reliquidacion!B",A31,";",L31,"!W:W)") -> =SUMAR.SI(EFACT_CNE!B:B;Reliquidacion!B31;EFACT_CNE!W:W) | P31: =CONCATENATE("=SUMAR.SI(",L31,"!B:B;Reliquidacion!B",A31,";",L31,"!X:X)") -> =SUMAR.SI(EFACT_CNE!B:B;Reliquidacion!B31;EFACT_CNE!X:X) | Q31: =CONCATENATE("=(R",A31,"/P",A31,")") -> =(R31/P31) | R31: =CONCATENATE("=SUMAR.SI(",L31,"!B:B;Reliquidacion!B",A31,";",L31,"!AB:AB)") -> =SUMAR.SI(EFACT_CNE!B:B;Reliquidacion!B31;EFACT_CNE!AB:AB) | S31: =CONCATENATE("=(O",A31,"+R",A31,")") -> =(O31+R31) | U31: =CONCATENATE("=(S",A31,"-J",A31,")") -> =(S31-J31)
A32: =A31+1 -> 32 | B32: 43070 | C32: =IF(VLOOKUP(B32,'MAPA DATA'!C:F,2,0)=1,"FACT_EMITIDA",IF(VLOOKUP(B32,'MAPA DATA'!C:F,3,0)=1,"FACT_EST_EFACT",(IF(VLOOKUP(B32,'MAPA DATA'!C:F,4,0)=1,"FACT_EST_CEN","SIN DATA")))) -> FACT_EST_EFACT | D32: =CONCATENATE("=SUMAR.SI(",IF(C32="FACT_EMITIDA","SIGGE_E",C32),"!B:B;Reliquidacion!B",A32,";",IF(C32="FACT_EMITIDA","SIGGE_E",C32),"!F:F)") -> =SUMAR.SI(FACT_EST_EFACT!B:B;Reliquidacion!B32;FACT_EST_EFACT!F:F) | E32: =CONCATENATE("=(F",A32,"/D",A32,")") -> =(F32/D32) | F32: =CONCATENATE("=SUMAR.SI(",IF(C32="FACT_EMITIDA","SIGGE_E",C32),"!B:B;Reliquidacion!B",A32,";",IF(C32="FACT_EMITIDA","SIGGE_E",C32),"!H:H)") -> =SUMAR.SI(FACT_EST_EFACT!B:B;Reliquidacion!B32;FACT_EST_EFACT!H:H) | G32: =CONCATENATE("=SUMAR.SI(",IF(C32="FACT_EMITIDA","SIGGE_P",C32),"!B:B;Reliquidacion!B",A32,";",IF(C32="FACT_EMITIDA","SIGGE_P",C32),"!F:F)") -> =SUMAR.SI(FACT_EST_EFACT!B:B;Reliquidacion!B32;FACT_EST_EFACT!F:F) | H32: =CONCATENATE("=(I",A32,"/G",A32,")") -> =(I32/G32) | I32: =CONCATENATE("=SUMAR.SI(",IF(C32="FACT_EMITIDA","SIGGE_P",C32),"!B:B;Reliquidacion!B",A32,";",IF(C32="FACT_EMITIDA","SIGGE_P",C32),"!H:H)") -> =SUMAR.SI(FACT_EST_EFACT!B:B;Reliquidacion!B32;FACT_EST_EFACT!H:H) | J32: =CONCATENATE("=(F",A32,"+I",A32,")") -> =(F32+I32) | L32: =IF(VLOOKUP(B32,'MAPA DATA'!C:H,5,0)=1,"EFACT_CNE",IF(VLOOKUP(B32,'MAPA DATA'!C:H,6,0)=1,"EFACT_EST_CNE","SIN DATA")) -> EFACT_CNE | M32: =CONCATENATE("=SUMAR.SI(",L32,"!B:B;Reliquidacion!B",A32,";",L32,"!S:S)") -> =SUMAR.SI(EFACT_CNE!B:B;Reliquidacion!B32;EFACT_CNE!S:S) | N32: =CONCATENATE("=(O",A32,"/M",A32,")") -> =(O32/M32) | O32: =CONCATENATE("=SUMAR.SI(",L32,"!B:B;Reliquidacion!B",A32,";",L32,"!W:W)") -> =SUMAR.SI(EFACT_CNE!B:B;Reliquidacion!B32;EFACT_CNE!W:W) | P32: =CONCATENATE("=SUMAR.SI(",L32,"!B:B;Reliquidacion!B",A32,";",L32,"!X:X)") -> =SUMAR.SI(EFACT_CNE!B:B;Reliquidacion!B32;EFACT_CNE!X:X) | Q32: =CONCATENATE("=(R",A32,"/P",A32,")") -> =(R32/P32) | R32: =CONCATENATE("=SUMAR.SI(",L32,"!B:B;Reliquidacion!B",A32,";",L32,"!AB:AB)") -> =SUMAR.SI(EFACT_CNE!B:B;Reliquidacion!B32;EFACT_CNE!AB:AB) | S32: =CONCATENATE("=(O",A32,"+R",A32,")") -> =(O32+R32) | U32: =CONCATENATE("=(S",A32,"-J",A32,")") -> =(S32-J32)
A33: =A32+1 -> 33 | B33: 43101 | C33: =IF(VLOOKUP(B33,'MAPA DATA'!C:F,2,0)=1,"FACT_EMITIDA",IF(VLOOKUP(B33,'MAPA DATA'!C:F,3,0)=1,"FACT_EST_EFACT",(IF(VLOOKUP(B33,'MAPA DATA'!C:F,4,0)=1,"FACT_EST_CEN","SIN DATA")))) -> FACT_EST_EFACT | D33: =CONCATENATE("=SUMAR.SI(",IF(C33="FACT_EMITIDA","SIGGE_E",C33),"!B:B;Reliquidacion!B",A33,";",IF(C33="FACT_EMITIDA","SIGGE_E",C33),"!F:F)") -> =SUMAR.SI(FACT_EST_EFACT!B:B;Reliquidacion!B33;FACT_EST_EFACT!F:F) | E33: =CONCATENATE("=(F",A33,"/D",A33,")") -> =(F33/D33) | F33: =CONCATENATE("=SUMAR.SI(",IF(C33="FACT_EMITIDA","SIGGE_E",C33),"!B:B;Reliquidacion!B",A33,";",IF(C33="FACT_EMITIDA","SIGGE_E",C33),"!H:H)") -> =SUMAR.SI(FACT_EST_EFACT!B:B;Reliquidacion!B33;FACT_EST_EFACT!H:H) | G33: =CONCATENATE("=SUMAR.SI(",IF(C33="FACT_EMITIDA","SIGGE_P",C33),"!B:B;Reliquidacion!B",A33,";",IF(C33="FACT_EMITIDA","SIGGE_P",C33),"!F:F)") -> =SUMAR.SI(FACT_EST_EFACT!B:B;Reliquidacion!B33;FACT_EST_EFACT!F:F) | H33: =CONCATENATE("=(I",A33,"/G",A33,")") -> =(I33/G33) | I33: =CONCATENATE("=SUMAR.SI(",IF(C33="FACT_EMITIDA","SIGGE_P",C33),"!B:B;Reliquidacion!B",A33,";",IF(C33="FACT_EMITIDA","SIGGE_P",C33),"!H:H)") -> =SUMAR.SI(FACT_EST_EFACT!B:B;Reliquidacion!B33;FACT_EST_EFACT!H:H) | J33: =CONCATENATE("=(F",A33,"+I",A33,")") -> =(F33+I33) | L33: =IF(VLOOKUP(B33,'MAPA DATA'!C:H,5,0)=1,"EFACT_CNE",IF(VLOOKUP(B33,'MAPA DATA'!C:H,6,0)=1,"EFACT_EST_CNE","SIN DATA")) -> EFACT_CNE | M33: =CONCATENATE("=SUMAR.SI(",L33,"!B:B;Reliquidacion!B",A33,";",L33,"!S:S)") -> =SUMAR.SI(EFACT_CNE!B:B;Reliquidacion!B33;EFACT_CNE!S:S) | N33: =CONCATENATE("=(O",A33,"/M",A33,")") -> =(O33/M33) | O33: =CONCATENATE("=SUMAR.SI(",L33,"!B:B;Reliquidacion!B",A33,";",L33,"!W:W)") -> =SUMAR.SI(EFACT_CNE!B:B;Reliquidacion!B33;EFACT_CNE!W:W) | P33: =CONCATENATE("=SUMAR.SI(",L33,"!B:B;Reliquidacion!B",A33,";",L33,"!X:X)") -> =SUMAR.SI(EFACT_CNE!B:B;Reliquidacion!B33;EFACT_CNE!X:X) | Q33: =CONCATENATE("=(R",A33,"/P",A33,")") -> =(R33/P33) | R33: =CONCATENATE("=SUMAR.SI(",L33,"!B:B;Reliquidacion!B",A33,";",L33,"!AB:AB)") -> =SUMAR.SI(EFACT_CNE!B:B;Reliquidacion!B33;EFACT_CNE!AB:AB) | S33: =CONCATENATE("=(O",A33,"+R",A33,")") -> =(O33+R33) | U33: =CONCATENATE("=(S",A33,"-J",A33,")") -> =(S33-J33) | V33: PNP 7T/2018 | W33: =VLOOKUP(V33,#REF!,2,0) -> #REF! | X33: =VLOOKUP(V33,#REF!,6,0) -> #REF! | Y33: 43156 | Z33: 44377 | AA33: =Z33-Y33 -> 1221 | AB33: =+(1+X33)^(AA33/360)-1 -> #REF! | AC33: =AB33*U33 -> #REF! | AD33: =+U33+AC33 -> #VALUE!
A34: =A33+1 -> 34 | B34: 43132 | C34: =IF(VLOOKUP(B34,'MAPA DATA'!C:F,2,0)=1,"FACT_EMITIDA",IF(VLOOKUP(B34,'MAPA DATA'!C:F,3,0)=1,"FACT_EST_EFACT",(IF(VLOOKUP(B34,'MAPA DATA'!C:F,4,0)=1,"FACT_EST_CEN","SIN DATA")))) -> FACT_EST_EFACT | D34: =CONCATENATE("=SUMAR.SI(",IF(C34="FACT_EMITIDA","SIGGE_E",C34),"!B:B;Reliquidacion!B",A34,";",IF(C34="FACT_EMITIDA","SIGGE_E",C34),"!F:F)") -> =SUMAR.SI(FACT_EST_EFACT!B:B;Reliquidacion!B34;FACT_EST_EFACT!F:F) | E34: =CONCATENATE("=(F",A34,"/D",A34,")") -> =(F34/D34) | F34: =CONCATENATE("=SUMAR.SI(",IF(C34="FACT_EMITIDA","SIGGE_E",C34),"!B:B;Reliquidacion!B",A34,";",IF(C34="FACT_EMITIDA","SIGGE_E",C34),"!H:H)") -> =SUMAR.SI(FACT_EST_EFACT!B:B;Reliquidacion!B34;FACT_EST_EFACT!H:H) | G34: =CONCATENATE("=SUMAR.SI(",IF(C34="FACT_EMITIDA","SIGGE_P",C34),"!B:B;Reliquidacion!B",A34,";",IF(C34="FACT_EMITIDA","SIGGE_P",C34),"!F:F)") -> =SUMAR.SI(FACT_EST_EFACT!B:B;Reliquidacion!B34;FACT_EST_EFACT!F:F) | H34: =CONCATENATE("=(I",A34,"/G",A34,")") -> =(I34/G34) | I34: =CONCATENATE("=SUMAR.SI(",IF(C34="FACT_EMITIDA","SIGGE_P",C34),"!B:B;Reliquidacion!B",A34,";",IF(C34="FACT_EMITIDA","SIGGE_P",C34),"!H:H)") -> =SUMAR.SI(FACT_EST_EFACT!B:B;Reliquidacion!B34;FACT_EST_EFACT!H:H) | J34: =CONCATENATE("=(F",A34,"+I",A34,")") -> =(F34+I34) | L34: =IF(VLOOKUP(B34,'MAPA DATA'!C:H,5,0)=1,"EFACT_CNE",IF(VLOOKUP(B34,'MAPA DATA'!C:H,6,0)=1,"EFACT_EST_CNE","SIN DATA")) -> EFACT_CNE | M34: =CONCATENATE("=SUMAR.SI(",L34,"!B:B;Reliquidacion!B",A34,";",L34,"!S:S)") -> =SUMAR.SI(EFACT_CNE!B:B;Reliquidacion!B34;EFACT_CNE!S:S) | N34: =CONCATENATE("=(O",A34,"/M",A34,")") -> =(O34/M34) | O34: =CONCATENATE("=SUMAR.SI(",L34,"!B:B;Reliquidacion!B",A34,";",L34,"!W:W)") -> =SUMAR.SI(EFACT_CNE!B:B;Reliquidacion!B34;EFACT_CNE!W:W) | P34: =CONCATENATE("=SUMAR.SI(",L34,"!B:B;Reliquidacion!B",A34,";",L34,"!X:X)") -> =SUMAR.SI(EFACT_CNE!B:B;Reliquidacion!B34;EFACT_CNE!X:X) | Q34: =CONCATENATE("=(R",A34,"/P",A34,")") -> =(R34/P34) | R34: =CONCATENATE("=SUMAR.SI(",L34,"!B:B;Reliquidacion!B",A34,";",L34,"!AB:AB)") -> =SUMAR.SI(EFACT_CNE!B:B;Reliquidacion!B34;EFACT_CNE!AB:AB) | S34: =CONCATENATE("=(O",A34,"+R",A34,")") -> =(O34+R34) | U34: =CONCATENATE("=(S",A34,"-J",A34,")") -> =(S34-J34) | V34: PNP 7T/2018 | W34: =VLOOKUP(V34,#REF!,2,0) -> #REF! | X34: =VLOOKUP(V34,#REF!,6,0) -> #REF! | Y34: 43184 | Z34: =Z33 -> 44377 | AA34: =Z34-Y34 -> 1193 | AB34: =+(1+X34)^(AA34/360)-1 -> #REF! | AC34: =AB34*U34 -> #REF! | AD34: =+U34+AC34 -> #VALUE!
A35: =A34+1 -> 35 | B35: 43160 | C35: =IF(VLOOKUP(B35,'MAPA DATA'!C:F,2,0)=1,"FACT_EMITIDA",IF(VLOOKUP(B35,'MAPA DATA'!C:F,3,0)=1,"FACT_EST_EFACT",(IF(VLOOKUP(B35,'MAPA DATA'!C:F,4,0)=1,"FACT_EST_CEN","SIN DATA")))) -> FACT_EST_EFACT | D35: =CONCATENATE("=SUMAR.SI(",IF(C35="FACT_EMITIDA","SIGGE_E",C35),"!B:B;Reliquidacion!B",A35,";",IF(C35="FACT_EMITIDA","SIGGE_E",C35),"!F:F)") -> =SUMAR.SI(FACT_EST_EFACT!B:B;Reliquidacion!B35;FACT_EST_EFACT!F:F) | E35: =CONCATENATE("=(F",A35,"/D",A35,")") -> =(F35/D35) | F35: =CONCATENATE("=SUMAR.SI(",IF(C35="FACT_EMITIDA","SIGGE_E",C35),"!B:B;Reliquidacion!B",A35,";",IF(C35="FACT_EMITIDA","SIGGE_E",C35),"!H:H)") -> =SUMAR.SI(FACT_EST_EFACT!B:B;Reliquidacion!B35;FACT_EST_EFACT!H:H) | G35: =CONCATENATE("=SUMAR.SI(",IF(C35="FACT_EMITIDA","SIGGE_P",C35),"!B:B;Reliquidacion!B",A35,";",IF(C35="FACT_EMITIDA","SIGGE_P",C35),"!F:F)") -> =SUMAR.SI(FACT_EST_EFACT!B:B;Reliquidacion!B35;FACT_EST_EFACT!F:F) | H35: =CONCATENATE("=(I",A35,"/G",A35,")") -> =(I35/G35) | I35: =CONCATENATE("=SUMAR.SI(",IF(C35="FACT_EMITIDA","SIGGE_P",C35),"!B:B;Reliquidacion!B",A35,";",IF(C35="FACT_EMITIDA","SIGGE_P",C35),"!H:H)") -> =SUMAR.SI(FACT_EST_EFACT!B:B;Reliquidacion!B35;FACT_EST_EFACT!H:H) | J35: =CONCATENATE("=(F",A35,"+I",A35,")") -> =(F35+I35) | L35: =IF(VLOOKUP(B35,'MAPA DATA'!C:H,5,0)=1,"EFACT_CNE",IF(VLOOKUP(B35,'MAPA DATA'!C:H,6,0)=1,"EFACT_EST_CNE","SIN DATA")) -> EFACT_CNE | M35: =CONCATENATE("=SUMAR.SI(",L35,"!B:B;Reliquidacion!B",A35,";",L35,"!S:S)") -> =SUMAR.SI(EFACT_CNE!B:B;Reliquidacion!B35;EFACT_CNE!S:S) | N35: =CONCATENATE("=(O",A35,"/M",A35,")") -> =(O35/M35) | O35: =CONCATENATE("=SUMAR.SI(",L35,"!B:B;Reliquidacion!B",A35,";",L35,"!W:W)") -> =SUMAR.SI(EFACT_CNE!B:B;Reliquidacion!B35;EFACT_CNE!W:W) | P35: =CONCATENATE("=SUMAR.SI(",L35,"!B:B;Reliquidacion!B",A35,";",L35,"!X:X)") -> =SUMAR.SI(EFACT_CNE!B:B;Reliquidacion!B35;EFACT_CNE!X:X) | Q35: =CONCATENATE("=(R",A35,"/P",A35,")") -> =(R35/P35) | R35: =CONCATENATE("=SUMAR.SI(",L35,"!B:B;Reliquidacion!B",A35,";",L35,"!AB:AB)") -> =SUMAR.SI(EFACT_CNE!B:B;Reliquidacion!B35;EFACT_CNE!AB:AB) | S35: =CONCATENATE("=(O",A35,"+R",A35,")") -> =(O35+R35) | U35: =CONCATENATE("=(S",A35,"-J",A35,")") -> =(S35-J35) | V35: PNP 20T/2019 | W35: =VLOOKUP(V35,#REF!,2,0) -> #REF! | X35: =VLOOKUP(V35,#REF!,6,0) -> #REF! | Y35: 43215 | Z35: =Z34 -> 44377 | AA35: =Z35-Y35 -> 1162 | AB35: =+(1+X35)^(AA35/360)-1 -> #REF! | AC35: =AB35*U35 -> #REF! | AD35: =+U35+AC35 -> #VALUE!
A36: =A35+1 -> 36 | B36: 43191 | C36: =IF(VLOOKUP(B36,'MAPA DATA'!C:F,2,0)=1,"FACT_EMITIDA",IF(VLOOKUP(B36,'MAPA DATA'!C:F,3,0)=1,"FACT_EST_EFACT",(IF(VLOOKUP(B36,'MAPA DATA'!C:F,4,0)=1,"FACT_EST_CEN","SIN DATA")))) -> FACT_EST_EFACT | D36: =CONCATENATE("=SUMAR.SI(",IF(C36="FACT_EMITIDA","SIGGE_E",C36),"!B:B;Reliquidacion!B",A36,";",IF(C36="FACT_EMITIDA","SIGGE_E",C36),"!F:F)") -> =SUMAR.SI(FACT_EST_EFACT!B:B;Reliquidacion!B36;FACT_EST_EFACT!F:F) | E36: =CONCATENATE("=(F",A36,"/D",A36,")") -> =(F36/D36) | F36: =CONCATENATE("=SUMAR.SI(",IF(C36="FACT_EMITIDA","SIGGE_E",C36),"!B:B;Reliquidacion!B",A36,";",IF(C36="FACT_EMITIDA","SIGGE_E",C36),"!H:H)") -> =SUMAR.SI(FACT_EST_EFACT!B:B;Reliquidacion!B36;FACT_EST_EFACT!H:H) | G36: =CONCATENATE("=SUMAR.SI(",IF(C36="FACT_EMITIDA","SIGGE_P",C36),"!B:B;Reliquidacion!B",A36,";",IF(C36="FACT_EMITIDA","SIGGE_P",C36),"!F:F)") -> =SUMAR.SI(FACT_EST_EFACT!B:B;Reliquidacion!B36;FACT_EST_EFACT!F:F) | H36: =CONCATENATE("=(I",A36,"/G",A36,")") -> =(I36/G36) | I36: =CONCATENATE("=SUMAR.SI(",IF(C36="FACT_EMITIDA","SIGGE_P",C36),"!B:B;Reliquidacion!B",A36,";",IF(C36="FACT_EMITIDA","SIGGE_P",C36),"!H:H)") -> =SUMAR.SI(FACT_EST_EFACT!B:B;Reliquidacion!B36;FACT_EST_EFACT!H:H) | J36: =CONCATENATE("=(F",A36,"+I",A36,")") -> =(F36+I36) | L36: =IF(VLOOKUP(B36,'MAPA DATA'!C:H,5,0)=1,"EFACT_CNE",IF(VLOOKUP(B36,'MAPA DATA'!C:H,6,0)=1,"EFACT_EST_CNE","SIN DATA")) -> EFACT_CNE | M36: =CONCATENATE("=SUMAR.SI(",L36,"!B:B;Reliquidacion!B",A36,";",L36,"!S:S)") -> =SUMAR.SI(EFACT_CNE!B:B;Reliquidacion!B36;EFACT_CNE!S:S) | N36: =CONCATENATE("=(O",A36,"/M",A36,")") -> =(O36/M36) | O36: =CONCATENATE("=SUMAR.SI(",L36,"!B:B;Reliquidacion!B",A36,";",L36,"!W:W)") -> =SUMAR.SI(EFACT_CNE!B:B;Reliquidacion!B36;EFACT_CNE!W:W) | P36: =CONCATENATE("=SUMAR.SI(",L36,"!B:B;Reliquidacion!B",A36,";",L36,"!X:X)") -> =SUMAR.SI(EFACT_CNE!B:B;Reliquidacion!B36;EFACT_CNE!X:X) | Q36: =CONCATENATE("=(R",A36,"/P",A36,")") -> =(R36/P36) | R36: =CONCATENATE("=SUMAR.SI(",L36,"!B:B;Reliquidacion!B",A36,";",L36,"!AB:AB)") -> =SUMAR.SI(EFACT_CNE!B:B;Reliquidacion!B36;EFACT_CNE!AB:AB) | S36: =CONCATENATE("=(O",A36,"+R",A36,")") -> =(O36+R36) | U36: =CONCATENATE("=(S",A36,"-J",A36,")") -> =(S36-J36) | V36: PNP 20T/2019 | W36: =VLOOKUP(V36,#REF!,2,0) -> #REF! | X36: =VLOOKUP(V36,#REF!,6,0) -> #REF! | Y36: 43245 | Z36: =Z35 -> 44377 | AA36: =Z36-Y36 -> 1132 | AB36: =+(1+X36)^(AA36/360)-1 -> #REF! | AC36: =AB36*U36 -> #REF! | AD36: =+U36+AC36 -> #VALUE!
A37: =A36+1 -> 37 | B37: 43221 | C37: =IF(VLOOKUP(B37,'MAPA DATA'!C:F,2,0)=1,"FACT_EMITIDA",IF(VLOOKUP(B37,'MAPA DATA'!C:F,3,0)=1,"FACT_EST_EFACT",(IF(VLOOKUP(B37,'MAPA DATA'!C:F,4,0)=1,"FACT_EST_CEN","SIN DATA")))) -> FACT_EST_EFACT | D37: =CONCATENATE("=SUMAR.SI(",IF(C37="FACT_EMITIDA","SIGGE_E",C37),"!B:B;Reliquidacion!B",A37,";",IF(C37="FACT_EMITIDA","SIGGE_E",C37),"!F:F)") -> =SUMAR.SI(FACT_EST_EFACT!B:B;Reliquidacion!B37;FACT_EST_EFACT!F:F) | E37: =CONCATENATE("=(F",A37,"/D",A37,")") -> =(F37/D37) | F37: =CONCATENATE("=SUMAR.SI(",IF(C37="FACT_EMITIDA","SIGGE_E",C37),"!B:B;Reliquidacion!B",A37,";",IF(C37="FACT_EMITIDA","SIGGE_E",C37),"!H:H)") -> =SUMAR.SI(FACT_EST_EFACT!B:B;Reliquidacion!B37;FACT_EST_EFACT!H:H) | G37: =CONCATENATE("=SUMAR.SI(",IF(C37="FACT_EMITIDA","SIGGE_P",C37),"!B:B;Reliquidacion!B",A37,";",IF(C37="FACT_EMITIDA","SIGGE_P",C37),"!F:F)") -> =SUMAR.SI(FACT_EST_EFACT!B:B;Reliquidacion!B37;FACT_EST_EFACT!F:F) | H37: =CONCATENATE("=(I",A37,"/G",A37,")") -> =(I37/G37) | I37: =CONCATENATE("=SUMAR.SI(",IF(C37="FACT_EMITIDA","SIGGE_P",C37),"!B:B;Reliquidacion!B",A37,";",IF(C37="FACT_EMITIDA","SIGGE_P",C37),"!H:H)") -> =SUMAR.SI(FACT_EST_EFACT!B:B;Reliquidacion!B37;FACT_EST_EFACT!H:H) | J37: =CONCATENATE("=(F",A37,"+I",A37,")") -> =(F37+I37) | L37: =IF(VLOOKUP(B37,'MAPA DATA'!C:H,5,0)=1,"EFACT_CNE",IF(VLOOKUP(B37,'MAPA DATA'!C:H,6,0)=1,"EFACT_EST_CNE","SIN DATA")) -> EFACT_CNE | M37: =CONCATENATE("=SUMAR.SI(",L37,"!B:B;Reliquidacion!B",A37,";",L37,"!S:S)") -> =SUMAR.SI(EFACT_CNE!B:B;Reliquidacion!B37;EFACT_CNE!S:S) | N37: =CONCATENATE("=(O",A37,"/M",A37,")") -> =(O37/M37) | O37: =CONCATENATE("=SUMAR.SI(",L37,"!B:B;Reliquidacion!B",A37,";",L37,"!W:W)") -> =SUMAR.SI(EFACT_CNE!B:B;Reliquidacion!B37;EFACT_CNE!W:W) | P37: =CONCATENATE("=SUMAR.SI(",L37,"!B:B;Reliquidacion!B",A37,";",L37,"!X:X)") -> =SUMAR.SI(EFACT_CNE!B:B;Reliquidacion!B37;EFACT_CNE!X:X) | Q37: =CONCATENATE("=(R",A37,"/P",A37,")") -> =(R37/P37) | R37: =CONCATENATE("=SUMAR.SI(",L37,"!B:B;Reliquidacion!B",A37,";",L37,"!AB:AB)") -> =SUMAR.SI(EFACT_CNE!B:B;Reliquidacion!B37;EFACT_CNE!AB:AB) | S37: =CONCATENATE("=(O",A37,"+R",A37,")") -> =(O37+R37) | U37: =CONCATENATE("=(S",A37,"-J",A37,")") -> =(S37-J37) | V37: PNP 20T/2019 | W37: =VLOOKUP(V37,#REF!,2,0) -> #REF! | X37: =VLOOKUP(V37,#REF!,6,0) -> #REF! | Y37: 43276 | Z37: =Z36 -> 44377 | AA37: =Z37-Y37 -> 1101 | AB37: =+(1+X37)^(AA37/360)-1 -> #REF! | AC37: =AB37*U37 -> #REF! | AD37: =+U37+AC37 -> #VALUE!
A38: =A37+1 -> 38 | B38: 43252 | C38: =IF(VLOOKUP(B38,'MAPA DATA'!C:F,2,0)=1,"FACT_EMITIDA",IF(VLOOKUP(B38,'MAPA DATA'!C:F,3,0)=1,"FACT_EST_EFACT",(IF(VLOOKUP(B38,'MAPA DATA'!C:F,4,0)=1,"FACT_EST_CEN","SIN DATA")))) -> FACT_EST_EFACT | D38: =CONCATENATE("=SUMAR.SI(",IF(C38="FACT_EMITIDA","SIGGE_E",C38),"!B:B;Reliquidacion!B",A38,";",IF(C38="FACT_EMITIDA","SIGGE_E",C38),"!F:F)") -> =SUMAR.SI(FACT_EST_EFACT!B:B;Reliquidacion!B38;FACT_EST_EFACT!F:F) | E38: =CONCATENATE("=(F",A38,"/D",A38,")") -> =(F38/D38) | F38: =CONCATENATE("=SUMAR.SI(",IF(C38="FACT_EMITIDA","SIGGE_E",C38),"!B:B;Reliquidacion!B",A38,";",IF(C38="FACT_EMITIDA","SIGGE_E",C38),"!H:H)") -> =SUMAR.SI(FACT_EST_EFACT!B:B;Reliquidacion!B38;FACT_EST_EFACT!H:H) | G38: =CONCATENATE("=SUMAR.SI(",IF(C38="FACT_EMITIDA","SIGGE_P",C38),"!B:B;Reliquidacion!B",A38,";",IF(C38="FACT_EMITIDA","SIGGE_P",C38),"!F:F)") -> =SUMAR.SI(FACT_EST_EFACT!B:B;Reliquidacion!B38;FACT_EST_EFACT!F:F) | H38: =CONCATENATE("=(I",A38,"/G",A38,")") -> =(I38/G38) | I38: =CONCATENATE("=SUMAR.SI(",IF(C38="FACT_EMITIDA","SIGGE_P",C38),"!B:B;Reliquidacion!B",A38,";",IF(C38="FACT_EMITIDA","SIGGE_P",C38),"!H:H)") -> =SUMAR.SI(FACT_EST_EFACT!B:B;Reliquidacion!B38;FACT_EST_EFACT!H:H) | J38: =CONCATENATE("=(F",A38,"+I",A38,")") -> =(F38+I38) | L38: =IF(VLOOKUP(B38,'MAPA DATA'!C:H,5,0)=1,"EFACT_CNE",IF(VLOOKUP(B38,'MAPA DATA'!C:H,6,0)=1,"EFACT_EST_CNE","SIN DATA")) -> EFACT_CNE | M38: =CONCATENATE("=SUMAR.SI(",L38,"!B:B;Reliquidacion!B",A38,";",L38,"!S:S)") -> =SUMAR.SI(EFACT_CNE!B:B;Reliquidacion!B38;EFACT_CNE!S:S) | N38: =CONCATENATE("=(O",A38,"/M",A38,")") -> =(O38/M38) | O38: =CONCATENATE("=SUMAR.SI(",L38,"!B:B;Reliquidacion!B",A38,";",L38,"!W:W)") -> =SUMAR.SI(EFACT_CNE!B:B;Reliquidacion!B38;EFACT_CNE!W:W) | P38: =CONCATENATE("=SUMAR.SI(",L38,"!B:B;Reliquidacion!B",A38,";",L38,"!X:X)") -> =SUMAR.SI(EFACT_CNE!B:B;Reliquidacion!B38;EFACT_CNE!X:X) | Q38: =CONCATENATE("=(R",A38,"/P",A38,")") -> =(R38/P38) | R38: =CONCATENATE("=SUMAR.SI(",L38,"!B:B;Reliquidacion!B",A38,";",L38,"!AB:AB)") -> =SUMAR.SI(EFACT_CNE!B:B;Reliquidacion!B38;EFACT_CNE!AB:AB) | S38: =CONCATENATE("=(O",A38,"+R",A38,")") -> =(O38+R38) | U38: =CONCATENATE("=(S",A38,"-J",A38,")") -> =(S38-J38) | V38: PNP 20T/2019 | W38: =VLOOKUP(V38,#REF!,2,0) -> #REF! | X38: =VLOOKUP(V38,#REF!,6,0) -> #REF! | Y38: 43306 | Z38: =Z37 -> 44377 | AA38: =Z38-Y38 -> 1071 | AB38: =+(1+X38)^(AA38/360)-1 -> #REF! | AC38: =AB38*U38 -> #REF! | AD38: =+U38+AC38 -> #VALUE!
A39: =A38+1 -> 39 | B39: 43282 | C39: =IF(VLOOKUP(B39,'MAPA DATA'!C:F,2,0)=1,"FACT_EMITIDA",IF(VLOOKUP(B39,'MAPA DATA'!C:F,3,0)=1,"FACT_EST_EFACT",(IF(VLOOKUP(B39,'MAPA DATA'!C:F,4,0)=1,"FACT_EST_CEN","SIN DATA")))) -> FACT_EST_EFACT | D39: =CONCATENATE("=SUMAR.SI(",IF(C39="FACT_EMITIDA","SIGGE_E",C39),"!B:B;Reliquidacion!B",A39,";",IF(C39="FACT_EMITIDA","SIGGE_E",C39),"!F:F)") -> =SUMAR.SI(FACT_EST_EFACT!B:B;Reliquidacion!B39;FACT_EST_EFACT!F:F) | E39: =CONCATENATE("=(F",A39,"/D",A39,")") -> =(F39/D39) | F39: =CONCATENATE("=SUMAR.SI(",IF(C39="FACT_EMITIDA","SIGGE_E",C39),"!B:B;Reliquidacion!B",A39,";",IF(C39="FACT_EMITIDA","SIGGE_E",C39),"!H:H)") -> =SUMAR.SI(FACT_EST_EFACT!B:B;Reliquidacion!B39;FACT_EST_EFACT!H:H) | G39: =CONCATENATE("=SUMAR.SI(",IF(C39="FACT_EMITIDA","SIGGE_P",C39),"!B:B;Reliquidacion!B",A39,";",IF(C39="FACT_EMITIDA","SIGGE_P",C39),"!F:F)") -> =SUMAR.SI(FACT_EST_EFACT!B:B;Reliquidacion!B39;FACT_EST_EFACT!F:F) | H39: =CONCATENATE("=(I",A39,"/G",A39,")") -> =(I39/G39) | I39: =CONCATENATE("=SUMAR.SI(",IF(C39="FACT_EMITIDA","SIGGE_P",C39),"!B:B;Reliquidacion!B",A39,";",IF(C39="FACT_EMITIDA","SIGGE_P",C39),"!H:H)") -> =SUMAR.SI(FACT_EST_EFACT!B:B;Reliquidacion!B39;FACT_EST_EFACT!H:H) | J39: =CONCATENATE("=(F",A39,"+I",A39,")") -> =(F39+I39) | L39: =IF(VLOOKUP(B39,'MAPA DATA'!C:H,5,0)=1,"EFACT_CNE",IF(VLOOKUP(B39,'MAPA DATA'!C:H,6,0)=1,"EFACT_EST_CNE","SIN DATA")) -> EFACT_CNE | M39: =CONCATENATE("=SUMAR.SI(",L39,"!B:B;Reliquidacion!B",A39,";",L39,"!S:S)") -> =SUMAR.SI(EFACT_CNE!B:B;Reliquidacion!B39;EFACT_CNE!S:S) | N39: =CONCATENATE("=(O",A39,"/M",A39,")") -> =(O39/M39) | O39: =CONCATENATE("=SUMAR.SI(",L39,"!B:B;Reliquidacion!B",A39,";",L39,"!W:W)") -> =SUMAR.SI(EFACT_CNE!B:B;Reliquidacion!B39;EFACT_CNE!W:W) | P39: =CONCATENATE("=SUMAR.SI(",L39,"!B:B;Reliquidacion!B",A39,";",L39,"!X:X)") -> =SUMAR.SI(EFACT_CNE!B:B;Reliquidacion!B39;EFACT_CNE!X:X) | Q39: =CONCATENATE("=(R",A39,"/P",A39,")") -> =(R39/P39) | R39: =CONCATENATE("=SUMAR.SI(",L39,"!B:B;Reliquidacion!B",A39,";",L39,"!AB:AB)") -> =SUMAR.SI(EFACT_CNE!B:B;Reliquidacion!B39;EFACT_CNE!AB:AB) | S39: =CONCATENATE("=(O",A39,"+R",A39,")") -> =(O39+R39) | U39: =CONCATENATE("=(S",A39,"-J",A39,")") -> =(S39-J39) | V39: PNP 20T/2019 | W39: =VLOOKUP(V39,#REF!,2,0) -> #REF! | X39: =VLOOKUP(V39,#REF!,6,0) -> #REF! | Y39: 43337 | Z39: =Z38 -> 44377 | AA39: =Z39-Y39 -> 1040 | AB39: =+(1+X39)^(AA39/360)-1 -> #REF! | AC39: =AB39*U39 -> #REF! | AD39: =+U39+AC39 -> #VALUE!
A40: =A39+1 -> 40 | B40: 43313 | C40: =IF(VLOOKUP(B40,'MAPA DATA'!C:F,2,0)=1,"FACT_EMITIDA",IF(VLOOKUP(B40,'MAPA DATA'!C:F,3,0)=1,"FACT_EST_EFACT",(IF(VLOOKUP(B40,'MAPA DATA'!C:F,4,0)=1,"FACT_EST_CEN","SIN DATA")))) -> FACT_EST_EFACT | D40: =CONCATENATE("=SUMAR.SI(",IF(C40="FACT_EMITIDA","SIGGE_E",C40),"!B:B;Reliquidacion!B",A40,";",IF(C40="FACT_EMITIDA","SIGGE_E",C40),"!F:F)") -> =SUMAR.SI(FACT_EST_EFACT!B:B;Reliquidacion!B40;FACT_EST_EFACT!F:F) | E40: =CONCATENATE("=(F",A40,"/D",A40,")") -> =(F40/D40) | F40: =CONCATENATE("=SUMAR.SI(",IF(C40="FACT_EMITIDA","SIGGE_E",C40),"!B:B;Reliquidacion!B",A40,";",IF(C40="FACT_EMITIDA","SIGGE_E",C40),"!H:H)") -> =SUMAR.SI(FACT_EST_EFACT!B:B;Reliquidacion!B40;FACT_EST_EFACT!H:H) | G40: =CONCATENATE("=SUMAR.SI(",IF(C40="FACT_EMITIDA","SIGGE_P",C40),"!B:B;Reliquidacion!B",A40,";",IF(C40="FACT_EMITIDA","SIGGE_P",C40),"!F:F)") -> =SUMAR.SI(FACT_EST_EFACT!B:B;Reliquidacion!B40;FACT_EST_EFACT!F:F) | H40: =CONCATENATE("=(I",A40,"/G",A40,")") -> =(I40/G40) | I40: =CONCATENATE("=SUMAR.SI(",IF(C40="FACT_EMITIDA","SIGGE_P",C40),"!B:B;Reliquidacion!B",A40,";",IF(C40="FACT_EMITIDA","SIGGE_P",C40),"!H:H)") -> =SUMAR.SI(FACT_EST_EFACT!B:B;Reliquidacion!B40;FACT_EST_EFACT!H:H) | J40: =CONCATENATE("=(F",A40,"+I",A40,")") -> =(F40+I40) | L40: =IF(VLOOKUP(B40,'MAPA DATA'!C:H,5,0)=1,"EFACT_CNE",IF(VLOOKUP(B40,'MAPA DATA'!C:H,6,0)=1,"EFACT_EST_CNE","SIN DATA")) -> EFACT_CNE | M40: =CONCATENATE("=SUMAR.SI(",L40,"!B:B;Reliquidacion!B",A40,";",L40,"!S:S)") -> =SUMAR.SI(EFACT_CNE!B:B;Reliquidacion!B40;EFACT_CNE!S:S) | N40: =CONCATENATE("=(O",A40,"/M",A40,")") -> =(O40/M40) | O40: =CONCATENATE("=SUMAR.SI(",L40,"!B:B;Reliquidacion!B",A40,";",L40,"!W:W)") -> =SUMAR.SI(EFACT_CNE!B:B;Reliquidacion!B40;EFACT_CNE!W:W) | P40: =CONCATENATE("=SUMAR.SI(",L40,"!B:B;Reliquidacion!B",A40,";",L40,"!X:X)") -> =SUMAR.SI(EFACT_CNE!B:B;Reliquidacion!B40;EFACT_CNE!X:X) | Q40: =CONCATENATE("=(R",A40,"/P",A40,")") -> =(R40/P40) | R40: =CONCATENATE("=SUMAR.SI(",L40,"!B:B;Reliquidacion!B",A40,";",L40,"!AB:AB)") -> =SUMAR.SI(EFACT_CNE!B:B;Reliquidacion!B40;EFACT_CNE!AB:AB) | S40: =CONCATENATE("=(O",A40,"+R",A40,")") -> =(O40+R40) | U40: =CONCATENATE("=(S",A40,"-J",A40,")") -> =(S40-J40) | V40: PNP 20T/2019 | W40: =VLOOKUP(V40,#REF!,2,0) -> #REF! | X40: =VLOOKUP(V40,#REF!,6,0) -> #REF! | Y40: 43368 | Z40: =Z39 -> 44377 | AA40: =Z40-Y40 -> 1009 | AB40: =+(1+X40)^(AA40/360)-1 -> #REF! | AC40: =AB40*U40 -> #REF! | AD40: =+U40+AC40 -> #VALUE!
A41: =A40+1 -> 41 | B41: 43344 | C41: =IF(VLOOKUP(B41,'MAPA DATA'!C:F,2,0)=1,"FACT_EMITIDA",IF(VLOOKUP(B41,'MAPA DATA'!C:F,3,0)=1,"FACT_EST_EFACT",(IF(VLOOKUP(B41,'MAPA DATA'!C:F,4,0)=1,"FACT_EST_CEN","SIN DATA")))) -> FACT_EMITIDA | D41: =CONCATENATE("=SUMAR.SI(",IF(C41="FACT_EMITIDA","SIGGE_E",C41),"!B:B;Reliquidacion!B",A41,";",IF(C41="FACT_EMITIDA","SIGGE_E",C41),"!F:F)") -> =SUMAR.SI(SIGGE_E!B:B;Reliquidacion!B41;SIGGE_E!F:F) | E41: =CONCATENATE("=(F",A41,"/D",A41,")") -> =(F41/D41) | F41: =CONCATENATE("=SUMAR.SI(",IF(C41="FACT_EMITIDA","SIGGE_E",C41),"!B:B;Reliquidacion!B",A41,";",IF(C41="FACT_EMITIDA","SIGGE_E",C41),"!H:H)") -> =SUMAR.SI(SIGGE_E!B:B;Reliquidacion!B41;SIGGE_E!H:H) | G41: =CONCATENATE("=SUMAR.SI(",IF(C41="FACT_EMITIDA","SIGGE_P",C41),"!B:B;Reliquidacion!B",A41,";",IF(C41="FACT_EMITIDA","SIGGE_P",C41),"!F:F)") -> =SUMAR.SI(SIGGE_P!B:B;Reliquidacion!B41;SIGGE_P!F:F) | H41: =CONCATENATE("=(I",A41,"/G",A41,")") -> =(I41/G41) | I41: =CONCATENATE("=SUMAR.SI(",IF(C41="FACT_EMITIDA","SIGGE_P",C41),"!B:B;Reliquidacion!B",A41,";",IF(C41="FACT_EMITIDA","SIGGE_P",C41),"!H:H)") -> =SUMAR.SI(SIGGE_P!B:B;Reliquidacion!B41;SIGGE_P!H:H) | J41: =CONCATENATE("=(F",A41,"+I",A41,")") -> =(F41+I41) | L41: =IF(VLOOKUP(B41,'MAPA DATA'!C:H,5,0)=1,"EFACT_CNE",IF(VLOOKUP(B41,'MAPA DATA'!C:H,6,0)=1,"EFACT_EST_CNE","SIN DATA")) -> EFACT_CNE | M41: =CONCATENATE("=SUMAR.SI(",L41,"!B:B;Reliquidacion!B",A41,";",L41,"!S:S)") -> =SUMAR.SI(EFACT_CNE!B:B;Reliquidacion!B41;EFACT_CNE!S:S) | N41: =CONCATENATE("=(O",A41,"/M",A41,")") -> =(O41/M41) | O41: =CONCATENATE("=SUMAR.SI(",L41,"!B:B;Reliquidacion!B",A41,";",L41,"!W:W)") -> =SUMAR.SI(EFACT_CNE!B:B;Reliquidacion!B41;EFACT_CNE!W:W) | P41: =CONCATENATE("=SUMAR.SI(",L41,"!B:B;Reliquidacion!B",A41,";",L41,"!X:X)") -> =SUMAR.SI(EFACT_CNE!B:B;Reliquidacion!B41;EFACT_CNE!X:X) | Q41: =CONCATENATE("=(R",A41,"/P",A41,")") -> =(R41/P41) | R41: =CONCATENATE("=SUMAR.SI(",L41,"!B:B;Reliquidacion!B",A41,";",L41,"!AB:AB)") -> =SUMAR.SI(EFACT_CNE!B:B;Reliquidacion!B41;EFACT_CNE!AB:AB) | S41: =CONCATENATE("=(O",A41,"+R",A41,")") -> =(O41+R41) | U41: =CONCATENATE("=(S",A41,"-J",A41,")") -> =(S41-J41) | V41: PNP 6T/2020 | W41: =VLOOKUP(V41,#REF!,2,0) -> #REF! | X41: =VLOOKUP(V41,#REF!,6,0) -> #REF! | Y41: 43398 | Z41: =Z40 -> 44377 | AA41: =Z41-Y41 -> 979 | AB41: =+(1+X41)^(AA41/360)-1 -> #REF! | AC41: =AB41*U41 -> #REF! | AD41: =+U41+AC41 -> #VALUE!
A42: =A41+1 -> 42 | B42: 43374 | C42: =IF(VLOOKUP(B42,'MAPA DATA'!C:F,2,0)=1,"FACT_EMITIDA",IF(VLOOKUP(B42,'MAPA DATA'!C:F,3,0)=1,"FACT_EST_EFACT",(IF(VLOOKUP(B42,'MAPA DATA'!C:F,4,0)=1,"FACT_EST_CEN","SIN DATA")))) -> FACT_EMITIDA | D42: =CONCATENATE("=SUMAR.SI(",IF(C42="FACT_EMITIDA","SIGGE_E",C42),"!B:B;Reliquidacion!B",A42,";",IF(C42="FACT_EMITIDA","SIGGE_E",C42),"!F:F)") -> =SUMAR.SI(SIGGE_E!B:B;Reliquidacion!B42;SIGGE_E!F:F) | E42: =CONCATENATE("=(F",A42,"/D",A42,")") -> =(F42/D42) | F42: =CONCATENATE("=SUMAR.SI(",IF(C42="FACT_EMITIDA","SIGGE_E",C42),"!B:B;Reliquidacion!B",A42,";",IF(C42="FACT_EMITIDA","SIGGE_E",C42),"!H:H)") -> =SUMAR.SI(SIGGE_E!B:B;Reliquidacion!B42;SIGGE_E!H:H) | G42: =CONCATENATE("=SUMAR.SI(",IF(C42="FACT_EMITIDA","SIGGE_P",C42),"!B:B;Reliquidacion!B",A42,";",IF(C42="FACT_EMITIDA","SIGGE_P",C42),"!F:F)") -> =SUMAR.SI(SIGGE_P!B:B;Reliquidacion!B42;SIGGE_P!F:F) | H42: =CONCATENATE("=(I",A42,"/G",A42,")") -> =(I42/G42) | I42: =CONCATENATE("=SUMAR.SI(",IF(C42="FACT_EMITIDA","SIGGE_P",C42),"!B:B;Reliquidacion!B",A42,";",IF(C42="FACT_EMITIDA","SIGGE_P",C42),"!H:H)") -> =SUMAR.SI(SIGGE_P!B:B;Reliquidacion!B42;SIGGE_P!H:H) | J42: =CONCATENATE("=(F",A42,"+I",A42,")") -> =(F42+I42) | L42: =IF(VLOOKUP(B42,'MAPA DATA'!C:H,5,0)=1,"EFACT_CNE",IF(VLOOKUP(B42,'MAPA DATA'!C:H,6,0)=1,"EFACT_EST_CNE","SIN DATA")) -> EFACT_CNE | M42: =CONCATENATE("=SUMAR.SI(",L42,"!B:B;Reliquidacion!B",A42,";",L42,"!S:S)") -> =SUMAR.SI(EFACT_CNE!B:B;Reliquidacion!B42;EFACT_CNE!S:S) | N42: =CONCATENATE("=(O",A42,"/M",A42,")") -> =(O42/M42) | O42: =CONCATENATE("=SUMAR.SI(",L42,"!B:B;Reliquidacion!B",A42,";",L42,"!W:W)") -> =SUMAR.SI(EFACT_CNE!B:B;Reliquidacion!B42;EFACT_CNE!W:W) | P42: =CONCATENATE("=SUMAR.SI(",L42,"!B:B;Reliquidacion!B",A42,";",L42,"!X:X)") -> =SUMAR.SI(EFACT_CNE!B:B;Reliquidacion!B42;EFACT_CNE!X:X) | Q42: =CONCATENATE("=(R",A42,"/P",A42,")") -> =(R42/P42) | R42: =CONCATENATE("=SUMAR.SI(",L42,"!B:B;Reliquidacion!B",A42,";",L42,"!AB:AB)") -> =SUMAR.SI(EFACT_CNE!B:B;Reliquidacion!B42;EFACT_CNE!AB:AB) | S42: =CONCATENATE("=(O",A42,"+R",A42,")") -> =(O42+R42) | U42: =CONCATENATE("=(S",A42,"-J",A42,")") -> =(S42-J42) | V42: PNP 6T/2020 | W42: =VLOOKUP(V42,#REF!,2,0) -> #REF! | X42: =VLOOKUP(V42,#REF!,6,0) -> #REF! | Y42: 43429 | Z42: =Z41 -> 44377 | AA42: =Z42-Y42 -> 948 | AB42: =+(1+X42)^(AA42/360)-1 -> #REF! | AC42: =AB42*U42 -> #REF! | AD42: =+U42+AC42 -> #VALUE!
A43: =A42+1 -> 43 | B43: 43405 | C43: =IF(VLOOKUP(B43,'MAPA DATA'!C:F,2,0)=1,"FACT_EMITIDA",IF(VLOOKUP(B43,'MAPA DATA'!C:F,3,0)=1,"FACT_EST_EFACT",(IF(VLOOKUP(B43,'MAPA DATA'!C:F,4,0)=1,"FACT_EST_CEN","SIN DATA")))) -> FACT_EMITIDA | D43: =CONCATENATE("=SUMAR.SI(",IF(C43="FACT_EMITIDA","SIGGE_E",C43),"!B:B;Reliquidacion!B",A43,";",IF(C43="FACT_EMITIDA","SIGGE_E",C43),"!F:F)") -> =SUMAR.SI(SIGGE_E!B:B;Reliquidacion!B43;SIGGE_E!F:F) | E43: =CONCATENATE("=(F",A43,"/D",A43,")") -> =(F43/D43) | F43: =CONCATENATE("=SUMAR.SI(",IF(C43="FACT_EMITIDA","SIGGE_E",C43),"!B:B;Reliquidacion!B",A43,";",IF(C43="FACT_EMITIDA","SIGGE_E",C43),"!H:H)") -> =SUMAR.SI(SIGGE_E!B:B;Reliquidacion!B43;SIGGE_E!H:H) | G43: =CONCATENATE("=SUMAR.SI(",IF(C43="FACT_EMITIDA","SIGGE_P",C43),"!B:B;Reliquidacion!B",A43,";",IF(C43="FACT_EMITIDA","SIGGE_P",C43),"!F:F)") -> =SUMAR.SI(SIGGE_P!B:B;Reliquidacion!B43;SIGGE_P!F:F) | H43: =CONCATENATE("=(I",A43,"/G",A43,")") -> =(I43/G43) | I43: =CONCATENATE("=SUMAR.SI(",IF(C43="FACT_EMITIDA","SIGGE_P",C43),"!B:B;Reliquidacion!B",A43,";",IF(C43="FACT_EMITIDA","SIGGE_P",C43),"!H:H)") -> =SUMAR.SI(SIGGE_P!B:B;Reliquidacion!B43;SIGGE_P!H:H) | J43: =CONCATENATE("=(F",A43,"+I",A43,")") -> =(F43+I43) | L43: =IF(VLOOKUP(B43,'MAPA DATA'!C:H,5,0)=1,"EFACT_CNE",IF(VLOOKUP(B43,'MAPA DATA'!C:H,6,0)=1,"EFACT_EST_CNE","SIN DATA")) -> EFACT_CNE | M43: =CONCATENATE("=SUMAR.SI(",L43,"!B:B;Reliquidacion!B",A43,";",L43,"!S:S)") -> =SUMAR.SI(EFACT_CNE!B:B;Reliquidacion!B43;EFACT_CNE!S:S) | N43: =CONCATENATE("=(O",A43,"/M",A43,")") -> =(O43/M43) | O43: =CONCATENATE("=SUMAR.SI(",L43,"!B:B;Reliquidacion!B",A43,";",L43,"!W:W)") -> =SUMAR.SI(EFACT_CNE!B:B;Reliquidacion!B43;EFACT_CNE!W:W) | P43: =CONCATENATE("=SUMAR.SI(",L43,"!B:B;Reliquidacion!B",A43,";",L43,"!X:X)") -> =SUMAR.SI(EFACT_CNE!B:B;Reliquidacion!B43;EFACT_CNE!X:X) | Q43: =CONCATENATE("=(R",A43,"/P",A43,")") -> =(R43/P43) | R43: =CONCATENATE("=SUMAR.SI(",L43,"!B:B;Reliquidacion!B",A43,";",L43,"!AB:AB)") -> =SUMAR.SI(EFACT_CNE!B:B;Reliquidacion!B43;EFACT_CNE!AB:AB) | S43: =CONCATENATE("=(O",A43,"+R",A43,")") -> =(O43+R43) | U43: =CONCATENATE("=(S",A43,"-J",A43,")") -> =(S43-J43) | V43: PNP 6T/2020 | W43: =VLOOKUP(V43,#REF!,2,0) -> #REF! | X43: =VLOOKUP(V43,#REF!,6,0) -> #REF! | Y43: 43459 | Z43: =Z42 -> 44377 | AA43: =Z43-Y43 -> 918 | AB43: =+(1+X43)^(AA43/360)-1 -> #REF! | AC43: =AB43*U43 -> #REF! | AD43: =+U43+AC43 -> #VALUE!
A44: =A43+1 -> 44 | B44: 43435 | C44: =IF(VLOOKUP(B44,'MAPA DATA'!C:F,2,0)=1,"FACT_EMITIDA",IF(VLOOKUP(B44,'MAPA DATA'!C:F,3,0)=1,"FACT_EST_EFACT",(IF(VLOOKUP(B44,'MAPA DATA'!C:F,4,0)=1,"FACT_EST_CEN","SIN DATA")))) -> FACT_EMITIDA | D44: =CONCATENATE("=SUMAR.SI(",IF(C44="FACT_EMITIDA","SIGGE_E",C44),"!B:B;Reliquidacion!B",A44,";",IF(C44="FACT_EMITIDA","SIGGE_E",C44),"!F:F)") -> =SUMAR.SI(SIGGE_E!B:B;Reliquidacion!B44;SIGGE_E!F:F) | E44: =CONCATENATE("=(F",A44,"/D",A44,")") -> =(F44/D44) | F44: =CONCATENATE("=SUMAR.SI(",IF(C44="FACT_EMITIDA","SIGGE_E",C44),"!B:B;Reliquidacion!B",A44,";",IF(C44="FACT_EMITIDA","SIGGE_E",C44),"!H:H)") -> =SUMAR.SI(SIGGE_E!B:B;Reliquidacion!B44;SIGGE_E!H:H) | G44: =CONCATENATE("=SUMAR.SI(",IF(C44="FACT_EMITIDA","SIGGE_P",C44),"!B:B;Reliquidacion!B",A44,";",IF(C44="FACT_EMITIDA","SIGGE_P",C44),"!F:F)") -> =SUMAR.SI(SIGGE_P!B:B;Reliquidacion!B44;SIGGE_P!F:F) | H44: =CONCATENATE("=(I",A44,"/G",A44,")") -> =(I44/G44) | I44: =CONCATENATE("=SUMAR.SI(",IF(C44="FACT_EMITIDA","SIGGE_P",C44),"!B:B;Reliquidacion!B",A44,";",IF(C44="FACT_EMITIDA","SIGGE_P",C44),"!H:H)") -> =SUMAR.SI(SIGGE_P!B:B;Reliquidacion!B44;SIGGE_P!H:H) | J44: =CONCATENATE("=(F",A44,"+I",A44,")") -> =(F44+I44) | L44: =IF(VLOOKUP(B44,'MAPA DATA'!C:H,5,0)=1,"EFACT_CNE",IF(VLOOKUP(B44,'MAPA DATA'!C:H,6,0)=1,"EFACT_EST_CNE","SIN DATA")) -> EFACT_CNE | M44: =CONCATENATE("=SUMAR.SI(",L44,"!B:B;Reliquidacion!B",A44,";",L44,"!S:S)") -> =SUMAR.SI(EFACT_CNE!B:B;Reliquidacion!B44;EFACT_CNE!S:S) | N44: =CONCATENATE("=(O",A44,"/M",A44,")") -> =(O44/M44) | O44: =CONCATENATE("=SUMAR.SI(",L44,"!B:B;Reliquidacion!B",A44,";",L44,"!W:W)") -> =SUMAR.SI(EFACT_CNE!B:B;Reliquidacion!B44;EFACT_CNE!W:W) | P44: =CONCATENATE("=SUMAR.SI(",L44,"!B:B;Reliquidacion!B",A44,";",L44,"!X:X)") -> =SUMAR.SI(EFACT_CNE!B:B;Reliquidacion!B44;EFACT_CNE!X:X) | Q44: =CONCATENATE("=(R",A44,"/P",A44,")") -> =(R44/P44) | R44: =CONCATENATE("=SUMAR.SI(",L44,"!B:B;Reliquidacion!B",A44,";",L44,"!AB:AB)") -> =SUMAR.SI(EFACT_CNE!B:B;Reliquidacion!B44;EFACT_CNE!AB:AB) | S44: =CONCATENATE("=(O",A44,"+R",A44,")") -> =(O44+R44) | U44: =CONCATENATE("=(S",A44,"-J",A44,")") -> =(S44-J44) | V44: PNP 6T/2020 | W44: =VLOOKUP(V44,#REF!,2,0) -> #REF! | X44: =VLOOKUP(V44,#REF!,6,0) -> #REF! | Y44: 43490 | Z44: =Z43 -> 44377 | AA44: =Z44-Y44 -> 887 | AB44: =+(1+X44)^(AA44/360)-1 -> #REF! | AC44: =AB44*U44 -> #REF! | AD44: =+U44+AC44 -> #VALUE!
A45: =A44+1 -> 45 | B45: 43466 | C45: =IF(VLOOKUP(B45,'MAPA DATA'!C:F,2,0)=1,"FACT_EMITIDA",IF(VLOOKUP(B45,'MAPA DATA'!C:F,3,0)=1,"FACT_EST_EFACT",(IF(VLOOKUP(B45,'MAPA DATA'!C:F,4,0)=1,"FACT_EST_CEN","SIN DATA")))) -> FACT_EMITIDA | D45: =CONCATENATE("=SUMAR.SI(",IF(C45="FACT_EMITIDA","SIGGE_E",C45),"!B:B;Reliquidacion!B",A45,";",IF(C45="FACT_EMITIDA","SIGGE_E",C45),"!F:F)") -> =SUMAR.SI(SIGGE_E!B:B;Reliquidacion!B45;SIGGE_E!F:F) | E45: =CONCATENATE("=(F",A45,"/D",A45,")") -> =(F45/D45) | F45: =CONCATENATE("=SUMAR.SI(",IF(C45="FACT_EMITIDA","SIGGE_E",C45),"!B:B;Reliquidacion!B",A45,";",IF(C45="FACT_EMITIDA","SIGGE_E",C45),"!H:H)") -> =SUMAR.SI(SIGGE_E!B:B;Reliquidacion!B45;SIGGE_E!H:H) | G45: =CONCATENATE("=SUMAR.SI(",IF(C45="FACT_EMITIDA","SIGGE_P",C45),"!B:B;Reliquidacion!B",A45,";",IF(C45="FACT_EMITIDA","SIGGE_P",C45),"!F:F)") -> =SUMAR.SI(SIGGE_P!B:B;Reliquidacion!B45;SIGGE_P!F:F) | H45: =CONCATENATE("=(I",A45,"/G",A45,")") -> =(I45/G45) | I45: =CONCATENATE("=SUMAR.SI(",IF(C45="FACT_EMITIDA","SIGGE_P",C45),"!B:B;Reliquidacion!B",A45,";",IF(C45="FACT_EMITIDA","SIGGE_P",C45),"!H:H)") -> =SUMAR.SI(SIGGE_P!B:B;Reliquidacion!B45;SIGGE_P!H:H) | J45: =CONCATENATE("=(F",A45,"+I",A45,")") -> =(F45+I45) | L45: =IF(VLOOKUP(B45,'MAPA DATA'!C:H,5,0)=1,"EFACT_CNE",IF(VLOOKUP(B45,'MAPA DATA'!C:H,6,0)=1,"EFACT_EST_CNE","SIN DATA")) -> EFACT_CNE | M45: =CONCATENATE("=SUMAR.SI(",L45,"!B:B;Reliquidacion!B",A45,";",L45,"!S:S)") -> =SUMAR.SI(EFACT_CNE!B:B;Reliquidacion!B45;EFACT_CNE!S:S) | N45: =CONCATENATE("=(O",A45,"/M",A45,")") -> =(O45/M45) | O45: =CONCATENATE("=SUMAR.SI(",L45,"!B:B;Reliquidacion!B",A45,";",L45,"!W:W)") -> =SUMAR.SI(EFACT_CNE!B:B;Reliquidacion!B45;EFACT_CNE!W:W) | P45: =CONCATENATE("=SUMAR.SI(",L45,"!B:B;Reliquidacion!B",A45,";",L45,"!X:X)") -> =SUMAR.SI(EFACT_CNE!B:B;Reliquidacion!B45;EFACT_CNE!X:X) | Q45: =CONCATENATE("=(R",A45,"/P",A45,")") -> =(R45/P45) | R45: =CONCATENATE("=SUMAR.SI(",L45,"!B:B;Reliquidacion!B",A45,";",L45,"!AB:AB)") -> =SUMAR.SI(EFACT_CNE!B:B;Reliquidacion!B45;EFACT_CNE!AB:AB) | S45: =CONCATENATE("=(O",A45,"+R",A45,")") -> =(O45+R45) | U45: =CONCATENATE("=(S",A45,"-J",A45,")") -> =(S45-J45) | V45: PNP 6T/2020 | W45: =VLOOKUP(V45,#REF!,2,0) -> #REF! | X45: =VLOOKUP(V45,#REF!,6,0) -> #REF! | Y45: 43521 | Z45: =Z44 -> 44377 | AA45: =Z45-Y45 -> 856 | AB45: =+(1+X45)^(AA45/360)-1 -> #REF! | AC45: =AB45*U45 -> #REF! | AD45: =+U45+AC45 -> #VALUE!
... A61: =A60+1 -> 61 | B61: 43952 | C61: =IF(VLOOKUP(B61,'MAPA DATA'!C:F,2,0)=1,"FACT_EMITIDA",IF(VLOOKUP(B61,'MAPA DATA'!C:F,3,0)=1,"FACT_EST_EFACT",(IF(VLOOKUP(B61,'MAPA DATA'!C:F,4,0)=1,"FACT_EST_CEN","SIN DATA")))) -> FACT_EMITIDA | D61: =CONCATENATE("=SUMAR.SI(",IF(C61="FACT_EMITIDA","SIGGE_E",C61),"!B:B;Reliquidacion!B",A61,";",IF(C61="FACT_EMITIDA","SIGGE_E",C61),"!F:F)") -> =SUMAR.SI(SIGGE_E!B:B;Reliquidacion!B61;SIGGE_E!F:F) | E61: =CONCATENATE("=(F",A61,"/D",A61,")") -> =(F61/D61) | F61: =CONCATENATE("=SUMAR.SI(",IF(C61="FACT_EMITIDA","SIGGE_E",C61),"!B:B;Reliquidacion!B",A61,";",IF(C61="FACT_EMITIDA","SIGGE_E",C61),"!H:H)") -> =SUMAR.SI(SIGGE_E!B:B;Reliquidacion!B61;SIGGE_E!H:H) | G61: =CONCATENATE("=SUMAR.SI(",IF(C61="FACT_EMITIDA","SIGGE_P",C61),"!B:B;Reliquidacion!B",A61,";",IF(C61="FACT_EMITIDA","SIGGE_P",C61),"!F:F)") -> =SUMAR.SI(SIGGE_P!B:B;Reliquidacion!B61;SIGGE_P!F:F) | H61: =CONCATENATE("=(I",A61,"/G",A61,")") -> =(I61/G61) | I61: =CONCATENATE("=SUMAR.SI(",IF(C61="FACT_EMITIDA","SIGGE_P",C61),"!B:B;Reliquidacion!B",A61,";",IF(C61="FACT_EMITIDA","SIGGE_P",C61),"!H:H)") -> =SUMAR.SI(SIGGE_P!B:B;Reliquidacion!B61;SIGGE_P!H:H) | J61: =CONCATENATE("=(F",A61,"+I",A61,")") -> =(F61+I61) | L61: =IF(VLOOKUP(B61,'MAPA DATA'!C:H,5,0)=1,"EFACT_CNE",IF(VLOOKUP(B61,'MAPA DATA'!C:H,6,0)=1,"EFACT_EST_CNE","SIN DATA")) -> SIN DATA | M61: =CONCATENATE("=SUMAR.SI(",L61,"!B:B;Reliquidacion!B",A61,";",L61,"!S:S)") -> =SUMAR.SI(SIN DATA!B:B;Reliquidacion!B61;SIN DATA!S:S) | N61: =CONCATENATE("=(O",A61,"/M",A61,")") -> =(O61/M61) | O61: =CONCATENATE("=SUMAR.SI(",L61,"!B:B;Reliquidacion!B",A61,";",L61,"!W:W)") -> =SUMAR.SI(SIN DATA!B:B;Reliquidacion!B61;SIN DATA!W:W) | P61: =CONCATENATE("=SUMAR.SI(",L61,"!B:B;Reliquidacion!B",A61,";",L61,"!X:X)") -> =SUMAR.SI(SIN DATA!B:B;Reliquidacion!B61;SIN DATA!X:X) | Q61: =CONCATENATE("=(R",A61,"/P",A61,")") -> =(R61/P61) | R61: =CONCATENATE("=SUMAR.SI(",L61,"!B:B;Reliquidacion!B",A61,";",L61,"!AB:AB)") -> =SUMAR.SI(SIN DATA!B:B;Reliquidacion!B61;SIN DATA!AB:AB) | S61: =CONCATENATE("=(O",A61,"+R",A61,")") -> =(O61+R61) | U61: =CONCATENATE("=(S",A61,"-J",A61,")") -> =(S61-J61) | V61: PNP 16T/2021 | W61: =VLOOKUP(V61,#REF!,2,0) -> #REF! | X61: =VLOOKUP(V61,#REF!,6,0) -> #REF! | Y61: 44007 | Z61: =Z60 -> 44377 | AA61: =Z61-Y61 -> 370 | AB61: =+(1+X61)^(AA61/360)-1 -> #REF! | AC61: =AB61*U61 -> #REF! | AD61: =+U61+AC61 -> #VALUE!
A62: =A61+1 -> 62 | B62: 43983 | C62: =IF(VLOOKUP(B62,'MAPA DATA'!C:F,2,0)=1,"FACT_EMITIDA",IF(VLOOKUP(B62,'MAPA DATA'!C:F,3,0)=1,"FACT_EST_EFACT",(IF(VLOOKUP(B62,'MAPA DATA'!C:F,4,0)=1,"FACT_EST_CEN","SIN DATA")))) -> FACT_EMITIDA | D62: =CONCATENATE("=SUMAR.SI(",IF(C62="FACT_EMITIDA","SIGGE_E",C62),"!B:B;Reliquidacion!B",A62,";",IF(C62="FACT_EMITIDA","SIGGE_E",C62),"!F:F)") -> =SUMAR.SI(SIGGE_E!B:B;Reliquidacion!B62;SIGGE_E!F:F) | E62: =CONCATENATE("=(F",A62,"/D",A62,")") -> =(F62/D62) | F62: =CONCATENATE("=SUMAR.SI(",IF(C62="FACT_EMITIDA","SIGGE_E",C62),"!B:B;Reliquidacion!B",A62,";",IF(C62="FACT_EMITIDA","SIGGE_E",C62),"!H:H)") -> =SUMAR.SI(SIGGE_E!B:B;Reliquidacion!B62;SIGGE_E!H:H) | G62: =CONCATENATE("=SUMAR.SI(",IF(C62="FACT_EMITIDA","SIGGE_P",C62),"!B:B;Reliquidacion!B",A62,";",IF(C62="FACT_EMITIDA","SIGGE_P",C62),"!F:F)") -> =SUMAR.SI(SIGGE_P!B:B;Reliquidacion!B62;SIGGE_P!F:F) | H62: =CONCATENATE("=(I",A62,"/G",A62,")") -> =(I62/G62) | I62: =CONCATENATE("=SUMAR.SI(",IF(C62="FACT_EMITIDA","SIGGE_P",C62),"!B:B;Reliquidacion!B",A62,";",IF(C62="FACT_EMITIDA","SIGGE_P",C62),"!H:H)") -> =SUMAR.SI(SIGGE_P!B:B;Reliquidacion!B62;SIGGE_P!H:H) | J62: =CONCATENATE("=(F",A62,"+I",A62,")") -> =(F62+I62) | L62: =IF(VLOOKUP(B62,'MAPA DATA'!C:H,5,0)=1,"EFACT_CNE",IF(VLOOKUP(B62,'MAPA DATA'!C:H,6,0)=1,"EFACT_EST_CNE","SIN DATA")) -> SIN DATA | M62: =CONCATENATE("=SUMAR.SI(",L62,"!B:B;Reliquidacion!B",A62,";",L62,"!S:S)") -> =SUMAR.SI(SIN DATA!B:B;Reliquidacion!B62;SIN DATA!S:S) | N62: =CONCATENATE("=(O",A62,"/M",A62,")") -> =(O62/M62) | O62: =CONCATENATE("=SUMAR.SI(",L62,"!B:B;Reliquidacion!B",A62,";",L62,"!W:W)") -> =SUMAR.SI(SIN DATA!B:B;Reliquidacion!B62;SIN DATA!W:W) | P62: =CONCATENATE("=SUMAR.SI(",L62,"!B:B;Reliquidacion!B",A62,";",L62,"!X:X)") -> =SUMAR.SI(SIN DATA!B:B;Reliquidacion!B62;SIN DATA!X:X) | Q62: =CONCATENATE("=(R",A62,"/P",A62,")") -> =(R62/P62) | R62: =CONCATENATE("=SUMAR.SI(",L62,"!B:B;Reliquidacion!B",A62,";",L62,"!AB:AB)") -> =SUMAR.SI(SIN DATA!B:B;Reliquidacion!B62;SIN DATA!AB:AB) | S62: =CONCATENATE("=(O",A62,"+R",A62,")") -> =(O62+R62) | U62: =CONCATENATE("=(S",A62,"-J",A62,")") -> =(S62-J62) | V62: PNP 16T/2021 | W62: =VLOOKUP(V62,#REF!,2,0) -> #REF! | X62: =VLOOKUP(V62,#REF!,6,0) -> #REF! | Y62: 44037 | Z62: =Z60 -> 44377 | AA62: =Z62-Y62 -> 340 | AB62: =+(1+X62)^(AA62/360)-1 -> #REF! | AC62: =AB62*U62 -> #REF! | AD62: =+U62+AC62 -> #VALUE!
A63: =A62+1 -> 63 | B63: 44013 | C63: =IF(VLOOKUP(B63,'MAPA DATA'!C:F,2,0)=1,"FACT_EMITIDA",IF(VLOOKUP(B63,'MAPA DATA'!C:F,3,0)=1,"FACT_EST_EFACT",(IF(VLOOKUP(B63,'MAPA DATA'!C:F,4,0)=1,"FACT_EST_CEN","SIN DATA")))) -> FACT_EMITIDA | D63: =CONCATENATE("=SUMAR.SI(",IF(C63="FACT_EMITIDA","SIGGE_E",C63),"!B:B;Reliquidacion!B",A63,";",IF(C63="FACT_EMITIDA","SIGGE_E",C63),"!F:F)") -> =SUMAR.SI(SIGGE_E!B:B;Reliquidacion!B63;SIGGE_E!F:F) | E63: =CONCATENATE("=(F",A63,"/D",A63,")") -> =(F63/D63) | F63: =CONCATENATE("=SUMAR.SI(",IF(C63="FACT_EMITIDA","SIGGE_E",C63),"!B:B;Reliquidacion!B",A63,";",IF(C63="FACT_EMITIDA","SIGGE_E",C63),"!H:H)") -> =SUMAR.SI(SIGGE_E!B:B;Reliquidacion!B63;SIGGE_E!H:H) | G63: =CONCATENATE("=SUMAR.SI(",IF(C63="FACT_EMITIDA","SIGGE_P",C63),"!B:B;Reliquidacion!B",A63,";",IF(C63="FACT_EMITIDA","SIGGE_P",C63),"!F:F)") -> =SUMAR.SI(SIGGE_P!B:B;Reliquidacion!B63;SIGGE_P!F:F) | H63: =CONCATENATE("=(I",A63,"/G",A63,")") -> =(I63/G63) | I63: =CONCATENATE("=SUMAR.SI(",IF(C63="FACT_EMITIDA","SIGGE_P",C63),"!B:B;Reliquidacion!B",A63,";",IF(C63="FACT_EMITIDA","SIGGE_P",C63),"!H:H)") -> =SUMAR.SI(SIGGE_P!B:B;Reliquidacion!B63;SIGGE_P!H:H) | J63: =CONCATENATE("=(F",A63,"+I",A63,")") -> =(F63+I63) | L63: =IF(VLOOKUP(B63,'MAPA DATA'!C:H,5,0)=1,"EFACT_CNE",IF(VLOOKUP(B63,'MAPA DATA'!C:H,6,0)=1,"EFACT_EST_CNE","SIN DATA")) -> SIN DATA | M63: =CONCATENATE("=SUMAR.SI(",L63,"!B:B;Reliquidacion!B",A63,";",L63,"!S:S)") -> =SUMAR.SI(SIN DATA!B:B;Reliquidacion!B63;SIN DATA!S:S) | N63: =CONCATENATE("=(O",A63,"/M",A63,")") -> =(O63/M63) | O63: =CONCATENATE("=SUMAR.SI(",L63,"!B:B;Reliquidacion!B",A63,";",L63,"!W:W)") -> =SUMAR.SI(SIN DATA!B:B;Reliquidacion!B63;SIN DATA!W:W) | P63: =CONCATENATE("=SUMAR.SI(",L63,"!B:B;Reliquidacion!B",A63,";",L63,"!X:X)") -> =SUMAR.SI(SIN DATA!B:B;Reliquidacion!B63;SIN DATA!X:X) | Q63: =CONCATENATE("=(R",A63,"/P",A63,")") -> =(R63/P63) | R63: =CONCATENATE("=SUMAR.SI(",L63,"!B:B;Reliquidacion!B",A63,";",L63,"!AB:AB)") -> =SUMAR.SI(SIN DATA!B:B;Reliquidacion!B63;SIN DATA!AB:AB) | S63: =CONCATENATE("=(O",A63,"+R",A63,")") -> =(O63+R63) | U63: =CONCATENATE("=(S",A63,"-J",A63,")") -> =(S63-J63) | V63: PNP 19T/2021 | W63: =VLOOKUP(V63,#REF!,2,0) -> #REF! | X63: =VLOOKUP(V63,#REF!,6,0) -> #REF! | Y63: 44068 | Z63: =Z59 -> 44377 | AA63: =Z63-Y63 -> 309 | AB63: =+(1+X63)^(AA63/360)-1 -> #REF! | AC63: =AB63*U63 -> #REF! | AD63: =+U63+AC63 -> #VALUE!
A64: =A63+1 -> 64 | B64: 44044 | C64: =IF(VLOOKUP(B64,'MAPA DATA'!C:F,2,0)=1,"FACT_EMITIDA",IF(VLOOKUP(B64,'MAPA DATA'!C:F,3,0)=1,"FACT_EST_EFACT",(IF(VLOOKUP(B64,'MAPA DATA'!C:F,4,0)=1,"FACT_EST_CEN","SIN DATA")))) -> FACT_EMITIDA | D64: =CONCATENATE("=SUMAR.SI(",IF(C64="FACT_EMITIDA","SIGGE_E",C64),"!B:B;Reliquidacion!B",A64,";",IF(C64="FACT_EMITIDA","SIGGE_E",C64),"!F:F)") -> =SUMAR.SI(SIGGE_E!B:B;Reliquidacion!B64;SIGGE_E!F:F) | E64: =CONCATENATE("=(F",A64,"/D",A64,")") -> =(F64/D64) | F64: =CONCATENATE("=SUMAR.SI(",IF(C64="FACT_EMITIDA","SIGGE_E",C64),"!B:B;Reliquidacion!B",A64,";",IF(C64="FACT_EMITIDA","SIGGE_E",C64),"!H:H)") -> =SUMAR.SI(SIGGE_E!B:B;Reliquidacion!B64;SIGGE_E!H:H) | G64: =CONCATENATE("=SUMAR.SI(",IF(C64="FACT_EMITIDA","SIGGE_P",C64),"!B:B;Reliquidacion!B",A64,";",IF(C64="FACT_EMITIDA","SIGGE_P",C64),"!F:F)") -> =SUMAR.SI(SIGGE_P!B:B;Reliquidacion!B64;SIGGE_P!F:F) | H64: =CONCATENATE("=(I",A64,"/G",A64,")") -> =(I64/G64) | I64: =CONCATENATE("=SUMAR.SI(",IF(C64="FACT_EMITIDA","SIGGE_P",C64),"!B:B;Reliquidacion!B",A64,";",IF(C64="FACT_EMITIDA","SIGGE_P",C64),"!H:H)") -> =SUMAR.SI(SIGGE_P!B:B;Reliquidacion!B64;SIGGE_P!H:H) | J64: =CONCATENATE("=(F",A64,"+I",A64,")") -> =(F64+I64) | L64: =IF(VLOOKUP(B64,'MAPA DATA'!C:H,5,0)=1,"EFACT_CNE",IF(VLOOKUP(B64,'MAPA DATA'!C:H,6,0)=1,"EFACT_EST_CNE","SIN DATA")) -> SIN DATA | M64: =CONCATENATE("=SUMAR.SI(",L64,"!B:B;Reliquidacion!B",A64,";",L64,"!S:S)") -> =SUMAR.SI(SIN DATA!B:B;Reliquidacion!B64;SIN DATA!S:S) | N64: =CONCATENATE("=(O",A64,"/M",A64,")") -> =(O64/M64) | O64: =CONCATENATE("=SUMAR.SI(",L64,"!B:B;Reliquidacion!B",A64,";",L64,"!W:W)") -> =SUMAR.SI(SIN DATA!B:B;Reliquidacion!B64;SIN DATA!W:W) | P64: =CONCATENATE("=SUMAR.SI(",L64,"!B:B;Reliquidacion!B",A64,";",L64,"!X:X)") -> =SUMAR.SI(SIN DATA!B:B;Reliquidacion!B64;SIN DATA!X:X) | Q64: =CONCATENATE("=(R",A64,"/P",A64,")") -> =(R64/P64) | R64: =CONCATENATE("=SUMAR.SI(",L64,"!B:B;Reliquidacion!B",A64,";",L64,"!AB:AB)") -> =SUMAR.SI(SIN DATA!B:B;Reliquidacion!B64;SIN DATA!AB:AB) | S64: =CONCATENATE("=(O",A64,"+R",A64,")") -> =(O64+R64) | U64: =CONCATENATE("=(S",A64,"-J",A64,")") -> =(S64-J64) | V64: PNP 19T/2021 | W64: =VLOOKUP(V64,#REF!,2,0) -> #REF! | X64: =VLOOKUP(V64,#REF!,6,0) -> #REF! | Y64: 44099 | Z64: =Z60 -> 44377 | AA64: =Z64-Y64 -> 278 | AB64: =+(1+X64)^(AA64/360)-1 -> #REF! | AC64: =AB64*U64 -> #REF! | AD64: =+U64+AC64 -> #VALUE!
A65: =A64+1 -> 65 | B65: 44075 | C65: =IF(VLOOKUP(B65,'MAPA DATA'!C:F,2,0)=1,"FACT_EMITIDA",IF(VLOOKUP(B65,'MAPA DATA'!C:F,3,0)=1,"FACT_EST_EFACT",(IF(VLOOKUP(B65,'MAPA DATA'!C:F,4,0)=1,"FACT_EST_CEN","SIN DATA")))) -> FACT_EMITIDA | D65: =CONCATENATE("=SUMAR.SI(",IF(C65="FACT_EMITIDA","SIGGE_E",C65),"!B:B;Reliquidacion!B",A65,";",IF(C65="FACT_EMITIDA","SIGGE_E",C65),"!F:F)") -> =SUMAR.SI(SIGGE_E!B:B;Reliquidacion!B65;SIGGE_E!F:F) | E65: =CONCATENATE("=(F",A65,"/D",A65,")") -> =(F65/D65) | F65: =CONCATENATE("=SUMAR.SI(",IF(C65="FACT_EMITIDA","SIGGE_E",C65),"!B:B;Reliquidacion!B",A65,";",IF(C65="FACT_EMITIDA","SIGGE_E",C65),"!H:H)") -> =SUMAR.SI(SIGGE_E!B:B;Reliquidacion!B65;SIGGE_E!H:H) | G65: =CONCATENATE("=SUMAR.SI(",IF(C65="FACT_EMITIDA","SIGGE_P",C65),"!B:B;Reliquidacion!B",A65,";",IF(C65="FACT_EMITIDA","SIGGE_P",C65),"!F:F)") -> =SUMAR.SI(SIGGE_P!B:B;Reliquidacion!B65;SIGGE_P!F:F) | H65: =CONCATENATE("=(I",A65,"/G",A65,")") -> =(I65/G65) | I65: =CONCATENATE("=SUMAR.SI(",IF(C65="FACT_EMITIDA","SIGGE_P",C65),"!B:B;Reliquidacion!B",A65,";",IF(C65="FACT_EMITIDA","SIGGE_P",C65),"!H:H)") -> =SUMAR.SI(SIGGE_P!B:B;Reliquidacion!B65;SIGGE_P!H:H) | J65: =CONCATENATE("=(F",A65,"+I",A65,")") -> =(F65+I65) | L65: =IF(VLOOKUP(B65,'MAPA DATA'!C:H,5,0)=1,"EFACT_CNE",IF(VLOOKUP(B65,'MAPA DATA'!C:H,6,0)=1,"EFACT_EST_CNE","SIN DATA")) -> SIN DATA | M65: =CONCATENATE("=SUMAR.SI(",L65,"!B:B;Reliquidacion!B",A65,";",L65,"!S:S)") -> =SUMAR.SI(SIN DATA!B:B;Reliquidacion!B65;SIN DATA!S:S) | N65: =CONCATENATE("=(O",A65,"/M",A65,")") -> =(O65/M65) | O65: =CONCATENATE("=SUMAR.SI(",L65,"!B:B;Reliquidacion!B",A65,";",L65,"!W:W)") -> =SUMAR.SI(SIN DATA!B:B;Reliquidacion!B65;SIN DATA!W:W) | P65: =CONCATENATE("=SUMAR.SI(",L65,"!B:B;Reliquidacion!B",A65,";",L65,"!X:X)") -> =SUMAR.SI(SIN DATA!B:B;Reliquidacion!B65;SIN DATA!X:X) | Q65: =CONCATENATE("=(R",A65,"/P",A65,")") -> =(R65/P65) | R65: =CONCATENATE("=SUMAR.SI(",L65,"!B:B;Reliquidacion!B",A65,";",L65,"!AB:AB)") -> =SUMAR.SI(SIN DATA!B:B;Reliquidacion!B65;SIN DATA!AB:AB) | S65: =CONCATENATE("=(O",A65,"+R",A65,")") -> =(O65+R65) | U65: =CONCATENATE("=(S",A65,"-J",A65,")") -> =(S65-J65) | V65: PNP 19T/2021 | W65: =VLOOKUP(V65,#REF!,2,0) -> #REF! | X65: =VLOOKUP(V65,#REF!,6,0) -> #REF! | Y65: 44129 | Z65: =Z61 -> 44377 | AA65: =Z65-Y65 -> 248 | AB65: =+(1+X65)^(AA65/360)-1 -> #REF! | AC65: =AB65*U65 -> #REF! | AD65: =+U65+AC65 -> #VALUE!
AC66: Reliquidación | AD66: =SUM(AD33:AD65) -> #VALUE!
AB68: Montos a favor | AC68: Caren emite factura
AB69: Montos en contra | AC69: Caren emite nota de crédito

Sheet MAPA DATA
A2: Generador | B2: [GX] | D2: EFACT_CNE | E2: Información de facturación definitiva proveniente de los archivos EFACT publicados por la CNE en los Decretos de Precio de Nudo
A3: Distribuidor | B3: [EEDD] | D3: EFACT_EST_CEN | E3: Información de facturación definitiva estimada en base a los balances emitidos por el Coordinador
A4: Licitacion | B4: 2013/03-2° Llamado | D4: FACT_EMITIDA | E4: Información de facturación real desde PDFs y sistema SIGGE (gestión facturación electrónica)
A5: Bloque | B5: [BLOQUE] | D5: FACT_EST_EFACT | E5: Estimación de facturación emitida en base a información de los EFACT Decretos Precios de Nudo
D6: FACT_EST_CEN | E6: Estimación de facturación emitida en base a información de los Balances del Coordinador
D8: Lo que se facturó | G8: Lo que se debió haber facturado
A9: Prioridad de información | D9: 1 | E9: 2 | F9: 3 | G9: 1 | H9: 2
A10: Año | B10: Mes | C10: Fecha | D10: FACT_EMITIDA | E10: FACT_EST_EFACT | F10: FACT_EST_CEN | G10: EFACT_CNE | H10: EFACT_EST_CEN
A11: 2016 | B11: 1 | C11: 42370 | D11: =IF(COUNTIF(FACT_EMITIDA!B:B,'MAPA DATA'!C11)>0,1,0) -> 0 | E11: =IF(COUNTIF(FACT_EST_EFACT!B:B,'MAPA DATA'!C11)>0,1,0) -> 0 | F11: =IF(COUNTIF(FACT_EST_CEN!B:B,'MAPA DATA'!C11)>0,1,0) -> 0 | G11: =IF(COUNTIF(EFACT_CNE!B:B,'MAPA DATA'!C11)>0,1,0) -> 1 | H11: =IF(COUNTIF(EFACT_EST_CEN!B:B,'MAPA DATA'!C11)>0,1,0) -> 0
A12: 2016 | B12: 2 | C12: 42401 | D12: =IF(COUNTIF(FACT_EMITIDA!B:B,'MAPA DATA'!C12)>0,1,0) -> 0 | E12: =IF(COUNTIF(FACT_EST_EFACT!B:B,'MAPA DATA'!C12)>0,1,0) -> 0 | F12: =IF(COUNTIF(FACT_EST_CEN!B:B,'MAPA DATA'!C12)>0,1,0) -> 0 | G12: =IF(COUNTIF(EFACT_CNE!B:B,'MAPA DATA'!C12)>0,1,0) -> 1 | H12: =IF(COUNTIF(EFACT_EST_CEN!B:B,'MAPA DATA'!C12)>0,1,0) -> 0
A13: 2016 | B13: 3 | C13: 42430 | D13: =IF(COUNTIF(FACT_EMITIDA!B:B,'MAPA DATA'!C13)>0,1,0) -> 0 | E13: =IF(COUNTIF(FACT_EST_EFACT!B:B,'MAPA DATA'!C13)>0,1,0) -> 1 | F13: =IF(COUNTIF(FACT_EST_CEN!B:B,'MAPA DATA'!C13)>0,1,0) -> 0 | G13: =IF(COUNTIF(EFACT_CNE!B:B,'MAPA DATA'!C13)>0,1,0) -> 1 | H13: =IF(COUNTIF(EFACT_EST_CEN!B:B,'MAPA DATA'!C13)>0,1,0) -> 0
A14: 2016 | B14: 4 | C14: 42461 | D14: =IF(COUNTIF(FACT_EMITIDA!B:B,'MAPA DATA'!C14)>0,1,0) -> 0 | E14: =IF(COUNTIF(FACT_EST_EFACT!B:B,'MAPA DATA'!C14)>0,1,0) -> 1 | F14: =IF(COUNTIF(FACT_EST_CEN!B:B,'MAPA DATA'!C14)>0,1,0) -> 0 | G14: =IF(COUNTIF(EFACT_CNE!B:B,'MAPA DATA'!C14)>0,1,0) -> 1 | H14: =IF(COUNTIF(EFACT_EST_CEN!B:B,'MAPA DATA'!C14)>0,1,0) -> 0
A15: 2016 | B15: 5 | C15: 42491 | D15: =IF(COUNTIF(FACT_EMITIDA!B:B,'MAPA DATA'!C15)>0,1,0) -> 0 | E15: =IF(COUNTIF(FACT_EST_EFACT!B:B,'MAPA DATA'!C15)>0,1,0) -> 1 | F15: =IF(COUNTIF(FACT_EST_CEN!B:B,'MAPA DATA'!C15)>0,1,0) -> 0 | G15: =IF(COUNTIF(EFACT_CNE!B:B,'MAPA DATA'!C15)>0,1,0) -> 1 | H15: =IF(COUNTIF(EFACT_EST_CEN!B:B,'MAPA DATA'!C15)>0,1,0) -> 0
A16: 2016 | B16: 6 | C16: 42522 | D16: =IF(COUNTIF(FACT_EMITIDA!B:B,'MAPA DATA'!C16)>0,1,0) -> 0 | E16: =IF(COUNTIF(FACT_EST_EFACT!B:B,'MAPA DATA'!C16)>0,1,0) -> 1 | F16: =IF(COUNTIF(FACT_EST_CEN!B:B,'MAPA DATA'!C16)>0,1,0) -> 0 | G16: =IF(COUNTIF(EFACT_CNE!B:B,'MAPA DATA'!C16)>0,1,0) -> 1 | H16: =IF(COUNTIF(EFACT_EST_CEN!B:B,'MAPA DATA'!C16)>0,1,0) -> 0
A17: 2016 | B17: 7 | C17: 42552 | D17: =IF(COUNTIF(FACT_EMITIDA!B:B,'MAPA DATA'!C17)>0,1,0) -> 0 | E17: =IF(COUNTIF(FACT_EST_EFACT!B:B,'MAPA DATA'!C17)>0,1,0) -> 1 | F17: =IF(COUNTIF(FACT_EST_CEN!B:B,'MAPA DATA'!C17)>0,1,0) -> 0 | G17: =IF(COUNTIF(EFACT_CNE!B:B,'MAPA DATA'!C17)>0,1,0) -> 1 | H17: =IF(COUNTIF(EFACT_EST_CEN!B:B,'MAPA DATA'!C17)>0,1,0) -> 0
A18: 2016 | B18: 8 | C18: 42583 | D18: =IF(COUNTIF(FACT_EMITIDA!B:B,'MAPA DATA'!C18)>0,1,0) -> 0 | E18: =IF(COUNTIF(FACT_EST_EFACT!B:B,'MAPA DATA'!C18)>0,1,0) -> 0 | F18: =IF(COUNTIF(FACT_EST_CEN!B:B,'MAPA DATA'!C18)>0,1,0) -> 0 | G18: =IF(COUNTIF(EFACT_CNE!B:B,'MAPA DATA'!C18)>0,1,0) -> 1 | H18: =IF(COUNTIF(EFACT_EST_CEN!B:B,'MAPA DATA'!C18)>0,1,0) -> 0
A19: 2016 | B19: 9 | C19: 42614 | D19: =IF(COUNTIF(FACT_EMITIDA!B:B,'MAPA DATA'!C19)>0,1,0) -> 0 | E19: =IF(COUNTIF(FACT_EST_EFACT!B:B,'MAPA DATA'!C19)>0,1,0) -> 1 | F19: =IF(COUNTIF(FACT_EST_CEN!B:B,'MAPA DATA'!C19)>0,1,0) -> 0 | G19: =IF(COUNTIF(EFACT_CNE!B:B,'MAPA DATA'!C19)>0,1,0) -> 1 | H19: =IF(COUNTIF(EFACT_EST_CEN!B:B,'MAPA DATA'!C19)>0,1,0) -> 0
A20: 2016 | B20: 10 | C20: 42644 | D20: =IF(COUNTIF(FACT_EMITIDA!B:B,'MAPA DATA'!C20)>0,1,0) -> 0 | E20: =IF(COUNTIF(FACT_EST_EFACT!B:B,'MAPA DATA'!C20)>0,1,0) -> 1 | F20: =IF(COUNTIF(FACT_EST_CEN!B:B,'MAPA DATA'!C20)>0,1,0) -> 0 | G20: =IF(COUNTIF(EFACT_CNE!B:B,'MAPA DATA'!C20)>0,1,0) -> 1 | H20: =IF(COUNTIF(EFACT_EST_CEN!B:B,'MAPA DATA'!C20)>0,1,0) -> 0
A21: 2016 | B21: 11 | C21: 42675 | D21: =IF(COUNTIF(FACT_EMITIDA!B:B,'MAPA DATA'!C21)>0,1,0) -> 0 | E21: =IF(COUNTIF(FACT_EST_EFACT!B:B,'MAPA DATA'!C21)>0,1,0) -> 1 | F21: =IF(COUNTIF(FACT_EST_CEN!B:B,'MAPA DATA'!C21)>0,1,0) -> 0 | G21: =IF(COUNTIF(EFACT_CNE!B:B,'MAPA DATA'!C21)>0,1,0) -> 1 | H21: =IF(COUNTIF(EFACT_EST_CEN!B:B,'MAPA DATA'!C21)>0,1,0) -> 0
A22: 2016 | B22: 12 | C22: 42705 | D22: =IF(COUNTIF(FACT_EMITIDA!B:B,'MAPA DATA'!C22)>0,1,0) -> 0 | E22: =IF(COUNTIF(FACT_EST_EFACT!B:B,'MAPA DATA'!C22)>0,1,0) -> 1 | F22: =IF(COUNTIF(FACT_EST_CEN!B:B,'MAPA DATA'!C22)>0,1,0) -> 0 | G22: =IF(COUNTIF(EFACT_CNE!B:B,'MAPA DATA'!C22)>0,1,0) -> 1 | H22: =IF(COUNTIF(EFACT_EST_CEN!B:B,'MAPA DATA'!C22)>0,1,0) -> 0
A23: =A11+1 -> 2017 | B23: =B11 -> 1 | C23: 42736 | D23: =IF(COUNTIF(FACT_EMITIDA!B:B,'MAPA DATA'!C23)>0,1,0) -> 0 | E23: =IF(COUNTIF(FACT_EST_EFACT!B:B,'MAPA DATA'!C23)>0,1,0) -> 0 | F23: =IF(COUNTIF(FACT_EST_CEN!B:B,'MAPA DATA'!C23)>0,1,0) -> 0 | G23: =IF(COUNTIF(EFACT_CNE!B:B,'MAPA DATA'!C23)>0,1,0) -> 1 | H23: =IF(COUNTIF(EFACT_EST_CEN!B:B,'MAPA DATA'!C23)>0,1,0) -> 0
A24: =A12+1 -> 2017 | B24: =B12 -> 2 | C24: 42767 | D24: =IF(COUNTIF(FACT_EMITIDA!B:B,'MAPA DATA'!C24)>0,1,0) -> 0 | E24: =IF(COUNTIF(FACT_EST_EFACT!B:B,'MAPA DATA'!C24)>0,1,0) -> 1 | F24: =IF(COUNTIF(FACT_EST_CEN!B:B,'MAPA DATA'!C24)>0,1,0) -> 0 | G24: =IF(COUNTIF(EFACT_CNE!B:B,'MAPA DATA'!C24)>0,1,0) -> 1 | H24: =IF(COUNTIF(EFACT_EST_CEN!B:B,'MAPA DATA'!C24)>0,1,0) -> 0
A25: =A13+1 -> 2017 | B25: =B13 -> 3 | C25: 42795 | D25: =IF(COUNTIF(FACT_EMITIDA!B:B,'MAPA DATA'!C25)>0,1,0) -> 0 | E25: =IF(COUNTIF(FACT_EST_EFACT!B:B,'MAPA DATA'!C25)>0,1,0) -> 1 | F25: =IF(COUNTIF(FACT_EST_CEN!B:B,'MAPA DATA'!C25)>0,1,0) -> 0 | G25: =IF(COUNTIF(EFACT_CNE!B:B,'MAPA DATA'!C25)>0,1,0) -> 1 | H25: =IF(COUNTIF(EFACT_EST_CEN!B:B,'MAPA DATA'!C25)>0,1,0) -> 0
A26: =A14+1 -> 2017 | B26: =B14 -> 4 | C26: 42826 | D26: =IF(COUNTIF(FACT_EMITIDA!B:B,'MAPA DATA'!C26)>0,1,0) -> 0 | E26: =IF(COUNTIF(FACT_EST_EFACT!B:B,'MAPA DATA'!C26)>0,1,0) -> 1 | F26: =IF(COUNTIF(FACT_EST_CEN!B:B,'MAPA DATA'!C26)>0,1,0) -> 0 | G26: =IF(COUNTIF(EFACT_CNE!B:B,'MAPA DATA'!C26)>0,1,0) -> 1 | H26: =IF(COUNTIF(EFACT_EST_CEN!B:B,'MAPA DATA'!C26)>0,1,0) -> 0
A27: =A15+1 -> 2017 | B27: =B15 -> 5 | C27: 42856 | D27: =IF(COUNTIF(FACT_EMITIDA!B:B,'MAPA DATA'!C27)>0,1,0) -> 0 | E27: =IF(COUNTIF(FACT_EST_EFACT!B:B,'MAPA DATA'!C27)>0,1,0) -> 1 | F27: =IF(COUNTIF(FACT_EST_CEN!B:B,'MAPA DATA'!C27)>0,1,0) -> 0 | G27: =IF(COUNTIF(EFACT_CNE!B:B,'MAPA DATA'!C27)>0,1,0) -> 1 | H27: =IF(COUNTIF(EFACT_EST_CEN!B:B,'MAPA DATA'!C27)>0,1,0) -> 0
A28: =A16+1 -> 2017 | B28: =B16 -> 6 | C28: 42887 | D28: =IF(COUNTIF(FACT_EMITIDA!B:B,'MAPA DATA'!C28)>0,1,0) -> 0 | E28: =IF(COUNTIF(FACT_EST_EFACT!B:B,'MAPA DATA'!C28)>0,1,0) -> 1 | F28: =IF(COUNTIF(FACT_EST_CEN!B:B,'MAPA DATA'!C28)>0,1,0) -> 0 | G28: =IF(COUNTIF(EFACT_CNE!B:B,'MAPA DATA'!C28)>0,1,0) -> 1 | H28: =IF(COUNTIF(EFACT_EST_CEN!B:B,'MAPA DATA'!C28)>0,1,0) -> 0
A29: =A17+1 -> 2017 | B29: =B17 -> 7 | C29: 42917 | D29: =IF(COUNTIF(FACT_EMITIDA!B:B,'MAPA DATA'!C29)>0,1,0) -> 0 | E29: =IF(COUNTIF(FACT_EST_EFACT!B:B,'MAPA DATA'!C29)>0,1,0) -> 1 | F29: =IF(COUNTIF(FACT_EST_CEN!B:B,'MAPA DATA'!C29)>0,1,0) -> 0 | G29: =IF(COUNTIF(EFACT_CNE!B:B,'MAPA DATA'!C29)>0,1,0) -> 1 | H29: =IF(COUNTIF(EFACT_EST_CEN!B:B,'MAPA DATA'!C29)>0,1,0) -> 0
A30: =A18+1 -> 2017 | B30: =B18 -> 8 | C30: 42948 | D30: =IF(COUNTIF(FACT_EMITIDA!B:B,'MAPA DATA'!C30)>0,1,0) -> 0 | E30: =IF(COUNTIF(FACT_EST_EFACT!B:B,'MAPA DATA'!C30)>0,1,0) -> 1 | F30: =IF(COUNTIF(FACT_EST_CEN!B:B,'MAPA DATA'!C30)>0,1,0) -> 0 | G30: =IF(COUNTIF(EFACT_CNE!B:B,'MAPA DATA'!C30)>0,1,0) -> 1 | H30: =IF(COUNTIF(EFACT_EST_CEN!B:B,'MAPA DATA'!C30)>0,1,0) -> 0
A31: =A19+1 -> 2017 | B31: =B19 -> 9 | C31: 42979 | D31: =IF(COUNTIF(FACT_EMITIDA!B:B,'MAPA DATA'!C31)>0,1,0) -> 0 | E31: =IF(COUNTIF(FACT_EST_EFACT!B:B,'MAPA DATA'!C31)>0,1,0) -> 1 | F31: =IF(COUNTIF(FACT_EST_CEN!B:B,'MAPA DATA'!C31)>0,1,0) -> 0 | G31: =IF(COUNTIF(EFACT_CNE!B:B,'MAPA DATA'!C31)>0,1,0) -> 1 | H31: =IF(COUNTIF(EFACT_EST_CEN!B:B,'MAPA DATA'!C31)>0,1,0) -> 0
A32: =A20+1 -> 2017 | B32: =B20 -> 10 | C32: 43009 | D32: =IF(COUNTIF(FACT_EMITIDA!B:B,'MAPA DATA'!C32)>0,1,0) -> 0 | E32: =IF(COUNTIF(FACT_EST_EFACT!B:B,'MAPA DATA'!C32)>0,1,0) -> 1 | F32: =IF(COUNTIF(FACT_EST_CEN!B:B,'MAPA DATA'!C32)>0,1,0) -> 0 | G32: =IF(COUNTIF(EFACT_CNE!B:B,'MAPA DATA'!C32)>0,1,0) -> 1 | H32: =IF(COUNTIF(EFACT_EST_CEN!B:B,'MAPA DATA'!C32)>0,1,0) -> 0
A33: =A21+1 -> 2017 | B33: =B21 -> 11 | C33: 43040 | D33: =IF(COUNTIF(FACT_EMITIDA!B:B,'MAPA DATA'!C33)>0,1,0) -> 0 | E33: =IF(COUNTIF(FACT_EST_EFACT!B:B,'MAPA DATA'!C33)>0,1,0) -> 1 | F33: =IF(COUNTIF(FACT_EST_CEN!B:B,'MAPA DATA'!C33)>0,1,0) -> 0 | G33: =IF(COUNTIF(EFACT_CNE!B:B,'MAPA DATA'!C33)>0,1,0) -> 1 | H33: =IF(COUNTIF(EFACT_EST_CEN!B:B,'MAPA DATA'!C33)>0,1,0) -> 0
A34: =A22+1 -> 2017 | B34: =B22 -> 12 | C34: 43070 | D34: =IF(COUNTIF(FACT_EMITIDA!B:B,'MAPA DATA'!C34)>0,1,0) -> 0 | E34: =IF(COUNTIF(FACT_EST_EFACT!B:B,'MAPA DATA'!C34)>0,1,0) -> 1 | F34: =IF(COUNTIF(FACT_EST_CEN!B:B,'MAPA DATA'!C34)>0,1,0) -> 0 | G34: =IF(COUNTIF(EFACT_CNE!B:B,'MAPA DATA'!C34)>0,1,0) -> 1 | H34: =IF(COUNTIF(EFACT_EST_CEN!B:B,'MAPA DATA'!C34)>0,1,0) -> 0
... A67: =A55+1 -> 2020 | B67: =B55 -> 9 | C67: 44075 | D67: =IF(COUNTIF(FACT_EMITIDA!B:B,'MAPA DATA'!C67)>0,1,0) -> 1 | E67: =IF(COUNTIF(FACT_EST_EFACT!B:B,'MAPA DATA'!C67)>0,1,0) -> 0 | F67: =IF(COUNTIF(FACT_EST_CEN!B:B,'MAPA DATA'!C67)>0,1,0) -> 0 | G67: =IF(COUNTIF(EFACT_CNE!B:B,'MAPA DATA'!C67)>0,1,0) -> 0 | H67: =IF(COUNTIF(EFACT_EST_CEN!B:B,'MAPA DATA'!C67)>0,1,0) -> 0

Sheet FACT_EST_CEN

Sheet FACT_EST_EFACT
A1: IdContrato | B1: MesDevengado | C1: Anho | D1: Mes | E1: Codigo | F1: DX | G1: NomEmpresaDistribuidora | H1: GX | I1: NomSuministrador | J1: CodigoContrato | K1: PuntoRetiro | L1: Contrato | M1: Energia_kWh | N1: Potencia_kW | O1: Sistema | P1: DataCreated | Q1: IdBarra | R1: NomBarra | S1: Energia | T1: PrecioEnergia | U1: PrecioEnergiaAjustado | V1: TotalEnergia | W1: TotalEnergiaAjustado | X1: Potencia | Y1: PrecioPotencia | Z1: PrecioPotenciaAjustado | AA1: TotalPotencia | AB1: TotalPotenciaAjustado | AC1: EmpresaDistribuidora | AD1: Fecha
A2: 607827 | B2: 01-03-2016 | C2: 2016 | D2: 3 | E2: QUINTA | F2: CEC | G2: CEC | H2: Empresa Eléctrica Carén S.A. | I2: CAREN | J2: SIC 2013/03_2_BS1A_BB_CEC_Empresa Eléctrica Carén S.A. | K2: QUINTA 13,2 | L2: SIC 2013/03_2_BS1A_BB | M2: 1703.6854 | N2: 0 | O2: SIC4 | P2: 44330.495 | Q2: 5439222 | R2: Charrua 220 | S2: 45.689989 | X2: 0 | AC2: CEC | AD2: 42430
A3: 607809 | B3: 01-03-2016 | C3: 2016 | D3: 3 | E3: Curico | F3: CEC | G3: CEC | H3: Empresa Eléctrica Carén S.A. | I3: CAREN | J3: SIC 2013/03_2_BS1A_BB_CEC_Empresa Eléctrica Carén S.A. | K3: CURICÓ 13,2 | L3: SIC 2013/03_2_BS1A_BB | M3: 6396.7767 | N3: 0 | O3: SIC4 | P3: 44330.495 | Q3: 5439188 | R3: Charrua 220 | S3: 95.084381 | X3: 0 | AC3: CEC | AD3: 42430
A4: 607845 | B4: 01-03-2016 | C4: 2016 | D4: 3 | E4: TENO | F4: CEC | G4: CEC | H4: Empresa Eléctrica Carén S.A. | I4: CAREN | J4: SIC 2013/03_2_BS1A_BB_CEC_Empresa Eléctrica Carén S.A. | K4: TENO 13,2 | L4: SIC 2013/03_2_BS1A_BB | M4: 2312.6678 | N4: 0 | O4: SIC4 | P4: 44330.495 | Q4: 5439256 | R4: Charrua 220 | S4: 61.060298 | X4: 0 | AC4: CEC | AD4: 42430
A5: 607827 | B5: 01-03-2016 | C5: 2016 | D5: 3 | E5: QUINTA | F5: CEC | G5: CEC | H5: Empresa Eléctrica Carén S.A. | I5: CAREN | J5: SIC 2013/03_2_BS1A_BB_CEC_Empresa Eléctrica Carén S.A. | K5: QUINTA 13,2 | L5: SIC 2013/03_2_BS1A_BB | M5: 1703.6854 | N5: 0 | O5: SIC4 | P5: 44330.495 | Q5: 5439221 | R5: Itahue 220 | S5: 1725.2398 | X5: 0 | AC5: CEC | AD5: 42430
A6: 607845 | B6: 01-03-2016 | C6: 2016 | D6: 3 | E6: TENO | F6: CEC | G6: CEC | H6: Empresa Eléctrica Carén S.A. | I6: CAREN | J6: SIC 2013/03_2_BS1A_BB_CEC_Empresa Eléctrica Carén S.A. | K6: TENO 13,2 | L6: SIC 2013/03_2_BS1A_BB | M6: 2312.6678 | N6: 0 | O6: SIC4 | P6: 44330.495 | Q6: 5439255 | R6: Itahue 220 | S6: 2342.8885 | X6: 0 | AC6: CEC | AD6: 42430
A7: 607809 | B7: 01-03-2016 | C7: 2016 | D7: 3 | E7: Curico | F7: CEC | G7: CEC | H7: Empresa Eléctrica Carén S.A. | I7: CAREN | J7: SIC 2013/03_2_BS1A_BB_CEC_Empresa Eléctrica Carén S.A. | K7: CURICÓ 13,2 | L7: SIC 2013/03_2_BS1A_BB | M7: 6396.7767 | N7: 0 | O7: SIC4 | P7: 44330.495 | Q7: 5439187 | R7: Itahue 220 | S7: 6554.173 | X7: 0 | AC7: CEC | AD7: 42430
A8: 600911 | B8: 01-04-2016 | C8: 2016 | D8: 4 | E8: Curico | F8: CEC | G8: CEC | H8: Empresa Eléctrica Carén S.A. | I8: CAREN | J8: SIC 2013/03_2_BS1A_BB_CEC_Empresa Eléctrica Carén S.A. | K8: CURICÓ 13,2 | L8: SIC 2013/03_2_BS1A_BB | M8: 4919.3409 | N8: 0 | O8: SIC4 | P8: 44330.488 | Q8: 5423000 | R8: Charrua 220 | S8: 73.123154 | X8: 0 | AC8: CEC | AD8: 42461
A9: 600947 | B9: 01-04-2016 | C9: 2016 | D9: 4 | E9: TENO | F9: CEC | G9: CEC | H9: Empresa Eléctrica Carén S.A. | I9: CAREN | J9: SIC 2013/03_2_BS1A_BB_CEC_Empresa Eléctrica Carén S.A. | K9: TENO 13,2 | L9: SIC 2013/03_2_BS1A_BB | M9: 2065.7815 | N9: 0 | O9: SIC4 | P9: 44330.488 | Q9: 5423068 | R9: Charrua 220 | S9: 54.541875 | X9: 0 | AC9: CEC | AD9: 42461
A10: 600929 | B10: 01-04-2016 | C10: 2016 | D10: 4 | E10: QUINTA | F10: CEC | G10: CEC | H10: Empresa Eléctrica Carén S.A. | I10: CAREN | J10: SIC 2013/03_2_BS1A_BB_CEC_Empresa Eléctrica Carén S.A. | K10: QUINTA 13,2 | L10: SIC 2013/03_2_BS1A_BB | M10: 1317.6215 | N10: 0 | O10: SIC4 | P10: 44330.488 | Q10: 5423034 | R10: Charrua 220 | S10: 35.336403 | X10: 0 | AC10: CEC | AD10: 42461
A11: 600929 | B11: 01-04-2016 | C11: 2016 | D11: 4 | E11: QUINTA | F11: CEC | G11: CEC | H11: Empresa Eléctrica Carén S.A. | I11: CAREN | J11: SIC 2013/03_2_BS1A_BB_CEC_Empresa Eléctrica Carén S.A. | K11: QUINTA 13,2 | L11: SIC 2013/03_2_BS1A_BB | M11: 1317.6215 | N11: 0 | O11: SIC4 | P11: 44330.488 | Q11: 5423033 | R11: Itahue 220 | S11: 1334.2916 | X11: 0 | AC11: CEC | AD11: 42461
A12: 600911 | B12: 01-04-2016 | C12: 2016 | D12: 4 | E12: Curico | F12: CEC | G12: CEC | H12: Empresa Eléctrica Carén S.A. | I12: CAREN | J12: SIC 2013/03_2_BS1A_BB_CEC_Empresa Eléctrica Carén S.A. | K12: CURICÓ 13,2 | L12: SIC 2013/03_2_BS1A_BB | M12: 4919.3409 | N12: 0 | O12: SIC4 | P12: 44330.488 | Q12: 5422999 | R12: Itahue 220 | S12: 5040.3841 | X12: 0 | AC12: CEC | AD12: 42461
A13: 600947 | B13: 01-04-2016 | C13: 2016 | D13: 4 | E13: TENO | F13: CEC | G13: CEC | H13: Empresa Eléctrica Carén S.A. | I13: CAREN | J13: SIC 2013/03_2_BS1A_BB_CEC_Empresa Eléctrica Carén S.A. | K13: TENO 13,2 | L13: SIC 2013/03_2_BS1A_BB | M13: 2065.7815 | N13: 0 | O13: SIC4 | P13: 44330.488 | Q13: 5423067 | R13: Itahue 220 | S13: 2092.776 | X13: 0 | AC13: CEC | AD13: 42461
... A517: 420506 | B517: 01-06-2020 | C517: 2020 | D517: 6 | E517: Curico 13.2 | F517: CEC | G517: CEC | H517: Empresa Eléctrica Carén S.A. | I517: Empresa Eléctrica Carén S.A. | J517: SIC 2013/03_2_BS1A_BB_CEC_Empresa Eléctrica Carén S.A. | K517: Curico 13.2 | L517: SIC 2013/03_2_BS1A_BB | M517: 2681.58 | N517: 0 | O517: STX E | P517: 44277.586 | Q517: 3980788 | R517: RAPEL 220 | S517: 8.3052895 | X517: 0 | AC517: CEC | AD517: 43983

Sheet FACT_EMITIDA
A1: Periodo | B1: MesDevengado | C1: Nombre | D1: Num | E1: Barra | F1: Cantidad | G1: Precio | H1: Monto | I1: Concepto | J1: Agrupacion | K1: Glosa | L1: FechaCarga | M1: TipoDocumento | N1: Folio | O1: Vendedor | P1: Comprador | Q1: Bloque | R1: Empresa | S1: ClaveEEDD | T1: Licitacion | U1: NomAgrupacion
A2: 01-09-2018 | B2: 01-09-2018 | C2: Licitación Caren y Cec (SIC 2013/03-2) BS1A | D2: 1 | E2: TotalBarras | F2: 3000 | G2: 58.085 | H2: 174255 | I2: Energia Licitaciones | J2: Energía | K2: Lic. SIC 2013/03-2 bloques BS1A: Energía sep 2018 | L2: 2018-10-19 00:00:00 | M2: 33 | N2: 6305 | O2: s | P2: s | Q2: BS1A | R2: Caren | S2: Cec | T2: 2013/03-2 | U2: CEC
A3: 01-10-2018 | B3: 01-10-2018 | C3: Licitación Caren y Cec (SIC 2013/03-2) BS1A | D3: 1 | E3: TotalBarras | F3: 3000 | G3: 59.678 | H3: 179035 | I3: Energia Licitaciones | J3: Energía | K3: Lic. SIC 2013/03-2 bloques BS1A: Energía oct 2018 | L3: 2018-11-27 00:00:00 | M3: 33 | N3: 6796 | O3: s | P3: s | Q3: BS1A | R3: Caren | S3: Cec | T3: 2013/03-2 | U3: CEC
A4: 01-11-2018 | B4: 01-11-2018 | C4: Licitación Caren y Cec (SIC 2013/03-2) BS1A | D4: 1 | E4: TotalBarras | F4: 4000 | G4: 59.635 | H4: 238540 | I4: Energia Licitaciones | J4: Energía | K4: Lic. SIC 2013/03-2 bloques BS1A: Energía nov 2018 | L4: 2018-12-14 00:00:00 | M4: 33 | N4: 6939 | O4: s | P4: s | Q4: BS1A | R4: Caren | S4: Cec | T4: 2013/03-2 | U4: CEC
A5: 01-12-2018 | B5: 01-12-2018 | C5: Licitación Caren y Cec (SIC 2013/03-2) BS1A | D5: 1 | E5: TotalBarras | F5: 5000 | G5: 67.951 | H5: 339757 | I5: Energia Licitaciones | J5: Energía | K5: Lic. SIC 2013/03-2 bloques BS1A: Energía dic 2018 | L5: 2019-01-21 00:00:00 | M5: 33 | N5: 7194 | O5: s | P5: s | Q5: BS1A | R5: Caren | S5: Cec | T5: 2013/03-2 | U5: CEC
A6: 01-01-2019 | B6: 01-01-2019 | C6: Licitación Caren y Cec (SIC 2013/03-2) BS1A | D6: 1 | E6: A.JAHUEL 220 | F6: 1.46188 | G6: 66.9 | H6: 98 | I6: Reliq. Energia Licitaciones | J6: Energía | K6: Lic. SIC 2013/03-2 bloques BS1A: Reliq. Energía ene 2019 | L6: 2019-03-15 00:00:00 | M6: 33 | O6: s | P6: s | Q6: BS1A | R6: Caren | S6: Cec | T6: 2013/03-2 | U6: CEC
A7: 01-01-2019 | B7: 01-01-2019 | C7: Licitación Caren y Cec (SIC 2013/03-2) BS1A | D7: 1 | E7: A.JAHUEL 220 | F7: 1371.306 | G7: 66.9 | H7: 91740 | I7: Energia Licitaciones | J7: Energía | K7: Lic. SIC 2013/03-2 bloques BS1A: Energía ene 2019 | L7: 2019-02-08 00:00:00 | M7: 33 | N7: 7513 | O7: s | P7: s | Q7: BS1A | R7: Caren | S7: Cec | T7: 2013/03-2 | U7: CEC
A8: 01-01-2019 | B8: 01-01-2019 | C8: Licitación Caren y Cec (SIC 2013/03-2) BS1A | D8: 2 | E8: A.MELIP 220 | F8: 0.009388 | G8: 69.014 | H8: 1 | I8: Reliq. Energia Licitaciones | J8: Energía | K8: Lic. SIC 2013/03-2 bloques BS1A: Reliq. Energía ene 2019 | L8: 2019-03-15 00:00:00 | M8: 33 | O8: s | P8: s | Q8: BS1A | R8: Caren | S8: Cec | T8: 2013/03-2 | U8: CEC
A9: 01-01-2019 | B9: 01-01-2019 | C9: Licitación Caren y Cec (SIC 2013/03-2) BS1A | D9: 2 | E9: A.MELIP 220 | F9: 8.806166 | G9: 69.014 | H9: 608 | I9: Energia Licitaciones | J9: Energía | K9: Lic. SIC 2013/03-2 bloques BS1A: Energía ene 2019 | L9: 2019-02-08 00:00:00 | M9: 33 | N9: 7513 | O9: s | P9: s | Q9: BS1A | R9: Caren | S9: Cec | T9: 2013/03-2 | U9: CEC
A10: 01-01-2019 | B10: 01-01-2019 | C10: Licitación Caren y Cec (SIC 2013/03-2) BS1A | D10: 3 | E10: CHARRUA 220 | F10: 0.453721 | G10: 63.27 | H10: 29 | I10: Reliq. Energia Licitaciones | J10: Energía | K10: Lic. SIC 2013/03-2 bloques BS1A: Reliq. Energía ene 2019 | L10: 2019-03-15 00:00:00 | M10: 33 | O10: s | P10: s | Q10: BS1A | R10: Caren | S10: Cec | T10: 2013/03-2 | U10: CEC
A11: 01-01-2019 | B11: 01-01-2019 | C11: Licitación Caren y Cec (SIC 2013/03-2) BS1A | D11: 3 | E11: CHARRUA 220 | F11: 425.60961 | G11: 63.27 | H11: 26928 | I11: Energia Licitaciones | J11: Energía | K11: Lic. SIC 2013/03-2 bloques BS1A: Energía ene 2019 | L11: 2019-02-08 00:00:00 | M11: 33 | N11: 7513 | O11: s | P11: s | Q11: BS1A | R11: Caren | S11: Cec | T11: 2013/03-2 | U11: CEC
A12: 01-01-2019 | B12: 01-01-2019 | C12: Licitación Caren y Cec (SIC 2013/03-2) BS1A | D12: 4 | E12: ITAHUE 220 | F12: 2.212452 | G12: 65.349 | H12: 145 | I12: Reliq. Energia Licitaciones | J12: Energía | K12: Lic. SIC 2013/03-2 bloques BS1A: Reliq. Energía ene 2019 | L12: 2019-03-15 00:00:00 | M12: 33 | O12: s | P12: s | Q12: BS1A | R12: Caren | S12: Cec | T12: 2013/03-2 | U12: CEC
A13: 01-01-2019 | B13: 01-01-2019 | C13: Licitación Caren y Cec (SIC 2013/03-2) BS1A | D13: 4 | E13: ITAHUE 220 | F13: 2075.374 | G13: 65.349 | H13: 135624 | I13: Energia Licitaciones | J13: Energía | K13: Lic. SIC 2013/03-2 bloques BS1A: Energía ene 2019 | L13: 2019-02-08 00:00:00 | M13: 33 | N13: 7513 | O13: s | P13: s | Q13: BS1A | R13: Caren | S13: Cec | T13: 2013/03-2 | U13: CEC
A14: 01-01-2019 | B14: 01-01-2019 | C14: Licitación Caren y Cec (SIC 2013/03-2) BS1A | D14: 5 | E14: RAPEL 220 | F14: 8.102057 | G14: 69.368 | H14: 562 | I14: Energia Licitaciones | J14: Energía | K14: Lic. SIC 2013/03-2 bloques BS1A: Energía ene 2019 | L14: 2019-02-08 00:00:00 | M14: 33 | N14: 7513 | O14: s | P14: s | Q14: BS1A | R14: Caren | S14: Cec | T14: 2013/03-2 | U14: CEC
A15: 01-01-2019 | B15: 01-01-2019 | C15: Licitación Caren y Cec (SIC 2013/03-2) BS1A | D15: 5 | E15: RAPEL 220 | F15: 0.008637 | G15: 69.368 | H15: 1 | I15: Reliq. Energia Licitaciones | J15: Energía | K15: Lic. SIC 2013/03-2 bloques BS1A: Reliq. Energía ene 2019 | L15: 2019-03-15 00:00:00 | M15: 33 | O15: s | P15: s | Q15: BS1A | R15: Caren | S15: Cec | T15: 2013/03-2 | U15: CEC
A16: 01-02-2019 | B16: 01-02-2019 | C16: Licitación Caren y Cec (SIC 2013/03-2) BS1A | D16: 1 | E16: A.JAHUEL 220 | F16: 1368.5299 | G16: 66.9 | H16: 91555 | I16: Energia Licitaciones | J16: Energía | K16: Lic. SIC 2013/03-2 bloques BS1A: Energía feb 2019 | L16: 2019-03-08 00:00:00 | M16: 33 | N16: 7798 | O16: s | P16: s | Q16: BS1A | R16: Caren | S16: Cec | T16: 2013/03-2 | U16: CEC
A17: 01-02-2019 | B17: 01-02-2019 | C17: Licitación Caren y Cec (SIC 2013/03-2) BS1A | D17: 1 | E17: A.JAHUEL 220 | F17: 0.23349 | G17: 66.9 | H17: 16 | I17: Reliq. Energia Licitaciones | J17: Energía | K17: Lic. SIC 2013/03-2 bloques BS1A: Reliq. Energía feb 2019 | L17: 2019-04-09 00:00:00 | M17: 61 | O17: s | P17: s | Q17: BS1A | R17: Caren | S17: Cec | T17: 2013/03-2 | U17: CEC
A18: 01-02-2019 | B18: 01-02-2019 | C18: Licitación Caren y Cec (SIC 2013/03-2) BS1A | D18: 2 | E18: A.MELIP 220 | F18: 8.816632 | G18: 69.014 | H18: 608 | I18: Energia Licitaciones | J18: Energía | K18: Lic. SIC 2013/03-2 bloques BS1A: Energía feb 2019 | L18: 2019-03-08 00:00:00 | M18: 33 | N18: 7798 | O18: s | P18: s | Q18: BS1A | R18: Caren | S18: Cec | T18: 2013/03-2 | U18: CEC
A19: 01-02-2019 | B19: 01-02-2019 | C19: Licitación Caren y Cec (SIC 2013/03-2) BS1A | D19: 3 | E19: CHARRUA 220 | F19: 422.52678 | G19: 63.27 | H19: 26733 | I19: Energia Licitaciones | J19: Energía | K19: Lic. SIC 2013/03-2 bloques BS1A: Energía feb 2019 | L19: 2019-03-08 00:00:00 | M19: 33 | N19: 7798 | O19: s | P19: s | Q19: BS1A | R19: Caren | S19: Cec | T19: 2013/03-2 | U19: CEC
A20: 01-02-2019 | B20: 01-02-2019 | C20: Licitación Caren y Cec (SIC 2013/03-2) BS1A | D20: 3 | E20: CHARRUA 220 | F20: 0.072089 | G20: 63.27 | H20: 5 | I20: Reliq. Energia Licitaciones | J20: Energía | K20: Lic. SIC 2013/03-2 bloques BS1A: Reliq. Energía feb 2019 | L20: 2019-04-09 00:00:00 | M20: 61 | O20: s | P20: s | Q20: BS1A | R20: Caren | S20: Cec | T20: 2013/03-2 | U20: CEC
A21: 01-02-2019 | B21: 01-02-2019 | C21: Licitación Caren y Cec (SIC 2013/03-2) BS1A | D21: 4 | E21: ITAHUE 220 | F21: 0.353269 | G21: 65.349 | H21: 23 | I21: Reliq. Energia Licitaciones | J21: Energía | K21: Lic. SIC 2013/03-2 bloques BS1A: Reliq. Energía feb 2019 | L21: 2019-04-09 00:00:00 | M21: 61 | O21: s | P21: s | Q21: BS1A | R21: Caren | S21: Cec | T21: 2013/03-2 | U21: CEC
A22: 01-02-2019 | B22: 01-02-2019 | C22: Licitación Caren y Cec (SIC 2013/03-2) BS1A | D22: 4 | E22: ITAHUE 220 | F22: 2070.5801 | G22: 65.349 | H22: 135310 | I22: Energia Licitaciones | J22: Energía | K22: Lic. SIC 2013/03-2 bloques BS1A: Energía feb 2019 | L22: 2019-03-08 00:00:00 | M22: 33 | N22: 7798 | O22: s | P22: s | Q22: BS1A | R22: Caren | S22: Cec | T22: 2013/03-2 | U22: CEC
A23: 01-02-2019 | B23: 01-02-2019 | C23: Licitación Caren y Cec (SIC 2013/03-2) BS1A | D23: 5 | E23: RAPEL 220 | F23: 8.102328 | G23: 69.368 | H23: 562 | I23: Energia Licitaciones | J23: Energía | K23: Lic. SIC 2013/03-2 bloques BS1A: Energía feb 2019 | L23: 2019-03-08 00:00:00 | M23: 33 | N23: 7798 | O23: s | P23: s | Q23: BS1A | R23: Caren | S23: Cec | T23: 2013/03-2 | U23: CEC
A24: 01-03-2019 | B24: 01-03-2019 | C24: Licitación Caren y Cec (SIC 2013/03-2) BS1A | D24: 1 | E24: A.JAHUEL 220 | F24: 1311.6233 | G24: 66.9 | H24: 87748 | I24: Energia Licitaciones | J24: Energía | K24: Lic. SIC 2013/03-2 bloques BS1A: Energía mar 2019 | L24: 2019-04-08 00:00:00 | M24: 33 | N24: 8389 | O24: s | P24: s | Q24: BS1A | R24: Caren | S24: Cec | T24: 2013/03-2 | U24: CEC
A25: 01-03-2019 | B25: 01-03-2019 | C25: Licitación Caren y Cec (SIC 2013/03-2) BS1A | D25: 1 | E25: A.JAHUEL 220 | F25: 0.580609 | G25: 66.9 | H25: 39 | I25: Reliq. Energia Licitaciones | J25: Energía | K25: Lic. SIC 2013/03-2 bloques BS1A: Reliq. Energía mar 2019 | L25: 2019-05-13 00:00:00 | M25: 33 | O25: s | P25: s | Q25: BS1A | R25: Caren | S25: Cec | T25: 2013/03-2 | U25: CEC
A26: 01-03-2019 | B26: 01-03-2019 | C26: Licitación Caren y Cec (SIC 2013/03-2) BS1A | D26: 2 | E26: A.MELIP 220 | F26: 8.173697 | G26: 69.014 | H26: 564 | I26: Energia Licitaciones | J26: Energía | K26: Lic. SIC 2013/03-2 bloques BS1A: Energía mar 2019 | L26: 2019-04-08 00:00:00 | M26: 33 | N26: 8389 | O26: s | P26: s | Q26: BS1A | R26: Caren | S26: Cec | T26: 2013/03-2 | U26: CEC
A27: 01-03-2019 | B27: 01-03-2019 | C27: Licitación Caren y Cec (SIC 2013/03-2) BS1A | D27: 3 | E27: CHARRUA 220 | F27: 0.178218 | G27: 63.27 | H27: 11 | I27: Reliq. Energia Licitaciones | J27: Energía | K27: Lic. SIC 2013/03-2 bloques BS1A: Reliq. Energía mar 2019 | L27: 2019-05-13 00:00:00 | M27: 33 | O27: s | P27: s | Q27: BS1A | R27: Caren | S27: Cec | T27: 2013/03-2 | U27: CEC
A28: 01-03-2019 | B28: 01-03-2019 | C28: Licitación Caren y Cec (SIC 2013/03-2) BS1A | D28: 3 | E28: CHARRUA 220 | F28: 402.60399 | G28: 63.27 | H28: 25473 | I28: Energia Licitaciones | J28: Energía | K28: Lic. SIC 2013/03-2 bloques BS1A: Energía mar 2019 | L28: 2019-04-08 00:00:00 | M28: 33 | N28: 8389 | O28: s | P28: s | Q28: BS1A | R28: Caren | S28: Cec | T28: 2013/03-2 | U28: CEC
A29: 01-03-2019 | B29: 01-03-2019 | C29: Licitación Caren y Cec (SIC 2013/03-2) BS1A | D29: 4 | E29: ITAHUE 220 | F29: 1967.9945 | G29: 65.349 | H29: 128606 | I29: Energia Licitaciones | J29: Energía | K29: Lic. SIC 2013/03-2 bloques BS1A: Energía mar 2019 | L29: 2019-04-08 00:00:00 | M29: 33 | N29: 8389 | O29: s | P29: s | Q29: BS1A | R29: Caren | S29: Cec | T29: 2013/03-2 | U29: CEC
A30: 01-03-2019 | B30: 01-03-2019 | C30: Licitación Caren y Cec (SIC 2013/03-2) BS1A | D30: 4 | E30: ITAHUE 220 | F30: 0.87116 | G30: 65.349 | H30: 57 | I30: Reliq. Energia Licitaciones | J30: Energía | K30: Lic. SIC 2013/03-2 bloques BS1A: Reliq. Energía mar 2019 | L30: 2019-05-13 00:00:00 | M30: 33 | O30: s | P30: s | Q30: BS1A | R30: Caren | S30: Cec | T30: 2013/03-2 | U30: CEC
A31: 01-03-2019 | B31: 01-03-2019 | C31: Licitación Caren y Cec (SIC 2013/03-2) BS1A | D31: 5 | E31: RAPEL 220 | F31: 7.514895 | G31: 69.368 | H31: 521 | I31: Energia Licitaciones | J31: Energía | K31: Lic. SIC 2013/03-2 bloques BS1A: Energía mar 2019 | L31: 2019-04-08 00:00:00 | M31: 33 | N31: 8389 | O31: s | P31: s | Q31: BS1A | R31: Caren | S31: Cec | T31: 2013/03-2 | U31: CEC
A32: 01-04-2019 | B32: 01-04-2019 | C32: Licitación Caren y Cec (SIC 2013/03-2) BS1A | D32: 1 | E32: A.JAHUEL 220 | F32: 1 | G32: -1091 | H32: -1091 | I32: Reliq. Energia Licitaciones | J32: Energía | K32: Lic. SIC 2013/03-2 bloques BS1A: Reliq. Energía abr 2019 | L32: 2020-03-23 11:56:36 | M32: 61 | O32: s | P32: s | Q32: BS1A | R32: Caren | S32: Cec | T32: 2013/03-2 | U32: CEC
A33: 01-04-2019 | B33: 01-04-2019 | C33: Licitación Caren y Cec (SIC 2013/03-2) BS1A | D33: 1 | E33: A.JAHUEL 220 | F33: 0 | G33: 0 | H33: 0 | I33: Potencia Licitaciones | J33: Potencia | K33: Lic. SIC 2013/03-2 bloques BS1A: Potencia abr 2019 | L33: 2019-05-13 00:00:00 | M33: 33 | N33: 8451 | O33: s | P33: s | Q33: BS1A | R33: Caren | S33: Cec | T33: 2013/03-2 | U33: CEC
A34: 01-04-2019 | B34: 01-04-2019 | C34: Licitación Caren y Cec (SIC 2013/03-2) BS1A | D34: 1 | E34: A.JAHUEL 220 | F34: 897.9651 | G34: 66.9 | H34: 60074 | I34: Energia Licitaciones | J34: Energía | K34: Lic. SIC 2013/03-2 bloques BS1A: Energía abr 2019 | L34: 2019-05-13 00:00:00 | M34: 33 | N34: 8451 | O34: s | P34: s | Q34: BS1A | R34: Caren | S34: Cec | T34: 2013/03-2 | U34: CEC
A35: 01-04-2019 | B35: 01-04-2019 | C35: Licitación Caren y Cec (SIC 2013/03-2) BS1A | D35: 1 | E35: A.JAHUEL 220 | F35: 0 | G35: 0 | H35: 0 | I35: Ajuste por Armonizacion Tarifaria Licitaciones | J35: AAT | K35: Lic. SIC 2013/03-2 bloques BS1A: AAT abr 2019 | L35: 2019-05-13 00:00:00 | M35: 33 | N35: 8451 | O35: s | P35: s | Q35: BS1A | R35: Caren | S35: Cec | T35: 2013/03-2 | U35: CEC
A36: 01-04-2019 | B36: 01-04-2019 | C36: Licitación Caren y Cec (SIC 2013/03-2) BS1A | D36: 1 | E36: A.JAHUEL 220 | F36: 0 | G36: 0 | H36: 0 | I36: Reactivos Licitaciones | J36: Reactivo | K36: Lic. SIC 2013/03-2 bloques BS1A: Reactivo abr 2019 | L36: 2019-05-13 00:00:00 | M36: 33 | N36: 8451 | O36: s | P36: s | Q36: BS1A | R36: Caren | S36: Cec | T36: 2013/03-2 | U36: CEC
A37: 01-04-2019 | B37: 01-04-2019 | C37: Licitación Caren y Cec (SIC 2013/03-2) BS1A | D37: 2 | E37: A.MELIP 220 | F37: 0 | G37: 0 | H37: 0 | I37: Potencia Licitaciones | J37: Potencia | K37: Lic. SIC 2013/03-2 bloques BS1A: Potencia abr 2019 | L37: 2019-05-13 00:00:00 | M37: 33 | N37: 8451 | O37: s | P37: s | Q37: BS1A | R37: Caren | S37: Cec | T37: 2013/03-2 | U37: CEC
A38: 01-04-2019 | B38: 01-04-2019 | C38: Licitación Caren y Cec (SIC 2013/03-2) BS1A | D38: 2 | E38: A.MELIP 220 | F38: 0 | G38: 0 | H38: 0 | I38: Ajuste por Armonizacion Tarifaria Licitaciones | J38: AAT | K38: Lic. SIC 2013/03-2 bloques BS1A: AAT abr 2019 | L38: 2019-05-13 00:00:00 | M38: 33 | N38: 8451 | O38: s | P38: s | Q38: BS1A | R38: Caren | S38: Cec | T38: 2013/03-2 | U38: CEC
A39: 01-04-2019 | B39: 01-04-2019 | C39: Licitación Caren y Cec (SIC 2013/03-2) BS1A | D39: 2 | E39: A.MELIP 220 | F39: 5.912451 | G39: 69.014 | H39: 408 | I39: Energia Licitaciones | J39: Energía | K39: Lic. SIC 2013/03-2 bloques BS1A: Energía abr 2019 | L39: 2019-05-13 00:00:00 | M39: 33 | N39: 8451 | O39: s | P39: s | Q39: BS1A | R39: Caren | S39: Cec | T39: 2013/03-2 | U39: CEC
A40: 01-04-2019 | B40: 01-04-2019 | C40: Licitación Caren y Cec (SIC 2013/03-2) BS1A | D40: 2 | E40: A.MELIP 220 | F40: 0 | G40: 0 | H40: 0 | I40: Reactivos Licitaciones | J40: Reactivo | K40: Lic. SIC 2013/03-2 bloques BS1A: Reactivo abr 2019 | L40: 2019-05-13 00:00:00 | M40: 33 | N40: 8451 | O40: s | P40: s | Q40: BS1A | R40: Caren | S40: Cec | T40: 2013/03-2 | U40: CEC
A41: 01-04-2019 | B41: 01-04-2019 | C41: Licitación Caren y Cec (SIC 2013/03-2) BS1A | D41: 2 | E41: A.MELIP 220 | F41: 1 | G41: -8 | H41: -8 | I41: Reliq. Energia Licitaciones | J41: Energía | K41: Lic. SIC 2013/03-2 bloques BS1A: Reliq. Energía abr 2019 | L41: 2020-03-23 11:56:36 | M41: 61 | O41: s | P41: s | Q41: BS1A | R41: Caren | S41: Cec | T41: 2013/03-2 | U41: CEC
A42: 01-04-2019 | B42: 01-04-2019 | C42: Licitación Caren y Cec (SIC 2013/03-2) BS1A | D42: 3 | E42: CHARRUA 220 | F42: 278.37089 | G42: 63.27 | H42: 17613 | I42: Energia Licitaciones | J42: Energía | K42: Lic. SIC 2013/03-2 bloques BS1A: Energía abr 2019 | L42: 2019-05-13 00:00:00 | M42: 33 | N42: 8451 | O42: s | P42: s | Q42: BS1A | R42: Caren | S42: Cec | T42: 2013/03-2 | U42: CEC
A43: 01-04-2019 | B43: 01-04-2019 | C43: Licitación Caren y Cec (SIC 2013/03-2) BS1A | D43: 3 | E43: CHARRUA 220 | F43: 0 | G43: 0 | H43: 0 | I43: Ajuste por Armonizacion Tarifaria Licitaciones | J43: AAT | K43: Lic. SIC 2013/03-2 bloques BS1A: AAT abr 2019 | L43: 2019-05-13 00:00:00 | M43: 33 | N43: 8451 | O43: s | P43: s | Q43: BS1A | R43: Caren | S43: Cec | T43: 2013/03-2 | U43: CEC
A44: 01-04-2019 | B44: 01-04-2019 | C44: Licitación Caren y Cec (SIC 2013/03-2) BS1A | D44: 3 | E44: CHARRUA 220 | F44: 1 | G44: -327 | H44: -327 | I44: Reliq. Energia Licitaciones | J44: Energía | K44: Lic. SIC 2013/03-2 bloques BS1A: Reliq. Energía abr 2019 | L44: 2020-03-23 11:56:36 | M44: 61 | O44: s | P44: s | Q44: BS1A | R44: Caren | S44: Cec | T44: 2013/03-2 | U44: CEC
A45: 01-04-2019 | B45: 01-04-2019 | C45: Licitación Caren y Cec (SIC 2013/03-2) BS1A | D45: 3 | E45: CHARRUA 220 | F45: 0 | G45: 0 | H45: 0 | I45: Potencia Licitaciones | J45: Potencia | K45: Lic. SIC 2013/03-2 bloques BS1A: Potencia abr 2019 | L45: 2019-05-13 00:00:00 | M45: 33 | N45: 8451 | O45: s | P45: s | Q45: BS1A | R45: Caren | S45: Cec | T45: 2013/03-2 | U45: CEC
A46: 01-04-2019 | B46: 01-04-2019 | C46: Licitación Caren y Cec (SIC 2013/03-2) BS1A | D46: 3 | E46: CHARRUA 220 | F46: 0 | G46: 0 | H46: 0 | I46: Reactivos Licitaciones | J46: Reactivo | K46: Lic. SIC 2013/03-2 bloques BS1A: Reactivo abr 2019 | L46: 2019-05-13 00:00:00 | M46: 33 | N46: 8451 | O46: s | P46: s | Q46: BS1A | R46: Caren | S46: Cec | T46: 2013/03-2 | U46: CEC
A47: 01-04-2019 | B47: 01-04-2019 | C47: Licitación Caren y Cec (SIC 2013/03-2) BS1A | D47: 4 | E47: ITAHUE 220 | F47: 1 | G47: -1638 | H47: -1638 | I47: Reliq. Energia Licitaciones | J47: Energía | K47: Lic. SIC 2013/03-2 bloques BS1A: Reliq. Energía abr 2019 | L47: 2020-03-23 11:56:36 | M47: 61 | O47: s | P47: s | Q47: BS1A | R47: Caren | S47: Cec | T47: 2013/03-2 | U47: CEC
A48: 01-04-2019 | B48: 01-04-2019 | C48: Licitación Caren y Cec (SIC 2013/03-2) BS1A | D48: 4 | E48: ITAHUE 220 | F48: 0 | G48: 0 | H48: 0 | I48: Ajuste por Armonizacion Tarifaria Licitaciones | J48: AAT | K48: Lic. SIC 2013/03-2 bloques BS1A: AAT abr 2019 | L48: 2019-05-13 00:00:00 | M48: 33 | N48: 8451 | O48: s | P48: s | Q48: BS1A | R48: Caren | S48: Cec | T48: 2013/03-2 | U48: CEC
A49: 01-04-2019 | B49: 01-04-2019 | C49: Licitación Caren y Cec (SIC 2013/03-2) BS1A | D49: 4 | E49: ITAHUE 220 | F49: 1366.2586 | G49: 65.349 | H49: 89284 | I49: Energia Licitaciones | J49: Energía | K49: Lic. SIC 2013/03-2 bloques BS1A: Energía abr 2019 | L49: 2019-05-13 00:00:00 | M49: 33 | N49: 8451 | O49: s | P49: s | Q49: BS1A | R49: Caren | S49: Cec | T49: 2013/03-2 | U49: CEC
A50: 01-04-2019 | B50: 01-04-2019 | C50: Licitación Caren y Cec (SIC 2013/03-2) BS1A | D50: 4 | E50: ITAHUE 220 | F50: 0 | G50: 0 | H50: 0 | I50: Potencia Licitaciones | J50: Potencia | K50: Lic. SIC 2013/03-2 bloques BS1A: Potencia abr 2019 | L50: 2019-05-13 00:00:00 | M50: 33 | N50: 8451 | O50: s | P50: s | Q50: BS1A | R50: Caren | S50: Cec | T50: 2013/03-2 | U50: CEC
A51: 01-04-2019 | B51: 01-04-2019 | C51: Licitación Caren y Cec (SIC 2013/03-2) BS1A | D51: 4 | E51: ITAHUE 220 | F51: 0 | G51: 0 | H51: 0 | I51: Reactivos Licitaciones | J51: Reactivo | K51: Lic. SIC 2013/03-2 bloques BS1A: Reactivo abr 2019 | L51: 2019-05-13 00:00:00 | M51: 33 | N51: 8451 | O51: s | P51: s | Q51: BS1A | R51: Caren | S51: Cec | T51: 2013/03-2 | U51: CEC
A52: 01-04-2019 | B52: 01-04-2019 | C52: Licitación Caren y Cec (SIC 2013/03-2) BS1A | D52: 5 | E52: RAPEL 220 | F52: 0 | G52: 0 | H52: 0 | I52: Potencia Licitaciones | J52: Potencia | K52: Lic. SIC 2013/03-2 bloques BS1A: Potencia abr 2019 | L52: 2019-05-13 00:00:00 | M52: 33 | N52: 8451 | O52: s | P52: s | Q52: BS1A | R52: Caren | S52: Cec | T52: 2013/03-2 | U52: CEC
A53: 01-04-2019 | B53: 01-04-2019 | C53: Licitación Caren y Cec (SIC 2013/03-2) BS1A | D53: 5 | E53: RAPEL 220 | F53: 0 | G53: 0 | H53: 0 | I53: Ajuste por Armonizacion Tarifaria Licitaciones | J53: AAT | K53: Lic. SIC 2013/03-2 bloques BS1A: AAT abr 2019 | L53: 2019-05-13 00:00:00 | M53: 33 | N53: 8451 | O53: s | P53: s | Q53: BS1A | R53: Caren | S53: Cec | T53: 2013/03-2 | U53: CEC
A54: 01-04-2019 | B54: 01-04-2019 | C54: Licitación Caren y Cec (SIC 2013/03-2) BS1A | D54: 5 | E54: RAPEL 220 | F54: 0 | G54: 0 | H54: 0 | I54: Reactivos Licitaciones | J54: Reactivo | K54: Lic. SIC 2013/03-2 bloques BS1A: Reactivo abr 2019 | L54: 2019-05-13 00:00:00 | M54: 33 | N54: 8451 | O54: s | P54: s | Q54: BS1A | R54: Caren | S54: Cec | T54: 2013/03-2 | U54: CEC
A55: 01-04-2019 | B55: 01-04-2019 | C55: Licitación Caren y Cec (SIC 2013/03-2) BS1A | D55: 5 | E55: RAPEL 220 | F55: 1 | G55: -7 | H55: -7 | I55: Reliq. Energia Licitaciones | J55: Energía | K55: Lic. SIC 2013/03-2 bloques BS1A: Reliq. Energía abr 2019 | L55: 2020-03-23 11:56:36 | M55: 61 | O55: s | P55: s | Q55: BS1A | R55: Caren | S55: Cec | T55: 2013/03-2 | U55: CEC
A56: 01-04-2019 | B56: 01-04-2019 | C56: Licitación Caren y Cec (SIC 2013/03-2) BS1A | D56: 5 | E56: RAPEL 220 | F56: 5.432024 | G56: 69.368 | H56: 377 | I56: Energia Licitaciones | J56: Energía | K56: Lic. SIC 2013/03-2 bloques BS1A: Energía abr 2019 | L56: 2019-05-13 00:00:00 | M56: 33 | N56: 8451 | O56: s | P56: s | Q56: BS1A | R56: Caren | S56: Cec | T56: 2013/03-2 | U56: CEC
A57: 01-05-2019 | B57: 01-05-2019 | C57: Licitación Caren y Cec (SIC 2013/03-2) BS1A | D57: 1 | E57: A.JAHUEL 220 | F57: 0 | G57: 0 | H57: 0 | I57: Reactivos Licitaciones | J57: Reactivo | K57: Lic. SIC 2013/03-2 bloques BS1A: Reactivo may 2019 | L57: 2019-06-11 00:00:00 | M57: 33 | N57: 8768 | O57: s | P57: s | Q57: BS1A | R57: Caren | S57: Cec | T57: 2013/03-2 | U57: CEC
A58: 01-05-2019 | B58: 01-05-2019 | C58: Licitación Caren y Cec (SIC 2013/03-2) BS1A | D58: 1 | E58: A.JAHUEL 220 | F58: 1 | G58: -337 | H58: -337 | I58: Reliq. Energia Licitaciones | J58: Energía | K58: Lic. SIC 2013/03-2 bloques BS1A: Reliq. Energía may 2019 | L58: 2020-03-25 15:09:20 | M58: 61 | O58: s | P58: s | Q58: BS1A | R58: Caren | S58: Cec | T58: 2013/03-2 | U58: CEC
A59: 01-05-2019 | B59: 01-05-2019 | C59: Licitación Caren y Cec (SIC 2013/03-2) BS1A | D59: 1 | E59: A.JAHUEL 220 | F59: 0 | G59: 0 | H59: 0 | I59: Potencia Licitaciones | J59: Potencia | K59: Lic. SIC 2013/03-2 bloques BS1A: Potencia may 2019 | L59: 2019-06-11 00:00:00 | M59: 33 | N59: 8768 | O59: s | P59: s | Q59: BS1A | R59: Caren | S59: Cec | T59: 2013/03-2 | U59: CEC
A60: 01-05-2019 | B60: 01-05-2019 | C60: Licitación Caren y Cec (SIC 2013/03-2) BS1A | D60: 1 | E60: A.JAHUEL 220 | F60: 1 | G60: -4 | H60: -4 | I60: Reliq. Ajuste por Armonizacion Tarifaria Licitaciones | J60: AAT | K60: Lic. SIC 2013/03-2 bloques BS1A: Reliq. AAT may 2019 | L60: 2020-03-25 15:09:20 | M60: 61 | O60: s | P60: s | Q60: BS1A | R60: Caren | S60: Cec | T60: 2013/03-2 | U60: CEC
A61: 01-05-2019 | B61: 01-05-2019 | C61: Licitación Caren y Cec (SIC 2013/03-2) BS1A | D61: 1 | E61: A.JAHUEL 220 | F61: 885.88967 | G61: 74.401 | H61: 65911 | I61: Energia Licitaciones | J61: Energía | K61: Lic. SIC 2013/03-2 bloques BS1A: Energía may 2019 | L61: 2019-06-11 00:00:00 | M61: 33 | N61: 8768 | O61: s | P61: s | Q61: BS1A | R61: Caren | S61: Cec | T61: 2013/03-2 | U61: CEC
A62: 01-05-2019 | B62: 01-05-2019 | C62: Licitación Caren y Cec (SIC 2013/03-2) BS1A | D62: 1 | E62: A.JAHUEL 220 | F62: 885.88967 | G62: 1.067 | H62: 945 | I62: Ajuste por Armonizacion Tarifaria Licitaciones | J62: AAT | K62: Lic. SIC 2013/03-2 bloques BS1A: AAT may 2019 | L62: 2019-06-11 00:00:00 | M62: 33 | N62: 8768 | O62: s | P62: s | Q62: BS1A | R62: Caren | S62: Cec | T62: 2013/03-2 | U62: CEC
A63: 01-05-2019 | B63: 01-05-2019 | C63: Licitación Caren y Cec (SIC 2013/03-2) BS1A | D63: 2 | E63: A.MELIP 220 | F63: 0 | G63: 0 | H63: 0 | I63: Reactivos Licitaciones | J63: Reactivo | K63: Lic. SIC 2013/03-2 bloques BS1A: Reactivo may 2019 | L63: 2019-06-11 00:00:00 | M63: 33 | N63: 8768 | O63: s | P63: s | Q63: BS1A | R63: Caren | S63: Cec | T63: 2013/03-2 | U63: CEC
A64: 01-05-2019 | B64: 01-05-2019 | C64: Licitación Caren y Cec (SIC 2013/03-2) BS1A | D64: 2 | E64: A.MELIP 220 | F64: 1 | G64: -2 | H64: -2 | I64: Reliq. Energia Licitaciones | J64: Energía | K64: Lic. SIC 2013/03-2 bloques BS1A: Reliq. Energía may 2019 | L64: 2020-03-25 15:09:20 | M64: 61 | O64: s | P64: s | Q64: BS1A | R64: Caren | S64: Cec | T64: 2013/03-2 | U64: CEC
A65: 01-05-2019 | B65: 01-05-2019 | C65: Licitación Caren y Cec (SIC 2013/03-2) BS1A | D65: 2 | E65: A.MELIP 220 | F65: 5.728447 | G65: 75.737 | H65: 434 | I65: Energia Licitaciones | J65: Energía | K65: Lic. SIC 2013/03-2 bloques BS1A: Energía may 2019 | L65: 2019-06-11 00:00:00 | M65: 33 | N65: 8768 | O65: s | P65: s | Q65: BS1A | R65: Caren | S65: Cec | T65: 2013/03-2 | U65: CEC
A66: 01-05-2019 | B66: 01-05-2019 | C66: Licitación Caren y Cec (SIC 2013/03-2) BS1A | D66: 2 | E66: A.MELIP 220 | F66: 0 | G66: 0 | H66: 0 | I66: Potencia Licitaciones | J66: Potencia | K66: Lic. SIC 2013/03-2 bloques BS1A: Potencia may 2019 | L66: 2019-06-11 00:00:00 | M66: 33 | N66: 8768 | O66: s | P66: s | Q66: BS1A | R66: Caren | S66: Cec | T66: 2013/03-2 | U66: CEC
A67: 01-05-2019 | B67: 01-05-2019 | C67: Licitación Caren y Cec (SIC 2013/03-2) BS1A | D67: 2 | E67: A.MELIP 220 | F67: 5.728447 | G67: 1.067 | H67: 6 | I67: Ajuste por Armonizacion Tarifaria Licitaciones | J67: AAT | K67: Lic. SIC 2013/03-2 bloques BS1A: AAT may 2019 | L67: 2019-06-11 00:00:00 | M67: 33 | N67: 8768 | O67: s | P67: s | Q67: BS1A | R67: Caren | S67: Cec | T67: 2013/03-2 | U67: CEC
A68: 01-05-2019 | B68: 01-05-2019 | C68: Licitación Caren y Cec (SIC 2013/03-2) BS1A | D68: 3 | E68: CHARRUA 220 | F68: 273.81804 | G68: 70.437 | H68: 19287 | I68: Energia Licitaciones | J68: Energía | K68: Lic. SIC 2013/03-2 bloques BS1A: Energía may 2019 | L68: 2019-06-11 00:00:00 | M68: 33 | N68: 8768 | O68: s | P68: s | Q68: BS1A | R68: Caren | S68: Cec | T68: 2013/03-2 | U68: CEC
A69: 01-05-2019 | B69: 01-05-2019 | C69: Licitación Caren y Cec (SIC 2013/03-2) BS1A | D69: 3 | E69: CHARRUA 220 | F69: 0 | G69: 0 | H69: 0 | I69: Potencia Licitaciones | J69: Potencia | K69: Lic. SIC 2013/03-2 bloques BS1A: Potencia may 2019 | L69: 2019-06-11 00:00:00 | M69: 33 | N69: 8768 | O69: s | P69: s | Q69: BS1A | R69: Caren | S69: Cec | T69: 2013/03-2 | U69: CEC
A70: 01-05-2019 | B70: 01-05-2019 | C70: Licitación Caren y Cec (SIC 2013/03-2) BS1A | D70: 3 | E70: CHARRUA 220 | F70: 1 | G70: -1 | H70: -1 | I70: Reliq. Ajuste por Armonizacion Tarifaria Licitaciones | J70: AAT | K70: Lic. SIC 2013/03-2 bloques BS1A: Reliq. AAT may 2019 | L70: 2020-03-25 15:09:20 | M70: 61 | O70: s | P70: s | Q70: BS1A | R70: Caren | S70: Cec | T70: 2013/03-2 | U70: CEC
A71: 01-05-2019 | B71: 01-05-2019 | C71: Licitación Caren y Cec (SIC 2013/03-2) BS1A | D71: 3 | E71: CHARRUA 220 | F71: 0 | G71: 0 | H71: 0 | I71: Reactivos Licitaciones | J71: Reactivo | K71: Lic. SIC 2013/03-2 bloques BS1A: Reactivo may 2019 | L71: 2019-06-11 00:00:00 | M71: 33 | N71: 8768 | O71: s | P71: s | Q71: BS1A | R71: Caren | S71: Cec | T71: 2013/03-2 | U71: CEC
A72: 01-05-2019 | B72: 01-05-2019 | C72: Licitación Caren y Cec (SIC 2013/03-2) BS1A | D72: 3 | E72: CHARRUA 220 | F72: 273.81804 | G72: 1.067 | H72: 292 | I72: Ajuste por Armonizacion Tarifaria Licitaciones | J72: AAT | K72: Lic. SIC 2013/03-2 bloques BS1A: AAT may 2019 | L72: 2019-06-11 00:00:00 | M72: 33 | N72: 8768 | O72: s | P72: s | Q72: BS1A | R72: Caren | S72: Cec | T72: 2013/03-2 | U72: CEC
A73: 01-05-2019 | B73: 01-05-2019 | C73: Licitación Caren y Cec (SIC 2013/03-2) BS1A | D73: 3 | E73: CHARRUA 220 | F73: 1 | G73: -99 | H73: -99 | I73: Reliq. Energia Licitaciones | J73: Energía | K73: Lic. SIC 2013/03-2 bloques BS1A: Reliq. Energía may 2019 | L73: 2020-03-25 15:09:20 | M73: 61 | O73: s | P73: s | Q73: BS1A | R73: Caren | S73: Cec | T73: 2013/03-2 | U73: CEC
A74: 01-05-2019 | B74: 01-05-2019 | C74: Licitación Caren y Cec (SIC 2013/03-2) BS1A | D74: 4 | E74: ITAHUE 220 | F74: 1 | G74: -8 | H74: -8 | I74: Reliq. Ajuste por Armonizacion Tarifaria Licitaciones | J74: AAT | K74: Lic. SIC 2013/03-2 bloques BS1A: Reliq. AAT may 2019 | L74: 2020-03-25 15:09:20 | M74: 61 | O74: s | P74: s | Q74: BS1A | R74: Caren | S74: Cec | T74: 2013/03-2 | U74: CEC
A75: 01-05-2019 | B75: 01-05-2019 | C75: Licitación Caren y Cec (SIC 2013/03-2) BS1A | D75: 4 | E75: ITAHUE 220 | F75: 1 | G75: -494 | H75: -494 | I75: Reliq. Energia Licitaciones | J75: Energía | K75: Lic. SIC 2013/03-2 bloques BS1A: Reliq. Energía may 2019 | L75: 2020-03-25 15:09:20 | M75: 61 | O75: s | P75: s | Q75: BS1A | R75: Caren | S75: Cec | T75: 2013/03-2 | U75: CEC
A76: 01-05-2019 | B76: 01-05-2019 | C76: Licitación Caren y Cec (SIC 2013/03-2) BS1A | D76: 4 | E76: ITAHUE 220 | F76: 0 | G76: 0 | H76: 0 | I76: Potencia Licitaciones | J76: Potencia | K76: Lic. SIC 2013/03-2 bloques BS1A: Potencia may 2019 | L76: 2019-06-11 00:00:00 | M76: 33 | N76: 8768 | O76: s | P76: s | Q76: BS1A | R76: Caren | S76: Cec | T76: 2013/03-2 | U76: CEC
A77: 01-05-2019 | B77: 01-05-2019 | C77: Licitación Caren y Cec (SIC 2013/03-2) BS1A | D77: 4 | E77: ITAHUE 220 | F77: 0 | G77: 0 | H77: 0 | I77: Reactivos Licitaciones | J77: Reactivo | K77: Lic. SIC 2013/03-2 bloques BS1A: Reactivo may 2019 | L77: 2019-06-11 00:00:00 | M77: 33 | N77: 8768 | O77: s | P77: s | Q77: BS1A | R77: Caren | S77: Cec | T77: 2013/03-2 | U77: CEC
A78: 01-05-2019 | B78: 01-05-2019 | C78: Licitación Caren y Cec (SIC 2013/03-2) BS1A | D78: 4 | E78: ITAHUE 220 | F78: 1341.7257 | G78: 1.067 | H78: 1432 | I78: Ajuste por Armonizacion Tarifaria Licitaciones | J78: AAT | K78: Lic. SIC 2013/03-2 bloques BS1A: AAT may 2019 | L78: 2019-06-11 00:00:00 | M78: 33 | N78: 8768 | O78: s | P78: s | Q78: BS1A | R78: Caren | S78: Cec | T78: 2013/03-2 | U78: CEC
A79: 01-05-2019 | B79: 01-05-2019 | C79: Licitación Caren y Cec (SIC 2013/03-2) BS1A | D79: 4 | E79: ITAHUE 220 | F79: 1341.7257 | G79: 71.984 | H79: 96583 | I79: Energia Licitaciones | J79: Energía | K79: Lic. SIC 2013/03-2 bloques BS1A: Energía may 2019 | L79: 2019-06-11 00:00:00 | M79: 33 | N79: 8768 | O79: s | P79: s | Q79: BS1A | R79: Caren | S79: Cec | T79: 2013/03-2 | U79: CEC
A80: 01-05-2019 | B80: 01-05-2019 | C80: Licitación Caren y Cec (SIC 2013/03-2) BS1A | D80: 5 | E80: RAPEL 220 | F80: 1 | G80: -2 | H80: -2 | I80: Reliq. Energia Licitaciones | J80: Energía | K80: Lic. SIC 2013/03-2 bloques BS1A: Reliq. Energía may 2019 | L80: 2020-03-25 15:09:20 | M80: 61 | O80: s | P80: s | Q80: BS1A | R80: Caren | S80: Cec | T80: 2013/03-2 | U80: CEC
A81: 01-05-2019 | B81: 01-05-2019 | C81: Licitación Caren y Cec (SIC 2013/03-2) BS1A | D81: 5 | E81: RAPEL 220 | F81: 0 | G81: 0 | H81: 0 | I81: Potencia Licitaciones | J81: Potencia | K81: Lic. SIC 2013/03-2 bloques BS1A: Potencia may 2019 | L81: 2019-06-11 00:00:00 | M81: 33 | N81: 8768 | O81: s | P81: s | Q81: BS1A | R81: Caren | S81: Cec | T81: 2013/03-2 | U81: CEC
A82: 01-05-2019 | B82: 01-05-2019 | C82: Licitación Caren y Cec (SIC 2013/03-2) BS1A | D82: 5 | E82: RAPEL 220 | F82: 0 | G82: 0 | H82: 0 | I82: Reactivos Licitaciones | J82: Reactivo | K82: Lic. SIC 2013/03-2 bloques BS1A: Reactivo may 2019 | L82: 2019-06-11 00:00:00 | M82: 33 | N82: 8768 | O82: s | P82: s | Q82: BS1A | R82: Caren | S82: Cec | T82: 2013/03-2 | U82: CEC
A83: 01-05-2019 | B83: 01-05-2019 | C83: Licitación Caren y Cec (SIC 2013/03-2) BS1A | D83: 5 | E83: RAPEL 220 | F83: 5.26453 | G83: 1.067 | H83: 6 | I83: Ajuste por Armonizacion Tarifaria Licitaciones | J83: AAT | K83: Lic. SIC 2013/03-2 bloques BS1A: AAT may 2019 | L83: 2019-06-11 00:00:00 | M83: 33 | N83: 8768 | O83: s | P83: s | Q83: BS1A | R83: Caren | S83: Cec | T83: 2013/03-2 | U83: CEC
A84: 01-05-2019 | B84: 01-05-2019 | C84: Licitación Caren y Cec (SIC 2013/03-2) BS1A | D84: 5 | E84: RAPEL 220 | F84: 5.26453 | G84: 75.617 | H84: 398 | I84: Energia Licitaciones | J84: Energía | K84: Lic. SIC 2013/03-2 bloques BS1A: Energía may 2019 | L84: 2019-06-11 00:00:00 | M84: 33 | N84: 8768 | O84: s | P84: s | Q84: BS1A | R84: Caren | S84: Cec | T84: 2013/03-2 | U84: CEC
A85: 01-06-2019 | B85: 01-06-2019 | C85: Licitación Caren y Cec (SIC 2013/03-2) BS1A | D85: 1 | E85: A.JAHUEL 220 | F85: 0 | G85: 0 | H85: 0 | I85: Potencia Licitaciones | J85: Potencia | K85: Lic. SIC 2013/03-2 bloques BS1A: Potencia jun 2019 | L85: 2019-07-09 00:00:00 | M85: 33 | N85: 9022 | O85: s | P85: s | Q85: BS1A | R85: Caren | S85: Cec | T85: 2013/03-2 | U85: CEC
A86: 01-06-2019 | B86: 01-06-2019 | C86: Licitación Caren y Cec (SIC 2013/03-2) BS1A | D86: 1 | E86: A.JAHUEL 220 | F86: 1.775945 | G86: 74.401 | H86: 132 | I86: Reliq. Energia Licitaciones | J86: Energía | K86: Lic. SIC 2013/03-2 bloques BS1A: Reliq. Energía jun 2019 | L86: 2019-08-16 00:00:00 | M86: 33 | O86: s | P86: s | Q86: BS1A | R86: Caren | S86: Cec | T86: 2013/03-2 | U86: CEC
A87: 01-06-2019 | B87: 01-06-2019 | C87: Licitación Caren y Cec (SIC 2013/03-2) BS1A | D87: 1 | E87: A.JAHUEL 220 | F87: 0 | G87: 0 | H87: 0 | I87: Reactivos Licitaciones | J87: Reactivo | K87: Lic. SIC 2013/03-2 bloques BS1A: Reactivo jun 2019 | L87: 2019-07-09 00:00:00 | M87: 33 | N87: 9022 | O87: s | P87: s | Q87: BS1A | R87: Caren | S87: Cec | T87: 2013/03-2 | U87: CEC
A88: 01-06-2019 | B88: 01-06-2019 | C88: Licitación Caren y Cec (SIC 2013/03-2) BS1A | D88: 1 | E88: A.JAHUEL 220 | F88: 790.40863 | G88: 74.401 | H88: 58807 | I88: Energia Licitaciones | J88: Energía | K88: Lic. SIC 2013/03-2 bloques BS1A: Energía jun 2019 | L88: 2019-07-09 00:00:00 | M88: 33 | N88: 9022 | O88: s | P88: s | Q88: BS1A | R88: Caren | S88: Cec | T88: 2013/03-2 | U88: CEC
A89: 01-06-2019 | B89: 01-06-2019 | C89: Licitación Caren y Cec (SIC 2013/03-2) BS1A | D89: 1 | E89: A.JAHUEL 220 | F89: 1.775945 | G89: 1.067 | H89: 2 | I89: Reliq. Ajuste por Armonizacion Tarifaria Licitaciones | J89: AAT | K89: Lic. SIC 2013/03-2 bloques BS1A: Reliq. AAT jun 2019 | L89: 2019-08-16 00:00:00 | M89: 33 | O89: s | P89: s | Q89: BS1A | R89: Caren | S89: Cec | T89: 2013/03-2 | U89: CEC
A90: 01-06-2019 | B90: 01-06-2019 | C90: Licitación Caren y Cec (SIC 2013/03-2) BS1A | D90: 1 | E90: A.JAHUEL 220 | F90: 790.40863 | G90: 1.067 | H90: 843 | I90: Ajuste por Armonizacion Tarifaria Licitaciones | J90: AAT | K90: Lic. SIC 2013/03-2 bloques BS1A: AAT jun 2019 | L90: 2019-07-09 00:00:00 | M90: 33 | N90: 9022 | O90: s | P90: s | Q90: BS1A | R90: Caren | S90: Cec | T90: 2013/03-2 | U90: CEC
A91: 01-06-2019 | B91: 01-06-2019 | C91: Licitación Caren y Cec (SIC 2013/03-2) BS1A | D91: 2 | E91: A.MELIP 220 | F91: 0 | G91: 0 | H91: 0 | I91: Reactivos Licitaciones | J91: Reactivo | K91: Lic. SIC 2013/03-2 bloques BS1A: Reactivo jun 2019 | L91: 2019-07-09 00:00:00 | M91: 33 | N91: 9022 | O91: s | P91: s | Q91: BS1A | R91: Caren | S91: Cec | T91: 2013/03-2 | U91: CEC
A92: 01-06-2019 | B92: 01-06-2019 | C92: Licitación Caren y Cec (SIC 2013/03-2) BS1A | D92: 2 | E92: A.MELIP 220 | F92: 0.011666 | G92: 75.737 | H92: 1 | I92: Reliq. Energia Licitaciones | J92: Energía | K92: Lic. SIC 2013/03-2 bloques BS1A: Reliq. Energía jun 2019 | L92: 2019-08-16 00:00:00 | M92: 33 | O92: s | P92: s | Q92: BS1A | R92: Caren | S92: Cec | T92: 2013/03-2 | U92: CEC
A93: 01-06-2019 | B93: 01-06-2019 | C93: Licitación Caren y Cec (SIC 2013/03-2) BS1A | D93: 2 | E93: A.MELIP 220 | F93: 0 | G93: 0 | H93: 0 | I93: Potencia Licitaciones | J93: Potencia | K93: Lic. SIC 2013/03-2 bloques BS1A: Potencia jun 2019 | L93: 2019-07-09 00:00:00 | M93: 33 | N93: 9022 | O93: s | P93: s | Q93: BS1A | R93: Caren | S93: Cec | T93: 2013/03-2 | U93: CEC
A94: 01-06-2019 | B94: 01-06-2019 | C94: Licitación Caren y Cec (SIC 2013/03-2) BS1A | D94: 2 | E94: A.MELIP 220 | F94: 5.19207 | G94: 1.067 | H94: 6 | I94: Ajuste por Armonizacion Tarifaria Licitaciones | J94: AAT | K94: Lic. SIC 2013/03-2 bloques BS1A: AAT jun 2019 | L94: 2019-07-09 00:00:00 | M94: 33 | N94: 9022 | O94: s | P94: s | Q94: BS1A | R94: Caren | S94: Cec | T94: 2013/03-2 | U94: CEC
A95: 01-06-2019 | B95: 01-06-2019 | C95: Licitación Caren y Cec (SIC 2013/03-2) BS1A | D95: 2 | E95: A.MELIP 220 | F95: 5.19207 | G95: 75.737 | H95: 393 | I95: Energia Licitaciones | J95: Energía | K95: Lic. SIC 2013/03-2 bloques BS1A: Energía jun 2019 | L95: 2019-07-09 00:00:00 | M95: 33 | N95: 9022 | O95: s | P95: s | Q95: BS1A | R95: Caren | S95: Cec | T95: 2013/03-2 | U95: CEC
A96: 01-06-2019 | B96: 01-06-2019 | C96: Licitación Caren y Cec (SIC 2013/03-2) BS1A | D96: 3 | E96: CHARRUA 220 | F96: 0.551932 | G96: 1.067 | H96: 1 | I96: Reliq. Ajuste por Armonizacion Tarifaria Licitaciones | J96: AAT | K96: Lic. SIC 2013/03-2 bloques BS1A: Reliq. AAT jun 2019 | L96: 2019-08-16 00:00:00 | M96: 33 | O96: s | P96: s | Q96: BS1A | R96: Caren | S96: Cec | T96: 2013/03-2 | U96: CEC
A97: 01-06-2019 | B97: 01-06-2019 | C97: Licitación Caren y Cec (SIC 2013/03-2) BS1A | D97: 3 | E97: CHARRUA 220 | F97: 0 | G97: 0 | H97: 0 | I97: Reactivos Licitaciones | J97: Reactivo | K97: Lic. SIC 2013/03-2 bloques BS1A: Reactivo jun 2019 | L97: 2019-07-09 00:00:00 | M97: 33 | N97: 9022 | O97: s | P97: s | Q97: BS1A | R97: Caren | S97: Cec | T97: 2013/03-2 | U97: CEC
A98: 01-06-2019 | B98: 01-06-2019 | C98: Licitación Caren y Cec (SIC 2013/03-2) BS1A | D98: 3 | E98: CHARRUA 220 | F98: 245.64498 | G98: 1.067 | H98: 262 | I98: Ajuste por Armonizacion Tarifaria Licitaciones | J98: AAT | K98: Lic. SIC 2013/03-2 bloques BS1A: AAT jun 2019 | L98: 2019-07-09 00:00:00 | M98: 33 | N98: 9022 | O98: s | P98: s | Q98: BS1A | R98: Caren | S98: Cec | T98: 2013/03-2 | U98: CEC
A99: 01-06-2019 | B99: 01-06-2019 | C99: Licitación Caren y Cec (SIC 2013/03-2) BS1A | D99: 3 | E99: CHARRUA 220 | F99: 0 | G99: 0 | H99: 0 | I99: Potencia Licitaciones | J99: Potencia | K99: Lic. SIC 2013/03-2 bloques BS1A: Potencia jun 2019 | L99: 2019-07-09 00:00:00 | M99: 33 | N99: 9022 | O99: s | P99: s | Q99: BS1A | R99: Caren | S99: Cec | T99: 2013/03-2 | U99: CEC
A100: 01-06-2019 | B100: 01-06-2019 | C100: Licitación Caren y Cec (SIC 2013/03-2) BS1A | D100: 3 | E100: CHARRUA 220 | F100: 245.64498 | G100: 70.437 | H100: 17302 | I100: Energia Licitaciones | J100: Energía | K100: Lic. SIC 2013/03-2 bloques BS1A: Energía jun 2019 | L100: 2019-07-09 00:00:00 | M100: 33 | N100: 9022 | O100: s | P100: s | Q100: BS1A | R100: Caren | S100: Cec | T100: 2013/03-2 | U100: CEC
...

Sheet SIGGE_E
A1: Periodo | B1: MesDevengado | C1: Nombre | D1: Num | E1: Barra | F1: Cantidad | G1: Precio | H1: Monto | I1: Concepto | J1: Agrupacion | K1: Glosa | L1: FechaCarga | M1: TipoDocumento | N1: Folio | O1: Vendedor | P1: Comprador | Q1: Bloque | R1: Empresa | S1: ClaveEEDD | T1: Licitacion | U1: NomAgrupacion
A2: 01-09-2018 | B2: 01-09-2018 | C2: Licitación Caren y Cec (SIC 2013/03-2) BS1A | D2: 1 | E2: TotalBarras | F2: 3000 | G2: 58.085 | H2: 174255 | I2: Energia Licitaciones | J2: Energía | K2: Lic. SIC 2013/03-2 bloques BS1A: Energía sep 2018 | L2: 2018-10-19 00:00:00 | M2: 33 | N2: 6305 | O2: s | P2: s | Q2: BS1A | R2: Caren | S2: Cec | T2: 2013/03-2 | U2: CEC
A3: 01-10-2018 | B3: 01-10-2018 | C3: Licitación Caren y Cec (SIC 2013/03-2) BS1A | D3: 1 | E3: TotalBarras | F3: 3000 | G3: 59.678 | H3: 179035 | I3: Energia Licitaciones | J3: Energía | K3: Lic. SIC 2013/03-2 bloques BS1A: Energía oct 2018 | L3: 2018-11-27 00:00:00 | M3: 33 | N3: 6796 | O3: s | P3: s | Q3: BS1A | R3: Caren | S3: Cec | T3: 2013/03-2 | U3: CEC
A4: 01-11-2018 | B4: 01-11-2018 | C4: Licitación Caren y Cec (SIC 2013/03-2) BS1A | D4: 1 | E4: TotalBarras | F4: 4000 | G4: 59.635 | H4: 238540 | I4: Energia Licitaciones | J4: Energía | K4: Lic. SIC 2013/03-2 bloques BS1A: Energía nov 2018 | L4: 2018-12-14 00:00:00 | M4: 33 | N4: 6939 | O4: s | P4: s | Q4: BS1A | R4: Caren | S4: Cec | T4: 2013/03-2 | U4: CEC
A5: 01-12-2018 | B5: 01-12-2018 | C5: Licitación Caren y Cec (SIC 2013/03-2) BS1A | D5: 1 | E5: TotalBarras | F5: 5000 | G5: 67.951 | H5: 339757 | I5: Energia Licitaciones | J5: Energía | K5: Lic. SIC 2013/03-2 bloques BS1A: Energía dic 2018 | L5: 2019-01-21 00:00:00 | M5: 33 | N5: 7194 | O5: s | P5: s | Q5: BS1A | R5: Caren | S5: Cec | T5: 2013/03-2 | U5: CEC
A6: 01-01-2019 | B6: 01-01-2019 | C6: Licitación Caren y Cec (SIC 2013/03-2) BS1A | D6: 1 | E6: A.JAHUEL 220 | F6: 1.46188 | G6: 66.9 | H6: 98 | I6: Reliq. Energia Licitaciones | J6: Energía | K6: Lic. SIC 2013/03-2 bloques BS1A: Reliq. Energía ene 2019 | L6: 2019-03-15 00:00:00 | M6: 33 | O6: s | P6: s | Q6: BS1A | R6: Caren | S6: Cec | T6: 2013/03-2 | U6: CEC
A7: 01-01-2019 | B7: 01-01-2019 | C7: Licitación Caren y Cec (SIC 2013/03-2) BS1A | D7: 1 | E7: A.JAHUEL 220 | F7: 1371.306 | G7: 66.9 | H7: 91740 | I7: Energia Licitaciones | J7: Energía | K7: Lic. SIC 2013/03-2 bloques BS1A: Energía ene 2019 | L7: 2019-02-08 00:00:00 | M7: 33 | N7: 7513 | O7: s | P7: s | Q7: BS1A | R7: Caren | S7: Cec | T7: 2013/03-2 | U7: CEC
A8: 01-01-2019 | B8: 01-01-2019 | C8: Licitación Caren y Cec (SIC 2013/03-2) BS1A | D8: 2 | E8: A.MELIP 220 | F8: 0.009388 | G8: 69.014 | H8: 1 | I8: Reliq. Energia Licitaciones | J8: Energía | K8: Lic. SIC 2013/03-2 bloques BS1A: Reliq. Energía ene 2019 | L8: 2019-03-15 00:00:00 | M8: 33 | O8: s | P8: s | Q8: BS1A | R8: Caren | S8: Cec | T8: 2013/03-2 | U8: CEC
A9: 01-01-2019 | B9: 01-01-2019 | C9: Licitación Caren y Cec (SIC 2013/03-2) BS1A | D9: 2 | E9: A.MELIP 220 | F9: 8.806166 | G9: 69.014 | H9: 608 | I9: Energia Licitaciones | J9: Energía | K9: Lic. SIC 2013/03-2 bloques BS1A: Energía ene 2019 | L9: 2019-02-08 00:00:00 | M9: 33 | N9: 7513 | O9: s | P9: s | Q9: BS1A | R9: Caren | S9: Cec | T9: 2013/03-2 | U9: CEC
A10: 01-01-2019 | B10: 01-01-2019 | C10: Licitación Caren y Cec (SIC 2013/03-2) BS1A | D10: 3 | E10: CHARRUA 220 | F10: 0.453721 | G10: 63.27 | H10: 29 | I10: Reliq. Energia Licitaciones | J10: Energía | K10: Lic. SIC 2013/03-2 bloques BS1A: Reliq. Energía ene 2019 | L10: 2019-03-15 00:00:00 | M10: 33 | O10: s | P10: s | Q10: BS1A | R10: Caren | S10: Cec | T10: 2013/03-2 | U10: CEC
A11: 01-01-2019 | B11: 01-01-2019 | C11: Licitación Caren y Cec (SIC 2013/03-2) BS1A | D11: 3 | E11: CHARRUA 220 | F11: 425.60961 | G11: 63.27 | H11: 26928 | I11: Energia Licitaciones | J11: Energía | K11: Lic. SIC 2013/03-2 bloques BS1A: Energía ene 2019 | L11: 2019-02-08 00:00:00 | M11: 33 | N11: 7513 | O11: s | P11: s | Q11: BS1A | R11: Caren | S11: Cec | T11: 2013/03-2 | U11: CEC
A12: 01-01-2019 | B12: 01-01-2019 | C12: Licitación Caren y Cec (SIC 2013/03-2) BS1A | D12: 4 | E12: ITAHUE 220 | F12: 2.212452 | G12: 65.349 | H12: 145 | I12: Reliq. Energia Licitaciones | J12: Energía | K12: Lic. SIC 2013/03-2 bloques BS1A: Reliq. Energía ene 2019 | L12: 2019-03-15 00:00:00 | M12: 33 | O12: s | P12: s | Q12: BS1A | R12: Caren | S12: Cec | T12: 2013/03-2 | U12: CEC
A13: 01-01-2019 | B13: 01-01-2019 | C13: Licitación Caren y Cec (SIC 2013/03-2) BS1A | D13: 4 | E13: ITAHUE 220 | F13: 2075.374 | G13: 65.349 | H13: 135624 | I13: Energia Licitaciones | J13: Energía | K13: Lic. SIC 2013/03-2 bloques BS1A: Energía ene 2019 | L13: 2019-02-08 00:00:00 | M13: 33 | N13: 7513 | O13: s | P13: s | Q13: BS1A | R13: Caren | S13: Cec | T13: 2013/03-2 | U13: CEC
A14: 01-01-2019 | B14: 01-01-2019 | C14: Licitación Caren y Cec (SIC 2013/03-2) BS1A | D14: 5 | E14: RAPEL 220 | F14: 8.102057 | G14: 69.368 | H14: 562 | I14: Energia Licitaciones | J14: Energía | K14: Lic. SIC 2013/03-2 bloques BS1A: Energía ene 2019 | L14: 2019-02-08 00:00:00 | M14: 33 | N14: 7513 | O14: s | P14: s | Q14: BS1A | R14: Caren | S14: Cec | T14: 2013/03-2 | U14: CEC
A15: 01-01-2019 | B15: 01-01-2019 | C15: Licitación Caren y Cec (SIC 2013/03-2) BS1A | D15: 5 | E15: RAPEL 220 | F15: 0.008637 | G15: 69.368 | H15: 1 | I15: Reliq. Energia Licitaciones | J15: Energía | K15: Lic. SIC 2013/03-2 bloques BS1A: Reliq. Energía ene 2019 | L15: 2019-03-15 00:00:00 | M15: 33 | O15: s | P15: s | Q15: BS1A | R15: Caren | S15: Cec | T15: 2013/03-2 | U15: CEC
A16: 01-02-2019 | B16: 01-02-2019 | C16: Licitación Caren y Cec (SIC 2013/03-2) BS1A | D16: 1 | E16: A.JAHUEL 220 | F16: 1368.5299 | G16: 66.9 | H16: 91555 | I16: Energia Licitaciones | J16: Energía | K16: Lic. SIC 2013/03-2 bloques BS1A: Energía feb 2019 | L16: 2019-03-08 00:00:00 | M16: 33 | N16: 7798 | O16: s | P16: s | Q16: BS1A | R16: Caren | S16: Cec | T16: 2013/03-2 | U16: CEC
A17: 01-02-2019 | B17: 01-02-2019 | C17: Licitación Caren y Cec (SIC 2013/03-2) BS1A | D17: 1 | E17: A.JAHUEL 220 | F17: 0.23349 | G17: 66.9 | H17: 16 | I17: Reliq. Energia Licitaciones | J17: Energía | K17: Lic. SIC 2013/03-2 bloques BS1A: Reliq. Energía feb 2019 | L17: 2019-04-09 00:00:00 | M17: 61 | O17: s | P17: s | Q17: BS1A | R17: Caren | S17: Cec | T17: 2013/03-2 | U17: CEC
A18: 01-02-2019 | B18: 01-02-2019 | C18: Licitación Caren y Cec (SIC 2013/03-2) BS1A | D18: 2 | E18: A.MELIP 220 | F18: 8.816632 | G18: 69.014 | H18: 608 | I18: Energia Licitaciones | J18: Energía | K18: Lic. SIC 2013/03-2 bloques BS1A: Energía feb 2019 | L18: 2019-03-08 00:00:00 | M18: 33 | N18: 7798 | O18: s | P18: s | Q18: BS1A | R18: Caren | S18: Cec | T18: 2013/03-2 | U18: CEC
A19: 01-02-2019 | B19: 01-02-2019 | C19: Licitación Caren y Cec (SIC 2013/03-2) BS1A | D19: 3 | E19: CHARRUA 220 | F19: 422.52678 | G19: 63.27 | H19: 26733 | I19: Energia Licitaciones | J19: Energía | K19: Lic. SIC 2013/03-2 bloques BS1A: Energía feb 2019 | L19: 2019-03-08 00:00:00 | M19: 33 | N19: 7798 | O19: s | P19: s | Q19: BS1A | R19: Caren | S19: Cec | T19: 2013/03-2 | U19: CEC
A20: 01-02-2019 | B20: 01-02-2019 | C20: Licitación Caren y Cec (SIC 2013/03-2) BS1A | D20: 3 | E20: CHARRUA 220 | F20: 0.072089 | G20: 63.27 | H20: 5 | I20: Reliq. Energia Licitaciones | J20: Energía | K20: Lic. SIC 2013/03-2 bloques BS1A: Reliq. Energía feb 2019 | L20: 2019-04-09 00:00:00 | M20: 61 | O20: s | P20: s | Q20: BS1A | R20: Caren | S20: Cec | T20: 2013/03-2 | U20: CEC
A21: 01-02-2019 | B21: 01-02-2019 | C21: Licitación Caren y Cec (SIC 2013/03-2) BS1A | D21: 4 | E21: ITAHUE 220 | F21: 0.353269 | G21: 65.349 | H21: 23 | I21: Reliq. Energia Licitaciones | J21: Energía | K21: Lic. SIC 2013/03-2 bloques BS1A: Reliq. Energía feb 2019 | L21: 2019-04-09 00:00:00 | M21: 61 | O21: s | P21: s | Q21: BS1A | R21: Caren | S21: Cec | T21: 2013/03-2 | U21: CEC
A22: 01-02-2019 | B22: 01-02-2019 | C22: Licitación Caren y Cec (SIC 2013/03-2) BS1A | D22: 4 | E22: ITAHUE 220 | F22: 2070.5801 | G22: 65.349 | H22: 135310 | I22: Energia Licitaciones | J22: Energía | K22: Lic. SIC 2013/03-2 bloques BS1A: Energía feb 2019 | L22: 2019-03-08 00:00:00 | M22: 33 | N22: 7798 | O22: s | P22: s | Q22: BS1A | R22: Caren | S22: Cec | T22: 2013/03-2 | U22: CEC
A23: 01-02-2019 | B23: 01-02-2019 | C23: Licitación Caren y Cec (SIC 2013/03-2) BS1A | D23: 5 | E23: RAPEL 220 | F23: 8.102328 | G23: 69.368 | H23: 562 | I23: Energia Licitaciones | J23: Energía | K23: Lic. SIC 2013/03-2 bloques BS1A: Energía feb 2019 | L23: 2019-03-08 00:00:00 | M23: 33 | N23: 7798 | O23: s | P23: s | Q23: BS1A | R23: Caren | S23: Cec | T23: 2013/03-2 | U23: CEC
A24: 01-03-2019 | B24: 01-03-2019 | C24: Licitación Caren y Cec (SIC 2013/03-2) BS1A | D24: 1 | E24: A.JAHUEL 220 | F24: 1311.6233 | G24: 66.9 | H24: 87748 | I24: Energia Licitaciones | J24: Energía | K24: Lic. SIC 2013/03-2 bloques BS1A: Energía mar 2019 | L24: 2019-04-08 00:00:00 | M24: 33 | N24: 8389 | O24: s | P24: s | Q24: BS1A | R24: Caren | S24: Cec | T24: 2013/03-2 | U24: CEC
A25: 01-03-2019 | B25: 01-03-2019 | C25: Licitación Caren y Cec (SIC 2013/03-2) BS1A | D25: 1 | E25: A.JAHUEL 220 | F25: 0.580609 | G25: 66.9 | H25: 39 | I25: Reliq. Energia Licitaciones | J25: Energía | K25: Lic. SIC 2013/03-2 bloques BS1A: Reliq. Energía mar 2019 | L25: 2019-05-13 00:00:00 | M25: 33 | O25: s | P25: s | Q25: BS1A | R25: Caren | S25: Cec | T25: 2013/03-2 | U25: CEC
A26: 01-03-2019 | B26: 01-03-2019 | C26: Licitación Caren y Cec (SIC 2013/03-2) BS1A | D26: 2 | E26: A.MELIP 220 | F26: 8.173697 | G26: 69.014 | H26: 564 | I26: Energia Licitaciones | J26: Energía | K26: Lic. SIC 2013/03-2 bloques BS1A: Energía mar 2019 | L26: 2019-04-08 00:00:00 | M26: 33 | N26: 8389 | O26: s | P26: s | Q26: BS1A | R26: Caren | S26: Cec | T26: 2013/03-2 | U26: CEC
A27: 01-03-2019 | B27: 01-03-2019 | C27: Licitación Caren y Cec (SIC 2013/03-2) BS1A | D27: 3 | E27: CHARRUA 220 | F27: 0.178218 | G27: 63.27 | H27: 11 | I27: Reliq. Energia Licitaciones | J27: Energía | K27: Lic. SIC 2013/03-2 bloques BS1A: Reliq. Energía mar 2019 | L27: 2019-05-13 00:00:00 | M27: 33 | O27: s | P27: s | Q27: BS1A | R27: Caren | S27: Cec | T27: 2013/03-2 | U27: CEC
A28: 01-03-2019 | B28: 01-03-2019 | C28: Licitación Caren y Cec (SIC 2013/03-2) BS1A | D28: 3 | E28: CHARRUA 220 | F28: 402.60399 | G28: 63.27 | H28: 25473 | I28: Energia Licitaciones | J28: Energía | K28: Lic. SIC 2013/03-2 bloques BS1A: Energía mar 2019 | L28: 2019-04-08 00:00:00 | M28: 33 | N28: 8389 | O28: s | P28: s | Q28: BS1A | R28: Caren | S28: Cec | T28: 2013/03-2 | U28: CEC
A29: 01-03-2019 | B29: 01-03-2019 | C29: Licitación Caren y Cec (SIC 2013/03-2) BS1A | D29: 4 | E29: ITAHUE 220 | F29: 1967.9945 | G29: 65.349 | H29: 128606 | I29: Energia Licitaciones | J29: Energía | K29: Lic. SIC 2013/03-2 bloques BS1A: Energía mar 2019 | L29: 2019-04-08 00:00:00 | M29: 33 | N29: 8389 | O29: s | P29: s | Q29: BS1A | R29: Caren | S29: Cec | T29: 2013/03-2 | U29: CEC
A30: 01-03-2019 | B30: 01-03-2019 | C30: Licitación Caren y Cec (SIC 2013/03-2) BS1A | D30: 4 | E30: ITAHUE 220 | F30: 0.87116 | G30: 65.349 | H30: 57 | I30: Reliq. Energia Licitaciones | J30: Energía | K30: Lic. SIC 2013/03-2 bloques BS1A: Reliq. Energía mar 2019 | L30: 2019-05-13 00:00:00 | M30: 33 | O30: s | P30: s | Q30: BS1A | R30: Caren | S30: Cec | T30: 2013/03-2 | U30: CEC
A31: 01-03-2019 | B31: 01-03-2019 | C31: Licitación Caren y Cec (SIC 2013/03-2) BS1A | D31: 5 | E31: RAPEL 220 | F31: 7.514895 | G31: 69.368 | H31: 521 | I31: Energia Licitaciones | J31: Energía | K31: Lic. SIC 2013/03-2 bloques BS1A: Energía mar 2019 | L31: 2019-04-08 00:00:00 | M31: 33 | N31: 8389 | O31: s | P31: s | Q31: BS1A | R31: Caren | S31: Cec | T31: 2013/03-2 | U31: CEC
A32: 01-04-2019 | B32: 01-04-2019 | C32: Licitación Caren y Cec (SIC 2013/03-2) BS1A | D32: 1 | E32: A.JAHUEL 220 | F32: 1 | G32: -1091 | H32: -1091 | I32: Reliq. Energia Licitaciones | J32: Energía | K32: Lic. SIC 2013/03-2 bloques BS1A: Reliq. Energía abr 2019 | L32: 2020-03-23 11:56:36 | M32: 61 | O32: s | P32: s | Q32: BS1A | R32: Caren | S32: Cec | T32: 2013/03-2 | U32: CEC
A33: 01-04-2019 | B33: 01-04-2019 | C33: Licitación Caren y Cec (SIC 2013/03-2) BS1A | D33: 1 | E33: A.JAHUEL 220 | F33: 0 | G33: 0 | H33: 0 | I33: Potencia Licitaciones | J33: Potencia | K33: Lic. SIC 2013/03-2 bloques BS1A: Potencia abr 2019 | L33: 2019-05-13 00:00:00 | M33: 33 | N33: 8451 | O33: s | P33: s | Q33: BS1A | R33: Caren | S33: Cec | T33: 2013/03-2 | U33: CEC
A34: 01-04-2019 | B34: 01-04-2019 | C34: Licitación Caren y Cec (SIC 2013/03-2) BS1A | D34: 1 | E34: A.JAHUEL 220 | F34: 897.9651 | G34: 66.9 | H34: 60074 | I34: Energia Licitaciones | J34: Energía | K34: Lic. SIC 2013/03-2 bloques BS1A: Energía abr 2019 | L34: 2019-05-13 00:00:00 | M34: 33 | N34: 8451 | O34: s | P34: s | Q34: BS1A | R34: Caren | S34: Cec | T34: 2013/03-2 | U34: CEC
A35: 01-04-2019 | B35: 01-04-2019 | C35: Licitación Caren y Cec (SIC 2013/03-2) BS1A | D35: 1 | E35: A.JAHUEL 220 | F35: 0 | G35: 0 | H35: 0 | I35: Ajuste por Armonizacion Tarifaria Licitaciones | J35: AAT | K35: Lic. SIC 2013/03-2 bloques BS1A: AAT abr 2019 | L35: 2019-05-13 00:00:00 | M35: 33 | N35: 8451 | O35: s | P35: s | Q35: BS1A | R35: Caren | S35: Cec | T35: 2013/03-2 | U35: CEC
A36: 01-04-2019 | B36: 01-04-2019 | C36: Licitación Caren y Cec (SIC 2013/03-2) BS1A | D36: 1 | E36: A.JAHUEL 220 | F36: 0 | G36: 0 | H36: 0 | I36: Reactivos Licitaciones | J36: Reactivo | K36: Lic. SIC 2013/03-2 bloques BS1A: Reactivo abr 2019 | L36: 2019-05-13 00:00:00 | M36: 33 | N36: 8451 | O36: s | P36: s | Q36: BS1A | R36: Caren | S36: Cec | T36: 2013/03-2 | U36: CEC
A37: 01-04-2019 | B37: 01-04-2019 | C37: Licitación Caren y Cec (SIC 2013/03-2) BS1A | D37: 2 | E37: A.MELIP 220 | F37: 0 | G37: 0 | H37: 0 | I37: Potencia Licitaciones | J37: Potencia | K37: Lic. SIC 2013/03-2 bloques BS1A: Potencia abr 2019 | L37: 2019-05-13 00:00:00 | M37: 33 | N37: 8451 | O37: s | P37: s | Q37: BS1A | R37: Caren | S37: Cec | T37: 2013/03-2 | U37: CEC
A38: 01-04-2019 | B38: 01-04-2019 | C38: Licitación Caren y Cec (SIC 2013/03-2) BS1A | D38: 2 | E38: A.MELIP 220 | F38: 0 | G38: 0 | H38: 0 | I38: Ajuste por Armonizacion Tarifaria Licitaciones | J38: AAT | K38: Lic. SIC 2013/03-2 bloques BS1A: AAT abr 2019 | L38: 2019-05-13 00:00:00 | M38: 33 | N38: 8451 | O38: s | P38: s | Q38: BS1A | R38: Caren | S38: Cec | T38: 2013/03-2 | U38: CEC
A39: 01-04-2019 | B39: 01-04-2019 | C39: Licitación Caren y Cec (SIC 2013/03-2) BS1A | D39: 2 | E39: A.MELIP 220 | F39: 5.912451 | G39: 69.014 | H39: 408 | I39: Energia Licitaciones | J39: Energía | K39: Lic. SIC 2013/03-2 bloques BS1A: Energía abr 2019 | L39: 2019-05-13 00:00:00 | M39: 33 | N39: 8451 | O39: s | P39: s | Q39: BS1A | R39: Caren | S39: Cec | T39: 2013/03-2 | U39: CEC
A40: 01-04-2019 | B40: 01-04-2019 | C40: Licitación Caren y Cec (SIC 2013/03-2) BS1A | D40: 2 | E40: A.MELIP 220 | F40: 0 | G40: 0 | H40: 0 | I40: Reactivos Licitaciones | J40: Reactivo | K40: Lic. SIC 2013/03-2 bloques BS1A: Reactivo abr 2019 | L40: 2019-05-13 00:00:00 | M40: 33 | N40: 8451 | O40: s | P40: s | Q40: BS1A | R40: Caren | S40: Cec | T40: 2013/03-2 | U40: CEC
A41: 01-04-2019 | B41: 01-04-2019 | C41: Licitación Caren y Cec (SIC 2013/03-2) BS1A | D41: 2 | E41: A.MELIP 220 | F41: 1 | G41: -8 | H41: -8 | I41: Reliq. Energia Licitaciones | J41: Energía | K41: Lic. SIC 2013/03-2 bloques BS1A: Reliq. Energía abr 2019 | L41: 2020-03-23 11:56:36 | M41: 61 | O41: s | P41: s | Q41: BS1A | R41: Caren | S41: Cec | T41: 2013/03-2 | U41: CEC
A42: 01-04-2019 | B42: 01-04-2019 | C42: Licitación Caren y Cec (SIC 2013/03-2) BS1A | D42: 3 | E42: CHARRUA 220 | F42: 278.37089 | G42: 63.27 | H42: 17613 | I42: Energia Licitaciones | J42: Energía | K42: Lic. SIC 2013/03-2 bloques BS1A: Energía abr 2019 | L42: 2019-05-13 00:00:00 | M42: 33 | N42: 8451 | O42: s | P42: s | Q42: BS1A | R42: Caren | S42: Cec | T42: 2013/03-2 | U42: CEC
A43: 01-04-2019 | B43: 01-04-2019 | C43: Licitación Caren y Cec (SIC 2013/03-2) BS1A | D43: 3 | E43: CHARRUA 220 | F43: 0 | G43: 0 | H43: 0 | I43: Ajuste por Armonizacion Tarifaria Licitaciones | J43: AAT | K43: Lic. SIC 2013/03-2 bloques BS1A: AAT abr 2019 | L43: 2019-05-13 00:00:00 | M43: 33 | N43: 8451 | O43: s | P43: s | Q43: BS1A | R43: Caren | S43: Cec | T43: 2013/03-2 | U43: CEC
A44: 01-04-2019 | B44: 01-04-2019 | C44: Licitación Caren y Cec (SIC 2013/03-2) BS1A | D44: 3 | E44: CHARRUA 220 | F44: 1 | G44: -327 | H44: -327 | I44: Reliq. Energia Licitaciones | J44: Energía | K44: Lic. SIC 2013/03-2 bloques BS1A: Reliq. Energía abr 2019 | L44: 2020-03-23 11:56:36 | M44: 61 | O44: s | P44: s | Q44: BS1A | R44: Caren | S44: Cec | T44: 2013/03-2 | U44: CEC
A45: 01-04-2019 | B45: 01-04-2019 | C45: Licitación Caren y Cec (SIC 2013/03-2) BS1A | D45: 3 | E45: CHARRUA 220 | F45: 0 | G45: 0 | H45: 0 | I45: Potencia Licitaciones | J45: Potencia | K45: Lic. SIC 2013/03-2 bloques BS1A: Potencia abr 2019 | L45: 2019-05-13 00:00:00 | M45: 33 | N45: 8451 | O45: s | P45: s | Q45: BS1A | R45: Caren | S45: Cec | T45: 2013/03-2 | U45: CEC
A46: 01-04-2019 | B46: 01-04-2019 | C46: Licitación Caren y Cec (SIC 2013/03-2) BS1A | D46: 3 | E46: CHARRUA 220 | F46: 0 | G46: 0 | H46: 0 | I46: Reactivos Licitaciones | J46: Reactivo | K46: Lic. SIC 2013/03-2 bloques BS1A: Reactivo abr 2019 | L46: 2019-05-13 00:00:00 | M46: 33 | N46: 8451 | O46: s | P46: s | Q46: BS1A | R46: Caren | S46: Cec | T46: 2013/03-2 | U46: CEC
A47: 01-04-2019 | B47: 01-04-2019 | C47: Licitación Caren y Cec (SIC 2013/03-2) BS1A | D47: 4 | E47: ITAHUE 220 | F47: 1 | G47: -1638 | H47: -1638 | I47: Reliq. Energia Licitaciones | J47: Energía | K47: Lic. SIC 2013/03-2 bloques BS1A: Reliq. Energía abr 2019 | L47: 2020-03-23 11:56:36 | M47: 61 | O47: s | P47: s | Q47: BS1A | R47: Caren | S47: Cec | T47: 2013/03-2 | U47: CEC
A48: 01-04-2019 | B48: 01-04-2019 | C48: Licitación Caren y Cec (SIC 2013/03-2) BS1A | D48: 4 | E48: ITAHUE 220 | F48: 0 | G48: 0 | H48: 0 | I48: Ajuste por Armonizacion Tarifaria Licitaciones | J48: AAT | K48: Lic. SIC 2013/03-2 bloques BS1A: AAT abr 2019 | L48: 2019-05-13 00:00:00 | M48: 33 | N48: 8451 | O48: s | P48: s | Q48: BS1A | R48: Caren | S48: Cec | T48: 2013/03-2 | U48: CEC
A49: 01-04-2019 | B49: 01-04-2019 | C49: Licitación Caren y Cec (SIC 2013/03-2) BS1A | D49: 4 | E49: ITAHUE 220 | F49: 1366.2586 | G49: 65.349 | H49: 89284 | I49: Energia Licitaciones | J49: Energía | K49: Lic. SIC 2013/03-2 bloques BS1A: Energía abr 2019 | L49: 2019-05-13 00:00:00 | M49: 33 | N49: 8451 | O49: s | P49: s | Q49: BS1A | R49: Caren | S49: Cec | T49: 2013/03-2 | U49: CEC
A50: 01-04-2019 | B50: 01-04-2019 | C50: Licitación Caren y Cec (SIC 2013/03-2) BS1A | D50: 4 | E50: ITAHUE 220 | F50: 0 | G50: 0 | H50: 0 | I50: Potencia Licitaciones | J50: Potencia | K50: Lic. SIC 2013/03-2 bloques BS1A: Potencia abr 2019 | L50: 2019-05-13 00:00:00 | M50: 33 | N50: 8451 | O50: s | P50: s | Q50: BS1A | R50: Caren | S50: Cec | T50: 2013/03-2 | U50: CEC
A51: 01-04-2019 | B51: 01-04-2019 | C51: Licitación Caren y Cec (SIC 2013/03-2) BS1A | D51: 4 | E51: ITAHUE 220 | F51: 0 | G51: 0 | H51: 0 | I51: Reactivos Licitaciones | J51: Reactivo | K51: Lic. SIC 2013/03-2 bloques BS1A: Reactivo abr 2019 | L51: 2019-05-13 00:00:00 | M51: 33 | N51: 8451 | O51: s | P51: s | Q51: BS1A | R51: Caren | S51: Cec | T51: 2013/03-2 | U51: CEC
A52: 01-04-2019 | B52: 01-04-2019 | C52: Licitación Caren y Cec (SIC 2013/03-2) BS1A | D52: 5 | E52: RAPEL 220 | F52: 0 | G52: 0 | H52: 0 | I52: Potencia Licitaciones | J52: Potencia | K52: Lic. SIC 2013/03-2 bloques BS1A: Potencia abr 2019 | L52: 2019-05-13 00:00:00 | M52: 33 | N52: 8451 | O52: s | P52: s | Q52: BS1A | R52: Caren | S52: Cec | T52: 2013/03-2 | U52: CEC
A53: 01-04-2019 | B53: 01-04-2019 | C53: Licitación Caren y Cec (SIC 2013/03-2) BS1A | D53: 5 | E53: RAPEL 220 | F53: 0 | G53: 0 | H53: 0 | I53: Ajuste por Armonizacion Tarifaria Licitaciones | J53: AAT | K53: Lic. SIC 2013/03-2 bloques BS1A: AAT abr 2019 | L53: 2019-05-13 00:00:00 | M53: 33 | N53: 8451 | O53: s | P53: s | Q53: BS1A | R53: Caren | S53: Cec | T53: 2013/03-2 | U53: CEC
A54: 01-04-2019 | B54: 01-04-2019 | C54: Licitación Caren y Cec (SIC 2013/03-2) BS1A | D54: 5 | E54: RAPEL 220 | F54: 0 | G54: 0 | H54: 0 | I54: Reactivos Licitaciones | J54: Reactivo | K54: Lic. SIC 2013/03-2 bloques BS1A: Reactivo abr 2019 | L54: 2019-05-13 00:00:00 | M54: 33 | N54: 8451 | O54: s | P54: s | Q54: BS1A | R54: Caren | S54: Cec | T54: 2013/03-2 | U54: CEC
A55: 01-04-2019 | B55: 01-04-2019 | C55: Licitación Caren y Cec (SIC 2013/03-2) BS1A | D55: 5 | E55: RAPEL 220 | F55: 1 | G55: -7 | H55: -7 | I55: Reliq. Energia Licitaciones | J55: Energía | K55: Lic. SIC 2013/03-2 bloques BS1A: Reliq. Energía abr 2019 | L55: 2020-03-23 11:56:36 | M55: 61 | O55: s | P55: s | Q55: BS1A | R55: Caren | S55: Cec | T55: 2013/03-2 | U55: CEC
A56: 01-04-2019 | B56: 01-04-2019 | C56: Licitación Caren y Cec (SIC 2013/03-2) BS1A | D56: 5 | E56: RAPEL 220 | F56: 5.432024 | G56: 69.368 | H56: 377 | I56: Energia Licitaciones | J56: Energía | K56: Lic. SIC 2013/03-2 bloques BS1A: Energía abr 2019 | L56: 2019-05-13 00:00:00 | M56: 33 | N56: 8451 | O56: s | P56: s | Q56: BS1A | R56: Caren | S56: Cec | T56: 2013/03-2 | U56: CEC
A57: 01-05-2019 | B57: 01-05-2019 | C57: Licitación Caren y Cec (SIC 2013/03-2) BS1A | D57: 1 | E57: A.JAHUEL 220 | F57: 0 | G57: 0 | H57: 0 | I57: Reactivos Licitaciones | J57: Reactivo | K57: Lic. SIC 2013/03-2 bloques BS1A: Reactivo may 2019 | L57: 2019-06-11 00:00:00 | M57: 33 | N57: 8768 | O57: s | P57: s | Q57: BS1A | R57: Caren | S57: Cec | T57: 2013/03-2 | U57: CEC
A58: 01-05-2019 | B58: 01-05-2019 | C58: Licitación Caren y Cec (SIC 2013/03-2) BS1A | D58: 1 | E58: A.JAHUEL 220 | F58: 1 | G58: -337 | H58: -337 | I58: Reliq. Energia Licitaciones | J58: Energía | K58: Lic. SIC 2013/03-2 bloques BS1A: Reliq. Energía may 2019 | L58: 2020-03-25 15:09:20 | M58: 61 | O58: s | P58: s | Q58: BS1A | R58: Caren | S58: Cec | T58: 2013/03-2 | U58: CEC
A59: 01-05-2019 | B59: 01-05-2019 | C59: Licitación Caren y Cec (SIC 2013/03-2) BS1A | D59: 1 | E59: A.JAHUEL 220 | F59: 0 | G59: 0 | H59: 0 | I59: Potencia Licitaciones | J59: Potencia | K59: Lic. SIC 2013/03-2 bloques BS1A: Potencia may 2019 | L59: 2019-06-11 00:00:00 | M59: 33 | N59: 8768 | O59: s | P59: s | Q59: BS1A | R59: Caren | S59: Cec | T59: 2013/03-2 | U59: CEC
A60: 01-05-2019 | B60: 01-05-2019 | C60: Licitación Caren y Cec (SIC 2013/03-2) BS1A | D60: 1 | E60: A.JAHUEL 220 | F60: 1 | G60: -4 | H60: -4 | I60: Reliq. Ajuste por Armonizacion Tarifaria Licitaciones | J60: AAT | K60: Lic. SIC 2013/03-2 bloques BS1A: Reliq. AAT may 2019 | L60: 2020-03-25 15:09:20 | M60: 61 | O60: s | P60: s | Q60: BS1A | R60: Caren | S60: Cec | T60: 2013/03-2 | U60: CEC
A61: 01-05-2019 | B61: 01-05-2019 | C61: Licitación Caren y Cec (SIC 2013/03-2) BS1A | D61: 1 | E61: A.JAHUEL 220 | F61: 885.88967 | G61: 74.401 | H61: 65911 | I61: Energia Licitaciones | J61: Energía | K61: Lic. SIC 2013/03-2 bloques BS1A: Energía may 2019 | L61: 2019-06-11 00:00:00 | M61: 33 | N61: 8768 | O61: s | P61: s | Q61: BS1A | R61: Caren | S61: Cec | T61: 2013/03-2 | U61: CEC
A62: 01-05-2019 | B62: 01-05-2019 | C62: Licitación Caren y Cec (SIC 2013/03-2) BS1A | D62: 1 | E62: A.JAHUEL 220 | F62: 885.88967 | G62: 1.067 | H62: 945 | I62: Ajuste por Armonizacion Tarifaria Licitaciones | J62: AAT | K62: Lic. SIC 2013/03-2 bloques BS1A: AAT may 2019 | L62: 2019-06-11 00:00:00 | M62: 33 | N62: 8768 | O62: s | P62: s | Q62: BS1A | R62: Caren | S62: Cec | T62: 2013/03-2 | U62: CEC
A63: 01-05-2019 | B63: 01-05-2019 | C63: Licitación Caren y Cec (SIC 2013/03-2) BS1A | D63: 2 | E63: A.MELIP 220 | F63: 0 | G63: 0 | H63: 0 | I63: Reactivos Licitaciones | J63: Reactivo | K63: Lic. SIC 2013/03-2 bloques BS1A: Reactivo may 2019 | L63: 2019-06-11 00:00:00 | M63: 33 | N63: 8768 | O63: s | P63: s | Q63: BS1A | R63: Caren | S63: Cec | T63: 2013/03-2 | U63: CEC
A64: 01-05-2019 | B64: 01-05-2019 | C64: Licitación Caren y Cec (SIC 2013/03-2) BS1A | D64: 2 | E64: A.MELIP 220 | F64: 1 | G64: -2 | H64: -2 | I64: Reliq. Energia Licitaciones | J64: Energía | K64: Lic. SIC 2013/03-2 bloques BS1A: Reliq. Energía may 2019 | L64: 2020-03-25 15:09:20 | M64: 61 | O64: s | P64: s | Q64: BS1A | R64: Caren | S64: Cec | T64: 2013/03-2 | U64: CEC
A65: 01-05-2019 | B65: 01-05-2019 | C65: Licitación Caren y Cec (SIC 2013/03-2) BS1A | D65: 2 | E65: A.MELIP 220 | F65: 5.728447 | G65: 75.737 | H65: 434 | I65: Energia Licitaciones | J65: Energía | K65: Lic. SIC 2013/03-2 bloques BS1A: Energía may 2019 | L65: 2019-06-11 00:00:00 | M65: 33 | N65: 8768 | O65: s | P65: s | Q65: BS1A | R65: Caren | S65: Cec | T65: 2013/03-2 | U65: CEC
A66: 01-05-2019 | B66: 01-05-2019 | C66: Licitación Caren y Cec (SIC 2013/03-2) BS1A | D66: 2 | E66: A.MELIP 220 | F66: 0 | G66: 0 | H66: 0 | I66: Potencia Licitaciones | J66: Potencia | K66: Lic. SIC 2013/03-2 bloques BS1A: Potencia may 2019 | L66: 2019-06-11 00:00:00 | M66: 33 | N66: 8768 | O66: s | P66: s | Q66: BS1A | R66: Caren | S66: Cec | T66: 2013/03-2 | U66: CEC
A67: 01-05-2019 | B67: 01-05-2019 | C67: Licitación Caren y Cec (SIC 2013/03-2) BS1A | D67: 2 | E67: A.MELIP 220 | F67: 5.728447 | G67: 1.067 | H67: 6 | I67: Ajuste por Armonizacion Tarifaria Licitaciones | J67: AAT | K67: Lic. SIC 2013/03-2 bloques BS1A: AAT may 2019 | L67: 2019-06-11 00:00:00 | M67: 33 | N67: 8768 | O67: s | P67: s | Q67: BS1A | R67: Caren | S67: Cec | T67: 2013/03-2 | U67: CEC
A68: 01-05-2019 | B68: 01-05-2019 | C68: Licitación Caren y Cec (SIC 2013/03-2) BS1A | D68: 3 | E68: CHARRUA 220 | F68: 273.81804 | G68: 70.437 | H68: 19287 | I68: Energia Licitaciones | J68: Energía | K68: Lic. SIC 2013/03-2 bloques BS1A: Energía may 2019 | L68: 2019-06-11 00:00:00 | M68: 33 | N68: 8768 | O68: s | P68: s | Q68: BS1A | R68: Caren | S68: Cec | T68: 2013/03-2 | U68: CEC
A69: 01-05-2019 | B69: 01-05-2019 | C69: Licitación Caren y Cec (SIC 2013/03-2) BS1A | D69: 3 | E69: CHARRUA 220 | F69: 0 | G69: 0 | H69: 0 | I69: Potencia Licitaciones | J69: Potencia | K69: Lic. SIC 2013/03-2 bloques BS1A: Potencia may 2019 | L69: 2019-06-11 00:00:00 | M69: 33 | N69: 8768 | O69: s | P69: s | Q69: BS1A | R69: Caren | S69: Cec | T69: 2013/03-2 | U69: CEC
A70: 01-05-2019 | B70: 01-05-2019 | C70: Licitación Caren y Cec (SIC 2013/03-2) BS1A | D70: 3 | E70: CHARRUA 220 | F70: 1 | G70: -1 | H70: -1 | I70: Reliq. Ajuste por Armonizacion Tarifaria Licitaciones | J70: AAT | K70: Lic. SIC 2013/03-2 bloques BS1A: Reliq. AAT may 2019 | L70: 2020-03-25 15:09:20 | M70: 61 | O70: s | P70: s | Q70: BS1A | R70: Caren | S70: Cec | T70: 2013/03-2 | U70: CEC
A71: 01-05-2019 | B71: 01-05-2019 | C71: Licitación Caren y Cec (SIC 2013/03-2) BS1A | D71: 3 | E71: CHARRUA 220 | F71: 0 | G71: 0 | H71: 0 | I71: Reactivos Licitaciones | J71: Reactivo | K71: Lic. SIC 2013/03-2 bloques BS1A: Reactivo may 2019 | L71: 2019-06-11 00:00:00 | M71: 33 | N71: 8768 | O71: s | P71: s | Q71: BS1A | R71: Caren | S71: Cec | T71: 2013/03-2 | U71: CEC
A72: 01-05-2019 | B72: 01-05-2019 | C72: Licitación Caren y Cec (SIC 2013/03-2) BS1A | D72: 3 | E72: CHARRUA 220 | F72: 273.81804 | G72: 1.067 | H72: 292 | I72: Ajuste por Armonizacion Tarifaria Licitaciones | J72: AAT | K72: Lic. SIC 2013/03-2 bloques BS1A: AAT may 2019 | L72: 2019-06-11 00:00:00 | M72: 33 | N72: 8768 | O72: s | P72: s | Q72: BS1A | R72: Caren | S72: Cec | T72: 2013/03-2 | U72: CEC
A73: 01-05-2019 | B73: 01-05-2019 | C73: Licitación Caren y Cec (SIC 2013/03-2) BS1A | D73: 3 | E73: CHARRUA 220 | F73: 1 | G73: -99 | H73: -99 | I73: Reliq. Energia Licitaciones | J73: Energía | K73: Lic. SIC 2013/03-2 bloques BS1A: Reliq. Energía may 2019 | L73: 2020-03-25 15:09:20 | M73: 61 | O73: s | P73: s | Q73: BS1A | R73: Caren | S73: Cec | T73: 2013/03-2 | U73: CEC
A74: 01-05-2019 | B74: 01-05-2019 | C74: Licitación Caren y Cec (SIC 2013/03-2) BS1A | D74: 4 | E74: ITAHUE 220 | F74: 1 | G74: -8 | H74: -8 | I74: Reliq. Ajuste por Armonizacion Tarifaria Licitaciones | J74: AAT | K74: Lic. SIC 2013/03-2 bloques BS1A: Reliq. AAT may 2019 | L74: 2020-03-25 15:09:20 | M74: 61 | O74: s | P74: s | Q74: BS1A | R74: Caren | S74: Cec | T74: 2013/03-2 | U74: CEC
A75: 01-05-2019 | B75: 01-05-2019 | C75: Licitación Caren y Cec (SIC 2013/03-2) BS1A | D75: 4 | E75: ITAHUE 220 | F75: 1 | G75: -494 | H75: -494 | I75: Reliq. Energia Licitaciones | J75: Energía | K75: Lic. SIC 2013/03-2 bloques BS1A: Reliq. Energía may 2019 | L75: 2020-03-25 15:09:20 | M75: 61 | O75: s | P75: s | Q75: BS1A | R75: Caren | S75: Cec | T75: 2013/03-2 | U75: CEC
A76: 01-05-2019 | B76: 01-05-2019 | C76: Licitación Caren y Cec (SIC 2013/03-2) BS1A | D76: 4 | E76: ITAHUE 220 | F76: 0 | G76: 0 | H76: 0 | I76: Potencia Licitaciones | J76: Potencia | K76: Lic. SIC 2013/03-2 bloques BS1A: Potencia may 2019 | L76: 2019-06-11 00:00:00 | M76: 33 | N76: 8768 | O76: s | P76: s | Q76: BS1A | R76: Caren | S76: Cec | T76: 2013/03-2 | U76: CEC
A77: 01-05-2019 | B77: 01-05-2019 | C77: Licitación Caren y Cec (SIC 2013/03-2) BS1A | D77: 4 | E77: ITAHUE 220 | F77: 0 | G77: 0 | H77: 0 | I77: Reactivos Licitaciones | J77: Reactivo | K77: Lic. SIC 2013/03-2 bloques BS1A: Reactivo may 2019 | L77: 2019-06-11 00:00:00 | M77: 33 | N77: 8768 | O77: s | P77: s | Q77: BS1A | R77: Caren | S77: Cec | T77: 2013/03-2 | U77: CEC
A78: 01-05-2019 | B78: 01-05-2019 | C78: Licitación Caren y Cec (SIC 2013/03-2) BS1A | D78: 4 | E78: ITAHUE 220 | F78: 1341.7257 | G78: 1.067 | H78: 1432 | I78: Ajuste por Armonizacion Tarifaria Licitaciones | J78: AAT | K78: Lic. SIC 2013/03-2 bloques BS1A: AAT may 2019 | L78: 2019-06-11 00:00:00 | M78: 33 | N78: 8768 | O78: s | P78: s | Q78: BS1A | R78: Caren | S78: Cec | T78: 2013/03-2 | U78: CEC
A79: 01-05-2019 | B79: 01-05-2019 | C79: Licitación Caren y Cec (SIC 2013/03-2) BS1A | D79: 4 | E79: ITAHUE 220 | F79: 1341.7257 | G79: 71.984 | H79: 96583 | I79: Energia Licitaciones | J79: Energía | K79: Lic. SIC 2013/03-2 bloques BS1A: Energía may 2019 | L79: 2019-06-11 00:00:00 | M79: 33 | N79: 8768 | O79: s | P79: s | Q79: BS1A | R79: Caren | S79: Cec | T79: 2013/03-2 | U79: CEC
A80: 01-05-2019 | B80: 01-05-2019 | C80: Licitación Caren y Cec (SIC 2013/03-2) BS1A | D80: 5 | E80: RAPEL 220 | F80: 1 | G80: -2 | H80: -2 | I80: Reliq. Energia Licitaciones | J80: Energía | K80: Lic. SIC 2013/03-2 bloques BS1A: Reliq. Energía may 2019 | L80: 2020-03-25 15:09:20 | M80: 61 | O80: s | P80: s | Q80: BS1A | R80: Caren | S80: Cec | T80: 2013/03-2 | U80: CEC
A81: 01-05-2019 | B81: 01-05-2019 | C81: Licitación Caren y Cec (SIC 2013/03-2) BS1A | D81: 5 | E81: RAPEL 220 | F81: 0 | G81: 0 | H81: 0 | I81: Potencia Licitaciones | J81: Potencia | K81: Lic. SIC 2013/03-2 bloques BS1A: Potencia may 2019 | L81: 2019-06-11 00:00:00 | M81: 33 | N81: 8768 | O81: s | P81: s | Q81: BS1A | R81: Caren | S81: Cec | T81: 2013/03-2 | U81: CEC
A82: 01-05-2019 | B82: 01-05-2019 | C82: Licitación Caren y Cec (SIC 2013/03-2) BS1A | D82: 5 | E82: RAPEL 220 | F82: 0 | G82: 0 | H82: 0 | I82: Reactivos Licitaciones | J82: Reactivo | K82: Lic. SIC 2013/03-2 bloques BS1A: Reactivo may 2019 | L82: 2019-06-11 00:00:00 | M82: 33 | N82: 8768 | O82: s | P82: s | Q82: BS1A | R82: Caren | S82: Cec | T82: 2013/03-2 | U82: CEC
A83: 01-05-2019 | B83: 01-05-2019 | C83: Licitación Caren y Cec (SIC 2013/03-2) BS1A | D83: 5 | E83: RAPEL 220 | F83: 5.26453 | G83: 1.067 | H83: 6 | I83: Ajuste por Armonizacion Tarifaria Licitaciones | J83: AAT | K83: Lic. SIC 2013/03-2 bloques BS1A: AAT may 2019 | L83: 2019-06-11 00:00:00 | M83: 33 | N83: 8768 | O83: s | P83: s | Q83: BS1A | R83: Caren | S83: Cec | T83: 2013/03-2 | U83: CEC
A84: 01-05-2019 | B84: 01-05-2019 | C84: Licitación Caren y Cec (SIC 2013/03-2) BS1A | D84: 5 | E84: RAPEL 220 | F84: 5.26453 | G84: 75.617 | H84: 398 | I84: Energia Licitaciones | J84: Energía | K84: Lic. SIC 2013/03-2 bloques BS1A: Energía may 2019 | L84: 2019-06-11 00:00:00 | M84: 33 | N84: 8768 | O84: s | P84: s | Q84: BS1A | R84: Caren | S84: Cec | T84: 2013/03-2 | U84: CEC
A85: 01-06-2019 | B85: 01-06-2019 | C85: Licitación Caren y Cec (SIC 2013/03-2) BS1A | D85: 1 | E85: A.JAHUEL 220 | F85: 0 | G85: 0 | H85: 0 | I85: Potencia Licitaciones | J85: Potencia | K85: Lic. SIC 2013/03-2 bloques BS1A: Potencia jun 2019 | L85: 2019-07-09 00:00:00 | M85: 33 | N85: 9022 | O85: s | P85: s | Q85: BS1A | R85: Caren | S85: Cec | T85: 2013/03-2 | U85: CEC
A86: 01-06-2019 | B86: 01-06-2019 | C86: Licitación Caren y Cec (SIC 2013/03-2) BS1A | D86: 1 | E86: A.JAHUEL 220 | F86: 1.775945 | G86: 74.401 | H86: 132 | I86: Reliq. Energia Licitaciones | J86: Energía | K86: Lic. SIC 2013/03-2 bloques BS1A: Reliq. Energía jun 2019 | L86: 2019-08-16 00:00:00 | M86: 33 | O86: s | P86: s | Q86: BS1A | R86: Caren | S86: Cec | T86: 2013/03-2 | U86: CEC
A87: 01-06-2019 | B87: 01-06-2019 | C87: Licitación Caren y Cec (SIC 2013/03-2) BS1A | D87: 1 | E87: A.JAHUEL 220 | F87: 0 | G87: 0 | H87: 0 | I87: Reactivos Licitaciones | J87: Reactivo | K87: Lic. SIC 2013/03-2 bloques BS1A: Reactivo jun 2019 | L87: 2019-07-09 00:00:00 | M87: 33 | N87: 9022 | O87: s | P87: s | Q87: BS1A | R87: Caren | S87: Cec | T87: 2013/03-2 | U87: CEC
A88: 01-06-2019 | B88: 01-06-2019 | C88: Licitación Caren y Cec (SIC 2013/03-2) BS1A | D88: 1 | E88: A.JAHUEL 220 | F88: 790.40863 | G88: 74.401 | H88: 58807 | I88: Energia Licitaciones | J88: Energía | K88: Lic. SIC 2013/03-2 bloques BS1A: Energía jun 2019 | L88: 2019-07-09 00:00:00 | M88: 33 | N88: 9022 | O88: s | P88: s | Q88: BS1A | R88: Caren | S88: Cec | T88: 2013/03-2 | U88: CEC
A89: 01-06-2019 | B89: 01-06-2019 | C89: Licitación Caren y Cec (SIC 2013/03-2) BS1A | D89: 1 | E89: A.JAHUEL 220 | F89: 1.775945 | G89: 1.067 | H89: 2 | I89: Reliq. Ajuste por Armonizacion Tarifaria Licitaciones | J89: AAT | K89: Lic. SIC 2013/03-2 bloques BS1A: Reliq. AAT jun 2019 | L89: 2019-08-16 00:00:00 | M89: 33 | O89: s | P89: s | Q89: BS1A | R89: Caren | S89: Cec | T89: 2013/03-2 | U89: CEC
A90: 01-06-2019 | B90: 01-06-2019 | C90: Licitación Caren y Cec (SIC 2013/03-2) BS1A | D90: 1 | E90: A.JAHUEL 220 | F90: 790.40863 | G90: 1.067 | H90: 843 | I90: Ajuste por Armonizacion Tarifaria Licitaciones | J90: AAT | K90: Lic. SIC 2013/03-2 bloques BS1A: AAT jun 2019 | L90: 2019-07-09 00:00:00 | M90: 33 | N90: 9022 | O90: s | P90: s | Q90: BS1A | R90: Caren | S90: Cec | T90: 2013/03-2 | U90: CEC
A91: 01-06-2019 | B91: 01-06-2019 | C91: Licitación Caren y Cec (SIC 2013/03-2) BS1A | D91: 2 | E91: A.MELIP 220 | F91: 0 | G91: 0 | H91: 0 | I91: Reactivos Licitaciones | J91: Reactivo | K91: Lic. SIC 2013/03-2 bloques BS1A: Reactivo jun 2019 | L91: 2019-07-09 00:00:00 | M91: 33 | N91: 9022 | O91: s | P91: s | Q91: BS1A | R91: Caren | S91: Cec | T91: 2013/03-2 | U91: CEC
A92: 01-06-2019 | B92: 01-06-2019 | C92: Licitación Caren y Cec (SIC 2013/03-2) BS1A | D92: 2 | E92: A.MELIP 220 | F92: 0.011666 | G92: 75.737 | H92: 1 | I92: Reliq. Energia Licitaciones | J92: Energía | K92: Lic. SIC 2013/03-2 bloques BS1A: Reliq. Energía jun 2019 | L92: 2019-08-16 00:00:00 | M92: 33 | O92: s | P92: s | Q92: BS1A | R92: Caren | S92: Cec | T92: 2013/03-2 | U92: CEC
A93: 01-06-2019 | B93: 01-06-2019 | C93: Licitación Caren y Cec (SIC 2013/03-2) BS1A | D93: 2 | E93: A.MELIP 220 | F93: 0 | G93: 0 | H93: 0 | I93: Potencia Licitaciones | J93: Potencia | K93: Lic. SIC 2013/03-2 bloques BS1A: Potencia jun 2019 | L93: 2019-07-09 00:00:00 | M93: 33 | N93: 9022 | O93: s | P93: s | Q93: BS1A | R93: Caren | S93: Cec | T93: 2013/03-2 | U93: CEC
A94: 01-06-2019 | B94: 01-06-2019 | C94: Licitación Caren y Cec (SIC 2013/03-2) BS1A | D94: 2 | E94: A.MELIP 220 | F94: 5.19207 | G94: 1.067 | H94: 6 | I94: Ajuste por Armonizacion Tarifaria Licitaciones | J94: AAT | K94: Lic. SIC 2013/03-2 bloques BS1A: AAT jun 2019 | L94: 2019-07-09 00:00:00 | M94: 33 | N94: 9022 | O94: s | P94: s | Q94: BS1A | R94: Caren | S94: Cec | T94: 2013/03-2 | U94: CEC
A95: 01-06-2019 | B95: 01-06-2019 | C95: Licitación Caren y Cec (SIC 2013/03-2) BS1A | D95: 2 | E95: A.MELIP 220 | F95: 5.19207 | G95: 75.737 | H95: 393 | I95: Energia Licitaciones | J95: Energía | K95: Lic. SIC 2013/03-2 bloques BS1A: Energía jun 2019 | L95: 2019-07-09 00:00:00 | M95: 33 | N95: 9022 | O95: s | P95: s | Q95: BS1A | R95: Caren | S95: Cec | T95: 2013/03-2 | U95: CEC
A96: 01-06-2019 | B96: 01-06-2019 | C96: Licitación Caren y Cec (SIC 2013/03-2) BS1A | D96: 3 | E96: CHARRUA 220 | F96: 0.551932 | G96: 1.067 | H96: 1 | I96: Reliq. Ajuste por Armonizacion Tarifaria Licitaciones | J96: AAT | K96: Lic. SIC 2013/03-2 bloques BS1A: Reliq. AAT jun 2019 | L96: 2019-08-16 00:00:00 | M96: 33 | O96: s | P96: s | Q96: BS1A | R96: Caren | S96: Cec | T96: 2013/03-2 | U96: CEC
A97: 01-06-2019 | B97: 01-06-2019 | C97: Licitación Caren y Cec (SIC 2013/03-2) BS1A | D97: 3 | E97: CHARRUA 220 | F97: 0 | G97: 0 | H97: 0 | I97: Reactivos Licitaciones | J97: Reactivo | K97: Lic. SIC 2013/03-2 bloques BS1A: Reactivo jun 2019 | L97: 2019-07-09 00:00:00 | M97: 33 | N97: 9022 | O97: s | P97: s | Q97: BS1A | R97: Caren | S97: Cec | T97: 2013/03-2 | U97: CEC
A98: 01-06-2019 | B98: 01-06-2019 | C98: Licitación Caren y Cec (SIC 2013/03-2) BS1A | D98: 3 | E98: CHARRUA 220 | F98: 245.64498 | G98: 1.067 | H98: 262 | I98: Ajuste por Armonizacion Tarifaria Licitaciones | J98: AAT | K98: Lic. SIC 2013/03-2 bloques BS1A: AAT jun 2019 | L98: 2019-07-09 00:00:00 | M98: 33 | N98: 9022 | O98: s | P98: s | Q98: BS1A | R98: Caren | S98: Cec | T98: 2013/03-2 | U98: CEC
A99: 01-06-2019 | B99: 01-06-2019 | C99: Licitación Caren y Cec (SIC 2013/03-2) BS1A | D99: 3 | E99: CHARRUA 220 | F99: 0 | G99: 0 | H99: 0 | I99: Potencia Licitaciones | J99: Potencia | K99: Lic. SIC 2013/03-2 bloques BS1A: Potencia jun 2019 | L99: 2019-07-09 00:00:00 | M99: 33 | N99: 9022 | O99: s | P99: s | Q99: BS1A | R99: Caren | S99: Cec | T99: 2013/03-2 | U99: CEC
A100: 01-06-2019 | B100: 01-06-2019 | C100: Licitación Caren y Cec (SIC 2013/03-2) BS1A | D100: 3 | E100: CHARRUA 220 | F100: 245.64498 | G100: 70.437 | H100: 17302 | I100: Energia Licitaciones | J100: Energía | K100: Lic. SIC 2013/03-2 bloques BS1A: Energía jun 2019 | L100: 2019-07-09 00:00:00 | M100: 33 | N100: 9022 | O100: s | P100: s | Q100: BS1A | R100: Caren | S100: Cec | T100: 2013/03-2 | U100: CEC
...

Sheet SIGGE_P
A1: Periodo | B1: MesDevengado | C1: Nombre | D1: Num | E1: Barra | F1: Cantidad | G1: Precio | H1: Monto | I1: Concepto | J1: Agrupacion | K1: Glosa | L1: FechaCarga | M1: TipoDocumento | N1: Folio | O1: Vendedor | P1: Comprador | Q1: Bloque | R1: Empresa | S1: ClaveEEDD | T1: Licitacion | U1: NomAgrupacion
A2: 01-09-2018 | B2: 01-09-2018 | C2: Licitación Caren y Cec (SIC 2013/03-2) BS1A | D2: 1 | E2: TotalBarras | F2: 3000 | G2: 58.085 | H2: 174255 | I2: Energia Licitaciones | J2: Energía | K2: Lic. SIC 2013/03-2 bloques BS1A: Energía sep 2018 | L2: 2018-10-19 00:00:00 | M2: 33 | N2: 6305 | O2: s | P2: s | Q2: BS1A | R2: Caren | S2: Cec | T2: 2013/03-2 | U2: CEC
A3: 01-10-2018 | B3: 01-10-2018 | C3: Licitación Caren y Cec (SIC 2013/03-2) BS1A | D3: 1 | E3: TotalBarras | F3: 3000 | G3: 59.678 | H3: 179035 | I3: Energia Licitaciones | J3: Energía | K3: Lic. SIC 2013/03-2 bloques BS1A: Energía oct 2018 | L3: 2018-11-27 00:00:00 | M3: 33 | N3: 6796 | O3: s | P3: s | Q3: BS1A | R3: Caren | S3: Cec | T3: 2013/03-2 | U3: CEC
A4: 01-11-2018 | B4: 01-11-2018 | C4: Licitación Caren y Cec (SIC 2013/03-2) BS1A | D4: 1 | E4: TotalBarras | F4: 4000 | G4: 59.635 | H4: 238540 | I4: Energia Licitaciones | J4: Energía | K4: Lic. SIC 2013/03-2 bloques BS1A: Energía nov 2018 | L4: 2018-12-14 00:00:00 | M4: 33 | N4: 6939 | O4: s | P4: s | Q4: BS1A | R4: Caren | S4: Cec | T4: 2013/03-2 | U4: CEC
A5: 01-12-2018 | B5: 01-12-2018 | C5: Licitación Caren y Cec (SIC 2013/03-2) BS1A | D5: 1 | E5: TotalBarras | F5: 5000 | G5: 67.951 | H5: 339757 | I5: Energia Licitaciones | J5: Energía | K5: Lic. SIC 2013/03-2 bloques BS1A: Energía dic 2018 | L5: 2019-01-21 00:00:00 | M5: 33 | N5: 7194 | O5: s | P5: s | Q5: BS1A | R5: Caren | S5: Cec | T5: 2013/03-2 | U5: CEC
A6: 01-01-2019 | B6: 01-01-2019 | C6: Licitación Caren y Cec (SIC 2013/03-2) BS1A | D6: 1 | E6: A.JAHUEL 220 | F6: 1.46188 | G6: 66.9 | H6: 98 | I6: Reliq. Energia Licitaciones | J6: Energía | K6: Lic. SIC 2013/03-2 bloques BS1A: Reliq. Energía ene 2019 | L6: 2019-03-15 00:00:00 | M6: 33 | O6: s | P6: s | Q6: BS1A | R6: Caren | S6: Cec | T6: 2013/03-2 | U6: CEC
A7: 01-01-2019 | B7: 01-01-2019 | C7: Licitación Caren y Cec (SIC 2013/03-2) BS1A | D7: 1 | E7: A.JAHUEL 220 | F7: 1371.306 | G7: 66.9 | H7: 91740 | I7: Energia Licitaciones | J7: Energía | K7: Lic. SIC 2013/03-2 bloques BS1A: Energía ene 2019 | L7: 2019-02-08 00:00:00 | M7: 33 | N7: 7513 | O7: s | P7: s | Q7: BS1A | R7: Caren | S7: Cec | T7: 2013/03-2 | U7: CEC
A8: 01-01-2019 | B8: 01-01-2019 | C8: Licitación Caren y Cec (SIC 2013/03-2) BS1A | D8: 2 | E8: A.MELIP 220 | F8: 0.009388 | G8: 69.014 | H8: 1 | I8: Reliq. Energia Licitaciones | J8: Energía | K8: Lic. SIC 2013/03-2 bloques BS1A: Reliq. Energía ene 2019 | L8: 2019-03-15 00:00:00 | M8: 33 | O8: s | P8: s | Q8: BS1A | R8: Caren | S8: Cec | T8: 2013/03-2 | U8: CEC
A9: 01-01-2019 | B9: 01-01-2019 | C9: Licitación Caren y Cec (SIC 2013/03-2) BS1A | D9: 2 | E9: A.MELIP 220 | F9: 8.806166 | G9: 69.014 | H9: 608 | I9: Energia Licitaciones | J9: Energía | K9: Lic. SIC 2013/03-2 bloques BS1A: Energía ene 2019 | L9: 2019-02-08 00:00:00 | M9: 33 | N9: 7513 | O9: s | P9: s | Q9: BS1A | R9: Caren | S9: Cec | T9: 2013/03-2 | U9: CEC
A10: 01-01-2019 | B10: 01-01-2019 | C10: Licitación Caren y Cec (SIC 2013/03-2) BS1A | D10: 3 | E10: CHARRUA 220 | F10: 0.453721 | G10: 63.27 | H10: 29 | I10: Reliq. Energia Licitaciones | J10: Energía | K10: Lic. SIC 2013/03-2 bloques BS1A: Reliq. Energía ene 2019 | L10: 2019-03-15 00:00:00 | M10: 33 | O10: s | P10: s | Q10: BS1A | R10: Caren | S10: Cec | T10: 2013/03-2 | U10: CEC
A11: 01-01-2019 | B11: 01-01-2019 | C11: Licitación Caren y Cec (SIC 2013/03-2) BS1A | D11: 3 | E11: CHARRUA 220 | F11: 425.60961 | G11: 63.27 | H11: 26928 | I11: Energia Licitaciones | J11: Energía | K11: Lic. SIC 2013/03-2 bloques BS1A: Energía ene 2019 | L11: 2019-02-08 00:00:00 | M11: 33 | N11: 7513 | O11: s | P11: s | Q11: BS1A | R11: Caren | S11: Cec | T11: 2013/03-2 | U11: CEC
A12: 01-01-2019 | B12: 01-01-2019 | C12: Licitación Caren y Cec (SIC 2013/03-2) BS1A | D12: 4 | E12: ITAHUE 220 | F12: 2.212452 | G12: 65.349 | H12: 145 | I12: Reliq. Energia Licitaciones | J12: Energía | K12: Lic. SIC 2013/03-2 bloques BS1A: Reliq. Energía ene 2019 | L12: 2019-03-15 00:00:00 | M12: 33 | O12: s | P12: s | Q12: BS1A | R12: Caren | S12: Cec | T12: 2013/03-2 | U12: CEC
A13: 01-01-2019 | B13: 01-01-2019 | C13: Licitación Caren y Cec (SIC 2013/03-2) BS1A | D13: 4 | E13: ITAHUE 220 | F13: 2075.374 | G13: 65.349 | H13: 135624 | I13: Energia Licitaciones | J13: Energía | K13: Lic. SIC 2013/03-2 bloques BS1A: Energía ene 2019 | L13: 2019-02-08 00:00:00 | M13: 33 | N13: 7513 | O13: s | P13: s | Q13: BS1A | R13: Caren | S13: Cec | T13: 2013/03-2 | U13: CEC
A14: 01-01-2019 | B14: 01-01-2019 | C14: Licitación Caren y Cec (SIC 2013/03-2) BS1A | D14: 5 | E14: RAPEL 220 | F14: 8.102057 | G14: 69.368 | H14: 562 | I14: Energia Licitaciones | J14: Energía | K14: Lic. SIC 2013/03-2 bloques BS1A: Energía ene 2019 | L14: 2019-02-08 00:00:00 | M14: 33 | N14: 7513 | O14: s | P14: s | Q14: BS1A | R14: Caren | S14: Cec | T14: 2013/03-2 | U14: CEC
A15: 01-01-2019 | B15: 01-01-2019 | C15: Licitación Caren y Cec (SIC 2013/03-2) BS1A | D15: 5 | E15: RAPEL 220 | F15: 0.008637 | G15: 69.368 | H15: 1 | I15: Reliq. Energia Licitaciones | J15: Energía | K15: Lic. SIC 2013/03-2 bloques BS1A: Reliq. Energía ene 2019 | L15: 2019-03-15 00:00:00 | M15: 33 | O15: s | P15: s | Q15: BS1A | R15: Caren | S15: Cec | T15: 2013/03-2 | U15: CEC
A16: 01-02-2019 | B16: 01-02-2019 | C16: Licitación Caren y Cec (SIC 2013/03-2) BS1A | D16: 1 | E16: A.JAHUEL 220 | F16: 1368.5299 | G16: 66.9 | H16: 91555 | I16: Energia Licitaciones | J16: Energía | K16: Lic. SIC 2013/03-2 bloques BS1A: Energía feb 2019 | L16: 2019-03-08 00:00:00 | M16: 33 | N16: 7798 | O16: s | P16: s | Q16: BS1A | R16: Caren | S16: Cec | T16: 2013/03-2 | U16: CEC
A17: 01-02-2019 | B17: 01-02-2019 | C17: Licitación Caren y Cec (SIC 2013/03-2) BS1A | D17: 1 | E17: A.JAHUEL 220 | F17: 0.23349 | G17: 66.9 | H17: 16 | I17: Reliq. Energia Licitaciones | J17: Energía | K17: Lic. SIC 2013/03-2 bloques BS1A: Reliq. Energía feb 2019 | L17: 2019-04-09 00:00:00 | M17: 61 | O17: s | P17: s | Q17: BS1A | R17: Caren | S17: Cec | T17: 2013/03-2 | U17: CEC
A18: 01-02-2019 | B18: 01-02-2019 | C18: Licitación Caren y Cec (SIC 2013/03-2) BS1A | D18: 2 | E18: A.MELIP 220 | F18: 8.816632 | G18: 69.014 | H18: 608 | I18: Energia Licitaciones | J18: Energía | K18: Lic. SIC 2013/03-2 bloques BS1A: Energía feb 2019 | L18: 2019-03-08 00:00:00 | M18: 33 | N18: 7798 | O18: s | P18: s | Q18: BS1A | R18: Caren | S18: Cec | T18: 2013/03-2 | U18: CEC
