Workbook

Sheet Reliquidacion
A2: Generador | B2: [GX]
A3: Distribuidor | B3: [EEDD]
A4: Licitacion | B4: 2013/03-2° Llamado
A5: Bloque | B5: [BLOQUE]
C7: LO QUE SE FACTURÓ | L7: LO QUE SE DEBIÓ HABER FACTURADO | U7: RELQUIDACIÓN Y CÁLCULO INTERESES
A8: ID | B8: MES | C8: ORIGEN DATA | D8: Energía (kWh) | E8: $/kWh | F8: Monto Energía ($) | G8: Potencia (kW) | H8: $/kW-mes | I8: Monto Potencia ($) | J8: Monto Total ($) | L8: ORIGEN DATA | M8: Energía (kWh) | N8: $/kWh | O8: Monto Energía ($) | P8: Potencia (kW) | Q8: $/kW-mes | R8: Monto Potencia ($) | S8: Monto Total ($) | U8: Mes | V8: Reliquidación mensual ($) | W8: Decreto PNP Reliquidación | X8: Fecha publicación Diario Oficial | Y8: Interés Anual | Z8: Fecha Facturación | AA8: Fecha Reliquidación | AB8: N° de días de intereses | AC8: Interés total según n° de días | AD8: Intereses ($) | AE8: Reliquidación Total ($)
A9: 9 | B9: 42370 | C9: =CONCATENATE("IF(VLOOKUP(B9,MAPA_DATA!D:G,2,0)=1,'FACT_EMITIDA',IF(VLOOKUP(B",A9,",MAPA_DATA!D:G,3,0)=1,'FACT_EST_EFACT',(IF(VLOOKUP(B",A9,",MAPA_DATA!D:G,4,0)=1,'FACT_EST_CEN','SIN_DATA')))") -> IF(VLOOKUP(B9,MAPA_DATA!D:G,2,0)=1,'FACT_EMITIDA',IF(VLOOKUP(B9,MAPA_DATA!D:G,3,0)=1,'FACT_EST_EFACT',(IF(VLOOKUP(B9,MAPA_DATA!D:G,4,0)=1,'FACT_EST_CEN','SIN_DATA'))) | D9: =CONCATENATE("SUMIF(",IF(C9="FACT_EMITIDA","SIGGE_E",C9),"!B:B,Reliquidacion!B",A9,",",IF(C9="FACT_EMITIDA","SIGGE_E",C9),"!F:F)") -> SUMIF(IF(VLOOKUP(B9,MAPA_DATA!D:G,2,0)=1,'FACT_EMITIDA',IF(VLOOKUP(B9,MAPA_DATA!D:G,3,0)=1,'FACT_EST_EFACT',(IF(VLOOKUP(B9,MAPA_DATA!D:G,4,0)=1,'FACT_EST_CEN','SIN_DATA')))!B:B,Reliquidacion!B9,IF(VLOOKUP(B9,MAPA_DATA!D:G,2,0)=1,'FACT_EMITIDA',IF(VLOOKUP(B9,MAPA_DATA!D:G,3,0)=1,'FACT_EST_EFACT',(IF(VLOOKUP(B9,MAPA_DATA!D:G,4,0)=1,'FACT_EST_CEN','SIN_DATA')))!F:F) | E9: =CONCATENATE("(F",A9,"/D",A9,")") -> (F9/D9) | F9: =CONCATENATE("SUMIF(",IF(C9="FACT_EMITIDA","SIGGE_E",C9),"!B:B,Reliquidacion!B",A9,",",IF(C9="FACT_EMITIDA","SIGGE_E",C9),"!H:H)") -> SUMIF(IF(VLOOKUP(B9,MAPA_DATA!D:G,2,0)=1,'FACT_EMITIDA',IF(VLOOKUP(B9,MAPA_DATA!D:G,3,0)=1,'FACT_EST_EFACT',(IF(VLOOKUP(B9,MAPA_DATA!D:G,4,0)=1,'FACT_EST_CEN','SIN_DATA')))!B:B,Reliquidacion!B9,IF(VLOOKUP(B9,MAPA_DATA!D:G,2,0)=1,'FACT_EMITIDA',IF(VLOOKUP(B9,MAPA_DATA!D:G,3,0)=1,'FACT_EST_EFACT',(IF(VLOOKUP(B9,MAPA_DATA!D:G,4,0)=1,'FACT_EST_CEN','SIN_DATA')))!H:H) | G9: =CONCATENATE("SUMIF(",IF(C9="FACT_EMITIDA","SIGGE_P",C9),"!B:B,Reliquidacion!B",A9,",",IF(C9="FACT_EMITIDA","SIGGE_P",C9),"!F:F)") -> SUMIF(IF(VLOOKUP(B9,MAPA_DATA!D:G,2,0)=1,'FACT_EMITIDA',IF(VLOOKUP(B9,MAPA_DATA!D:G,3,0)=1,'FACT_EST_EFACT',(IF(VLOOKUP(B9,MAPA_DATA!D:G,4,0)=1,'FACT_EST_CEN','SIN_DATA')))!B:B,Reliquidacion!B9,IF(VLOOKUP(B9,MAPA_DATA!D:G,2,0)=1,'FACT_EMITIDA',IF(VLOOKUP(B9,MAPA_DATA!D:G,3,0)=1,'FACT_EST_EFACT',(IF(VLOOKUP(B9,MAPA_DATA!D:G,4,0)=1,'FACT_EST_CEN','SIN_DATA')))!F:F) | H9: =CONCATENATE("(I",A9,"/G",A9,")") -> (I9/G9) | I9: =CONCATENATE("SUMIF(",IF(C9="FACT_EMITIDA","SIGGE_P",C9),"!B:B,Reliquidacion!B",A9,",",IF(C9="FACT_EMITIDA","SIGGE_P",C9),"!H:H)") -> SUMIF(IF(VLOOKUP(B9,MAPA_DATA!D:G,2,0)=1,'FACT_EMITIDA',IF(VLOOKUP(B9,MAPA_DATA!D:G,3,0)=1,'FACT_EST_EFACT',(IF(VLOOKUP(B9,MAPA_DATA!D:G,4,0)=1,'FACT_EST_CEN','SIN_DATA')))!B:B,Reliquidacion!B9,IF(VLOOKUP(B9,MAPA_DATA!D:G,2,0)=1,'FACT_EMITIDA',IF(VLOOKUP(B9,MAPA_DATA!D:G,3,0)=1,'FACT_EST_EFACT',(IF(VLOOKUP(B9,MAPA_DATA!D:G,4,0)=1,'FACT_EST_CEN','SIN_DATA')))!H:H) | J9: =CONCATENATE("(F",A9,"+I",A9,")") -> (F9+I9) | L9: =IF(VLOOKUP(B9,MAPA_DATA!D:I,5,0)=1,"EFACT_CNE",IF(VLOOKUP(B9,MAPA_DATA!D:I,6,0)=1,"EFACT_EST_CNE","SIN_DATA")) -> SIN_DATA | M9: =CONCATENATE("SUMIF(",L9,"!B:B;Reliquidacion!B",A9,";",L9,"!S:S)") -> SUMIF(SIN_DATA!B:B;Reliquidacion!B9;SIN_DATA!S:S) | N9: =CONCATENATE("(O",A9,"/M",A9,")") -> (O9/M9) | O9: =CONCATENATE("SUMIF(",L9,"!B:B;Reliquidacion!B",A9,";",L9,"!W:W)") -> SUMIF(SIN_DATA!B:B;Reliquidacion!B9;SIN_DATA!W:W) | P9: =CONCATENATE("SUMIF(",L9,"!B:B;Reliquidacion!B",A9,";",L9,"!X:X)") -> SUMIF(SIN_DATA!B:B;Reliquidacion!B9;SIN_DATA!X:X) | Q9: =CONCATENATE("(R",A9,"/P",A9,")") -> (R9/P9) | R9: =CONCATENATE("SUMIF(",L9,"!B:B;Reliquidacion!B",A9,";",L9,"!AB:AB)") -> SUMIF(SIN_DATA!B:B;Reliquidacion!B9;SIN_DATA!AB:AB) | S9: =CONCATENATE("(O",A9,"+R",A9,")") -> (O9+R9) | U9: 42370 | V9: =CONCATENATE("=(S",A9,"-J",A9,")") -> =(S9-J9) | W9: 8T/11-07-2016 | X9: =VLOOKUP(W9,[1]INTERESES!A:B,2,0) -> 0 | Y9: =VLOOKUP(W9,#REF!,6,0) -> #REF! | Z9: 43156 | AA9: 44377 | AB9: =AA9-Z9 -> 1221 | AC9: =+(1+Y9)^(AB9/360)-1 -> #REF! | AD9: =AC9*V9 -> #REF! | AE9: =+V9+AD9 -> #VALUE!
A10: =A9+1 -> 10 | B10: 42401 | C10: =CONCATENATE("IF(VLOOKUP(B9,MAPA_DATA!D:G,2,0)=1,'FACT_EMITIDA',IF(VLOOKUP(B",A10,",MAPA_DATA!D:G,3,0)=1,'FACT_EST_EFACT',(IF(VLOOKUP(B",A10,",MAPA_DATA!D:G,4,0)=1,'FACT_EST_CEN','SIN_DATA')))") -> IF(VLOOKUP(B9,MAPA_DATA!D:G,2,0)=1,'FACT_EMITIDA',IF(VLOOKUP(B10,MAPA_DATA!D:G,3,0)=1,'FACT_EST_EFACT',(IF(VLOOKUP(B10,MAPA_DATA!D:G,4,0)=1,'FACT_EST_CEN','SIN_DATA'))) | D10: =CONCATENATE("SUMIF(",IF(C10="FACT_EMITIDA","SIGGE_E",C10),"!B:B,Reliquidacion!B",A10,",",IF(C10="FACT_EMITIDA","SIGGE_E",C10),"!F:F)") -> SUMIF(IF(VLOOKUP(B9,MAPA_DATA!D:G,2,0)=1,'FACT_EMITIDA',IF(VLOOKUP(B10,MAPA_DATA!D:G,3,0)=1,'FACT_EST_EFACT',(IF(VLOOKUP(B10,MAPA_DATA!D:G,4,0)=1,'FACT_EST_CEN','SIN_DATA')))!B:B,Reliquidacion!B10,IF(VLOOKUP(B9,MAPA_DATA!D:G,2,0)=1,'FACT_EMITIDA',IF(VLOOKUP(B10,MAPA_DATA!D:G,3,0)=1,'FACT_EST_EFACT',(IF(VLOOKUP(B10,MAPA_DATA!D:G,4,0)=1,'FACT_EST_CEN','SIN_DATA')))!F:F) | E10: =CONCATENATE("(F",A10,"/D",A10,")") -> (F10/D10) | F10: =CONCATENATE("SUMIF(",IF(C10="FACT_EMITIDA","SIGGE_E",C10),"!B:B,Reliquidacion!B",A10,",",IF(C10="FACT_EMITIDA","SIGGE_E",C10),"!H:H)") -> SUMIF(IF(VLOOKUP(B9,MAPA_DATA!D:G,2,0)=1,'FACT_EMITIDA',IF(VLOOKUP(B10,MAPA_DATA!D:G,3,0)=1,'FACT_EST_EFACT',(IF(VLOOKUP(B10,MAPA_DATA!D:G,4,0)=1,'FACT_EST_CEN','SIN_DATA')))!B:B,Reliquidacion!B10,IF(VLOOKUP(B9,MAPA_DATA!D:G,2,0)=1,'FACT_EMITIDA',IF(VLOOKUP(B10,MAPA_DATA!D:G,3,0)=1,'FACT_EST_EFACT',(IF(VLOOKUP(B10,MAPA_DATA!D:G,4,0)=1,'FACT_EST_CEN','SIN_DATA')))!H:H) | G10: =CONCATENATE("SUMIF(",IF(C10="FACT_EMITIDA","SIGGE_P",C10),"!B:B,Reliquidacion!B",A10,",",IF(C10="FACT_EMITIDA","SIGGE_P",C10),"!F:F)") -> SUMIF(IF(VLOOKUP(B9,MAPA_DATA!D:G,2,0)=1,'FACT_EMITIDA',IF(VLOOKUP(B10,MAPA_DATA!D:G,3,0)=1,'FACT_EST_EFACT',(IF(VLOOKUP(B10,MAPA_DATA!D:G,4,0)=1,'FACT_EST_CEN','SIN_DATA')))!B:B,Reliquidacion!B10,IF(VLOOKUP(B9,MAPA_DATA!D:G,2,0)=1,'FACT_EMITIDA',IF(VLOOKUP(B10,MAPA_DATA!D:G,3,0)=1,'FACT_EST_EFACT',(IF(VLOOKUP(B10,MAPA_DATA!D:G,4,0)=1,'FACT_EST_CEN','SIN_DATA')))!F:F) | H10: =CONCATENATE("(I",A10,"/G",A10,")") -> (I10/G10) | I10: =CONCATENATE("SUMIF(",IF(C10="FACT_EMITIDA","SIGGE_P",C10),"!B:B,Reliquidacion!B",A10,",",IF(C10="FACT_EMITIDA","SIGGE_P",C10),"!H:H)") -> SUMIF(IF(VLOOKUP(B9,MAPA_DATA!D:G,2,0)=1,'FACT_EMITIDA',IF(VLOOKUP(B10,MAPA_DATA!D:G,3,0)=1,'FACT_EST_EFACT',(IF(VLOOKUP(B10,MAPA_DATA!D:G,4,0)=1,'FACT_EST_CEN','SIN_DATA')))!B:B,Reliquidacion!B10,IF(VLOOKUP(B9,MAPA_DATA!D:G,2,0)=1,'FACT_EMITIDA',IF(VLOOKUP(B10,MAPA_DATA!D:G,3,0)=1,'FACT_EST_EFACT',(IF(VLOOKUP(B10,MAPA_DATA!D:G,4,0)=1,'FACT_EST_CEN','SIN_DATA')))!H:H) | J10: =CONCATENATE("(F",A10,"+I",A10,")") -> (F10+I10) | L10: =IF(VLOOKUP(B10,MAPA_DATA!D:I,5,0)=1,"EFACT_CNE",IF(VLOOKUP(B10,MAPA_DATA!D:I,6,0)=1,"EFACT_EST_CNE","SIN_DATA")) -> SIN_DATA | M10: =CONCATENATE("SUMIF(",L10,"!B:B;Reliquidacion!B",A10,";",L10,"!S:S)") -> SUMIF(SIN_DATA!B:B;Reliquidacion!B10;SIN_DATA!S:S) | N10: =CONCATENATE("(O",A10,"/M",A10,")") -> (O10/M10) | O10: =CONCATENATE("SUMIF(",L10,"!B:B;Reliquidacion!B",A10,";",L10,"!W:W)") -> SUMIF(SIN_DATA!B:B;Reliquidacion!B10;SIN_DATA!W:W) | P10: =CONCATENATE("SUMIF(",L10,"!B:B;Reliquidacion!B",A10,";",L10,"!X:X)") -> SUMIF(SIN_DATA!B:B;Reliquidacion!B10;SIN_DATA!X:X) | Q10: =CONCATENATE("(R",A10,"/P",A10,")") -> (R10/P10) | R10: =CONCATENATE("SUMIF(",L10,"!B:B;Reliquidacion!B",A10,";",L10,"!AB:AB)") -> SUMIF(SIN_DATA!B:B;Reliquidacion!B10;SIN_DATA!AB:AB) | S10: =CONCATENATE("(O",A10,"+R",A10,")") -> (O10+R10) | U10: 42401 | V10: =CONCATENATE("=(S",A10,"-J",A10,")") -> =(S10-J10) | W10: 8T/11-07-2016 | X10: =VLOOKUP(W10,[1]INTERESES!A:B,2,0) -> 0 | Y10: =VLOOKUP(W10,#REF!,6,0) -> #REF! | Z10: 43156 | AA10: 44377 | AB10: =AA10-Z10 -> 1221 | AC10: =+(1+Y10)^(AB10/360)-1 -> #REF! | AD10: =AC10*V10 -> #REF! | AE10: =+V10+AD10 -> #VALUE!
A11: =A10+1 -> 11 | B11: 42430 | C11: =CONCATENATE("IF(VLOOKUP(B9,MAPA_DATA!D:G,2,0)=1,'FACT_EMITIDA',IF(VLOOKUP(B",A11,",MAPA_DATA!D:G,3,0)=1,'FACT_EST_EFACT',(IF(VLOOKUP(B",A11,",MAPA_DATA!D:G,4,0)=1,'FACT_EST_CEN','SIN_DATA')))") -> IF(VLOOKUP(B9,MAPA_DATA!D:G,2,0)=1,'FACT_EMITIDA',IF(VLOOKUP(B11,MAPA_DATA!D:G,3,0)=1,'FACT_EST_EFACT',(IF(VLOOKUP(B11,MAPA_DATA!D:G,4,0)=1,'FACT_EST_CEN','SIN_DATA'))) | D11: =CONCATENATE("SUMIF(",IF(C11="FACT_EMITIDA","SIGGE_E",C11),"!B:B,Reliquidacion!B",A11,",",IF(C11="FACT_EMITIDA","SIGGE_E",C11),"!F:F)") -> SUMIF(IF(VLOOKUP(B9,MAPA_DATA!D:G,2,0)=1,'FACT_EMITIDA',IF(VLOOKUP(B11,MAPA_DATA!D:G,3,0)=1,'FACT_EST_EFACT',(IF(VLOOKUP(B11,MAPA_DATA!D:G,4,0)=1,'FACT_EST_CEN','SIN_DATA')))!B:B,Reliquidacion!B11,IF(VLOOKUP(B9,MAPA_DATA!D:G,2,0)=1,'FACT_EMITIDA',IF(VLOOKUP(B11,MAPA_DATA!D:G,3,0)=1,'FACT_EST_EFACT',(IF(VLOOKUP(B11,MAPA_DATA!D:G,4,0)=1,'FACT_EST_CEN','SIN_DATA')))!F:F) | E11: =CONCATENATE("(F",A11,"/D",A11,")") -> (F11/D11) | F11: =CONCATENATE("SUMIF(",IF(C11="FACT_EMITIDA","SIGGE_E",C11),"!B:B,Reliquidacion!B",A11,",",IF(C11="FACT_EMITIDA","SIGGE_E",C11),"!H:H)") -> SUMIF(IF(VLOOKUP(B9,MAPA_DATA!D:G,2,0)=1,'FACT_EMITIDA',IF(VLOOKUP(B11,MAPA_DATA!D:G,3,0)=1,'FACT_EST_EFACT',(IF(VLOOKUP(B11,MAPA_DATA!D:G,4,0)=1,'FACT_EST_CEN','SIN_DATA')))!B:B,Reliquidacion!B11,IF(VLOOKUP(B9,MAPA_DATA!D:G,2,0)=1,'FACT_EMITIDA',IF(VLOOKUP(B11,MAPA_DATA!D:G,3,0)=1,'FACT_EST_EFACT',(IF(VLOOKUP(B11,MAPA_DATA!D:G,4,0)=1,'FACT_EST_CEN','SIN_DATA')))!H:H) | G11: =CONCATENATE("SUMIF(",IF(C11="FACT_EMITIDA","SIGGE_P",C11),"!B:B,Reliquidacion!B",A11,",",IF(C11="FACT_EMITIDA","SIGGE_P",C11),"!F:F)") -> SUMIF(IF(VLOOKUP(B9,MAPA_DATA!D:G,2,0)=1,'FACT_EMITIDA',IF(VLOOKUP(B11,MAPA_DATA!D:G,3,0)=1,'FACT_EST_EFACT',(IF(VLOOKUP(B11,MAPA_DATA!D:G,4,0)=1,'FACT_EST_CEN','SIN_DATA')))!B:B,Reliquidacion!B11,IF(VLOOKUP(B9,MAPA_DATA!D:G,2,0)=1,'FACT_EMITIDA',IF(VLOOKUP(B11,MAPA_DATA!D:G,3,0)=1,'FACT_EST_EFACT',(IF(VLOOKUP(B11,MAPA_DATA!D:G,4,0)=1,'FACT_EST_CEN','SIN_DATA')))!F:F) | H11: =CONCATENATE("(I",A11,"/G",A11,")") -> (I11/G11) | I11: =CONCATENATE("SUMIF(",IF(C11="FACT_EMITIDA","SIGGE_P",C11),"!B:B,Reliquidacion!B",A11,",",IF(C11="FACT_EMITIDA","SIGGE_P",C11),"!H:H)") -> SUMIF(IF(VLOOKUP(B9,MAPA_DATA!D:G,2,0)=1,'FACT_EMITIDA',IF(VLOOKUP(B11,MAPA_DATA!D:G,3,0)=1,'FACT_EST_EFACT',(IF(VLOOKUP(B11,MAPA_DATA!D:G,4,0)=1,'FACT_EST_CEN','SIN_DATA')))!B:B,Reliquidacion!B11,IF(VLOOKUP(B9,MAPA_DATA!D:G,2,0)=1,'FACT_EMITIDA',IF(VLOOKUP(B11,MAPA_DATA!D:G,3,0)=1,'FACT_EST_EFACT',(IF(VLOOKUP(B11,MAPA_DATA!D:G,4,0)=1,'FACT_EST_CEN','SIN_DATA')))!H:H) | J11: =CONCATENATE("(F",A11,"+I",A11,")") -> (F11+I11) | L11: =IF(VLOOKUP(B11,MAPA_DATA!D:I,5,0)=1,"EFACT_CNE",IF(VLOOKUP(B11,MAPA_DATA!D:I,6,0)=1,"EFACT_EST_CNE","SIN_DATA")) -> SIN_DATA | M11: =CONCATENATE("SUMIF(",L11,"!B:B;Reliquidacion!B",A11,";",L11,"!S:S)") -> SUMIF(SIN_DATA!B:B;Reliquidacion!B11;SIN_DATA!S:S) | N11: =CONCATENATE("(O",A11,"/M",A11,")") -> (O11/M11) | O11: =CONCATENATE("SUMIF(",L11,"!B:B;Reliquidacion!B",A11,";",L11,"!W:W)") -> SUMIF(SIN_DATA!B:B;Reliquidacion!B11;SIN_DATA!W:W) | P11: =CONCATENATE("SUMIF(",L11,"!B:B;Reliquidacion!B",A11,";",L11,"!X:X)") -> SUMIF(SIN_DATA!B:B;Reliquidacion!B11;SIN_DATA!X:X) | Q11: =CONCATENATE("(R",A11,"/P",A11,")") -> (R11/P11) | R11: =CONCATENATE("SUMIF(",L11,"!B:B;Reliquidacion!B",A11,";",L11,"!AB:AB)") -> SUMIF(SIN_DATA!B:B;Reliquidacion!B11;SIN_DATA!AB:AB) | S11: =CONCATENATE("(O",A11,"+R",A11,")") -> (O11+R11) | U11: 42430 | V11: =CONCATENATE("=(S",A11,"-J",A11,")") -> =(S11-J11) | W11: 12T/20-12-2016 | X11: =VLOOKUP(W11,[1]INTERESES!A:B,2,0) -> 0 | Y11: =VLOOKUP(W11,#REF!,6,0) -> #REF! | Z11: 43156 | AA11: 44377 | AB11: =AA11-Z11 -> 1221 | AC11: =+(1+Y11)^(AB11/360)-1 -> #REF! | AD11: =AC11*V11 -> #REF! | AE11: =+V11+AD11 -> #VALUE!
A12: =A11+1 -> 12 | B12: 42461 | C12: =CONCATENATE("IF(VLOOKUP(B9,MAPA_DATA!D:G,2,0)=1,'FACT_EMITIDA',IF(VLOOKUP(B",A12,",MAPA_DATA!D:G,3,0)=1,'FACT_EST_EFACT',(IF(VLOOKUP(B",A12,",MAPA_DATA!D:G,4,0)=1,'FACT_EST_CEN','SIN_DATA')))") -> IF(VLOOKUP(B9,MAPA_DATA!D:G,2,0)=1,'FACT_EMITIDA',IF(VLOOKUP(B12,MAPA_DATA!D:G,3,0)=1,'FACT_EST_EFACT',(IF(VLOOKUP(B12,MAPA_DATA!D:G,4,0)=1,'FACT_EST_CEN','SIN_DATA'))) | D12: =CONCATENATE("SUMIF(",IF(C12="FACT_EMITIDA","SIGGE_E",C12),"!B:B,Reliquidacion!B",A12,",",IF(C12="FACT_EMITIDA","SIGGE_E",C12),"!F:F)") -> SUMIF(IF(VLOOKUP(B9,MAPA_DATA!D:G,2,0)=1,'FACT_EMITIDA',IF(VLOOKUP(B12,MAPA_DATA!D:G,3,0)=1,'FACT_EST_EFACT',(IF(VLOOKUP(B12,MAPA_DATA!D:G,4,0)=1,'FACT_EST_CEN','SIN_DATA')))!B:B,Reliquidacion!B12,IF(VLOOKUP(B9,MAPA_DATA!D:G,2,0)=1,'FACT_EMITIDA',IF(VLOOKUP(B12,MAPA_DATA!D:G,3,0)=1,'FACT_EST_EFACT',(IF(VLOOKUP(B12,MAPA_DATA!D:G,4,0)=1,'FACT_EST_CEN','SIN_DATA')))!F:F) | E12: =CONCATENATE("(F",A12,"/D",A12,")") -> (F12/D12) | F12: =CONCATENATE("SUMIF(",IF(C12="FACT_EMITIDA","SIGGE_E",C12),"!B:B,Reliquidacion!B",A12,",",IF(C12="FACT_EMITIDA","SIGGE_E",C12),"!H:H)") -> SUMIF(IF(VLOOKUP(B9,MAPA_DATA!D:G,2,0)=1,'FACT_EMITIDA',IF(VLOOKUP(B12,MAPA_DATA!D:G,3,0)=1,'FACT_EST_EFACT',(IF(VLOOKUP(B12,MAPA_DATA!D:G,4,0)=1,'FACT_EST_CEN','SIN_DATA')))!B:B,Reliquidacion!B12,IF(VLOOKUP(B9,MAPA_DATA!D:G,2,0)=1,'FACT_EMITIDA',IF(VLOOKUP(B12,MAPA_DATA!D:G,3,0)=1,'FACT_EST_EFACT',(IF(VLOOKUP(B12,MAPA_DATA!D:G,4,0)=1,'FACT_EST_CEN','SIN_DATA')))!H:H) | G12: =CONCATENATE("SUMIF(",IF(C12="FACT_EMITIDA","SIGGE_P",C12),"!B:B,Reliquidacion!B",A12,",",IF(C12="FACT_EMITIDA","SIGGE_P",C12),"!F:F)") -> SUMIF(IF(VLOOKUP(B9,MAPA_DATA!D:G,2,0)=1,'FACT_EMITIDA',IF(VLOOKUP(B12,MAPA_DATA!D:G,3,0)=1,'FACT_EST_EFACT',(IF(VLOOKUP(B12,MAPA_DATA!D:G,4,0)=1,'FACT_EST_CEN','SIN_DATA')))!B:B,Reliquidacion!B12,IF(VLOOKUP(B9,MAPA_DATA!D:G,2,0)=1,'FACT_EMITIDA',IF(VLOOKUP(B12,MAPA_DATA!D:G,3,0)=1,'FACT_EST_EFACT',(IF(VLOOKUP(B12,MAPA_DATA!D:G,4,0)=1,'FACT_EST_CEN','SIN_DATA')))!F:F) | H12: =CONCATENATE("(I",A12,"/G",A12,")") -> (I12/G12) | I12: =CONCATENATE("SUMIF(",IF(C12="FACT_EMITIDA","SIGGE_P",C12),"!B:B,Reliquidacion!B",A12,",",IF(C12="FACT_EMITIDA","SIGGE_P",C12),"!H:H)") -> SUMIF(IF(VLOOKUP(B9,MAPA_DATA!D:G,2,0)=1,'FACT_EMITIDA',IF(VLOOKUP(B12,MAPA_DATA!D:G,3,0)=1,'FACT_EST_EFACT',(IF(VLOOKUP(B12,MAPA_DATA!D:G,4,0)=1,'FACT_EST_CEN','SIN_DATA')))!B:B,Reliquidacion!B12,IF(VLOOKUP(B9,MAPA_DATA!D:G,2,0)=1,'FACT_EMITIDA',IF(VLOOKUP(B12,MAPA_DATA!D:G,3,0)=1,'FACT_EST_EFACT',(IF(VLOOKUP(B12,MAPA_DATA!D:G,4,0)=1,'FACT_EST_CEN','SIN_DATA')))!H:H) | J12: =CONCATENATE("(F",A12,"+I",A12,")") -> (F12+I12) | L12: =IF(VLOOKUP(B12,MAPA_DATA!D:I,5,0)=1,"EFACT_CNE",IF(VLOOKUP(B12,MAPA_DATA!D:I,6,0)=1,"EFACT_EST_CNE","SIN_DATA")) -> SIN_DATA | M12: =CONCATENATE("SUMIF(",L12,"!B:B;Reliquidacion!B",A12,";",L12,"!S:S)") -> SUMIF(SIN_DATA!B:B;Reliquidacion!B12;SIN_DATA!S:S) | N12: =CONCATENATE("(O",A12,"/M",A12,")") -> (O12/M12) | O12: =CONCATENATE("SUMIF(",L12,"!B:B;Reliquidacion!B",A12,";",L12,"!W:W)") -> SUMIF(SIN_DATA!B:B;Reliquidacion!B12;SIN_DATA!W:W) | P12: =CONCATENATE("SUMIF(",L12,"!B:B;Reliquidacion!B",A12,";",L12,"!X:X)") -> SUMIF(SIN_DATA!B:B;Reliquidacion!B12;SIN_DATA!X:X) | Q12: =CONCATENATE("(R",A12,"/P",A12,")") -> (R12/P12) | R12: =CONCATENATE("SUMIF(",L12,"!B:B;Reliquidacion!B",A12,";",L12,"!AB:AB)") -> SUMIF(SIN_DATA!B:B;Reliquidacion!B12;SIN_DATA!AB:AB) | S12: =CONCATENATE("(O",A12,"+R",A12,")") -> (O12+R12) | U12: 42461 | V12: =CONCATENATE("=(S",A12,"-J",A12,")") -> =(S12-J12) | W12: 12T/20-12-2016 | X12: =VLOOKUP(W12,[1]INTERESES!A:B,2,0) -> 0 | Y12: =VLOOKUP(W12,#REF!,6,0) -> #REF! | Z12: 43156 | AA12: 44377 | AB12: =AA12-Z12 -> 1221 | AC12: =+(1+Y12)^(AB12/360)-1 -> #REF! | AD12: =AC12*V12 -> #REF! | AE12: =+V12+AD12 -> #VALUE!
A13: =A12+1 -> 13 | B13: 42491 | C13: =CONCATENATE("IF(VLOOKUP(B9,MAPA_DATA!D:G,2,0)=1,'FACT_EMITIDA',IF(VLOOKUP(B",A13,",MAPA_DATA!D:G,3,0)=1,'FACT_EST_EFACT',(IF(VLOOKUP(B",A13,",MAPA_DATA!D:G,4,0)=1,'FACT_EST_CEN','SIN_DATA')))") -> IF(VLOOKUP(B9,MAPA_DATA!D:G,2,0)=1,'FACT_EMITIDA',IF(VLOOKUP(B13,MAPA_DATA!D:G,3,0)=1,'FACT_EST_EFACT',(IF(VLOOKUP(B13,MAPA_DATA!D:G,4,0)=1,'FACT_EST_CEN','SIN_DATA'))) | D13: =CONCATENATE("SUMIF(",IF(C13="FACT_EMITIDA","SIGGE_E",C13),"!B:B,Reliquidacion!B",A13,",",IF(C13="FACT_EMITIDA","SIGGE_E",C13),"!F:F)") -> SUMIF(IF(VLOOKUP(B9,MAPA_DATA!D:G,2,0)=1,'FACT_EMITIDA',IF(VLOOKUP(B13,MAPA_DATA!D:G,3,0)=1,'FACT_EST_EFACT',(IF(VLOOKUP(B13,MAPA_DATA!D:G,4,0)=1,'FACT_EST_CEN','SIN_DATA')))!B:B,Reliquidacion!B13,IF(VLOOKUP(B9,MAPA_DATA!D:G,2,0)=1,'FACT_EMITIDA',IF(VLOOKUP(B13,MAPA_DATA!D:G,3,0)=1,'FACT_EST_EFACT',(IF(VLOOKUP(B13,MAPA_DATA!D:G,4,0)=1,'FACT_EST_CEN','SIN_DATA')))!F:F) | E13: =CONCATENATE("(F",A13,"/D",A13,")") -> (F13/D13) | F13: =CONCATENATE("SUMIF(",IF(C13="FACT_EMITIDA","SIGGE_E",C13),"!B:B,Reliquidacion!B",A13,",",IF(C13="FACT_EMITIDA","SIGGE_E",C13),"!H:H)") -> SUMIF(IF(VLOOKUP(B9,MAPA_DATA!D:G,2,0)=1,'FACT_EMITIDA',IF(VLOOKUP(B13,MAPA_DATA!D:G,3,0)=1,'FACT_EST_EFACT',(IF(VLOOKUP(B13,MAPA_DATA!D:G,4,0)=1,'FACT_EST_CEN','SIN_DATA')))!B:B,Reliquidacion!B13,IF(VLOOKUP(B9,MAPA_DATA!D:G,2,0)=1,'FACT_EMITIDA',IF(VLOOKUP(B13,MAPA_DATA!D:G,3,0)=1,'FACT_EST_EFACT',(IF(VLOOKUP(B13,MAPA_DATA!D:G,4,0)=1,'FACT_EST_CEN','SIN_DATA')))!H:H) | G13: =CONCATENATE("SUMIF(",IF(C13="FACT_EMITIDA","SIGGE_P",C13),"!B:B,Reliquidacion!B",A13,",",IF(C13="FACT_EMITIDA","SIGGE_P",C13),"!F:F)") -> SUMIF(IF(VLOOKUP(B9,MAPA_DATA!D:G,2,0)=1,'FACT_EMITIDA',IF(VLOOKUP(B13,MAPA_DATA!D:G,3,0)=1,'FACT_EST_EFACT',(IF(VLOOKUP(B13,MAPA_DATA!D:G,4,0)=1,'FACT_EST_CEN','SIN_DATA')))!B:B,Reliquidacion!B13,IF(VLOOKUP(B9,MAPA_DATA!D:G,2,0)=1,'FACT_EMITIDA',IF(VLOOKUP(B13,MAPA_DATA!D:G,3,0)=1,'FACT_EST_EFACT',(IF(VLOOKUP(B13,MAPA_DATA!D:G,4,0)=1,'FACT_EST_CEN','SIN_DATA')))!F:F) | H13: =CONCATENATE("(I",A13,"/G",A13,")") -> (I13/G13) | I13: =CONCATENATE("SUMIF(",IF(C13="FACT_EMITIDA","SIGGE_P",C13),"!B:B,Reliquidacion!B",A13,",",IF(C13="FACT_EMITIDA","SIGGE_P",C13),"!H:H)") -> SUMIF(IF(VLOOKUP(B9,MAPA_DATA!D:G,2,0)=1,'FACT_EMITIDA',IF(VLOOKUP(B13,MAPA_DATA!D:G,3,0)=1,'FACT_EST_EFACT',(IF(VLOOKUP(B13,MAPA_DATA!D:G,4,0)=1,'FACT_EST_CEN','SIN_DATA')))!B:B,Reliquidacion!B13,IF(VLOOKUP(B9,MAPA_DATA!D:G,2,0)=1,'FACT_EMITIDA',IF(VLOOKUP(B13,MAPA_DATA!D:G,3,0)=1,'FACT_EST_EFACT',(IF(VLOOKUP(B13,MAPA_DATA!D:G,4,0)=1,'FACT_EST_CEN','SIN_DATA')))!H:H) | J13: =CONCATENATE("(F",A13,"+I",A13,")") -> (F13+I13) | L13: =IF(VLOOKUP(B13,MAPA_DATA!D:I,5,0)=1,"EFACT_CNE",IF(VLOOKUP(B13,MAPA_DATA!D:I,6,0)=1,"EFACT_EST_CNE","SIN_DATA")) -> SIN_DATA | M13: =CONCATENATE("SUMIF(",L13,"!B:B;Reliquidacion!B",A13,";",L13,"!S:S)") -> SUMIF(SIN_DATA!B:B;Reliquidacion!B13;SIN_DATA!S:S) | N13: =CONCATENATE("(O",A13,"/M",A13,")") -> (O13/M13) | O13: =CONCATENATE("SUMIF(",L13,"!B:B;Reliquidacion!B",A13,";",L13,"!W:W)") -> SUMIF(SIN_DATA!B:B;Reliquidacion!B13;SIN_DATA!W:W) | P13: =CONCATENATE("SUMIF(",L13,"!B:B;Reliquidacion!B",A13,";",L13,"!X:X)") -> SUMIF(SIN_DATA!B:B;Reliquidacion!B13;SIN_DATA!X:X) | Q13: =CONCATENATE("(R",A13,"/P",A13,")") -> (R13/P13) | R13: =CONCATENATE("SUMIF(",L13,"!B:B;Reliquidacion!B",A13,";",L13,"!AB:AB)") -> SUMIF(SIN_DATA!B:B;Reliquidacion!B13;SIN_DATA!AB:AB) | S13: =CONCATENATE("(O",A13,"+R",A13,")") -> (O13+R13) | U13: 42491 | V13: =CONCATENATE("=(S",A13,"-J",A13,")") -> =(S13-J13) | W13: 3T/15-05-2017 | X13: =VLOOKUP(W13,[1]INTERESES!A:B,2,0) -> 0 | Y13: =VLOOKUP(W13,#REF!,6,0) -> #REF! | Z13: 43156 | AA13: 44377 | AB13: =AA13-Z13 -> 1221 | AC13: =+(1+Y13)^(AB13/360)-1 -> #REF! | AD13: =AC13*V13 -> #REF! | AE13: =+V13+AD13 -> #VALUE!
A14: =A13+1 -> 14 | B14: 42522 | C14: =CONCATENATE("IF(VLOOKUP(B9,MAPA_DATA!D:G,2,0)=1,'FACT_EMITIDA',IF(VLOOKUP(B",A14,",MAPA_DATA!D:G,3,0)=1,'FACT_EST_EFACT',(IF(VLOOKUP(B",A14,",MAPA_DATA!D:G,4,0)=1,'FACT_EST_CEN','SIN_DATA')))") -> IF(VLOOKUP(B9,MAPA_DATA!D:G,2,0)=1,'FACT_EMITIDA',IF(VLOOKUP(B14,MAPA_DATA!D:G,3,0)=1,'FACT_EST_EFACT',(IF(VLOOKUP(B14,MAPA_DATA!D:G,4,0)=1,'FACT_EST_CEN','SIN_DATA'))) | D14: =CONCATENATE("SUMIF(",IF(C14="FACT_EMITIDA","SIGGE_E",C14),"!B:B,Reliquidacion!B",A14,",",IF(C14="FACT_EMITIDA","SIGGE_E",C14),"!F:F)") -> SUMIF(IF(VLOOKUP(B9,MAPA_DATA!D:G,2,0)=1,'FACT_EMITIDA',IF(VLOOKUP(B14,MAPA_DATA!D:G,3,0)=1,'FACT_EST_EFACT',(IF(VLOOKUP(B14,MAPA_DATA!D:G,4,0)=1,'FACT_EST_CEN','SIN_DATA')))!B:B,Reliquidacion!B14,IF(VLOOKUP(B9,MAPA_DATA!D:G,2,0)=1,'FACT_EMITIDA',IF(VLOOKUP(B14,MAPA_DATA!D:G,3,0)=1,'FACT_EST_EFACT',(IF(VLOOKUP(B14,MAPA_DATA!D:G,4,0)=1,'FACT_EST_CEN','SIN_DATA')))!F:F) | E14: =CONCATENATE("(F",A14,"/D",A14,")") -> (F14/D14) | F14: =CONCATENATE("SUMIF(",IF(C14="FACT_EMITIDA","SIGGE_E",C14),"!B:B,Reliquidacion!B",A14,",",IF(C14="FACT_EMITIDA","SIGGE_E",C14),"!H:H)") -> SUMIF(IF(VLOOKUP(B9,MAPA_DATA!D:G,2,0)=1,'FACT_EMITIDA',IF(VLOOKUP(B14,MAPA_DATA!D:G,3,0)=1,'FACT_EST_EFACT',(IF(VLOOKUP(B14,MAPA_DATA!D:G,4,0)=1,'FACT_EST_CEN','SIN_DATA')))!B:B,Reliquidacion!B14,IF(VLOOKUP(B9,MAPA_DATA!D:G,2,0)=1,'FACT_EMITIDA',IF(VLOOKUP(B14,MAPA_DATA!D:G,3,0)=1,'FACT_EST_EFACT',(IF(VLOOKUP(B14,MAPA_DATA!D:G,4,0)=1,'FACT_EST_CEN','SIN_DATA')))!H:H) | G14: =CONCATENATE("SUMIF(",IF(C14="FACT_EMITIDA","SIGGE_P",C14),"!B:B,Reliquidacion!B",A14,",",IF(C14="FACT_EMITIDA","SIGGE_P",C14),"!F:F)") -> SUMIF(IF(VLOOKUP(B9,MAPA_DATA!D:G,2,0)=1,'FACT_EMITIDA',IF(VLOOKUP(B14,MAPA_DATA!D:G,3,0)=1,'FACT_EST_EFACT',(IF(VLOOKUP(B14,MAPA_DATA!D:G,4,0)=1,'FACT_EST_CEN','SIN_DATA')))!B:B,Reliquidacion!B14,IF(VLOOKUP(B9,MAPA_DATA!D:G,2,0)=1,'FACT_EMITIDA',IF(VLOOKUP(B14,MAPA_DATA!D:G,3,0)=1,'FACT_EST_EFACT',(IF(VLOOKUP(B14,MAPA_DATA!D:G,4,0)=1,'FACT_EST_CEN','SIN_DATA')))!F:F) | H14: =CONCATENATE("(I",A14,"/G",A14,")") -> (I14/G14) | I14: =CONCATENATE("SUMIF(",IF(C14="FACT_EMITIDA","SIGGE_P",C14),"!B:B,Reliquidacion!B",A14,",",IF(C14="FACT_EMITIDA","SIGGE_P",C14),"!H:H)") -> SUMIF(IF(VLOOKUP(B9,MAPA_DATA!D:G,2,0)=1,'FACT_EMITIDA',IF(VLOOKUP(B14,MAPA_DATA!D:G,3,0)=1,'FACT_EST_EFACT',(IF(VLOOKUP(B14,MAPA_DATA!D:G,4,0)=1,'FACT_EST_CEN','SIN_DATA')))!B:B,Reliquidacion!B14,IF(VLOOKUP(B9,MAPA_DATA!D:G,2,0)=1,'FACT_EMITIDA',IF(VLOOKUP(B14,MAPA_DATA!D:G,3,0)=1,'FACT_EST_EFACT',(IF(VLOOKUP(B14,MAPA_DATA!D:G,4,0)=1,'FACT_EST_CEN','SIN_DATA')))!H:H) | J14: =CONCATENATE("(F",A14,"+I",A14,")") -> (F14+I14) | L14: =IF(VLOOKUP(B14,MAPA_DATA!D:I,5,0)=1,"EFACT_CNE",IF(VLOOKUP(B14,MAPA_DATA!D:I,6,0)=1,"EFACT_EST_CNE","SIN_DATA")) -> SIN_DATA | M14: =CONCATENATE("SUMIF(",L14,"!B:B;Reliquidacion!B",A14,";",L14,"!S:S)") -> SUMIF(SIN_DATA!B:B;Reliquidacion!B14;SIN_DATA!S:S) | N14: =CONCATENATE("(O",A14,"/M",A14,")") -> (O14/M14) | O14: =CONCATENATE("SUMIF(",L14,"!B:B;Reliquidacion!B",A14,";",L14,"!W:W)") -> SUMIF(SIN_DATA!B:B;Reliquidacion!B14;SIN_DATA!W:W) | P14: =CONCATENATE("SUMIF(",L14,"!B:B;Reliquidacion!B",A14,";",L14,"!X:X)") -> SUMIF(SIN_DATA!B:B;Reliquidacion!B14;SIN_DATA!X:X) | Q14: =CONCATENATE("(R",A14,"/P",A14,")") -> (R14/P14) | R14: =CONCATENATE("SUMIF(",L14,"!B:B;Reliquidacion!B",A14,";",L14,"!AB:AB)") -> SUMIF(SIN_DATA!B:B;Reliquidacion!B14;SIN_DATA!AB:AB) | S14: =CONCATENATE("(O",A14,"+R",A14,")") -> (O14+R14) | U14: 42522 | V14: =CONCATENATE("=(S",A14,"-J",A14,")") -> =(S14-J14) | W14: 3T/15-05-2017 | X14: =VLOOKUP(W14,[1]INTERESES!A:B,2,0) -> 0 | Y14: =VLOOKUP(W14,#REF!,6,0) -> #REF! | Z14: 43156 | AA14: 44377 | AB14: =AA14-Z14 -> 1221 | AC14: =+(1+Y14)^(AB14/360)-1 -> #REF! | AD14: =AC14*V14 -> #REF! | AE14: =+V14+AD14 -> #VALUE!
A15: =A14+1 -> 15 | B15: 42552 | C15: =CONCATENATE("IF(VLOOKUP(B9,MAPA_DATA!D:G,2,0)=1,'FACT_EMITIDA',IF(VLOOKUP(B",A15,",MAPA_DATA!D:G,3,0)=1,'FACT_EST_EFACT',(IF(VLOOKUP(B",A15,",MAPA_DATA!D:G,4,0)=1,'FACT_EST_CEN','SIN_DATA')))") -> IF(VLOOKUP(B9,MAPA_DATA!D:G,2,0)=1,'FACT_EMITIDA',IF(VLOOKUP(B15,MAPA_DATA!D:G,3,0)=1,'FACT_EST_EFACT',(IF(VLOOKUP(B15,MAPA_DATA!D:G,4,0)=1,'FACT_EST_CEN','SIN_DATA'))) | D15: =CONCATENATE("SUMIF(",IF(C15="FACT_EMITIDA","SIGGE_E",C15),"!B:B,Reliquidacion!B",A15,",",IF(C15="FACT_EMITIDA","SIGGE_E",C15),"!F:F)") -> SUMIF(IF(VLOOKUP(B9,MAPA_DATA!D:G,2,0)=1,'FACT_EMITIDA',IF(VLOOKUP(B15,MAPA_DATA!D:G,3,0)=1,'FACT_EST_EFACT',(IF(VLOOKUP(B15,MAPA_DATA!D:G,4,0)=1,'FACT_EST_CEN','SIN_DATA')))!B:B,Reliquidacion!B15,IF(VLOOKUP(B9,MAPA_DATA!D:G,2,0)=1,'FACT_EMITIDA',IF(VLOOKUP(B15,MAPA_DATA!D:G,3,0)=1,'FACT_EST_EFACT',(IF(VLOOKUP(B15,MAPA_DATA!D:G,4,0)=1,'FACT_EST_CEN','SIN_DATA')))!F:F) | E15: =CONCATENATE("(F",A15,"/D",A15,")") -> (F15/D15) | F15: =CONCATENATE("SUMIF(",IF(C15="FACT_EMITIDA","SIGGE_E",C15),"!B:B,Reliquidacion!B",A15,",",IF(C15="FACT_EMITIDA","SIGGE_E",C15),"!H:H)") -> SUMIF(IF(VLOOKUP(B9,MAPA_DATA!D:G,2,0)=1,'FACT_EMITIDA',IF(VLOOKUP(B15,MAPA_DATA!D:G,3,0)=1,'FACT_EST_EFACT',(IF(VLOOKUP(B15,MAPA_DATA!D:G,4,0)=1,'FACT_EST_CEN','SIN_DATA')))!B:B,Reliquidacion!B15,IF(VLOOKUP(B9,MAPA_DATA!D:G,2,0)=1,'FACT_EMITIDA',IF(VLOOKUP(B15,MAPA_DATA!D:G,3,0)=1,'FACT_EST_EFACT',(IF(VLOOKUP(B15,MAPA_DATA!D:G,4,0)=1,'FACT_EST_CEN','SIN_DATA')))!H:H) | G15: =CONCATENATE("SUMIF(",IF(C15="FACT_EMITIDA","SIGGE_P",C15),"!B:B,Reliquidacion!B",A15,",",IF(C15="FACT_EMITIDA","SIGGE_P",C15),"!F:F)") -> SUMIF(IF(VLOOKUP(B9,MAPA_DATA!D:G,2,0)=1,'FACT_EMITIDA',IF(VLOOKUP(B15,MAPA_DATA!D:G,3,0)=1,'FACT_EST_EFACT',(IF(VLOOKUP(B15,MAPA_DATA!D:G,4,0)=1,'FACT_EST_CEN','SIN_DATA')))!B:B,Reliquidacion!B15,IF(VLOOKUP(B9,MAPA_DATA!D:G,2,0)=1,'FACT_EMITIDA',IF(VLOOKUP(B15,MAPA_DATA!D:G,3,0)=1,'FACT_EST_EFACT',(IF(VLOOKUP(B15,MAPA_DATA!D:G,4,0)=1,'FACT_EST_CEN','SIN_DATA')))!F:F) | H15: =CONCATENATE("(I",A15,"/G",A15,")") -> (I15/G15) | I15: =CONCATENATE("SUMIF(",IF(C15="FACT_EMITIDA","SIGGE_P",C15),"!B:B,Reliquidacion!B",A15,",",IF(C15="FACT_EMITIDA","SIGGE_P",C15),"!H:H)") -> SUMIF(IF(VLOOKUP(B9,MAPA_DATA!D:G,2,0)=1,'FACT_EMITIDA',IF(VLOOKUP(B15,MAPA_DATA!D:G,3,0)=1,'FACT_EST_EFACT',(IF(VLOOKUP(B15,MAPA_DATA!D:G,4,0)=1,'FACT_EST_CEN','SIN_DATA')))!B:B,Reliquidacion!B15,IF(VLOOKUP(B9,MAPA_DATA!D:G,2,0)=1,'FACT_EMITIDA',IF(VLOOKUP(B15,MAPA_DATA!D:G,3,0)=1,'FACT_EST_EFACT',(IF(VLOOKUP(B15,MAPA_DATA!D:G,4,0)=1,'FACT_EST_CEN','SIN_DATA')))!H:H) | J15: =CONCATENATE("(F",A15,"+I",A15,")") -> (F15+I15) | L15: =IF(VLOOKUP(B15,MAPA_DATA!D:I,5,0)=1,"EFACT_CNE",IF(VLOOKUP(B15,MAPA_DATA!D:I,6,0)=1,"EFACT_EST_CNE","SIN_DATA")) -> SIN_DATA | M15: =CONCATENATE("SUMIF(",L15,"!B:B;Reliquidacion!B",A15,";",L15,"!S:S)") -> SUMIF(SIN_DATA!B:B;Reliquidacion!B15;SIN_DATA!S:S) | N15: =CONCATENATE("(O",A15,"/M",A15,")") -> (O15/M15) | O15: =CONCATENATE("SUMIF(",L15,"!B:B;Reliquidacion!B",A15,";",L15,"!W:W)") -> SUMIF(SIN_DATA!B:B;Reliquidacion!B15;SIN_DATA!W:W) | P15: =CONCATENATE("SUMIF(",L15,"!B:B;Reliquidacion!B",A15,";",L15,"!X:X)") -> SUMIF(SIN_DATA!B:B;Reliquidacion!B15;SIN_DATA!X:X) | Q15: =CONCATENATE("(R",A15,"/P",A15,")") -> (R15/P15) | R15: =CONCATENATE("SUMIF(",L15,"!B:B;Reliquidacion!B",A15,";",L15,"!AB:AB)") -> SUMIF(SIN_DATA!B:B;Reliquidacion!B15;SIN_DATA!AB:AB) | S15: =CONCATENATE("(O",A15,"+R",A15,")") -> (O15+R15) | U15: 42552 | V15: =CONCATENATE("=(S",A15,"-J",A15,")") -> =(S15-J15) | W15: 3T/15-05-2017 | X15: =VLOOKUP(W15,[1]INTERESES!A:B,2,0) -> 0 | Y15: =VLOOKUP(W15,#REF!,6,0) -> #REF! | Z15: 43156 | AA15: 44377 | AB15: =AA15-Z15 -> 1221 | AC15: =+(1+Y15)^(AB15/360)-1 -> #REF! | AD15: =AC15*V15 -> #REF! | AE15: =+V15+AD15 -> #VALUE!
A16: =A15+1 -> 16 | B16: 42583 | C16: =CONCATENATE("IF(VLOOKUP(B9,MAPA_DATA!D:G,2,0)=1,'FACT_EMITIDA',IF(VLOOKUP(B",A16,",MAPA_DATA!D:G,3,0)=1,'FACT_EST_EFACT',(IF(VLOOKUP(B",A16,",MAPA_DATA!D:G,4,0)=1,'FACT_EST_CEN','SIN_DATA')))") -> IF(VLOOKUP(B9,MAPA_DATA!D:G,2,0)=1,'FACT_EMITIDA',IF(VLOOKUP(B16,MAPA_DATA!D:G,3,0)=1,'FACT_EST_EFACT',(IF(VLOOKUP(B16,MAPA_DATA!D:G,4,0)=1,'FACT_EST_CEN','SIN_DATA'))) | D16: =CONCATENATE("SUMIF(",IF(C16="FACT_EMITIDA","SIGGE_E",C16),"!B:B,Reliquidacion!B",A16,",",IF(C16="FACT_EMITIDA","SIGGE_E",C16),"!F:F)") -> SUMIF(IF(VLOOKUP(B9,MAPA_DATA!D:G,2,0)=1,'FACT_EMITIDA',IF(VLOOKUP(B16,MAPA_DATA!D:G,3,0)=1,'FACT_EST_EFACT',(IF(VLOOKUP(B16,MAPA_DATA!D:G,4,0)=1,'FACT_EST_CEN','SIN_DATA')))!B:B,Reliquidacion!B16,IF(VLOOKUP(B9,MAPA_DATA!D:G,2,0)=1,'FACT_EMITIDA',IF(VLOOKUP(B16,MAPA_DATA!D:G,3,0)=1,'FACT_EST_EFACT',(IF(VLOOKUP(B16,MAPA_DATA!D:G,4,0)=1,'FACT_EST_CEN','SIN_DATA')))!F:F) | E16: =CONCATENATE("(F",A16,"/D",A16,")") -> (F16/D16) | F16: =CONCATENATE("SUMIF(",IF(C16="FACT_EMITIDA","SIGGE_E",C16),"!B:B,Reliquidacion!B",A16,",",IF(C16="FACT_EMITIDA","SIGGE_E",C16),"!H:H)") -> SUMIF(IF(VLOOKUP(B9,MAPA_DATA!D:G,2,0)=1,'FACT_EMITIDA',IF(VLOOKUP(B16,MAPA_DATA!D:G,3,0)=1,'FACT_EST_EFACT',(IF(VLOOKUP(B16,MAPA_DATA!D:G,4,0)=1,'FACT_EST_CEN','SIN_DATA')))!B:B,Reliquidacion!B16,IF(VLOOKUP(B9,MAPA_DATA!D:G,2,0)=1,'FACT_EMITIDA',IF(VLOOKUP(B16,MAPA_DATA!D:G,3,0)=1,'FACT_EST_EFACT',(IF(VLOOKUP(B16,MAPA_DATA!D:G,4,0)=1,'FACT_EST_CEN','SIN_DATA')))!H:H) | G16: =CONCATENATE("SUMIF(",IF(C16="FACT_EMITIDA","SIGGE_P",C16),"!B:B,Reliquidacion!B",A16,",",IF(C16="FACT_EMITIDA","SIGGE_P",C16),"!F:F)") -> SUMIF(IF(VLOOKUP(B9,MAPA_DATA!D:G,2,0)=1,'FACT_EMITIDA',IF(VLOOKUP(B16,MAPA_DATA!D:G,3,0)=1,'FACT_EST_EFACT',(IF(VLOOKUP(B16,MAPA_DATA!D:G,4,0)=1,'FACT_EST_CEN','SIN_DATA')))!B:B,Reliquidacion!B16,IF(VLOOKUP(B9,MAPA_DATA!D:G,2,0)=1,'FACT_EMITIDA',IF(VLOOKUP(B16,MAPA_DATA!D:G,3,0)=1,'FACT_EST_EFACT',(IF(VLOOKUP(B16,MAPA_DATA!D:G,4,0)=1,'FACT_EST_CEN','SIN_DATA')))!F:F) | H16: =CONCATENATE("(I",A16,"/G",A16,")") -> (I16/G16) | I16: =CONCATENATE("SUMIF(",IF(C16="FACT_EMITIDA","SIGGE_P",C16),"!B:B,Reliquidacion!B",A16,",",IF(C16="FACT_EMITIDA","SIGGE_P",C16),"!H:H)") -> SUMIF(IF(VLOOKUP(B9,MAPA_DATA!D:G,2,0)=1,'FACT_EMITIDA',IF(VLOOKUP(B16,MAPA_DATA!D:G,3,0)=1,'FACT_EST_EFACT',(IF(VLOOKUP(B16,MAPA_DATA!D:G,4,0)=1,'FACT_EST_CEN','SIN_DATA')))!B:B,Reliquidacion!B16,IF(VLOOKUP(B9,MAPA_DATA!D:G,2,0)=1,'FACT_EMITIDA',IF(VLOOKUP(B16,MAPA_DATA!D:G,3,0)=1,'FACT_EST_EFACT',(IF(VLOOKUP(B16,MAPA_DATA!D:G,4,0)=1,'FACT_EST_CEN','SIN_DATA')))!H:H) | J16: =CONCATENATE("(F",A16,"+I",A16,")") -> (F16+I16) | L16: =IF(VLOOKUP(B16,MAPA_DATA!D:I,5,0)=1,"EFACT_CNE",IF(VLOOKUP(B16,MAPA_DATA!D:I,6,0)=1,"EFACT_EST_CNE","SIN_DATA")) -> SIN_DATA | M16: =CONCATENATE("SUMIF(",L16,"!B:B;Reliquidacion!B",A16,";",L16,"!S:S)") -> SUMIF(SIN_DATA!B:B;Reliquidacion!B16;SIN_DATA!S:S) | N16: =CONCATENATE("(O",A16,"/M",A16,")") -> (O16/M16) | O16: =CONCATENATE("SUMIF(",L16,"!B:B;Reliquidacion!B",A16,";",L16,"!W:W)") -> SUMIF(SIN_DATA!B:B;Reliquidacion!B16;SIN_DATA!W:W) | P16: =CONCATENATE("SUMIF(",L16,"!B:B;Reliquidacion!B",A16,";",L16,"!X:X)") -> SUMIF(SIN_DATA!B:B;Reliquidacion!B16;SIN_DATA!X:X) | Q16: =CONCATENATE("(R",A16,"/P",A16,")") -> (R16/P16) | R16: =CONCATENATE("SUMIF(",L16,"!B:B;Reliquidacion!B",A16,";",L16,"!AB:AB)") -> SUMIF(SIN_DATA!B:B;Reliquidacion!B16;SIN_DATA!AB:AB) | S16: =CONCATENATE("(O",A16,"+R",A16,")") -> (O16+R16) | U16: 42583 | V16: =CONCATENATE("=(S",A16,"-J",A16,")") -> =(S16-J16) | W16: 3T/15-05-2017 | X16: =VLOOKUP(W16,[1]INTERESES!A:B,2,0) -> 0 | Y16: =VLOOKUP(W16,#REF!,6,0) -> #REF! | Z16: 43156 | AA16: 44377 | AB16: =AA16-Z16 -> 1221 | AC16: =+(1+Y16)^(AB16/360)-1 -> #REF! | AD16: =AC16*V16 -> #REF! | AE16: =+V16+AD16 -> #VALUE!
A17: =A16+1 -> 17 | B17: 42614 | C17: =CONCATENATE("IF(VLOOKUP(B9,MAPA_DATA!D:G,2,0)=1,'FACT_EMITIDA',IF(VLOOKUP(B",A17,",MAPA_DATA!D:G,3,0)=1,'FACT_EST_EFACT',(IF(VLOOKUP(B",A17,",MAPA_DATA!D:G,4,0)=1,'FACT_EST_CEN','SIN_DATA')))") -> IF(VLOOKUP(B9,MAPA_DATA!D:G,2,0)=1,'FACT_EMITIDA',IF(VLOOKUP(B17,MAPA_DATA!D:G,3,0)=1,'FACT_EST_EFACT',(IF(VLOOKUP(B17,MAPA_DATA!D:G,4,0)=1,'FACT_EST_CEN','SIN_DATA'))) | D17: =CONCATENATE("SUMIF(",IF(C17="FACT_EMITIDA","SIGGE_E",C17),"!B:B,Reliquidacion!B",A17,",",IF(C17="FACT_EMITIDA","SIGGE_E",C17),"!F:F)") -> SUMIF(IF(VLOOKUP(B9,MAPA_DATA!D:G,2,0)=1,'FACT_EMITIDA',IF(VLOOKUP(B17,MAPA_DATA!D:G,3,0)=1,'FACT_EST_EFACT',(IF(VLOOKUP(B17,MAPA_DATA!D:G,4,0)=1,'FACT_EST_CEN','SIN_DATA')))!B:B,Reliquidacion!B17,IF(VLOOKUP(B9,MAPA_DATA!D:G,2,0)=1,'FACT_EMITIDA',IF(VLOOKUP(B17,MAPA_DATA!D:G,3,0)=1,'FACT_EST_EFACT',(IF(VLOOKUP(B17,MAPA_DATA!D:G,4,0)=1,'FACT_EST_CEN','SIN_DATA')))!F:F) | E17: =CONCATENATE("(F",A17,"/D",A17,")") -> (F17/D17) | F17: =CONCATENATE("SUMIF(",IF(C17="FACT_EMITIDA","SIGGE_E",C17),"!B:B,Reliquidacion!B",A17,",",IF(C17="FACT_EMITIDA","SIGGE_E",C17),"!H:H)") -> SUMIF(IF(VLOOKUP(B9,MAPA_DATA!D:G,2,0)=1,'FACT_EMITIDA',IF(VLOOKUP(B17,MAPA_DATA!D:G,3,0)=1,'FACT_EST_EFACT',(IF(VLOOKUP(B17,MAPA_DATA!D:G,4,0)=1,'FACT_EST_CEN','SIN_DATA')))!B:B,Reliquidacion!B17,IF(VLOOKUP(B9,MAPA_DATA!D:G,2,0)=1,'FACT_EMITIDA',IF(VLOOKUP(B17,MAPA_DATA!D:G,3,0)=1,'FACT_EST_EFACT',(IF(VLOOKUP(B17,MAPA_DATA!D:G,4,0)=1,'FACT_EST_CEN','SIN_DATA')))!H:H) | G17: =CONCATENATE("SUMIF(",IF(C17="FACT_EMITIDA","SIGGE_P",C17),"!B:B,Reliquidacion!B",A17,",",IF(C17="FACT_EMITIDA","SIGGE_P",C17),"!F:F)") -> SUMIF(IF(VLOOKUP(B9,MAPA_DATA!D:G,2,0)=1,'FACT_EMITIDA',IF(VLOOKUP(B17,MAPA_DATA!D:G,3,0)=1,'FACT_EST_EFACT',(IF(VLOOKUP(B17,MAPA_DATA!D:G,4,0)=1,'FACT_EST_CEN','SIN_DATA')))!B:B,Reliquidacion!B17,IF(VLOOKUP(B9,MAPA_DATA!D:G,2,0)=1,'FACT_EMITIDA',IF(VLOOKUP(B17,MAPA_DATA!D:G,3,0)=1,'FACT_EST_EFACT',(IF(VLOOKUP(B17,MAPA_DATA!D:G,4,0)=1,'FACT_EST_CEN','SIN_DATA')))!F:F) | H17: =CONCATENATE("(I",A17,"/G",A17,")") -> (I17/G17) | I17: =CONCATENATE("SUMIF(",IF(C17="FACT_EMITIDA","SIGGE_P",C17),"!B:B,Reliquidacion!B",A17,",",IF(C17="FACT_EMITIDA","SIGGE_P",C17),"!H:H)") -> SUMIF(IF(VLOOKUP(B9,MAPA_DATA!D:G,2,0)=1,'FACT_EMITIDA',IF(VLOOKUP(B17,MAPA_DATA!D:G,3,0)=1,'FACT_EST_EFACT',(IF(VLOOKUP(B17,MAPA_DATA!D:G,4,0)=1,'FACT_EST_CEN','SIN_DATA')))!B:B,Reliquidacion!B17,IF(VLOOKUP(B9,MAPA_DATA!D:G,2,0)=1,'FACT_EMITIDA',IF(VLOOKUP(B17,MAPA_DATA!D:G,3,0)=1,'FACT_EST_EFACT',(IF(VLOOKUP(B17,MAPA_DATA!D:G,4,0)=1,'FACT_EST_CEN','SIN_DATA')))!H:H) | J17: =CONCATENATE("(F",A17,"+I",A17,")") -> (F17+I17) | L17: =IF(VLOOKUP(B17,MAPA_DATA!D:I,5,0)=1,"EFACT_CNE",IF(VLOOKUP(B17,MAPA_DATA!D:I,6,0)=1,"EFACT_EST_CNE","SIN_DATA")) -> SIN_DATA | M17: =CONCATENATE("SUMIF(",L17,"!B:B;Reliquidacion!B",A17,";",L17,"!S:S)") -> SUMIF(SIN_DATA!B:B;Reliquidacion!B17;SIN_DATA!S:S) | N17: =CONCATENATE("(O",A17,"/M",A17,")") -> (O17/M17) | O17: =CONCATENATE("SUMIF(",L17,"!B:B;Reliquidacion!B",A17,";",L17,"!W:W)") -> SUMIF(SIN_DATA!B:B;Reliquidacion!B17;SIN_DATA!W:W) | P17: =CONCATENATE("SUMIF(",L17,"!B:B;Reliquidacion!B",A17,";",L17,"!X:X)") -> SUMIF(SIN_DATA!B:B;Reliquidacion!B17;SIN_DATA!X:X) | Q17: =CONCATENATE("(R",A17,"/P",A17,")") -> (R17/P17) | R17: =CONCATENATE("SUMIF(",L17,"!B:B;Reliquidacion!B",A17,";",L17,"!AB:AB)") -> SUMIF(SIN_DATA!B:B;Reliquidacion!B17;SIN_DATA!AB:AB) | S17: =CONCATENATE("(O",A17,"+R",A17,")") -> (O17+R17) | U17: 42614 | V17: =CONCATENATE("=(S",A17,"-J",A17,")") -> =(S17-J17) | W17: 3T/15-05-2017 | X17: =VLOOKUP(W17,[1]INTERESES!A:B,2,0) -> 0 | Y17: =VLOOKUP(W17,#REF!,6,0) -> #REF! | Z17: 43156 | AA17: 44377 | AB17: =AA17-Z17 -> 1221 | AC17: =+(1+Y17)^(AB17/360)-1 -> #REF! | AD17: =AC17*V17 -> #REF! | AE17: =+V17+AD17 -> #VALUE!
A18: =A17+1 -> 18 | B18: 42644 | C18: =CONCATENATE("IF(VLOOKUP(B9,MAPA_DATA!D:G,2,0)=1,'FACT_EMITIDA',IF(VLOOKUP(B",A18,",MAPA_DATA!D:G,3,0)=1,'FACT_EST_EFACT',(IF(VLOOKUP(B",A18,",MAPA_DATA!D:G,4,0)=1,'FACT_EST_CEN','SIN_DATA')))") -> IF(VLOOKUP(B9,MAPA_DATA!D:G,2,0)=1,'FACT_EMITIDA',IF(VLOOKUP(B18,MAPA_DATA!D:G,3,0)=1,'FACT_EST_EFACT',(IF(VLOOKUP(B18,MAPA_DATA!D:G,4,0)=1,'FACT_EST_CEN','SIN_DATA'))) | D18: =CONCATENATE("SUMIF(",IF(C18="FACT_EMITIDA","SIGGE_E",C18),"!B:B,Reliquidacion!B",A18,",",IF(C18="FACT_EMITIDA","SIGGE_E",C18),"!F:F)") -> SUMIF(IF(VLOOKUP(B9,MAPA_DATA!D:G,2,0)=1,'FACT_EMITIDA',IF(VLOOKUP(B18,MAPA_DATA!D:G,3,0)=1,'FACT_EST_EFACT',(IF(VLOOKUP(B18,MAPA_DATA!D:G,4,0)=1,'FACT_EST_CEN','SIN_DATA')))!B:B,Reliquidacion!B18,IF(VLOOKUP(B9,MAPA_DATA!D:G,2,0)=1,'FACT_EMITIDA',IF(VLOOKUP(B18,MAPA_DATA!D:G,3,0)=1,'FACT_EST_EFACT',(IF(VLOOKUP(B18,MAPA_DATA!D:G,4,0)=1,'FACT_EST_CEN','SIN_DATA')))!F:F) | E18: =CONCATENATE("(F",A18,"/D",A18,")") -> (F18/D18) | F18: =CONCATENATE("SUMIF(",IF(C18="FACT_EMITIDA","SIGGE_E",C18),"!B:B,Reliquidacion!B",A18,",",IF(C18="FACT_EMITIDA","SIGGE_E",C18),"!H:H)") -> SUMIF(IF(VLOOKUP(B9,MAPA_DATA!D:G,2,0)=1,'FACT_EMITIDA',IF(VLOOKUP(B18,MAPA_DATA!D:G,3,0)=1,'FACT_EST_EFACT',(IF(VLOOKUP(B18,MAPA_DATA!D:G,4,0)=1,'FACT_EST_CEN','SIN_DATA')))!B:B,Reliquidacion!B18,IF(VLOOKUP(B9,MAPA_DATA!D:G,2,0)=1,'FACT_EMITIDA',IF(VLOOKUP(B18,MAPA_DATA!D:G,3,0)=1,'FACT_EST_EFACT',(IF(VLOOKUP(B18,MAPA_DATA!D:G,4,0)=1,'FACT_EST_CEN','SIN_DATA')))!H:H) | G18: =CONCATENATE("SUMIF(",IF(C18="FACT_EMITIDA","SIGGE_P",C18),"!B:B,Reliquidacion!B",A18,",",IF(C18="FACT_EMITIDA","SIGGE_P",C18),"!F:F)") -> SUMIF(IF(VLOOKUP(B9,MAPA_DATA!D:G,2,0)=1,'FACT_EMITIDA',IF(VLOOKUP(B18,MAPA_DATA!D:G,3,0)=1,'FACT_EST_EFACT',(IF(VLOOKUP(B18,MAPA_DATA!D:G,4,0)=1,'FACT_EST_CEN','SIN_DATA')))!B:B,Reliquidacion!B18,IF(VLOOKUP(B9,MAPA_DATA!D:G,2,0)=1,'FACT_EMITIDA',IF(VLOOKUP(B18,MAPA_DATA!D:G,3,0)=1,'FACT_EST_EFACT',(IF(VLOOKUP(B18,MAPA_DATA!D:G,4,0)=1,'FACT_EST_CEN','SIN_DATA')))!F:F) | H18: =CONCATENATE("(I",A18,"/G",A18,")") -> (I18/G18) | I18: =CONCATENATE("SUMIF(",IF(C18="FACT_EMITIDA","SIGGE_P",C18),"!B:B,Reliquidacion!B",A18,",",IF(C18="FACT_EMITIDA","SIGGE_P",C18),"!H:H)") -> SUMIF(IF(VLOOKUP(B9,MAPA_DATA!D:G,2,0)=1,'FACT_EMITIDA',IF(VLOOKUP(B18,MAPA_DATA!D:G,3,0)=1,'FACT_EST_EFACT',(IF(VLOOKUP(B18,MAPA_DATA!D:G,4,0)=1,'FACT_EST_CEN','SIN_DATA')))!B:B,Reliquidacion!B18,IF(VLOOKUP(B9,MAPA_DATA!D:G,2,0)=1,'FACT_EMITIDA',IF(VLOOKUP(B18,MAPA_DATA!D:G,3,0)=1,'FACT_EST_EFACT',(IF(VLOOKUP(B18,MAPA_DATA!D:G,4,0)=1,'FACT_EST_CEN','SIN_DATA')))!H:H) | J18: =CONCATENATE("(F",A18,"+I",A18,")") -> (F18+I18) | L18: =IF(VLOOKUP(B18,MAPA_DATA!D:I,5,0)=1,"EFACT_CNE",IF(VLOOKUP(B18,MAPA_DATA!D:I,6,0)=1,"EFACT_EST_CNE","SIN_DATA")) -> SIN_DATA | M18: =CONCATENATE("SUMIF(",L18,"!B:B;Reliquidacion!B",A18,";",L18,"!S:S)") -> SUMIF(SIN_DATA!B:B;Reliquidacion!B18;SIN_DATA!S:S) | N18: =CONCATENATE("(O",A18,"/M",A18,")") -> (O18/M18) | O18: =CONCATENATE("SUMIF(",L18,"!B:B;Reliquidacion!B",A18,";",L18,"!W:W)") -> SUMIF(SIN_DATA!B:B;Reliquidacion!B18;SIN_DATA!W:W) | P18: =CONCATENATE("SUMIF(",L18,"!B:B;Reliquidacion!B",A18,";",L18,"!X:X)") -> SUMIF(SIN_DATA!B:B;Reliquidacion!B18;SIN_DATA!X:X) | Q18: =CONCATENATE("(R",A18,"/P",A18,")") -> (R18/P18) | R18: =CONCATENATE("SUMIF(",L18,"!B:B;Reliquidacion!B",A18,";",L18,"!AB:AB)") -> SUMIF(SIN_DATA!B:B;Reliquidacion!B18;SIN_DATA!AB:AB) | S18: =CONCATENATE("(O",A18,"+R",A18,")") -> (O18+R18) | U18: 42644 | V18: =CONCATENATE("=(S",A18,"-J",A18,")") -> =(S18-J18) | W18: 3T/15-05-2017 | X18: =VLOOKUP(W18,[1]INTERESES!A:B,2,0) -> 0 | Y18: =VLOOKUP(W18,#REF!,6,0) -> #REF! | Z18: 43156 | AA18: 44377 | AB18: =AA18-Z18 -> 1221 | AC18: =+(1+Y18)^(AB18/360)-1 -> #REF! | AD18: =AC18*V18 -> #REF! | AE18: =+V18+AD18 -> #VALUE!
A19: =A18+1 -> 19 | B19: 42675 | C19: =CONCATENATE("IF(VLOOKUP(B9,MAPA_DATA!D:G,2,0)=1,'FACT_EMITIDA',IF(VLOOKUP(B",A19,",MAPA_DATA!D:G,3,0)=1,'FACT_EST_EFACT',(IF(VLOOKUP(B",A19,",MAPA_DATA!D:G,4,0)=1,'FACT_EST_CEN','SIN_DATA')))") -> IF(VLOOKUP(B9,MAPA_DATA!D:G,2,0)=1,'FACT_EMITIDA',IF(VLOOKUP(B19,MAPA_DATA!D:G,3,0)=1,'FACT_EST_EFACT',(IF(VLOOKUP(B19,MAPA_DATA!D:G,4,0)=1,'FACT_EST_CEN','SIN_DATA'))) | D19: =CONCATENATE("SUMIF(",IF(C19="FACT_EMITIDA","SIGGE_E",C19),"!B:B,Reliquidacion!B",A19,",",IF(C19="FACT_EMITIDA","SIGGE_E",C19),"!F:F)") -> SUMIF(IF(VLOOKUP(B9,MAPA_DATA!D:G,2,0)=1,'FACT_EMITIDA',IF(VLOOKUP(B19,MAPA_DATA!D:G,3,0)=1,'FACT_EST_EFACT',(IF(VLOOKUP(B19,MAPA_DATA!D:G,4,0)=1,'FACT_EST_CEN','SIN_DATA')))!B:B,Reliquidacion!B19,IF(VLOOKUP(B9,MAPA_DATA!D:G,2,0)=1,'FACT_EMITIDA',IF(VLOOKUP(B19,MAPA_DATA!D:G,3,0)=1,'FACT_EST_EFACT',(IF(VLOOKUP(B19,MAPA_DATA!D:G,4,0)=1,'FACT_EST_CEN','SIN_DATA')))!F:F) | E19: =CONCATENATE("(F",A19,"/D",A19,")") -> (F19/D19) | F19: =CONCATENATE("SUMIF(",IF(C19="FACT_EMITIDA","SIGGE_E",C19),"!B:B,Reliquidacion!B",A19,",",IF(C19="FACT_EMITIDA","SIGGE_E",C19),"!H:H)") -> SUMIF(IF(VLOOKUP(B9,MAPA_DATA!D:G,2,0)=1,'FACT_EMITIDA',IF(VLOOKUP(B19,MAPA_DATA!D:G,3,0)=1,'FACT_EST_EFACT',(IF(VLOOKUP(B19,MAPA_DATA!D:G,4,0)=1,'FACT_EST_CEN','SIN_DATA')))!B:B,Reliquidacion!B19,IF(VLOOKUP(B9,MAPA_DATA!D:G,2,0)=1,'FACT_EMITIDA',IF(VLOOKUP(B19,MAPA_DATA!D:G,3,0)=1,'FACT_EST_EFACT',(IF(VLOOKUP(B19,MAPA_DATA!D:G,4,0)=1,'FACT_EST_CEN','SIN_DATA')))!H:H) | G19: =CONCATENATE("SUMIF(",IF(C19="FACT_EMITIDA","SIGGE_P",C19),"!B:B,Reliquidacion!B",A19,",",IF(C19="FACT_EMITIDA","SIGGE_P",C19),"!F:F)") -> SUMIF(IF(VLOOKUP(B9,MAPA_DATA!D:G,2,0)=1,'FACT_EMITIDA',IF(VLOOKUP(B19,MAPA_DATA!D:G,3,0)=1,'FACT_EST_EFACT',(IF(VLOOKUP(B19,MAPA_DATA!D:G,4,0)=1,'FACT_EST_CEN','SIN_DATA')))!B:B,Reliquidacion!B19,IF(VLOOKUP(B9,MAPA_DATA!D:G,2,0)=1,'FACT_EMITIDA',IF(VLOOKUP(B19,MAPA_DATA!D:G,3,0)=1,'FACT_EST_EFACT',(IF(VLOOKUP(B19,MAPA_DATA!D:G,4,0)=1,'FACT_EST_CEN','SIN_DATA')))!F:F) | H19: =CONCATENATE("(I",A19,"/G",A19,")") -> (I19/G19) | I19: =CONCATENATE("SUMIF(",IF(C19="FACT_EMITIDA","SIGGE_P",C19),"!B:B,Reliquidacion!B",A19,",",IF(C19="FACT_EMITIDA","SIGGE_P",C19),"!H:H)") -> SUMIF(IF(VLOOKUP(B9,MAPA_DATA!D:G,2,0)=1,'FACT_EMITIDA',IF(VLOOKUP(B19,MAPA_DATA!D:G,3,0)=1,'FACT_EST_EFACT',(IF(VLOOKUP(B19,MAPA_DATA!D:G,4,0)=1,'FACT_EST_CEN','SIN_DATA')))!B:B,Reliquidacion!B19,IF(VLOOKUP(B9,MAPA_DATA!D:G,2,0)=1,'FACT_EMITIDA',IF(VLOOKUP(B19,MAPA_DATA!D:G,3,0)=1,'FACT_EST_EFACT',(IF(VLOOKUP(B19,MAPA_DATA!D:G,4,0)=1,'FACT_EST_CEN','SIN_DATA')))!H:H) | J19: =CONCATENATE("(F",A19,"+I",A19,")") -> (F19+I19) | L19: =IF(VLOOKUP(B19,MAPA_DATA!D:I,5,0)=1,"EFACT_CNE",IF(VLOOKUP(B19,MAPA_DATA!D:I,6,0)=1,"EFACT_EST_CNE","SIN_DATA")) -> SIN_DATA | M19: =CONCATENATE("SUMIF(",L19,"!B:B;Reliquidacion!B",A19,";",L19,"!S:S)") -> SUMIF(SIN_DATA!B:B;Reliquidacion!B19;SIN_DATA!S:S) | N19: =CONCATENATE("(O",A19,"/M",A19,")") -> (O19/M19) | O19: =CONCATENATE("SUMIF(",L19,"!B:B;Reliquidacion!B",A19,";",L19,"!W:W)") -> SUMIF(SIN_DATA!B:B;Reliquidacion!B19;SIN_DATA!W:W) | P19: =CONCATENATE("SUMIF(",L19,"!B:B;Reliquidacion!B",A19,";",L19,"!X:X)") -> SUMIF(SIN_DATA!B:B;Reliquidacion!B19;SIN_DATA!X:X) | Q19: =CONCATENATE("(R",A19,"/P",A19,")") -> (R19/P19) | R19: =CONCATENATE("SUMIF(",L19,"!B:B;Reliquidacion!B",A19,";",L19,"!AB:AB)") -> SUMIF(SIN_DATA!B:B;Reliquidacion!B19;SIN_DATA!AB:AB) | S19: =CONCATENATE("(O",A19,"+R",A19,")") -> (O19+R19) | U19: 42675 | V19: =CONCATENATE("=(S",A19,"-J",A19,")") -> =(S19-J19) | W19: 3T/15-05-2017 | X19: =VLOOKUP(W19,[1]INTERESES!A:B,2,0) -> 0 | Y19: =VLOOKUP(W19,#REF!,6,0) -> #REF! | Z19: 43156 | AA19: 44377 | AB19: =AA19-Z19 -> 1221 | AC19: =+(1+Y19)^(AB19/360)-1 -> #REF! | AD19: =AC19*V19 -> #REF! | AE19: =+V19+AD19 -> #VALUE!
A20: =A19+1 -> 20 | B20: 42705 | C20: =CONCATENATE("IF(VLOOKUP(B9,MAPA_DATA!D:G,2,0)=1,'FACT_EMITIDA',IF(VLOOKUP(B",A20,",MAPA_DATA!D:G,3,0)=1,'FACT_EST_EFACT',(IF(VLOOKUP(B",A20,",MAPA_DATA!D:G,4,0)=1,'FACT_EST_CEN','SIN_DATA')))") -> IF(VLOOKUP(B9,MAPA_DATA!D:G,2,0)=1,'FACT_EMITIDA',IF(VLOOKUP(B20,MAPA_DATA!D:G,3,0)=1,'FACT_EST_EFACT',(IF(VLOOKUP(B20,MAPA_DATA!D:G,4,0)=1,'FACT_EST_CEN','SIN_DATA'))) | D20: =CONCATENATE("SUMIF(",IF(C20="FACT_EMITIDA","SIGGE_E",C20),"!B:B,Reliquidacion!B",A20,",",IF(C20="FACT_EMITIDA","SIGGE_E",C20),"!F:F)") -> SUMIF(IF(VLOOKUP(B9,MAPA_DATA!D:G,2,0)=1,'FACT_EMITIDA',IF(VLOOKUP(B20,MAPA_DATA!D:G,3,0)=1,'FACT_EST_EFACT',(IF(VLOOKUP(B20,MAPA_DATA!D:G,4,0)=1,'FACT_EST_CEN','SIN_DATA')))!B:B,Reliquidacion!B20,IF(VLOOKUP(B9,MAPA_DATA!D:G,2,0)=1,'FACT_EMITIDA',IF(VLOOKUP(B20,MAPA_DATA!D:G,3,0)=1,'FACT_EST_EFACT',(IF(VLOOKUP(B20,MAPA_DATA!D:G,4,0)=1,'FACT_EST_CEN','SIN_DATA')))!F:F) | E20: =CONCATENATE("(F",A20,"/D",A20,")") -> (F20/D20) | F20: =CONCATENATE("SUMIF(",IF(C20="FACT_EMITIDA","SIGGE_E",C20),"!B:B,Reliquidacion!B",A20,",",IF(C20="FACT_EMITIDA","SIGGE_E",C20),"!H:H)") -> SUMIF(IF(VLOOKUP(B9,MAPA_DATA!D:G,2,0)=1,'FACT_EMITIDA',IF(VLOOKUP(B20,MAPA_DATA!D:G,3,0)=1,'FACT_EST_EFACT',(IF(VLOOKUP(B20,MAPA_DATA!D:G,4,0)=1,'FACT_EST_CEN','SIN_DATA')))!B:B,Reliquidacion!B20,IF(VLOOKUP(B9,MAPA_DATA!D:G,2,0)=1,'FACT_EMITIDA',IF(VLOOKUP(B20,MAPA_DATA!D:G,3,0)=1,'FACT_EST_EFACT',(IF(VLOOKUP(B20,MAPA_DATA!D:G,4,0)=1,'FACT_EST_CEN','SIN_DATA')))!H:H) | G20: =CONCATENATE("SUMIF(",IF(C20="FACT_EMITIDA","SIGGE_P",C20),"!B:B,Reliquidacion!B",A20,",",IF(C20="FACT_EMITIDA","SIGGE_P",C20),"!F:F)") -> SUMIF(IF(VLOOKUP(B9,MAPA_DATA!D:G,2,0)=1,'FACT_EMITIDA',IF(VLOOKUP(B20,MAPA_DATA!D:G,3,0)=1,'FACT_EST_EFACT',(IF(VLOOKUP(B20,MAPA_DATA!D:G,4,0)=1,'FACT_EST_CEN','SIN_DATA')))!B:B,Reliquidacion!B20,IF(VLOOKUP(B9,MAPA_DATA!D:G,2,0)=1,'FACT_EMITIDA',IF(VLOOKUP(B20,MAPA_DATA!D:G,3,0)=1,'FACT_EST_EFACT',(IF(VLOOKUP(B20,MAPA_DATA!D:G,4,0)=1,'FACT_EST_CEN','SIN_DATA')))!F:F) | H20: =CONCATENATE("(I",A20,"/G",A20,")") -> (I20/G20) | I20: =CONCATENATE("SUMIF(",IF(C20="FACT_EMITIDA","SIGGE_P",C20),"!B:B,Reliquidacion!B",A20,",",IF(C20="FACT_EMITIDA","SIGGE_P",C20),"!H:H)") -> SUMIF(IF(VLOOKUP(B9,MAPA_DATA!D:G,2,0)=1,'FACT_EMITIDA',IF(VLOOKUP(B20,MAPA_DATA!D:G,3,0)=1,'FACT_EST_EFACT',(IF(VLOOKUP(B20,MAPA_DATA!D:G,4,0)=1,'FACT_EST_CEN','SIN_DATA')))!B:B,Reliquidacion!B20,IF(VLOOKUP(B9,MAPA_DATA!D:G,2,0)=1,'FACT_EMITIDA',IF(VLOOKUP(B20,MAPA_DATA!D:G,3,0)=1,'FACT_EST_EFACT',(IF(VLOOKUP(B20,MAPA_DATA!D:G,4,0)=1,'FACT_EST_CEN','SIN_DATA')))!H:H) | J20: =CONCATENATE("(F",A20,"+I",A20,")") -> (F20+I20) | L20: =IF(VLOOKUP(B20,MAPA_DATA!D:I,5,0)=1,"EFACT_CNE",IF(VLOOKUP(B20,MAPA_DATA!D:I,6,0)=1,"EFACT_EST_CNE","SIN_DATA")) -> SIN_DATA | M20: =CONCATENATE("SUMIF(",L20,"!B:B;Reliquidacion!B",A20,";",L20,"!S:S)") -> SUMIF(SIN_DATA!B:B;Reliquidacion!B20;SIN_DATA!S:S) | N20: =CONCATENATE("(O",A20,"/M",A20,")") -> (O20/M20) | O20: =CONCATENATE("SUMIF(",L20,"!B:B;Reliquidacion!B",A20,";",L20,"!W:W)") -> SUMIF(SIN_DATA!B:B;Reliquidacion!B20;SIN_DATA!W:W) | P20: =CONCATENATE("SUMIF(",L20,"!B:B;Reliquidacion!B",A20,";",L20,"!X:X)") -> SUMIF(SIN_DATA!B:B;Reliquidacion!B20;SIN_DATA!X:X) | Q20: =CONCATENATE("(R",A20,"/P",A20,")") -> (R20/P20) | R20: =CONCATENATE("SUMIF(",L20,"!B:B;Reliquidacion!B",A20,";",L20,"!AB:AB)") -> SUMIF(SIN_DATA!B:B;Reliquidacion!B20;SIN_DATA!AB:AB) | S20: =CONCATENATE("(O",A20,"+R",A20,")") -> (O20+R20) | U20: 42705 | V20: =CONCATENATE("=(S",A20,"-J",A20,")") -> =(S20-J20) | W20: 3T/15-05-2017 | X20: =VLOOKUP(W20,[1]INTERESES!A:B,2,0) -> 0 | Y20: =VLOOKUP(W20,#REF!,6,0) -> #REF! | Z20: 43156 | AA20: 44377 | AB20: =AA20-Z20 -> 1221 | AC20: =+(1+Y20)^(AB20/360)-1 -> #REF! | AD20: =AC20*V20 -> #REF! | AE20: =+V20+AD20 -> #VALUE!
A21: =A20+1 -> 21 | B21: 42736 | C21: =CONCATENATE("IF(VLOOKUP(B9,MAPA_DATA!D:G,2,0)=1,'FACT_EMITIDA',IF(VLOOKUP(B",A21,",MAPA_DATA!D:G,3,0)=1,'FACT_EST_EFACT',(IF(VLOOKUP(B",A21,",MAPA_DATA!D:G,4,0)=1,'FACT_EST_CEN','SIN_DATA')))") -> IF(VLOOKUP(B9,MAPA_DATA!D:G,2,0)=1,'FACT_EMITIDA',IF(VLOOKUP(B21,MAPA_DATA!D:G,3,0)=1,'FACT_EST_EFACT',(IF(VLOOKUP(B21,MAPA_DATA!D:G,4,0)=1,'FACT_EST_CEN','SIN_DATA'))) | D21: =CONCATENATE("SUMIF(",IF(C21="FACT_EMITIDA","SIGGE_E",C21),"!B:B,Reliquidacion!B",A21,",",IF(C21="FACT_EMITIDA","SIGGE_E",C21),"!F:F)") -> SUMIF(IF(VLOOKUP(B9,MAPA_DATA!D:G,2,0)=1,'FACT_EMITIDA',IF(VLOOKUP(B21,MAPA_DATA!D:G,3,0)=1,'FACT_EST_EFACT',(IF(VLOOKUP(B21,MAPA_DATA!D:G,4,0)=1,'FACT_EST_CEN','SIN_DATA')))!B:B,Reliquidacion!B21,IF(VLOOKUP(B9,MAPA_DATA!D:G,2,0)=1,'FACT_EMITIDA',IF(VLOOKUP(B21,MAPA_DATA!D:G,3,0)=1,'FACT_EST_EFACT',(IF(VLOOKUP(B21,MAPA_DATA!D:G,4,0)=1,'FACT_EST_CEN','SIN_DATA')))!F:F) | E21: =CONCATENATE("(F",A21,"/D",A21,")") -> (F21/D21) | F21: =CONCATENATE("SUMIF(",IF(C21="FACT_EMITIDA","SIGGE_E",C21),"!B:B,Reliquidacion!B",A21,",",IF(C21="FACT_EMITIDA","SIGGE_E",C21),"!H:H)") -> SUMIF(IF(VLOOKUP(B9,MAPA_DATA!D:G,2,0)=1,'FACT_EMITIDA',IF(VLOOKUP(B21,MAPA_DATA!D:G,3,0)=1,'FACT_EST_EFACT',(IF(VLOOKUP(B21,MAPA_DATA!D:G,4,0)=1,'FACT_EST_CEN','SIN_DATA')))!B:B,Reliquidacion!B21,IF(VLOOKUP(B9,MAPA_DATA!D:G,2,0)=1,'FACT_EMITIDA',IF(VLOOKUP(B21,MAPA_DATA!D:G,3,0)=1,'FACT_EST_EFACT',(IF(VLOOKUP(B21,MAPA_DATA!D:G,4,0)=1,'FACT_EST_CEN','SIN_DATA')))!H:H) | G21: =CONCATENATE("SUMIF(",IF(C21="FACT_EMITIDA","SIGGE_P",C21),"!B:B,Reliquidacion!B",A21,",",IF(C21="FACT_EMITIDA","SIGGE_P",C21),"!F:F)") -> SUMIF(IF(VLOOKUP(B9,MAPA_DATA!D:G,2,0)=1,'FACT_EMITIDA',IF(VLOOKUP(B21,MAPA_DATA!D:G,3,0)=1,'FACT_EST_EFACT',(IF(VLOOKUP(B21,MAPA_DATA!D:G,4,0)=1,'FACT_EST_CEN','SIN_DATA')))!B:B,Reliquidacion!B21,IF(VLOOKUP(B9,MAPA_DATA!D:G,2,0)=1,'FACT_EMITIDA',IF(VLOOKUP(B21,MAPA_DATA!D:G,3,0)=1,'FACT_EST_EFACT',(IF(VLOOKUP(B21,MAPA_DATA!D:G,4,0)=1,'FACT_EST_CEN','SIN_DATA')))!F:F) | H21: =CONCATENATE("(I",A21,"/G",A21,")") -> (I21/G21) | I21: =CONCATENATE("SUMIF(",IF(C21="FACT_EMITIDA","SIGGE_P",C21),"!B:B,Reliquidacion!B",A21,",",IF(C21="FACT_EMITIDA","SIGGE_P",C21),"!H:H)") -> SUMIF(IF(VLOOKUP(B9,MAPA_DATA!D:G,2,0)=1,'FACT_EMITIDA',IF(VLOOKUP(B21,MAPA_DATA!D:G,3,0)=1,'FACT_EST_EFACT',(IF(VLOOKUP(B21,MAPA_DATA!D:G,4,0)=1,'FACT_EST_CEN','SIN_DATA')))!B:B,Reliquidacion!B21,IF(VLOOKUP(B9,MAPA_DATA!D:G,2,0)=1,'FACT_EMITIDA',IF(VLOOKUP(B21,MAPA_DATA!D:G,3,0)=1,'FACT_EST_EFACT',(IF(VLOOKUP(B21,MAPA_DATA!D:G,4,0)=1,'FACT_EST_CEN','SIN_DATA')))!H:H) | J21: =CONCATENATE("(F",A21,"+I",A21,")") -> (F21+I21) | L21: =IF(VLOOKUP(B21,MAPA_DATA!D:I,5,0)=1,"EFACT_CNE",IF(VLOOKUP(B21,MAPA_DATA!D:I,6,0)=1,"EFACT_EST_CNE","SIN_DATA")) -> SIN_DATA | M21: =CONCATENATE("SUMIF(",L21,"!B:B;Reliquidacion!B",A21,";",L21,"!S:S)") -> SUMIF(SIN_DATA!B:B;Reliquidacion!B21;SIN_DATA!S:S) | N21: =CONCATENATE("(O",A21,"/M",A21,")") -> (O21/M21) | O21: =CONCATENATE("SUMIF(",L21,"!B:B;Reliquidacion!B",A21,";",L21,"!W:W)") -> SUMIF(SIN_DATA!B:B;Reliquidacion!B21;SIN_DATA!W:W) | P21: =CONCATENATE("SUMIF(",L21,"!B:B;Reliquidacion!B",A21,";",L21,"!X:X)") -> SUMIF(SIN_DATA!B:B;Reliquidacion!B21;SIN_DATA!X:X) | Q21: =CONCATENATE("(R",A21,"/P",A21,")") -> (R21/P21) | R21: =CONCATENATE("SUMIF(",L21,"!B:B;Reliquidacion!B",A21,";",L21,"!AB:AB)") -> SUMIF(SIN_DATA!B:B;Reliquidacion!B21;SIN_DATA!AB:AB) | S21: =CONCATENATE("(O",A21,"+R",A21,")") -> (O21+R21) | U21: 42736 | V21: =CONCATENATE("=(S",A21,"-J",A21,")") -> =(S21-J21) | W21: 3T/15-05-2017 | X21: =VLOOKUP(W21,[1]INTERESES!A:B,2,0) -> 0 | Y21: =VLOOKUP(W21,#REF!,6,0) -> #REF! | Z21: 43156 | AA21: 44377 | AB21: =AA21-Z21 -> 1221 | AC21: =+(1+Y21)^(AB21/360)-1 -> #REF! | AD21: =AC21*V21 -> #REF! | AE21: =+V21+AD21 -> #VALUE!
A22: =A21+1 -> 22 | B22: 42767 | C22: =CONCATENATE("IF(VLOOKUP(B9,MAPA_DATA!D:G,2,0)=1,'FACT_EMITIDA',IF(VLOOKUP(B",A22,",MAPA_DATA!D:G,3,0)=1,'FACT_EST_EFACT',(IF(VLOOKUP(B",A22,",MAPA_DATA!D:G,4,0)=1,'FACT_EST_CEN','SIN_DATA')))") -> IF(VLOOKUP(B9,MAPA_DATA!D:G,2,0)=1,'FACT_EMITIDA',IF(VLOOKUP(B22,MAPA_DATA!D:G,3,0)=1,'FACT_EST_EFACT',(IF(VLOOKUP(B22,MAPA_DATA!D:G,4,0)=1,'FACT_EST_CEN','SIN_DATA'))) | D22: =CONCATENATE("SUMIF(",IF(C22="FACT_EMITIDA","SIGGE_E",C22),"!B:B,Reliquidacion!B",A22,",",IF(C22="FACT_EMITIDA","SIGGE_E",C22),"!F:F)") -> SUMIF(IF(VLOOKUP(B9,MAPA_DATA!D:G,2,0)=1,'FACT_EMITIDA',IF(VLOOKUP(B22,MAPA_DATA!D:G,3,0)=1,'FACT_EST_EFACT',(IF(VLOOKUP(B22,MAPA_DATA!D:G,4,0)=1,'FACT_EST_CEN','SIN_DATA')))!B:B,Reliquidacion!B22,IF(VLOOKUP(B9,MAPA_DATA!D:G,2,0)=1,'FACT_EMITIDA',IF(VLOOKUP(B22,MAPA_DATA!D:G,3,0)=1,'FACT_EST_EFACT',(IF(VLOOKUP(B22,MAPA_DATA!D:G,4,0)=1,'FACT_EST_CEN','SIN_DATA')))!F:F) | E22: =CONCATENATE("(F",A22,"/D",A22,")") -> (F22/D22) | F22: =CONCATENATE("SUMIF(",IF(C22="FACT_EMITIDA","SIGGE_E",C22),"!B:B,Reliquidacion!B",A22,",",IF(C22="FACT_EMITIDA","SIGGE_E",C22),"!H:H)") -> SUMIF(IF(VLOOKUP(B9,MAPA_DATA!D:G,2,0)=1,'FACT_EMITIDA',IF(VLOOKUP(B22,MAPA_DATA!D:G,3,0)=1,'FACT_EST_EFACT',(IF(VLOOKUP(B22,MAPA_DATA!D:G,4,0)=1,'FACT_EST_CEN','SIN_DATA')))!B:B,Reliquidacion!B22,IF(VLOOKUP(B9,MAPA_DATA!D:G,2,0)=1,'FACT_EMITIDA',IF(VLOOKUP(B22,MAPA_DATA!D:G,3,0)=1,'FACT_EST_EFACT',(IF(VLOOKUP(B22,MAPA_DATA!D:G,4,0)=1,'FACT_EST_CEN','SIN_DATA')))!H:H) | G22: =CONCATENATE("SUMIF(",IF(C22="FACT_EMITIDA","SIGGE_P",C22),"!B:B,Reliquidacion!B",A22,",",IF(C22="FACT_EMITIDA","SIGGE_P",C22),"!F:F)") -> SUMIF(IF(VLOOKUP(B9,MAPA_DATA!D:G,2,0)=1,'FACT_EMITIDA',IF(VLOOKUP(B22,MAPA_DATA!D:G,3,0)=1,'FACT_EST_EFACT',(IF(VLOOKUP(B22,MAPA_DATA!D:G,4,0)=1,'FACT_EST_CEN','SIN_DATA')))!B:B,Reliquidacion!B22,IF(VLOOKUP(B9,MAPA_DATA!D:G,2,0)=1,'FACT_EMITIDA',IF(VLOOKUP(B22,MAPA_DATA!D:G,3,0)=1,'FACT_EST_EFACT',(IF(VLOOKUP(B22,MAPA_DATA!D:G,4,0)=1,'FACT_EST_CEN','SIN_DATA')))!F:F) | H22: =CONCATENATE("(I",A22,"/G",A22,")") -> (I22/G22) | I22: =CONCATENATE("SUMIF(",IF(C22="FACT_EMITIDA","SIGGE_P",C22),"!B:B,Reliquidacion!B",A22,",",IF(C22="FACT_EMITIDA","SIGGE_P",C22),"!H:H)") -> SUMIF(IF(VLOOKUP(B9,MAPA_DATA!D:G,2,0)=1,'FACT_EMITIDA',IF(VLOOKUP(B22,MAPA_DATA!D:G,3,0)=1,'FACT_EST_EFACT',(IF(VLOOKUP(B22,MAPA_DATA!D:G,4,0)=1,'FACT_EST_CEN','SIN_DATA')))!B:B,Reliquidacion!B22,IF(VLOOKUP(B9,MAPA_DATA!D:G,2,0)=1,'FACT_EMITIDA',IF(VLOOKUP(B22,MAPA_DATA!D:G,3,0)=1,'FACT_EST_EFACT',(IF(VLOOKUP(B22,MAPA_DATA!D:G,4,0)=1,'FACT_EST_CEN','SIN_DATA')))!H:H) | J22: =CONCATENATE("(F",A22,"+I",A22,")") -> (F22+I22) | L22: =IF(VLOOKUP(B22,MAPA_DATA!D:I,5,0)=1,"EFACT_CNE",IF(VLOOKUP(B22,MAPA_DATA!D:I,6,0)=1,"EFACT_EST_CNE","SIN_DATA")) -> SIN_DATA | M22: =CONCATENATE("SUMIF(",L22,"!B:B;Reliquidacion!B",A22,";",L22,"!S:S)") -> SUMIF(SIN_DATA!B:B;Reliquidacion!B22;SIN_DATA!S:S) | N22: =CONCATENATE("(O",A22,"/M",A22,")") -> (O22/M22) | O22: =CONCATENATE("SUMIF(",L22,"!B:B;Reliquidacion!B",A22,";",L22,"!W:W)") -> SUMIF(SIN_DATA!B:B;Reliquidacion!B22;SIN_DATA!W:W) | P22: =CONCATENATE("SUMIF(",L22,"!B:B;Reliquidacion!B",A22,";",L22,"!X:X)") -> SUMIF(SIN_DATA!B:B;Reliquidacion!B22;SIN_DATA!X:X) | Q22: =CONCATENATE("(R",A22,"/P",A22,")") -> (R22/P22) | R22: =CONCATENATE("SUMIF(",L22,"!B:B;Reliquidacion!B",A22,";",L22,"!AB:AB)") -> SUMIF(SIN_DATA!B:B;Reliquidacion!B22;SIN_DATA!AB:AB) | S22: =CONCATENATE("(O",A22,"+R",A22,")") -> (O22+R22) | U22: 42767 | V22: =CONCATENATE("=(S",A22,"-J",A22,")") -> =(S22-J22) | W22: 12T/28-11-2017 | X22: =VLOOKUP(W22,[1]INTERESES!A:B,2,0) -> 0 | Y22: =VLOOKUP(W22,#REF!,6,0) -> #REF! | Z22: 43156 | AA22: 44377 | AB22: =AA22-Z22 -> 1221 | AC22: =+(1+Y22)^(AB22/360)-1 -> #REF! | AD22: =AC22*V22 -> #REF! | AE22: =+V22+AD22 -> #VALUE!
A23: =A22+1 -> 23 | B23: 42795 | C23: =CONCATENATE("IF(VLOOKUP(B9,MAPA_DATA!D:G,2,0)=1,'FACT_EMITIDA',IF(VLOOKUP(B",A23,",MAPA_DATA!D:G,3,0)=1,'FACT_EST_EFACT',(IF(VLOOKUP(B",A23,",MAPA_DATA!D:G,4,0)=1,'FACT_EST_CEN','SIN_DATA')))") -> IF(VLOOKUP(B9,MAPA_DATA!D:G,2,0)=1,'FACT_EMITIDA',IF(VLOOKUP(B23,MAPA_DATA!D:G,3,0)=1,'FACT_EST_EFACT',(IF(VLOOKUP(B23,MAPA_DATA!D:G,4,0)=1,'FACT_EST_CEN','SIN_DATA'))) | D23: =CONCATENATE("SUMIF(",IF(C23="FACT_EMITIDA","SIGGE_E",C23),"!B:B,Reliquidacion!B",A23,",",IF(C23="FACT_EMITIDA","SIGGE_E",C23),"!F:F)") -> SUMIF(IF(VLOOKUP(B9,MAPA_DATA!D:G,2,0)=1,'FACT_EMITIDA',IF(VLOOKUP(B23,MAPA_DATA!D:G,3,0)=1,'FACT_EST_EFACT',(IF(VLOOKUP(B23,MAPA_DATA!D:G,4,0)=1,'FACT_EST_CEN','SIN_DATA')))!B:B,Reliquidacion!B23,IF(VLOOKUP(B9,MAPA_DATA!D:G,2,0)=1,'FACT_EMITIDA',IF(VLOOKUP(B23,MAPA_DATA!D:G,3,0)=1,'FACT_EST_EFACT',(IF(VLOOKUP(B23,MAPA_DATA!D:G,4,0)=1,'FACT_EST_CEN','SIN_DATA')))!F:F) | E23: =CONCATENATE("(F",A23,"/D",A23,")") -> (F23/D23) | F23: =CONCATENATE("SUMIF(",IF(C23="FACT_EMITIDA","SIGGE_E",C23),"!B:B,Reliquidacion!B",A23,",",IF(C23="FACT_EMITIDA","SIGGE_E",C23),"!H:H)") -> SUMIF(IF(VLOOKUP(B9,MAPA_DATA!D:G,2,0)=1,'FACT_EMITIDA',IF(VLOOKUP(B23,MAPA_DATA!D:G,3,0)=1,'FACT_EST_EFACT',(IF(VLOOKUP(B23,MAPA_DATA!D:G,4,0)=1,'FACT_EST_CEN','SIN_DATA')))!B:B,Reliquidacion!B23,IF(VLOOKUP(B9,MAPA_DATA!D:G,2,0)=1,'FACT_EMITIDA',IF(VLOOKUP(B23,MAPA_DATA!D:G,3,0)=1,'FACT_EST_EFACT',(IF(VLOOKUP(B23,MAPA_DATA!D:G,4,0)=1,'FACT_EST_CEN','SIN_DATA')))!H:H) | G23: =CONCATENATE("SUMIF(",IF(C23="FACT_EMITIDA","SIGGE_P",C23),"!B:B,Reliquidacion!B",A23,",",IF(C23="FACT_EMITIDA","SIGGE_P",C23),"!F:F)") -> SUMIF(IF(VLOOKUP(B9,MAPA_DATA!D:G,2,0)=1,'FACT_EMITIDA',IF(VLOOKUP(B23,MAPA_DATA!D:G,3,0)=1,'FACT_EST_EFACT',(IF(VLOOKUP(B23,MAPA_DATA!D:G,4,0)=1,'FACT_EST_CEN','SIN_DATA')))!B:B,Reliquidacion!B23,IF(VLOOKUP(B9,MAPA_DATA!D:G,2,0)=1,'FACT_EMITIDA',IF(VLOOKUP(B23,MAPA_DATA!D:G,3,0)=1,'FACT_EST_EFACT',(IF(VLOOKUP(B23,MAPA_DATA!D:G,4,0)=1,'FACT_EST_CEN','SIN_DATA')))!F:F) | H23: =CONCATENATE("(I",A23,"/G",A23,")") -> (I23/G23) | I23: =CONCATENATE("SUMIF(",IF(C23="FACT_EMITIDA","SIGGE_P",C23),"!B:B,Reliquidacion!B",A23,",",IF(C23="FACT_EMITIDA","SIGGE_P",C23),"!H:H)") -> SUMIF(IF(VLOOKUP(B9,MAPA_DATA!D:G,2,0)=1,'FACT_EMITIDA',IF(VLOOKUP(B23,MAPA_DATA!D:G,3,0)=1,'FACT_EST_EFACT',(IF(VLOOKUP(B23,MAPA_DATA!D:G,4,0)=1,'FACT_EST_CEN','SIN_DATA')))!B:B,Reliquidacion!B23,IF(VLOOKUP(B9,MAPA_DATA!D:G,2,0)=1,'FACT_EMITIDA',IF(VLOOKUP(B23,MAPA_DATA!D:G,3,0)=1,'FACT_EST_EFACT',(IF(VLOOKUP(B23,MAPA_DATA!D:G,4,0)=1,'FACT_EST_CEN','SIN_DATA')))!H:H) | J23: =CONCATENATE("(F",A23,"+I",A23,")") -> (F23+I23) | L23: =IF(VLOOKUP(B23,MAPA_DATA!D:I,5,0)=1,"EFACT_CNE",IF(VLOOKUP(B23,MAPA_DATA!D:I,6,0)=1,"EFACT_EST_CNE","SIN_DATA")) -> SIN_DATA | M23: =CONCATENATE("SUMIF(",L23,"!B:B;Reliquidacion!B",A23,";",L23,"!S:S)") -> SUMIF(SIN_DATA!B:B;Reliquidacion!B23;SIN_DATA!S:S) | N23: =CONCATENATE("(O",A23,"/M",A23,")") -> (O23/M23) | O23: =CONCATENATE("SUMIF(",L23,"!B:B;Reliquidacion!B",A23,";",L23,"!W:W)") -> SUMIF(SIN_DATA!B:B;Reliquidacion!B23;SIN_DATA!W:W) | P23: =CONCATENATE("SUMIF(",L23,"!B:B;Reliquidacion!B",A23,";",L23,"!X:X)") -> SUMIF(SIN_DATA!B:B;Reliquidacion!B23;SIN_DATA!X:X) | Q23: =CONCATENATE("(R",A23,"/P",A23,")") -> (R23/P23) | R23: =CONCATENATE("SUMIF(",L23,"!B:B;Reliquidacion!B",A23,";",L23,"!AB:AB)") -> SUMIF(SIN_DATA!B:B;Reliquidacion!B23;SIN_DATA!AB:AB) | S23: =CONCATENATE("(O",A23,"+R",A23,")") -> (O23+R23) | U23: 42795 | V23: =CONCATENATE("=(S",A23,"-J",A23,")") -> =(S23-J23) | W23: 12T/28-11-2017 | X23: =VLOOKUP(W23,[1]INTERESES!A:B,2,0) -> 0
A24: =A23+1 -> 24 | B24: 42826 | C24: =CONCATENATE("IF(VLOOKUP(B9,MAPA_DATA!D:G,2,0)=1,'FACT_EMITIDA',IF(VLOOKUP(B",A24,",MAPA_DATA!D:G,3,0)=1,'FACT_EST_EFACT',(IF(VLOOKUP(B",A24,",MAPA_DATA!D:G,4,0)=1,'FACT_EST_CEN','SIN_DATA')))") -> IF(VLOOKUP(B9,MAPA_DATA!D:G,2,0)=1,'FACT_EMITIDA',IF(VLOOKUP(B24,MAPA_DATA!D:G,3,0)=1,'FACT_EST_EFACT',(IF(VLOOKUP(B24,MAPA_DATA!D:G,4,0)=1,'FACT_EST_CEN','SIN_DATA'))) | D24: =CONCATENATE("SUMIF(",IF(C24="FACT_EMITIDA","SIGGE_E",C24),"!B:B,Reliquidacion!B",A24,",",IF(C24="FACT_EMITIDA","SIGGE_E",C24),"!F:F)") -> SUMIF(IF(VLOOKUP(B9,MAPA_DATA!D:G,2,0)=1,'FACT_EMITIDA',IF(VLOOKUP(B24,MAPA_DATA!D:G,3,0)=1,'FACT_EST_EFACT',(IF(VLOOKUP(B24,MAPA_DATA!D:G,4,0)=1,'FACT_EST_CEN','SIN_DATA')))!B:B,Reliquidacion!B24,IF(VLOOKUP(B9,MAPA_DATA!D:G,2,0)=1,'FACT_EMITIDA',IF(VLOOKUP(B24,MAPA_DATA!D:G,3,0)=1,'FACT_EST_EFACT',(IF(VLOOKUP(B24,MAPA_DATA!D:G,4,0)=1,'FACT_EST_CEN','SIN_DATA')))!F:F) | E24: =CONCATENATE("(F",A24,"/D",A24,")") -> (F24/D24) | F24: =CONCATENATE("SUMIF(",IF(C24="FACT_EMITIDA","SIGGE_E",C24),"!B:B,Reliquidacion!B",A24,",",IF(C24="FACT_EMITIDA","SIGGE_E",C24),"!H:H)") -> SUMIF(IF(VLOOKUP(B9,MAPA_DATA!D:G,2,0)=1,'FACT_EMITIDA',IF(VLOOKUP(B24,MAPA_DATA!D:G,3,0)=1,'FACT_EST_EFACT',(IF(VLOOKUP(B24,MAPA_DATA!D:G,4,0)=1,'FACT_EST_CEN','SIN_DATA')))!B:B,Reliquidacion!B24,IF(VLOOKUP(B9,MAPA_DATA!D:G,2,0)=1,'FACT_EMITIDA',IF(VLOOKUP(B24,MAPA_DATA!D:G,3,0)=1,'FACT_EST_EFACT',(IF(VLOOKUP(B24,MAPA_DATA!D:G,4,0)=1,'FACT_EST_CEN','SIN_DATA')))!H:H) | G24: =CONCATENATE("SUMIF(",IF(C24="FACT_EMITIDA","SIGGE_P",C24),"!B:B,Reliquidacion!B",A24,",",IF(C24="FACT_EMITIDA","SIGGE_P",C24),"!F:F)") -> SUMIF(IF(VLOOKUP(B9,MAPA_DATA!D:G,2,0)=1,'FACT_EMITIDA',IF(VLOOKUP(B24,MAPA_DATA!D:G,3,0)=1,'FACT_EST_EFACT',(IF(VLOOKUP(B24,MAPA_DATA!D:G,4,0)=1,'FACT_EST_CEN','SIN_DATA')))!B:B,Reliquidacion!B24,IF(VLOOKUP(B9,MAPA_DATA!D:G,2,0)=1,'FACT_EMITIDA',IF(VLOOKUP(B24,MAPA_DATA!D:G,3,0)=1,'FACT_EST_EFACT',(IF(VLOOKUP(B24,MAPA_DATA!D:G,4,0)=1,'FACT_EST_CEN','SIN_DATA')))!F:F) | H24: =CONCATENATE("(I",A24,"/G",A24,")") -> (I24/G24) | I24: =CONCATENATE("SUMIF(",IF(C24="FACT_EMITIDA","SIGGE_P",C24),"!B:B,Reliquidacion!B",A24,",",IF(C24="FACT_EMITIDA","SIGGE_P",C24),"!H:H)") -> SUMIF(IF(VLOOKUP(B9,MAPA_DATA!D:G,2,0)=1,'FACT_EMITIDA',IF(VLOOKUP(B24,MAPA_DATA!D:G,3,0)=1,'FACT_EST_EFACT',(IF(VLOOKUP(B24,MAPA_DATA!D:G,4,0)=1,'FACT_EST_CEN','SIN_DATA')))!B:B,Reliquidacion!B24,IF(VLOOKUP(B9,MAPA_DATA!D:G,2,0)=1,'FACT_EMITIDA',IF(VLOOKUP(B24,MAPA_DATA!D:G,3,0)=1,'FACT_EST_EFACT',(IF(VLOOKUP(B24,MAPA_DATA!D:G,4,0)=1,'FACT_EST_CEN','SIN_DATA')))!H:H) | J24: =CONCATENATE("(F",A24,"+I",A24,")") -> (F24+I24) | L24: =IF(VLOOKUP(B24,MAPA_DATA!D:I,5,0)=1,"EFACT_CNE",IF(VLOOKUP(B24,MAPA_DATA!D:I,6,0)=1,"EFACT_EST_CNE","SIN_DATA")) -> SIN_DATA | M24: =CONCATENATE("SUMIF(",L24,"!B:B;Reliquidacion!B",A24,";",L24,"!S:S)") -> SUMIF(SIN_DATA!B:B;Reliquidacion!B24;SIN_DATA!S:S) | N24: =CONCATENATE("(O",A24,"/M",A24,")") -> (O24/M24) | O24: =CONCATENATE("SUMIF(",L24,"!B:B;Reliquidacion!B",A24,";",L24,"!W:W)") -> SUMIF(SIN_DATA!B:B;Reliquidacion!B24;SIN_DATA!W:W) | P24: =CONCATENATE("SUMIF(",L24,"!B:B;Reliquidacion!B",A24,";",L24,"!X:X)") -> SUMIF(SIN_DATA!B:B;Reliquidacion!B24;SIN_DATA!X:X) | Q24: =CONCATENATE("(R",A24,"/P",A24,")") -> (R24/P24) | R24: =CONCATENATE("SUMIF(",L24,"!B:B;Reliquidacion!B",A24,";",L24,"!AB:AB)") -> SUMIF(SIN_DATA!B:B;Reliquidacion!B24;SIN_DATA!AB:AB) | S24: =CONCATENATE("(O",A24,"+R",A24,")") -> (O24+R24) | U24: 42826 | V24: =CONCATENATE("=(S",A24,"-J",A24,")") -> =(S24-J24) | W24: 12T/28-11-2017 | X24: =VLOOKUP(W24,[1]INTERESES!A:B,2,0) -> 0
A25: =A24+1 -> 25 | B25: 42856 | C25: =CONCATENATE("IF(VLOOKUP(B9,MAPA_DATA!D:G,2,0)=1,'FACT_EMITIDA',IF(VLOOKUP(B",A25,",MAPA_DATA!D:G,3,0)=1,'FACT_EST_EFACT',(IF(VLOOKUP(B",A25,",MAPA_DATA!D:G,4,0)=1,'FACT_EST_CEN','SIN_DATA')))") -> IF(VLOOKUP(B9,MAPA_DATA!D:G,2,0)=1,'FACT_EMITIDA',IF(VLOOKUP(B25,MAPA_DATA!D:G,3,0)=1,'FACT_EST_EFACT',(IF(VLOOKUP(B25,MAPA_DATA!D:G,4,0)=1,'FACT_EST_CEN','SIN_DATA'))) | D25: =CONCATENATE("SUMIF(",IF(C25="FACT_EMITIDA","SIGGE_E",C25),"!B:B,Reliquidacion!B",A25,",",IF(C25="FACT_EMITIDA","SIGGE_E",C25),"!F:F)") -> SUMIF(IF(VLOOKUP(B9,MAPA_DATA!D:G,2,0)=1,'FACT_EMITIDA',IF(VLOOKUP(B25,MAPA_DATA!D:G,3,0)=1,'FACT_EST_EFACT',(IF(VLOOKUP(B25,MAPA_DATA!D:G,4,0)=1,'FACT_EST_CEN','SIN_DATA')))!B:B,Reliquidacion!B25,IF(VLOOKUP(B9,MAPA_DATA!D:G,2,0)=1,'FACT_EMITIDA',IF(VLOOKUP(B25,MAPA_DATA!D:G,3,0)=1,'FACT_EST_EFACT',(IF(VLOOKUP(B25,MAPA_DATA!D:G,4,0)=1,'FACT_EST_CEN','SIN_DATA')))!F:F) | E25: =CONCATENATE("(F",A25,"/D",A25,")") -> (F25/D25) | F25: =CONCATENATE("SUMIF(",IF(C25="FACT_EMITIDA","SIGGE_E",C25),"!B:B,Reliquidacion!B",A25,",",IF(C25="FACT_EMITIDA","SIGGE_E",C25),"!H:H)") -> SUMIF(IF(VLOOKUP(B9,MAPA_DATA!D:G,2,0)=1,'FACT_EMITIDA',IF(VLOOKUP(B25,MAPA_DATA!D:G,3,0)=1,'FACT_EST_EFACT',(IF(VLOOKUP(B25,MAPA_DATA!D:G,4,0)=1,'FACT_EST_CEN','SIN_DATA')))!B:B,Reliquidacion!B25,IF(VLOOKUP(B9,MAPA_DATA!D:G,2,0)=1,'FACT_EMITIDA',IF(VLOOKUP(B25,MAPA_DATA!D:G,3,0)=1,'FACT_EST_EFACT',(IF(VLOOKUP(B25,MAPA_DATA!D:G,4,0)=1,'FACT_EST_CEN','SIN_DATA')))!H:H) | G25: =CONCATENATE("SUMIF(",IF(C25="FACT_EMITIDA","SIGGE_P",C25),"!B:B,Reliquidacion!B",A25,",",IF(C25="FACT_EMITIDA","SIGGE_P",C25),"!F:F)") -> SUMIF(IF(VLOOKUP(B9,MAPA_DATA!D:G,2,0)=1,'FACT_EMITIDA',IF(VLOOKUP(B25,MAPA_DATA!D:G,3,0)=1,'FACT_EST_EFACT',(IF(VLOOKUP(B25,MAPA_DATA!D:G,4,0)=1,'FACT_EST_CEN','SIN_DATA')))!B:B,Reliquidacion!B25,IF(VLOOKUP(B9,MAPA_DATA!D:G,2,0)=1,'FACT_EMITIDA',IF(VLOOKUP(B25,MAPA_DATA!D:G,3,0)=1,'FACT_EST_EFACT',(IF(VLOOKUP(B25,MAPA_DATA!D:G,4,0)=1,'FACT_EST_CEN','SIN_DATA')))!F:F) | H25: =CONCATENATE("(I",A25,"/G",A25,")") -> (I25/G25) | I25: =CONCATENATE("SUMIF(",IF(C25="FACT_EMITIDA","SIGGE_P",C25),"!B:B,Reliquidacion!B",A25,",",IF(C25="FACT_EMITIDA","SIGGE_P",C25),"!H:H)") -> SUMIF(IF(VLOOKUP(B9,MAPA_DATA!D:G,2,0)=1,'FACT_EMITIDA',IF(VLOOKUP(B25,MAPA_DATA!D:G,3,0)=1,'FACT_EST_EFACT',(IF(VLOOKUP(B25,MAPA_DATA!D:G,4,0)=1,'FACT_EST_CEN','SIN_DATA')))!B:B,Reliquidacion!B25,IF(VLOOKUP(B9,MAPA_DATA!D:G,2,0)=1,'FACT_EMITIDA',IF(VLOOKUP(B25,MAPA_DATA!D:G,3,0)=1,'FACT_EST_EFACT',(IF(VLOOKUP(B25,MAPA_DATA!D:G,4,0)=1,'FACT_EST_CEN','SIN_DATA')))!H:H) | J25: =CONCATENATE("(F",A25,"+I",A25,")") -> (F25+I25) | L25: =IF(VLOOKUP(B25,MAPA_DATA!D:I,5,0)=1,"EFACT_CNE",IF(VLOOKUP(B25,MAPA_DATA!D:I,6,0)=1,"EFACT_EST_CNE","SIN_DATA")) -> SIN_DATA | M25: =CONCATENATE("SUMIF(",L25,"!B:B;Reliquidacion!B",A25,";",L25,"!S:S)") -> SUMIF(SIN_DATA!B:B;Reliquidacion!B25;SIN_DATA!S:S) | N25: =CONCATENATE("(O",A25,"/M",A25,")") -> (O25/M25) | O25: =CONCATENATE("SUMIF(",L25,"!B:B;Reliquidacion!B",A25,";",L25,"!W:W)") -> SUMIF(SIN_DATA!B:B;Reliquidacion!B25;SIN_DATA!W:W) | P25: =CONCATENATE("SUMIF(",L25,"!B:B;Reliquidacion!B",A25,";",L25,"!X:X)") -> SUMIF(SIN_DATA!B:B;Reliquidacion!B25;SIN_DATA!X:X) | Q25: =CONCATENATE("(R",A25,"/P",A25,")") -> (R25/P25) | R25: =CONCATENATE("SUMIF(",L25,"!B:B;Reliquidacion!B",A25,";",L25,"!AB:AB)") -> SUMIF(SIN_DATA!B:B;Reliquidacion!B25;SIN_DATA!AB:AB) | S25: =CONCATENATE("(O",A25,"+R",A25,")") -> (O25+R25) | U25: 42856 | V25: =CONCATENATE("=(S",A25,"-J",A25,")") -> =(S25-J25) | W25: 12T/28-11-2017 | X25: =VLOOKUP(W25,[1]INTERESES!A:B,2,0) -> 0
A26: =A25+1 -> 26 | B26: 42887 | C26: =CONCATENATE("IF(VLOOKUP(B9,MAPA_DATA!D:G,2,0)=1,'FACT_EMITIDA',IF(VLOOKUP(B",A26,",MAPA_DATA!D:G,3,0)=1,'FACT_EST_EFACT',(IF(VLOOKUP(B",A26,",MAPA_DATA!D:G,4,0)=1,'FACT_EST_CEN','SIN_DATA')))") -> IF(VLOOKUP(B9,MAPA_DATA!D:G,2,0)=1,'FACT_EMITIDA',IF(VLOOKUP(B26,MAPA_DATA!D:G,3,0)=1,'FACT_EST_EFACT',(IF(VLOOKUP(B26,MAPA_DATA!D:G,4,0)=1,'FACT_EST_CEN','SIN_DATA'))) | D26: =CONCATENATE("SUMIF(",IF(C26="FACT_EMITIDA","SIGGE_E",C26),"!B:B,Reliquidacion!B",A26,",",IF(C26="FACT_EMITIDA","SIGGE_E",C26),"!F:F)") -> SUMIF(IF(VLOOKUP(B9,MAPA_DATA!D:G,2,0)=1,'FACT_EMITIDA',IF(VLOOKUP(B26,MAPA_DATA!D:G,3,0)=1,'FACT_EST_EFACT',(IF(VLOOKUP(B26,MAPA_DATA!D:G,4,0)=1,'FACT_EST_CEN','SIN_DATA')))!B:B,Reliquidacion!B26,IF(VLOOKUP(B9,MAPA_DATA!D:G,2,0)=1,'FACT_EMITIDA',IF(VLOOKUP(B26,MAPA_DATA!D:G,3,0)=1,'FACT_EST_EFACT',(IF(VLOOKUP(B26,MAPA_DATA!D:G,4,0)=1,'FACT_EST_CEN','SIN_DATA')))!F:F) | E26: =CONCATENATE("(F",A26,"/D",A26,")") -> (F26/D26) | F26: =CONCATENATE("SUMIF(",IF(C26="FACT_EMITIDA","SIGGE_E",C26),"!B:B,Reliquidacion!B",A26,",",IF(C26="FACT_EMITIDA","SIGGE_E",C26),"!H:H)") -> SUMIF(IF(VLOOKUP(B9,MAPA_DATA!D:G,2,0)=1,'FACT_EMITIDA',IF(VLOOKUP(B26,MAPA_DATA!D:G,3,0)=1,'FACT_EST_EFACT',(IF(VLOOKUP(B26,MAPA_DATA!D:G,4,0)=1,'FACT_EST_CEN','SIN_DATA')))!B:B,Reliquidacion!B26,IF(VLOOKUP(B9,MAPA_DATA!D:G,2,0)=1,'FACT_EMITIDA',IF(VLOOKUP(B26,MAPA_DATA!D:G,3,0)=1,'FACT_EST_EFACT',(IF(VLOOKUP(B26,MAPA_DATA!D:G,4,0)=1,'FACT_EST_CEN','SIN_DATA')))!H:H) | G26: =CONCATENATE("SUMIF(",IF(C26="FACT_EMITIDA","SIGGE_P",C26),"!B:B,Reliquidacion!B",A26,",",IF(C26="FACT_EMITIDA","SIGGE_P",C26),"!F:F)") -> SUMIF(IF(VLOOKUP(B9,MAPA_DATA!D:G,2,0)=1,'FACT_EMITIDA',IF(VLOOKUP(B26,MAPA_DATA!D:G,3,0)=1,'FACT_EST_EFACT',(IF(VLOOKUP(B26,MAPA_DATA!D:G,4,0)=1,'FACT_EST_CEN','SIN_DATA')))!B:B,Reliquidacion!B26,IF(VLOOKUP(B9,MAPA_DATA!D:G,2,0)=1,'FACT_EMITIDA',IF(VLOOKUP(B26,MAPA_DATA!D:G,3,0)=1,'FACT_EST_EFACT',(IF(VLOOKUP(B26,MAPA_DATA!D:G,4,0)=1,'FACT_EST_CEN','SIN_DATA')))!F:F) | H26: =CONCATENATE("(I",A26,"/G",A26,")") -> (I26/G26) | I26: =CONCATENATE("SUMIF(",IF(C26="FACT_EMITIDA","SIGGE_P",C26),"!B:B,Reliquidacion!B",A26,",",IF(C26="FACT_EMITIDA","SIGGE_P",C26),"!H:H)") -> SUMIF(IF(VLOOKUP(B9,MAPA_DATA!D:G,2,0)=1,'FACT_EMITIDA',IF(VLOOKUP(B26,MAPA_DATA!D:G,3,0)=1,'FACT_EST_EFACT',(IF(VLOOKUP(B26,MAPA_DATA!D:G,4,0)=1,'FACT_EST_CEN','SIN_DATA')))!B:B,Reliquidacion!B26,IF(VLOOKUP(B9,MAPA_DATA!D:G,2,0)=1,'FACT_EMITIDA',IF(VLOOKUP(B26,MAPA_DATA!D:G,3,0)=1,'FACT_EST_EFACT',(IF(VLOOKUP(B26,MAPA_DATA!D:G,4,0)=1,'FACT_EST_CEN','SIN_DATA')))!H:H) | J26: =CONCATENATE("(F",A26,"+I",A26,")") -> (F26+I26) | L26: =IF(VLOOKUP(B26,MAPA_DATA!D:I,5,0)=1,"EFACT_CNE",IF(VLOOKUP(B26,MAPA_DATA!D:I,6,0)=1,"EFACT_EST_CNE","SIN_DATA")) -> SIN_DATA | M26: =CONCATENATE("SUMIF(",L26,"!B:B;Reliquidacion!B",A26,";",L26,"!S:S)") -> SUMIF(SIN_DATA!B:B;Reliquidacion!B26;SIN_DATA!S:S) | N26: =CONCATENATE("(O",A26,"/M",A26,")") -> (O26/M26) | O26: =CONCATENATE("SUMIF(",L26,"!B:B;Reliquidacion!B",A26,";",L26,"!W:W)") -> SUMIF(SIN_DATA!B:B;Reliquidacion!B26;SIN_DATA!W:W) | P26: =CONCATENATE("SUMIF(",L26,"!B:B;Reliquidacion!B",A26,";",L26,"!X:X)") -> SUMIF(SIN_DATA!B:B;Reliquidacion!B26;SIN_DATA!X:X) | Q26: =CONCATENATE("(R",A26,"/P",A26,")") -> (R26/P26) | R26: =CONCATENATE("SUMIF(",L26,"!B:B;Reliquidacion!B",A26,";",L26,"!AB:AB)") -> SUMIF(SIN_DATA!B:B;Reliquidacion!B26;SIN_DATA!AB:AB) | S26: =CONCATENATE("(O",A26,"+R",A26,")") -> (O26+R26) | U26: 42887 | V26: =CONCATENATE("=(S",A26,"-J",A26,")") -> =(S26-J26) | W26: 12T/28-11-2017 | X26: =VLOOKUP(W26,[1]INTERESES!A:B,2,0) -> 0
A27: =A26+1 -> 27 | B27: 42917 | C27: =CONCATENATE("IF(VLOOKUP(B9,MAPA_DATA!D:G,2,0)=1,'FACT_EMITIDA',IF(VLOOKUP(B",A27,",MAPA_DATA!D:G,3,0)=1,'FACT_EST_EFACT',(IF(VLOOKUP(B",A27,",MAPA_DATA!D:G,4,0)=1,'FACT_EST_CEN','SIN_DATA')))") -> IF(VLOOKUP(B9,MAPA_DATA!D:G,2,0)=1,'FACT_EMITIDA',IF(VLOOKUP(B27,MAPA_DATA!D:G,3,0)=1,'FACT_EST_EFACT',(IF(VLOOKUP(B27,MAPA_DATA!D:G,4,0)=1,'FACT_EST_CEN','SIN_DATA'))) | D27: =CONCATENATE("SUMIF(",IF(C27="FACT_EMITIDA","SIGGE_E",C27),"!B:B,Reliquidacion!B",A27,",",IF(C27="FACT_EMITIDA","SIGGE_E",C27),"!F:F)") -> SUMIF(IF(VLOOKUP(B9,MAPA_DATA!D:G,2,0)=1,'FACT_EMITIDA',IF(VLOOKUP(B27,MAPA_DATA!D:G,3,0)=1,'FACT_EST_EFACT',(IF(VLOOKUP(B27,MAPA_DATA!D:G,4,0)=1,'FACT_EST_CEN','SIN_DATA')))!B:B,Reliquidacion!B27,IF(VLOOKUP(B9,MAPA_DATA!D:G,2,0)=1,'FACT_EMITIDA',IF(VLOOKUP(B27,MAPA_DATA!D:G,3,0)=1,'FACT_EST_EFACT',(IF(VLOOKUP(B27,MAPA_DATA!D:G,4,0)=1,'FACT_EST_CEN','SIN_DATA')))!F:F) | E27: =CONCATENATE("(F",A27,"/D",A27,")") -> (F27/D27) | F27: =CONCATENATE("SUMIF(",IF(C27="FACT_EMITIDA","SIGGE_E",C27),"!B:B,Reliquidacion!B",A27,",",IF(C27="FACT_EMITIDA","SIGGE_E",C27),"!H:H)") -> SUMIF(IF(VLOOKUP(B9,MAPA_DATA!D:G,2,0)=1,'FACT_EMITIDA',IF(VLOOKUP(B27,MAPA_DATA!D:G,3,0)=1,'FACT_EST_EFACT',(IF(VLOOKUP(B27,MAPA_DATA!D:G,4,0)=1,'FACT_EST_CEN','SIN_DATA')))!B:B,Reliquidacion!B27,IF(VLOOKUP(B9,MAPA_DATA!D:G,2,0)=1,'FACT_EMITIDA',IF(VLOOKUP(B27,MAPA_DATA!D:G,3,0)=1,'FACT_EST_EFACT',(IF(VLOOKUP(B27,MAPA_DATA!D:G,4,0)=1,'FACT_EST_CEN','SIN_DATA')))!H:H) | G27: =CONCATENATE("SUMIF(",IF(C27="FACT_EMITIDA","SIGGE_P",C27),"!B:B,Reliquidacion!B",A27,",",IF(C27="FACT_EMITIDA","SIGGE_P",C27),"!F:F)") -> SUMIF(IF(VLOOKUP(B9,MAPA_DATA!D:G,2,0)=1,'FACT_EMITIDA',IF(VLOOKUP(B27,MAPA_DATA!D:G,3,0)=1,'FACT_EST_EFACT',(IF(VLOOKUP(B27,MAPA_DATA!D:G,4,0)=1,'FACT_EST_CEN','SIN_DATA')))!B:B,Reliquidacion!B27,IF(VLOOKUP(B9,MAPA_DATA!D:G,2,0)=1,'FACT_EMITIDA',IF(VLOOKUP(B27,MAPA_DATA!D:G,3,0)=1,'FACT_EST_EFACT',(IF(VLOOKUP(B27,MAPA_DATA!D:G,4,0)=1,'FACT_EST_CEN','SIN_DATA')))!F:F) | H27: =CONCATENATE("(I",A27,"/G",A27,")") -> (I27/G27) | I27: =CONCATENATE("SUMIF(",IF(C27="FACT_EMITIDA","SIGGE_P",C27),"!B:B,Reliquidacion!B",A27,",",IF(C27="FACT_EMITIDA","SIGGE_P",C27),"!H:H)") -> SUMIF(IF(VLOOKUP(B9,MAPA_DATA!D:G,2,0)=1,'FACT_EMITIDA',IF(VLOOKUP(B27,MAPA_DATA!D:G,3,0)=1,'FACT_EST_EFACT',(IF(VLOOKUP(B27,MAPA_DATA!D:G,4,0)=1,'FACT_EST_CEN','SIN_DATA')))!B:B,Reliquidacion!B27,IF(VLOOKUP(B9,MAPA_DATA!D:G,2,0)=1,'FACT_EMITIDA',IF(VLOOKUP(B27,MAPA_DATA!D:G,3,0)=1,'FACT_EST_EFACT',(IF(VLOOKUP(B27,MAPA_DATA!D:G,4,0)=1,'FACT_EST_CEN','SIN_DATA')))!H:H) | J27: =CONCATENATE("(F",A27,"+I",A27,")") -> (F27+I27) | L27: =IF(VLOOKUP(B27,MAPA_DATA!D:I,5,0)=1,"EFACT_CNE",IF(VLOOKUP(B27,MAPA_DATA!D:I,6,0)=1,"EFACT_EST_CNE","SIN_DATA")) -> SIN_DATA | M27: =CONCATENATE("SUMIF(",L27,"!B:B;Reliquidacion!B",A27,";",L27,"!S:S)") -> SUMIF(SIN_DATA!B:B;Reliquidacion!B27;SIN_DATA!S:S) | N27: =CONCATENATE("(O",A27,"/M",A27,")") -> (O27/M27) | O27: =CONCATENATE("SUMIF(",L27,"!B:B;Reliquidacion!B",A27,";",L27,"!W:W)") -> SUMIF(SIN_DATA!B:B;Reliquidacion!B27;SIN_DATA!W:W) | P27: =CONCATENATE("SUMIF(",L27,"!B:B;Reliquidacion!B",A27,";",L27,"!X:X)") -> SUMIF(SIN_DATA!B:B;Reliquidacion!B27;SIN_DATA!X:X) | Q27: =CONCATENATE("(R",A27,"/P",A27,")") -> (R27/P27) | R27: =CONCATENATE("SUMIF(",L27,"!B:B;Reliquidacion!B",A27,";",L27,"!AB:AB)") -> SUMIF(SIN_DATA!B:B;Reliquidacion!B27;SIN_DATA!AB:AB) | S27: =CONCATENATE("(O",A27,"+R",A27,")") -> (O27+R27) | U27: 42917 | V27: =CONCATENATE("=(S",A27,"-J",A27,")") -> =(S27-J27) | W27: 12T/28-11-2017 | X27: =VLOOKUP(W27,[1]INTERESES!A:B,2,0) -> 0
A28: =A27+1 -> 28 | B28: 42948 | C28: =CONCATENATE("IF(VLOOKUP(B9,MAPA_DATA!D:G,2,0)=1,'FACT_EMITIDA',IF(VLOOKUP(B",A28,",MAPA_DATA!D:G,3,0)=1,'FACT_EST_EFACT',(IF(VLOOKUP(B",A28,",MAPA_DATA!D:G,4,0)=1,'FACT_EST_CEN','SIN_DATA')))") -> IF(VLOOKUP(B9,MAPA_DATA!D:G,2,0)=1,'FACT_EMITIDA',IF(VLOOKUP(B28,MAPA_DATA!D:G,3,0)=1,'FACT_EST_EFACT',(IF(VLOOKUP(B28,MAPA_DATA!D:G,4,0)=1,'FACT_EST_CEN','SIN_DATA'))) | D28: =CONCATENATE("SUMIF(",IF(C28="FACT_EMITIDA","SIGGE_E",C28),"!B:B,Reliquidacion!B",A28,",",IF(C28="FACT_EMITIDA","SIGGE_E",C28),"!F:F)") -> SUMIF(IF(VLOOKUP(B9,MAPA_DATA!D:G,2,0)=1,'FACT_EMITIDA',IF(VLOOKUP(B28,MAPA_DATA!D:G,3,0)=1,'FACT_EST_EFACT',(IF(VLOOKUP(B28,MAPA_DATA!D:G,4,0)=1,'FACT_EST_CEN','SIN_DATA')))!B:B,Reliquidacion!B28,IF(VLOOKUP(B9,MAPA_DATA!D:G,2,0)=1,'FACT_EMITIDA',IF(VLOOKUP(B28,MAPA_DATA!D:G,3,0)=1,'FACT_EST_EFACT',(IF(VLOOKUP(B28,MAPA_DATA!D:G,4,0)=1,'FACT_EST_CEN','SIN_DATA')))!F:F) | E28: =CONCATENATE("(F",A28,"/D",A28,")") -> (F28/D28) | F28: =CONCATENATE("SUMIF(",IF(C28="FACT_EMITIDA","SIGGE_E",C28),"!B:B,Reliquidacion!B",A28,",",IF(C28="FACT_EMITIDA","SIGGE_E",C28),"!H:H)") -> SUMIF(IF(VLOOKUP(B9,MAPA_DATA!D:G,2,0)=1,'FACT_EMITIDA',IF(VLOOKUP(B28,MAPA_DATA!D:G,3,0)=1,'FACT_EST_EFACT',(IF(VLOOKUP(B28,MAPA_DATA!D:G,4,0)=1,'FACT_EST_CEN','SIN_DATA')))!B:B,Reliquidacion!B28,IF(VLOOKUP(B9,MAPA_DATA!D:G,2,0)=1,'FACT_EMITIDA',IF(VLOOKUP(B28,MAPA_DATA!D:G,3,0)=1,'FACT_EST_EFACT',(IF(VLOOKUP(B28,MAPA_DATA!D:G,4,0)=1,'FACT_EST_CEN','SIN_DATA')))!H:H) | G28: =CONCATENATE("SUMIF(",IF(C28="FACT_EMITIDA","SIGGE_P",C28),"!B:B,Reliquidacion!B",A28,",",IF(C28="FACT_EMITIDA","SIGGE_P",C28),"!F:F)") -> SUMIF(IF(VLOOKUP(B9,MAPA_DATA!D:G,2,0)=1,'FACT_EMITIDA',IF(VLOOKUP(B28,MAPA_DATA!D:G,3,0)=1,'FACT_EST_EFACT',(IF(VLOOKUP(B28,MAPA_DATA!D:G,4,0)=1,'FACT_EST_CEN','SIN_DATA')))!B:B,Reliquidacion!B28,IF(VLOOKUP(B9,MAPA_DATA!D:G,2,0)=1,'FACT_EMITIDA',IF(VLOOKUP(B28,MAPA_DATA!D:G,3,0)=1,'FACT_EST_EFACT',(IF(VLOOKUP(B28,MAPA_DATA!D:G,4,0)=1,'FACT_EST_CEN','SIN_DATA')))!F:F) | H28: =CONCATENATE("(I",A28,"/G",A28,")") -> (I28/G28) | I28: =CONCATENATE("SUMIF(",IF(C28="FACT_EMITIDA","SIGGE_P",C28),"!B:B,Reliquidacion!B",A28,",",IF(C28="FACT_EMITIDA","SIGGE_P",C28),"!H:H)") -> SUMIF(IF(VLOOKUP(B9,MAPA_DATA!D:G,2,0)=1,'FACT_EMITIDA',IF(VLOOKUP(B28,MAPA_DATA!D:G,3,0)=1,'FACT_EST_EFACT',(IF(VLOOKUP(B28,MAPA_DATA!D:G,4,0)=1,'FACT_EST_CEN','SIN_DATA')))!B:B,Reliquidacion!B28,IF(VLOOKUP(B9,MAPA_DATA!D:G,2,0)=1,'FACT_EMITIDA',IF(VLOOKUP(B28,MAPA_DATA!D:G,3,0)=1,'FACT_EST_EFACT',(IF(VLOOKUP(B28,MAPA_DATA!D:G,4,0)=1,'FACT_EST_CEN','SIN_DATA')))!H:H) | J28: =CONCATENATE("(F",A28,"+I",A28,")") -> (F28+I28) | L28: =IF(VLOOKUP(B28,MAPA_DATA!D:I,5,0)=1,"EFACT_CNE",IF(VLOOKUP(B28,MAPA_DATA!D:I,6,0)=1,"EFACT_EST_CNE","SIN_DATA")) -> SIN_DATA | M28: =CONCATENATE("SUMIF(",L28,"!B:B;Reliquidacion!B",A28,";",L28,"!S:S)") -> SUMIF(SIN_DATA!B:B;Reliquidacion!B28;SIN_DATA!S:S) | N28: =CONCATENATE("(O",A28,"/M",A28,")") -> (O28/M28) | O28: =CONCATENATE("SUMIF(",L28,"!B:B;Reliquidacion!B",A28,";",L28,"!W:W)") -> SUMIF(SIN_DATA!B:B;Reliquidacion!B28;SIN_DATA!W:W) | P28: =CONCATENATE("SUMIF(",L28,"!B:B;Reliquidacion!B",A28,";",L28,"!X:X)") -> SUMIF(SIN_DATA!B:B;Reliquidacion!B28;SIN_DATA!X:X) | Q28: =CONCATENATE("(R",A28,"/P",A28,")") -> (R28/P28) | R28: =CONCATENATE("SUMIF(",L28,"!B:B;Reliquidacion!B",A28,";",L28,"!AB:AB)") -> SUMIF(SIN_DATA!B:B;Reliquidacion!B28;SIN_DATA!AB:AB) | S28: =CONCATENATE("(O",A28,"+R",A28,")") -> (O28+R28) | U28: 42948 | V28: =CONCATENATE("=(S",A28,"-J",A28,")") -> =(S28-J28) | W28: 12T/28-11-2017 | X28: =VLOOKUP(W28,[1]INTERESES!A:B,2,0) -> 0
A29: =A28+1 -> 29 | B29: 42979 | C29: =CONCATENATE("IF(VLOOKUP(B9,MAPA_DATA!D:G,2,0)=1,'FACT_EMITIDA',IF(VLOOKUP(B",A29,",MAPA_DATA!D:G,3,0)=1,'FACT_EST_EFACT',(IF(VLOOKUP(B",A29,",MAPA_DATA!D:G,4,0)=1,'FACT_EST_CEN','SIN_DATA')))") -> IF(VLOOKUP(B9,MAPA_DATA!D:G,2,0)=1,'FACT_EMITIDA',IF(VLOOKUP(B29,MAPA_DATA!D:G,3,0)=1,'FACT_EST_EFACT',(IF(VLOOKUP(B29,MAPA_DATA!D:G,4,0)=1,'FACT_EST_CEN','SIN_DATA'))) | D29: =CONCATENATE("SUMIF(",IF(C29="FACT_EMITIDA","SIGGE_E",C29),"!B:B,Reliquidacion!B",A29,",",IF(C29="FACT_EMITIDA","SIGGE_E",C29),"!F:F)") -> SUMIF(IF(VLOOKUP(B9,MAPA_DATA!D:G,2,0)=1,'FACT_EMITIDA',IF(VLOOKUP(B29,MAPA_DATA!D:G,3,0)=1,'FACT_EST_EFACT',(IF(VLOOKUP(B29,MAPA_DATA!D:G,4,0)=1,'FACT_EST_CEN','SIN_DATA')))!B:B,Reliquidacion!B29,IF(VLOOKUP(B9,MAPA_DATA!D:G,2,0)=1,'FACT_EMITIDA',IF(VLOOKUP(B29,MAPA_DATA!D:G,3,0)=1,'FACT_EST_EFACT',(IF(VLOOKUP(B29,MAPA_DATA!D:G,4,0)=1,'FACT_EST_CEN','SIN_DATA')))!F:F) | E29: =CONCATENATE("(F",A29,"/D",A29,")") -> (F29/D29) | F29: =CONCATENATE("SUMIF(",IF(C29="FACT_EMITIDA","SIGGE_E",C29),"!B:B,Reliquidacion!B",A29,",",IF(C29="FACT_EMITIDA","SIGGE_E",C29),"!H:H)") -> SUMIF(IF(VLOOKUP(B9,MAPA_DATA!D:G,2,0)=1,'FACT_EMITIDA',IF(VLOOKUP(B29,MAPA_DATA!D:G,3,0)=1,'FACT_EST_EFACT',(IF(VLOOKUP(B29,MAPA_DATA!D:G,4,0)=1,'FACT_EST_CEN','SIN_DATA')))!B:B,Reliquidacion!B29,IF(VLOOKUP(B9,MAPA_DATA!D:G,2,0)=1,'FACT_EMITIDA',IF(VLOOKUP(B29,MAPA_DATA!D:G,3,0)=1,'FACT_EST_EFACT',(IF(VLOOKUP(B29,MAPA_DATA!D:G,4,0)=1,'FACT_EST_CEN','SIN_DATA')))!H:H) | G29: =CONCATENATE("SUMIF(",IF(C29="FACT_EMITIDA","SIGGE_P",C29),"!B:B,Reliquidacion!B",A29,",",IF(C29="FACT_EMITIDA","SIGGE_P",C29),"!F:F)") -> SUMIF(IF(VLOOKUP(B9,MAPA_DATA!D:G,2,0)=1,'FACT_EMITIDA',IF(VLOOKUP(B29,MAPA_DATA!D:G,3,0)=1,'FACT_EST_EFACT',(IF(VLOOKUP(B29,MAPA_DATA!D:G,4,0)=1,'FACT_EST_CEN','SIN_DATA')))!B:B,Reliquidacion!B29,IF(VLOOKUP(B9,MAPA_DATA!D:G,2,0)=1,'FACT_EMITIDA',IF(VLOOKUP(B29,MAPA_DATA!D:G,3,0)=1,'FACT_EST_EFACT',(IF(VLOOKUP(B29,MAPA_DATA!D:G,4,0)=1,'FACT_EST_CEN','SIN_DATA')))!F:F) | H29: =CONCATENATE("(I",A29,"/G",A29,")") -> (I29/G29) | I29: =CONCATENATE("SUMIF(",IF(C29="FACT_EMITIDA","SIGGE_P",C29),"!B:B,Reliquidacion!B",A29,",",IF(C29="FACT_EMITIDA","SIGGE_P",C29),"!H:H)") -> SUMIF(IF(VLOOKUP(B9,MAPA_DATA!D:G,2,0)=1,'FACT_EMITIDA',IF(VLOOKUP(B29,MAPA_DATA!D:G,3,0)=1,'FACT_EST_EFACT',(IF(VLOOKUP(B29,MAPA_DATA!D:G,4,0)=1,'FACT_EST_CEN','SIN_DATA')))!B:B,Reliquidacion!B29,IF(VLOOKUP(B9,MAPA_DATA!D:G,2,0)=1,'FACT_EMITIDA',IF(VLOOKUP(B29,MAPA_DATA!D:G,3,0)=1,'FACT_EST_EFACT',(IF(VLOOKUP(B29,MAPA_DATA!D:G,4,0)=1,'FACT_EST_CEN','SIN_DATA')))!H:H) | J29: =CONCATENATE("(F",A29,"+I",A29,")") -> (F29+I29) | L29: =IF(VLOOKUP(B29,MAPA_DATA!D:I,5,0)=1,"EFACT_CNE",IF(VLOOKUP(B29,MAPA_DATA!D:I,6,0)=1,"EFACT_EST_CNE","SIN_DATA")) -> SIN_DATA | M29: =CONCATENATE("SUMIF(",L29,"!B:B;Reliquidacion!B",A29,";",L29,"!S:S)") -> SUMIF(SIN_DATA!B:B;Reliquidacion!B29;SIN_DATA!S:S) | N29: =CONCATENATE("(O",A29,"/M",A29,")") -> (O29/M29) | O29: =CONCATENATE("SUMIF(",L29,"!B:B;Reliquidacion!B",A29,";",L29,"!W:W)") -> SUMIF(SIN_DATA!B:B;Reliquidacion!B29;SIN_DATA!W:W) | P29: =CONCATENATE("SUMIF(",L29,"!B:B;Reliquidacion!B",A29,";",L29,"!X:X)") -> SUMIF(SIN_DATA!B:B;Reliquidacion!B29;SIN_DATA!X:X) | Q29: =CONCATENATE("(R",A29,"/P",A29,")") -> (R29/P29) | R29: =CONCATENATE("SUMIF(",L29,"!B:B;Reliquidacion!B",A29,";",L29,"!AB:AB)") -> SUMIF(SIN_DATA!B:B;Reliquidacion!B29;SIN_DATA!AB:AB) | S29: =CONCATENATE("(O",A29,"+R",A29,")") -> (O29+R29) | U29: 42979 | V29: =CONCATENATE("=(S",A29,"-J",A29,")") -> =(S29-J29) | W29: 7T/18-05-2018 | X29: =VLOOKUP(W29,[1]INTERESES!A:B,2,0) -> 0
A30: =A29+1 -> 30 | B30: 43009 | C30: =CONCATENATE("IF(VLOOKUP(B9,MAPA_DATA!D:G,2,0)=1,'FACT_EMITIDA',IF(VLOOKUP(B",A30,",MAPA_DATA!D:G,3,0)=1,'FACT_EST_EFACT',(IF(VLOOKUP(B",A30,",MAPA_DATA!D:G,4,0)=1,'FACT_EST_CEN','SIN_DATA')))") -> IF(VLOOKUP(B9,MAPA_DATA!D:G,2,0)=1,'FACT_EMITIDA',IF(VLOOKUP(B30,MAPA_DATA!D:G,3,0)=1,'FACT_EST_EFACT',(IF(VLOOKUP(B30,MAPA_DATA!D:G,4,0)=1,'FACT_EST_CEN','SIN_DATA'))) | D30: =CONCATENATE("SUMIF(",IF(C30="FACT_EMITIDA","SIGGE_E",C30),"!B:B,Reliquidacion!B",A30,",",IF(C30="FACT_EMITIDA","SIGGE_E",C30),"!F:F)") -> SUMIF(IF(VLOOKUP(B9,MAPA_DATA!D:G,2,0)=1,'FACT_EMITIDA',IF(VLOOKUP(B30,MAPA_DATA!D:G,3,0)=1,'FACT_EST_EFACT',(IF(VLOOKUP(B30,MAPA_DATA!D:G,4,0)=1,'FACT_EST_CEN','SIN_DATA')))!B:B,Reliquidacion!B30,IF(VLOOKUP(B9,MAPA_DATA!D:G,2,0)=1,'FACT_EMITIDA',IF(VLOOKUP(B30,MAPA_DATA!D:G,3,0)=1,'FACT_EST_EFACT',(IF(VLOOKUP(B30,MAPA_DATA!D:G,4,0)=1,'FACT_EST_CEN','SIN_DATA')))!F:F) | E30: =CONCATENATE("(F",A30,"/D",A30,")") -> (F30/D30) | F30: =CONCATENATE("SUMIF(",IF(C30="FACT_EMITIDA","SIGGE_E",C30),"!B:B,Reliquidacion!B",A30,",",IF(C30="FACT_EMITIDA","SIGGE_E",C30),"!H:H)") -> SUMIF(IF(VLOOKUP(B9,MAPA_DATA!D:G,2,0)=1,'FACT_EMITIDA',IF(VLOOKUP(B30,MAPA_DATA!D:G,3,0)=1,'FACT_EST_EFACT',(IF(VLOOKUP(B30,MAPA_DATA!D:G,4,0)=1,'FACT_EST_CEN','SIN_DATA')))!B:B,Reliquidacion!B30,IF(VLOOKUP(B9,MAPA_DATA!D:G,2,0)=1,'FACT_EMITIDA',IF(VLOOKUP(B30,MAPA_DATA!D:G,3,0)=1,'FACT_EST_EFACT',(IF(VLOOKUP(B30,MAPA_DATA!D:G,4,0)=1,'FACT_EST_CEN','SIN_DATA')))!H:H) | G30: =CONCATENATE("SUMIF(",IF(C30="FACT_EMITIDA","SIGGE_P",C30),"!B:B,Reliquidacion!B",A30,",",IF(C30="FACT_EMITIDA","SIGGE_P",C30),"!F:F)") -> SUMIF(IF(VLOOKUP(B9,MAPA_DATA!D:G,2,0)=1,'FACT_EMITIDA',IF(VLOOKUP(B30,MAPA_DATA!D:G,3,0)=1,'FACT_EST_EFACT',(IF(VLOOKUP(B30,MAPA_DATA!D:G,4,0)=1,'FACT_EST_CEN','SIN_DATA')))!B:B,Reliquidacion!B30,IF(VLOOKUP(B9,MAPA_DATA!D:G,2,0)=1,'FACT_EMITIDA',IF(VLOOKUP(B30,MAPA_DATA!D:G,3,0)=1,'FACT_EST_EFACT',(IF(VLOOKUP(B30,MAPA_DATA!D:G,4,0)=1,'FACT_EST_CEN','SIN_DATA')))!F:F) | H30: =CONCATENATE("(I",A30,"/G",A30,")") -> (I30/G30) | I30: =CONCATENATE("SUMIF(",IF(C30="FACT_EMITIDA","SIGGE_P",C30),"!B:B,Reliquidacion!B",A30,",",IF(C30="FACT_EMITIDA","SIGGE_P",C30),"!H:H)") -> SUMIF(IF(VLOOKUP(B9,MAPA_DATA!D:G,2,0)=1,'FACT_EMITIDA',IF(VLOOKUP(B30,MAPA_DATA!D:G,3,0)=1,'FACT_EST_EFACT',(IF(VLOOKUP(B30,MAPA_DATA!D:G,4,0)=1,'FACT_EST_CEN','SIN_DATA')))!B:B,Reliquidacion!B30,IF(VLOOKUP(B9,MAPA_DATA!D:G,2,0)=1,'FACT_EMITIDA',IF(VLOOKUP(B30,MAPA_DATA!D:G,3,0)=1,'FACT_EST_EFACT',(IF(VLOOKUP(B30,MAPA_DATA!D:G,4,0)=1,'FACT_EST_CEN','SIN_DATA')))!H:H) | J30: =CONCATENATE("(F",A30,"+I",A30,")") -> (F30+I30) | L30: =IF(VLOOKUP(B30,MAPA_DATA!D:I,5,0)=1,"EFACT_CNE",IF(VLOOKUP(B30,MAPA_DATA!D:I,6,0)=1,"EFACT_EST_CNE","SIN_DATA")) -> SIN_DATA | M30: =CONCATENATE("SUMIF(",L30,"!B:B;Reliquidacion!B",A30,";",L30,"!S:S)") -> SUMIF(SIN_DATA!B:B;Reliquidacion!B30;SIN_DATA!S:S) | N30: =CONCATENATE("(O",A30,"/M",A30,")") -> (O30/M30) | O30: =CONCATENATE("SUMIF(",L30,"!B:B;Reliquidacion!B",A30,";",L30,"!W:W)") -> SUMIF(SIN_DATA!B:B;Reliquidacion!B30;SIN_DATA!W:W) | P30: =CONCATENATE("SUMIF(",L30,"!B:B;Reliquidacion!B",A30,";",L30,"!X:X)") -> SUMIF(SIN_DATA!B:B;Reliquidacion!B30;SIN_DATA!X:X) | Q30: =CONCATENATE("(R",A30,"/P",A30,")") -> (R30/P30) | R30: =CONCATENATE("SUMIF(",L30,"!B:B;Reliquidacion!B",A30,";",L30,"!AB:AB)") -> SUMIF(SIN_DATA!B:B;Reliquidacion!B30;SIN_DATA!AB:AB) | S30: =CONCATENATE("(O",A30,"+R",A30,")") -> (O30+R30) | U30: 43009 | V30: =CONCATENATE("=(S",A30,"-J",A30,")") -> =(S30-J30) | W30: 7T/18-05-2018 | X30: =VLOOKUP(W30,[1]INTERESES!A:B,2,0) -> 0
A31: =A30+1 -> 31 | B31: 43040 | C31: =CONCATENATE("IF(VLOOKUP(B9,MAPA_DATA!D:G,2,0)=1,'FACT_EMITIDA',IF(VLOOKUP(B",A31,",MAPA_DATA!D:G,3,0)=1,'FACT_EST_EFACT',(IF(VLOOKUP(B",A31,",MAPA_DATA!D:G,4,0)=1,'FACT_EST_CEN','SIN_DATA')))") -> IF(VLOOKUP(B9,MAPA_DATA!D:G,2,0)=1,'FACT_EMITIDA',IF(VLOOKUP(B31,MAPA_DATA!D:G,3,0)=1,'FACT_EST_EFACT',(IF(VLOOKUP(B31,MAPA_DATA!D:G,4,0)=1,'FACT_EST_CEN','SIN_DATA'))) | D31: =CONCATENATE("SUMIF(",IF(C31="FACT_EMITIDA","SIGGE_E",C31),"!B:B,Reliquidacion!B",A31,",",IF(C31="FACT_EMITIDA","SIGGE_E",C31),"!F:F)") -> SUMIF(IF(VLOOKUP(B9,MAPA_DATA!D:G,2,0)=1,'FACT_EMITIDA',IF(VLOOKUP(B31,MAPA_DATA!D:G,3,0)=1,'FACT_EST_EFACT',(IF(VLOOKUP(B31,MAPA_DATA!D:G,4,0)=1,'FACT_EST_CEN','SIN_DATA')))!B:B,Reliquidacion!B31,IF(VLOOKUP(B9,MAPA_DATA!D:G,2,0)=1,'FACT_EMITIDA',IF(VLOOKUP(B31,MAPA_DATA!D:G,3,0)=1,'FACT_EST_EFACT',(IF(VLOOKUP(B31,MAPA_DATA!D:G,4,0)=1,'FACT_EST_CEN','SIN_DATA')))!F:F) | E31: =CONCATENATE("(F",A31,"/D",A31,")") -> (F31/D31) | F31: =CONCATENATE("SUMIF(",IF(C31="FACT_EMITIDA","SIGGE_E",C31),"!B:B,Reliquidacion!B",A31,",",IF(C31="FACT_EMITIDA","SIGGE_E",C31),"!H:H)") -> SUMIF(IF(VLOOKUP(B9,MAPA_DATA!D:G,2,0)=1,'FACT_EMITIDA',IF(VLOOKUP(B31,MAPA_DATA!D:G,3,0)=1,'FACT_EST_EFACT',(IF(VLOOKUP(B31,MAPA_DATA!D:G,4,0)=1,'FACT_EST_CEN','SIN_DATA')))!B:B,Reliquidacion!B31,IF(VLOOKUP(B9,MAPA_DATA!D:G,2,0)=1,'FACT_EMITIDA',IF(VLOOKUP(B31,MAPA_DATA!D:G,3,0)=1,'FACT_EST_EFACT',(IF(VLOOKUP(B31,MAPA_DATA!D:G,4,0)=1,'FACT_EST_CEN','SIN_DATA')))!H:H) | G31: =CONCATENATE("SUMIF(",IF(C31="FACT_EMITIDA","SIGGE_P",C31),"!B:B,Reliquidacion!B",A31,",",IF(C31="FACT_EMITIDA","SIGGE_P",C31),"!F:F)") -> SUMIF(IF(VLOOKUP(B9,MAPA_DATA!D:G,2,0)=1,'FACT_EMITIDA',IF(VLOOKUP(B31,MAPA_DATA!D:G,3,0)=1,'FACT_EST_EFACT',(IF(VLOOKUP(B31,MAPA_DATA!D:G,4,0)=1,'FACT_EST_CEN','SIN_DATA')))!B:B,Reliquidacion!B31,IF(VLOOKUP(B9,MAPA_DATA!D:G,2,0)=1,'FACT_EMITIDA',IF(VLOOKUP(B31,MAPA_DATA!D:G,3,0)=1,'FACT_EST_EFACT',(IF(VLOOKUP(B31,MAPA_DATA!D:G,4,0)=1,'FACT_EST_CEN','SIN_DATA')))!F:F) | H31: =CONCATENATE("(I",A31,"/G",A31,")") -> (I31/G31) | I31: =CONCATENATE("SUMIF(",IF(C31="FACT_EMITIDA","SIGGE_P",C31),"!B:B,Reliquidacion!B",A31,",",IF(C31="FACT_EMITIDA","SIGGE_P",C31),"!H:H)") -> SUMIF(IF(VLOOKUP(B9,MAPA_DATA!D:G,2,0)=1,'FACT_EMITIDA',IF(VLOOKUP(B31,MAPA_DATA!D:G,3,0)=1,'FACT_EST_EFACT',(IF(VLOOKUP(B31,MAPA_DATA!D:G,4,0)=1,'FACT_EST_CEN','SIN_DATA')))!B:B,Reliquidacion!B31,IF(VLOOKUP(B9,MAPA_DATA!D:G,2,0)=1,'FACT_EMITIDA',IF(VLOOKUP(B31,MAPA_DATA!D:G,3,0)=1,'FACT_EST_EFACT',(IF(VLOOKUP(B31,MAPA_DATA!D:G,4,0)=1,'FACT_EST_CEN','SIN_DATA')))!H:H) | J31: =CONCATENATE("(F",A31,"+I",A31,")") -> (F31+I31) | L31: =IF(VLOOKUP(B31,MAPA_DATA!D:I,5,0)=1,"EFACT_CNE",IF(VLOOKUP(B31,MAPA_DATA!D:I,6,0)=1,"EFACT_EST_CNE","SIN_DATA")) -> SIN_DATA | M31: =CONCATENATE("SUMIF(",L31,"!B:B;Reliquidacion!B",A31,";",L31,"!S:S)") -> SUMIF(SIN_DATA!B:B;Reliquidacion!B31;SIN_DATA!S:S) | N31: =CONCATENATE("(O",A31,"/M",A31,")") -> (O31/M31) | O31: =CONCATENATE("SUMIF(",L31,"!B:B;Reliquidacion!B",A31,";",L31,"!W:W)") -> SUMIF(SIN_DATA!B:B;Reliquidacion!B31;SIN_DATA!W:W) | P31: =CONCATENATE("SUMIF(",L31,"!B:B;Reliquidacion!B",A31,";",L31,"!X:X)") -> SUMIF(SIN_DATA!B:B;Reliquidacion!B31;SIN_DATA!X:X) | Q31: =CONCATENATE("(R",A31,"/P",A31,")") -> (R31/P31) | R31: =CONCATENATE("SUMIF(",L31,"!B:B;Reliquidacion!B",A31,";",L31,"!AB:AB)") -> SUMIF(SIN_DATA!B:B;Reliquidacion!B31;SIN_DATA!AB:AB) | S31: =CONCATENATE("(O",A31,"+R",A31,")") -> (O31+R31) | U31: 43040 | V31: =CONCATENATE("=(S",A31,"-J",A31,")") -> =(S31-J31) | W31: 7T/18-05-2018 | X31: =VLOOKUP(W31,[1]INTERESES!A:B,2,0) -> 0
A32: =A31+1 -> 32 | B32: 43070 | C32: =CONCATENATE("IF(VLOOKUP(B9,MAPA_DATA!D:G,2,0)=1,'FACT_EMITIDA',IF(VLOOKUP(B",A32,",MAPA_DATA!D:G,3,0)=1,'FACT_EST_EFACT',(IF(VLOOKUP(B",A32,",MAPA_DATA!D:G,4,0)=1,'FACT_EST_CEN','SIN_DATA')))") -> IF(VLOOKUP(B9,MAPA_DATA!D:G,2,0)=1,'FACT_EMITIDA',IF(VLOOKUP(B32,MAPA_DATA!D:G,3,0)=1,'FACT_EST_EFACT',(IF(VLOOKUP(B32,MAPA_DATA!D:G,4,0)=1,'FACT_EST_CEN','SIN_DATA'))) | D32: =CONCATENATE("SUMIF(",IF(C32="FACT_EMITIDA","SIGGE_E",C32),"!B:B,Reliquidacion!B",A32,",",IF(C32="FACT_EMITIDA","SIGGE_E",C32),"!F:F)") -> SUMIF(IF(VLOOKUP(B9,MAPA_DATA!D:G,2,0)=1,'FACT_EMITIDA',IF(VLOOKUP(B32,MAPA_DATA!D:G,3,0)=1,'FACT_EST_EFACT',(IF(VLOOKUP(B32,MAPA_DATA!D:G,4,0)=1,'FACT_EST_CEN','SIN_DATA')))!B:B,Reliquidacion!B32,IF(VLOOKUP(B9,MAPA_DATA!D:G,2,0)=1,'FACT_EMITIDA',IF(VLOOKUP(B32,MAPA_DATA!D:G,3,0)=1,'FACT_EST_EFACT',(IF(VLOOKUP(B32,MAPA_DATA!D:G,4,0)=1,'FACT_EST_CEN','SIN_DATA')))!F:F) | E32: =CONCATENATE("(F",A32,"/D",A32,")") -> (F32/D32) | F32: =CONCATENATE("SUMIF(",IF(C32="FACT_EMITIDA","SIGGE_E",C32),"!B:B,Reliquidacion!B",A32,",",IF(C32="FACT_EMITIDA","SIGGE_E",C32),"!H:H)") -> SUMIF(IF(VLOOKUP(B9,MAPA_DATA!D:G,2,0)=1,'FACT_EMITIDA',IF(VLOOKUP(B32,MAPA_DATA!D:G,3,0)=1,'FACT_EST_EFACT',(IF(VLOOKUP(B32,MAPA_DATA!D:G,4,0)=1,'FACT_EST_CEN','SIN_DATA')))!B:B,Reliquidacion!B32,IF(VLOOKUP(B9,MAPA_DATA!D:G,2,0)=1,'FACT_EMITIDA',IF(VLOOKUP(B32,MAPA_DATA!D:G,3,0)=1,'FACT_EST_EFACT',(IF(VLOOKUP(B32,MAPA_DATA!D:G,4,0)=1,'FACT_EST_CEN','SIN_DATA')))!H:H) | G32: =CONCATENATE("SUMIF(",IF(C32="FACT_EMITIDA","SIGGE_P",C32),"!B:B,Reliquidacion!B",A32,",",IF(C32="FACT_EMITIDA","SIGGE_P",C32),"!F:F)") -> SUMIF(IF(VLOOKUP(B9,MAPA_DATA!D:G,2,0)=1,'FACT_EMITIDA',IF(VLOOKUP(B32,MAPA_DATA!D:G,3,0)=1,'FACT_EST_EFACT',(IF(VLOOKUP(B32,MAPA_DATA!D:G,4,0)=1,'FACT_EST_CEN','SIN_DATA')))!B:B,Reliquidacion!B32,IF(VLOOKUP(B9,MAPA_DATA!D:G,2,0)=1,'FACT_EMITIDA',IF(VLOOKUP(B32,MAPA_DATA!D:G,3,0)=1,'FACT_EST_EFACT',(IF(VLOOKUP(B32,MAPA_DATA!D:G,4,0)=1,'FACT_EST_CEN','SIN_DATA')))!F:F) | H32: =CONCATENATE("(I",A32,"/G",A32,")") -> (I32/G32) | I32: =CONCATENATE("SUMIF(",IF(C32="FACT_EMITIDA","SIGGE_P",C32),"!B:B,Reliquidacion!B",A32,",",IF(C32="FACT_EMITIDA","SIGGE_P",C32),"!H:H)") -> SUMIF(IF(VLOOKUP(B9,MAPA_DATA!D:G,2,0)=1,'FACT_EMITIDA',IF(VLOOKUP(B32,MAPA_DATA!D:G,3,0)=1,'FACT_EST_EFACT',(IF(VLOOKUP(B32,MAPA_DATA!D:G,4,0)=1,'FACT_EST_CEN','SIN_DATA')))!B:B,Reliquidacion!B32,IF(VLOOKUP(B9,MAPA_DATA!D:G,2,0)=1,'FACT_EMITIDA',IF(VLOOKUP(B32,MAPA_DATA!D:G,3,0)=1,'FACT_EST_EFACT',(IF(VLOOKUP(B32,MAPA_DATA!D:G,4,0)=1,'FACT_EST_CEN','SIN_DATA')))!H:H) | J32: =CONCATENATE("(F",A32,"+I",A32,")") -> (F32+I32) | L32: =IF(VLOOKUP(B32,MAPA_DATA!D:I,5,0)=1,"EFACT_CNE",IF(VLOOKUP(B32,MAPA_DATA!D:I,6,0)=1,"EFACT_EST_CNE","SIN_DATA")) -> SIN_DATA | M32: =CONCATENATE("SUMIF(",L32,"!B:B;Reliquidacion!B",A32,";",L32,"!S:S)") -> SUMIF(SIN_DATA!B:B;Reliquidacion!B32;SIN_DATA!S:S) | N32: =CONCATENATE("(O",A32,"/M",A32,")") -> (O32/M32) | O32: =CONCATENATE("SUMIF(",L32,"!B:B;Reliquidacion!B",A32,";",L32,"!W:W)") -> SUMIF(SIN_DATA!B:B;Reliquidacion!B32;SIN_DATA!W:W) | P32: =CONCATENATE("SUMIF(",L32,"!B:B;Reliquidacion!B",A32,";",L32,"!X:X)") -> SUMIF(SIN_DATA!B:B;Reliquidacion!B32;SIN_DATA!X:X) | Q32: =CONCATENATE("(R",A32,"/P",A32,")") -> (R32/P32) | R32: =CONCATENATE("SUMIF(",L32,"!B:B;Reliquidacion!B",A32,";",L32,"!AB:AB)") -> SUMIF(SIN_DATA!B:B;Reliquidacion!B32;SIN_DATA!AB:AB) | S32: =CONCATENATE("(O",A32,"+R",A32,")") -> (O32+R32) | U32: 43070 | V32: =CONCATENATE("=(S",A32,"-J",A32,")") -> =(S32-J32) | W32: 7T/18-05-2018 | X32: =VLOOKUP(W32,[1]INTERESES!A:B,2,0) -> 0
A33: =A32+1 -> 33 | B33: 43101 | C33: =CONCATENATE("IF(VLOOKUP(B9,MAPA_DATA!D:G,2,0)=1,'FACT_EMITIDA',IF(VLOOKUP(B",A33,",MAPA_DATA!D:G,3,0)=1,'FACT_EST_EFACT',(IF(VLOOKUP(B",A33,",MAPA_DATA!D:G,4,0)=1,'FACT_EST_CEN','SIN_DATA')))") -> IF(VLOOKUP(B9,MAPA_DATA!D:G,2,0)=1,'FACT_EMITIDA',IF(VLOOKUP(B33,MAPA_DATA!D:G,3,0)=1,'FACT_EST_EFACT',(IF(VLOOKUP(B33,MAPA_DATA!D:G,4,0)=1,'FACT_EST_CEN','SIN_DATA'))) | D33: =CONCATENATE("SUMIF(",IF(C33="FACT_EMITIDA","SIGGE_E",C33),"!B:B,Reliquidacion!B",A33,",",IF(C33="FACT_EMITIDA","SIGGE_E",C33),"!F:F)") -> SUMIF(IF(VLOOKUP(B9,MAPA_DATA!D:G,2,0)=1,'FACT_EMITIDA',IF(VLOOKUP(B33,MAPA_DATA!D:G,3,0)=1,'FACT_EST_EFACT',(IF(VLOOKUP(B33,MAPA_DATA!D:G,4,0)=1,'FACT_EST_CEN','SIN_DATA')))!B:B,Reliquidacion!B33,IF(VLOOKUP(B9,MAPA_DATA!D:G,2,0)=1,'FACT_EMITIDA',IF(VLOOKUP(B33,MAPA_DATA!D:G,3,0)=1,'FACT_EST_EFACT',(IF(VLOOKUP(B33,MAPA_DATA!D:G,4,0)=1,'FACT_EST_CEN','SIN_DATA')))!F:F) | E33: =CONCATENATE("(F",A33,"/D",A33,")") -> (F33/D33) | F33: =CONCATENATE("SUMIF(",IF(C33="FACT_EMITIDA","SIGGE_E",C33),"!B:B,Reliquidacion!B",A33,",",IF(C33="FACT_EMITIDA","SIGGE_E",C33),"!H:H)") -> SUMIF(IF(VLOOKUP(B9,MAPA_DATA!D:G,2,0)=1,'FACT_EMITIDA',IF(VLOOKUP(B33,MAPA_DATA!D:G,3,0)=1,'FACT_EST_EFACT',(IF(VLOOKUP(B33,MAPA_DATA!D:G,4,0)=1,'FACT_EST_CEN','SIN_DATA')))!B:B,Reliquidacion!B33,IF(VLOOKUP(B9,MAPA_DATA!D:G,2,0)=1,'FACT_EMITIDA',IF(VLOOKUP(B33,MAPA_DATA!D:G,3,0)=1,'FACT_EST_EFACT',(IF(VLOOKUP(B33,MAPA_DATA!D:G,4,0)=1,'FACT_EST_CEN','SIN_DATA')))!H:H) | G33: =CONCATENATE("SUMIF(",IF(C33="FACT_EMITIDA","SIGGE_P",C33),"!B:B,Reliquidacion!B",A33,",",IF(C33="FACT_EMITIDA","SIGGE_P",C33),"!F:F)") -> SUMIF(IF(VLOOKUP(B9,MAPA_DATA!D:G,2,0)=1,'FACT_EMITIDA',IF(VLOOKUP(B33,MAPA_DATA!D:G,3,0)=1,'FACT_EST_EFACT',(IF(VLOOKUP(B33,MAPA_DATA!D:G,4,0)=1,'FACT_EST_CEN','SIN_DATA')))!B:B,Reliquidacion!B33,IF(VLOOKUP(B9,MAPA_DATA!D:G,2,0)=1,'FACT_EMITIDA',IF(VLOOKUP(B33,MAPA_DATA!D:G,3,0)=1,'FACT_EST_EFACT',(IF(VLOOKUP(B33,MAPA_DATA!D:G,4,0)=1,'FACT_EST_CEN','SIN_DATA')))!F:F) | H33: =CONCATENATE("(I",A33,"/G",A33,")") -> (I33/G33) | I33: =CONCATENATE("SUMIF(",IF(C33="FACT_EMITIDA","SIGGE_P",C33),"!B:B,Reliquidacion!B",A33,",",IF(C33="FACT_EMITIDA","SIGGE_P",C33),"!H:H)") -> SUMIF(IF(VLOOKUP(B9,MAPA_DATA!D:G,2,0)=1,'FACT_EMITIDA',IF(VLOOKUP(B33,MAPA_DATA!D:G,3,0)=1,'FACT_EST_EFACT',(IF(VLOOKUP(B33,MAPA_DATA!D:G,4,0)=1,'FACT_EST_CEN','SIN_DATA')))!B:B,Reliquidacion!B33,IF(VLOOKUP(B9,MAPA_DATA!D:G,2,0)=1,'FACT_EMITIDA',IF(VLOOKUP(B33,MAPA_DATA!D:G,3,0)=1,'FACT_EST_EFACT',(IF(VLOOKUP(B33,MAPA_DATA!D:G,4,0)=1,'FACT_EST_CEN','SIN_DATA')))!H:H) | J33: =CONCATENATE("(F",A33,"+I",A33,")") -> (F33+I33) | L33: =IF(VLOOKUP(B33,MAPA_DATA!D:I,5,0)=1,"EFACT_CNE",IF(VLOOKUP(B33,MAPA_DATA!D:I,6,0)=1,"EFACT_EST_CNE","SIN_DATA")) -> SIN_DATA | M33: =CONCATENATE("SUMIF(",L33,"!B:B;Reliquidacion!B",A33,";",L33,"!S:S)") -> SUMIF(SIN_DATA!B:B;Reliquidacion!B33;SIN_DATA!S:S) | N33: =CONCATENATE("(O",A33,"/M",A33,")") -> (O33/M33) | O33: =CONCATENATE("SUMIF(",L33,"!B:B;Reliquidacion!B",A33,";",L33,"!W:W)") -> SUMIF(SIN_DATA!B:B;Reliquidacion!B33;SIN_DATA!W:W) | P33: =CONCATENATE("SUMIF(",L33,"!B:B;Reliquidacion!B",A33,";",L33,"!X:X)") -> SUMIF(SIN_DATA!B:B;Reliquidacion!B33;SIN_DATA!X:X) | Q33: =CONCATENATE("(R",A33,"/P",A33,")") -> (R33/P33) | R33: =CONCATENATE("SUMIF(",L33,"!B:B;Reliquidacion!B",A33,";",L33,"!AB:AB)") -> SUMIF(SIN_DATA!B:B;Reliquidacion!B33;SIN_DATA!AB:AB) | S33: =CONCATENATE("(O",A33,"+R",A33,")") -> (O33+R33) | U33: 43101 | V33: =CONCATENATE("=(S",A33,"-J",A33,")") -> =(S33-J33) | W33: 7T/18-05-2018 | X33: =VLOOKUP(W33,[1]INTERESES!A:B,2,0) -> 0 | Y33: =VLOOKUP(W33,#REF!,6,0) -> #REF! | Z33: 43156 | AA33: 44377 | AB33: =AA33-Z33 -> 1221 | AC33: =+(1+Y33)^(AB33/360)-1 -> #REF! | AD33: =AC33*V33 -> #REF! | AE33: =+V33+AD33 -> #VALUE!
A34: =A33+1 -> 34 | B34: 43132 | C34: =CONCATENATE("IF(VLOOKUP(B9,MAPA_DATA!D:G,2,0)=1,'FACT_EMITIDA',IF(VLOOKUP(B",A34,",MAPA_DATA!D:G,3,0)=1,'FACT_EST_EFACT',(IF(VLOOKUP(B",A34,",MAPA_DATA!D:G,4,0)=1,'FACT_EST_CEN','SIN_DATA')))") -> IF(VLOOKUP(B9,MAPA_DATA!D:G,2,0)=1,'FACT_EMITIDA',IF(VLOOKUP(B34,MAPA_DATA!D:G,3,0)=1,'FACT_EST_EFACT',(IF(VLOOKUP(B34,MAPA_DATA!D:G,4,0)=1,'FACT_EST_CEN','SIN_DATA'))) | D34: =CONCATENATE("SUMIF(",IF(C34="FACT_EMITIDA","SIGGE_E",C34),"!B:B,Reliquidacion!B",A34,",",IF(C34="FACT_EMITIDA","SIGGE_E",C34),"!F:F)") -> SUMIF(IF(VLOOKUP(B9,MAPA_DATA!D:G,2,0)=1,'FACT_EMITIDA',IF(VLOOKUP(B34,MAPA_DATA!D:G,3,0)=1,'FACT_EST_EFACT',(IF(VLOOKUP(B34,MAPA_DATA!D:G,4,0)=1,'FACT_EST_CEN','SIN_DATA')))!B:B,Reliquidacion!B34,IF(VLOOKUP(B9,MAPA_DATA!D:G,2,0)=1,'FACT_EMITIDA',IF(VLOOKUP(B34,MAPA_DATA!D:G,3,0)=1,'FACT_EST_EFACT',(IF(VLOOKUP(B34,MAPA_DATA!D:G,4,0)=1,'FACT_EST_CEN','SIN_DATA')))!F:F) | E34: =CONCATENATE("(F",A34,"/D",A34,")") -> (F34/D34) | F34: =CONCATENATE("SUMIF(",IF(C34="FACT_EMITIDA","SIGGE_E",C34),"!B:B,Reliquidacion!B",A34,",",IF(C34="FACT_EMITIDA","SIGGE_E",C34),"!H:H)") -> SUMIF(IF(VLOOKUP(B9,MAPA_DATA!D:G,2,0)=1,'FACT_EMITIDA',IF(VLOOKUP(B34,MAPA_DATA!D:G,3,0)=1,'FACT_EST_EFACT',(IF(VLOOKUP(B34,MAPA_DATA!D:G,4,0)=1,'FACT_EST_CEN','SIN_DATA')))!B:B,Reliquidacion!B34,IF(VLOOKUP(B9,MAPA_DATA!D:G,2,0)=1,'FACT_EMITIDA',IF(VLOOKUP(B34,MAPA_DATA!D:G,3,0)=1,'FACT_EST_EFACT',(IF(VLOOKUP(B34,MAPA_DATA!D:G,4,0)=1,'FACT_EST_CEN','SIN_DATA')))!H:H) | G34: =CONCATENATE("SUMIF(",IF(C34="FACT_EMITIDA","SIGGE_P",C34),"!B:B,Reliquidacion!B",A34,",",IF(C34="FACT_EMITIDA","SIGGE_P",C34),"!F:F)") -> SUMIF(IF(VLOOKUP(B9,MAPA_DATA!D:G,2,0)=1,'FACT_EMITIDA',IF(VLOOKUP(B34,MAPA_DATA!D:G,3,0)=1,'FACT_EST_EFACT',(IF(VLOOKUP(B34,MAPA_DATA!D:G,4,0)=1,'FACT_EST_CEN','SIN_DATA')))!B:B,Reliquidacion!B34,IF(VLOOKUP(B9,MAPA_DATA!D:G,2,0)=1,'FACT_EMITIDA',IF(VLOOKUP(B34,MAPA_DATA!D:G,3,0)=1,'FACT_EST_EFACT',(IF(VLOOKUP(B34,MAPA_DATA!D:G,4,0)=1,'FACT_EST_CEN','SIN_DATA')))!F:F) | H34: =CONCATENATE("(I",A34,"/G",A34,")") -> (I34/G34) | I34: =CONCATENATE("SUMIF(",IF(C34="FACT_EMITIDA","SIGGE_P",C34),"!B:B,Reliquidacion!B",A34,",",IF(C34="FACT_EMITIDA","SIGGE_P",C34),"!H:H)") -> SUMIF(IF(VLOOKUP(B9,MAPA_DATA!D:G,2,0)=1,'FACT_EMITIDA',IF(VLOOKUP(B34,MAPA_DATA!D:G,3,0)=1,'FACT_EST_EFACT',(IF(VLOOKUP(B34,MAPA_DATA!D:G,4,0)=1,'FACT_EST_CEN','SIN_DATA')))!B:B,Reliquidacion!B34,IF(VLOOKUP(B9,MAPA_DATA!D:G,2,0)=1,'FACT_EMITIDA',IF(VLOOKUP(B34,MAPA_DATA!D:G,3,0)=1,'FACT_EST_EFACT',(IF(VLOOKUP(B34,MAPA_DATA!D:G,4,0)=1,'FACT_EST_CEN','SIN_DATA')))!H:H) | J34: =CONCATENATE("(F",A34,"+I",A34,")") -> (F34+I34) | L34: =IF(VLOOKUP(B34,MAPA_DATA!D:I,5,0)=1,"EFACT_CNE",IF(VLOOKUP(B34,MAPA_DATA!D:I,6,0)=1,"EFACT_EST_CNE","SIN_DATA")) -> SIN_DATA | M34: =CONCATENATE("SUMIF(",L34,"!B:B;Reliquidacion!B",A34,";",L34,"!S:S)") -> SUMIF(SIN_DATA!B:B;Reliquidacion!B34;SIN_DATA!S:S) | N34: =CONCATENATE("(O",A34,"/M",A34,")") -> (O34/M34) | O34: =CONCATENATE("SUMIF(",L34,"!B:B;Reliquidacion!B",A34,";",L34,"!W:W)") -> SUMIF(SIN_DATA!B:B;Reliquidacion!B34;SIN_DATA!W:W) | P34: =CONCATENATE("SUMIF(",L34,"!B:B;Reliquidacion!B",A34,";",L34,"!X:X)") -> SUMIF(SIN_DATA!B:B;Reliquidacion!B34;SIN_DATA!X:X) | Q34: =CONCATENATE("(R",A34,"/P",A34,")") -> (R34/P34) | R34: =CONCATENATE("SUMIF(",L34,"!B:B;Reliquidacion!B",A34,";",L34,"!AB:AB)") -> SUMIF(SIN_DATA!B:B;Reliquidacion!B34;SIN_DATA!AB:AB) | S34: =CONCATENATE("(O",A34,"+R",A34,")") -> (O34+R34) | U34: 43132 | V34: =CONCATENATE("=(S",A34,"-J",A34,")") -> =(S34-J34) | W34: 7T/18-05-2018 | X34: =VLOOKUP(W34,[1]INTERESES!A:B,2,0) -> 0 | Y34: =VLOOKUP(W34,#REF!,6,0) -> #REF! | Z34: 43184 | AA34: =AA33 -> 44377 | AB34: =AA34-Z34 -> 1193 | AC34: =+(1+Y34)^(AB34/360)-1 -> #REF! | AD34: =AC34*V34 -> #REF! | AE34: =+V34+AD34 -> #VALUE!
A35: =A34+1 -> 35 | B35: 43160 | C35: =CONCATENATE("IF(VLOOKUP(B9,MAPA_DATA!D:G,2,0)=1,'FACT_EMITIDA',IF(VLOOKUP(B",A35,",MAPA_DATA!D:G,3,0)=1,'FACT_EST_EFACT',(IF(VLOOKUP(B",A35,",MAPA_DATA!D:G,4,0)=1,'FACT_EST_CEN','SIN_DATA')))") -> IF(VLOOKUP(B9,MAPA_DATA!D:G,2,0)=1,'FACT_EMITIDA',IF(VLOOKUP(B35,MAPA_DATA!D:G,3,0)=1,'FACT_EST_EFACT',(IF(VLOOKUP(B35,MAPA_DATA!D:G,4,0)=1,'FACT_EST_CEN','SIN_DATA'))) | D35: =CONCATENATE("SUMIF(",IF(C35="FACT_EMITIDA","SIGGE_E",C35),"!B:B,Reliquidacion!B",A35,",",IF(C35="FACT_EMITIDA","SIGGE_E",C35),"!F:F)") -> SUMIF(IF(VLOOKUP(B9,MAPA_DATA!D:G,2,0)=1,'FACT_EMITIDA',IF(VLOOKUP(B35,MAPA_DATA!D:G,3,0)=1,'FACT_EST_EFACT',(IF(VLOOKUP(B35,MAPA_DATA!D:G,4,0)=1,'FACT_EST_CEN','SIN_DATA')))!B:B,Reliquidacion!B35,IF(VLOOKUP(B9,MAPA_DATA!D:G,2,0)=1,'FACT_EMITIDA',IF(VLOOKUP(B35,MAPA_DATA!D:G,3,0)=1,'FACT_EST_EFACT',(IF(VLOOKUP(B35,MAPA_DATA!D:G,4,0)=1,'FACT_EST_CEN','SIN_DATA')))!F:F) | E35: =CONCATENATE("(F",A35,"/D",A35,")") -> (F35/D35) | F35: =CONCATENATE("SUMIF(",IF(C35="FACT_EMITIDA","SIGGE_E",C35),"!B:B,Reliquidacion!B",A35,",",IF(C35="FACT_EMITIDA","SIGGE_E",C35),"!H:H)") -> SUMIF(IF(VLOOKUP(B9,MAPA_DATA!D:G,2,0)=1,'FACT_EMITIDA',IF(VLOOKUP(B35,MAPA_DATA!D:G,3,0)=1,'FACT_EST_EFACT',(IF(VLOOKUP(B35,MAPA_DATA!D:G,4,0)=1,'FACT_EST_CEN','SIN_DATA')))!B:B,Reliquidacion!B35,IF(VLOOKUP(B9,MAPA_DATA!D:G,2,0)=1,'FACT_EMITIDA',IF(VLOOKUP(B35,MAPA_DATA!D:G,3,0)=1,'FACT_EST_EFACT',(IF(VLOOKUP(B35,MAPA_DATA!D:G,4,0)=1,'FACT_EST_CEN','SIN_DATA')))!H:H) | G35: =CONCATENATE("SUMIF(",IF(C35="FACT_EMITIDA","SIGGE_P",C35),"!B:B,Reliquidacion!B",A35,",",IF(C35="FACT_EMITIDA","SIGGE_P",C35),"!F:F)") -> SUMIF(IF(VLOOKUP(B9,MAPA_DATA!D:G,2,0)=1,'FACT_EMITIDA',IF(VLOOKUP(B35,MAPA_DATA!D:G,3,0)=1,'FACT_EST_EFACT',(IF(VLOOKUP(B35,MAPA_DATA!D:G,4,0)=1,'FACT_EST_CEN','SIN_DATA')))!B:B,Reliquidacion!B35,IF(VLOOKUP(B9,MAPA_DATA!D:G,2,0)=1,'FACT_EMITIDA',IF(VLOOKUP(B35,MAPA_DATA!D:G,3,0)=1,'FACT_EST_EFACT',(IF(VLOOKUP(B35,MAPA_DATA!D:G,4,0)=1,'FACT_EST_CEN','SIN_DATA')))!F:F) | H35: =CONCATENATE("(I",A35,"/G",A35,")") -> (I35/G35) | I35: =CONCATENATE("SUMIF(",IF(C35="FACT_EMITIDA","SIGGE_P",C35),"!B:B,Reliquidacion!B",A35,",",IF(C35="FACT_EMITIDA","SIGGE_P",C35),"!H:H)") -> SUMIF(IF(VLOOKUP(B9,MAPA_DATA!D:G,2,0)=1,'FACT_EMITIDA',IF(VLOOKUP(B35,MAPA_DATA!D:G,3,0)=1,'FACT_EST_EFACT',(IF(VLOOKUP(B35,MAPA_DATA!D:G,4,0)=1,'FACT_EST_CEN','SIN_DATA')))!B:B,Reliquidacion!B35,IF(VLOOKUP(B9,MAPA_DATA!D:G,2,0)=1,'FACT_EMITIDA',IF(VLOOKUP(B35,MAPA_DATA!D:G,3,0)=1,'FACT_EST_EFACT',(IF(VLOOKUP(B35,MAPA_DATA!D:G,4,0)=1,'FACT_EST_CEN','SIN_DATA')))!H:H) | J35: =CONCATENATE("(F",A35,"+I",A35,")") -> (F35+I35) | L35: =IF(VLOOKUP(B35,MAPA_DATA!D:I,5,0)=1,"EFACT_CNE",IF(VLOOKUP(B35,MAPA_DATA!D:I,6,0)=1,"EFACT_EST_CNE","SIN_DATA")) -> SIN_DATA | M35: =CONCATENATE("SUMIF(",L35,"!B:B;Reliquidacion!B",A35,";",L35,"!S:S)") -> SUMIF(SIN_DATA!B:B;Reliquidacion!B35;SIN_DATA!S:S) | N35: =CONCATENATE("(O",A35,"/M",A35,")") -> (O35/M35) | O35: =CONCATENATE("SUMIF(",L35,"!B:B;Reliquidacion!B",A35,";",L35,"!W:W)") -> SUMIF(SIN_DATA!B:B;Reliquidacion!B35;SIN_DATA!W:W) | P35: =CONCATENATE("SUMIF(",L35,"!B:B;Reliquidacion!B",A35,";",L35,"!X:X)") -> SUMIF(SIN_DATA!B:B;Reliquidacion!B35;SIN_DATA!X:X) | Q35: =CONCATENATE("(R",A35,"/P",A35,")") -> (R35/P35) | R35: =CONCATENATE("SUMIF(",L35,"!B:B;Reliquidacion!B",A35,";",L35,"!AB:AB)") -> SUMIF(SIN_DATA!B:B;Reliquidacion!B35;SIN_DATA!AB:AB) | S35: =CONCATENATE("(O",A35,"+R",A35,")") -> (O35+R35) | U35: 43160 | V35: =CONCATENATE("=(S",A35,"-J",A35,")") -> =(S35-J35) | W35: 20T/13-12-2018 | X35: =VLOOKUP(W35,[1]INTERESES!A:B,2,0) -> 0 | Y35: =VLOOKUP(W35,#REF!,6,0) -> #REF! | Z35: 43215 | AA35: =AA34 -> 44377 | AB35: =AA35-Z35 -> 1162 | AC35: =+(1+Y35)^(AB35/360)-1 -> #REF! | AD35: =AC35*V35 -> #REF! | AE35: =+V35+AD35 -> #VALUE!
A36: =A35+1 -> 36 | B36: 43191 | C36: =CONCATENATE("IF(VLOOKUP(B9,MAPA_DATA!D:G,2,0)=1,'FACT_EMITIDA',IF(VLOOKUP(B",A36,",MAPA_DATA!D:G,3,0)=1,'FACT_EST_EFACT',(IF(VLOOKUP(B",A36,",MAPA_DATA!D:G,4,0)=1,'FACT_EST_CEN','SIN_DATA')))") -> IF(VLOOKUP(B9,MAPA_DATA!D:G,2,0)=1,'FACT_EMITIDA',IF(VLOOKUP(B36,MAPA_DATA!D:G,3,0)=1,'FACT_EST_EFACT',(IF(VLOOKUP(B36,MAPA_DATA!D:G,4,0)=1,'FACT_EST_CEN','SIN_DATA'))) | D36: =CONCATENATE("SUMIF(",IF(C36="FACT_EMITIDA","SIGGE_E",C36),"!B:B,Reliquidacion!B",A36,",",IF(C36="FACT_EMITIDA","SIGGE_E",C36),"!F:F)") -> SUMIF(IF(VLOOKUP(B9,MAPA_DATA!D:G,2,0)=1,'FACT_EMITIDA',IF(VLOOKUP(B36,MAPA_DATA!D:G,3,0)=1,'FACT_EST_EFACT',(IF(VLOOKUP(B36,MAPA_DATA!D:G,4,0)=1,'FACT_EST_CEN','SIN_DATA')))!B:B,Reliquidacion!B36,IF(VLOOKUP(B9,MAPA_DATA!D:G,2,0)=1,'FACT_EMITIDA',IF(VLOOKUP(B36,MAPA_DATA!D:G,3,0)=1,'FACT_EST_EFACT',(IF(VLOOKUP(B36,MAPA_DATA!D:G,4,0)=1,'FACT_EST_CEN','SIN_DATA')))!F:F) | E36: =CONCATENATE("(F",A36,"/D",A36,")") -> (F36/D36) | F36: =CONCATENATE("SUMIF(",IF(C36="FACT_EMITIDA","SIGGE_E",C36),"!B:B,Reliquidacion!B",A36,",",IF(C36="FACT_EMITIDA","SIGGE_E",C36),"!H:H)") -> SUMIF(IF(VLOOKUP(B9,MAPA_DATA!D:G,2,0)=1,'FACT_EMITIDA',IF(VLOOKUP(B36,MAPA_DATA!D:G,3,0)=1,'FACT_EST_EFACT',(IF(VLOOKUP(B36,MAPA_DATA!D:G,4,0)=1,'FACT_EST_CEN','SIN_DATA')))!B:B,Reliquidacion!B36,IF(VLOOKUP(B9,MAPA_DATA!D:G,2,0)=1,'FACT_EMITIDA',IF(VLOOKUP(B36,MAPA_DATA!D:G,3,0)=1,'FACT_EST_EFACT',(IF(VLOOKUP(B36,MAPA_DATA!D:G,4,0)=1,'FACT_EST_CEN','SIN_DATA')))!H:H) | G36: =CONCATENATE("SUMIF(",IF(C36="FACT_EMITIDA","SIGGE_P",C36),"!B:B,Reliquidacion!B",A36,",",IF(C36="FACT_EMITIDA","SIGGE_P",C36),"!F:F)") -> SUMIF(IF(VLOOKUP(B9,MAPA_DATA!D:G,2,0)=1,'FACT_EMITIDA',IF(VLOOKUP(B36,MAPA_DATA!D:G,3,0)=1,'FACT_EST_EFACT',(IF(VLOOKUP(B36,MAPA_DATA!D:G,4,0)=1,'FACT_EST_CEN','SIN_DATA')))!B:B,Reliquidacion!B36,IF(VLOOKUP(B9,MAPA_DATA!D:G,2,0)=1,'FACT_EMITIDA',IF(VLOOKUP(B36,MAPA_DATA!D:G,3,0)=1,'FACT_EST_EFACT',(IF(VLOOKUP(B36,MAPA_DATA!D:G,4,0)=1,'FACT_EST_CEN','SIN_DATA')))!F:F) | H36: =CONCATENATE("(I",A36,"/G",A36,")") -> (I36/G36) | I36: =CONCATENATE("SUMIF(",IF(C36="FACT_EMITIDA","SIGGE_P",C36),"!B:B,Reliquidacion!B",A36,",",IF(C36="FACT_EMITIDA","SIGGE_P",C36),"!H:H)") -> SUMIF(IF(VLOOKUP(B9,MAPA_DATA!D:G,2,0)=1,'FACT_EMITIDA',IF(VLOOKUP(B36,MAPA_DATA!D:G,3,0)=1,'FACT_EST_EFACT',(IF(VLOOKUP(B36,MAPA_DATA!D:G,4,0)=1,'FACT_EST_CEN','SIN_DATA')))!B:B,Reliquidacion!B36,IF(VLOOKUP(B9,MAPA_DATA!D:G,2,0)=1,'FACT_EMITIDA',IF(VLOOKUP(B36,MAPA_DATA!D:G,3,0)=1,'FACT_EST_EFACT',(IF(VLOOKUP(B36,MAPA_DATA!D:G,4,0)=1,'FACT_EST_CEN','SIN_DATA')))!H:H) | J36: =CONCATENATE("(F",A36,"+I",A36,")") -> (F36+I36) | L36: =IF(VLOOKUP(B36,MAPA_DATA!D:I,5,0)=1,"EFACT_CNE",IF(VLOOKUP(B36,MAPA_DATA!D:I,6,0)=1,"EFACT_EST_CNE","SIN_DATA")) -> SIN_DATA | M36: =CONCATENATE("SUMIF(",L36,"!B:B;Reliquidacion!B",A36,";",L36,"!S:S)") -> SUMIF(SIN_DATA!B:B;Reliquidacion!B36;SIN_DATA!S:S) | N36: =CONCATENATE("(O",A36,"/M",A36,")") -> (O36/M36) | O36: =CONCATENATE("SUMIF(",L36,"!B:B;Reliquidacion!B",A36,";",L36,"!W:W)") -> SUMIF(SIN_DATA!B:B;Reliquidacion!B36;SIN_DATA!W:W) | P36: =CONCATENATE("SUMIF(",L36,"!B:B;Reliquidacion!B",A36,";",L36,"!X:X)") -> SUMIF(SIN_DATA!B:B;Reliquidacion!B36;SIN_DATA!X:X) | Q36: =CONCATENATE("(R",A36,"/P",A36,")") -> (R36/P36) | R36: =CONCATENATE("SUMIF(",L36,"!B:B;Reliquidacion!B",A36,";",L36,"!AB:AB)") -> SUMIF(SIN_DATA!B:B;Reliquidacion!B36;SIN_DATA!AB:AB) | S36: =CONCATENATE("(O",A36,"+R",A36,")") -> (O36+R36) | U36: 43191 | V36: =CONCATENATE("=(S",A36,"-J",A36,")") -> =(S36-J36) | W36: 20T/13-12-2018 | X36: =VLOOKUP(W36,[1]INTERESES!A:B,2,0) -> 0 | Y36: =VLOOKUP(W36,#REF!,6,0) -> #REF! | Z36: 43245 | AA36: =AA35 -> 44377 | AB36: =AA36-Z36 -> 1132 | AC36: =+(1+Y36)^(AB36/360)-1 -> #REF! | AD36: =AC36*V36 -> #REF! | AE36: =+V36+AD36 -> #VALUE!
A37: =A36+1 -> 37 | B37: 43221 | C37: =CONCATENATE("IF(VLOOKUP(B9,MAPA_DATA!D:G,2,0)=1,'FACT_EMITIDA',IF(VLOOKUP(B",A37,",MAPA_DATA!D:G,3,0)=1,'FACT_EST_EFACT',(IF(VLOOKUP(B",A37,",MAPA_DATA!D:G,4,0)=1,'FACT_EST_CEN','SIN_DATA')))") -> IF(VLOOKUP(B9,MAPA_DATA!D:G,2,0)=1,'FACT_EMITIDA',IF(VLOOKUP(B37,MAPA_DATA!D:G,3,0)=1,'FACT_EST_EFACT',(IF(VLOOKUP(B37,MAPA_DATA!D:G,4,0)=1,'FACT_EST_CEN','SIN_DATA'))) | D37: =CONCATENATE("SUMIF(",IF(C37="FACT_EMITIDA","SIGGE_E",C37),"!B:B,Reliquidacion!B",A37,",",IF(C37="FACT_EMITIDA","SIGGE_E",C37),"!F:F)") -> SUMIF(IF(VLOOKUP(B9,MAPA_DATA!D:G,2,0)=1,'FACT_EMITIDA',IF(VLOOKUP(B37,MAPA_DATA!D:G,3,0)=1,'FACT_EST_EFACT',(IF(VLOOKUP(B37,MAPA_DATA!D:G,4,0)=1,'FACT_EST_CEN','SIN_DATA')))!B:B,Reliquidacion!B37,IF(VLOOKUP(B9,MAPA_DATA!D:G,2,0)=1,'FACT_EMITIDA',IF(VLOOKUP(B37,MAPA_DATA!D:G,3,0)=1,'FACT_EST_EFACT',(IF(VLOOKUP(B37,MAPA_DATA!D:G,4,0)=1,'FACT_EST_CEN','SIN_DATA')))!F:F) | E37: =CONCATENATE("(F",A37,"/D",A37,")") -> (F37/D37) | F37: =CONCATENATE("SUMIF(",IF(C37="FACT_EMITIDA","SIGGE_E",C37),"!B:B,Reliquidacion!B",A37,",",IF(C37="FACT_EMITIDA","SIGGE_E",C37),"!H:H)") -> SUMIF(IF(VLOOKUP(B9,MAPA_DATA!D:G,2,0)=1,'FACT_EMITIDA',IF(VLOOKUP(B37,MAPA_DATA!D:G,3,0)=1,'FACT_EST_EFACT',(IF(VLOOKUP(B37,MAPA_DATA!D:G,4,0)=1,'FACT_EST_CEN','SIN_DATA')))!B:B,Reliquidacion!B37,IF(VLOOKUP(B9,MAPA_DATA!D:G,2,0)=1,'FACT_EMITIDA',IF(VLOOKUP(B37,MAPA_DATA!D:G,3,0)=1,'FACT_EST_EFACT',(IF(VLOOKUP(B37,MAPA_DATA!D:G,4,0)=1,'FACT_EST_CEN','SIN_DATA')))!H:H) | G37: =CONCATENATE("SUMIF(",IF(C37="FACT_EMITIDA","SIGGE_P",C37),"!B:B,Reliquidacion!B",A37,",",IF(C37="FACT_EMITIDA","SIGGE_P",C37),"!F:F)") -> SUMIF(IF(VLOOKUP(B9,MAPA_DATA!D:G,2,0)=1,'FACT_EMITIDA',IF(VLOOKUP(B37,MAPA_DATA!D:G,3,0)=1,'FACT_EST_EFACT',(IF(VLOOKUP(B37,MAPA_DATA!D:G,4,0)=1,'FACT_EST_CEN','SIN_DATA')))!B:B,Reliquidacion!B37,IF(VLOOKUP(B9,MAPA_DATA!D:G,2,0)=1,'FACT_EMITIDA',IF(VLOOKUP(B37,MAPA_DATA!D:G,3,0)=1,'FACT_EST_EFACT',(IF(VLOOKUP(B37,MAPA_DATA!D:G,4,0)=1,'FACT_EST_CEN','SIN_DATA')))!F:F) | H37: =CONCATENATE("(I",A37,"/G",A37,")") -> (I37/G37) | I37: =CONCATENATE("SUMIF(",IF(C37="FACT_EMITIDA","SIGGE_P",C37),"!B:B,Reliquidacion!B",A37,",",IF(C37="FACT_EMITIDA","SIGGE_P",C37),"!H:H)") -> SUMIF(IF(VLOOKUP(B9,MAPA_DATA!D:G,2,0)=1,'FACT_EMITIDA',IF(VLOOKUP(B37,MAPA_DATA!D:G,3,0)=1,'FACT_EST_EFACT',(IF(VLOOKUP(B37,MAPA_DATA!D:G,4,0)=1,'FACT_EST_CEN','SIN_DATA')))!B:B,Reliquidacion!B37,IF(VLOOKUP(B9,MAPA_DATA!D:G,2,0)=1,'FACT_EMITIDA',IF(VLOOKUP(B37,MAPA_DATA!D:G,3,0)=1,'FACT_EST_EFACT',(IF(VLOOKUP(B37,MAPA_DATA!D:G,4,0)=1,'FACT_EST_CEN','SIN_DATA')))!H:H) | J37: =CONCATENATE("(F",A37,"+I",A37,")") -> (F37+I37) | L37: =IF(VLOOKUP(B37,MAPA_DATA!D:I,5,0)=1,"EFACT_CNE",IF(VLOOKUP(B37,MAPA_DATA!D:I,6,0)=1,"EFACT_EST_CNE","SIN_DATA")) -> SIN_DATA | M37: =CONCATENATE("SUMIF(",L37,"!B:B;Reliquidacion!B",A37,";",L37,"!S:S)") -> SUMIF(SIN_DATA!B:B;Reliquidacion!B37;SIN_DATA!S:S) | N37: =CONCATENATE("(O",A37,"/M",A37,")") -> (O37/M37) | O37: =CONCATENATE("SUMIF(",L37,"!B:B;Reliquidacion!B",A37,";",L37,"!W:W)") -> SUMIF(SIN_DATA!B:B;Reliquidacion!B37;SIN_DATA!W:W) | P37: =CONCATENATE("SUMIF(",L37,"!B:B;Reliquidacion!B",A37,";",L37,"!X:X)") -> SUMIF(SIN_DATA!B:B;Reliquidacion!B37;SIN_DATA!X:X) | Q37: =CONCATENATE("(R",A37,"/P",A37,")") -> (R37/P37) | R37: =CONCATENATE("SUMIF(",L37,"!B:B;Reliquidacion!B",A37,";",L37,"!AB:AB)") -> SUMIF(SIN_DATA!B:B;Reliquidacion!B37;SIN_DATA!AB:AB) | S37: =CONCATENATE("(O",A37,"+R",A37,")") -> (O37+R37) | U37: 43221 | V37: =CONCATENATE("=(S",A37,"-J",A37,")") -> =(S37-J37) | W37: 20T/13-12-2018 | X37: =VLOOKUP(W37,[1]INTERESES!A:B,2,0) -> 0 | Y37: =VLOOKUP(W37,#REF!,6,0) -> #REF! | Z37: 43276 | AA37: =AA36 -> 44377 | AB37: =AA37-Z37 -> 1101 | AC37: =+(1+Y37)^(AB37/360)-1 -> #REF! | AD37: =AC37*V37 -> #REF! | AE37: =+V37+AD37 -> #VALUE!
A38: =A37+1 -> 38 | B38: 43252 | C38: =CONCATENATE("IF(VLOOKUP(B9,MAPA_DATA!D:G,2,0)=1,'FACT_EMITIDA',IF(VLOOKUP(B",A38,",MAPA_DATA!D:G,3,0)=1,'FACT_EST_EFACT',(IF(VLOOKUP(B",A38,",MAPA_DATA!D:G,4,0)=1,'FACT_EST_CEN','SIN_DATA')))") -> IF(VLOOKUP(B9,MAPA_DATA!D:G,2,0)=1,'FACT_EMITIDA',IF(VLOOKUP(B38,MAPA_DATA!D:G,3,0)=1,'FACT_EST_EFACT',(IF(VLOOKUP(B38,MAPA_DATA!D:G,4,0)=1,'FACT_EST_CEN','SIN_DATA'))) | D38: =CONCATENATE("SUMIF(",IF(C38="FACT_EMITIDA","SIGGE_E",C38),"!B:B,Reliquidacion!B",A38,",",IF(C38="FACT_EMITIDA","SIGGE_E",C38),"!F:F)") -> SUMIF(IF(VLOOKUP(B9,MAPA_DATA!D:G,2,0)=1,'FACT_EMITIDA',IF(VLOOKUP(B38,MAPA_DATA!D:G,3,0)=1,'FACT_EST_EFACT',(IF(VLOOKUP(B38,MAPA_DATA!D:G,4,0)=1,'FACT_EST_CEN','SIN_DATA')))!B:B,Reliquidacion!B38,IF(VLOOKUP(B9,MAPA_DATA!D:G,2,0)=1,'FACT_EMITIDA',IF(VLOOKUP(B38,MAPA_DATA!D:G,3,0)=1,'FACT_EST_EFACT',(IF(VLOOKUP(B38,MAPA_DATA!D:G,4,0)=1,'FACT_EST_CEN','SIN_DATA')))!F:F) | E38: =CONCATENATE("(F",A38,"/D",A38,")") -> (F38/D38) | F38: =CONCATENATE("SUMIF(",IF(C38="FACT_EMITIDA","SIGGE_E",C38),"!B:B,Reliquidacion!B",A38,",",IF(C38="FACT_EMITIDA","SIGGE_E",C38),"!H:H)") -> SUMIF(IF(VLOOKUP(B9,MAPA_DATA!D:G,2,0)=1,'FACT_EMITIDA',IF(VLOOKUP(B38,MAPA_DATA!D:G,3,0)=1,'FACT_EST_EFACT',(IF(VLOOKUP(B38,MAPA_DATA!D:G,4,0)=1,'FACT_EST_CEN','SIN_DATA')))!B:B,Reliquidacion!B38,IF(VLOOKUP(B9,MAPA_DATA!D:G,2,0)=1,'FACT_EMITIDA',IF(VLOOKUP(B38,MAPA_DATA!D:G,3,0)=1,'FACT_EST_EFACT',(IF(VLOOKUP(B38,MAPA_DATA!D:G,4,0)=1,'FACT_EST_CEN','SIN_DATA')))!H:H) | G38: =CONCATENATE("SUMIF(",IF(C38="FACT_EMITIDA","SIGGE_P",C38),"!B:B,Reliquidacion!B",A38,",",IF(C38="FACT_EMITIDA","SIGGE_P",C38),"!F:F)") -> SUMIF(IF(VLOOKUP(B9,MAPA_DATA!D:G,2,0)=1,'FACT_EMITIDA',IF(VLOOKUP(B38,MAPA_DATA!D:G,3,0)=1,'FACT_EST_EFACT',(IF(VLOOKUP(B38,MAPA_DATA!D:G,4,0)=1,'FACT_EST_CEN','SIN_DATA')))!B:B,Reliquidacion!B38,IF(VLOOKUP(B9,MAPA_DATA!D:G,2,0)=1,'FACT_EMITIDA',IF(VLOOKUP(B38,MAPA_DATA!D:G,3,0)=1,'FACT_EST_EFACT',(IF(VLOOKUP(B38,MAPA_DATA!D:G,4,0)=1,'FACT_EST_CEN','SIN_DATA')))!F:F) | H38: =CONCATENATE("(I",A38,"/G",A38,")") -> (I38/G38) | I38: =CONCATENATE("SUMIF(",IF(C38="FACT_EMITIDA","SIGGE_P",C38),"!B:B,Reliquidacion!B",A38,",",IF(C38="FACT_EMITIDA","SIGGE_P",C38),"!H:H)") -> SUMIF(IF(VLOOKUP(B9,MAPA_DATA!D:G,2,0)=1,'FACT_EMITIDA',IF(VLOOKUP(B38,MAPA_DATA!D:G,3,0)=1,'FACT_EST_EFACT',(IF(VLOOKUP(B38,MAPA_DATA!D:G,4,0)=1,'FACT_EST_CEN','SIN_DATA')))!B:B,Reliquidacion!B38,IF(VLOOKUP(B9,MAPA_DATA!D:G,2,0)=1,'FACT_EMITIDA',IF(VLOOKUP(B38,MAPA_DATA!D:G,3,0)=1,'FACT_EST_EFACT',(IF(VLOOKUP(B38,MAPA_DATA!D:G,4,0)=1,'FACT_EST_CEN','SIN_DATA')))!H:H) | J38: =CONCATENATE("(F",A38,"+I",A38,")") -> (F38+I38) | L38: =IF(VLOOKUP(B38,MAPA_DATA!D:I,5,0)=1,"EFACT_CNE",IF(VLOOKUP(B38,MAPA_DATA!D:I,6,0)=1,"EFACT_EST_CNE","SIN_DATA")) -> SIN_DATA | M38: =CONCATENATE("SUMIF(",L38,"!B:B;Reliquidacion!B",A38,";",L38,"!S:S)") -> SUMIF(SIN_DATA!B:B;Reliquidacion!B38;SIN_DATA!S:S) | N38: =CONCATENATE("(O",A38,"/M",A38,")") -> (O38/M38) | O38: =CONCATENATE("SUMIF(",L38,"!B:B;Reliquidacion!B",A38,";",L38,"!W:W)") -> SUMIF(SIN_DATA!B:B;Reliquidacion!B38;SIN_DATA!W:W) | P38: =CONCATENATE("SUMIF(",L38,"!B:B;Reliquidacion!B",A38,";",L38,"!X:X)") -> SUMIF(SIN_DATA!B:B;Reliquidacion!B38;SIN_DATA!X:X) | Q38: =CONCATENATE("(R",A38,"/P",A38,")") -> (R38/P38) | R38: =CONCATENATE("SUMIF(",L38,"!B:B;Reliquidacion!B",A38,";",L38,"!AB:AB)") -> SUMIF(SIN_DATA!B:B;Reliquidacion!B38;SIN_DATA!AB:AB) | S38: =CONCATENATE("(O",A38,"+R",A38,")") -> (O38+R38) | U38: 43252 | V38: =CONCATENATE("=(S",A38,"-J",A38,")") -> =(S38-J38) | W38: 20T/13-12-2018 | X38: =VLOOKUP(W38,[1]INTERESES!A:B,2,0) -> 0 | Y38: =VLOOKUP(W38,#REF!,6,0) -> #REF! | Z38: 43306 | AA38: =AA37 -> 44377 | AB38: =AA38-Z38 -> 1071 | AC38: =+(1+Y38)^(AB38/360)-1 -> #REF! | AD38: =AC38*V38 -> #REF! | AE38: =+V38+AD38 -> #VALUE!
A39: =A38+1 -> 39 | B39: 43282 | C39: =CONCATENATE("IF(VLOOKUP(B9,MAPA_DATA!D:G,2,0)=1,'FACT_EMITIDA',IF(VLOOKUP(B",A39,",MAPA_DATA!D:G,3,0)=1,'FACT_EST_EFACT',(IF(VLOOKUP(B",A39,",MAPA_DATA!D:G,4,0)=1,'FACT_EST_CEN','SIN_DATA')))") -> IF(VLOOKUP(B9,MAPA_DATA!D:G,2,0)=1,'FACT_EMITIDA',IF(VLOOKUP(B39,MAPA_DATA!D:G,3,0)=1,'FACT_EST_EFACT',(IF(VLOOKUP(B39,MAPA_DATA!D:G,4,0)=1,'FACT_EST_CEN','SIN_DATA'))) | D39: =CONCATENATE("SUMIF(",IF(C39="FACT_EMITIDA","SIGGE_E",C39),"!B:B,Reliquidacion!B",A39,",",IF(C39="FACT_EMITIDA","SIGGE_E",C39),"!F:F)") -> SUMIF(IF(VLOOKUP(B9,MAPA_DATA!D:G,2,0)=1,'FACT_EMITIDA',IF(VLOOKUP(B39,MAPA_DATA!D:G,3,0)=1,'FACT_EST_EFACT',(IF(VLOOKUP(B39,MAPA_DATA!D:G,4,0)=1,'FACT_EST_CEN','SIN_DATA')))!B:B,Reliquidacion!B39,IF(VLOOKUP(B9,MAPA_DATA!D:G,2,0)=1,'FACT_EMITIDA',IF(VLOOKUP(B39,MAPA_DATA!D:G,3,0)=1,'FACT_EST_EFACT',(IF(VLOOKUP(B39,MAPA_DATA!D:G,4,0)=1,'FACT_EST_CEN','SIN_DATA')))!F:F) | E39: =CONCATENATE("(F",A39,"/D",A39,")") -> (F39/D39) | F39: =CONCATENATE("SUMIF(",IF(C39="FACT_EMITIDA","SIGGE_E",C39),"!B:B,Reliquidacion!B",A39,",",IF(C39="FACT_EMITIDA","SIGGE_E",C39),"!H:H)") -> SUMIF(IF(VLOOKUP(B9,MAPA_DATA!D:G,2,0)=1,'FACT_EMITIDA',IF(VLOOKUP(B39,MAPA_DATA!D:G,3,0)=1,'FACT_EST_EFACT',(IF(VLOOKUP(B39,MAPA_DATA!D:G,4,0)=1,'FACT_EST_CEN','SIN_DATA')))!B:B,Reliquidacion!B39,IF(VLOOKUP(B9,MAPA_DATA!D:G,2,0)=1,'FACT_EMITIDA',IF(VLOOKUP(B39,MAPA_DATA!D:G,3,0)=1,'FACT_EST_EFACT',(IF(VLOOKUP(B39,MAPA_DATA!D:G,4,0)=1,'FACT_EST_CEN','SIN_DATA')))!H:H) | G39: =CONCATENATE("SUMIF(",IF(C39="FACT_EMITIDA","SIGGE_P",C39),"!B:B,Reliquidacion!B",A39,",",IF(C39="FACT_EMITIDA","SIGGE_P",C39),"!F:F)") -> SUMIF(IF(VLOOKUP(B9,MAPA_DATA!D:G,2,0)=1,'FACT_EMITIDA',IF(VLOOKUP(B39,MAPA_DATA!D:G,3,0)=1,'FACT_EST_EFACT',(IF(VLOOKUP(B39,MAPA_DATA!D:G,4,0)=1,'FACT_EST_CEN','SIN_DATA')))!B:B,Reliquidacion!B39,IF(VLOOKUP(B9,MAPA_DATA!D:G,2,0)=1,'FACT_EMITIDA',IF(VLOOKUP(B39,MAPA_DATA!D:G,3,0)=1,'FACT_EST_EFACT',(IF(VLOOKUP(B39,MAPA_DATA!D:G,4,0)=1,'FACT_EST_CEN','SIN_DATA')))!F:F) | H39: =CONCATENATE("(I",A39,"/G",A39,")") -> (I39/G39) | I39: =CONCATENATE("SUMIF(",IF(C39="FACT_EMITIDA","SIGGE_P",C39),"!B:B,Reliquidacion!B",A39,",",IF(C39="FACT_EMITIDA","SIGGE_P",C39),"!H:H)") -> SUMIF(IF(VLOOKUP(B9,MAPA_DATA!D:G,2,0)=1,'FACT_EMITIDA',IF(VLOOKUP(B39,MAPA_DATA!D:G,3,0)=1,'FACT_EST_EFACT',(IF(VLOOKUP(B39,MAPA_DATA!D:G,4,0)=1,'FACT_EST_CEN','SIN_DATA')))!B:B,Reliquidacion!B39,IF(VLOOKUP(B9,MAPA_DATA!D:G,2,0)=1,'FACT_EMITIDA',IF(VLOOKUP(B39,MAPA_DATA!D:G,3,0)=1,'FACT_EST_EFACT',(IF(VLOOKUP(B39,MAPA_DATA!D:G,4,0)=1,'FACT_EST_CEN','SIN_DATA')))!H:H) | J39: =CONCATENATE("(F",A39,"+I",A39,")") -> (F39+I39) | L39: =IF(VLOOKUP(B39,MAPA_DATA!D:I,5,0)=1,"EFACT_CNE",IF(VLOOKUP(B39,MAPA_DATA!D:I,6,0)=1,"EFACT_EST_CNE","SIN_DATA")) -> SIN_DATA | M39: =CONCATENATE("SUMIF(",L39,"!B:B;Reliquidacion!B",A39,";",L39,"!S:S)") -> SUMIF(SIN_DATA!B:B;Reliquidacion!B39;SIN_DATA!S:S) | N39: =CONCATENATE("(O",A39,"/M",A39,")") -> (O39/M39) | O39: =CONCATENATE("SUMIF(",L39,"!B:B;Reliquidacion!B",A39,";",L39,"!W:W)") -> SUMIF(SIN_DATA!B:B;Reliquidacion!B39;SIN_DATA!W:W) | P39: =CONCATENATE("SUMIF(",L39,"!B:B;Reliquidacion!B",A39,";",L39,"!X:X)") -> SUMIF(SIN_DATA!B:B;Reliquidacion!B39;SIN_DATA!X:X) | Q39: =CONCATENATE("(R",A39,"/P",A39,")") -> (R39/P39) | R39: =CONCATENATE("SUMIF(",L39,"!B:B;Reliquidacion!B",A39,";",L39,"!AB:AB)") -> SUMIF(SIN_DATA!B:B;Reliquidacion!B39;SIN_DATA!AB:AB) | S39: =CONCATENATE("(O",A39,"+R",A39,")") -> (O39+R39) | U39: 43282 | V39: =CONCATENATE("=(S",A39,"-J",A39,")") -> =(S39-J39) | W39: 20T/13-12-2018 | X39: =VLOOKUP(W39,[1]INTERESES!A:B,2,0) -> 0 | Y39: =VLOOKUP(W39,#REF!,6,0) -> #REF! | Z39: 43337 | AA39: =AA38 -> 44377 | AB39: =AA39-Z39 -> 1040 | AC39: =+(1+Y39)^(AB39/360)-1 -> #REF! | AD39: =AC39*V39 -> #REF! | AE39: =+V39+AD39 -> #VALUE!
A40: =A39+1 -> 40 | B40: 43313 | C40: =CONCATENATE("IF(VLOOKUP(B9,MAPA_DATA!D:G,2,0)=1,'FACT_EMITIDA',IF(VLOOKUP(B",A40,",MAPA_DATA!D:G,3,0)=1,'FACT_EST_EFACT',(IF(VLOOKUP(B",A40,",MAPA_DATA!D:G,4,0)=1,'FACT_EST_CEN','SIN_DATA')))") -> IF(VLOOKUP(B9,MAPA_DATA!D:G,2,0)=1,'FACT_EMITIDA',IF(VLOOKUP(B40,MAPA_DATA!D:G,3,0)=1,'FACT_EST_EFACT',(IF(VLOOKUP(B40,MAPA_DATA!D:G,4,0)=1,'FACT_EST_CEN','SIN_DATA'))) | D40: =CONCATENATE("SUMIF(",IF(C40="FACT_EMITIDA","SIGGE_E",C40),"!B:B,Reliquidacion!B",A40,",",IF(C40="FACT_EMITIDA","SIGGE_E",C40),"!F:F)") -> SUMIF(IF(VLOOKUP(B9,MAPA_DATA!D:G,2,0)=1,'FACT_EMITIDA',IF(VLOOKUP(B40,MAPA_DATA!D:G,3,0)=1,'FACT_EST_EFACT',(IF(VLOOKUP(B40,MAPA_DATA!D:G,4,0)=1,'FACT_EST_CEN','SIN_DATA')))!B:B,Reliquidacion!B40,IF(VLOOKUP(B9,MAPA_DATA!D:G,2,0)=1,'FACT_EMITIDA',IF(VLOOKUP(B40,MAPA_DATA!D:G,3,0)=1,'FACT_EST_EFACT',(IF(VLOOKUP(B40,MAPA_DATA!D:G,4,0)=1,'FACT_EST_CEN','SIN_DATA')))!F:F) | E40: =CONCATENATE("(F",A40,"/D",A40,")") -> (F40/D40) | F40: =CONCATENATE("SUMIF(",IF(C40="FACT_EMITIDA","SIGGE_E",C40),"!B:B,Reliquidacion!B",A40,",",IF(C40="FACT_EMITIDA","SIGGE_E",C40),"!H:H)") -> SUMIF(IF(VLOOKUP(B9,MAPA_DATA!D:G,2,0)=1,'FACT_EMITIDA',IF(VLOOKUP(B40,MAPA_DATA!D:G,3,0)=1,'FACT_EST_EFACT',(IF(VLOOKUP(B40,MAPA_DATA!D:G,4,0)=1,'FACT_EST_CEN','SIN_DATA')))!B:B,Reliquidacion!B40,IF(VLOOKUP(B9,MAPA_DATA!D:G,2,0)=1,'FACT_EMITIDA',IF(VLOOKUP(B40,MAPA_DATA!D:G,3,0)=1,'FACT_EST_EFACT',(IF(VLOOKUP(B40,MAPA_DATA!D:G,4,0)=1,'FACT_EST_CEN','SIN_DATA')))!H:H) | G40: =CONCATENATE("SUMIF(",IF(C40="FACT_EMITIDA","SIGGE_P",C40),"!B:B,Reliquidacion!B",A40,",",IF(C40="FACT_EMITIDA","SIGGE_P",C40),"!F:F)") -> SUMIF(IF(VLOOKUP(B9,MAPA_DATA!D:G,2,0)=1,'FACT_EMITIDA',IF(VLOOKUP(B40,MAPA_DATA!D:G,3,0)=1,'FACT_EST_EFACT',(IF(VLOOKUP(B40,MAPA_DATA!D:G,4,0)=1,'FACT_EST_CEN','SIN_DATA')))!B:B,Reliquidacion!B40,IF(VLOOKUP(B9,MAPA_DATA!D:G,2,0)=1,'FACT_EMITIDA',IF(VLOOKUP(B40,MAPA_DATA!D:G,3,0)=1,'FACT_EST_EFACT',(IF(VLOOKUP(B40,MAPA_DATA!D:G,4,0)=1,'FACT_EST_CEN','SIN_DATA')))!F:F) | H40: =CONCATENATE("(I",A40,"/G",A40,")") -> (I40/G40) | I40: =CONCATENATE("SUMIF(",IF(C40="FACT_EMITIDA","SIGGE_P",C40),"!B:B,Reliquidacion!B",A40,",",IF(C40="FACT_EMITIDA","SIGGE_P",C40),"!H:H)") -> SUMIF(IF(VLOOKUP(B9,MAPA_DATA!D:G,2,0)=1,'FACT_EMITIDA',IF(VLOOKUP(B40,MAPA_DATA!D:G,3,0)=1,'FACT_EST_EFACT',(IF(VLOOKUP(B40,MAPA_DATA!D:G,4,0)=1,'FACT_EST_CEN','SIN_DATA')))!B:B,Reliquidacion!B40,IF(VLOOKUP(B9,MAPA_DATA!D:G,2,0)=1,'FACT_EMITIDA',IF(VLOOKUP(B40,MAPA_DATA!D:G,3,0)=1,'FACT_EST_EFACT',(IF(VLOOKUP(B40,MAPA_DATA!D:G,4,0)=1,'FACT_EST_CEN','SIN_DATA')))!H:H) | J40: =CONCATENATE("(F",A40,"+I",A40,")") -> (F40+I40) | L40: =IF(VLOOKUP(B40,MAPA_DATA!D:I,5,0)=1,"EFACT_CNE",IF(VLOOKUP(B40,MAPA_DATA!D:I,6,0)=1,"EFACT_EST_CNE","SIN_DATA")) -> SIN_DATA | M40: =CONCATENATE("SUMIF(",L40,"!B:B;Reliquidacion!B",A40,";",L40,"!S:S)") -> SUMIF(SIN_DATA!B:B;Reliquidacion!B40;SIN_DATA!S:S) | N40: =CONCATENATE("(O",A40,"/M",A40,")") -> (O40/M40) | O40: =CONCATENATE("SUMIF(",L40,"!B:B;Reliquidacion!B",A40,";",L40,"!W:W)") -> SUMIF(SIN_DATA!B:B;Reliquidacion!B40;SIN_DATA!W:W) | P40: =CONCATENATE("SUMIF(",L40,"!B:B;Reliquidacion!B",A40,";",L40,"!X:X)") -> SUMIF(SIN_DATA!B:B;Reliquidacion!B40;SIN_DATA!X:X) | Q40: =CONCATENATE("(R",A40,"/P",A40,")") -> (R40/P40) | R40: =CONCATENATE("SUMIF(",L40,"!B:B;Reliquidacion!B",A40,";",L40,"!AB:AB)") -> SUMIF(SIN_DATA!B:B;Reliquidacion!B40;SIN_DATA!AB:AB) | S40: =CONCATENATE("(O",A40,"+R",A40,")") -> (O40+R40) | U40: 43313 | V40: =CONCATENATE("=(S",A40,"-J",A40,")") -> =(S40-J40) | W40: 20T/13-12-2018 | X40: =VLOOKUP(W40,[1]INTERESES!A:B,2,0) -> 0 | Y40: =VLOOKUP(W40,#REF!,6,0) -> #REF! | Z40: 43368 | AA40: =AA39 -> 44377 | AB40: =AA40-Z40 -> 1009 | AC40: =+(1+Y40)^(AB40/360)-1 -> #REF! | AD40: =AC40*V40 -> #REF! | AE40: =+V40+AD40 -> #VALUE!
A41: =A40+1 -> 41 | B41: 43344 | C41: =CONCATENATE("IF(VLOOKUP(B9,MAPA_DATA!D:G,2,0)=1,'FACT_EMITIDA',IF(VLOOKUP(B",A41,",MAPA_DATA!D:G,3,0)=1,'FACT_EST_EFACT',(IF(VLOOKUP(B",A41,",MAPA_DATA!D:G,4,0)=1,'FACT_EST_CEN','SIN_DATA')))") -> IF(VLOOKUP(B9,MAPA_DATA!D:G,2,0)=1,'FACT_EMITIDA',IF(VLOOKUP(B41,MAPA_DATA!D:G,3,0)=1,'FACT_EST_EFACT',(IF(VLOOKUP(B41,MAPA_DATA!D:G,4,0)=1,'FACT_EST_CEN','SIN_DATA'))) | D41: =CONCATENATE("SUMIF(",IF(C41="FACT_EMITIDA","SIGGE_E",C41),"!B:B,Reliquidacion!B",A41,",",IF(C41="FACT_EMITIDA","SIGGE_E",C41),"!F:F)") -> SUMIF(IF(VLOOKUP(B9,MAPA_DATA!D:G,2,0)=1,'FACT_EMITIDA',IF(VLOOKUP(B41,MAPA_DATA!D:G,3,0)=1,'FACT_EST_EFACT',(IF(VLOOKUP(B41,MAPA_DATA!D:G,4,0)=1,'FACT_EST_CEN','SIN_DATA')))!B:B,Reliquidacion!B41,IF(VLOOKUP(B9,MAPA_DATA!D:G,2,0)=1,'FACT_EMITIDA',IF(VLOOKUP(B41,MAPA_DATA!D:G,3,0)=1,'FACT_EST_EFACT',(IF(VLOOKUP(B41,MAPA_DATA!D:G,4,0)=1,'FACT_EST_CEN','SIN_DATA')))!F:F) | E41: =CONCATENATE("(F",A41,"/D",A41,")") -> (F41/D41) | F41: =CONCATENATE("SUMIF(",IF(C41="FACT_EMITIDA","SIGGE_E",C41),"!B:B,Reliquidacion!B",A41,",",IF(C41="FACT_EMITIDA","SIGGE_E",C41),"!H:H)") -> SUMIF(IF(VLOOKUP(B9,MAPA_DATA!D:G,2,0)=1,'FACT_EMITIDA',IF(VLOOKUP(B41,MAPA_DATA!D:G,3,0)=1,'FACT_EST_EFACT',(IF(VLOOKUP(B41,MAPA_DATA!D:G,4,0)=1,'FACT_EST_CEN','SIN_DATA')))!B:B,Reliquidacion!B41,IF(VLOOKUP(B9,MAPA_DATA!D:G,2,0)=1,'FACT_EMITIDA',IF(VLOOKUP(B41,MAPA_DATA!D:G,3,0)=1,'FACT_EST_EFACT',(IF(VLOOKUP(B41,MAPA_DATA!D:G,4,0)=1,'FACT_EST_CEN','SIN_DATA')))!H:H) | G41: =CONCATENATE("SUMIF(",IF(C41="FACT_EMITIDA","SIGGE_P",C41),"!B:B,Reliquidacion!B",A41,",",IF(C41="FACT_EMITIDA","SIGGE_P",C41),"!F:F)") -> SUMIF(IF(VLOOKUP(B9,MAPA_DATA!D:G,2,0)=1,'FACT_EMITIDA',IF(VLOOKUP(B41,MAPA_DATA!D:G,3,0)=1,'FACT_EST_EFACT',(IF(VLOOKUP(B41,MAPA_DATA!D:G,4,0)=1,'FACT_EST_CEN','SIN_DATA')))!B:B,Reliquidacion!B41,IF(VLOOKUP(B9,MAPA_DATA!D:G,2,0)=1,'FACT_EMITIDA',IF(VLOOKUP(B41,MAPA_DATA!D:G,3,0)=1,'FACT_EST_EFACT',(IF(VLOOKUP(B41,MAPA_DATA!D:G,4,0)=1,'FACT_EST_CEN','SIN_DATA')))!F:F) | H41: =CONCATENATE("(I",A41,"/G",A41,")") -> (I41/G41) | I41: =CONCATENATE("SUMIF(",IF(C41="FACT_EMITIDA","SIGGE_P",C41),"!B:B,Reliquidacion!B",A41,",",IF(C41="FACT_EMITIDA","SIGGE_P",C41),"!H:H)") -> SUMIF(IF(VLOOKUP(B9,MAPA_DATA!D:G,2,0)=1,'FACT_EMITIDA',IF(VLOOKUP(B41,MAPA_DATA!D:G,3,0)=1,'FACT_EST_EFACT',(IF(VLOOKUP(B41,MAPA_DATA!D:G,4,0)=1,'FACT_EST_CEN','SIN_DATA')))!B:B,Reliquidacion!B41,IF(VLOOKUP(B9,MAPA_DATA!D:G,2,0)=1,'FACT_EMITIDA',IF(VLOOKUP(B41,MAPA_DATA!D:G,3,0)=1,'FACT_EST_EFACT',(IF(VLOOKUP(B41,MAPA_DATA!D:G,4,0)=1,'FACT_EST_CEN','SIN_DATA')))!H:H) | J41: =CONCATENATE("(F",A41,"+I",A41,")") -> (F41+I41) | L41: =IF(VLOOKUP(B41,MAPA_DATA!D:I,5,0)=1,"EFACT_CNE",IF(VLOOKUP(B41,MAPA_DATA!D:I,6,0)=1,"EFACT_EST_CNE","SIN_DATA")) -> SIN_DATA | M41: =CONCATENATE("SUMIF(",L41,"!B:B;Reliquidacion!B",A41,";",L41,"!S:S)") -> SUMIF(SIN_DATA!B:B;Reliquidacion!B41;SIN_DATA!S:S) | N41: =CONCATENATE("(O",A41,"/M",A41,")") -> (O41/M41) | O41: =CONCATENATE("SUMIF(",L41,"!B:B;Reliquidacion!B",A41,";",L41,"!W:W)") -> SUMIF(SIN_DATA!B:B;Reliquidacion!B41;SIN_DATA!W:W) | P41: =CONCATENATE("SUMIF(",L41,"!B:B;Reliquidacion!B",A41,";",L41,"!X:X)") -> SUMIF(SIN_DATA!B:B;Reliquidacion!B41;SIN_DATA!X:X) | Q41: =CONCATENATE("(R",A41,"/P",A41,")") -> (R41/P41) | R41: =CONCATENATE("SUMIF(",L41,"!B:B;Reliquidacion!B",A41,";",L41,"!AB:AB)") -> SUMIF(SIN_DATA!B:B;Reliquidacion!B41;SIN_DATA!AB:AB) | S41: =CONCATENATE("(O",A41,"+R",A41,")") -> (O41+R41) | U41: 43344 | V41: =CONCATENATE("=(S",A41,"-J",A41,")") -> =(S41-J41) | W41: 6T/08-05-2020 | X41: =VLOOKUP(W41,[1]INTERESES!A:B,2,0) -> 0 | Y41: =VLOOKUP(W41,#REF!,6,0) -> #REF! | Z41: 43398 | AA41: =AA40 -> 44377 | AB41: =AA41-Z41 -> 979 | AC41: =+(1+Y41)^(AB41/360)-1 -> #REF! | AD41: =AC41*V41 -> #REF! | AE41: =+V41+AD41 -> #VALUE!
A42: =A41+1 -> 42 | B42: 43374 | C42: =CONCATENATE("IF(VLOOKUP(B9,MAPA_DATA!D:G,2,0)=1,'FACT_EMITIDA',IF(VLOOKUP(B",A42,",MAPA_DATA!D:G,3,0)=1,'FACT_EST_EFACT',(IF(VLOOKUP(B",A42,",MAPA_DATA!D:G,4,0)=1,'FACT_EST_CEN','SIN_DATA')))") -> IF(VLOOKUP(B9,MAPA_DATA!D:G,2,0)=1,'FACT_EMITIDA',IF(VLOOKUP(B42,MAPA_DATA!D:G,3,0)=1,'FACT_EST_EFACT',(IF(VLOOKUP(B42,MAPA_DATA!D:G,4,0)=1,'FACT_EST_CEN','SIN_DATA'))) | D42: =CONCATENATE("SUMIF(",IF(C42="FACT_EMITIDA","SIGGE_E",C42),"!B:B,Reliquidacion!B",A42,",",IF(C42="FACT_EMITIDA","SIGGE_E",C42),"!F:F)") -> SUMIF(IF(VLOOKUP(B9,MAPA_DATA!D:G,2,0)=1,'FACT_EMITIDA',IF(VLOOKUP(B42,MAPA_DATA!D:G,3,0)=1,'FACT_EST_EFACT',(IF(VLOOKUP(B42,MAPA_DATA!D:G,4,0)=1,'FACT_EST_CEN','SIN_DATA')))!B:B,Reliquidacion!B42,IF(VLOOKUP(B9,MAPA_DATA!D:G,2,0)=1,'FACT_EMITIDA',IF(VLOOKUP(B42,MAPA_DATA!D:G,3,0)=1,'FACT_EST_EFACT',(IF(VLOOKUP(B42,MAPA_DATA!D:G,4,0)=1,'FACT_EST_CEN','SIN_DATA')))!F:F) | E42: =CONCATENATE("(F",A42,"/D",A42,")") -> (F42/D42) | F42: =CONCATENATE("SUMIF(",IF(C42="FACT_EMITIDA","SIGGE_E",C42),"!B:B,Reliquidacion!B",A42,",",IF(C42="FACT_EMITIDA","SIGGE_E",C42),"!H:H)") -> SUMIF(IF(VLOOKUP(B9,MAPA_DATA!D:G,2,0)=1,'FACT_EMITIDA',IF(VLOOKUP(B42,MAPA_DATA!D:G,3,0)=1,'FACT_EST_EFACT',(IF(VLOOKUP(B42,MAPA_DATA!D:G,4,0)=1,'FACT_EST_CEN','SIN_DATA')))!B:B,Reliquidacion!B42,IF(VLOOKUP(B9,MAPA_DATA!D:G,2,0)=1,'FACT_EMITIDA',IF(VLOOKUP(B42,MAPA_DATA!D:G,3,0)=1,'FACT_EST_EFACT',(IF(VLOOKUP(B42,MAPA_DATA!D:G,4,0)=1,'FACT_EST_CEN','SIN_DATA')))!H:H) | G42: =CONCATENATE("SUMIF(",IF(C42="FACT_EMITIDA","SIGGE_P",C42),"!B:B,Reliquidacion!B",A42,",",IF(C42="FACT_EMITIDA","SIGGE_P",C42),"!F:F)") -> SUMIF(IF(VLOOKUP(B9,MAPA_DATA!D:G,2,0)=1,'FACT_EMITIDA',IF(VLOOKUP(B42,MAPA_DATA!D:G,3,0)=1,'FACT_EST_EFACT',(IF(VLOOKUP(B42,MAPA_DATA!D:G,4,0)=1,'FACT_EST_CEN','SIN_DATA')))!B:B,Reliquidacion!B42,IF(VLOOKUP(B9,MAPA_DATA!D:G,2,0)=1,'FACT_EMITIDA',IF(VLOOKUP(B42,MAPA_DATA!D:G,3,0)=1,'FACT_EST_EFACT',(IF(VLOOKUP(B42,MAPA_DATA!D:G,4,0)=1,'FACT_EST_CEN','SIN_DATA')))!F:F) | H42: =CONCATENATE("(I",A42,"/G",A42,")") -> (I42/G42) | I42: =CONCATENATE("SUMIF(",IF(C42="FACT_EMITIDA","SIGGE_P",C42),"!B:B,Reliquidacion!B",A42,",",IF(C42="FACT_EMITIDA","SIGGE_P",C42),"!H:H)") -> SUMIF(IF(VLOOKUP(B9,MAPA_DATA!D:G,2,0)=1,'FACT_EMITIDA',IF(VLOOKUP(B42,MAPA_DATA!D:G,3,0)=1,'FACT_EST_EFACT',(IF(VLOOKUP(B42,MAPA_DATA!D:G,4,0)=1,'FACT_EST_CEN','SIN_DATA')))!B:B,Reliquidacion!B42,IF(VLOOKUP(B9,MAPA_DATA!D:G,2,0)=1,'FACT_EMITIDA',IF(VLOOKUP(B42,MAPA_DATA!D:G,3,0)=1,'FACT_EST_EFACT',(IF(VLOOKUP(B42,MAPA_DATA!D:G,4,0)=1,'FACT_EST_CEN','SIN_DATA')))!H:H) | J42: =CONCATENATE("(F",A42,"+I",A42,")") -> (F42+I42) | L42: =IF(VLOOKUP(B42,MAPA_DATA!D:I,5,0)=1,"EFACT_CNE",IF(VLOOKUP(B42,MAPA_DATA!D:I,6,0)=1,"EFACT_EST_CNE","SIN_DATA")) -> SIN_DATA | M42: =CONCATENATE("SUMIF(",L42,"!B:B;Reliquidacion!B",A42,";",L42,"!S:S)") -> SUMIF(SIN_DATA!B:B;Reliquidacion!B42;SIN_DATA!S:S) | N42: =CONCATENATE("(O",A42,"/M",A42,")") -> (O42/M42) | O42: =CONCATENATE("SUMIF(",L42,"!B:B;Reliquidacion!B",A42,";",L42,"!W:W)") -> SUMIF(SIN_DATA!B:B;Reliquidacion!B42;SIN_DATA!W:W) | P42: =CONCATENATE("SUMIF(",L42,"!B:B;Reliquidacion!B",A42,";",L42,"!X:X)") -> SUMIF(SIN_DATA!B:B;Reliquidacion!B42;SIN_DATA!X:X) | Q42: =CONCATENATE("(R",A42,"/P",A42,")") -> (R42/P42) | R42: =CONCATENATE("SUMIF(",L42,"!B:B;Reliquidacion!B",A42,";",L42,"!AB:AB)") -> SUMIF(SIN_DATA!B:B;Reliquidacion!B42;SIN_DATA!AB:AB) | S42: =CONCATENATE("(O",A42,"+R",A42,")") -> (O42+R42) | U42: 43374 | V42: =CONCATENATE("=(S",A42,"-J",A42,")") -> =(S42-J42) | W42: 6T/08-05-2020 | X42: =VLOOKUP(W42,[1]INTERESES!A:B,2,0) -> 0 | Y42: =VLOOKUP(W42,#REF!,6,0) -> #REF! | Z42: 43429 | AA42: =AA41 -> 44377 | AB42: =AA42-Z42 -> 948 | AC42: =+(1+Y42)^(AB42/360)-1 -> #REF! | AD42: =AC42*V42 -> #REF! | AE42: =+V42+AD42 -> #VALUE!
A43: =A42+1 -> 43 | B43: 43405 | C43: =CONCATENATE("IF(VLOOKUP(B9,MAPA_DATA!D:G,2,0)=1,'FACT_EMITIDA',IF(VLOOKUP(B",A43,",MAPA_DATA!D:G,3,0)=1,'FACT_EST_EFACT',(IF(VLOOKUP(B",A43,",MAPA_DATA!D:G,4,0)=1,'FACT_EST_CEN','SIN_DATA')))") -> IF(VLOOKUP(B9,MAPA_DATA!D:G,2,0)=1,'FACT_EMITIDA',IF(VLOOKUP(B43,MAPA_DATA!D:G,3,0)=1,'FACT_EST_EFACT',(IF(VLOOKUP(B43,MAPA_DATA!D:G,4,0)=1,'FACT_EST_CEN','SIN_DATA'))) | D43: =CONCATENATE("SUMIF(",IF(C43="FACT_EMITIDA","SIGGE_E",C43),"!B:B,Reliquidacion!B",A43,",",IF(C43="FACT_EMITIDA","SIGGE_E",C43),"!F:F)") -> SUMIF(IF(VLOOKUP(B9,MAPA_DATA!D:G,2,0)=1,'FACT_EMITIDA',IF(VLOOKUP(B43,MAPA_DATA!D:G,3,0)=1,'FACT_EST_EFACT',(IF(VLOOKUP(B43,MAPA_DATA!D:G,4,0)=1,'FACT_EST_CEN','SIN_DATA')))!B:B,Reliquidacion!B43,IF(VLOOKUP(B9,MAPA_DATA!D:G,2,0)=1,'FACT_EMITIDA',IF(VLOOKUP(B43,MAPA_DATA!D:G,3,0)=1,'FACT_EST_EFACT',(IF(VLOOKUP(B43,MAPA_DATA!D:G,4,0)=1,'FACT_EST_CEN','SIN_DATA')))!F:F) | E43: =CONCATENATE("(F",A43,"/D",A43,")") -> (F43/D43) | F43: =CONCATENATE("SUMIF(",IF(C43="FACT_EMITIDA","SIGGE_E",C43),"!B:B,Reliquidacion!B",A43,",",IF(C43="FACT_EMITIDA","SIGGE_E",C43),"!H:H)") -> SUMIF(IF(VLOOKUP(B9,MAPA_DATA!D:G,2,0)=1,'FACT_EMITIDA',IF(VLOOKUP(B43,MAPA_DATA!D:G,3,0)=1,'FACT_EST_EFACT',(IF(VLOOKUP(B43,MAPA_DATA!D:G,4,0)=1,'FACT_EST_CEN','SIN_DATA')))!B:B,Reliquidacion!B43,IF(VLOOKUP(B9,MAPA_DATA!D:G,2,0)=1,'FACT_EMITIDA',IF(VLOOKUP(B43,MAPA_DATA!D:G,3,0)=1,'FACT_EST_EFACT',(IF(VLOOKUP(B43,MAPA_DATA!D:G,4,0)=1,'FACT_EST_CEN','SIN_DATA')))!H:H) | G43: =CONCATENATE("SUMIF(",IF(C43="FACT_EMITIDA","SIGGE_P",C43),"!B:B,Reliquidacion!B",A43,",",IF(C43="FACT_EMITIDA","SIGGE_P",C43),"!F:F)") -> SUMIF(IF(VLOOKUP(B9,MAPA_DATA!D:G,2,0)=1,'FACT_EMITIDA',IF(VLOOKUP(B43,MAPA_DATA!D:G,3,0)=1,'FACT_EST_EFACT',(IF(VLOOKUP(B43,MAPA_DATA!D:G,4,0)=1,'FACT_EST_CEN','SIN_DATA')))!B:B,Reliquidacion!B43,IF(VLOOKUP(B9,MAPA_DATA!D:G,2,0)=1,'FACT_EMITIDA',IF(VLOOKUP(B43,MAPA_DATA!D:G,3,0)=1,'FACT_EST_EFACT',(IF(VLOOKUP(B43,MAPA_DATA!D:G,4,0)=1,'FACT_EST_CEN','SIN_DATA')))!F:F) | H43: =CONCATENATE("(I",A43,"/G",A43,")") -> (I43/G43) | I43: =CONCATENATE("SUMIF(",IF(C43="FACT_EMITIDA","SIGGE_P",C43),"!B:B,Reliquidacion!B",A43,",",IF(C43="FACT_EMITIDA","SIGGE_P",C43),"!H:H)") -> SUMIF(IF(VLOOKUP(B9,MAPA_DATA!D:G,2,0)=1,'FACT_EMITIDA',IF(VLOOKUP(B43,MAPA_DATA!D:G,3,0)=1,'FACT_EST_EFACT',(IF(VLOOKUP(B43,MAPA_DATA!D:G,4,0)=1,'FACT_EST_CEN','SIN_DATA')))!B:B,Reliquidacion!B43,IF(VLOOKUP(B9,MAPA_DATA!D:G,2,0)=1,'FACT_EMITIDA',IF(VLOOKUP(B43,MAPA_DATA!D:G,3,0)=1,'FACT_EST_EFACT',(IF(VLOOKUP(B43,MAPA_DATA!D:G,4,0)=1,'FACT_EST_CEN','SIN_DATA')))!H:H) | J43: =CONCATENATE("(F",A43,"+I",A43,")") -> (F43+I43) | L43: =IF(VLOOKUP(B43,MAPA_DATA!D:I,5,0)=1,"EFACT_CNE",IF(VLOOKUP(B43,MAPA_DATA!D:I,6,0)=1,"EFACT_EST_CNE","SIN_DATA")) -> SIN_DATA | M43: =CONCATENATE("SUMIF(",L43,"!B:B;Reliquidacion!B",A43,";",L43,"!S:S)") -> SUMIF(SIN_DATA!B:B;Reliquidacion!B43;SIN_DATA!S:S) | N43: =CONCATENATE("(O",A43,"/M",A43,")") -> (O43/M43) | O43: =CONCATENATE("SUMIF(",L43,"!B:B;Reliquidacion!B",A43,";",L43,"!W:W)") -> SUMIF(SIN_DATA!B:B;Reliquidacion!B43;SIN_DATA!W:W) | P43: =CONCATENATE("SUMIF(",L43,"!B:B;Reliquidacion!B",A43,";",L43,"!X:X)") -> SUMIF(SIN_DATA!B:B;Reliquidacion!B43;SIN_DATA!X:X) | Q43: =CONCATENATE("(R",A43,"/P",A43,")") -> (R43/P43) | R43: =CONCATENATE("SUMIF(",L43,"!B:B;Reliquidacion!B",A43,";",L43,"!AB:AB)") -> SUMIF(SIN_DATA!B:B;Reliquidacion!B43;SIN_DATA!AB:AB) | S43: =CONCATENATE("(O",A43,"+R",A43,")") -> (O43+R43) | U43: 43405 | V43: =CONCATENATE("=(S",A43,"-J",A43,")") -> =(S43-J43) | W43: 6T/08-05-2020 | X43: =VLOOKUP(W43,[1]INTERESES!A:B,2,0) -> 0 | Y43: =VLOOKUP(W43,#REF!,6,0) -> #REF! | Z43: 43459 | AA43: =AA42 -> 44377 | AB43: =AA43-Z43 -> 918 | AC43: =+(1+Y43)^(AB43/360)-1 -> #REF! | AD43: =AC43*V43 -> #REF! | AE43: =+V43+AD43 -> #VALUE!
A44: =A43+1 -> 44 | B44: 43435 | C44: =CONCATENATE("IF(VLOOKUP(B9,MAPA_DATA!D:G,2,0)=1,'FACT_EMITIDA',IF(VLOOKUP(B",A44,",MAPA_DATA!D:G,3,0)=1,'FACT_EST_EFACT',(IF(VLOOKUP(B",A44,",MAPA_DATA!D:G,4,0)=1,'FACT_EST_CEN','SIN_DATA')))") -> IF(VLOOKUP(B9,MAPA_DATA!D:G,2,0)=1,'FACT_EMITIDA',IF(VLOOKUP(B44,MAPA_DATA!D:G,3,0)=1,'FACT_EST_EFACT',(IF(VLOOKUP(B44,MAPA_DATA!D:G,4,0)=1,'FACT_EST_CEN','SIN_DATA'))) | D44: =CONCATENATE("SUMIF(",IF(C44="FACT_EMITIDA","SIGGE_E",C44),"!B:B,Reliquidacion!B",A44,",",IF(C44="FACT_EMITIDA","SIGGE_E",C44),"!F:F)") -> SUMIF(IF(VLOOKUP(B9,MAPA_DATA!D:G,2,0)=1,'FACT_EMITIDA',IF(VLOOKUP(B44,MAPA_DATA!D:G,3,0)=1,'FACT_EST_EFACT',(IF(VLOOKUP(B44,MAPA_DATA!D:G,4,0)=1,'FACT_EST_CEN','SIN_DATA')))!B:B,Reliquidacion!B44,IF(VLOOKUP(B9,MAPA_DATA!D:G,2,0)=1,'FACT_EMITIDA',IF(VLOOKUP(B44,MAPA_DATA!D:G,3,0)=1,'FACT_EST_EFACT',(IF(VLOOKUP(B44,MAPA_DATA!D:G,4,0)=1,'FACT_EST_CEN','SIN_DATA')))!F:F) | E44: =CONCATENATE("(F",A44,"/D",A44,")") -> (F44/D44) | F44: =CONCATENATE("SUMIF(",IF(C44="FACT_EMITIDA","SIGGE_E",C44),"!B:B,Reliquidacion!B",A44,",",IF(C44="FACT_EMITIDA","SIGGE_E",C44),"!H:H)") -> SUMIF(IF(VLOOKUP(B9,MAPA_DATA!D:G,2,0)=1,'FACT_EMITIDA',IF(VLOOKUP(B44,MAPA_DATA!D:G,3,0)=1,'FACT_EST_EFACT',(IF(VLOOKUP(B44,MAPA_DATA!D:G,4,0)=1,'FACT_EST_CEN','SIN_DATA')))!B:B,Reliquidacion!B44,IF(VLOOKUP(B9,MAPA_DATA!D:G,2,0)=1,'FACT_EMITIDA',IF(VLOOKUP(B44,MAPA_DATA!D:G,3,0)=1,'FACT_EST_EFACT',(IF(VLOOKUP(B44,MAPA_DATA!D:G,4,0)=1,'FACT_EST_CEN','SIN_DATA')))!H:H) | G44: =CONCATENATE("SUMIF(",IF(C44="FACT_EMITIDA","SIGGE_P",C44),"!B:B,Reliquidacion!B",A44,",",IF(C44="FACT_EMITIDA","SIGGE_P",C44),"!F:F)") -> SUMIF(IF(VLOOKUP(B9,MAPA_DATA!D:G,2,0)=1,'FACT_EMITIDA',IF(VLOOKUP(B44,MAPA_DATA!D:G,3,0)=1,'FACT_EST_EFACT',(IF(VLOOKUP(B44,MAPA_DATA!D:G,4,0)=1,'FACT_EST_CEN','SIN_DATA')))!B:B,Reliquidacion!B44,IF(VLOOKUP(B9,MAPA_DATA!D:G,2,0)=1,'FACT_EMITIDA',IF(VLOOKUP(B44,MAPA_DATA!D:G,3,0)=1,'FACT_EST_EFACT',(IF(VLOOKUP(B44,MAPA_DATA!D:G,4,0)=1,'FACT_EST_CEN','SIN_DATA')))!F:F) | H44: =CONCATENATE("(I",A44,"/G",A44,")") -> (I44/G44) | I44: =CONCATENATE("SUMIF(",IF(C44="FACT_EMITIDA","SIGGE_P",C44),"!B:B,Reliquidacion!B",A44,",",IF(C44="FACT_EMITIDA","SIGGE_P",C44),"!H:H)") -> SUMIF(IF(VLOOKUP(B9,MAPA_DATA!D:G,2,0)=1,'FACT_EMITIDA',IF(VLOOKUP(B44,MAPA_DATA!D:G,3,0)=1,'FACT_EST_EFACT',(IF(VLOOKUP(B44,MAPA_DATA!D:G,4,0)=1,'FACT_EST_CEN','SIN_DATA')))!B:B,Reliquidacion!B44,IF(VLOOKUP(B9,MAPA_DATA!D:G,2,0)=1,'FACT_EMITIDA',IF(VLOOKUP(B44,MAPA_DATA!D:G,3,0)=1,'FACT_EST_EFACT',(IF(VLOOKUP(B44,MAPA_DATA!D:G,4,0)=1,'FACT_EST_CEN','SIN_DATA')))!H:H) | J44: =CONCATENATE("(F",A44,"+I",A44,")") -> (F44+I44) | L44: =IF(VLOOKUP(B44,MAPA_DATA!D:I,5,0)=1,"EFACT_CNE",IF(VLOOKUP(B44,MAPA_DATA!D:I,6,0)=1,"EFACT_EST_CNE","SIN_DATA")) -> SIN_DATA | M44: =CONCATENATE("SUMIF(",L44,"!B:B;Reliquidacion!B",A44,";",L44,"!S:S)") -> SUMIF(SIN_DATA!B:B;Reliquidacion!B44;SIN_DATA!S:S) | N44: =CONCATENATE("(O",A44,"/M",A44,")") -> (O44/M44) | O44: =CONCATENATE("SUMIF(",L44,"!B:B;Reliquidacion!B",A44,";",L44,"!W:W)") -> SUMIF(SIN_DATA!B:B;Reliquidacion!B44;SIN_DATA!W:W) | P44: =CONCATENATE("SUMIF(",L44,"!B:B;Reliquidacion!B",A44,";",L44,"!X:X)") -> SUMIF(SIN_DATA!B:B;Reliquidacion!B44;SIN_DATA!X:X) | Q44: =CONCATENATE("(R",A44,"/P",A44,")") -> (R44/P44) | R44: =CONCATENATE("SUMIF(",L44,"!B:B;Reliquidacion!B",A44,";",L44,"!AB:AB)") -> SUMIF(SIN_DATA!B:B;Reliquidacion!B44;SIN_DATA!AB:AB) | S44: =CONCATENATE("(O",A44,"+R",A44,")") -> (O44+R44) | U44: 43435 | V44: =CONCATENATE("=(S",A44,"-J",A44,")") -> =(S44-J44) | W44: 6T/08-05-2020 | X44: =VLOOKUP(W44,[1]INTERESES!A:B,2,0) -> 0 | Y44: =VLOOKUP(W44,#REF!,6,0) -> #REF! | Z44: 43490 | AA44: =AA43 -> 44377 | AB44: =AA44-Z44 -> 887 | AC44: =+(1+Y44)^(AB44/360)-1 -> #REF! | AD44: =AC44*V44 -> #REF! | AE44: =+V44+AD44 -> #VALUE!
A45: =A44+1 -> 45 | B45: 43466 | C45: =CONCATENATE("IF(VLOOKUP(B9,MAPA_DATA!D:G,2,0)=1,'FACT_EMITIDA',IF(VLOOKUP(B",A45,",MAPA_DATA!D:G,3,0)=1,'FACT_EST_EFACT',(IF(VLOOKUP(B",A45,",MAPA_DATA!D:G,4,0)=1,'FACT_EST_CEN','SIN_DATA')))") -> IF(VLOOKUP(B9,MAPA_DATA!D:G,2,0)=1,'FACT_EMITIDA',IF(VLOOKUP(B45,MAPA_DATA!D:G,3,0)=1,'FACT_EST_EFACT',(IF(VLOOKUP(B45,MAPA_DATA!D:G,4,0)=1,'FACT_EST_CEN','SIN_DATA'))) | D45: =CONCATENATE("SUMIF(",IF(C45="FACT_EMITIDA","SIGGE_E",C45),"!B:B,Reliquidacion!B",A45,",",IF(C45="FACT_EMITIDA","SIGGE_E",C45),"!F:F)") -> SUMIF(IF(VLOOKUP(B9,MAPA_DATA!D:G,2,0)=1,'FACT_EMITIDA',IF(VLOOKUP(B45,MAPA_DATA!D:G,3,0)=1,'FACT_EST_EFACT',(IF(VLOOKUP(B45,MAPA_DATA!D:G,4,0)=1,'FACT_EST_CEN','SIN_DATA')))!B:B,Reliquidacion!B45,IF(VLOOKUP(B9,MAPA_DATA!D:G,2,0)=1,'FACT_EMITIDA',IF(VLOOKUP(B45,MAPA_DATA!D:G,3,0)=1,'FACT_EST_EFACT',(IF(VLOOKUP(B45,MAPA_DATA!D:G,4,0)=1,'FACT_EST_CEN','SIN_DATA')))!F:F) | E45: =CONCATENATE("(F",A45,"/D",A45,")") -> (F45/D45) | F45: =CONCATENATE("SUMIF(",IF(C45="FACT_EMITIDA","SIGGE_E",C45),"!B:B,Reliquidacion!B",A45,",",IF(C45="FACT_EMITIDA","SIGGE_E",C45),"!H:H)") -> SUMIF(IF(VLOOKUP(B9,MAPA_DATA!D:G,2,0)=1,'FACT_EMITIDA',IF(VLOOKUP(B45,MAPA_DATA!D:G,3,0)=1,'FACT_EST_EFACT',(IF(VLOOKUP(B45,MAPA_DATA!D:G,4,0)=1,'FACT_EST_CEN','SIN_DATA')))!B:B,Reliquidacion!B45,IF(VLOOKUP(B9,MAPA_DATA!D:G,2,0)=1,'FACT_EMITIDA',IF(VLOOKUP(B45,MAPA_DATA!D:G,3,0)=1,'FACT_EST_EFACT',(IF(VLOOKUP(B45,MAPA_DATA!D:G,4,0)=1,'FACT_EST_CEN','SIN_DATA')))!H:H) | G45: =CONCATENATE("SUMIF(",IF(C45="FACT_EMITIDA","SIGGE_P",C45),"!B:B,Reliquidacion!B",A45,",",IF(C45="FACT_EMITIDA","SIGGE_P",C45),"!F:F)") -> SUMIF(IF(VLOOKUP(B9,MAPA_DATA!D:G,2,0)=1,'FACT_EMITIDA',IF(VLOOKUP(B45,MAPA_DATA!D:G,3,0)=1,'FACT_EST_EFACT',(IF(VLOOKUP(B45,MAPA_DATA!D:G,4,0)=1,'FACT_EST_CEN','SIN_DATA')))!B:B,Reliquidacion!B45,IF(VLOOKUP(B9,MAPA_DATA!D:G,2,0)=1,'FACT_EMITIDA',IF(VLOOKUP(B45,MAPA_DATA!D:G,3,0)=1,'FACT_EST_EFACT',(IF(VLOOKUP(B45,MAPA_DATA!D:G,4,0)=1,'FACT_EST_CEN','SIN_DATA')))!F:F) | H45: =CONCATENATE("(I",A45,"/G",A45,")") -> (I45/G45) | I45: =CONCATENATE("SUMIF(",IF(C45="FACT_EMITIDA","SIGGE_P",C45),"!B:B,Reliquidacion!B",A45,",",IF(C45="FACT_EMITIDA","SIGGE_P",C45),"!H:H)") -> SUMIF(IF(VLOOKUP(B9,MAPA_DATA!D:G,2,0)=1,'FACT_EMITIDA',IF(VLOOKUP(B45,MAPA_DATA!D:G,3,0)=1,'FACT_EST_EFACT',(IF(VLOOKUP(B45,MAPA_DATA!D:G,4,0)=1,'FACT_EST_CEN','SIN_DATA')))!B:B,Reliquidacion!B45,IF(VLOOKUP(B9,MAPA_DATA!D:G,2,0)=1,'FACT_EMITIDA',IF(VLOOKUP(B45,MAPA_DATA!D:G,3,0)=1,'FACT_EST_EFACT',(IF(VLOOKUP(B45,MAPA_DATA!D:G,4,0)=1,'FACT_EST_CEN','SIN_DATA')))!H:H) | J45: =CONCATENATE("(F",A45,"+I",A45,")") -> (F45+I45) | L45: =IF(VLOOKUP(B45,MAPA_DATA!D:I,5,0)=1,"EFACT_CNE",IF(VLOOKUP(B45,MAPA_DATA!D:I,6,0)=1,"EFACT_EST_CNE","SIN_DATA")) -> SIN_DATA | M45: =CONCATENATE("SUMIF(",L45,"!B:B;Reliquidacion!B",A45,";",L45,"!S:S)") -> SUMIF(SIN_DATA!B:B;Reliquidacion!B45;SIN_DATA!S:S) | N45: =CONCATENATE("(O",A45,"/M",A45,")") -> (O45/M45) | O45: =CONCATENATE("SUMIF(",L45,"!B:B;Reliquidacion!B",A45,";",L45,"!W:W)") -> SUMIF(SIN_DATA!B:B;Reliquidacion!B45;SIN_DATA!W:W) | P45: =CONCATENATE("SUMIF(",L45,"!B:B;Reliquidacion!B",A45,";",L45,"!X:X)") -> SUMIF(SIN_DATA!B:B;Reliquidacion!B45;SIN_DATA!X:X) | Q45: =CONCATENATE("(R",A45,"/P",A45,")") -> (R45/P45) | R45: =CONCATENATE("SUMIF(",L45,"!B:B;Reliquidacion!B",A45,";",L45,"!AB:AB)") -> SUMIF(SIN_DATA!B:B;Reliquidacion!B45;SIN_DATA!AB:AB) | S45: =CONCATENATE("(O",A45,"+R",A45,")") -> (O45+R45) | U45: 43466 | V45: =CONCATENATE("=(S",A45,"-J",A45,")") -> =(S45-J45) | W45: 6T/08-05-2020 | X45: =VLOOKUP(W45,[1]INTERESES!A:B,2,0) -> 0 | Y45: =VLOOKUP(W45,#REF!,6,0) -> #REF! | Z45: 43521 | AA45: =AA44 -> 44377 | AB45: =AA45-Z45 -> 856 | AC45: =+(1+Y45)^(AB45/360)-1 -> #REF! | AD45: =AC45*V45 -> #REF! | AE45: =+V45+AD45 -> #VALUE!
... A61: =A60+1 -> 61 | B61: 43952 | C61: =CONCATENATE("IF(VLOOKUP(B9,MAPA_DATA!D:G,2,0)=1,'FACT_EMITIDA',IF(VLOOKUP(B",A61,",MAPA_DATA!D:G,3,0)=1,'FACT_EST_EFACT',(IF(VLOOKUP(B",A61,",MAPA_DATA!D:G,4,0)=1,'FACT_EST_CEN','SIN_DATA')))") -> IF(VLOOKUP(B9,MAPA_DATA!D:G,2,0)=1,'FACT_EMITIDA',IF(VLOOKUP(B61,MAPA_DATA!D:G,3,0)=1,'FACT_EST_EFACT',(IF(VLOOKUP(B61,MAPA_DATA!D:G,4,0)=1,'FACT_EST_CEN','SIN_DATA'))) | D61: =CONCATENATE("SUMIF(",IF(C61="FACT_EMITIDA","SIGGE_E",C61),"!B:B,Reliquidacion!B",A61,",",IF(C61="FACT_EMITIDA","SIGGE_E",C61),"!F:F)") -> SUMIF(IF(VLOOKUP(B9,MAPA_DATA!D:G,2,0)=1,'FACT_EMITIDA',IF(VLOOKUP(B61,MAPA_DATA!D:G,3,0)=1,'FACT_EST_EFACT',(IF(VLOOKUP(B61,MAPA_DATA!D:G,4,0)=1,'FACT_EST_CEN','SIN_DATA')))!B:B,Reliquidacion!B61,IF(VLOOKUP(B9,MAPA_DATA!D:G,2,0)=1,'FACT_EMITIDA',IF(VLOOKUP(B61,MAPA_DATA!D:G,3,0)=1,'FACT_EST_EFACT',(IF(VLOOKUP(B61,MAPA_DATA!D:G,4,0)=1,'FACT_EST_CEN','SIN_DATA')))!F:F) | E61: =CONCATENATE("(F",A61,"/D",A61,")") -> (F61/D61) | F61: =CONCATENATE("SUMIF(",IF(C61="FACT_EMITIDA","SIGGE_E",C61),"!B:B,Reliquidacion!B",A61,",",IF(C61="FACT_EMITIDA","SIGGE_E",C61),"!H:H)") -> SUMIF(IF(VLOOKUP(B9,MAPA_DATA!D:G,2,0)=1,'FACT_EMITIDA',IF(VLOOKUP(B61,MAPA_DATA!D:G,3,0)=1,'FACT_EST_EFACT',(IF(VLOOKUP(B61,MAPA_DATA!D:G,4,0)=1,'FACT_EST_CEN','SIN_DATA')))!B:B,Reliquidacion!B61,IF(VLOOKUP(B9,MAPA_DATA!D:G,2,0)=1,'FACT_EMITIDA',IF(VLOOKUP(B61,MAPA_DATA!D:G,3,0)=1,'FACT_EST_EFACT',(IF(VLOOKUP(B61,MAPA_DATA!D:G,4,0)=1,'FACT_EST_CEN','SIN_DATA')))!H:H) | G61: =CONCATENATE("SUMIF(",IF(C61="FACT_EMITIDA","SIGGE_P",C61),"!B:B,Reliquidacion!B",A61,",",IF(C61="FACT_EMITIDA","SIGGE_P",C61),"!F:F)") -> SUMIF(IF(VLOOKUP(B9,MAPA_DATA!D:G,2,0)=1,'FACT_EMITIDA',IF(VLOOKUP(B61,MAPA_DATA!D:G,3,0)=1,'FACT_EST_EFACT',(IF(VLOOKUP(B61,MAPA_DATA!D:G,4,0)=1,'FACT_EST_CEN','SIN_DATA')))!B:B,Reliquidacion!B61,IF(VLOOKUP(B9,MAPA_DATA!D:G,2,0)=1,'FACT_EMITIDA',IF(VLOOKUP(B61,MAPA_DATA!D:G,3,0)=1,'FACT_EST_EFACT',(IF(VLOOKUP(B61,MAPA_DATA!D:G,4,0)=1,'FACT_EST_CEN','SIN_DATA')))!F:F) | H61: =CONCATENATE("(I",A61,"/G",A61,")") -> (I61/G61) | I61: =CONCATENATE("SUMIF(",IF(C61="FACT_EMITIDA","SIGGE_P",C61),"!B:B,Reliquidacion!B",A61,",",IF(C61="FACT_EMITIDA","SIGGE_P",C61),"!H:H)") -> SUMIF(IF(VLOOKUP(B9,MAPA_DATA!D:G,2,0)=1,'FACT_EMITIDA',IF(VLOOKUP(B61,MAPA_DATA!D:G,3,0)=1,'FACT_EST_EFACT',(IF(VLOOKUP(B61,MAPA_DATA!D:G,4,0)=1,'FACT_EST_CEN','SIN_DATA')))!B:B,Reliquidacion!B61,IF(VLOOKUP(B9,MAPA_DATA!D:G,2,0)=1,'FACT_EMITIDA',IF(VLOOKUP(B61,MAPA_DATA!D:G,3,0)=1,'FACT_EST_EFACT',(IF(VLOOKUP(B61,MAPA_DATA!D:G,4,0)=1,'FACT_EST_CEN','SIN_DATA')))!H:H) | J61: =CONCATENATE("(F",A61,"+I",A61,")") -> (F61+I61) | L61: =IF(VLOOKUP(B61,MAPA_DATA!D:I,5,0)=1,"EFACT_CNE",IF(VLOOKUP(B61,MAPA_DATA!D:I,6,0)=1,"EFACT_EST_CNE","SIN_DATA")) -> SIN_DATA | M61: =CONCATENATE("SUMIF(",L61,"!B:B;Reliquidacion!B",A61,";",L61,"!S:S)") -> SUMIF(SIN_DATA!B:B;Reliquidacion!B61;SIN_DATA!S:S) | N61: =CONCATENATE("(O",A61,"/M",A61,")") -> (O61/M61) | O61: =CONCATENATE("SUMIF(",L61,"!B:B;Reliquidacion!B",A61,";",L61,"!W:W)") -> SUMIF(SIN_DATA!B:B;Reliquidacion!B61;SIN_DATA!W:W) | P61: =CONCATENATE("SUMIF(",L61,"!B:B;Reliquidacion!B",A61,";",L61,"!X:X)") -> SUMIF(SIN_DATA!B:B;Reliquidacion!B61;SIN_DATA!X:X) | Q61: =CONCATENATE("(R",A61,"/P",A61,")") -> (R61/P61) | R61: =CONCATENATE("SUMIF(",L61,"!B:B;Reliquidacion!B",A61,";",L61,"!AB:AB)") -> SUMIF(SIN_DATA!B:B;Reliquidacion!B61;SIN_DATA!AB:AB) | S61: =CONCATENATE("(O",A61,"+R",A61,")") -> (O61+R61) | U61: 43952 | V61: =CONCATENATE("=(S",A61,"-J",A61,")") -> =(S61-J61) | W61: 16T/02-11-2020 | X61: =VLOOKUP(W61,[1]INTERESES!A:B,2,0) -> 0 | Y61: =VLOOKUP(W61,#REF!,6,0) -> #REF! | Z61: 44007 | AA61: =AA60 -> 44377 | AB61: =AA61-Z61 -> 370 | AC61: =+(1+Y61)^(AB61/360)-1 -> #REF! | AD61: =AC61*V61 -> #REF! | AE61: =+V61+AD61 -> #VALUE!
A62: =A61+1 -> 62 | B62: 43983 | C62: =CONCATENATE("IF(VLOOKUP(B9,MAPA_DATA!D:G,2,0)=1,'FACT_EMITIDA',IF(VLOOKUP(B",A62,",MAPA_DATA!D:G,3,0)=1,'FACT_EST_EFACT',(IF(VLOOKUP(B",A62,",MAPA_DATA!D:G,4,0)=1,'FACT_EST_CEN','SIN_DATA')))") -> IF(VLOOKUP(B9,MAPA_DATA!D:G,2,0)=1,'FACT_EMITIDA',IF(VLOOKUP(B62,MAPA_DATA!D:G,3,0)=1,'FACT_EST_EFACT',(IF(VLOOKUP(B62,MAPA_DATA!D:G,4,0)=1,'FACT_EST_CEN','SIN_DATA'))) | D62: =CONCATENATE("SUMIF(",IF(C62="FACT_EMITIDA","SIGGE_E",C62),"!B:B,Reliquidacion!B",A62,",",IF(C62="FACT_EMITIDA","SIGGE_E",C62),"!F:F)") -> SUMIF(IF(VLOOKUP(B9,MAPA_DATA!D:G,2,0)=1,'FACT_EMITIDA',IF(VLOOKUP(B62,MAPA_DATA!D:G,3,0)=1,'FACT_EST_EFACT',(IF(VLOOKUP(B62,MAPA_DATA!D:G,4,0)=1,'FACT_EST_CEN','SIN_DATA')))!B:B,Reliquidacion!B62,IF(VLOOKUP(B9,MAPA_DATA!D:G,2,0)=1,'FACT_EMITIDA',IF(VLOOKUP(B62,MAPA_DATA!D:G,3,0)=1,'FACT_EST_EFACT',(IF(VLOOKUP(B62,MAPA_DATA!D:G,4,0)=1,'FACT_EST_CEN','SIN_DATA')))!F:F) | E62: =CONCATENATE("(F",A62,"/D",A62,")") -> (F62/D62) | F62: =CONCATENATE("SUMIF(",IF(C62="FACT_EMITIDA","SIGGE_E",C62),"!B:B,Reliquidacion!B",A62,",",IF(C62="FACT_EMITIDA","SIGGE_E",C62),"!H:H)") -> SUMIF(IF(VLOOKUP(B9,MAPA_DATA!D:G,2,0)=1,'FACT_EMITIDA',IF(VLOOKUP(B62,MAPA_DATA!D:G,3,0)=1,'FACT_EST_EFACT',(IF(VLOOKUP(B62,MAPA_DATA!D:G,4,0)=1,'FACT_EST_CEN','SIN_DATA')))!B:B,Reliquidacion!B62,IF(VLOOKUP(B9,MAPA_DATA!D:G,2,0)=1,'FACT_EMITIDA',IF(VLOOKUP(B62,MAPA_DATA!D:G,3,0)=1,'FACT_EST_EFACT',(IF(VLOOKUP(B62,MAPA_DATA!D:G,4,0)=1,'FACT_EST_CEN','SIN_DATA')))!H:H) | G62: =CONCATENATE("SUMIF(",IF(C62="FACT_EMITIDA","SIGGE_P",C62),"!B:B,Reliquidacion!B",A62,",",IF(C62="FACT_EMITIDA","SIGGE_P",C62),"!F:F)") -> SUMIF(IF(VLOOKUP(B9,MAPA_DATA!D:G,2,0)=1,'FACT_EMITIDA',IF(VLOOKUP(B62,MAPA_DATA!D:G,3,0)=1,'FACT_EST_EFACT',(IF(VLOOKUP(B62,MAPA_DATA!D:G,4,0)=1,'FACT_EST_CEN','SIN_DATA')))!B:B,Reliquidacion!B62,IF(VLOOKUP(B9,MAPA_DATA!D:G,2,0)=1,'FACT_EMITIDA',IF(VLOOKUP(B62,MAPA_DATA!D:G,3,0)=1,'FACT_EST_EFACT',(IF(VLOOKUP(B62,MAPA_DATA!D:G,4,0)=1,'FACT_EST_CEN','SIN_DATA')))!F:F) | H62: =CONCATENATE("(I",A62,"/G",A62,")") -> (I62/G62) | I62: =CONCATENATE("SUMIF(",IF(C62="FACT_EMITIDA","SIGGE_P",C62),"!B:B,Reliquidacion!B",A62,",",IF(C62="FACT_EMITIDA","SIGGE_P",C62),"!H:H)") -> SUMIF(IF(VLOOKUP(B9,MAPA_DATA!D:G,2,0)=1,'FACT_EMITIDA',IF(VLOOKUP(B62,MAPA_DATA!D:G,3,0)=1,'FACT_EST_EFACT',(IF(VLOOKUP(B62,MAPA_DATA!D:G,4,0)=1,'FACT_EST_CEN','SIN_DATA')))!B:B,Reliquidacion!B62,IF(VLOOKUP(B9,MAPA_DATA!D:G,2,0)=1,'FACT_EMITIDA',IF(VLOOKUP(B62,MAPA_DATA!D:G,3,0)=1,'FACT_EST_EFACT',(IF(VLOOKUP(B62,MAPA_DATA!D:G,4,0)=1,'FACT_EST_CEN','SIN_DATA')))!H:H) | J62: =CONCATENATE("(F",A62,"+I",A62,")") -> (F62+I62) | L62: =IF(VLOOKUP(B62,MAPA_DATA!D:I,5,0)=1,"EFACT_CNE",IF(VLOOKUP(B62,MAPA_DATA!D:I,6,0)=1,"EFACT_EST_CNE","SIN_DATA")) -> SIN_DATA | M62: =CONCATENATE("SUMIF(",L62,"!B:B;Reliquidacion!B",A62,";",L62,"!S:S)") -> SUMIF(SIN_DATA!B:B;Reliquidacion!B62;SIN_DATA!S:S) | N62: =CONCATENATE("(O",A62,"/M",A62,")") -> (O62/M62) | O62: =CONCATENATE("SUMIF(",L62,"!B:B;Reliquidacion!B",A62,";",L62,"!W:W)") -> SUMIF(SIN_DATA!B:B;Reliquidacion!B62;SIN_DATA!W:W) | P62: =CONCATENATE("SUMIF(",L62,"!B:B;Reliquidacion!B",A62,";",L62,"!X:X)") -> SUMIF(SIN_DATA!B:B;Reliquidacion!B62;SIN_DATA!X:X) | Q62: =CONCATENATE("(R",A62,"/P",A62,")") -> (R62/P62) | R62: =CONCATENATE("SUMIF(",L62,"!B:B;Reliquidacion!B",A62,";",L62,"!AB:AB)") -> SUMIF(SIN_DATA!B:B;Reliquidacion!B62;SIN_DATA!AB:AB) | S62: =CONCATENATE("(O",A62,"+R",A62,")") -> (O62+R62) | U62: 43983 | V62: =CONCATENATE("=(S",A62,"-J",A62,")") -> =(S62-J62) | W62: 16T/02-11-2020 | X62: =VLOOKUP(W62,[1]INTERESES!A:B,2,0) -> 0 | Y62: =VLOOKUP(W62,#REF!,6,0) -> #REF! | Z62: 44037 | AA62: =AA60 -> 44377 | AB62: =AA62-Z62 -> 340 | AC62: =+(1+Y62)^(AB62/360)-1 -> #REF! | AD62: =AC62*V62 -> #REF! | AE62: =+V62+AD62 -> #VALUE!
A63: =A62+1 -> 63 | B63: 44013 | C63: =CONCATENATE("IF(VLOOKUP(B9,MAPA_DATA!D:G,2,0)=1,'FACT_EMITIDA',IF(VLOOKUP(B",A63,",MAPA_DATA!D:G,3,0)=1,'FACT_EST_EFACT',(IF(VLOOKUP(B",A63,",MAPA_DATA!D:G,4,0)=1,'FACT_EST_CEN','SIN_DATA')))") -> IF(VLOOKUP(B9,MAPA_DATA!D:G,2,0)=1,'FACT_EMITIDA',IF(VLOOKUP(B63,MAPA_DATA!D:G,3,0)=1,'FACT_EST_EFACT',(IF(VLOOKUP(B63,MAPA_DATA!D:G,4,0)=1,'FACT_EST_CEN','SIN_DATA'))) | D63: =CONCATENATE("SUMIF(",IF(C63="FACT_EMITIDA","SIGGE_E",C63),"!B:B,Reliquidacion!B",A63,",",IF(C63="FACT_EMITIDA","SIGGE_E",C63),"!F:F)") -> SUMIF(IF(VLOOKUP(B9,MAPA_DATA!D:G,2,0)=1,'FACT_EMITIDA',IF(VLOOKUP(B63,MAPA_DATA!D:G,3,0)=1,'FACT_EST_EFACT',(IF(VLOOKUP(B63,MAPA_DATA!D:G,4,0)=1,'FACT_EST_CEN','SIN_DATA')))!B:B,Reliquidacion!B63,IF(VLOOKUP(B9,MAPA_DATA!D:G,2,0)=1,'FACT_EMITIDA',IF(VLOOKUP(B63,MAPA_DATA!D:G,3,0)=1,'FACT_EST_EFACT',(IF(VLOOKUP(B63,MAPA_DATA!D:G,4,0)=1,'FACT_EST_CEN','SIN_DATA')))!F:F) | E63: =CONCATENATE("(F",A63,"/D",A63,")") -> (F63/D63) | F63: =CONCATENATE("SUMIF(",IF(C63="FACT_EMITIDA","SIGGE_E",C63),"!B:B,Reliquidacion!B",A63,",",IF(C63="FACT_EMITIDA","SIGGE_E",C63),"!H:H)") -> SUMIF(IF(VLOOKUP(B9,MAPA_DATA!D:G,2,0)=1,'FACT_EMITIDA',IF(VLOOKUP(B63,MAPA_DATA!D:G,3,0)=1,'FACT_EST_EFACT',(IF(VLOOKUP(B63,MAPA_DATA!D:G,4,0)=1,'FACT_EST_CEN','SIN_DATA')))!B:B,Reliquidacion!B63,IF(VLOOKUP(B9,MAPA_DATA!D:G,2,0)=1,'FACT_EMITIDA',IF(VLOOKUP(B63,MAPA_DATA!D:G,3,0)=1,'FACT_EST_EFACT',(IF(VLOOKUP(B63,MAPA_DATA!D:G,4,0)=1,'FACT_EST_CEN','SIN_DATA')))!H:H) | G63: =CONCATENATE("SUMIF(",IF(C63="FACT_EMITIDA","SIGGE_P",C63),"!B:B,Reliquidacion!B",A63,",",IF(C63="FACT_EMITIDA","SIGGE_P",C63),"!F:F)") -> SUMIF(IF(VLOOKUP(B9,MAPA_DATA!D:G,2,0)=1,'FACT_EMITIDA',IF(VLOOKUP(B63,MAPA_DATA!D:G,3,0)=1,'FACT_EST_EFACT',(IF(VLOOKUP(B63,MAPA_DATA!D:G,4,0)=1,'FACT_EST_CEN','SIN_DATA')))!B:B,Reliquidacion!B63,IF(VLOOKUP(B9,MAPA_DATA!D:G,2,0)=1,'FACT_EMITIDA',IF(VLOOKUP(B63,MAPA_DATA!D:G,3,0)=1,'FACT_EST_EFACT',(IF(VLOOKUP(B63,MAPA_DATA!D:G,4,0)=1,'FACT_EST_CEN','SIN_DATA')))!F:F) | H63: =CONCATENATE("(I",A63,"/G",A63,")") -> (I63/G63) | I63: =CONCATENATE("SUMIF(",IF(C63="FACT_EMITIDA","SIGGE_P",C63),"!B:B,Reliquidacion!B",A63,",",IF(C63="FACT_EMITIDA","SIGGE_P",C63),"!H:H)") -> SUMIF(IF(VLOOKUP(B9,MAPA_DATA!D:G,2,0)=1,'FACT_EMITIDA',IF(VLOOKUP(B63,MAPA_DATA!D:G,3,0)=1,'FACT_EST_EFACT',(IF(VLOOKUP(B63,MAPA_DATA!D:G,4,0)=1,'FACT_EST_CEN','SIN_DATA')))!B:B,Reliquidacion!B63,IF(VLOOKUP(B9,MAPA_DATA!D:G,2,0)=1,'FACT_EMITIDA',IF(VLOOKUP(B63,MAPA_DATA!D:G,3,0)=1,'FACT_EST_EFACT',(IF(VLOOKUP(B63,MAPA_DATA!D:G,4,0)=1,'FACT_EST_CEN','SIN_DATA')))!H:H) | J63: =CONCATENATE("(F",A63,"+I",A63,")") -> (F63+I63) | L63: =IF(VLOOKUP(B63,MAPA_DATA!D:I,5,0)=1,"EFACT_CNE",IF(VLOOKUP(B63,MAPA_DATA!D:I,6,0)=1,"EFACT_EST_CNE","SIN_DATA")) -> SIN_DATA | M63: =CONCATENATE("SUMIF(",L63,"!B:B;Reliquidacion!B",A63,";",L63,"!S:S)") -> SUMIF(SIN_DATA!B:B;Reliquidacion!B63;SIN_DATA!S:S) | N63: =CONCATENATE("(O",A63,"/M",A63,")") -> (O63/M63) | O63: =CONCATENATE("SUMIF(",L63,"!B:B;Reliquidacion!B",A63,";",L63,"!W:W)") -> SUMIF(SIN_DATA!B:B;Reliquidacion!B63;SIN_DATA!W:W) | P63: =CONCATENATE("SUMIF(",L63,"!B:B;Reliquidacion!B",A63,";",L63,"!X:X)") -> SUMIF(SIN_DATA!B:B;Reliquidacion!B63;SIN_DATA!X:X) | Q63: =CONCATENATE("(R",A63,"/P",A63,")") -> (R63/P63) | R63: =CONCATENATE("SUMIF(",L63,"!B:B;Reliquidacion!B",A63,";",L63,"!AB:AB)") -> SUMIF(SIN_DATA!B:B;Reliquidacion!B63;SIN_DATA!AB:AB) | S63: =CONCATENATE("(O",A63,"+R",A63,")") -> (O63+R63) | U63: 44013 | V63: =CONCATENATE("=(S",A63,"-J",A63,")") -> =(S63-J63) | W63: 19T/30-12-2020 | X63: =VLOOKUP(W63,[1]INTERESES!A:B,2,0) -> 0 | Y63: =VLOOKUP(W63,#REF!,6,0) -> #REF! | Z63: 44068 | AA63: =AA59 -> 44377 | AB63: =AA63-Z63 -> 309 | AC63: =+(1+Y63)^(AB63/360)-1 -> #REF! | AD63: =AC63*V63 -> #REF! | AE63: =+V63+AD63 -> #VALUE!
A64: =A63+1 -> 64 | B64: 44044 | C64: =CONCATENATE("IF(VLOOKUP(B9,MAPA_DATA!D:G,2,0)=1,'FACT_EMITIDA',IF(VLOOKUP(B",A64,",MAPA_DATA!D:G,3,0)=1,'FACT_EST_EFACT',(IF(VLOOKUP(B",A64,",MAPA_DATA!D:G,4,0)=1,'FACT_EST_CEN','SIN_DATA')))") -> IF(VLOOKUP(B9,MAPA_DATA!D:G,2,0)=1,'FACT_EMITIDA',IF(VLOOKUP(B64,MAPA_DATA!D:G,3,0)=1,'FACT_EST_EFACT',(IF(VLOOKUP(B64,MAPA_DATA!D:G,4,0)=1,'FACT_EST_CEN','SIN_DATA'))) | D64: =CONCATENATE("SUMIF(",IF(C64="FACT_EMITIDA","SIGGE_E",C64),"!B:B,Reliquidacion!B",A64,",",IF(C64="FACT_EMITIDA","SIGGE_E",C64),"!F:F)") -> SUMIF(IF(VLOOKUP(B9,MAPA_DATA!D:G,2,0)=1,'FACT_EMITIDA',IF(VLOOKUP(B64,MAPA_DATA!D:G,3,0)=1,'FACT_EST_EFACT',(IF(VLOOKUP(B64,MAPA_DATA!D:G,4,0)=1,'FACT_EST_CEN','SIN_DATA')))!B:B,Reliquidacion!B64,IF(VLOOKUP(B9,MAPA_DATA!D:G,2,0)=1,'FACT_EMITIDA',IF(VLOOKUP(B64,MAPA_DATA!D:G,3,0)=1,'FACT_EST_EFACT',(IF(VLOOKUP(B64,MAPA_DATA!D:G,4,0)=1,'FACT_EST_CEN','SIN_DATA')))!F:F) | E64: =CONCATENATE("(F",A64,"/D",A64,")") -> (F64/D64) | F64: =CONCATENATE("SUMIF(",IF(C64="FACT_EMITIDA","SIGGE_E",C64),"!B:B,Reliquidacion!B",A64,",",IF(C64="FACT_EMITIDA","SIGGE_E",C64),"!H:H)") -> SUMIF(IF(VLOOKUP(B9,MAPA_DATA!D:G,2,0)=1,'FACT_EMITIDA',IF(VLOOKUP(B64,MAPA_DATA!D:G,3,0)=1,'FACT_EST_EFACT',(IF(VLOOKUP(B64,MAPA_DATA!D:G,4,0)=1,'FACT_EST_CEN','SIN_DATA')))!B:B,Reliquidacion!B64,IF(VLOOKUP(B9,MAPA_DATA!D:G,2,0)=1,'FACT_EMITIDA',IF(VLOOKUP(B64,MAPA_DATA!D:G,3,0)=1,'FACT_EST_EFACT',(IF(VLOOKUP(B64,MAPA_DATA!D:G,4,0)=1,'FACT_EST_CEN','SIN_DATA')))!H:H) | G64: =CONCATENATE("SUMIF(",IF(C64="FACT_EMITIDA","SIGGE_P",C64),"!B:B,Reliquidacion!B",A64,",",IF(C64="FACT_EMITIDA","SIGGE_P",C64),"!F:F)") -> SUMIF(IF(VLOOKUP(B9,MAPA_DATA!D:G,2,0)=1,'FACT_EMITIDA',IF(VLOOKUP(B64,MAPA_DATA!D:G,3,0)=1,'FACT_EST_EFACT',(IF(VLOOKUP(B64,MAPA_DATA!D:G,4,0)=1,'FACT_EST_CEN','SIN_DATA')))!B:B,Reliquidacion!B64,IF(VLOOKUP(B9,MAPA_DATA!D:G,2,0)=1,'FACT_EMITIDA',IF(VLOOKUP(B64,MAPA_DATA!D:G,3,0)=1,'FACT_EST_EFACT',(IF(VLOOKUP(B64,MAPA_DATA!D:G,4,0)=1,'FACT_EST_CEN','SIN_DATA')))!F:F) | H64: =CONCATENATE("(I",A64,"/G",A64,")") -> (I64/G64) | I64: =CONCATENATE("SUMIF(",IF(C64="FACT_EMITIDA","SIGGE_P",C64),"!B:B,Reliquidacion!B",A64,",",IF(C64="FACT_EMITIDA","SIGGE_P",C64),"!H:H)") -> SUMIF(IF(VLOOKUP(B9,MAPA_DATA!D:G,2,0)=1,'FACT_EMITIDA',IF(VLOOKUP(B64,MAPA_DATA!D:G,3,0)=1,'FACT_EST_EFACT',(IF(VLOOKUP(B64,MAPA_DATA!D:G,4,0)=1,'FACT_EST_CEN','SIN_DATA')))!B:B,Reliquidacion!B64,IF(VLOOKUP(B9,MAPA_DATA!D:G,2,0)=1,'FACT_EMITIDA',IF(VLOOKUP(B64,MAPA_DATA!D:G,3,0)=1,'FACT_EST_EFACT',(IF(VLOOKUP(B64,MAPA_DATA!D:G,4,0)=1,'FACT_EST_CEN','SIN_DATA')))!H:H) | J64: =CONCATENATE("(F",A64,"+I",A64,")") -> (F64+I64) | L64: =IF(VLOOKUP(B64,MAPA_DATA!D:I,5,0)=1,"EFACT_CNE",IF(VLOOKUP(B64,MAPA_DATA!D:I,6,0)=1,"EFACT_EST_CNE","SIN_DATA")) -> SIN_DATA | M64: =CONCATENATE("SUMIF(",L64,"!B:B;Reliquidacion!B",A64,";",L64,"!S:S)") -> SUMIF(SIN_DATA!B:B;Reliquidacion!B64;SIN_DATA!S:S) | N64: =CONCATENATE("(O",A64,"/M",A64,")") -> (O64/M64) | O64: =CONCATENATE("SUMIF(",L64,"!B:B;Reliquidacion!B",A64,";",L64,"!W:W)") -> SUMIF(SIN_DATA!B:B;Reliquidacion!B64;SIN_DATA!W:W) | P64: =CONCATENATE("SUMIF(",L64,"!B:B;Reliquidacion!B",A64,";",L64,"!X:X)") -> SUMIF(SIN_DATA!B:B;Reliquidacion!B64;SIN_DATA!X:X) | Q64: =CONCATENATE("(R",A64,"/P",A64,")") -> (R64/P64) | R64: =CONCATENATE("SUMIF(",L64,"!B:B;Reliquidacion!B",A64,";",L64,"!AB:AB)") -> SUMIF(SIN_DATA!B:B;Reliquidacion!B64;SIN_DATA!AB:AB) | S64: =CONCATENATE("(O",A64,"+R",A64,")") -> (O64+R64) | U64: 44044 | V64: =CONCATENATE("=(S",A64,"-J",A64,")") -> =(S64-J64) | W64: 19T/30-12-2020 | X64: =VLOOKUP(W64,[1]INTERESES!A:B,2,0) -> 0 | Y64: =VLOOKUP(W64,#REF!,6,0) -> #REF! | Z64: 44099 | AA64: =AA60 -> 44377 | AB64: =AA64-Z64 -> 278 | AC64: =+(1+Y64)^(AB64/360)-1 -> #REF! | AD64: =AC64*V64 -> #REF! | AE64: =+V64+AD64 -> #VALUE!
A65: =A64+1 -> 65 | B65: 44075 | C65: =CONCATENATE("IF(VLOOKUP(B9,MAPA_DATA!D:G,2,0)=1,'FACT_EMITIDA',IF(VLOOKUP(B",A65,",MAPA_DATA!D:G,3,0)=1,'FACT_EST_EFACT',(IF(VLOOKUP(B",A65,",MAPA_DATA!D:G,4,0)=1,'FACT_EST_CEN','SIN_DATA')))") -> IF(VLOOKUP(B9,MAPA_DATA!D:G,2,0)=1,'FACT_EMITIDA',IF(VLOOKUP(B65,MAPA_DATA!D:G,3,0)=1,'FACT_EST_EFACT',(IF(VLOOKUP(B65,MAPA_DATA!D:G,4,0)=1,'FACT_EST_CEN','SIN_DATA'))) | D65: =CONCATENATE("SUMIF(",IF(C65="FACT_EMITIDA","SIGGE_E",C65),"!B:B,Reliquidacion!B",A65,",",IF(C65="FACT_EMITIDA","SIGGE_E",C65),"!F:F)") -> SUMIF(IF(VLOOKUP(B9,MAPA_DATA!D:G,2,0)=1,'FACT_EMITIDA',IF(VLOOKUP(B65,MAPA_DATA!D:G,3,0)=1,'FACT_EST_EFACT',(IF(VLOOKUP(B65,MAPA_DATA!D:G,4,0)=1,'FACT_EST_CEN','SIN_DATA')))!B:B,Reliquidacion!B65,IF(VLOOKUP(B9,MAPA_DATA!D:G,2,0)=1,'FACT_EMITIDA',IF(VLOOKUP(B65,MAPA_DATA!D:G,3,0)=1,'FACT_EST_EFACT',(IF(VLOOKUP(B65,MAPA_DATA!D:G,4,0)=1,'FACT_EST_CEN','SIN_DATA')))!F:F) | E65: =CONCATENATE("(F",A65,"/D",A65,")") -> (F65/D65) | F65: =CONCATENATE("SUMIF(",IF(C65="FACT_EMITIDA","SIGGE_E",C65),"!B:B,Reliquidacion!B",A65,",",IF(C65="FACT_EMITIDA","SIGGE_E",C65),"!H:H)") -> SUMIF(IF(VLOOKUP(B9,MAPA_DATA!D:G,2,0)=1,'FACT_EMITIDA',IF(VLOOKUP(B65,MAPA_DATA!D:G,3,0)=1,'FACT_EST_EFACT',(IF(VLOOKUP(B65,MAPA_DATA!D:G,4,0)=1,'FACT_EST_CEN','SIN_DATA')))!B:B,Reliquidacion!B65,IF(VLOOKUP(B9,MAPA_DATA!D:G,2,0)=1,'FACT_EMITIDA',IF(VLOOKUP(B65,MAPA_DATA!D:G,3,0)=1,'FACT_EST_EFACT',(IF(VLOOKUP(B65,MAPA_DATA!D:G,4,0)=1,'FACT_EST_CEN','SIN_DATA')))!H:H) | G65: =CONCATENATE("SUMIF(",IF(C65="FACT_EMITIDA","SIGGE_P",C65),"!B:B,Reliquidacion!B",A65,",",IF(C65="FACT_EMITIDA","SIGGE_P",C65),"!F:F)") -> SUMIF(IF(VLOOKUP(B9,MAPA_DATA!D:G,2,0)=1,'FACT_EMITIDA',IF(VLOOKUP(B65,MAPA_DATA!D:G,3,0)=1,'FACT_EST_EFACT',(IF(VLOOKUP(B65,MAPA_DATA!D:G,4,0)=1,'FACT_EST_CEN','SIN_DATA')))!B:B,Reliquidacion!B65,IF(VLOOKUP(B9,MAPA_DATA!D:G,2,0)=1,'FACT_EMITIDA',IF(VLOOKUP(B65,MAPA_DATA!D:G,3,0)=1,'FACT_EST_EFACT',(IF(VLOOKUP(B65,MAPA_DATA!D:G,4,0)=1,'FACT_EST_CEN','SIN_DATA')))!F:F) | H65: =CONCATENATE("(I",A65,"/G",A65,")") -> (I65/G65) | I65: =CONCATENATE("SUMIF(",IF(C65="FACT_EMITIDA","SIGGE_P",C65),"!B:B,Reliquidacion!B",A65,",",IF(C65="FACT_EMITIDA","SIGGE_P",C65),"!H:H)") -> SUMIF(IF(VLOOKUP(B9,MAPA_DATA!D:G,2,0)=1,'FACT_EMITIDA',IF(VLOOKUP(B65,MAPA_DATA!D:G,3,0)=1,'FACT_EST_EFACT',(IF(VLOOKUP(B65,MAPA_DATA!D:G,4,0)=1,'FACT_EST_CEN','SIN_DATA')))!B:B,Reliquidacion!B65,IF(VLOOKUP(B9,MAPA_DATA!D:G,2,0)=1,'FACT_EMITIDA',IF(VLOOKUP(B65,MAPA_DATA!D:G,3,0)=1,'FACT_EST_EFACT',(IF(VLOOKUP(B65,MAPA_DATA!D:G,4,0)=1,'FACT_EST_CEN','SIN_DATA')))!H:H) | J65: =CONCATENATE("(F",A65,"+I",A65,")") -> (F65+I65) | L65: =IF(VLOOKUP(B65,MAPA_DATA!D:I,5,0)=1,"EFACT_CNE",IF(VLOOKUP(B65,MAPA_DATA!D:I,6,0)=1,"EFACT_EST_CNE","SIN_DATA")) -> SIN_DATA | M65: =CONCATENATE("SUMIF(",L65,"!B:B;Reliquidacion!B",A65,";",L65,"!S:S)") -> SUMIF(SIN_DATA!B:B;Reliquidacion!B65;SIN_DATA!S:S) | N65: =CONCATENATE("(O",A65,"/M",A65,")") -> (O65/M65) | O65: =CONCATENATE("SUMIF(",L65,"!B:B;Reliquidacion!B",A65,";",L65,"!W:W)") -> SUMIF(SIN_DATA!B:B;Reliquidacion!B65;SIN_DATA!W:W) | P65: =CONCATENATE("SUMIF(",L65,"!B:B;Reliquidacion!B",A65,";",L65,"!X:X)") -> SUMIF(SIN_DATA!B:B;Reliquidacion!B65;SIN_DATA!X:X) | Q65: =CONCATENATE("(R",A65,"/P",A65,")") -> (R65/P65) | R65: =CONCATENATE("SUMIF(",L65,"!B:B;Reliquidacion!B",A65,";",L65,"!AB:AB)") -> SUMIF(SIN_DATA!B:B;Reliquidacion!B65;SIN_DATA!AB:AB) | S65: =CONCATENATE("(O",A65,"+R",A65,")") -> (O65+R65) | U65: 44075 | V65: =CONCATENATE("=(S",A65,"-J",A65,")") -> =(S65-J65) | W65: 19T/30-12-2020 | X65: =VLOOKUP(W65,[1]INTERESES!A:B,2,0) -> 0 | Y65: =VLOOKUP(W65,#REF!,6,0) -> #REF! | Z65: 44129 | AA65: =AA61 -> 44377 | AB65: =AA65-Z65 -> 248 | AC65: =+(1+Y65)^(AB65/360)-1 -> #REF! | AD65: =AC65*V65 -> #REF! | AE65: =+V65+AD65 -> #VALUE!
AD66: Reliquidación | AE66: =SUM(AE33:AE65) -> #VALUE!
AC68: Montos a favor | AD68: LAP emite factura
AC69: Montos en contra | AD69: LAP emite nota de crédito

Sheet MAPA_DATA
A2: Generador | B2: [GX] | E2: EFACT_CNE | F2: Información de facturación definitiva proveniente de los archivos EFACT publicados por la CNE en los Decretos de Precio de Nudo
A3: Distribuidor | B3: [EEDD] | E3: EFACT_EST_CEN | F3: Información de facturación definitiva estimada en base a los balances emitidos por el Coordinador
A4: Licitacion | B4: 2013/03-2° Llamado | E4: FACT_EMITIDA | F4: Información de facturación real desde PDFs y sistema SIGGE (gestión facturación electrónica)
A5: Bloque | B5: [BLOQUE] | E5: FACT_EST_EFACT | F5: Estimación de facturación emitida en base a información de los EFACT Decretos Precios de Nudo
E6: FACT_EST_CEN | F6: Estimación de facturación emitida en base a información de los Balances del Coordinador
E8: Lo que se facturó | H8: Lo que se debió haber facturado
B9: Prioridad de información | E9: 1 | F9: 2 | G9: 3 | H9: 1 | I9: 2
A10: Id | B10: Año | C10: Mes | D10: Fecha | E10: FACT_EMITIDA | F10: FACT_EST_EFACT | G10: FACT_EST_CEN | H10: EFACT_CNE | I10: EFACT_EST_CEN
A11: 11 | B11: 2016 | C11: 1 | D11: 42370 | E11: =CONCATENATE("IF(COUNTIF(FACT_EMITIDA!B:B,'MAPA_DATA'!D",A11,")>0,1,0)") -> IF(COUNTIF(FACT_EMITIDA!B:B,'MAPA_DATA'!D11)>0,1,0) | F11: =CONCATENATE("IF(COUNTIF(FACT_EST_EFACT!B:B,'MAPA_DATA'!D",A11,")>0,1,0)") -> IF(COUNTIF(FACT_EST_EFACT!B:B,'MAPA_DATA'!D11)>0,1,0) | G11: =CONCATENATE("IF(COUNTIF(FACT_EST_CEN!B:B,'MAPA_DATA'!D",A11,")>0,1,0)") -> IF(COUNTIF(FACT_EST_CEN!B:B,'MAPA_DATA'!D11)>0,1,0) | H11: =CONCATENATE("IF(COUNTIF(EFACT_CNE!B:B,'MAPA_DATA'!D",A11,")>0,1,0)") -> IF(COUNTIF(EFACT_CNE!B:B,'MAPA_DATA'!D11)>0,1,0) | I11: =CONCATENATE("IF(COUNTIF(EFACT_EST_CEN!B:B,'MAPA_DATA'!D",A11,")>0,1,0)") -> IF(COUNTIF(EFACT_EST_CEN!B:B,'MAPA_DATA'!D11)>0,1,0)
A12: 12 | B12: 2016 | C12: 2 | D12: 42401 | E12: =CONCATENATE("IF(COUNTIF(FACT_EMITIDA!B:B,'MAPA_DATA'!D",A12,")>0,1,0)") -> IF(COUNTIF(FACT_EMITIDA!B:B,'MAPA_DATA'!D12)>0,1,0) | F12: =CONCATENATE("IF(COUNTIF(FACT_EST_EFACT!B:B,'MAPA_DATA'!D",A12,")>0,1,0)") -> IF(COUNTIF(FACT_EST_EFACT!B:B,'MAPA_DATA'!D12)>0,1,0) | G12: =CONCATENATE("IF(COUNTIF(FACT_EST_CEN!B:B,'MAPA_DATA'!D",A12,")>0,1,0)") -> IF(COUNTIF(FACT_EST_CEN!B:B,'MAPA_DATA'!D12)>0,1,0) | H12: =CONCATENATE("IF(COUNTIF(EFACT_CNE!B:B,'MAPA_DATA'!D",A12,")>0,1,0)") -> IF(COUNTIF(EFACT_CNE!B:B,'MAPA_DATA'!D12)>0,1,0) | I12: =CONCATENATE("IF(COUNTIF(EFACT_EST_CEN!B:B,'MAPA_DATA'!D",A12,")>0,1,0)") -> IF(COUNTIF(EFACT_EST_CEN!B:B,'MAPA_DATA'!D12)>0,1,0)
A13: 13 | B13: 2016 | C13: 3 | D13: 42430 | E13: =CONCATENATE("IF(COUNTIF(FACT_EMITIDA!B:B,'MAPA_DATA'!D",A13,")>0,1,0)") -> IF(COUNTIF(FACT_EMITIDA!B:B,'MAPA_DATA'!D13)>0,1,0) | F13: =CONCATENATE("IF(COUNTIF(FACT_EST_EFACT!B:B,'MAPA_DATA'!D",A13,")>0,1,0)") -> IF(COUNTIF(FACT_EST_EFACT!B:B,'MAPA_DATA'!D13)>0,1,0) | G13: =CONCATENATE("IF(COUNTIF(FACT_EST_CEN!B:B,'MAPA_DATA'!D",A13,")>0,1,0)") -> IF(COUNTIF(FACT_EST_CEN!B:B,'MAPA_DATA'!D13)>0,1,0) | H13: =CONCATENATE("IF(COUNTIF(EFACT_CNE!B:B,'MAPA_DATA'!D",A13,")>0,1,0)") -> IF(COUNTIF(EFACT_CNE!B:B,'MAPA_DATA'!D13)>0,1,0) | I13: =CONCATENATE("IF(COUNTIF(EFACT_EST_CEN!B:B,'MAPA_DATA'!D",A13,")>0,1,0)") -> IF(COUNTIF(EFACT_EST_CEN!B:B,'MAPA_DATA'!D13)>0,1,0)
A14: 14 | B14: 2016 | C14: 4 | D14: 42461 | E14: =CONCATENATE("IF(COUNTIF(FACT_EMITIDA!B:B,'MAPA_DATA'!D",A14,")>0,1,0)") -> IF(COUNTIF(FACT_EMITIDA!B:B,'MAPA_DATA'!D14)>0,1,0) | F14: =CONCATENATE("IF(COUNTIF(FACT_EST_EFACT!B:B,'MAPA_DATA'!D",A14,")>0,1,0)") -> IF(COUNTIF(FACT_EST_EFACT!B:B,'MAPA_DATA'!D14)>0,1,0) | G14: =CONCATENATE("IF(COUNTIF(FACT_EST_CEN!B:B,'MAPA_DATA'!D",A14,")>0,1,0)") -> IF(COUNTIF(FACT_EST_CEN!B:B,'MAPA_DATA'!D14)>0,1,0) | H14: =CONCATENATE("IF(COUNTIF(EFACT_CNE!B:B,'MAPA_DATA'!D",A14,")>0,1,0)") -> IF(COUNTIF(EFACT_CNE!B:B,'MAPA_DATA'!D14)>0,1,0) | I14: =CONCATENATE("IF(COUNTIF(EFACT_EST_CEN!B:B,'MAPA_DATA'!D",A14,")>0,1,0)") -> IF(COUNTIF(EFACT_EST_CEN!B:B,'MAPA_DATA'!D14)>0,1,0)
A15: 15 | B15: 2016 | C15: 5 | D15: 42491 | E15: =CONCATENATE("IF(COUNTIF(FACT_EMITIDA!B:B,'MAPA_DATA'!D",A15,")>0,1,0)") -> IF(COUNTIF(FACT_EMITIDA!B:B,'MAPA_DATA'!D15)>0,1,0) | F15: =CONCATENATE("IF(COUNTIF(FACT_EST_EFACT!B:B,'MAPA_DATA'!D",A15,")>0,1,0)") -> IF(COUNTIF(FACT_EST_EFACT!B:B,'MAPA_DATA'!D15)>0,1,0) | G15: =CONCATENATE("IF(COUNTIF(FACT_EST_CEN!B:B,'MAPA_DATA'!D",A15,")>0,1,0)") -> IF(COUNTIF(FACT_EST_CEN!B:B,'MAPA_DATA'!D15)>0,1,0) | H15: =CONCATENATE("IF(COUNTIF(EFACT_CNE!B:B,'MAPA_DATA'!D",A15,")>0,1,0)") -> IF(COUNTIF(EFACT_CNE!B:B,'MAPA_DATA'!D15)>0,1,0) | I15: =CONCATENATE("IF(COUNTIF(EFACT_EST_CEN!B:B,'MAPA_DATA'!D",A15,")>0,1,0)") -> IF(COUNTIF(EFACT_EST_CEN!B:B,'MAPA_DATA'!D15)>0,1,0)
A16: 16 | B16: 2016 | C16: 6 | D16: 42522 | E16: =CONCATENATE("IF(COUNTIF(FACT_EMITIDA!B:B,'MAPA_DATA'!D",A16,")>0,1,0)") -> IF(COUNTIF(FACT_EMITIDA!B:B,'MAPA_DATA'!D16)>0,1,0) | F16: =CONCATENATE("IF(COUNTIF(FACT_EST_EFACT!B:B,'MAPA_DATA'!D",A16,")>0,1,0)") -> IF(COUNTIF(FACT_EST_EFACT!B:B,'MAPA_DATA'!D16)>0,1,0) | G16: =CONCATENATE("IF(COUNTIF(FACT_EST_CEN!B:B,'MAPA_DATA'!D",A16,")>0,1,0)") -> IF(COUNTIF(FACT_EST_CEN!B:B,'MAPA_DATA'!D16)>0,1,0) | H16: =CONCATENATE("IF(COUNTIF(EFACT_CNE!B:B,'MAPA_DATA'!D",A16,")>0,1,0)") -> IF(COUNTIF(EFACT_CNE!B:B,'MAPA_DATA'!D16)>0,1,0) | I16: =CONCATENATE("IF(COUNTIF(EFACT_EST_CEN!B:B,'MAPA_DATA'!D",A16,")>0,1,0)") -> IF(COUNTIF(EFACT_EST_CEN!B:B,'MAPA_DATA'!D16)>0,1,0)
A17: 17 | B17: 2016 | C17: 7 | D17: 42552 | E17: =CONCATENATE("IF(COUNTIF(FACT_EMITIDA!B:B,'MAPA_DATA'!D",A17,")>0,1,0)") -> IF(COUNTIF(FACT_EMITIDA!B:B,'MAPA_DATA'!D17)>0,1,0) | F17: =CONCATENATE("IF(COUNTIF(FACT_EST_EFACT!B:B,'MAPA_DATA'!D",A17,")>0,1,0)") -> IF(COUNTIF(FACT_EST_EFACT!B:B,'MAPA_DATA'!D17)>0,1,0) | G17: =CONCATENATE("IF(COUNTIF(FACT_EST_CEN!B:B,'MAPA_DATA'!D",A17,")>0,1,0)") -> IF(COUNTIF(FACT_EST_CEN!B:B,'MAPA_DATA'!D17)>0,1,0) | H17: =CONCATENATE("IF(COUNTIF(EFACT_CNE!B:B,'MAPA_DATA'!D",A17,")>0,1,0)") -> IF(COUNTIF(EFACT_CNE!B:B,'MAPA_DATA'!D17)>0,1,0) | I17: =CONCATENATE("IF(COUNTIF(EFACT_EST_CEN!B:B,'MAPA_DATA'!D",A17,")>0,1,0)") -> IF(COUNTIF(EFACT_EST_CEN!B:B,'MAPA_DATA'!D17)>0,1,0)
A18: 18 | B18: 2016 | C18: 8 | D18: 42583 | E18: =CONCATENATE("IF(COUNTIF(FACT_EMITIDA!B:B,'MAPA_DATA'!D",A18,")>0,1,0)") -> IF(COUNTIF(FACT_EMITIDA!B:B,'MAPA_DATA'!D18)>0,1,0) | F18: =CONCATENATE("IF(COUNTIF(FACT_EST_EFACT!B:B,'MAPA_DATA'!D",A18,")>0,1,0)") -> IF(COUNTIF(FACT_EST_EFACT!B:B,'MAPA_DATA'!D18)>0,1,0) | G18: =CONCATENATE("IF(COUNTIF(FACT_EST_CEN!B:B,'MAPA_DATA'!D",A18,")>0,1,0)") -> IF(COUNTIF(FACT_EST_CEN!B:B,'MAPA_DATA'!D18)>0,1,0) | H18: =CONCATENATE("IF(COUNTIF(EFACT_CNE!B:B,'MAPA_DATA'!D",A18,")>0,1,0)") -> IF(COUNTIF(EFACT_CNE!B:B,'MAPA_DATA'!D18)>0,1,0) | I18: =CONCATENATE("IF(COUNTIF(EFACT_EST_CEN!B:B,'MAPA_DATA'!D",A18,")>0,1,0)") -> IF(COUNTIF(EFACT_EST_CEN!B:B,'MAPA_DATA'!D18)>0,1,0)
A19: 19 | B19: 2016 | C19: 9 | D19: 42614 | E19: =CONCATENATE("IF(COUNTIF(FACT_EMITIDA!B:B,'MAPA_DATA'!D",A19,")>0,1,0)") -> IF(COUNTIF(FACT_EMITIDA!B:B,'MAPA_DATA'!D19)>0,1,0) | F19: =CONCATENATE("IF(COUNTIF(FACT_EST_EFACT!B:B,'MAPA_DATA'!D",A19,")>0,1,0)") -> IF(COUNTIF(FACT_EST_EFACT!B:B,'MAPA_DATA'!D19)>0,1,0) | G19: =CONCATENATE("IF(COUNTIF(FACT_EST_CEN!B:B,'MAPA_DATA'!D",A19,")>0,1,0)") -> IF(COUNTIF(FACT_EST_CEN!B:B,'MAPA_DATA'!D19)>0,1,0) | H19: =CONCATENATE("IF(COUNTIF(EFACT_CNE!B:B,'MAPA_DATA'!D",A19,")>0,1,0)") -> IF(COUNTIF(EFACT_CNE!B:B,'MAPA_DATA'!D19)>0,1,0) | I19: =CONCATENATE("IF(COUNTIF(EFACT_EST_CEN!B:B,'MAPA_DATA'!D",A19,")>0,1,0)") -> IF(COUNTIF(EFACT_EST_CEN!B:B,'MAPA_DATA'!D19)>0,1,0)
A20: 20 | B20: 2016 | C20: 10 | D20: 42644 | E20: =CONCATENATE("IF(COUNTIF(FACT_EMITIDA!B:B,'MAPA_DATA'!D",A20,")>0,1,0)") -> IF(COUNTIF(FACT_EMITIDA!B:B,'MAPA_DATA'!D20)>0,1,0) | F20: =CONCATENATE("IF(COUNTIF(FACT_EST_EFACT!B:B,'MAPA_DATA'!D",A20,")>0,1,0)") -> IF(COUNTIF(FACT_EST_EFACT!B:B,'MAPA_DATA'!D20)>0,1,0) | G20: =CONCATENATE("IF(COUNTIF(FACT_EST_CEN!B:B,'MAPA_DATA'!D",A20,")>0,1,0)") -> IF(COUNTIF(FACT_EST_CEN!B:B,'MAPA_DATA'!D20)>0,1,0) | H20: =CONCATENATE("IF(COUNTIF(EFACT_CNE!B:B,'MAPA_DATA'!D",A20,")>0,1,0)") -> IF(COUNTIF(EFACT_CNE!B:B,'MAPA_DATA'!D20)>0,1,0) | I20: =CONCATENATE("IF(COUNTIF(EFACT_EST_CEN!B:B,'MAPA_DATA'!D",A20,")>0,1,0)") -> IF(COUNTIF(EFACT_EST_CEN!B:B,'MAPA_DATA'!D20)>0,1,0)
A21: 21 | B21: 2016 | C21: 11 | D21: 42675 | E21: =CONCATENATE("IF(COUNTIF(FACT_EMITIDA!B:B,'MAPA_DATA'!D",A21,")>0,1,0)") -> IF(COUNTIF(FACT_EMITIDA!B:B,'MAPA_DATA'!D21)>0,1,0) | F21: =CONCATENATE("IF(COUNTIF(FACT_EST_EFACT!B:B,'MAPA_DATA'!D",A21,")>0,1,0)") -> IF(COUNTIF(FACT_EST_EFACT!B:B,'MAPA_DATA'!D21)>0,1,0) | G21: =CONCATENATE("IF(COUNTIF(FACT_EST_CEN!B:B,'MAPA_DATA'!D",A21,")>0,1,0)") -> IF(COUNTIF(FACT_EST_CEN!B:B,'MAPA_DATA'!D21)>0,1,0) | H21: =CONCATENATE("IF(COUNTIF(EFACT_CNE!B:B,'MAPA_DATA'!D",A21,")>0,1,0)") -> IF(COUNTIF(EFACT_CNE!B:B,'MAPA_DATA'!D21)>0,1,0) | I21: =CONCATENATE("IF(COUNTIF(EFACT_EST_CEN!B:B,'MAPA_DATA'!D",A21,")>0,1,0)") -> IF(COUNTIF(EFACT_EST_CEN!B:B,'MAPA_DATA'!D21)>0,1,0)
A22: 22 | B22: 2016 | C22: 12 | D22: 42705 | E22: =CONCATENATE("IF(COUNTIF(FACT_EMITIDA!B:B,'MAPA_DATA'!D",A22,")>0,1,0)") -> IF(COUNTIF(FACT_EMITIDA!B:B,'MAPA_DATA'!D22)>0,1,0) | F22: =CONCATENATE("IF(COUNTIF(FACT_EST_EFACT!B:B,'MAPA_DATA'!D",A22,")>0,1,0)") -> IF(COUNTIF(FACT_EST_EFACT!B:B,'MAPA_DATA'!D22)>0,1,0) | G22: =CONCATENATE("IF(COUNTIF(FACT_EST_CEN!B:B,'MAPA_DATA'!D",A22,")>0,1,0)") -> IF(COUNTIF(FACT_EST_CEN!B:B,'MAPA_DATA'!D22)>0,1,0) | H22: =CONCATENATE("IF(COUNTIF(EFACT_CNE!B:B,'MAPA_DATA'!D",A22,")>0,1,0)") -> IF(COUNTIF(EFACT_CNE!B:B,'MAPA_DATA'!D22)>0,1,0) | I22: =CONCATENATE("IF(COUNTIF(EFACT_EST_CEN!B:B,'MAPA_DATA'!D",A22,")>0,1,0)") -> IF(COUNTIF(EFACT_EST_CEN!B:B,'MAPA_DATA'!D22)>0,1,0)
A23: 23 | B23: =B11+1 -> 2017 | C23: =C11 -> 1 | D23: 42736 | E23: =CONCATENATE("IF(COUNTIF(FACT_EMITIDA!B:B,'MAPA_DATA'!D",A23,")>0,1,0)") -> IF(COUNTIF(FACT_EMITIDA!B:B,'MAPA_DATA'!D23)>0,1,0) | F23: =CONCATENATE("IF(COUNTIF(FACT_EST_EFACT!B:B,'MAPA_DATA'!D",A23,")>0,1,0)") -> IF(COUNTIF(FACT_EST_EFACT!B:B,'MAPA_DATA'!D23)>0,1,0) | G23: =CONCATENATE("IF(COUNTIF(FACT_EST_CEN!B:B,'MAPA_DATA'!D",A23,")>0,1,0)") -> IF(COUNTIF(FACT_EST_CEN!B:B,'MAPA_DATA'!D23)>0,1,0) | H23: =CONCATENATE("IF(COUNTIF(EFACT_CNE!B:B,'MAPA_DATA'!D",A23,")>0,1,0)") -> IF(COUNTIF(EFACT_CNE!B:B,'MAPA_DATA'!D23)>0,1,0) | I23: =CONCATENATE("IF(COUNTIF(EFACT_EST_CEN!B:B,'MAPA_DATA'!D",A23,")>0,1,0)") -> IF(COUNTIF(EFACT_EST_CEN!B:B,'MAPA_DATA'!D23)>0,1,0)
A24: 24 | B24: =B12+1 -> 2017 | C24: =C12 -> 2 | D24: 42767 | E24: =CONCATENATE("IF(COUNTIF(FACT_EMITIDA!B:B,'MAPA_DATA'!D",A24,")>0,1,0)") -> IF(COUNTIF(FACT_EMITIDA!B:B,'MAPA_DATA'!D24)>0,1,0) | F24: =CONCATENATE("IF(COUNTIF(FACT_EST_EFACT!B:B,'MAPA_DATA'!D",A24,")>0,1,0)") -> IF(COUNTIF(FACT_EST_EFACT!B:B,'MAPA_DATA'!D24)>0,1,0) | G24: =CONCATENATE("IF(COUNTIF(FACT_EST_CEN!B:B,'MAPA_DATA'!D",A24,")>0,1,0)") -> IF(COUNTIF(FACT_EST_CEN!B:B,'MAPA_DATA'!D24)>0,1,0) | H24: =CONCATENATE("IF(COUNTIF(EFACT_CNE!B:B,'MAPA_DATA'!D",A24,")>0,1,0)") -> IF(COUNTIF(EFACT_CNE!B:B,'MAPA_DATA'!D24)>0,1,0) | I24: =CONCATENATE("IF(COUNTIF(EFACT_EST_CEN!B:B,'MAPA_DATA'!D",A24,")>0,1,0)") -> IF(COUNTIF(EFACT_EST_CEN!B:B,'MAPA_DATA'!D24)>0,1,0)
A25: 25 | B25: =B13+1 -> 2017 | C25: =C13 -> 3 | D25: 42795 | E25: =CONCATENATE("IF(COUNTIF(FACT_EMITIDA!B:B,'MAPA_DATA'!D",A25,")>0,1,0)") -> IF(COUNTIF(FACT_EMITIDA!B:B,'MAPA_DATA'!D25)>0,1,0) | F25: =CONCATENATE("IF(COUNTIF(FACT_EST_EFACT!B:B,'MAPA_DATA'!D",A25,")>0,1,0)") -> IF(COUNTIF(FACT_EST_EFACT!B:B,'MAPA_DATA'!D25)>0,1,0) | G25: =CONCATENATE("IF(COUNTIF(FACT_EST_CEN!B:B,'MAPA_DATA'!D",A25,")>0,1,0)") -> IF(COUNTIF(FACT_EST_CEN!B:B,'MAPA_DATA'!D25)>0,1,0) | H25: =CONCATENATE("IF(COUNTIF(EFACT_CNE!B:B,'MAPA_DATA'!D",A25,")>0,1,0)") -> IF(COUNTIF(EFACT_CNE!B:B,'MAPA_DATA'!D25)>0,1,0) | I25: =CONCATENATE("IF(COUNTIF(EFACT_EST_CEN!B:B,'MAPA_DATA'!D",A25,")>0,1,0)") -> IF(COUNTIF(EFACT_EST_CEN!B:B,'MAPA_DATA'!D25)>0,1,0)
A26: 26 | B26: =B14+1 -> 2017 | C26: =C14 -> 4 | D26: 42826 | E26: =CONCATENATE("IF(COUNTIF(FACT_EMITIDA!B:B,'MAPA_DATA'!D",A26,")>0,1,0)") -> IF(COUNTIF(FACT_EMITIDA!B:B,'MAPA_DATA'!D26)>0,1,0) | F26: =CONCATENATE("IF(COUNTIF(FACT_EST_EFACT!B:B,'MAPA_DATA'!D",A26,")>0,1,0)") -> IF(COUNTIF(FACT_EST_EFACT!B:B,'MAPA_DATA'!D26)>0,1,0) | G26: =CONCATENATE("IF(COUNTIF(FACT_EST_CEN!B:B,'MAPA_DATA'!D",A26,")>0,1,0)") -> IF(COUNTIF(FACT_EST_CEN!B:B,'MAPA_DATA'!D26)>0,1,0) | H26: =CONCATENATE("IF(COUNTIF(EFACT_CNE!B:B,'MAPA_DATA'!D",A26,")>0,1,0)") -> IF(COUNTIF(EFACT_CNE!B:B,'MAPA_DATA'!D26)>0,1,0) | I26: =CONCATENATE("IF(COUNTIF(EFACT_EST_CEN!B:B,'MAPA_DATA'!D",A26,")>0,1,0)") -> IF(COUNTIF(EFACT_EST_CEN!B:B,'MAPA_DATA'!D26)>0,1,0)
A27: 27 | B27: =B15+1 -> 2017 | C27: =C15 -> 5 | D27: 42856 | E27: =CONCATENATE("IF(COUNTIF(FACT_EMITIDA!B:B,'MAPA_DATA'!D",A27,")>0,1,0)") -> IF(COUNTIF(FACT_EMITIDA!B:B,'MAPA_DATA'!D27)>0,1,0) | F27: =CONCATENATE("IF(COUNTIF(FACT_EST_EFACT!B:B,'MAPA_DATA'!D",A27,")>0,1,0)") -> IF(COUNTIF(FACT_EST_EFACT!B:B,'MAPA_DATA'!D27)>0,1,0) | G27: =CONCATENATE("IF(COUNTIF(FACT_EST_CEN!B:B,'MAPA_DATA'!D",A27,")>0,1,0)") -> IF(COUNTIF(FACT_EST_CEN!B:B,'MAPA_DATA'!D27)>0,1,0) | H27: =CONCATENATE("IF(COUNTIF(EFACT_CNE!B:B,'MAPA_DATA'!D",A27,")>0,1,0)") -> IF(COUNTIF(EFACT_CNE!B:B,'MAPA_DATA'!D27)>0,1,0) | I27: =CONCATENATE("IF(COUNTIF(EFACT_EST_CEN!B:B,'MAPA_DATA'!D",A27,")>0,1,0)") -> IF(COUNTIF(EFACT_EST_CEN!B:B,'MAPA_DATA'!D27)>0,1,0)
A28: 28 | B28: =B16+1 -> 2017 | C28: =C16 -> 6 | D28: 42887 | E28: =CONCATENATE("IF(COUNTIF(FACT_EMITIDA!B:B,'MAPA_DATA'!D",A28,")>0,1,0)") -> IF(COUNTIF(FACT_EMITIDA!B:B,'MAPA_DATA'!D28)>0,1,0) | F28: =CONCATENATE("IF(COUNTIF(FACT_EST_EFACT!B:B,'MAPA_DATA'!D",A28,")>0,1,0)") -> IF(COUNTIF(FACT_EST_EFACT!B:B,'MAPA_DATA'!D28)>0,1,0) | G28: =CONCATENATE("IF(COUNTIF(FACT_EST_CEN!B:B,'MAPA_DATA'!D",A28,")>0,1,0)") -> IF(COUNTIF(FACT_EST_CEN!B:B,'MAPA_DATA'!D28)>0,1,0) | H28: =CONCATENATE("IF(COUNTIF(EFACT_CNE!B:B,'MAPA_DATA'!D",A28,")>0,1,0)") -> IF(COUNTIF(EFACT_CNE!B:B,'MAPA_DATA'!D28)>0,1,0) | I28: =CONCATENATE("IF(COUNTIF(EFACT_EST_CEN!B:B,'MAPA_DATA'!D",A28,")>0,1,0)") -> IF(COUNTIF(EFACT_EST_CEN!B:B,'MAPA_DATA'!D28)>0,1,0)
A29: 29 | B29: =B17+1 -> 2017 | C29: =C17 -> 7 | D29: 42917 | E29: =CONCATENATE("IF(COUNTIF(FACT_EMITIDA!B:B,'MAPA_DATA'!D",A29,")>0,1,0)") -> IF(COUNTIF(FACT_EMITIDA!B:B,'MAPA_DATA'!D29)>0,1,0) | F29: =CONCATENATE("IF(COUNTIF(FACT_EST_EFACT!B:B,'MAPA_DATA'!D",A29,")>0,1,0)") -> IF(COUNTIF(FACT_EST_EFACT!B:B,'MAPA_DATA'!D29)>0,1,0) | G29: =CONCATENATE("IF(COUNTIF(FACT_EST_CEN!B:B,'MAPA_DATA'!D",A29,")>0,1,0)") -> IF(COUNTIF(FACT_EST_CEN!B:B,'MAPA_DATA'!D29)>0,1,0) | H29: =CONCATENATE("IF(COUNTIF(EFACT_CNE!B:B,'MAPA_DATA'!D",A29,")>0,1,0)") -> IF(COUNTIF(EFACT_CNE!B:B,'MAPA_DATA'!D29)>0,1,0) | I29: =CONCATENATE("IF(COUNTIF(EFACT_EST_CEN!B:B,'MAPA_DATA'!D",A29,")>0,1,0)") -> IF(COUNTIF(EFACT_EST_CEN!B:B,'MAPA_DATA'!D29)>0,1,0)
A30: 30 | B30: =B18+1 -> 2017 | C30: =C18 -> 8 | D30: 42948 | E30: =CONCATENATE("IF(COUNTIF(FACT_EMITIDA!B:B,'MAPA_DATA'!D",A30,")>0,1,0)") -> IF(COUNTIF(FACT_EMITIDA!B:B,'MAPA_DATA'!D30)>0,1,0) | F30: =CONCATENATE("IF(COUNTIF(FACT_EST_EFACT!B:B,'MAPA_DATA'!D",A30,")>0,1,0)") -> IF(COUNTIF(FACT_EST_EFACT!B:B,'MAPA_DATA'!D30)>0,1,0) | G30: =CONCATENATE("IF(COUNTIF(FACT_EST_CEN!B:B,'MAPA_DATA'!D",A30,")>0,1,0)") -> IF(COUNTIF(FACT_EST_CEN!B:B,'MAPA_DATA'!D30)>0,1,0) | H30: =CONCATENATE("IF(COUNTIF(EFACT_CNE!B:B,'MAPA_DATA'!D",A30,")>0,1,0)") -> IF(COUNTIF(EFACT_CNE!B:B,'MAPA_DATA'!D30)>0,1,0) | I30: =CONCATENATE("IF(COUNTIF(EFACT_EST_CEN!B:B,'MAPA_DATA'!D",A30,")>0,1,0)") -> IF(COUNTIF(EFACT_EST_CEN!B:B,'MAPA_DATA'!D30)>0,1,0)
A31: 31 | B31: =B19+1 -> 2017 | C31: =C19 -> 9 | D31: 42979 | E31: =CONCATENATE("IF(COUNTIF(FACT_EMITIDA!B:B,'MAPA_DATA'!D",A31,")>0,1,0)") -> IF(COUNTIF(FACT_EMITIDA!B:B,'MAPA_DATA'!D31)>0,1,0) | F31: =CONCATENATE("IF(COUNTIF(FACT_EST_EFACT!B:B,'MAPA_DATA'!D",A31,")>0,1,0)") -> IF(COUNTIF(FACT_EST_EFACT!B:B,'MAPA_DATA'!D31)>0,1,0) | G31: =CONCATENATE("IF(COUNTIF(FACT_EST_CEN!B:B,'MAPA_DATA'!D",A31,")>0,1,0)") -> IF(COUNTIF(FACT_EST_CEN!B:B,'MAPA_DATA'!D31)>0,1,0) | H31: =CONCATENATE("IF(COUNTIF(EFACT_CNE!B:B,'MAPA_DATA'!D",A31,")>0,1,0)") -> IF(COUNTIF(EFACT_CNE!B:B,'MAPA_DATA'!D31)>0,1,0) | I31: =CONCATENATE("IF(COUNTIF(EFACT_EST_CEN!B:B,'MAPA_DATA'!D",A31,")>0,1,0)") -> IF(COUNTIF(EFACT_EST_CEN!B:B,'MAPA_DATA'!D31)>0,1,0)
A32: 32 | B32: =B20+1 -> 2017 | C32: =C20 -> 10 | D32: 43009 | E32: =CONCATENATE("IF(COUNTIF(FACT_EMITIDA!B:B,'MAPA_DATA'!D",A32,")>0,1,0)") -> IF(COUNTIF(FACT_EMITIDA!B:B,'MAPA_DATA'!D32)>0,1,0) | F32: =CONCATENATE("IF(COUNTIF(FACT_EST_EFACT!B:B,'MAPA_DATA'!D",A32,")>0,1,0)") -> IF(COUNTIF(FACT_EST_EFACT!B:B,'MAPA_DATA'!D32)>0,1,0) | G32: =CONCATENATE("IF(COUNTIF(FACT_EST_CEN!B:B,'MAPA_DATA'!D",A32,")>0,1,0)") -> IF(COUNTIF(FACT_EST_CEN!B:B,'MAPA_DATA'!D32)>0,1,0) | H32: =CONCATENATE("IF(COUNTIF(EFACT_CNE!B:B,'MAPA_DATA'!D",A32,")>0,1,0)") -> IF(COUNTIF(EFACT_CNE!B:B,'MAPA_DATA'!D32)>0,1,0) | I32: =CONCATENATE("IF(COUNTIF(EFACT_EST_CEN!B:B,'MAPA_DATA'!D",A32,")>0,1,0)") -> IF(COUNTIF(EFACT_EST_CEN!B:B,'MAPA_DATA'!D32)>0,1,0)
A33: 33 | B33: =B21+1 -> 2017 | C33: =C21 -> 11 | D33: 43040 | E33: =CONCATENATE("IF(COUNTIF(FACT_EMITIDA!B:B,'MAPA_DATA'!D",A33,")>0,1,0)") -> IF(COUNTIF(FACT_EMITIDA!B:B,'MAPA_DATA'!D33)>0,1,0) | F33: =CONCATENATE("IF(COUNTIF(FACT_EST_EFACT!B:B,'MAPA_DATA'!D",A33,")>0,1,0)") -> IF(COUNTIF(FACT_EST_EFACT!B:B,'MAPA_DATA'!D33)>0,1,0) | G33: =CONCATENATE("IF(COUNTIF(FACT_EST_CEN!B:B,'MAPA_DATA'!D",A33,")>0,1,0)") -> IF(COUNTIF(FACT_EST_CEN!B:B,'MAPA_DATA'!D33)>0,1,0) | H33: =CONCATENATE("IF(COUNTIF(EFACT_CNE!B:B,'MAPA_DATA'!D",A33,")>0,1,0)") -> IF(COUNTIF(EFACT_CNE!B:B,'MAPA_DATA'!D33)>0,1,0) | I33: =CONCATENATE("IF(COUNTIF(EFACT_EST_CEN!B:B,'MAPA_DATA'!D",A33,")>0,1,0)") -> IF(COUNTIF(EFACT_EST_CEN!B:B,'MAPA_DATA'!D33)>0,1,0)
A34: 34 | B34: =B22+1 -> 2017 | C34: =C22 -> 12 | D34: 43070 | E34: =CONCATENATE("IF(COUNTIF(FACT_EMITIDA!B:B,'MAPA_DATA'!D",A34,")>0,1,0)") -> IF(COUNTIF(FACT_EMITIDA!B:B,'MAPA_DATA'!D34)>0,1,0) | F34: =CONCATENATE("IF(COUNTIF(FACT_EST_EFACT!B:B,'MAPA_DATA'!D",A34,")>0,1,0)") -> IF(COUNTIF(FACT_EST_EFACT!B:B,'MAPA_DATA'!D34)>0,1,0) | G34: =CONCATENATE("IF(COUNTIF(FACT_EST_CEN!B:B,'MAPA_DATA'!D",A34,")>0,1,0)") -> IF(COUNTIF(FACT_EST_CEN!B:B,'MAPA_DATA'!D34)>0,1,0) | H34: =CONCATENATE("IF(COUNTIF(EFACT_CNE!B:B,'MAPA_DATA'!D",A34,")>0,1,0)") -> IF(COUNTIF(EFACT_CNE!B:B,'MAPA_DATA'!D34)>0,1,0) | I34: =CONCATENATE("IF(COUNTIF(EFACT_EST_CEN!B:B,'MAPA_DATA'!D",A34,")>0,1,0)") -> IF(COUNTIF(EFACT_EST_CEN!B:B,'MAPA_DATA'!D34)>0,1,0)
... A67: 67 | B67: =B55+1 -> 2020 | C67: =C55 -> 9 | D67: 44075 | E67: =CONCATENATE("IF(COUNTIF(FACT_EMITIDA!B:B,'MAPA_DATA'!D",A67,")>0,1,0)") -> IF(COUNTIF(FACT_EMITIDA!B:B,'MAPA_DATA'!D67)>0,1,0) | F67: =CONCATENATE("IF(COUNTIF(FACT_EST_EFACT!B:B,'MAPA_DATA'!D",A67,")>0,1,0)") -> IF(COUNTIF(FACT_EST_EFACT!B:B,'MAPA_DATA'!D67)>0,1,0) | G67: =CONCATENATE("IF(COUNTIF(FACT_EST_CEN!B:B,'MAPA_DATA'!D",A67,")>0,1,0)") -> IF(COUNTIF(FACT_EST_CEN!B:B,'MAPA_DATA'!D67)>0,1,0) | H67: =CONCATENATE("IF(COUNTIF(EFACT_CNE!B:B,'MAPA_DATA'!D",A67,")>0,1,0)") -> IF(COUNTIF(EFACT_CNE!B:B,'MAPA_DATA'!D67)>0,1,0) | I67: =CONCATENATE("IF(COUNTIF(EFACT_EST_CEN!B:B,'MAPA_DATA'!D",A67,")>0,1,0)") -> IF(COUNTIF(EFACT_EST_CEN!B:B,'MAPA_DATA'!D67)>0,1,0)

Sheet FACT_EMITIDA
A1: Periodo | B1: MesDevengado | C1: Nombre | D1: Num | E1: Barra | F1: Cantidad | G1: Precio | H1: Monto | I1: Concepto | J1: Agrupacion | K1: Glosa | L1: FechaCarga | M1: TipoDocumento | N1: Folio | O1: Vendedor | P1: Comprador | Q1: Bloque | R1: Empresa | S1: ClaveEEDD | T1: Licitacion | U1: NomAgrupacion
A2: 01-09-2018 | B2: 01-09-2018 | C2: Licitación Caren y Cec (SIC 2013/03-2) BS1A | D2: 1 | E2: TotalBarras | F2: 3000 | G2: 58.085 | H2: 174255 | I2: Energia Licitaciones | J2: Energía | K2: Lic. SIC 2013/03-2 bloques BS1A: Energía sep 2018 | L2: 2018-10-19 00:00:00 | M2: 33 | N2: 6305 | O2: s | P2: s | Q2: BS1A | R2: Caren | S2: Cec | T2: 2013/03-2 | U2: CEC
A3: 01-10-2018 | B3: 01-10-2018 | C3: Licitación Caren y Cec (SIC 2013/03-2) BS1A | D3: 1 | E3: TotalBarras | F3: 3000 | G3: 59.678 | H3: 179035 | I3: Energia Licitaciones | J3: Energía | K3: Lic. SIC 2013/03-2 bloques BS1A: Energía oct 2018 | L3: 2018-11-27 00:00:00 | M3: 33 | N3: 6796 | O3: s | P3: s | Q3: BS1A | R3: Caren | S3: Cec | T3: 2013/03-2 | U3: CEC
A4: 01-11-2018 | B4: 01-11-2018 | C4: Licitación Caren y Cec (SIC 2013/03-2) BS1A | D4: 1 | E4: TotalBarras | F4: 4000 | G4: 59.635 | H4: 238540 | I4: Energia Licitaciones | J4: Energía | K4: Lic. SIC 2013/03-2 bloques BS1A: Energía nov 2018 | L4: 2018-12-14 00:00:00 | M4: 33 | N4: 6939 | O4: s | P4: s | Q4: BS1A | R4: Caren | S4: Cec | T4: 2013/03-2 | U4: CEC
A5: 01-12-2018 | B5: 01-12-2018 | C5: Licitación Caren y Cec (SIC 2013/03-2) BS1A | D5: 1 | E5: TotalBarras | F5: 5000 | G5: 67.951 | H5: 339757 | I5: Energia Licitaciones | J5: Energía | K5: Lic. SIC 2013/03-2 bloques BS1A: Energía dic 2018 | L5: 2019-01-21 00:00:00 | M5: 33 | N5: 7194 | O5: s | P5: s | Q5: BS1A | R5: Caren | S5: Cec | T5: 2013/03-2 | U5: CEC
A6: 01-01-2019 | B6: 01-01-2019 | C6: Licitación Caren y Cec (SIC 2013/03-2) BS1A | D6: 1 | E6: A.JAHUEL 220 | F6: 1.46188 | G6: 66.9 | H6: 98 | I6: Reliq. Energia Licitaciones | J6: Energía | K6: Lic. SIC 2013/03-2 bloques BS1A: Reliq. Energía ene 2019 | L6: 2019-03-15 00:00:00 | M6: 33 | O6: s | P6: s | Q6: BS1A | R6: Caren | S6: Cec | T6: 2013/03-2 | U6: CEC
A7: 01-01-2019 | B7: 01-01-2019 | C7: Licitación Caren y Cec (SIC 2013/03-2) BS1A | D7: 1 | E7: A.JAHUEL 220 | F7: 1371.306 | G7: 66.9 | H7: 91740 | I7: Energia Licitaciones | J7: Energía | K7: Lic. SIC 2013/03-2 bloques BS1A: Energía ene 2019 | L7: 2019-02-08 00:00:00 | M7: 33 | N7: 7513 | O7: s | P7: s | Q7: BS1A | R7: Caren | S7: Cec | T7: 2013/03-2 | U7: CEC
A8: 01-01-2019 | B8: 01-01-2019 | C8: Licitación Caren y Cec (SIC 2013/03-2) BS1A | D8: 2 | E8: A.MELIP 220 | F8: 0.009388 | G8: 69.014 | H8: 1 | I8: Reliq. Energia Licitaciones | J8: Energía | K8: Lic. SIC 2013/03-2 bloques BS1A: Reliq. Energía ene 2019 | L8: 2019-03-15 00:00:00 | M8: 33 | O8: s | P8: s | Q8: BS1A | R8: Caren | S8: Cec | T8: 2013/03-2 | U8: CEC
A9: 01-01-2019 | B9: 01-01-2019 | C9: Licitación Caren y Cec (SIC 2013/03-2) BS1A | D9: 2 | E9: A.MELIP 220 | F9: 8.806166 | G9: 69.014 | H9: 608 | I9: Energia Licitaciones | J9: Energía | K9: Lic. SIC 2013/03-2 bloques BS1A: Energía ene 2019 | L9: 2019-02-08 00:00:00 | M9: 33 | N9: 7513 | O9: s | P9: s | Q9: BS1A | R9: Caren | S9: Cec | T9: 2013/03-2 | U9: CEC
A10: 01-01-2019 | B10: 01-01-2019 | C10: Licitación Caren y Cec (SIC 2013/03-2) BS1A | D10: 3 | E10: CHARRUA 220 | F10: 0.453721 | G10: 63.27 | H10: 29 | I10: Reliq. Energia Licitaciones | J10: Energía | K10: Lic. SIC 2013/03-2 bloques BS1A: Reliq. Energía ene 2019 | L10: 2019-03-15 00:00:00 | M10: 33 | O10: s | P10: s | Q10: BS1A | R10: Caren | S10: Cec | T10: 2013/03-2 | U10: CEC
A11: 01-01-2019 | B11: 01-01-2019 | C11: Licitación Caren y Cec (SIC 2013/03-2) BS1A | D11: 3 | E11: CHARRUA 220 | F11: 425.60961 | G11: 63.27 | H11: 26928 | I11: Energia Licitaciones | J11: Energía | K11: Lic. SIC 2013/03-2 bloques BS1A: Energía ene 2019 | L11: 2019-02-08 00:00:00 | M11: 33 | N11: 7513 | O11: s | P11: s | Q11: BS1A | R11: Caren | S11: Cec | T11: 2013/03-2 | U11: CEC
A12: 01-01-2019 | B12: 01-01-2019 | C12: Licitación Caren y Cec (SIC 2013/03-2) BS1A | D12: 4 | E12: ITAHUE 220 | F12: 2.212452 | G12: 65.349 | H12: 145 | I12: Reliq. Energia Licitaciones | J12: Energía | K12: Lic. SIC 2013/03-2 bloques BS1A: Reliq. Energía ene 2019 | L12: 2019-03-15 00:00:00 | M12: 33 | O12: s | P12: s | Q12: BS1A | R12: Caren | S12: Cec | T12: 2013/03-2 | U12: CEC
A13: 01-01-2019 | B13: 01-01-2019 | C13: Licitación Caren y Cec (SIC 2013/03-2) BS1A | D13: 4 | E13: ITAHUE 220 | F13: 2075.374 | G13: 65.349 | H13: 135624 | I13: Energia Licitaciones | J13: Energía | K13: Lic. SIC 2013/03-2 bloques BS1A: Energía ene 2019 | L13: 2019-02-08 00:00:00 | M13: 33 | N13: 7513 | O13: s | P13: s | Q13: BS1A | R13: Caren | S13: Cec | T13: 2013/03-2 | U13: CEC
A14: 01-01-2019 | B14: 01-01-2019 | C14: Licitación Caren y Cec (SIC 2013/03-2) BS1A | D14: 5 | E14: RAPEL 220 | F14: 8.102057 | G14: 69.368 | H14: 562 | I14: Energia Licitaciones | J14: Energía | K14: Lic. SIC 2013/03-2 bloques BS1A: Energía ene 2019 | L14: 2019-02-08 00:00:00 | M14: 33 | N14: 7513 | O14: s | P14: s | Q14: BS1A | R14: Caren | S14: Cec | T14: 2013/03-2 | U14: CEC
A15: 01-01-2019 | B15: 01-01-2019 | C15: Licitación Caren y Cec (SIC 2013/03-2) BS1A | D15: 5 | E15: RAPEL 220 | F15: 0.008637 | G15: 69.368 | H15: 1 | I15: Reliq. Energia Licitaciones | J15: Energía | K15: Lic. SIC 2013/03-2 bloques BS1A: Reliq. Energía ene 2019 | L15: 2019-03-15 00:00:00 | M15: 33 | O15: s | P15: s | Q15: BS1A | R15: Caren | S15: Cec | T15: 2013/03-2 | U15: CEC
A16: 01-02-2019 | B16: 01-02-2019 | C16: Licitación Caren y Cec (SIC 2013/03-2) BS1A | D16: 1 | E16: A.JAHUEL 220 | F16: 1368.5299 | G16: 66.9 | H16: 91555 | I16: Energia Licitaciones | J16: Energía | K16: Lic. SIC 2013/03-2 bloques BS1A: Energía feb 2019 | L16: 2019-03-08 00:00:00 | M16: 33 | N16: 7798 | O16: s | P16: s | Q16: BS1A | R16: Caren | S16: Cec | T16: 2013/03-2 | U16: CEC
A17: 01-02-2019 | B17: 01-02-2019 | C17: Licitación Caren y Cec (SIC 2013/03-2) BS1A | D17: 1 | E17: A.JAHUEL 220 | F17: 0.23349 | G17: 66.9 | H17: 16 | I17: Reliq. Energia Licitaciones | J17: Energía | K17: Lic. SIC 2013/03-2 bloques BS1A: Reliq. Energía feb 2019 | L17: 2019-04-09 00:00:00 | M17: 61 | O17: s | P17: s | Q17: BS1A | R17: Caren | S17: Cec | T17: 2013/03-2 | U17: CEC
A18: 01-02-2019 | B18: 01-02-2019 | C18: Licitación Caren y Cec (SIC 2013/03-2) BS1A | D18: 2 | E18: A.MELIP 220 | F18: 8.816632 | G18: 69.014 | H18: 608 | I18: Energia Licitaciones | J18: Energía | K18: Lic. SIC 2013/03-2 bloques BS1A: Energía feb 2019 | L18: 2019-03-08 00:00:00 | M18: 33 | N18: 7798 | O18: s | P18: s | Q18: BS1A | R18: Caren | S18: Cec | T18: 2013/03-2 | U18: CEC
A19: 01-02-2019 | B19: 01-02-2019 | C19: Licitación Caren y Cec (SIC 2013/03-2) BS1A | D19: 3 | E19: CHARRUA 220 | F19: 422.52678 | G19: 63.27 | H19: 26733 | I19: Energia Licitaciones | J19: Energía | K19: Lic. SIC 2013/03-2 bloques BS1A: Energía feb 2019 | L19: 2019-03-08 00:00:00 | M19: 33 | N19: 7798 | O19: s | P19: s | Q19: BS1A | R19: Caren | S19: Cec | T19: 2013/03-2 | U19: CEC
A20: 01-02-2019 | B20: 01-02-2019 | C20: Licitación Caren y Cec (SIC 2013/03-2) BS1A | D20: 3 | E20: CHARRUA 220 | F20: 0.072089 | G20: 63.27 | H20: 5 | I20: Reliq. Energia Licitaciones | J20: Energía | K20: Lic. SIC 2013/03-2 bloques BS1A: Reliq. Energía feb 2019 | L20: 2019-04-09 00:00:00 | M20: 61 | O20: s | P20: s | Q20: BS1A | R20: Caren | S20: Cec | T20: 2013/03-2 | U20: CEC
A21: 01-02-2019 | B21: 01-02-2019 | C21: Licitación Caren y Cec (SIC 2013/03-2) BS1A | D21: 4 | E21: ITAHUE 220 | F21: 0.353269 | G21: 65.349 | H21: 23 | I21: Reliq. Energia Licitaciones | J21: Energía | K21: Lic. SIC 2013/03-2 bloques BS1A: Reliq. Energía feb 2019 | L21: 2019-04-09 00:00:00 | M21: 61 | O21: s | P21: s | Q21: BS1A | R21: Caren | S21: Cec | T21: 2013/03-2 | U21: CEC
A22: 01-02-2019 | B22: 01-02-2019 | C22: Licitación Caren y Cec (SIC 2013/03-2) BS1A | D22: 4 | E22: ITAHUE 220 | F22: 2070.5801 | G22: 65.349 | H22: 135310 | I22: Energia Licitaciones | J22: Energía | K22: Lic. SIC 2013/03-2 bloques BS1A: Energía feb 2019 | L22: 2019-03-08 00:00:00 | M22: 33 | N22: 7798 | O22: s | P22: s | Q22: BS1A | R22: Caren | S22: Cec | T22: 2013/03-2 | U22: CEC
A23: 01-02-2019 | B23: 01-02-2019 | C23: Licitación Caren y Cec (SIC 2013/03-2) BS1A | D23: 5 | E23: RAPEL 220 | F23: 8.102328 | G23: 69.368 | H23: 562 | I23: Energia Licitaciones | J23: Energía | K23: Lic. SIC 2013/03-2 bloques BS1A: Energía feb 2019 | L23: 2019-03-08 00:00:00 | M23: 33 | N23: 7798 | O23: s | P23: s | Q23: BS1A | R23: Caren | S23: Cec | T23: 2013/03-2 | U23: CEC
A24: 01-03-2019 | B24: 01-03-2019 | C24: Licitación Caren y Cec (SIC 2013/03-2) BS1A | D24: 1 | E24: A.JAHUEL 220 | F24: 1311.6233 | G24: 66.9 | H24: 87748 | I24: Energia Licitaciones | J24: Energía | K24: Lic. SIC 2013/03-2 bloques BS1A: Energía mar 2019 | L24: 2019-04-08 00:00:00 | M24: 33 | N24: 8389 | O24: s | P24: s | Q24: BS1A | R24: Caren | S24: Cec | T24: 2013/03-2 | U24: CEC
A25: 01-03-2019 | B25: 01-03-2019 | C25: Licitación Caren y Cec (SIC 2013/03-2) BS1A | D25: 1 | E25: A.JAHUEL 220 | F25: 0.580609 | G25: 66.9 | H25: 39 | I25: Reliq. Energia Licitaciones | J25: Energía | K25: Lic. SIC 2013/03-2 bloques BS1A: Reliq. Energía mar 2019 | L25: 2019-05-13 00:00:00 | M25: 33 | O25: s | P25: s | Q25: BS1A | R25: Caren | S25: Cec | T25: 2013/03-2 | U25: CEC
A26: 01-03-2019 | B26: 01-03-2019 | C26: Licitación Caren y Cec (SIC 2013/03-2) BS1A | D26: 2 | E26: A.MELIP 220 | F26: 8.173697 | G26: 69.014 | H26: 564 | I26: Energia Licitaciones | J26: Energía | K26: Lic. SIC 2013/03-2 bloques BS1A: Energía mar 2019 | L26: 2019-04-08 00:00:00 | M26: 33 | N26: 8389 | O26: s | P26: s | Q26: BS1A | R26: Caren | S26: Cec | T26: 2013/03-2 | U26: CEC
A27: 01-03-2019 | B27: 01-03-2019 | C27: Licitación Caren y Cec (SIC 2013/03-2) BS1A | D27: 3 | E27: CHARRUA 220 | F27: 0.178218 | G27: 63.27 | H27: 11 | I27: Reliq. Energia Licitaciones | J27: Energía | K27: Lic. SIC 2013/03-2 bloques BS1A: Reliq. Energía mar 2019 | L27: 2019-05-13 00:00:00 | M27: 33 | O27: s | P27: s | Q27: BS1A | R27: Caren | S27: Cec | T27: 2013/03-2 | U27: CEC
A28: 01-03-2019 | B28: 01-03-2019 | C28: Licitación Caren y Cec (SIC 2013/03-2) BS1A | D28: 3 | E28: CHARRUA 220 | F28: 402.60399 | G28: 63.27 | H28: 25473 | I28: Energia Licitaciones | J28: Energía | K28: Lic. SIC 2013/03-2 bloques BS1A: Energía mar 2019 | L28: 2019-04-08 00:00:00 | M28: 33 | N28: 8389 | O28: s | P28: s | Q28: BS1A | R28: Caren | S28: Cec | T28: 2013/03-2 | U28: CEC
A29: 01-03-2019 | B29: 01-03-2019 | C29: Licitación Caren y Cec (SIC 2013/03-2) BS1A | D29: 4 | E29: ITAHUE 220 | F29: 1967.9945 | G29: 65.349 | H29: 128606 | I29: Energia Licitaciones | J29: Energía | K29: Lic. SIC 2013/03-2 bloques BS1A: Energía mar 2019 | L29: 2019-04-08 00:00:00 | M29: 33 | N29: 8389 | O29: s | P29: s | Q29: BS1A | R29: Caren | S29: Cec | T29: 2013/03-2 | U29: CEC
A30: 01-03-2019 | B30: 01-03-2019 | C30: Licitación Caren y Cec (SIC 2013/03-2) BS1A | D30: 4 | E30: ITAHUE 220 | F30: 0.87116 | G30: 65.349 | H30: 57 | I30: Reliq. Energia Licitaciones | J30: Energía | K30: Lic. SIC 2013/03-2 bloques BS1A: Reliq. Energía mar 2019 | L30: 2019-05-13 00:00:00 | M30: 33 | O30: s | P30: s | Q30: BS1A | R30: Caren | S30: Cec | T30: 2013/03-2 | U30: CEC
A31: 01-03-2019 | B31: 01-03-2019 | C31: Licitación Caren y Cec (SIC 2013/03-2) BS1A | D31: 5 | E31: RAPEL 220 | F31: 7.514895 | G31: 69.368 | H31: 521 | I31: Energia Licitaciones | J31: Energía | K31: Lic. SIC 2013/03-2 bloques BS1A: Energía mar 2019 | L31: 2019-04-08 00:00:00 | M31: 33 | N31: 8389 | O31: s | P31: s | Q31: BS1A | R31: Caren | S31: Cec | T31: 2013/03-2 | U31: CEC
A32: 01-04-2019 | B32: 01-04-2019 | C32: Licitación Caren y Cec (SIC 2013/03-2) BS1A | D32: 1 | E32: A.JAHUEL 220 | F32: 1 | G32: -1091 | H32: -1091 | I32: Reliq. Energia Licitaciones | J32: Energía | K32: Lic. SIC 2013/03-2 bloques BS1A: Reliq. Energía abr 2019 | L32: 2020-03-23 11:56:36 | M32: 61 | O32: s | P32: s | Q32: BS1A | R32: Caren | S32: Cec | T32: 2013/03-2 | U32: CEC
A33: 01-04-2019 | B33: 01-04-2019 | C33: Licitación Caren y Cec (SIC 2013/03-2) BS1A | D33: 1 | E33: A.JAHUEL 220 | F33: 0 | G33: 0 | H33: 0 | I33: Potencia Licitaciones | J33: Potencia | K33: Lic. SIC 2013/03-2 bloques BS1A: Potencia abr 2019 | L33: 2019-05-13 00:00:00 | M33: 33 | N33: 8451 | O33: s | P33: s | Q33: BS1A | R33: Caren | S33: Cec | T33: 2013/03-2 | U33: CEC
A34: 01-04-2019 | B34: 01-04-2019 | C34: Licitación Caren y Cec (SIC 2013/03-2) BS1A | D34: 1 | E34: A.JAHUEL 220 | F34: 897.9651 | G34: 66.9 | H34: 60074 | I34: Energia Licitaciones | J34: Energía | K34: Lic. SIC 2013/03-2 bloques BS1A: Energía abr 2019 | L34: 2019-05-13 00:00:00 | M34: 33 | N34: 8451 | O34: s | P34: s | Q34: BS1A | R34: Caren | S34: Cec | T34: 2013/03-2 | U34: CEC
A35: 01-04-2019 | B35: 01-04-2019 | C35: Licitación Caren y Cec (SIC 2013/03-2) BS1A | D35: 1 | E35: A.JAHUEL 220 | F35: 0 | G35: 0 | H35: 0 | I35: Ajuste por Armonizacion Tarifaria Licitaciones | J35: AAT | K35: Lic. SIC 2013/03-2 bloques BS1A: AAT abr 2019 | L35: 2019-05-13 00:00:00 | M35: 33 | N35: 8451 | O35: s | P35: s | Q35: BS1A | R35: Caren | S35: Cec | T35: 2013/03-2 | U35: CEC
A36: 01-04-2019 | B36: 01-04-2019 | C36: Licitación Caren y Cec (SIC 2013/03-2) BS1A | D36: 1 | E36: A.JAHUEL 220 | F36: 0 | G36: 0 | H36: 0 | I36: Reactivos Licitaciones | J36: Reactivo | K36: Lic. SIC 2013/03-2 bloques BS1A: Reactivo abr 2019 | L36: 2019-05-13 00:00:00 | M36: 33 | N36: 8451 | O36: s | P36: s | Q36: BS1A | R36: Caren | S36: Cec | T36: 2013/03-2 | U36: CEC
A37: 01-04-2019 | B37: 01-04-2019 | C37: Licitación Caren y Cec (SIC 2013/03-2) BS1A | D37: 2 | E37: A.MELIP 220 | F37: 0 | G37: 0 | H37: 0 | I37: Potencia Licitaciones | J37: Potencia | K37: Lic. SIC 2013/03-2 bloques BS1A: Potencia abr 2019 | L37: 2019-05-13 00:00:00 | M37: 33 | N37: 8451 | O37: s | P37: s | Q37: BS1A | R37: Caren | S37: Cec | T37: 2013/03-2 | U37: CEC
A38: 01-04-2019 | B38: 01-04-2019 | C38: Licitación Caren y Cec (SIC 2013/03-2) BS1A | D38: 2 | E38: A.MELIP 220 | F38: 0 | G38: 0 | H38: 0 | I38: Ajuste por Armonizacion Tarifaria Licitaciones | J38: AAT | K38: Lic. SIC 2013/03-2 bloques BS1A: AAT abr 2019 | L38: 2019-05-13 00:00:00 | M38: 33 | N38: 8451 | O38: s | P38: s | Q38: BS1A | R38: Caren | S38: Cec | T38: 2013/03-2 | U38: CEC
A39: 01-04-2019 | B39: 01-04-2019 | C39: Licitación Caren y Cec (SIC 2013/03-2) BS1A | D39: 2 | E39: A.MELIP 220 | F39: 5.912451 | G39: 69.014 | H39: 408 | I39: Energia Licitaciones | J39: Energía | K39: Lic. SIC 2013/03-2 bloques BS1A: Energía abr 2019 | L39: 2019-05-13 00:00:00 | M39: 33 | N39: 8451 | O39: s | P39: s | Q39: BS1A | R39: Caren | S39: Cec | T39: 2013/03-2 | U39: CEC
A40: 01-04-2019 | B40: 01-04-2019 | C40: Licitación Caren y Cec (SIC 2013/03-2) BS1A | D40: 2 | E40: A.MELIP 220 | F40: 0 | G40: 0 | H40: 0 | I40: Reactivos Licitaciones | J40: Reactivo | K40: Lic. SIC 2013/03-2 bloques BS1A: Reactivo abr 2019 | L40: 2019-05-13 00:00:00 | M40: 33 | N40: 8451 | O40: s | P40: s | Q40: BS1A | R40: Caren | S40: Cec | T40: 2013/03-2 | U40: CEC
A41: 01-04-2019 | B41: 01-04-2019 | C41: Licitación Caren y Cec (SIC 2013/03-2) BS1A | D41: 2 | E41: A.MELIP 220 | F41: 1 | G41: -8 | H41: -8 | I41: Reliq. Energia Licitaciones | J41: Energía | K41: Lic. SIC 2013/03-2 bloques BS1A: Reliq. Energía abr 2019 | L41: 2020-03-23 11:56:36 | M41: 61 | O41: s | P41: s | Q41: BS1A | R41: Caren | S41: Cec | T41: 2013/03-2 | U41: CEC
A42: 01-04-2019 | B42: 01-04-2019 | C42: Licitación Caren y Cec (SIC 2013/03-2) BS1A | D42: 3 | E42: CHARRUA 220 | F42: 278.37089 | G42: 63.27 | H42: 17613 | I42: Energia Licitaciones | J42: Energía | K42: Lic. SIC 2013/03-2 bloques BS1A: Energía abr 2019 | L42: 2019-05-13 00:00:00 | M42: 33 | N42: 8451 | O42: s | P42: s | Q42: BS1A | R42: Caren | S42: Cec | T42: 2013/03-2 | U42: CEC
A43: 01-04-2019 | B43: 01-04-2019 | C43: Licitación Caren y Cec (SIC 2013/03-2) BS1A | D43: 3 | E43: CHARRUA 220 | F43: 0 | G43: 0 | H43: 0 | I43: Ajuste por Armonizacion Tarifaria Licitaciones | J43: AAT | K43: Lic. SIC 2013/03-2 bloques BS1A: AAT abr 2019 | L43: 2019-05-13 00:00:00 | M43: 33 | N43: 8451 | O43: s | P43: s | Q43: BS1A | R43: Caren | S43: Cec | T43: 2013/03-2 | U43: CEC
A44: 01-04-2019 | B44: 01-04-2019 | C44: Licitación Caren y Cec (SIC 2013/03-2) BS1A | D44: 3 | E44: CHARRUA 220 | F44: 1 | G44: -327 | H44: -327 | I44: Reliq. Energia Licitaciones | J44: Energía | K44: Lic. SIC 2013/03-2 bloques BS1A: Reliq. Energía abr 2019 | L44: 2020-03-23 11:56:36 | M44: 61 | O44: s | P44: s | Q44: BS1A | R44: Caren | S44: Cec | T44: 2013/03-2 | U44: CEC
A45: 01-04-2019 | B45: 01-04-2019 | C45: Licitación Caren y Cec (SIC 2013/03-2) BS1A | D45: 3 | E45: CHARRUA 220 | F45: 0 | G45: 0 | H45: 0 | I45: Potencia Licitaciones | J45: Potencia | K45: Lic. SIC 2013/03-2 bloques BS1A: Potencia abr 2019 | L45: 2019-05-13 00:00:00 | M45: 33 | N45: 8451 | O45: s | P45: s | Q45: BS1A | R45: Caren | S45: Cec | T45: 2013/03-2 | U45: CEC
A46: 01-04-2019 | B46: 01-04-2019 | C46: Licitación Caren y Cec (SIC 2013/03-2) BS1A | D46: 3 | E46: CHARRUA 220 | F46: 0 | G46: 0 | H46: 0 | I46: Reactivos Licitaciones | J46: Reactivo | K46: Lic. SIC 2013/03-2 bloques BS1A: Reactivo abr 2019 | L46: 2019-05-13 00:00:00 | M46: 33 | N46: 8451 | O46: s | P46: s | Q46: BS1A | R46: Caren | S46: Cec | T46: 2013/03-2 | U46: CEC
A47: 01-04-2019 | B47: 01-04-2019 | C47: Licitación Caren y Cec (SIC 2013/03-2) BS1A | D47: 4 | E47: ITAHUE 220 | F47: 1 | G47: -1638 | H47: -1638 | I47: Reliq. Energia Licitaciones | J47: Energía | K47: Lic. SIC 2013/03-2 bloques BS1A: Reliq. Energía abr 2019 | L47: 2020-03-23 11:56:36 | M47: 61 | O47: s | P47: s | Q47: BS1A | R47: Caren | S47: Cec | T47: 2013/03-2 | U47: CEC
A48: 01-04-2019 | B48: 01-04-2019 | C48: Licitación Caren y Cec (SIC 2013/03-2) BS1A | D48: 4 | E48: ITAHUE 220 | F48: 0 | G48: 0 | H48: 0 | I48: Ajuste por Armonizacion Tarifaria Licitaciones | J48: AAT | K48: Lic. SIC 2013/03-2 bloques BS1A: AAT abr 2019 | L48: 2019-05-13 00:00:00 | M48: 33 | N48: 8451 | O48: s | P48: s | Q48: BS1A | R48: Caren | S48: Cec | T48: 2013/03-2 | U48: CEC
A49: 01-04-2019 | B49: 01-04-2019 | C49: Licitación Caren y Cec (SIC 2013/03-2) BS1A | D49: 4 | E49: ITAHUE 220 | F49: 1366.2586 | G49: 65.349 | H49: 89284 | I49: Energia Licitaciones | J49: Energía | K49: Lic. SIC 2013/03-2 bloques BS1A: Energía abr 2019 | L49: 2019-05-13 00:00:00 | M49: 33 | N49: 8451 | O49: s | P49: s | Q49: BS1A | R49: Caren | S49: Cec | T49: 2013/03-2 | U49: CEC
A50: 01-04-2019 | B50: 01-04-2019 | C50: Licitación Caren y Cec (SIC 2013/03-2) BS1A | D50: 4 | E50: ITAHUE 220 | F50: 0 | G50: 0 | H50: 0 | I50: Potencia Licitaciones | J50: Potencia | K50: Lic. SIC 2013/03-2 bloques BS1A: Potencia abr 2019 | L50: 2019-05-13 00:00:00 | M50: 33 | N50: 8451 | O50: s | P50: s | Q50: BS1A | R50: Caren | S50: Cec | T50: 2013/03-2 | U50: CEC
A51: 01-04-2019 | B51: 01-04-2019 | C51: Licitación Caren y Cec (SIC 2013/03-2) BS1A | D51: 4 | E51: ITAHUE 220 | F51: 0 | G51: 0 | H51: 0 | I51: Reactivos Licitaciones | J51: Reactivo | K51: Lic. SIC 2013/03-2 bloques BS1A: Reactivo abr 2019 | L51: 2019-05-13 00:00:00 | M51: 33 | N51: 8451 | O51: s | P51: s | Q51: BS1A | R51: Caren | S51: Cec | T51: 2013/03-2 | U51: CEC
A52: 01-04-2019 | B52: 01-04-2019 | C52: Licitación Caren y Cec (SIC 2013/03-2) BS1A | D52: 5 | E52: RAPEL 220 | F52: 0 | G52: 0 | H52: 0 | I52: Potencia Licitaciones | J52: Potencia | K52: Lic. SIC 2013/03-2 bloques BS1A: Potencia abr 2019 | L52: 2019-05-13 00:00:00 | M52: 33 | N52: 8451 | O52: s | P52: s | Q52: BS1A | R52: Caren | S52: Cec | T52: 2013/03-2 | U52: CEC
A53: 01-04-2019 | B53: 01-04-2019 | C53: Licitación Caren y Cec (SIC 2013/03-2) BS1A | D53: 5 | E53: RAPEL 220 | F53: 0 | G53: 0 | H53: 0 | I53: Ajuste por Armonizacion Tarifaria Licitaciones | J53: AAT | K53: Lic. SIC 2013/03-2 bloques BS1A: AAT abr 2019 | L53: 2019-05-13 00:00:00 | M53: 33 | N53: 8451 | O53: s | P53: s | Q53: BS1A | R53: Caren | S53: Cec | T53: 2013/03-2 | U53: CEC
A54: 01-04-2019 | B54: 01-04-2019 | C54: Licitación Caren y Cec (SIC 2013/03-2) BS1A | D54: 5 | E54: RAPEL 220 | F54: 0 | G54: 0 | H54: 0 | I54: Reactivos Licitaciones | J54: Reactivo | K54: Lic. SIC 2013/03-2 bloques BS1A: Reactivo abr 2019 | L54: 2019-05-13 00:00:00 | M54: 33 | N54: 8451 | O54: s | P54: s | Q54: BS1A | R54: Caren | S54: Cec | T54: 2013/03-2 | U54: CEC
A55: 01-04-2019 | B55: 01-04-2019 | C55: Licitación Caren y Cec (SIC 2013/03-2) BS1A | D55: 5 | E55: RAPEL 220 | F55: 1 | G55: -7 | H55: -7 | I55: Reliq. Energia Licitaciones | J55: Energía | K55: Lic. SIC 2013/03-2 bloques BS1A: Reliq. Energía abr 2019 | L55: 2020-03-23 11:56:36 | M55: 61 | O55: s | P55: s | Q55: BS1A | R55: Caren | S55: Cec | T55: 2013/03-2 | U55: CEC
A56: 01-04-2019 | B56: 01-04-2019 | C56: Licitación Caren y Cec (SIC 2013/03-2) BS1A | D56: 5 | E56: RAPEL 220 | F56: 5.432024 | G56: 69.368 | H56: 377 | I56: Energia Licitaciones | J56: Energía | K56: Lic. SIC 2013/03-2 bloques BS1A: Energía abr 2019 | L56: 2019-05-13 00:00:00 | M56: 33 | N56: 8451 | O56: s | P56: s | Q56: BS1A | R56: Caren | S56: Cec | T56: 2013/03-2 | U56: CEC
A57: 01-05-2019 | B57: 01-05-2019 | C57: Licitación Caren y Cec (SIC 2013/03-2) BS1A | D57: 1 | E57: A.JAHUEL 220 | F57: 0 | G57: 0 | H57: 0 | I57: Reactivos Licitaciones | J57: Reactivo | K57: Lic. SIC 2013/03-2 bloques BS1A: Reactivo may 2019 | L57: 2019-06-11 00:00:00 | M57: 33 | N57: 8768 | O57: s | P57: s | Q57: BS1A | R57: Caren | S57: Cec | T57: 2013/03-2 | U57: CEC
A58: 01-05-2019 | B58: 01-05-2019 | C58: Licitación Caren y Cec (SIC 2013/03-2) BS1A | D58: 1 | E58: A.JAHUEL 220 | F58: 1 | G58: -337 | H58: -337 | I58: Reliq. Energia Licitaciones | J58: Energía | K58: Lic. SIC 2013/03-2 bloques BS1A: Reliq. Energía may 2019 | L58: 2020-03-25 15:09:20 | M58: 61 | O58: s | P58: s | Q58: BS1A | R58: Caren | S58: Cec | T58: 2013/03-2 | U58: CEC
